Workbook

Sheet dashboard
A1: CBAM Policy Dashboard — Pass 7
A2: 5 countries × 8 products × 12 years. 5-scope coverage flags, global MRV per product, exports-only tax option, BF-BOF integrated, NH₃ chain explicitly accounted, EF matrix included.
A4: 1. COUNTRY & VIEW SETTINGS
A5: Country selector | B5: egy | C5: → | D5: Choose from: egy, alb, uzb, aze, ind.
A6: Detail year (for price-impact table) | B6: 2030 | C6: → | D6: Year for the price-impact section. | P6: =MATCH(TEXT($B$6,"0"),input_data!$M$3:$X$3,0) -> 7
A7: Pass-through θ (share of wedge to buyer prices) | B7: 0.7 | C7: → | D7: Share of carbon wedge passed to buyers (rest hits producer margins).
A9: 2. POLICY CHOICES
A10: 2a. Coverage flags — what the domestic CP is levied on (1 = covered, 0 = not)
A11: Coverage S1.fc (Scope 1 — Fuel combustion CO₂) | B11: 1 | C11: → | D11: Combustion fuels (heat, steam).
A12: Coverage S1.fp (Scope 1 — Fuel-as-reductant CO₂) | B12: 1 | C12: → | D12: Fuel-as-reductant (BF coke + PCI, DRI shaft NG, SMR reformer NG).
A13: Coverage S1.np (Scope 1 — Non-fuel process CO₂) | B13: 1 | C13: → | D13: Calcination CO₂ (cement, anode), urea CO₂ uptake (negative for urea).
A14: Coverage S1.no (Scope 1 — Non-CO₂ GHG (CO₂e)) | B14: 1 | C14: → | D14: N₂O from HNO₃, PFCs from Hall-Héroult.
A15: Coverage S2 (Scope 2 — Electricity (indirect)) | B15: 1 | C15: → | D15: Indirect electricity emissions.
A17: 2b. MRV per product (global — applies to all countries; 1 = MRV verified, EU uses actual)
A18: Product → | B18: DRI | C18: Scrap | D18: BF-BOF | E18: Cement | F18: NH₃ | G18: Urea | H18: AN | I18: Al
A19: MRV flag (edit here): | B19: 1 | C19: 1 | D19: 1 | E19: 1 | F19: 1 | G19: 1 | H19: 1 | I19: 1
A20: CBAM S2 scope (reg., Annex II = 0): | B20: =INDEX(input_data!$L:$L,MATCH("all.in.cs2.stl.drg.---",input_data!$A:$A,0)) -> 0 | C20: =INDEX(input_data!$L:$L,MATCH("all.in.cs2.stl.scr.---",input_data!$A:$A,0)) -> 0 | D20: =INDEX(input_data!$L:$L,MATCH("all.in.cs2.stl.bof.---",input_data!$A:$A,0)) -> 0 | E20: =INDEX(input_data!$L:$L,MATCH("all.in.cs2.cmt.dry.---",input_data!$A:$A,0)) -> 1 | F20: =INDEX(input_data!$L:$L,MATCH("all.in.cs2.frt.amc.---",input_data!$A:$A,0)) -> 1 | G20: =INDEX(input_data!$L:$L,MATCH("all.in.cs2.frt.ure.---",input_data!$A:$A,0)) -> 1 | H20: =INDEX(input_data!$L:$L,MATCH("all.in.cs2.frt.nit.---",input_data!$A:$A,0)) -> 1 | I20: =INDEX(input_data!$L:$L,MATCH("all.in.cs2.alu.prp.---",input_data!$A:$A,0)) -> 0
A22: 2c. Tax only exports? (1 = yes — no domestic CP on home consumption; 0 = no) | B22: 0 | C22: → | D22: When 1, the country's CP is levied only on EU + non-EU exports (not on domestic-consumed product). Useful for politically-constrained pricing.
A24: 3. CARBON PRICE TIME SERIES
A25: row | B25: unit | D25: 2024 | E25: 2025 | F25: 2026 | G25: 2027 | H25: 2028 | I25: 2029 | J25: 2030 | K25: 2031 | L25: 2032 | M25: 2033 | N25: 2034 | O25: 2035
A26: EU ETS price | B26: EUR/tCO2 | D26: =INDEX(input_data!$M:$X,MATCH("all.in.ets.---.---.---",input_data!$A:$A,0),1) -> 85 | E26: =INDEX(input_data!$M:$X,MATCH("all.in.ets.---.---.---",input_data!$A:$A,0),2) -> 90 | F26: =INDEX(input_data!$M:$X,MATCH("all.in.ets.---.---.---",input_data!$A:$A,0),3) -> 100 | G26: =INDEX(input_data!$M:$X,MATCH("all.in.ets.---.---.---",input_data!$A:$A,0),4) -> 105 | H26: =INDEX(input_data!$M:$X,MATCH("all.in.ets.---.---.---",input_data!$A:$A,0),5) -> 110 | I26: =INDEX(input_data!$M:$X,MATCH("all.in.ets.---.---.---",input_data!$A:$A,0),6) -> 110 | J26: =INDEX(input_data!$M:$X,MATCH("all.in.ets.---.---.---",input_data!$A:$A,0),7) -> 115 | K26: =INDEX(input_data!$M:$X,MATCH("all.in.ets.---.---.---",input_data!$A:$A,0),8) -> 120 | L26: =INDEX(input_data!$M:$X,MATCH("all.in.ets.---.---.---",input_data!$A:$A,0),9) -> 125 | M26: =INDEX(input_data!$M:$X,MATCH("all.in.ets.---.---.---",input_data!$A:$A,0),10) -> 130 | N26: =INDEX(input_data!$M:$X,MATCH("all.in.ets.---.---.---",input_data!$A:$A,0),11) -> 135 | O26: =INDEX(input_data!$M:$X,MATCH("all.in.ets.---.---.---",input_data!$A:$A,0),12) -> 140
A27: CBAM factor | B27: fraction | D27: =INDEX(input_data!$M:$X,MATCH("all.in.cbf.---.---.---",input_data!$A:$A,0),1) -> 0 | E27: =INDEX(input_data!$M:$X,MATCH("all.in.cbf.---.---.---",input_data!$A:$A,0),2) -> 0 | F27: =INDEX(input_data!$M:$X,MATCH("all.in.cbf.---.---.---",input_data!$A:$A,0),3) -> 0.025 | G27: =INDEX(input_data!$M:$X,MATCH("all.in.cbf.---.---.---",input_data!$A:$A,0),4) -> 0.05 | H27: =INDEX(input_data!$M:$X,MATCH("all.in.cbf.---.---.---",input_data!$A:$A,0),5) -> 0.1 | I27: =INDEX(input_data!$M:$X,MATCH("all.in.cbf.---.---.---",input_data!$A:$A,0),6) -> 0.225 | J27: =INDEX(input_data!$M:$X,MATCH("all.in.cbf.---.---.---",input_data!$A:$A,0),7) -> 0.485 | K27: =INDEX(input_data!$M:$X,MATCH("all.in.cbf.---.---.---",input_data!$A:$A,0),8) -> 0.61 | L27: =INDEX(input_data!$M:$X,MATCH("all.in.cbf.---.---.---",input_data!$A:$A,0),9) -> 0.735 | M27: =INDEX(input_data!$M:$X,MATCH("all.in.cbf.---.---.---",input_data!$A:$A,0),10) -> 0.86 | N27: =INDEX(input_data!$M:$X,MATCH("all.in.cbf.---.---.---",input_data!$A:$A,0),11) -> 1 | O27: =INDEX(input_data!$M:$X,MATCH("all.in.cbf.---.---.---",input_data!$A:$A,0),12) -> 1
A28: ↓ OPTIMAL CP (captures full CBAM as country revenue) | B28: USD/tCO2 | D28: =IFERROR((IFERROR(calculations!M21*calculations!M248,0)+IFERROR(calculations!M49*calculations!M253,0)+IFERROR(calculations!M77*calculations!M258,0)+IFERROR(calculations!M105*calculations!M263,0)+IFERROR(calculations!M133*calculations!M268,0)+IFERROR(calculations!M161*calculations!M273,0)+IFERROR(calculations!M189*calculations!M278,0)+IFERROR(calculations!M217*calculations!M283,0))/(IFERROR(calculations!M21/calculations!M20*((calculations!M41+calculations!M244)*$B$11+calculations!M42*$B$12+calculations!M43*$B$13+calculations!M44*$B$14+calculations!M45*$B$15*INDEX(input_data!$L:$L,MATCH("all.in.cs2.stl.drg.---",input_data!$A:$A,0))),0)+IFERROR(calculations!M49/calculations!M48*((calculations!M69+calculations!M249)*$B$11+calculations!M70*$B$12+calculations!M71*$B$13+calculations!M72*$B$14+calculations!M73*$B$15*INDEX(input_data!$L:$L,MATCH("all.in.cs2.stl.scr.---",input_data!$A:$A,0))),0)+IFERROR(calculations!M77/calculations!M76*((calculations!M97+calculations!M254)*$B$11+calculations!M98*$B$12+calculations!M99*$B$13+calculations!M100*$B$14+calculations!M101*$B$15*INDEX(input_data!$L:$L,MATCH("all.in.cs2.stl.bof.---",input_data!$A:$A,0))),0)+IFERROR(calculations!M105/calculations!M104*((calculations!M125+calculations!M259)*$B$11+calculations!M126*$B$12+calculations!M127*$B$13+calculations!M128*$B$14+calculations!M129*$B$15*INDEX(input_data!$L:$L,MATCH("all.in.cs2.cmt.dry.---",input_data!$A:$A,0))),0)+IFERROR(calculations!M133/calculations!M132*((calculations!M153+calculations!M264)*$B$11+calculations!M154*$B$12+calculations!M155*$B$13+calculations!M156*$B$14+calculations!M157*$B$15*INDEX(input_data!$L:$L,MATCH("all.in.cs2.frt.amc.---",input_data!$A:$A,0))),0)+IFERROR(calculations!M161/calculations!M160*((calculations!M181+calculations!M269)*$B$11+calculations!M182*$B$12+calculations!M183*$B$13+calculations!M184*$B$14+calculations!M185*$B$15*INDEX(input_data!$L:$L,MATCH("all.in.cs2.frt.ure.---",input_data!$A:$A,0))),0)+IFERROR(calculations!M189/calculations!M188*((calculations!M209+calculations!M274)*$B$11+calculations!M210*$B$12+calculations!M211*$B$13+calculations!M212*$B$14+calculations!M213*$B$15*INDEX(input_data!$L:$L,MATCH("all.in.cs2.frt.nit.---",input_data!$A:$A,0))),0)+IFERROR(calculations!M217/calculations!M216*((calculations!M237+calculations!M279)*$B$11+calculations!M238*$B$12+calculations!M239*$B$13+calculations!M240*$B$14+calculations!M241*$B$15*INDEX(input_data!$L:$L,MATCH("all.in.cs2.alu.prp.---",input_data!$A:$A,0))),0)),0) -> 0 | E28: =IFERROR((IFERROR(calculations!N21*calculations!N248,0)+IFERROR(calculations!N49*calculations!N253,0)+IFERROR(calculations!N77*calculations!N258,0)+IFERROR(calculations!N105*calculations!N263,0)+IFERROR(calculations!N133*calculations!N268,0)+IFERROR(calculations!N161*calculations!N273,0)+IFERROR(calculations!N189*calculations!N278,0)+IFERROR(calculations!N217*calculations!N283,0))/(IFERROR(calculations!N21/calculations!N20*((calculations!N41+calculations!N244)*$B$11+calculations!N42*$B$12+calculations!N43*$B$13+calculations!N44*$B$14+calculations!N45*$B$15*INDEX(input_data!$L:$L,MATCH("all.in.cs2.stl.drg.---",input_data!$A:$A,0))),0)+IFERROR(calculations!N49/calculations!N48*((calculations!N69+calculations!N249)*$B$11+calculations!N70*$B$12+calculations!N71*$B$13+calculations!N72*$B$14+calculations!N73*$B$15*INDEX(input_data!$L:$L,MATCH("all.in.cs2.stl.scr.---",input_data!$A:$A,0))),0)+IFERROR(calculations!N77/calculations!N76*((calculations!N97+calculations!N254)*$B$11+calculations!N98*$B$12+calculations!N99*$B$13+calculations!N100*$B$14+calculations!N101*$B$15*INDEX(input_data!$L:$L,MATCH("all.in.cs2.stl.bof.---",input_data!$A:$A,0))),0)+IFERROR(calculations!N105/calculations!N104*((calculations!N125+calculations!N259)*$B$11+calculations!N126*$B$12+calculations!N127*$B$13+calculations!N128*$B$14+calculations!N129*$B$15*INDEX(input_data!$L:$L,MATCH("all.in.cs2.cmt.dry.---",input_data!$A:$A,0))),0)+IFERROR(calculations!N133/calculations!N132*((calculations!N153+calculations!N264)*$B$11+calculations!N154*$B$12+calculations!N155*$B$13+calculations!N156*$B$14+calculations!N157*$B$15*INDEX(input_data!$L:$L,MATCH("all.in.cs2.frt.amc.---",input_data!$A:$A,0))),0)+IFERROR(calculations!N161/calculations!N160*((calculations!N181+calculations!N269)*$B$11+calculations!N182*$B$12+calculations!N183*$B$13+calculations!N184*$B$14+calculations!N185*$B$15*INDEX(input_data!$L:$L,MATCH("all.in.cs2.frt.ure.---",input_data!$A:$A,0))),0)+IFERROR(calculations!N189/calculations!N188*((calculations!N209+calculations!N274)*$B$11+calculations!N210*$B$12+calculations!N211*$B$13+calculations!N212*$B$14+calculations!N213*$B$15*INDEX(input_data!$L:$L,MATCH("all.in.cs2.frt.nit.---",input_data!$A:$A,0))),0)+IFERROR(calculations!N217/calculations!N216*((calculations!N237+calculations!N279)*$B$11+calculations!N238*$B$12+calculations!N239*$B$13+calculations!N240*$B$14+calculations!N241*$B$15*INDEX(input_data!$L:$L,MATCH("all.in.cs2.alu.prp.---",input_data!$A:$A,0))),0)),0) -> 0 | F28: =IFERROR((IFERROR(calculations!O21*calculations!O248,0)+IFERROR(calculations!O49*calculations!O253,0)+IFERROR(calculations!O77*calculations!O258,0)+IFERROR(calculations!O105*calculations!O263,0)+IFERROR(calculations!O133*calculations!O268,0)+IFERROR(calculations!O161*calculations!O273,0)+IFERROR(calculations!O189*calculations!O278,0)+IFERROR(calculations!O217*calculations!O283,0))/(IFERROR(calculations!O21/calculations!O20*((calculations!O41+calculations!O244)*$B$11+calculations!O42*$B$12+calculations!O43*$B$13+calculations!O44*$B$14+calculations!O45*$B$15*INDEX(input_data!$L:$L,MATCH("all.in.cs2.stl.drg.---",input_data!$A:$A,0))),0)+IFERROR(calculations!O49/calculations!O48*((calculations!O69+calculations!O249)*$B$11+calculations!O70*$B$12+calculations!O71*$B$13+calculations!O72*$B$14+calculations!O73*$B$15*INDEX(input_data!$L:$L,MATCH("all.in.cs2.stl.scr.---",input_data!$A:$A,0))),0)+IFERROR(calculations!O77/calculations!O76*((calculations!O97+calculations!O254)*$B$11+calculations!O98*$B$12+calculations!O99*$B$13+calculations!O100*$B$14+calculations!O101*$B$15*INDEX(input_data!$L:$L,MATCH("all.in.cs2.stl.bof.---",input_data!$A:$A,0))),0)+IFERROR(calculations!O105/calculations!O104*((calculations!O125+calculations!O259)*$B$11+calculations!O126*$B$12+calculations!O127*$B$13+calculations!O128*$B$14+calculations!O129*$B$15*INDEX(input_data!$L:$L,MATCH("all.in.cs2.cmt.dry.---",input_data!$A:$A,0))),0)+IFERROR(calculations!O133/calculations!O132*((calculations!O153+calculations!O264)*$B$11+calculations!O154*$B$12+calculations!O155*$B$13+calculations!O156*$B$14+calculations!O157*$B$15*INDEX(input_data!$L:$L,MATCH("all.in.cs2.frt.amc.---",input_data!$A:$A,0))),0)+IFERROR(calculations!O161/calculations!O160*((calculations!O181+calculations!O269)*$B$11+calculations!O182*$B$12+calculations!O183*$B$13+calculations!O184*$B$14+calculations!O185*$B$15*INDEX(input_data!$L:$L,MATCH("all.in.cs2.frt.ure.---",input_data!$A:$A,0))),0)+IFERROR(calculations!O189/calculations!O188*((calculations!O209+calculations!O274)*$B$11+calculations!O210*$B$12+calculations!O211*$B$13+calculations!O212*$B$14+calculations!O213*$B$15*INDEX(input_data!$L:$L,MATCH("all.in.cs2.frt.nit.---",input_data!$A:$A,0))),0)+IFERROR(calculations!O217/calculations!O216*((calculations!O237+calculations!O279)*$B$11+calculations!O238*$B$12+calculations!O239*$B$13+calculations!O240*$B$14+calculations!O241*$B$15*INDEX(input_data!$L:$L,MATCH("all.in.cs2.alu.prp.---",input_data!$A:$A,0))),0)),0) -> 58.95271 | G28: =IFERROR((IFERROR(calculations!P21*calculations!P248,0)+IFERROR(calculations!P49*calculations!P253,0)+IFERROR(calculations!P77*calculations!P258,0)+IFERROR(calculations!P105*calculations!P263,0)+IFERROR(calculations!P133*calculations!P268,0)+IFERROR(calculations!P161*calculations!P273,0)+IFERROR(calculations!P189*calculations!P278,0)+IFERROR(calculations!P217*calculations!P283,0))/(IFERROR(calculations!P21/calculations!P20*((calculations!P41+calculations!P244)*$B$11+calculations!P42*$B$12+calculations!P43*$B$13+calculations!P44*$B$14+calculations!P45*$B$15*INDEX(input_data!$L:$L,MATCH("all.in.cs2.stl.drg.---",input_data!$A:$A,0))),0)+IFERROR(calculations!P49/calculations!P48*((calculations!P69+calculations!P249)*$B$11+calculations!P70*$B$12+calculations!P71*$B$13+calculations!P72*$B$14+calculations!P73*$B$15*INDEX(input_data!$L:$L,MATCH("all.in.cs2.stl.scr.---",input_data!$A:$A,0))),0)+IFERROR(calculations!P77/calculations!P76*((calculations!P97+calculations!P254)*$B$11+calculations!P98*$B$12+calculations!P99*$B$13+calculations!P100*$B$14+calculations!P101*$B$15*INDEX(input_data!$L:$L,MATCH("all.in.cs2.stl.bof.---",input_data!$A:$A,0))),0)+IFERROR(calculations!P105/calculations!P104*((calculations!P125+calculations!P259)*$B$11+calculations!P126*$B$12+calculations!P127*$B$13+calculations!P128*$B$14+calculations!P129*$B$15*INDEX(input_data!$L:$L,MATCH("all.in.cs2.cmt.dry.---",input_data!$A:$A,0))),0)+IFERROR(calculations!P133/calculations!P132*((calculations!P153+calculations!P264)*$B$11+calculations!P154*$B$12+calculations!P155*$B$13+calculations!P156*$B$14+calculations!P157*$B$15*INDEX(input_data!$L:$L,MATCH("all.in.cs2.frt.amc.---",input_data!$A:$A,0))),0)+IFERROR(calculations!P161/calculations!P160*((calculations!P181+calculations!P269)*$B$11+calculations!P182*$B$12+calculations!P183*$B$13+calculations!P184*$B$14+calculations!P185*$B$15*INDEX(input_data!$L:$L,MATCH("all.in.cs2.frt.ure.---",input_data!$A:$A,0))),0)+IFERROR(calculations!P189/calculations!P188*((calculations!P209+calculations!P274)*$B$11+calculations!P210*$B$12+calculations!P211*$B$13+calculations!P212*$B$14+calculations!P213*$B$15*INDEX(input_data!$L:$L,MATCH("all.in.cs2.frt.nit.---",input_data!$A:$A,0))),0)+IFERROR(calculations!P217/calculations!P216*((calculations!P237+calculations!P279)*$B$11+calculations!P238*$B$12+calculations!P239*$B$13+calculations!P240*$B$14+calculations!P241*$B$15*INDEX(input_data!$L:$L,MATCH("all.in.cs2.alu.prp.---",input_data!$A:$A,0))),0)),0) -> 63.24289 | H28: =IFERROR((IFERROR(calculations!Q21*calculations!Q248,0)+IFERROR(calculations!Q49*calculations!Q253,0)+IFERROR(calculations!Q77*calculations!Q258,0)+IFERROR(calculations!Q105*calculations!Q263,0)+IFERROR(calculations!Q133*calculations!Q268,0)+IFERROR(calculations!Q161*calculations!Q273,0)+IFERROR(calculations!Q189*calculations!Q278,0)+IFERROR(calculations!Q217*calculations!Q283,0))/(IFERROR(calculations!Q21/calculations!Q20*((calculations!Q41+calculations!Q244)*$B$11+calculations!Q42*$B$12+calculations!Q43*$B$13+calculations!Q44*$B$14+calculations!Q45*$B$15*INDEX(input_data!$L:$L,MATCH("all.in.cs2.stl.drg.---",input_data!$A:$A,0))),0)+IFERROR(calculations!Q49/calculations!Q48*((calculations!Q69+calculations!Q249)*$B$11+calculations!Q70*$B$12+calculations!Q71*$B$13+calculations!Q72*$B$14+calculations!Q73*$B$15*INDEX(input_data!$L:$L,MATCH("all.in.cs2.stl.scr.---",input_data!$A:$A,0))),0)+IFERROR(calculations!Q77/calculations!Q76*((calculations!Q97+calculations!Q254)*$B$11+calculations!Q98*$B$12+calculations!Q99*$B$13+calculations!Q100*$B$14+calculations!Q101*$B$15*INDEX(input_data!$L:$L,MATCH("all.in.cs2.stl.bof.---",input_data!$A:$A,0))),0)+IFERROR(calculations!Q105/calculations!Q104*((calculations!Q125+calculations!Q259)*$B$11+calculations!Q126*$B$12+calculations!Q127*$B$13+calculations!Q128*$B$14+calculations!Q129*$B$15*INDEX(input_data!$L:$L,MATCH("all.in.cs2.cmt.dry.---",input_data!$A:$A,0))),0)+IFERROR(calculations!Q133/calculations!Q132*((calculations!Q153+calculations!Q264)*$B$11+calculations!Q154*$B$12+calculations!Q155*$B$13+calculations!Q156*$B$14+calculations!Q157*$B$15*INDEX(input_data!$L:$L,MATCH("all.in.cs2.frt.amc.---",input_data!$A:$A,0))),0)+IFERROR(calculations!Q161/calculations!Q160*((calculations!Q181+calculations!Q269)*$B$11+calculations!Q182*$B$12+calculations!Q183*$B$13+calculations!Q184*$B$14+calculations!Q185*$B$15*INDEX(input_data!$L:$L,MATCH("all.in.cs2.frt.ure.---",input_data!$A:$A,0))),0)+IFERROR(calculations!Q189/calculations!Q188*((calculations!Q209+calculations!Q274)*$B$11+calculations!Q210*$B$12+calculations!Q211*$B$13+calculations!Q212*$B$14+calculations!Q213*$B$15*INDEX(input_data!$L:$L,MATCH("all.in.cs2.frt.nit.---",input_data!$A:$A,0))),0)+IFERROR(calculations!Q217/calculations!Q216*((calculations!Q237+calculations!Q279)*$B$11+calculations!Q238*$B$12+calculations!Q239*$B$13+calculations!Q240*$B$14+calculations!Q241*$B$15*INDEX(input_data!$L:$L,MATCH("all.in.cs2.alu.prp.---",input_data!$A:$A,0))),0)),0) -> 68.910911 | I28: =IFERROR((IFERROR(calculations!R21*calculations!R248,0)+IFERROR(calculations!R49*calculations!R253,0)+IFERROR(calculations!R77*calculations!R258,0)+IFERROR(calculations!R105*calculations!R263,0)+IFERROR(calculations!R133*calculations!R268,0)+IFERROR(calculations!R161*calculations!R273,0)+IFERROR(calculations!R189*calculations!R278,0)+IFERROR(calculations!R217*calculations!R283,0))/(IFERROR(calculations!R21/calculations!R20*((calculations!R41+calculations!R244)*$B$11+calculations!R42*$B$12+calculations!R43*$B$13+calculations!R44*$B$14+calculations!R45*$B$15*INDEX(input_data!$L:$L,MATCH("all.in.cs2.stl.drg.---",input_data!$A:$A,0))),0)+IFERROR(calculations!R49/calculations!R48*((calculations!R69+calculations!R249)*$B$11+calculations!R70*$B$12+calculations!R71*$B$13+calculations!R72*$B$14+calculations!R73*$B$15*INDEX(input_data!$L:$L,MATCH("all.in.cs2.stl.scr.---",input_data!$A:$A,0))),0)+IFERROR(calculations!R77/calculations!R76*((calculations!R97+calculations!R254)*$B$11+calculations!R98*$B$12+calculations!R99*$B$13+calculations!R100*$B$14+calculations!R101*$B$15*INDEX(input_data!$L:$L,MATCH("all.in.cs2.stl.bof.---",input_data!$A:$A,0))),0)+IFERROR(calculations!R105/calculations!R104*((calculations!R125+calculations!R259)*$B$11+calculations!R126*$B$12+calculations!R127*$B$13+calculations!R128*$B$14+calculations!R129*$B$15*INDEX(input_data!$L:$L,MATCH("all.in.cs2.cmt.dry.---",input_data!$A:$A,0))),0)+IFERROR(calculations!R133/calculations!R132*((calculations!R153+calculations!R264)*$B$11+calculations!R154*$B$12+calculations!R155*$B$13+calculations!R156*$B$14+calculations!R157*$B$15*INDEX(input_data!$L:$L,MATCH("all.in.cs2.frt.amc.---",input_data!$A:$A,0))),0)+IFERROR(calculations!R161/calculations!R160*((calculations!R181+calculations!R269)*$B$11+calculations!R182*$B$12+calculations!R183*$B$13+calculations!R184*$B$14+calculations!R185*$B$15*INDEX(input_data!$L:$L,MATCH("all.in.cs2.frt.ure.---",input_data!$A:$A,0))),0)+IFERROR(calculations!R189/calculations!R188*((calculations!R209+calculations!R274)*$B$11+calculations!R210*$B$12+calculations!R211*$B$13+calculations!R212*$B$14+calculations!R213*$B$15*INDEX(input_data!$L:$L,MATCH("all.in.cs2.frt.nit.---",input_data!$A:$A,0))),0)+IFERROR(calculations!R217/calculations!R216*((calculations!R237+calculations!R279)*$B$11+calculations!R238*$B$12+calculations!R239*$B$13+calculations!R240*$B$14+calculations!R241*$B$15*INDEX(input_data!$L:$L,MATCH("all.in.cs2.alu.prp.---",input_data!$A:$A,0))),0)),0) -> 75.316603 | J28: =IFERROR((IFERROR(calculations!S21*calculations!S248,0)+IFERROR(calculations!S49*calculations!S253,0)+IFERROR(calculations!S77*calculations!S258,0)+IFERROR(calculations!S105*calculations!S263,0)+IFERROR(calculations!S133*calculations!S268,0)+IFERROR(calculations!S161*calculations!S273,0)+IFERROR(calculations!S189*calculations!S278,0)+IFERROR(calculations!S217*calculations!S283,0))/(IFERROR(calculations!S21/calculations!S20*((calculations!S41+calculations!S244)*$B$11+calculations!S42*$B$12+calculations!S43*$B$13+calculations!S44*$B$14+calculations!S45*$B$15*INDEX(input_data!$L:$L,MATCH("all.in.cs2.stl.drg.---",input_data!$A:$A,0))),0)+IFERROR(calculations!S49/calculations!S48*((calculations!S69+calculations!S249)*$B$11+calculations!S70*$B$12+calculations!S71*$B$13+calculations!S72*$B$14+calculations!S73*$B$15*INDEX(input_data!$L:$L,MATCH("all.in.cs2.stl.scr.---",input_data!$A:$A,0))),0)+IFERROR(calculations!S77/calculations!S76*((calculations!S97+calculations!S254)*$B$11+calculations!S98*$B$12+calculations!S99*$B$13+calculations!S100*$B$14+calculations!S101*$B$15*INDEX(input_data!$L:$L,MATCH("all.in.cs2.stl.bof.---",input_data!$A:$A,0))),0)+IFERROR(calculations!S105/calculations!S104*((calculations!S125+calculations!S259)*$B$11+calculations!S126*$B$12+calculations!S127*$B$13+calculations!S128*$B$14+calculations!S129*$B$15*INDEX(input_data!$L:$L,MATCH("all.in.cs2.cmt.dry.---",input_data!$A:$A,0))),0)+IFERROR(calculations!S133/calculations!S132*((calculations!S153+calculations!S264)*$B$11+calculations!S154*$B$12+calculations!S155*$B$13+calculations!S156*$B$14+calculations!S157*$B$15*INDEX(input_data!$L:$L,MATCH("all.in.cs2.frt.amc.---",input_data!$A:$A,0))),0)+IFERROR(calculations!S161/calculations!S160*((calculations!S181+calculations!S269)*$B$11+calculations!S182*$B$12+calculations!S183*$B$13+calculations!S184*$B$14+calculations!S185*$B$15*INDEX(input_data!$L:$L,MATCH("all.in.cs2.frt.ure.---",input_data!$A:$A,0))),0)+IFERROR(calculations!S189/calculations!S188*((calculations!S209+calculations!S274)*$B$11+calculations!S210*$B$12+calculations!S211*$B$13+calculations!S212*$B$14+calculations!S213*$B$15*INDEX(input_data!$L:$L,MATCH("all.in.cs2.frt.nit.---",input_data!$A:$A,0))),0)+IFERROR(calculations!S217/calculations!S216*((calculations!S237+calculations!S279)*$B$11+calculations!S238*$B$12+calculations!S239*$B$13+calculations!S240*$B$14+calculations!S241*$B$15*INDEX(input_data!$L:$L,MATCH("all.in.cs2.alu.prp.---",input_data!$A:$A,0))),0)),0) -> 94.247266 | K28: =IFERROR((IFERROR(calculations!T21*calculations!T248,0)+IFERROR(calculations!T49*calculations!T253,0)+IFERROR(calculations!T77*calculations!T258,0)+IFERROR(calculations!T105*calculations!T263,0)+IFERROR(calculations!T133*calculations!T268,0)+IFERROR(calculations!T161*calculations!T273,0)+IFERROR(calculations!T189*calculations!T278,0)+IFERROR(calculations!T217*calculations!T283,0))/(IFERROR(calculations!T21/calculations!T20*((calculations!T41+calculations!T244)*$B$11+calculations!T42*$B$12+calculations!T43*$B$13+calculations!T44*$B$14+calculations!T45*$B$15*INDEX(input_data!$L:$L,MATCH("all.in.cs2.stl.drg.---",input_data!$A:$A,0))),0)+IFERROR(calculations!T49/calculations!T48*((calculations!T69+calculations!T249)*$B$11+calculations!T70*$B$12+calculations!T71*$B$13+calculations!T72*$B$14+calculations!T73*$B$15*INDEX(input_data!$L:$L,MATCH("all.in.cs2.stl.scr.---",input_data!$A:$A,0))),0)+IFERROR(calculations!T77/calculations!T76*((calculations!T97+calculations!T254)*$B$11+calculations!T98*$B$12+calculations!T99*$B$13+calculations!T100*$B$14+calculations!T101*$B$15*INDEX(input_data!$L:$L,MATCH("all.in.cs2.stl.bof.---",input_data!$A:$A,0))),0)+IFERROR(calculations!T105/calculations!T104*((calculations!T125+calculations!T259)*$B$11+calculations!T126*$B$12+calculations!T127*$B$13+calculations!T128*$B$14+calculations!T129*$B$15*INDEX(input_data!$L:$L,MATCH("all.in.cs2.cmt.dry.---",input_data!$A:$A,0))),0)+IFERROR(calculations!T133/calculations!T132*((calculations!T153+calculations!T264)*$B$11+calculations!T154*$B$12+calculations!T155*$B$13+calculations!T156*$B$14+calculations!T157*$B$15*INDEX(input_data!$L:$L,MATCH("all.in.cs2.frt.amc.---",input_data!$A:$A,0))),0)+IFERROR(calculations!T161/calculations!T160*((calculations!T181+calculations!T269)*$B$11+calculations!T182*$B$12+calculations!T183*$B$13+calculations!T184*$B$14+calculations!T185*$B$15*INDEX(input_data!$L:$L,MATCH("all.in.cs2.frt.ure.---",input_data!$A:$A,0))),0)+IFERROR(calculations!T189/calculations!T188*((calculations!T209+calculations!T274)*$B$11+calculations!T210*$B$12+calculations!T211*$B$13+calculations!T212*$B$14+calculations!T213*$B$15*INDEX(input_data!$L:$L,MATCH("all.in.cs2.frt.nit.---",input_data!$A:$A,0))),0)+IFERROR(calculations!T217/calculations!T216*((calculations!T237+calculations!T279)*$B$11+calculations!T238*$B$12+calculations!T239*$B$13+calculations!T240*$B$14+calculations!T241*$B$15*INDEX(input_data!$L:$L,MATCH("all.in.cs2.alu.prp.---",input_data!$A:$A,0))),0)),0) -> 106.59872 | ... O28: =IFERROR((IFERROR(calculations!X21*calculations!X248,0)+IFERROR(calculations!X49*calculations!X253,0)+IFERROR(calculations!X77*calculations!X258,0)+IFERROR(calculations!X105*calculations!X263,0)+IFERROR(calculations!X133*calculations!X268,0)+IFERROR(calculations!X161*calculations!X273,0)+IFERROR(calculations!X189*calculations!X278,0)+IFERROR(calculations!X217*calculations!X283,0))/(IFERROR(calculations!X21/calculations!X20*((calculations!X41+calculations!X244)*$B$11+calculations!X42*$B$12+calculations!X43*$B$13+calculations!X44*$B$14+calculations!X45*$B$15*INDEX(input_data!$L:$L,MATCH("all.in.cs2.stl.drg.---",input_data!$A:$A,0))),0)+IFERROR(calculations!X49/calculations!X48*((calculations!X69+calculations!X249)*$B$11+calculations!X70*$B$12+calculations!X71*$B$13+calculations!X72*$B$14+calculations!X73*$B$15*INDEX(input_data!$L:$L,MATCH("all.in.cs2.stl.scr.---",input_data!$A:$A,0))),0)+IFERROR(calculations!X77/calculations!X76*((calculations!X97+calculations!X254)*$B$11+calculations!X98*$B$12+calculations!X99*$B$13+calculations!X100*$B$14+calculations!X101*$B$15*INDEX(input_data!$L:$L,MATCH("all.in.cs2.stl.bof.---",input_data!$A:$A,0))),0)+IFERROR(calculations!X105/calculations!X104*((calculations!X125+calculations!X259)*$B$11+calculations!X126*$B$12+calculations!X127*$B$13+calculations!X128*$B$14+calculations!X129*$B$15*INDEX(input_data!$L:$L,MATCH("all.in.cs2.cmt.dry.---",input_data!$A:$A,0))),0)+IFERROR(calculations!X133/calculations!X132*((calculations!X153+calculations!X264)*$B$11+calculations!X154*$B$12+calculations!X155*$B$13+calculations!X156*$B$14+calculations!X157*$B$15*INDEX(input_data!$L:$L,MATCH("all.in.cs2.frt.amc.---",input_data!$A:$A,0))),0)+IFERROR(calculations!X161/calculations!X160*((calculations!X181+calculations!X269)*$B$11+calculations!X182*$B$12+calculations!X183*$B$13+calculations!X184*$B$14+calculations!X185*$B$15*INDEX(input_data!$L:$L,MATCH("all.in.cs2.frt.ure.---",input_data!$A:$A,0))),0)+IFERROR(calculations!X189/calculations!X188*((calculations!X209+calculations!X274)*$B$11+calculations!X210*$B$12+calculations!X211*$B$13+calculations!X212*$B$14+calculations!X213*$B$15*INDEX(input_data!$L:$L,MATCH("all.in.cs2.frt.nit.---",input_data!$A:$A,0))),0)+IFERROR(calculations!X217/calculations!X216*((calculations!X237+calculations!X279)*$B$11+calculations!X238*$B$12+calculations!X239*$B$13+calculations!X240*$B$14+calculations!X241*$B$15*INDEX(input_data!$L:$L,MATCH("all.in.cs2.alu.prp.---",input_data!$A:$A,0))),0)),0) -> 154
A29: ↓ DOMESTIC CARBON PRICE (editable, default = optimal) | B29: USD/tCO2 | D29: =D28 -> 0 | E29: =E28 -> 0 | F29: =F28 -> 58.95271 | G29: =G28 -> 63.24289 | H29: =H28 -> 68.910911 | I29: =I28 -> 75.316603 | J29: =J28 -> 94.247266 | K29: =K28 -> 106.59872 | ... O29: =O28 -> 154
A31: 4. HEADLINE REVENUES (USD millions)
A32: row | B32: unit | D32: 2024 | E32: 2025 | F32: 2026 | G32: 2027 | H32: 2028 | I32: 2029 | J32: 2030 | K32: 2031 | L32: 2032 | M32: 2033 | N32: 2034 | O32: 2035
A33: EU CBAM obligation gross | B33: USD m | D33: =IFERROR(calculations!M21*calculations!M248,0)+IFERROR(calculations!M49*calculations!M253,0)+IFERROR(calculations!M77*calculations!M258,0)+IFERROR(calculations!M105*calculations!M263,0)+IFERROR(calculations!M133*calculations!M268,0)+IFERROR(calculations!M161*calculations!M273,0)+IFERROR(calculations!M189*calculations!M278,0)+IFERROR(calculations!M217*calculations!M283,0) -> 0 | E33: =IFERROR(calculations!N21*calculations!N248,0)+IFERROR(calculations!N49*calculations!N253,0)+IFERROR(calculations!N77*calculations!N258,0)+IFERROR(calculations!N105*calculations!N263,0)+IFERROR(calculations!N133*calculations!N268,0)+IFERROR(calculations!N161*calculations!N273,0)+IFERROR(calculations!N189*calculations!N278,0)+IFERROR(calculations!N217*calculations!N283,0) -> 0 | F33: =IFERROR(calculations!O21*calculations!O248,0)+IFERROR(calculations!O49*calculations!O253,0)+IFERROR(calculations!O77*calculations!O258,0)+IFERROR(calculations!O105*calculations!O263,0)+IFERROR(calculations!O133*calculations!O268,0)+IFERROR(calculations!O161*calculations!O273,0)+IFERROR(calculations!O189*calculations!O278,0)+IFERROR(calculations!O217*calculations!O283,0) -> 197.06749 | G33: =IFERROR(calculations!P21*calculations!P248,0)+IFERROR(calculations!P49*calculations!P253,0)+IFERROR(calculations!P77*calculations!P258,0)+IFERROR(calculations!P105*calculations!P263,0)+IFERROR(calculations!P133*calculations!P268,0)+IFERROR(calculations!P161*calculations!P273,0)+IFERROR(calculations!P189*calculations!P278,0)+IFERROR(calculations!P217*calculations!P283,0) -> 220.85903 | H33: =IFERROR(calculations!Q21*calculations!Q248,0)+IFERROR(calculations!Q49*calculations!Q253,0)+IFERROR(calculations!Q77*calculations!Q258,0)+IFERROR(calculations!Q105*calculations!Q263,0)+IFERROR(calculations!Q133*calculations!Q268,0)+IFERROR(calculations!Q161*calculations!Q273,0)+IFERROR(calculations!Q189*calculations!Q278,0)+IFERROR(calculations!Q217*calculations!Q283,0) -> 251.4489 | I33: =IFERROR(calculations!R21*calculations!R248,0)+IFERROR(calculations!R49*calculations!R253,0)+IFERROR(calculations!R77*calculations!R258,0)+IFERROR(calculations!R105*calculations!R263,0)+IFERROR(calculations!R133*calculations!R268,0)+IFERROR(calculations!R161*calculations!R273,0)+IFERROR(calculations!R189*calculations!R278,0)+IFERROR(calculations!R217*calculations!R283,0) -> 287.19454 | J33: =IFERROR(calculations!S21*calculations!S248,0)+IFERROR(calculations!S49*calculations!S253,0)+IFERROR(calculations!S77*calculations!S258,0)+IFERROR(calculations!S105*calculations!S263,0)+IFERROR(calculations!S133*calculations!S268,0)+IFERROR(calculations!S161*calculations!S273,0)+IFERROR(calculations!S189*calculations!S278,0)+IFERROR(calculations!S217*calculations!S283,0) -> 375.61474 | K33: =IFERROR(calculations!T21*calculations!T248,0)+IFERROR(calculations!T49*calculations!T253,0)+IFERROR(calculations!T77*calculations!T258,0)+IFERROR(calculations!T105*calculations!T263,0)+IFERROR(calculations!T133*calculations!T268,0)+IFERROR(calculations!T161*calculations!T273,0)+IFERROR(calculations!T189*calculations!T278,0)+IFERROR(calculations!T217*calculations!T283,0) -> 444.09747 | ... O33: =IFERROR(calculations!X21*calculations!X248,0)+IFERROR(calculations!X49*calculations!X253,0)+IFERROR(calculations!X77*calculations!X258,0)+IFERROR(calculations!X105*calculations!X263,0)+IFERROR(calculations!X133*calculations!X268,0)+IFERROR(calculations!X161*calculations!X273,0)+IFERROR(calculations!X189*calculations!X278,0)+IFERROR(calculations!X217*calculations!X283,0) -> 767.15512
A34: ● Country revenue on EU exports (total covered) | B34: USD m | D34: =IFERROR((calculations!M21/calculations!M20)*((calculations!M41+calculations!M244)*$B$11+calculations!M42*$B$12+calculations!M43*$B$13+calculations!M44*$B$14+calculations!M45*$B$15)*D29,0)+IFERROR((calculations!M49/calculations!M48)*((calculations!M69+calculations!M249)*$B$11+calculations!M70*$B$12+calculations!M71*$B$13+calculations!M72*$B$14+calculations!M73*$B$15)*D29,0)+IFERROR((calculations!M77/calculations!M76)*((calculations!M97+calculations!M254)*$B$11+calculations!M98*$B$12+calculations!M99*$B$13+calculations!M100*$B$14+calculations!M101*$B$15)*D29,0)+IFERROR((calculations!M105/calculations!M104)*((calculations!M125+calculations!M259)*$B$11+calculations!M126*$B$12+calculations!M127*$B$13+calculations!M128*$B$14+calculations!M129*$B$15)*D29,0)+IFERROR((calculations!M133/calculations!M132)*((calculations!M153+calculations!M264)*$B$11+calculations!M154*$B$12+calculations!M155*$B$13+calculations!M156*$B$14+calculations!M157*$B$15)*D29,0)+IFERROR((calculations!M161/calculations!M160)*((calculations!M181+calculations!M269)*$B$11+calculations!M182*$B$12+calculations!M183*$B$13+calculations!M184*$B$14+calculations!M185*$B$15)*D29,0)+IFERROR((calculations!M189/calculations!M188)*((calculations!M209+calculations!M274)*$B$11+calculations!M210*$B$12+calculations!M211*$B$13+calculations!M212*$B$14+calculations!M213*$B$15)*D29,0)+IFERROR((calculations!M217/calculations!M216)*((calculations!M237+calculations!M279)*$B$11+calculations!M238*$B$12+calculations!M239*$B$13+calculations!M240*$B$14+calculations!M241*$B$15)*D29,0) -> 0 | E34: =IFERROR((calculations!N21/calculations!N20)*((calculations!N41+calculations!N244)*$B$11+calculations!N42*$B$12+calculations!N43*$B$13+calculations!N44*$B$14+calculations!N45*$B$15)*E29,0)+IFERROR((calculations!N49/calculations!N48)*((calculations!N69+calculations!N249)*$B$11+calculations!N70*$B$12+calculations!N71*$B$13+calculations!N72*$B$14+calculations!N73*$B$15)*E29,0)+IFERROR((calculations!N77/calculations!N76)*((calculations!N97+calculations!N254)*$B$11+calculations!N98*$B$12+calculations!N99*$B$13+calculations!N100*$B$14+calculations!N101*$B$15)*E29,0)+IFERROR((calculations!N105/calculations!N104)*((calculations!N125+calculations!N259)*$B$11+calculations!N126*$B$12+calculations!N127*$B$13+calculations!N128*$B$14+calculations!N129*$B$15)*E29,0)+IFERROR((calculations!N133/calculations!N132)*((calculations!N153+calculations!N264)*$B$11+calculations!N154*$B$12+calculations!N155*$B$13+calculations!N156*$B$14+calculations!N157*$B$15)*E29,0)+IFERROR((calculations!N161/calculations!N160)*((calculations!N181+calculations!N269)*$B$11+calculations!N182*$B$12+calculations!N183*$B$13+calculations!N184*$B$14+calculations!N185*$B$15)*E29,0)+IFERROR((calculations!N189/calculations!N188)*((calculations!N209+calculations!N274)*$B$11+calculations!N210*$B$12+calculations!N211*$B$13+calculations!N212*$B$14+calculations!N213*$B$15)*E29,0)+IFERROR((calculations!N217/calculations!N216)*((calculations!N237+calculations!N279)*$B$11+calculations!N238*$B$12+calculations!N239*$B$13+calculations!N240*$B$14+calculations!N241*$B$15)*E29,0) -> 0 | F34: =IFERROR((calculations!O21/calculations!O20)*((calculations!O41+calculations!O244)*$B$11+calculations!O42*$B$12+calculations!O43*$B$13+calculations!O44*$B$14+calculations!O45*$B$15)*F29,0)+IFERROR((calculations!O49/calculations!O48)*((calculations!O69+calculations!O249)*$B$11+calculations!O70*$B$12+calculations!O71*$B$13+calculations!O72*$B$14+calculations!O73*$B$15)*F29,0)+IFERROR((calculations!O77/calculations!O76)*((calculations!O97+calculations!O254)*$B$11+calculations!O98*$B$12+calculations!O99*$B$13+calculations!O100*$B$14+calculations!O101*$B$15)*F29,0)+IFERROR((calculations!O105/calculations!O104)*((calculations!O125+calculations!O259)*$B$11+calculations!O126*$B$12+calculations!O127*$B$13+calculations!O128*$B$14+calculations!O129*$B$15)*F29,0)+IFERROR((calculations!O133/calculations!O132)*((calculations!O153+calculations!O264)*$B$11+calculations!O154*$B$12+calculations!O155*$B$13+calculations!O156*$B$14+calculations!O157*$B$15)*F29,0)+IFERROR((calculations!O161/calculations!O160)*((calculations!O181+calculations!O269)*$B$11+calculations!O182*$B$12+calculations!O183*$B$13+calculations!O184*$B$14+calculations!O185*$B$15)*F29,0)+IFERROR((calculations!O189/calculations!O188)*((calculations!O209+calculations!O274)*$B$11+calculations!O210*$B$12+calculations!O211*$B$13+calculations!O212*$B$14+calculations!O213*$B$15)*F29,0)+IFERROR((calculations!O217/calculations!O216)*((calculations!O237+calculations!O279)*$B$11+calculations!O238*$B$12+calculations!O239*$B$13+calculations!O240*$B$14+calculations!O241*$B$15)*F29,0) -> 259.30987 | G34: =IFERROR((calculations!P21/calculations!P20)*((calculations!P41+calculations!P244)*$B$11+calculations!P42*$B$12+calculations!P43*$B$13+calculations!P44*$B$14+calculations!P45*$B$15)*G29,0)+IFERROR((calculations!P49/calculations!P48)*((calculations!P69+calculations!P249)*$B$11+calculations!P70*$B$12+calculations!P71*$B$13+calculations!P72*$B$14+calculations!P73*$B$15)*G29,0)+IFERROR((calculations!P77/calculations!P76)*((calculations!P97+calculations!P254)*$B$11+calculations!P98*$B$12+calculations!P99*$B$13+calculations!P100*$B$14+calculations!P101*$B$15)*G29,0)+IFERROR((calculations!P105/calculations!P104)*((calculations!P125+calculations!P259)*$B$11+calculations!P126*$B$12+calculations!P127*$B$13+calculations!P128*$B$14+calculations!P129*$B$15)*G29,0)+IFERROR((calculations!P133/calculations!P132)*((calculations!P153+calculations!P264)*$B$11+calculations!P154*$B$12+calculations!P155*$B$13+calculations!P156*$B$14+calculations!P157*$B$15)*G29,0)+IFERROR((calculations!P161/calculations!P160)*((calculations!P181+calculations!P269)*$B$11+calculations!P182*$B$12+calculations!P183*$B$13+calculations!P184*$B$14+calculations!P185*$B$15)*G29,0)+IFERROR((calculations!P189/calculations!P188)*((calculations!P209+calculations!P274)*$B$11+calculations!P210*$B$12+calculations!P211*$B$13+calculations!P212*$B$14+calculations!P213*$B$15)*G29,0)+IFERROR((calculations!P217/calculations!P216)*((calculations!P237+calculations!P279)*$B$11+calculations!P238*$B$12+calculations!P239*$B$13+calculations!P240*$B$14+calculations!P241*$B$15)*G29,0) -> 289.37285 | H34: =IFERROR((calculations!Q21/calculations!Q20)*((calculations!Q41+calculations!Q244)*$B$11+calculations!Q42*$B$12+calculations!Q43*$B$13+calculations!Q44*$B$14+calculations!Q45*$B$15)*H29,0)+IFERROR((calculations!Q49/calculations!Q48)*((calculations!Q69+calculations!Q249)*$B$11+calculations!Q70*$B$12+calculations!Q71*$B$13+calculations!Q72*$B$14+calculations!Q73*$B$15)*H29,0)+IFERROR((calculations!Q77/calculations!Q76)*((calculations!Q97+calculations!Q254)*$B$11+calculations!Q98*$B$12+calculations!Q99*$B$13+calculations!Q100*$B$14+calculations!Q101*$B$15)*H29,0)+IFERROR((calculations!Q105/calculations!Q104)*((calculations!Q125+calculations!Q259)*$B$11+calculations!Q126*$B$12+calculations!Q127*$B$13+calculations!Q128*$B$14+calculations!Q129*$B$15)*H29,0)+IFERROR((calculations!Q133/calculations!Q132)*((calculations!Q153+calculations!Q264)*$B$11+calculations!Q154*$B$12+calculations!Q155*$B$13+calculations!Q156*$B$14+calculations!Q157*$B$15)*H29,0)+IFERROR((calculations!Q161/calculations!Q160)*((calculations!Q181+calculations!Q269)*$B$11+calculations!Q182*$B$12+calculations!Q183*$B$13+calculations!Q184*$B$14+calculations!Q185*$B$15)*H29,0)+IFERROR((calculations!Q189/calculations!Q188)*((calculations!Q209+calculations!Q274)*$B$11+calculations!Q210*$B$12+calculations!Q211*$B$13+calculations!Q212*$B$14+calculations!Q213*$B$15)*H29,0)+IFERROR((calculations!Q217/calculations!Q216)*((calculations!Q237+calculations!Q279)*$B$11+calculations!Q238*$B$12+calculations!Q239*$B$13+calculations!Q240*$B$14+calculations!Q241*$B$15)*H29,0) -> 328.01933 | I34: =IFERROR((calculations!R21/calculations!R20)*((calculations!R41+calculations!R244)*$B$11+calculations!R42*$B$12+calculations!R43*$B$13+calculations!R44*$B$14+calculations!R45*$B$15)*I29,0)+IFERROR((calculations!R49/calculations!R48)*((calculations!R69+calculations!R249)*$B$11+calculations!R70*$B$12+calculations!R71*$B$13+calculations!R72*$B$14+calculations!R73*$B$15)*I29,0)+IFERROR((calculations!R77/calculations!R76)*((calculations!R97+calculations!R254)*$B$11+calculations!R98*$B$12+calculations!R99*$B$13+calculations!R100*$B$14+calculations!R101*$B$15)*I29,0)+IFERROR((calculations!R105/calculations!R104)*((calculations!R125+calculations!R259)*$B$11+calculations!R126*$B$12+calculations!R127*$B$13+calculations!R128*$B$14+calculations!R129*$B$15)*I29,0)+IFERROR((calculations!R133/calculations!R132)*((calculations!R153+calculations!R264)*$B$11+calculations!R154*$B$12+calculations!R155*$B$13+calculations!R156*$B$14+calculations!R157*$B$15)*I29,0)+IFERROR((calculations!R161/calculations!R160)*((calculations!R181+calculations!R269)*$B$11+calculations!R182*$B$12+calculations!R183*$B$13+calculations!R184*$B$14+calculations!R185*$B$15)*I29,0)+IFERROR((calculations!R189/calculations!R188)*((calculations!R209+calculations!R274)*$B$11+calculations!R210*$B$12+calculations!R211*$B$13+calculations!R212*$B$14+calculations!R213*$B$15)*I29,0)+IFERROR((calculations!R217/calculations!R216)*((calculations!R237+calculations!R279)*$B$11+calculations!R238*$B$12+calculations!R239*$B$13+calculations!R240*$B$14+calculations!R241*$B$15)*I29,0) -> 372.99404 | J34: =IFERROR((calculations!S21/calculations!S20)*((calculations!S41+calculations!S244)*$B$11+calculations!S42*$B$12+calculations!S43*$B$13+calculations!S44*$B$14+calculations!S45*$B$15)*J29,0)+IFERROR((calculations!S49/calculations!S48)*((calculations!S69+calculations!S249)*$B$11+calculations!S70*$B$12+calculations!S71*$B$13+calculations!S72*$B$14+calculations!S73*$B$15)*J29,0)+IFERROR((calculations!S77/calculations!S76)*((calculations!S97+calculations!S254)*$B$11+calculations!S98*$B$12+calculations!S99*$B$13+calculations!S100*$B$14+calculations!S101*$B$15)*J29,0)+IFERROR((calculations!S105/calculations!S104)*((calculations!S125+calculations!S259)*$B$11+calculations!S126*$B$12+calculations!S127*$B$13+calculations!S128*$B$14+calculations!S129*$B$15)*J29,0)+IFERROR((calculations!S133/calculations!S132)*((calculations!S153+calculations!S264)*$B$11+calculations!S154*$B$12+calculations!S155*$B$13+calculations!S156*$B$14+calculations!S157*$B$15)*J29,0)+IFERROR((calculations!S161/calculations!S160)*((calculations!S181+calculations!S269)*$B$11+calculations!S182*$B$12+calculations!S183*$B$13+calculations!S184*$B$14+calculations!S185*$B$15)*J29,0)+IFERROR((calculations!S189/calculations!S188)*((calculations!S209+calculations!S274)*$B$11+calculations!S210*$B$12+calculations!S211*$B$13+calculations!S212*$B$14+calculations!S213*$B$15)*J29,0)+IFERROR((calculations!S217/calculations!S216)*((calculations!S237+calculations!S279)*$B$11+calculations!S238*$B$12+calculations!S239*$B$13+calculations!S240*$B$14+calculations!S241*$B$15)*J29,0) -> 485.6393 | K34: =IFERROR((calculations!T21/calculations!T20)*((calculations!T41+calculations!T244)*$B$11+calculations!T42*$B$12+calculations!T43*$B$13+calculations!T44*$B$14+calculations!T45*$B$15)*K29,0)+IFERROR((calculations!T49/calculations!T48)*((calculations!T69+calculations!T249)*$B$11+calculations!T70*$B$12+calculations!T71*$B$13+calculations!T72*$B$14+calculations!T73*$B$15)*K29,0)+IFERROR((calculations!T77/calculations!T76)*((calculations!T97+calculations!T254)*$B$11+calculations!T98*$B$12+calculations!T99*$B$13+calculations!T100*$B$14+calculations!T101*$B$15)*K29,0)+IFERROR((calculations!T105/calculations!T104)*((calculations!T125+calculations!T259)*$B$11+calculations!T126*$B$12+calculations!T127*$B$13+calculations!T128*$B$14+calculations!T129*$B$15)*K29,0)+IFERROR((calculations!T133/calculations!T132)*((calculations!T153+calculations!T264)*$B$11+calculations!T154*$B$12+calculations!T155*$B$13+calculations!T156*$B$14+calculations!T157*$B$15)*K29,0)+IFERROR((calculations!T161/calculations!T160)*((calculations!T181+calculations!T269)*$B$11+calculations!T182*$B$12+calculations!T183*$B$13+calculations!T184*$B$14+calculations!T185*$B$15)*K29,0)+IFERROR((calculations!T189/calculations!T188)*((calculations!T209+calculations!T274)*$B$11+calculations!T210*$B$12+calculations!T211*$B$13+calculations!T212*$B$14+calculations!T213*$B$15)*K29,0)+IFERROR((calculations!T217/calculations!T216)*((calculations!T237+calculations!T279)*$B$11+calculations!T238*$B$12+calculations!T239*$B$13+calculations!T240*$B$14+calculations!T241*$B$15)*K29,0) -> 571.56404 | ... O34: =IFERROR((calculations!X21/calculations!X20)*((calculations!X41+calculations!X244)*$B$11+calculations!X42*$B$12+calculations!X43*$B$13+calculations!X44*$B$14+calculations!X45*$B$15)*O29,0)+IFERROR((calculations!X49/calculations!X48)*((calculations!X69+calculations!X249)*$B$11+calculations!X70*$B$12+calculations!X71*$B$13+calculations!X72*$B$14+calculations!X73*$B$15)*O29,0)+IFERROR((calculations!X77/calculations!X76)*((calculations!X97+calculations!X254)*$B$11+calculations!X98*$B$12+calculations!X99*$B$13+calculations!X100*$B$14+calculations!X101*$B$15)*O29,0)+IFERROR((calculations!X105/calculations!X104)*((calculations!X125+calculations!X259)*$B$11+calculations!X126*$B$12+calculations!X127*$B$13+calculations!X128*$B$14+calculations!X129*$B$15)*O29,0)+IFERROR((calculations!X133/calculations!X132)*((calculations!X153+calculations!X264)*$B$11+calculations!X154*$B$12+calculations!X155*$B$13+calculations!X156*$B$14+calculations!X157*$B$15)*O29,0)+IFERROR((calculations!X161/calculations!X160)*((calculations!X181+calculations!X269)*$B$11+calculations!X182*$B$12+calculations!X183*$B$13+calculations!X184*$B$14+calculations!X185*$B$15)*O29,0)+IFERROR((calculations!X189/calculations!X188)*((calculations!X209+calculations!X274)*$B$11+calculations!X210*$B$12+calculations!X211*$B$13+calculations!X212*$B$14+calculations!X213*$B$15)*O29,0)+IFERROR((calculations!X217/calculations!X216)*((calculations!X237+calculations!X279)*$B$11+calculations!X238*$B$12+calculations!X239*$B$13+calculations!X240*$B$14+calculations!X241*$B$15)*O29,0) -> 968.81424
A35: of which creditable against CBAM | B35: USD m | D35: =IFERROR((calculations!M21/calculations!M20)*((calculations!M41+calculations!M244)*$B$11+calculations!M42*$B$12+calculations!M43*$B$13+calculations!M44*$B$14+calculations!M45*$B$15*INDEX(input_data!$L:$L,MATCH("all.in.cs2.stl.drg.---",input_data!$A:$A,0)))*D29,0)+IFERROR((calculations!M49/calculations!M48)*((calculations!M69+calculations!M249)*$B$11+calculations!M70*$B$12+calculations!M71*$B$13+calculations!M72*$B$14+calculations!M73*$B$15*INDEX(input_data!$L:$L,MATCH("all.in.cs2.stl.scr.---",input_data!$A:$A,0)))*D29,0)+IFERROR((calculations!M77/calculations!M76)*((calculations!M97+calculations!M254)*$B$11+calculations!M98*$B$12+calculations!M99*$B$13+calculations!M100*$B$14+calculations!M101*$B$15*INDEX(input_data!$L:$L,MATCH("all.in.cs2.stl.bof.---",input_data!$A:$A,0)))*D29,0)+IFERROR((calculations!M105/calculations!M104)*((calculations!M125+calculations!M259)*$B$11+calculations!M126*$B$12+calculations!M127*$B$13+calculations!M128*$B$14+calculations!M129*$B$15*INDEX(input_data!$L:$L,MATCH("all.in.cs2.cmt.dry.---",input_data!$A:$A,0)))*D29,0)+IFERROR((calculations!M133/calculations!M132)*((calculations!M153+calculations!M264)*$B$11+calculations!M154*$B$12+calculations!M155*$B$13+calculations!M156*$B$14+calculations!M157*$B$15*INDEX(input_data!$L:$L,MATCH("all.in.cs2.frt.amc.---",input_data!$A:$A,0)))*D29,0)+IFERROR((calculations!M161/calculations!M160)*((calculations!M181+calculations!M269)*$B$11+calculations!M182*$B$12+calculations!M183*$B$13+calculations!M184*$B$14+calculations!M185*$B$15*INDEX(input_data!$L:$L,MATCH("all.in.cs2.frt.ure.---",input_data!$A:$A,0)))*D29,0)+IFERROR((calculations!M189/calculations!M188)*((calculations!M209+calculations!M274)*$B$11+calculations!M210*$B$12+calculations!M211*$B$13+calculations!M212*$B$14+calculations!M213*$B$15*INDEX(input_data!$L:$L,MATCH("all.in.cs2.frt.nit.---",input_data!$A:$A,0)))*D29,0)+IFERROR((calculations!M217/calculations!M216)*((calculations!M237+calculations!M279)*$B$11+calculations!M238*$B$12+calculations!M239*$B$13+calculations!M240*$B$14+calculations!M241*$B$15*INDEX(input_data!$L:$L,MATCH("all.in.cs2.alu.prp.---",input_data!$A:$A,0)))*D29,0) -> 0 | E35: =IFERROR((calculations!N21/calculations!N20)*((calculations!N41+calculations!N244)*$B$11+calculations!N42*$B$12+calculations!N43*$B$13+calculations!N44*$B$14+calculations!N45*$B$15*INDEX(input_data!$L:$L,MATCH("all.in.cs2.stl.drg.---",input_data!$A:$A,0)))*E29,0)+IFERROR((calculations!N49/calculations!N48)*((calculations!N69+calculations!N249)*$B$11+calculations!N70*$B$12+calculations!N71*$B$13+calculations!N72*$B$14+calculations!N73*$B$15*INDEX(input_data!$L:$L,MATCH("all.in.cs2.stl.scr.---",input_data!$A:$A,0)))*E29,0)+IFERROR((calculations!N77/calculations!N76)*((calculations!N97+calculations!N254)*$B$11+calculations!N98*$B$12+calculations!N99*$B$13+calculations!N100*$B$14+calculations!N101*$B$15*INDEX(input_data!$L:$L,MATCH("all.in.cs2.stl.bof.---",input_data!$A:$A,0)))*E29,0)+IFERROR((calculations!N105/calculations!N104)*((calculations!N125+calculations!N259)*$B$11+calculations!N126*$B$12+calculations!N127*$B$13+calculations!N128*$B$14+calculations!N129*$B$15*INDEX(input_data!$L:$L,MATCH("all.in.cs2.cmt.dry.---",input_data!$A:$A,0)))*E29,0)+IFERROR((calculations!N133/calculations!N132)*((calculations!N153+calculations!N264)*$B$11+calculations!N154*$B$12+calculations!N155*$B$13+calculations!N156*$B$14+calculations!N157*$B$15*INDEX(input_data!$L:$L,MATCH("all.in.cs2.frt.amc.---",input_data!$A:$A,0)))*E29,0)+IFERROR((calculations!N161/calculations!N160)*((calculations!N181+calculations!N269)*$B$11+calculations!N182*$B$12+calculations!N183*$B$13+calculations!N184*$B$14+calculations!N185*$B$15*INDEX(input_data!$L:$L,MATCH("all.in.cs2.frt.ure.---",input_data!$A:$A,0)))*E29,0)+IFERROR((calculations!N189/calculations!N188)*((calculations!N209+calculations!N274)*$B$11+calculations!N210*$B$12+calculations!N211*$B$13+calculations!N212*$B$14+calculations!N213*$B$15*INDEX(input_data!$L:$L,MATCH("all.in.cs2.frt.nit.---",input_data!$A:$A,0)))*E29,0)+IFERROR((calculations!N217/calculations!N216)*((calculations!N237+calculations!N279)*$B$11+calculations!N238*$B$12+calculations!N239*$B$13+calculations!N240*$B$14+calculations!N241*$B$15*INDEX(input_data!$L:$L,MATCH("all.in.cs2.alu.prp.---",input_data!$A:$A,0)))*E29,0) -> 0 | F35: =IFERROR((calculations!O21/calculations!O20)*((calculations!O41+calculations!O244)*$B$11+calculations!O42*$B$12+calculations!O43*$B$13+calculations!O44*$B$14+calculations!O45*$B$15*INDEX(input_data!$L:$L,MATCH("all.in.cs2.stl.drg.---",input_data!$A:$A,0)))*F29,0)+IFERROR((calculations!O49/calculations!O48)*((calculations!O69+calculations!O249)*$B$11+calculations!O70*$B$12+calculations!O71*$B$13+calculations!O72*$B$14+calculations!O73*$B$15*INDEX(input_data!$L:$L,MATCH("all.in.cs2.stl.scr.---",input_data!$A:$A,0)))*F29,0)+IFERROR((calculations!O77/calculations!O76)*((calculations!O97+calculations!O254)*$B$11+calculations!O98*$B$12+calculations!O99*$B$13+calculations!O100*$B$14+calculations!O101*$B$15*INDEX(input_data!$L:$L,MATCH("all.in.cs2.stl.bof.---",input_data!$A:$A,0)))*F29,0)+IFERROR((calculations!O105/calculations!O104)*((calculations!O125+calculations!O259)*$B$11+calculations!O126*$B$12+calculations!O127*$B$13+calculations!O128*$B$14+calculations!O129*$B$15*INDEX(input_data!$L:$L,MATCH("all.in.cs2.cmt.dry.---",input_data!$A:$A,0)))*F29,0)+IFERROR((calculations!O133/calculations!O132)*((calculations!O153+calculations!O264)*$B$11+calculations!O154*$B$12+calculations!O155*$B$13+calculations!O156*$B$14+calculations!O157*$B$15*INDEX(input_data!$L:$L,MATCH("all.in.cs2.frt.amc.---",input_data!$A:$A,0)))*F29,0)+IFERROR((calculations!O161/calculations!O160)*((calculations!O181+calculations!O269)*$B$11+calculations!O182*$B$12+calculations!O183*$B$13+calculations!O184*$B$14+calculations!O185*$B$15*INDEX(input_data!$L:$L,MATCH("all.in.cs2.frt.ure.---",input_data!$A:$A,0)))*F29,0)+IFERROR((calculations!O189/calculations!O188)*((calculations!O209+calculations!O274)*$B$11+calculations!O210*$B$12+calculations!O211*$B$13+calculations!O212*$B$14+calculations!O213*$B$15*INDEX(input_data!$L:$L,MATCH("all.in.cs2.frt.nit.---",input_data!$A:$A,0)))*F29,0)+IFERROR((calculations!O217/calculations!O216)*((calculations!O237+calculations!O279)*$B$11+calculations!O238*$B$12+calculations!O239*$B$13+calculations!O240*$B$14+calculations!O241*$B$15*INDEX(input_data!$L:$L,MATCH("all.in.cs2.alu.prp.---",input_data!$A:$A,0)))*F29,0) -> 197.06749 | G35: =IFERROR((calculations!P21/calculations!P20)*((calculations!P41+calculations!P244)*$B$11+calculations!P42*$B$12+calculations!P43*$B$13+calculations!P44*$B$14+calculations!P45*$B$15*INDEX(input_data!$L:$L,MATCH("all.in.cs2.stl.drg.---",input_data!$A:$A,0)))*G29,0)+IFERROR((calculations!P49/calculations!P48)*((calculations!P69+calculations!P249)*$B$11+calculations!P70*$B$12+calculations!P71*$B$13+calculations!P72*$B$14+calculations!P73*$B$15*INDEX(input_data!$L:$L,MATCH("all.in.cs2.stl.scr.---",input_data!$A:$A,0)))*G29,0)+IFERROR((calculations!P77/calculations!P76)*((calculations!P97+calculations!P254)*$B$11+calculations!P98*$B$12+calculations!P99*$B$13+calculations!P100*$B$14+calculations!P101*$B$15*INDEX(input_data!$L:$L,MATCH("all.in.cs2.stl.bof.---",input_data!$A:$A,0)))*G29,0)+IFERROR((calculations!P105/calculations!P104)*((calculations!P125+calculations!P259)*$B$11+calculations!P126*$B$12+calculations!P127*$B$13+calculations!P128*$B$14+calculations!P129*$B$15*INDEX(input_data!$L:$L,MATCH("all.in.cs2.cmt.dry.---",input_data!$A:$A,0)))*G29,0)+IFERROR((calculations!P133/calculations!P132)*((calculations!P153+calculations!P264)*$B$11+calculations!P154*$B$12+calculations!P155*$B$13+calculations!P156*$B$14+calculations!P157*$B$15*INDEX(input_data!$L:$L,MATCH("all.in.cs2.frt.amc.---",input_data!$A:$A,0)))*G29,0)+IFERROR((calculations!P161/calculations!P160)*((calculations!P181+calculations!P269)*$B$11+calculations!P182*$B$12+calculations!P183*$B$13+calculations!P184*$B$14+calculations!P185*$B$15*INDEX(input_data!$L:$L,MATCH("all.in.cs2.frt.ure.---",input_data!$A:$A,0)))*G29,0)+IFERROR((calculations!P189/calculations!P188)*((calculations!P209+calculations!P274)*$B$11+calculations!P210*$B$12+calculations!P211*$B$13+calculations!P212*$B$14+calculations!P213*$B$15*INDEX(input_data!$L:$L,MATCH("all.in.cs2.frt.nit.---",input_data!$A:$A,0)))*G29,0)+IFERROR((calculations!P217/calculations!P216)*((calculations!P237+calculations!P279)*$B$11+calculations!P238*$B$12+calculations!P239*$B$13+calculations!P240*$B$14+calculations!P241*$B$15*INDEX(input_data!$L:$L,MATCH("all.in.cs2.alu.prp.---",input_data!$A:$A,0)))*G29,0) -> 220.85903 | H35: =IFERROR((calculations!Q21/calculations!Q20)*((calculations!Q41+calculations!Q244)*$B$11+calculations!Q42*$B$12+calculations!Q43*$B$13+calculations!Q44*$B$14+calculations!Q45*$B$15*INDEX(input_data!$L:$L,MATCH("all.in.cs2.stl.drg.---",input_data!$A:$A,0)))*H29,0)+IFERROR((calculations!Q49/calculations!Q48)*((calculations!Q69+calculations!Q249)*$B$11+calculations!Q70*$B$12+calculations!Q71*$B$13+calculations!Q72*$B$14+calculations!Q73*$B$15*INDEX(input_data!$L:$L,MATCH("all.in.cs2.stl.scr.---",input_data!$A:$A,0)))*H29,0)+IFERROR((calculations!Q77/calculations!Q76)*((calculations!Q97+calculations!Q254)*$B$11+calculations!Q98*$B$12+calculations!Q99*$B$13+calculations!Q100*$B$14+calculations!Q101*$B$15*INDEX(input_data!$L:$L,MATCH("all.in.cs2.stl.bof.---",input_data!$A:$A,0)))*H29,0)+IFERROR((calculations!Q105/calculations!Q104)*((calculations!Q125+calculations!Q259)*$B$11+calculations!Q126*$B$12+calculations!Q127*$B$13+calculations!Q128*$B$14+calculations!Q129*$B$15*INDEX(input_data!$L:$L,MATCH("all.in.cs2.cmt.dry.---",input_data!$A:$A,0)))*H29,0)+IFERROR((calculations!Q133/calculations!Q132)*((calculations!Q153+calculations!Q264)*$B$11+calculations!Q154*$B$12+calculations!Q155*$B$13+calculations!Q156*$B$14+calculations!Q157*$B$15*INDEX(input_data!$L:$L,MATCH("all.in.cs2.frt.amc.---",input_data!$A:$A,0)))*H29,0)+IFERROR((calculations!Q161/calculations!Q160)*((calculations!Q181+calculations!Q269)*$B$11+calculations!Q182*$B$12+calculations!Q183*$B$13+calculations!Q184*$B$14+calculations!Q185*$B$15*INDEX(input_data!$L:$L,MATCH("all.in.cs2.frt.ure.---",input_data!$A:$A,0)))*H29,0)+IFERROR((calculations!Q189/calculations!Q188)*((calculations!Q209+calculations!Q274)*$B$11+calculations!Q210*$B$12+calculations!Q211*$B$13+calculations!Q212*$B$14+calculations!Q213*$B$15*INDEX(input_data!$L:$L,MATCH("all.in.cs2.frt.nit.---",input_data!$A:$A,0)))*H29,0)+IFERROR((calculations!Q217/calculations!Q216)*((calculations!Q237+calculations!Q279)*$B$11+calculations!Q238*$B$12+calculations!Q239*$B$13+calculations!Q240*$B$14+calculations!Q241*$B$15*INDEX(input_data!$L:$L,MATCH("all.in.cs2.alu.prp.---",input_data!$A:$A,0)))*H29,0) -> 251.4489 | I35: =IFERROR((calculations!R21/calculations!R20)*((calculations!R41+calculations!R244)*$B$11+calculations!R42*$B$12+calculations!R43*$B$13+calculations!R44*$B$14+calculations!R45*$B$15*INDEX(input_data!$L:$L,MATCH("all.in.cs2.stl.drg.---",input_data!$A:$A,0)))*I29,0)+IFERROR((calculations!R49/calculations!R48)*((calculations!R69+calculations!R249)*$B$11+calculations!R70*$B$12+calculations!R71*$B$13+calculations!R72*$B$14+calculations!R73*$B$15*INDEX(input_data!$L:$L,MATCH("all.in.cs2.stl.scr.---",input_data!$A:$A,0)))*I29,0)+IFERROR((calculations!R77/calculations!R76)*((calculations!R97+calculations!R254)*$B$11+calculations!R98*$B$12+calculations!R99*$B$13+calculations!R100*$B$14+calculations!R101*$B$15*INDEX(input_data!$L:$L,MATCH("all.in.cs2.stl.bof.---",input_data!$A:$A,0)))*I29,0)+IFERROR((calculations!R105/calculations!R104)*((calculations!R125+calculations!R259)*$B$11+calculations!R126*$B$12+calculations!R127*$B$13+calculations!R128*$B$14+calculations!R129*$B$15*INDEX(input_data!$L:$L,MATCH("all.in.cs2.cmt.dry.---",input_data!$A:$A,0)))*I29,0)+IFERROR((calculations!R133/calculations!R132)*((calculations!R153+calculations!R264)*$B$11+calculations!R154*$B$12+calculations!R155*$B$13+calculations!R156*$B$14+calculations!R157*$B$15*INDEX(input_data!$L:$L,MATCH("all.in.cs2.frt.amc.---",input_data!$A:$A,0)))*I29,0)+IFERROR((calculations!R161/calculations!R160)*((calculations!R181+calculations!R269)*$B$11+calculations!R182*$B$12+calculations!R183*$B$13+calculations!R184*$B$14+calculations!R185*$B$15*INDEX(input_data!$L:$L,MATCH("all.in.cs2.frt.ure.---",input_data!$A:$A,0)))*I29,0)+IFERROR((calculations!R189/calculations!R188)*((calculations!R209+calculations!R274)*$B$11+calculations!R210*$B$12+calculations!R211*$B$13+calculations!R212*$B$14+calculations!R213*$B$15*INDEX(input_data!$L:$L,MATCH("all.in.cs2.frt.nit.---",input_data!$A:$A,0)))*I29,0)+IFERROR((calculations!R217/calculations!R216)*((calculations!R237+calculations!R279)*$B$11+calculations!R238*$B$12+calculations!R239*$B$13+calculations!R240*$B$14+calculations!R241*$B$15*INDEX(input_data!$L:$L,MATCH("all.in.cs2.alu.prp.---",input_data!$A:$A,0)))*I29,0) -> 287.19454 | J35: =IFERROR((calculations!S21/calculations!S20)*((calculations!S41+calculations!S244)*$B$11+calculations!S42*$B$12+calculations!S43*$B$13+calculations!S44*$B$14+calculations!S45*$B$15*INDEX(input_data!$L:$L,MATCH("all.in.cs2.stl.drg.---",input_data!$A:$A,0)))*J29,0)+IFERROR((calculations!S49/calculations!S48)*((calculations!S69+calculations!S249)*$B$11+calculations!S70*$B$12+calculations!S71*$B$13+calculations!S72*$B$14+calculations!S73*$B$15*INDEX(input_data!$L:$L,MATCH("all.in.cs2.stl.scr.---",input_data!$A:$A,0)))*J29,0)+IFERROR((calculations!S77/calculations!S76)*((calculations!S97+calculations!S254)*$B$11+calculations!S98*$B$12+calculations!S99*$B$13+calculations!S100*$B$14+calculations!S101*$B$15*INDEX(input_data!$L:$L,MATCH("all.in.cs2.stl.bof.---",input_data!$A:$A,0)))*J29,0)+IFERROR((calculations!S105/calculations!S104)*((calculations!S125+calculations!S259)*$B$11+calculations!S126*$B$12+calculations!S127*$B$13+calculations!S128*$B$14+calculations!S129*$B$15*INDEX(input_data!$L:$L,MATCH("all.in.cs2.cmt.dry.---",input_data!$A:$A,0)))*J29,0)+IFERROR((calculations!S133/calculations!S132)*((calculations!S153+calculations!S264)*$B$11+calculations!S154*$B$12+calculations!S155*$B$13+calculations!S156*$B$14+calculations!S157*$B$15*INDEX(input_data!$L:$L,MATCH("all.in.cs2.frt.amc.---",input_data!$A:$A,0)))*J29,0)+IFERROR((calculations!S161/calculations!S160)*((calculations!S181+calculations!S269)*$B$11+calculations!S182*$B$12+calculations!S183*$B$13+calculations!S184*$B$14+calculations!S185*$B$15*INDEX(input_data!$L:$L,MATCH("all.in.cs2.frt.ure.---",input_data!$A:$A,0)))*J29,0)+IFERROR((calculations!S189/calculations!S188)*((calculations!S209+calculations!S274)*$B$11+calculations!S210*$B$12+calculations!S211*$B$13+calculations!S212*$B$14+calculations!S213*$B$15*INDEX(input_data!$L:$L,MATCH("all.in.cs2.frt.nit.---",input_data!$A:$A,0)))*J29,0)+IFERROR((calculations!S217/calculations!S216)*((calculations!S237+calculations!S279)*$B$11+calculations!S238*$B$12+calculations!S239*$B$13+calculations!S240*$B$14+calculations!S241*$B$15*INDEX(input_data!$L:$L,MATCH("all.in.cs2.alu.prp.---",input_data!$A:$A,0)))*J29,0) -> 375.61474 | K35: =IFERROR((calculations!T21/calculations!T20)*((calculations!T41+calculations!T244)*$B$11+calculations!T42*$B$12+calculations!T43*$B$13+calculations!T44*$B$14+calculations!T45*$B$15*INDEX(input_data!$L:$L,MATCH("all.in.cs2.stl.drg.---",input_data!$A:$A,0)))*K29,0)+IFERROR((calculations!T49/calculations!T48)*((calculations!T69+calculations!T249)*$B$11+calculations!T70*$B$12+calculations!T71*$B$13+calculations!T72*$B$14+calculations!T73*$B$15*INDEX(input_data!$L:$L,MATCH("all.in.cs2.stl.scr.---",input_data!$A:$A,0)))*K29,0)+IFERROR((calculations!T77/calculations!T76)*((calculations!T97+calculations!T254)*$B$11+calculations!T98*$B$12+calculations!T99*$B$13+calculations!T100*$B$14+calculations!T101*$B$15*INDEX(input_data!$L:$L,MATCH("all.in.cs2.stl.bof.---",input_data!$A:$A,0)))*K29,0)+IFERROR((calculations!T105/calculations!T104)*((calculations!T125+calculations!T259)*$B$11+calculations!T126*$B$12+calculations!T127*$B$13+calculations!T128*$B$14+calculations!T129*$B$15*INDEX(input_data!$L:$L,MATCH("all.in.cs2.cmt.dry.---",input_data!$A:$A,0)))*K29,0)+IFERROR((calculations!T133/calculations!T132)*((calculations!T153+calculations!T264)*$B$11+calculations!T154*$B$12+calculations!T155*$B$13+calculations!T156*$B$14+calculations!T157*$B$15*INDEX(input_data!$L:$L,MATCH("all.in.cs2.frt.amc.---",input_data!$A:$A,0)))*K29,0)+IFERROR((calculations!T161/calculations!T160)*((calculations!T181+calculations!T269)*$B$11+calculations!T182*$B$12+calculations!T183*$B$13+calculations!T184*$B$14+calculations!T185*$B$15*INDEX(input_data!$L:$L,MATCH("all.in.cs2.frt.ure.---",input_data!$A:$A,0)))*K29,0)+IFERROR((calculations!T189/calculations!T188)*((calculations!T209+calculations!T274)*$B$11+calculations!T210*$B$12+calculations!T211*$B$13+calculations!T212*$B$14+calculations!T213*$B$15*INDEX(input_data!$L:$L,MATCH("all.in.cs2.frt.nit.---",input_data!$A:$A,0)))*K29,0)+IFERROR((calculations!T217/calculations!T216)*((calculations!T237+calculations!T279)*$B$11+calculations!T238*$B$12+calculations!T239*$B$13+calculations!T240*$B$14+calculations!T241*$B$15*INDEX(input_data!$L:$L,MATCH("all.in.cs2.alu.prp.---",input_data!$A:$A,0)))*K29,0) -> 444.09747 | ... O35: =IFERROR((calculations!X21/calculations!X20)*((calculations!X41+calculations!X244)*$B$11+calculations!X42*$B$12+calculations!X43*$B$13+calculations!X44*$B$14+calculations!X45*$B$15*INDEX(input_data!$L:$L,MATCH("all.in.cs2.stl.drg.---",input_data!$A:$A,0)))*O29,0)+IFERROR((calculations!X49/calculations!X48)*((calculations!X69+calculations!X249)*$B$11+calculations!X70*$B$12+calculations!X71*$B$13+calculations!X72*$B$14+calculations!X73*$B$15*INDEX(input_data!$L:$L,MATCH("all.in.cs2.stl.scr.---",input_data!$A:$A,0)))*O29,0)+IFERROR((calculations!X77/calculations!X76)*((calculations!X97+calculations!X254)*$B$11+calculations!X98*$B$12+calculations!X99*$B$13+calculations!X100*$B$14+calculations!X101*$B$15*INDEX(input_data!$L:$L,MATCH("all.in.cs2.stl.bof.---",input_data!$A:$A,0)))*O29,0)+IFERROR((calculations!X105/calculations!X104)*((calculations!X125+calculations!X259)*$B$11+calculations!X126*$B$12+calculations!X127*$B$13+calculations!X128*$B$14+calculations!X129*$B$15*INDEX(input_data!$L:$L,MATCH("all.in.cs2.cmt.dry.---",input_data!$A:$A,0)))*O29,0)+IFERROR((calculations!X133/calculations!X132)*((calculations!X153+calculations!X264)*$B$11+calculations!X154*$B$12+calculations!X155*$B$13+calculations!X156*$B$14+calculations!X157*$B$15*INDEX(input_data!$L:$L,MATCH("all.in.cs2.frt.amc.---",input_data!$A:$A,0)))*O29,0)+IFERROR((calculations!X161/calculations!X160)*((calculations!X181+calculations!X269)*$B$11+calculations!X182*$B$12+calculations!X183*$B$13+calculations!X184*$B$14+calculations!X185*$B$15*INDEX(input_data!$L:$L,MATCH("all.in.cs2.frt.ure.---",input_data!$A:$A,0)))*O29,0)+IFERROR((calculations!X189/calculations!X188)*((calculations!X209+calculations!X274)*$B$11+calculations!X210*$B$12+calculations!X211*$B$13+calculations!X212*$B$14+calculations!X213*$B$15*INDEX(input_data!$L:$L,MATCH("all.in.cs2.frt.nit.---",input_data!$A:$A,0)))*O29,0)+IFERROR((calculations!X217/calculations!X216)*((calculations!X237+calculations!X279)*$B$11+calculations!X238*$B$12+calculations!X239*$B$13+calculations!X240*$B$14+calculations!X241*$B$15*INDEX(input_data!$L:$L,MATCH("all.in.cs2.alu.prp.---",input_data!$A:$A,0)))*O29,0) -> 767.15512
A36: ● EU CBAM retained = MAX(gross − creditable, 0) | B36: USD m | D36: =MAX(D33-D35,0) -> 0 | E36: =MAX(E33-E35,0) -> 0 | F36: =MAX(F33-F35,0) -> 0 | G36: =MAX(G33-G35,0) -> 0 | H36: =MAX(H33-H35,0) -> 0 | I36: =MAX(I33-I35,0) -> 0 | J36: =MAX(J33-J35,0) -> 0 | K36: =MAX(K33-K35,0) -> 0 | ... O36: =MAX(O33-O35,0) -> 0
A37: ● Country revenue on non-EU exports | B37: USD m | D37: =IFERROR((calculations!M22/calculations!M20)*((calculations!M41+calculations!M244)*$B$11+calculations!M42*$B$12+calculations!M43*$B$13+calculations!M44*$B$14+calculations!M45*$B$15)*D29,0)+IFERROR((calculations!M50/calculations!M48)*((calculations!M69+calculations!M249)*$B$11+calculations!M70*$B$12+calculations!M71*$B$13+calculations!M72*$B$14+calculations!M73*$B$15)*D29,0)+IFERROR((calculations!M78/calculations!M76)*((calculations!M97+calculations!M254)*$B$11+calculations!M98*$B$12+calculations!M99*$B$13+calculations!M100*$B$14+calculations!M101*$B$15)*D29,0)+IFERROR((calculations!M106/calculations!M104)*((calculations!M125+calculations!M259)*$B$11+calculations!M126*$B$12+calculations!M127*$B$13+calculations!M128*$B$14+calculations!M129*$B$15)*D29,0)+IFERROR((calculations!M134/calculations!M132)*((calculations!M153+calculations!M264)*$B$11+calculations!M154*$B$12+calculations!M155*$B$13+calculations!M156*$B$14+calculations!M157*$B$15)*D29,0)+IFERROR((calculations!M162/calculations!M160)*((calculations!M181+calculations!M269)*$B$11+calculations!M182*$B$12+calculations!M183*$B$13+calculations!M184*$B$14+calculations!M185*$B$15)*D29,0)+IFERROR((calculations!M190/calculations!M188)*((calculations!M209+calculations!M274)*$B$11+calculations!M210*$B$12+calculations!M211*$B$13+calculations!M212*$B$14+calculations!M213*$B$15)*D29,0)+IFERROR((calculations!M218/calculations!M216)*((calculations!M237+calculations!M279)*$B$11+calculations!M238*$B$12+calculations!M239*$B$13+calculations!M240*$B$14+calculations!M241*$B$15)*D29,0) -> 0 | E37: =IFERROR((calculations!N22/calculations!N20)*((calculations!N41+calculations!N244)*$B$11+calculations!N42*$B$12+calculations!N43*$B$13+calculations!N44*$B$14+calculations!N45*$B$15)*E29,0)+IFERROR((calculations!N50/calculations!N48)*((calculations!N69+calculations!N249)*$B$11+calculations!N70*$B$12+calculations!N71*$B$13+calculations!N72*$B$14+calculations!N73*$B$15)*E29,0)+IFERROR((calculations!N78/calculations!N76)*((calculations!N97+calculations!N254)*$B$11+calculations!N98*$B$12+calculations!N99*$B$13+calculations!N100*$B$14+calculations!N101*$B$15)*E29,0)+IFERROR((calculations!N106/calculations!N104)*((calculations!N125+calculations!N259)*$B$11+calculations!N126*$B$12+calculations!N127*$B$13+calculations!N128*$B$14+calculations!N129*$B$15)*E29,0)+IFERROR((calculations!N134/calculations!N132)*((calculations!N153+calculations!N264)*$B$11+calculations!N154*$B$12+calculations!N155*$B$13+calculations!N156*$B$14+calculations!N157*$B$15)*E29,0)+IFERROR((calculations!N162/calculations!N160)*((calculations!N181+calculations!N269)*$B$11+calculations!N182*$B$12+calculations!N183*$B$13+calculations!N184*$B$14+calculations!N185*$B$15)*E29,0)+IFERROR((calculations!N190/calculations!N188)*((calculations!N209+calculations!N274)*$B$11+calculations!N210*$B$12+calculations!N211*$B$13+calculations!N212*$B$14+calculations!N213*$B$15)*E29,0)+IFERROR((calculations!N218/calculations!N216)*((calculations!N237+calculations!N279)*$B$11+calculations!N238*$B$12+calculations!N239*$B$13+calculations!N240*$B$14+calculations!N241*$B$15)*E29,0) -> 0 | F37: =IFERROR((calculations!O22/calculations!O20)*((calculations!O41+calculations!O244)*$B$11+calculations!O42*$B$12+calculations!O43*$B$13+calculations!O44*$B$14+calculations!O45*$B$15)*F29,0)+IFERROR((calculations!O50/calculations!O48)*((calculations!O69+calculations!O249)*$B$11+calculations!O70*$B$12+calculations!O71*$B$13+calculations!O72*$B$14+calculations!O73*$B$15)*F29,0)+IFERROR((calculations!O78/calculations!O76)*((calculations!O97+calculations!O254)*$B$11+calculations!O98*$B$12+calculations!O99*$B$13+calculations!O100*$B$14+calculations!O101*$B$15)*F29,0)+IFERROR((calculations!O106/calculations!O104)*((calculations!O125+calculations!O259)*$B$11+calculations!O126*$B$12+calculations!O127*$B$13+calculations!O128*$B$14+calculations!O129*$B$15)*F29,0)+IFERROR((calculations!O134/calculations!O132)*((calculations!O153+calculations!O264)*$B$11+calculations!O154*$B$12+calculations!O155*$B$13+calculations!O156*$B$14+calculations!O157*$B$15)*F29,0)+IFERROR((calculations!O162/calculations!O160)*((calculations!O181+calculations!O269)*$B$11+calculations!O182*$B$12+calculations!O183*$B$13+calculations!O184*$B$14+calculations!O185*$B$15)*F29,0)+IFERROR((calculations!O190/calculations!O188)*((calculations!O209+calculations!O274)*$B$11+calculations!O210*$B$12+calculations!O211*$B$13+calculations!O212*$B$14+calculations!O213*$B$15)*F29,0)+IFERROR((calculations!O218/calculations!O216)*((calculations!O237+calculations!O279)*$B$11+calculations!O238*$B$12+calculations!O239*$B$13+calculations!O240*$B$14+calculations!O241*$B$15)*F29,0) -> 388.11291 | G37: =IFERROR((calculations!P22/calculations!P20)*((calculations!P41+calculations!P244)*$B$11+calculations!P42*$B$12+calculations!P43*$B$13+calculations!P44*$B$14+calculations!P45*$B$15)*G29,0)+IFERROR((calculations!P50/calculations!P48)*((calculations!P69+calculations!P249)*$B$11+calculations!P70*$B$12+calculations!P71*$B$13+calculations!P72*$B$14+calculations!P73*$B$15)*G29,0)+IFERROR((calculations!P78/calculations!P76)*((calculations!P97+calculations!P254)*$B$11+calculations!P98*$B$12+calculations!P99*$B$13+calculations!P100*$B$14+calculations!P101*$B$15)*G29,0)+IFERROR((calculations!P106/calculations!P104)*((calculations!P125+calculations!P259)*$B$11+calculations!P126*$B$12+calculations!P127*$B$13+calculations!P128*$B$14+calculations!P129*$B$15)*G29,0)+IFERROR((calculations!P134/calculations!P132)*((calculations!P153+calculations!P264)*$B$11+calculations!P154*$B$12+calculations!P155*$B$13+calculations!P156*$B$14+calculations!P157*$B$15)*G29,0)+IFERROR((calculations!P162/calculations!P160)*((calculations!P181+calculations!P269)*$B$11+calculations!P182*$B$12+calculations!P183*$B$13+calculations!P184*$B$14+calculations!P185*$B$15)*G29,0)+IFERROR((calculations!P190/calculations!P188)*((calculations!P209+calculations!P274)*$B$11+calculations!P210*$B$12+calculations!P211*$B$13+calculations!P212*$B$14+calculations!P213*$B$15)*G29,0)+IFERROR((calculations!P218/calculations!P216)*((calculations!P237+calculations!P279)*$B$11+calculations!P238*$B$12+calculations!P239*$B$13+calculations!P240*$B$14+calculations!P241*$B$15)*G29,0) -> 433.83851 | H37: =IFERROR((calculations!Q22/calculations!Q20)*((calculations!Q41+calculations!Q244)*$B$11+calculations!Q42*$B$12+calculations!Q43*$B$13+calculations!Q44*$B$14+calculations!Q45*$B$15)*H29,0)+IFERROR((calculations!Q50/calculations!Q48)*((calculations!Q69+calculations!Q249)*$B$11+calculations!Q70*$B$12+calculations!Q71*$B$13+calculations!Q72*$B$14+calculations!Q73*$B$15)*H29,0)+IFERROR((calculations!Q78/calculations!Q76)*((calculations!Q97+calculations!Q254)*$B$11+calculations!Q98*$B$12+calculations!Q99*$B$13+calculations!Q100*$B$14+calculations!Q101*$B$15)*H29,0)+IFERROR((calculations!Q106/calculations!Q104)*((calculations!Q125+calculations!Q259)*$B$11+calculations!Q126*$B$12+calculations!Q127*$B$13+calculations!Q128*$B$14+calculations!Q129*$B$15)*H29,0)+IFERROR((calculations!Q134/calculations!Q132)*((calculations!Q153+calculations!Q264)*$B$11+calculations!Q154*$B$12+calculations!Q155*$B$13+calculations!Q156*$B$14+calculations!Q157*$B$15)*H29,0)+IFERROR((calculations!Q162/calculations!Q160)*((calculations!Q181+calculations!Q269)*$B$11+calculations!Q182*$B$12+calculations!Q183*$B$13+calculations!Q184*$B$14+calculations!Q185*$B$15)*H29,0)+IFERROR((calculations!Q190/calculations!Q188)*((calculations!Q209+calculations!Q274)*$B$11+calculations!Q210*$B$12+calculations!Q211*$B$13+calculations!Q212*$B$14+calculations!Q213*$B$15)*H29,0)+IFERROR((calculations!Q218/calculations!Q216)*((calculations!Q237+calculations!Q279)*$B$11+calculations!Q238*$B$12+calculations!Q239*$B$13+calculations!Q240*$B$14+calculations!Q241*$B$15)*H29,0) -> 492.59871 | I37: =IFERROR((calculations!R22/calculations!R20)*((calculations!R41+calculations!R244)*$B$11+calculations!R42*$B$12+calculations!R43*$B$13+calculations!R44*$B$14+calculations!R45*$B$15)*I29,0)+IFERROR((calculations!R50/calculations!R48)*((calculations!R69+calculations!R249)*$B$11+calculations!R70*$B$12+calculations!R71*$B$13+calculations!R72*$B$14+calculations!R73*$B$15)*I29,0)+IFERROR((calculations!R78/calculations!R76)*((calculations!R97+calculations!R254)*$B$11+calculations!R98*$B$12+calculations!R99*$B$13+calculations!R100*$B$14+calculations!R101*$B$15)*I29,0)+IFERROR((calculations!R106/calculations!R104)*((calculations!R125+calculations!R259)*$B$11+calculations!R126*$B$12+calculations!R127*$B$13+calculations!R128*$B$14+calculations!R129*$B$15)*I29,0)+IFERROR((calculations!R134/calculations!R132)*((calculations!R153+calculations!R264)*$B$11+calculations!R154*$B$12+calculations!R155*$B$13+calculations!R156*$B$14+calculations!R157*$B$15)*I29,0)+IFERROR((calculations!R162/calculations!R160)*((calculations!R181+calculations!R269)*$B$11+calculations!R182*$B$12+calculations!R183*$B$13+calculations!R184*$B$14+calculations!R185*$B$15)*I29,0)+IFERROR((calculations!R190/calculations!R188)*((calculations!R209+calculations!R274)*$B$11+calculations!R210*$B$12+calculations!R211*$B$13+calculations!R212*$B$14+calculations!R213*$B$15)*I29,0)+IFERROR((calculations!R218/calculations!R216)*((calculations!R237+calculations!R279)*$B$11+calculations!R238*$B$12+calculations!R239*$B$13+calculations!R240*$B$14+calculations!R241*$B$15)*I29,0) -> 561.06281 | J37: =IFERROR((calculations!S22/calculations!S20)*((calculations!S41+calculations!S244)*$B$11+calculations!S42*$B$12+calculations!S43*$B$13+calculations!S44*$B$14+calculations!S45*$B$15)*J29,0)+IFERROR((calculations!S50/calculations!S48)*((calculations!S69+calculations!S249)*$B$11+calculations!S70*$B$12+calculations!S71*$B$13+calculations!S72*$B$14+calculations!S73*$B$15)*J29,0)+IFERROR((calculations!S78/calculations!S76)*((calculations!S97+calculations!S254)*$B$11+calculations!S98*$B$12+calculations!S99*$B$13+calculations!S100*$B$14+calculations!S101*$B$15)*J29,0)+IFERROR((calculations!S106/calculations!S104)*((calculations!S125+calculations!S259)*$B$11+calculations!S126*$B$12+calculations!S127*$B$13+calculations!S128*$B$14+calculations!S129*$B$15)*J29,0)+IFERROR((calculations!S134/calculations!S132)*((calculations!S153+calculations!S264)*$B$11+calculations!S154*$B$12+calculations!S155*$B$13+calculations!S156*$B$14+calculations!S157*$B$15)*J29,0)+IFERROR((calculations!S162/calculations!S160)*((calculations!S181+calculations!S269)*$B$11+calculations!S182*$B$12+calculations!S183*$B$13+calculations!S184*$B$14+calculations!S185*$B$15)*J29,0)+IFERROR((calculations!S190/calculations!S188)*((calculations!S209+calculations!S274)*$B$11+calculations!S210*$B$12+calculations!S211*$B$13+calculations!S212*$B$14+calculations!S213*$B$15)*J29,0)+IFERROR((calculations!S218/calculations!S216)*((calculations!S237+calculations!S279)*$B$11+calculations!S238*$B$12+calculations!S239*$B$13+calculations!S240*$B$14+calculations!S241*$B$15)*J29,0) -> 731.69712 | K37: =IFERROR((calculations!T22/calculations!T20)*((calculations!T41+calculations!T244)*$B$11+calculations!T42*$B$12+calculations!T43*$B$13+calculations!T44*$B$14+calculations!T45*$B$15)*K29,0)+IFERROR((calculations!T50/calculations!T48)*((calculations!T69+calculations!T249)*$B$11+calculations!T70*$B$12+calculations!T71*$B$13+calculations!T72*$B$14+calculations!T73*$B$15)*K29,0)+IFERROR((calculations!T78/calculations!T76)*((calculations!T97+calculations!T254)*$B$11+calculations!T98*$B$12+calculations!T99*$B$13+calculations!T100*$B$14+calculations!T101*$B$15)*K29,0)+IFERROR((calculations!T106/calculations!T104)*((calculations!T125+calculations!T259)*$B$11+calculations!T126*$B$12+calculations!T127*$B$13+calculations!T128*$B$14+calculations!T129*$B$15)*K29,0)+IFERROR((calculations!T134/calculations!T132)*((calculations!T153+calculations!T264)*$B$11+calculations!T154*$B$12+calculations!T155*$B$13+calculations!T156*$B$14+calculations!T157*$B$15)*K29,0)+IFERROR((calculations!T162/calculations!T160)*((calculations!T181+calculations!T269)*$B$11+calculations!T182*$B$12+calculations!T183*$B$13+calculations!T184*$B$14+calculations!T185*$B$15)*K29,0)+IFERROR((calculations!T190/calculations!T188)*((calculations!T209+calculations!T274)*$B$11+calculations!T210*$B$12+calculations!T211*$B$13+calculations!T212*$B$14+calculations!T213*$B$15)*K29,0)+IFERROR((calculations!T218/calculations!T216)*((calculations!T237+calculations!T279)*$B$11+calculations!T238*$B$12+calculations!T239*$B$13+calculations!T240*$B$14+calculations!T241*$B$15)*K29,0) -> 862.54653 | ... O37: =IFERROR((calculations!X22/calculations!X20)*((calculations!X41+calculations!X244)*$B$11+calculations!X42*$B$12+calculations!X43*$B$13+calculations!X44*$B$14+calculations!X45*$B$15)*O29,0)+IFERROR((calculations!X50/calculations!X48)*((calculations!X69+calculations!X249)*$B$11+calculations!X70*$B$12+calculations!X71*$B$13+calculations!X72*$B$14+calculations!X73*$B$15)*O29,0)+IFERROR((calculations!X78/calculations!X76)*((calculations!X97+calculations!X254)*$B$11+calculations!X98*$B$12+calculations!X99*$B$13+calculations!X100*$B$14+calculations!X101*$B$15)*O29,0)+IFERROR((calculations!X106/calculations!X104)*((calculations!X125+calculations!X259)*$B$11+calculations!X126*$B$12+calculations!X127*$B$13+calculations!X128*$B$14+calculations!X129*$B$15)*O29,0)+IFERROR((calculations!X134/calculations!X132)*((calculations!X153+calculations!X264)*$B$11+calculations!X154*$B$12+calculations!X155*$B$13+calculations!X156*$B$14+calculations!X157*$B$15)*O29,0)+IFERROR((calculations!X162/calculations!X160)*((calculations!X181+calculations!X269)*$B$11+calculations!X182*$B$12+calculations!X183*$B$13+calculations!X184*$B$14+calculations!X185*$B$15)*O29,0)+IFERROR((calculations!X190/calculations!X188)*((calculations!X209+calculations!X274)*$B$11+calculations!X210*$B$12+calculations!X211*$B$13+calculations!X212*$B$14+calculations!X213*$B$15)*O29,0)+IFERROR((calculations!X218/calculations!X216)*((calculations!X237+calculations!X279)*$B$11+calculations!X238*$B$12+calculations!X239*$B$13+calculations!X240*$B$14+calculations!X241*$B$15)*O29,0) -> 1471.2284
A38: ● Country revenue on domestic consumption (zero if 2c=1) | B38: USD m | D38: =IFERROR((1-$B$22)*(calculations!M23/calculations!M20)*((calculations!M41+calculations!M244)*$B$11+calculations!M42*$B$12+calculations!M43*$B$13+calculations!M44*$B$14+calculations!M45*$B$15)*D29,0)+IFERROR((1-$B$22)*(calculations!M51/calculations!M48)*((calculations!M69+calculations!M249)*$B$11+calculations!M70*$B$12+calculations!M71*$B$13+calculations!M72*$B$14+calculations!M73*$B$15)*D29,0)+IFERROR((1-$B$22)*(calculations!M79/calculations!M76)*((calculations!M97+calculations!M254)*$B$11+calculations!M98*$B$12+calculations!M99*$B$13+calculations!M100*$B$14+calculations!M101*$B$15)*D29,0)+IFERROR((1-$B$22)*(calculations!M107/calculations!M104)*((calculations!M125+calculations!M259)*$B$11+calculations!M126*$B$12+calculations!M127*$B$13+calculations!M128*$B$14+calculations!M129*$B$15)*D29,0)+IFERROR((1-$B$22)*(calculations!M135/calculations!M132)*((calculations!M153+calculations!M264)*$B$11+calculations!M154*$B$12+calculations!M155*$B$13+calculations!M156*$B$14+calculations!M157*$B$15)*D29,0)+IFERROR((1-$B$22)*(calculations!M163/calculations!M160)*((calculations!M181+calculations!M269)*$B$11+calculations!M182*$B$12+calculations!M183*$B$13+calculations!M184*$B$14+calculations!M185*$B$15)*D29,0)+IFERROR((1-$B$22)*(calculations!M191/calculations!M188)*((calculations!M209+calculations!M274)*$B$11+calculations!M210*$B$12+calculations!M211*$B$13+calculations!M212*$B$14+calculations!M213*$B$15)*D29,0)+IFERROR((1-$B$22)*(calculations!M219/calculations!M216)*((calculations!M237+calculations!M279)*$B$11+calculations!M238*$B$12+calculations!M239*$B$13+calculations!M240*$B$14+calculations!M241*$B$15)*D29,0) -> 0 | E38: =IFERROR((1-$B$22)*(calculations!N23/calculations!N20)*((calculations!N41+calculations!N244)*$B$11+calculations!N42*$B$12+calculations!N43*$B$13+calculations!N44*$B$14+calculations!N45*$B$15)*E29,0)+IFERROR((1-$B$22)*(calculations!N51/calculations!N48)*((calculations!N69+calculations!N249)*$B$11+calculations!N70*$B$12+calculations!N71*$B$13+calculations!N72*$B$14+calculations!N73*$B$15)*E29,0)+IFERROR((1-$B$22)*(calculations!N79/calculations!N76)*((calculations!N97+calculations!N254)*$B$11+calculations!N98*$B$12+calculations!N99*$B$13+calculations!N100*$B$14+calculations!N101*$B$15)*E29,0)+IFERROR((1-$B$22)*(calculations!N107/calculations!N104)*((calculations!N125+calculations!N259)*$B$11+calculations!N126*$B$12+calculations!N127*$B$13+calculations!N128*$B$14+calculations!N129*$B$15)*E29,0)+IFERROR((1-$B$22)*(calculations!N135/calculations!N132)*((calculations!N153+calculations!N264)*$B$11+calculations!N154*$B$12+calculations!N155*$B$13+calculations!N156*$B$14+calculations!N157*$B$15)*E29,0)+IFERROR((1-$B$22)*(calculations!N163/calculations!N160)*((calculations!N181+calculations!N269)*$B$11+calculations!N182*$B$12+calculations!N183*$B$13+calculations!N184*$B$14+calculations!N185*$B$15)*E29,0)+IFERROR((1-$B$22)*(calculations!N191/calculations!N188)*((calculations!N209+calculations!N274)*$B$11+calculations!N210*$B$12+calculations!N211*$B$13+calculations!N212*$B$14+calculations!N213*$B$15)*E29,0)+IFERROR((1-$B$22)*(calculations!N219/calculations!N216)*((calculations!N237+calculations!N279)*$B$11+calculations!N238*$B$12+calculations!N239*$B$13+calculations!N240*$B$14+calculations!N241*$B$15)*E29,0) -> 0 | F38: =IFERROR((1-$B$22)*(calculations!O23/calculations!O20)*((calculations!O41+calculations!O244)*$B$11+calculations!O42*$B$12+calculations!O43*$B$13+calculations!O44*$B$14+calculations!O45*$B$15)*F29,0)+IFERROR((1-$B$22)*(calculations!O51/calculations!O48)*((calculations!O69+calculations!O249)*$B$11+calculations!O70*$B$12+calculations!O71*$B$13+calculations!O72*$B$14+calculations!O73*$B$15)*F29,0)+IFERROR((1-$B$22)*(calculations!O79/calculations!O76)*((calculations!O97+calculations!O254)*$B$11+calculations!O98*$B$12+calculations!O99*$B$13+calculations!O100*$B$14+calculations!O101*$B$15)*F29,0)+IFERROR((1-$B$22)*(calculations!O107/calculations!O104)*((calculations!O125+calculations!O259)*$B$11+calculations!O126*$B$12+calculations!O127*$B$13+calculations!O128*$B$14+calculations!O129*$B$15)*F29,0)+IFERROR((1-$B$22)*(calculations!O135/calculations!O132)*((calculations!O153+calculations!O264)*$B$11+calculations!O154*$B$12+calculations!O155*$B$13+calculations!O156*$B$14+calculations!O157*$B$15)*F29,0)+IFERROR((1-$B$22)*(calculations!O163/calculations!O160)*((calculations!O181+calculations!O269)*$B$11+calculations!O182*$B$12+calculations!O183*$B$13+calculations!O184*$B$14+calculations!O185*$B$15)*F29,0)+IFERROR((1-$B$22)*(calculations!O191/calculations!O188)*((calculations!O209+calculations!O274)*$B$11+calculations!O210*$B$12+calculations!O211*$B$13+calculations!O212*$B$14+calculations!O213*$B$15)*F29,0)+IFERROR((1-$B$22)*(calculations!O219/calculations!O216)*((calculations!O237+calculations!O279)*$B$11+calculations!O238*$B$12+calculations!O239*$B$13+calculations!O240*$B$14+calculations!O241*$B$15)*F29,0) -> 3612.3851 | G38: =IFERROR((1-$B$22)*(calculations!P23/calculations!P20)*((calculations!P41+calculations!P244)*$B$11+calculations!P42*$B$12+calculations!P43*$B$13+calculations!P44*$B$14+calculations!P45*$B$15)*G29,0)+IFERROR((1-$B$22)*(calculations!P51/calculations!P48)*((calculations!P69+calculations!P249)*$B$11+calculations!P70*$B$12+calculations!P71*$B$13+calculations!P72*$B$14+calculations!P73*$B$15)*G29,0)+IFERROR((1-$B$22)*(calculations!P79/calculations!P76)*((calculations!P97+calculations!P254)*$B$11+calculations!P98*$B$12+calculations!P99*$B$13+calculations!P100*$B$14+calculations!P101*$B$15)*G29,0)+IFERROR((1-$B$22)*(calculations!P107/calculations!P104)*((calculations!P125+calculations!P259)*$B$11+calculations!P126*$B$12+calculations!P127*$B$13+calculations!P128*$B$14+calculations!P129*$B$15)*G29,0)+IFERROR((1-$B$22)*(calculations!P135/calculations!P132)*((calculations!P153+calculations!P264)*$B$11+calculations!P154*$B$12+calculations!P155*$B$13+calculations!P156*$B$14+calculations!P157*$B$15)*G29,0)+IFERROR((1-$B$22)*(calculations!P163/calculations!P160)*((calculations!P181+calculations!P269)*$B$11+calculations!P182*$B$12+calculations!P183*$B$13+calculations!P184*$B$14+calculations!P185*$B$15)*G29,0)+IFERROR((1-$B$22)*(calculations!P191/calculations!P188)*((calculations!P209+calculations!P274)*$B$11+calculations!P210*$B$12+calculations!P211*$B$13+calculations!P212*$B$14+calculations!P213*$B$15)*G29,0)+IFERROR((1-$B$22)*(calculations!P219/calculations!P216)*((calculations!P237+calculations!P279)*$B$11+calculations!P238*$B$12+calculations!P239*$B$13+calculations!P240*$B$14+calculations!P241*$B$15)*G29,0) -> 4050.6364 | H38: =IFERROR((1-$B$22)*(calculations!Q23/calculations!Q20)*((calculations!Q41+calculations!Q244)*$B$11+calculations!Q42*$B$12+calculations!Q43*$B$13+calculations!Q44*$B$14+calculations!Q45*$B$15)*H29,0)+IFERROR((1-$B$22)*(calculations!Q51/calculations!Q48)*((calculations!Q69+calculations!Q249)*$B$11+calculations!Q70*$B$12+calculations!Q71*$B$13+calculations!Q72*$B$14+calculations!Q73*$B$15)*H29,0)+IFERROR((1-$B$22)*(calculations!Q79/calculations!Q76)*((calculations!Q97+calculations!Q254)*$B$11+calculations!Q98*$B$12+calculations!Q99*$B$13+calculations!Q100*$B$14+calculations!Q101*$B$15)*H29,0)+IFERROR((1-$B$22)*(calculations!Q107/calculations!Q104)*((calculations!Q125+calculations!Q259)*$B$11+calculations!Q126*$B$12+calculations!Q127*$B$13+calculations!Q128*$B$14+calculations!Q129*$B$15)*H29,0)+IFERROR((1-$B$22)*(calculations!Q135/calculations!Q132)*((calculations!Q153+calculations!Q264)*$B$11+calculations!Q154*$B$12+calculations!Q155*$B$13+calculations!Q156*$B$14+calculations!Q157*$B$15)*H29,0)+IFERROR((1-$B$22)*(calculations!Q163/calculations!Q160)*((calculations!Q181+calculations!Q269)*$B$11+calculations!Q182*$B$12+calculations!Q183*$B$13+calculations!Q184*$B$14+calculations!Q185*$B$15)*H29,0)+IFERROR((1-$B$22)*(calculations!Q191/calculations!Q188)*((calculations!Q209+calculations!Q274)*$B$11+calculations!Q210*$B$12+calculations!Q211*$B$13+calculations!Q212*$B$14+calculations!Q213*$B$15)*H29,0)+IFERROR((1-$B$22)*(calculations!Q219/calculations!Q216)*((calculations!Q237+calculations!Q279)*$B$11+calculations!Q238*$B$12+calculations!Q239*$B$13+calculations!Q240*$B$14+calculations!Q241*$B$15)*H29,0) -> 4613.5403 | I38: =IFERROR((1-$B$22)*(calculations!R23/calculations!R20)*((calculations!R41+calculations!R244)*$B$11+calculations!R42*$B$12+calculations!R43*$B$13+calculations!R44*$B$14+calculations!R45*$B$15)*I29,0)+IFERROR((1-$B$22)*(calculations!R51/calculations!R48)*((calculations!R69+calculations!R249)*$B$11+calculations!R70*$B$12+calculations!R71*$B$13+calculations!R72*$B$14+calculations!R73*$B$15)*I29,0)+IFERROR((1-$B$22)*(calculations!R79/calculations!R76)*((calculations!R97+calculations!R254)*$B$11+calculations!R98*$B$12+calculations!R99*$B$13+calculations!R100*$B$14+calculations!R101*$B$15)*I29,0)+IFERROR((1-$B$22)*(calculations!R107/calculations!R104)*((calculations!R125+calculations!R259)*$B$11+calculations!R126*$B$12+calculations!R127*$B$13+calculations!R128*$B$14+calculations!R129*$B$15)*I29,0)+IFERROR((1-$B$22)*(calculations!R135/calculations!R132)*((calculations!R153+calculations!R264)*$B$11+calculations!R154*$B$12+calculations!R155*$B$13+calculations!R156*$B$14+calculations!R157*$B$15)*I29,0)+IFERROR((1-$B$22)*(calculations!R163/calculations!R160)*((calculations!R181+calculations!R269)*$B$11+calculations!R182*$B$12+calculations!R183*$B$13+calculations!R184*$B$14+calculations!R185*$B$15)*I29,0)+IFERROR((1-$B$22)*(calculations!R191/calculations!R188)*((calculations!R209+calculations!R274)*$B$11+calculations!R210*$B$12+calculations!R211*$B$13+calculations!R212*$B$14+calculations!R213*$B$15)*I29,0)+IFERROR((1-$B$22)*(calculations!R219/calculations!R216)*((calculations!R237+calculations!R279)*$B$11+calculations!R238*$B$12+calculations!R239*$B$13+calculations!R240*$B$14+calculations!R241*$B$15)*I29,0) -> 5270.9042 | J38: =IFERROR((1-$B$22)*(calculations!S23/calculations!S20)*((calculations!S41+calculations!S244)*$B$11+calculations!S42*$B$12+calculations!S43*$B$13+calculations!S44*$B$14+calculations!S45*$B$15)*J29,0)+IFERROR((1-$B$22)*(calculations!S51/calculations!S48)*((calculations!S69+calculations!S249)*$B$11+calculations!S70*$B$12+calculations!S71*$B$13+calculations!S72*$B$14+calculations!S73*$B$15)*J29,0)+IFERROR((1-$B$22)*(calculations!S79/calculations!S76)*((calculations!S97+calculations!S254)*$B$11+calculations!S98*$B$12+calculations!S99*$B$13+calculations!S100*$B$14+calculations!S101*$B$15)*J29,0)+IFERROR((1-$B$22)*(calculations!S107/calculations!S104)*((calculations!S125+calculations!S259)*$B$11+calculations!S126*$B$12+calculations!S127*$B$13+calculations!S128*$B$14+calculations!S129*$B$15)*J29,0)+IFERROR((1-$B$22)*(calculations!S135/calculations!S132)*((calculations!S153+calculations!S264)*$B$11+calculations!S154*$B$12+calculations!S155*$B$13+calculations!S156*$B$14+calculations!S157*$B$15)*J29,0)+IFERROR((1-$B$22)*(calculations!S163/calculations!S160)*((calculations!S181+calculations!S269)*$B$11+calculations!S182*$B$12+calculations!S183*$B$13+calculations!S184*$B$14+calculations!S185*$B$15)*J29,0)+IFERROR((1-$B$22)*(calculations!S191/calculations!S188)*((calculations!S209+calculations!S274)*$B$11+calculations!S210*$B$12+calculations!S211*$B$13+calculations!S212*$B$14+calculations!S213*$B$15)*J29,0)+IFERROR((1-$B$22)*(calculations!S219/calculations!S216)*((calculations!S237+calculations!S279)*$B$11+calculations!S238*$B$12+calculations!S239*$B$13+calculations!S240*$B$14+calculations!S241*$B$15)*J29,0) -> 6894.8421 | K38: =IFERROR((1-$B$22)*(calculations!T23/calculations!T20)*((calculations!T41+calculations!T244)*$B$11+calculations!T42*$B$12+calculations!T43*$B$13+calculations!T44*$B$14+calculations!T45*$B$15)*K29,0)+IFERROR((1-$B$22)*(calculations!T51/calculations!T48)*((calculations!T69+calculations!T249)*$B$11+calculations!T70*$B$12+calculations!T71*$B$13+calculations!T72*$B$14+calculations!T73*$B$15)*K29,0)+IFERROR((1-$B$22)*(calculations!T79/calculations!T76)*((calculations!T97+calculations!T254)*$B$11+calculations!T98*$B$12+calculations!T99*$B$13+calculations!T100*$B$14+calculations!T101*$B$15)*K29,0)+IFERROR((1-$B$22)*(calculations!T107/calculations!T104)*((calculations!T125+calculations!T259)*$B$11+calculations!T126*$B$12+calculations!T127*$B$13+calculations!T128*$B$14+calculations!T129*$B$15)*K29,0)+IFERROR((1-$B$22)*(calculations!T135/calculations!T132)*((calculations!T153+calculations!T264)*$B$11+calculations!T154*$B$12+calculations!T155*$B$13+calculations!T156*$B$14+calculations!T157*$B$15)*K29,0)+IFERROR((1-$B$22)*(calculations!T163/calculations!T160)*((calculations!T181+calculations!T269)*$B$11+calculations!T182*$B$12+calculations!T183*$B$13+calculations!T184*$B$14+calculations!T185*$B$15)*K29,0)+IFERROR((1-$B$22)*(calculations!T191/calculations!T188)*((calculations!T209+calculations!T274)*$B$11+calculations!T210*$B$12+calculations!T211*$B$13+calculations!T212*$B$14+calculations!T213*$B$15)*K29,0)+IFERROR((1-$B$22)*(calculations!T219/calculations!T216)*((calculations!T237+calculations!T279)*$B$11+calculations!T238*$B$12+calculations!T239*$B$13+calculations!T240*$B$14+calculations!T241*$B$15)*K29,0) -> 8152.3273 | ... O38: =IFERROR((1-$B$22)*(calculations!X23/calculations!X20)*((calculations!X41+calculations!X244)*$B$11+calculations!X42*$B$12+calculations!X43*$B$13+calculations!X44*$B$14+calculations!X45*$B$15)*O29,0)+IFERROR((1-$B$22)*(calculations!X51/calculations!X48)*((calculations!X69+calculations!X249)*$B$11+calculations!X70*$B$12+calculations!X71*$B$13+calculations!X72*$B$14+calculations!X73*$B$15)*O29,0)+IFERROR((1-$B$22)*(calculations!X79/calculations!X76)*((calculations!X97+calculations!X254)*$B$11+calculations!X98*$B$12+calculations!X99*$B$13+calculations!X100*$B$14+calculations!X101*$B$15)*O29,0)+IFERROR((1-$B$22)*(calculations!X107/calculations!X104)*((calculations!X125+calculations!X259)*$B$11+calculations!X126*$B$12+calculations!X127*$B$13+calculations!X128*$B$14+calculations!X129*$B$15)*O29,0)+IFERROR((1-$B$22)*(calculations!X135/calculations!X132)*((calculations!X153+calculations!X264)*$B$11+calculations!X154*$B$12+calculations!X155*$B$13+calculations!X156*$B$14+calculations!X157*$B$15)*O29,0)+IFERROR((1-$B$22)*(calculations!X163/calculations!X160)*((calculations!X181+calculations!X269)*$B$11+calculations!X182*$B$12+calculations!X183*$B$13+calculations!X184*$B$14+calculations!X185*$B$15)*O29,0)+IFERROR((1-$B$22)*(calculations!X191/calculations!X188)*((calculations!X209+calculations!X274)*$B$11+calculations!X210*$B$12+calculations!X211*$B$13+calculations!X212*$B$14+calculations!X213*$B$15)*O29,0)+IFERROR((1-$B$22)*(calculations!X219/calculations!X216)*((calculations!X237+calculations!X279)*$B$11+calculations!X238*$B$12+calculations!X239*$B$13+calculations!X240*$B$14+calculations!X241*$B$15)*O29,0) -> 14069.274
A39: TOTAL COUNTRY REVENUE | B39: USD m | D39: =D34+D37+D38 -> 0 | E39: =E34+E37+E38 -> 0 | F39: =F34+F37+F38 -> 4259.8079 | G39: =G34+G37+G38 -> 4773.8477 | H39: =H34+H37+H38 -> 5434.1583 | I39: =I34+I37+I38 -> 6204.9611 | J39: =J34+J37+J38 -> 8112.1785 | K39: =K34+K37+K38 -> 9586.4379 | ... O39: =O34+O37+O38 -> 16509.316
A40: TOTAL POOL (country + EU) | B40: USD m | D40: =D39+D36 -> 0 | E40: =E39+E36 -> 0 | F40: =F39+F36 -> 4259.8079 | G40: =G39+G36 -> 4773.8477 | H40: =H39+H36 -> 5434.1583 | I40: =I39+I36 -> 6204.9611 | J40: =J39+J36 -> 8112.1785 | K40: =K39+K36 -> 9586.4379 | ... O40: =O39+O36 -> 16509.316
A42: 5. PRICE IMPACT BY PRODUCT (detail year set by B6)
A43: Product | B43: Pre-policy price (USD/t) | C43: EU wedge — CBAM/t | D43: Domestic wedge — CP × covered int | E43: Stack on EU exports | F43: Stack on non-EU exports | G43: Stack on domestic | H43: Buyer price ↑ EU | I43: Buyer price ↑ non-EU | J43: Producer margin hit EU | K43: Producer margin hit non-EU
A44: DRI-EAF steel (CN 7206 (D)) | B44: =INDEX(input_data!$L:$L,MATCH("all.in.ppx.stl.drg.---",input_data!$A:$A,0)) -> 750 | C44: =INDEX(calculations!$M:$X,248,$P$6) -> 179.15373 | D44: =IFERROR(((INDEX(calculations!$M:$X,41,$P$6)+INDEX(calculations!$M:$X,244,$P$6))*$B$11+INDEX(calculations!$M:$X,42,$P$6)*$B$12+INDEX(calculations!$M:$X,43,$P$6)*$B$13+INDEX(calculations!$M:$X,44,$P$6)*$B$14+INDEX(calculations!$M:$X,45,$P$6)*$B$15)/INDEX(calculations!$M:$X,20,$P$6),0)*INDEX($D$29:$O$29,$P$6) -> 186.27501 | E44: =MAX(C44,D44) -> 186.27501 | F44: =D44 -> 186.27501 | G44: =(1-$B$22)*D44 -> 186.27501 | H44: =$B$7*E44 -> 130.39251 | I44: =$B$7*F44 -> 130.39251 | J44: =(1-$B$7)*E44 -> 55.882502 | K44: =(1-$B$7)*F44 -> 55.882502
A45: Scrap-EAF steel (CN 7206 (E)) | B45: =INDEX(input_data!$L:$L,MATCH("all.in.ppx.stl.scr.---",input_data!$A:$A,0)) -> 680 | C45: =INDEX(calculations!$M:$X,253,$P$6) -> 14.925735 | D45: =IFERROR(((INDEX(calculations!$M:$X,69,$P$6)+INDEX(calculations!$M:$X,249,$P$6))*$B$11+INDEX(calculations!$M:$X,70,$P$6)*$B$12+INDEX(calculations!$M:$X,71,$P$6)*$B$13+INDEX(calculations!$M:$X,72,$P$6)*$B$14+INDEX(calculations!$M:$X,73,$P$6)*$B$15)/INDEX(calculations!$M:$X,48,$P$6),0)*INDEX($D$29:$O$29,$P$6) -> 67.62901 | E45: =MAX(C45,D45) -> 67.62901 | F45: =D45 -> 67.62901 | G45: =(1-$B$22)*D45 -> 67.62901 | H45: =$B$7*E45 -> 47.340307 | I45: =$B$7*F45 -> 47.340307 | J45: =(1-$B$7)*E45 -> 20.288703 | K45: =(1-$B$7)*F45 -> 20.288703
A46: BF-BOF steel (CN 7206 (C)) | B46: =INDEX(input_data!$L:$L,MATCH("all.in.ppx.stl.bof.---",input_data!$A:$A,0)) -> 620 | C46: =INDEX(calculations!$M:$X,258,$P$6) -> 0 | D46: =IFERROR(((INDEX(calculations!$M:$X,97,$P$6)+INDEX(calculations!$M:$X,254,$P$6))*$B$11+INDEX(calculations!$M:$X,98,$P$6)*$B$12+INDEX(calculations!$M:$X,99,$P$6)*$B$13+INDEX(calculations!$M:$X,100,$P$6)*$B$14+INDEX(calculations!$M:$X,101,$P$6)*$B$15)/INDEX(calculations!$M:$X,76,$P$6),0)*INDEX($D$29:$O$29,$P$6) -> 0 | E46: =MAX(C46,D46) -> 0 | F46: =D46 -> 0 | G46: =(1-$B$22)*D46 -> 0 | H46: =$B$7*E46 -> 0 | I46: =$B$7*F46 -> 0 | J46: =(1-$B$7)*E46 -> 0 | K46: =(1-$B$7)*F46 -> 0
A47: Cement (CN 25231000 (A)) | B47: =INDEX(input_data!$L:$L,MATCH("all.in.ppx.cmt.dry.---",input_data!$A:$A,0)) -> 110 | C47: =INDEX(calculations!$M:$X,263,$P$6) -> 64.20634 | D47: =IFERROR(((INDEX(calculations!$M:$X,125,$P$6)+INDEX(calculations!$M:$X,259,$P$6))*$B$11+INDEX(calculations!$M:$X,126,$P$6)*$B$12+INDEX(calculations!$M:$X,127,$P$6)*$B$13+INDEX(calculations!$M:$X,128,$P$6)*$B$14+INDEX(calculations!$M:$X,129,$P$6)*$B$15)/INDEX(calculations!$M:$X,104,$P$6),0)*INDEX($D$29:$O$29,$P$6) -> 80.162012 | E47: =MAX(C47,D47) -> 80.162012 | F47: =D47 -> 80.162012 | G47: =(1-$B$22)*D47 -> 80.162012 | H47: =$B$7*E47 -> 56.113408 | I47: =$B$7*F47 -> 56.113408 | J47: =(1-$B$7)*E47 -> 24.048604 | K47: =(1-$B$7)*F47 -> 24.048604
A48: Ammonia (CN 28141000) | B48: =INDEX(input_data!$L:$L,MATCH("all.in.ppx.frt.amc.---",input_data!$A:$A,0)) -> 450 | C48: =INDEX(calculations!$M:$X,268,$P$6) -> 161.06866 | D48: =IFERROR(((INDEX(calculations!$M:$X,153,$P$6)+INDEX(calculations!$M:$X,264,$P$6))*$B$11+INDEX(calculations!$M:$X,154,$P$6)*$B$12+INDEX(calculations!$M:$X,155,$P$6)*$B$13+INDEX(calculations!$M:$X,156,$P$6)*$B$14+INDEX(calculations!$M:$X,157,$P$6)*$B$15)/INDEX(calculations!$M:$X,132,$P$6),0)*INDEX($D$29:$O$29,$P$6) -> 193.87605 | E48: =MAX(C48,D48) -> 193.87605 | F48: =D48 -> 193.87605 | G48: =(1-$B$22)*D48 -> 193.87605 | H48: =$B$7*E48 -> 135.71324 | I48: =$B$7*F48 -> 135.71324 | J48: =(1-$B$7)*E48 -> 58.162815 | K48: =(1-$B$7)*F48 -> 58.162815
A49: Urea (CN 31021010) | B49: =INDEX(input_data!$L:$L,MATCH("all.in.ppx.frt.ure.---",input_data!$A:$A,0)) -> 380 | C49: =INDEX(calculations!$M:$X,273,$P$6) -> 19.402975 | D49: =IFERROR(((INDEX(calculations!$M:$X,181,$P$6)+INDEX(calculations!$M:$X,269,$P$6))*$B$11+INDEX(calculations!$M:$X,182,$P$6)*$B$12+INDEX(calculations!$M:$X,183,$P$6)*$B$13+INDEX(calculations!$M:$X,184,$P$6)*$B$14+INDEX(calculations!$M:$X,185,$P$6)*$B$15)/INDEX(calculations!$M:$X,160,$P$6),0)*INDEX($D$29:$O$29,$P$6) -> 58.23663 | E49: =MAX(C49,D49) -> 58.23663 | F49: =D49 -> 58.23663 | G49: =(1-$B$22)*D49 -> 58.23663 | H49: =$B$7*E49 -> 40.765641 | I49: =$B$7*F49 -> 40.765641 | J49: =(1-$B$7)*E49 -> 17.470989 | K49: =(1-$B$7)*F49 -> 17.470989
A50: Ammonium nitrate (CN 31023090) | B50: =INDEX(input_data!$L:$L,MATCH("all.in.ppx.frt.nit.---",input_data!$A:$A,0)) -> 320 | C50: =INDEX(calculations!$M:$X,278,$P$6) -> 366.38129 | D50: =IFERROR(((INDEX(calculations!$M:$X,209,$P$6)+INDEX(calculations!$M:$X,274,$P$6))*$B$11+INDEX(calculations!$M:$X,210,$P$6)*$B$12+INDEX(calculations!$M:$X,211,$P$6)*$B$13+INDEX(calculations!$M:$X,212,$P$6)*$B$14+INDEX(calculations!$M:$X,213,$P$6)*$B$15)/INDEX(calculations!$M:$X,188,$P$6),0)*INDEX($D$29:$O$29,$P$6) -> 287.62614 | E50: =MAX(C50,D50) -> 366.38129 | F50: =D50 -> 287.62614 | G50: =(1-$B$22)*D50 -> 287.62614 | H50: =$B$7*E50 -> 256.4669 | I50: =$B$7*F50 -> 201.3383 | J50: =(1-$B$7)*E50 -> 109.91439 | K50: =(1-$B$7)*F50 -> 86.287843
A51: Primary aluminium (CN 76011000 (K)) | B51: =INDEX(input_data!$L:$L,MATCH("all.in.ppx.alu.prp.---",input_data!$A:$A,0)) -> 2400 | C51: =INDEX(calculations!$M:$X,283,$P$6) -> 199.78841 | D51: =IFERROR(((INDEX(calculations!$M:$X,237,$P$6)+INDEX(calculations!$M:$X,279,$P$6))*$B$11+INDEX(calculations!$M:$X,238,$P$6)*$B$12+INDEX(calculations!$M:$X,239,$P$6)*$B$13+INDEX(calculations!$M:$X,240,$P$6)*$B$14+INDEX(calculations!$M:$X,241,$P$6)*$B$15)/INDEX(calculations!$M:$X,216,$P$6),0)*INDEX($D$29:$O$29,$P$6) -> 830.52575 | E51: =MAX(C51,D51) -> 830.52575 | F51: =D51 -> 830.52575 | G51: =(1-$B$22)*D51 -> 830.52575 | H51: =$B$7*E51 -> 581.36803 | I51: =$B$7*F51 -> 581.36803 | J51: =(1-$B$7)*E51 -> 249.15773 | K51: =(1-$B$7)*F51 -> 249.15773
A53: EU wedge = CBAM/t (uses CBAM-eligible intensity, Annex II respected). Domestic wedge = CP × covered_intensity (covers whatever scopes 2a flags say). Stack on EU = max(EU wedge, dom wedge) — producer pays whichever is higher. Stack on domestic = 0 when exports-only toggle (2c) is on. θ (B7) splits each wedge between buyer prices and producer margins.
A55: 6. EMISSIONS FACTOR MATRIX — all products, detail year (B6)
A56: 6a. Fuel emission factors (kgCO₂/GJ) — IPCC 2006 stationary combustion
A57: Code | B57: Fuel | C57: EF (kgCO₂/GJ) | D57: Source
A58: coa | B58: Coal | C58: =INDEX(input_data!$L:$L,MATCH("all.in.eff.---.---.coa",input_data!$A:$A,0)) -> 96.1 | D58: IPCC 2006 Vol.2 Ch.2 — stationary combustion defaults
A59: nga | B59: Natural gas | C59: =INDEX(input_data!$L:$L,MATCH("all.in.eff.---.---.nga",input_data!$A:$A,0)) -> 56.1 | D59: IPCC 2006 Vol.2 Ch.2 — stationary combustion defaults
A60: gso | B60: Gasoline | C60: =INDEX(input_data!$L:$L,MATCH("all.in.eff.---.---.gso",input_data!$A:$A,0)) -> 69.3 | D60: IPCC 2006 Vol.2 Ch.2 — stationary combustion defaults
A61: die | B61: Diesel | C61: =INDEX(input_data!$L:$L,MATCH("all.in.eff.---.---.die",input_data!$A:$A,0)) -> 74.1 | D61: IPCC 2006 Vol.2 Ch.2 — stationary combustion defaults
A62: ker | B62: Kerosene | C62: =INDEX(input_data!$L:$L,MATCH("all.in.eff.---.---.ker",input_data!$A:$A,0)) -> 71.9 | D62: IPCC 2006 Vol.2 Ch.2 — stationary combustion defaults
A63: lpg | B63: LPG | C63: =INDEX(input_data!$L:$L,MATCH("all.in.eff.---.---.lpg",input_data!$A:$A,0)) -> 63.1 | D63: IPCC 2006 Vol.2 Ch.2 — stationary combustion defaults
A64: bio | B64: Biomass | C64: =INDEX(input_data!$L:$L,MATCH("all.in.eff.---.---.bio",input_data!$A:$A,0)) -> 0 | D64: IPCC 2006 Vol.2 Ch.2 — stationary combustion defaults
A65: ren | B65: Self-gen renewables | C65: =INDEX(input_data!$L:$L,MATCH("all.in.eff.---.---.ren",input_data!$A:$A,0)) -> 0 | D65: IPCC 2006 Vol.2 Ch.2 — stationary combustion defaults
A67: 6b. Emission intensity matrix — all products, at detail year (B6). Scope-2 included in CBAM: green = YES (Annex II); orange = NO (direct only).
A68: Product | B68: Unit | C68: S1.fc combustion (tCO₂/t) | D68: S1.fp process fuel (tCO₂/t) | E68: S1.np non-fuel process(tCO₂/t) | F68: S1.no non-CO₂ (tCO₂e/t) | G68: S2 electricity (tCO₂/t) | H68: NH₃ chain (tCO₂/t) | I68: S2 in CBAM scope? | J68: Holistic intensity (tCO₂e/t) | K68: CBAM-eligible (MRV=1) (tCO₂e/t) | L68: EU benchmark (tCO₂/t) | M68: EU default value (tCO₂/t) | N68: Excess over benchmark (tCO₂/t) | O68: CN codes
A69: DRI-EAF steel (stl.drg) | B69: t | C69: =IFERROR(INDEX(calculations!$M:$X,41,$P$6)/INDEX(calculations!$M:$X,20,$P$6),0) -> 0.31755 | D69: =IFERROR(INDEX(calculations!$M:$X,42,$P$6)/INDEX(calculations!$M:$X,20,$P$6),0) -> 1.3464 | E69: =IFERROR(INDEX(calculations!$M:$X,43,$P$6)/INDEX(calculations!$M:$X,20,$P$6),0) -> 0 | F69: =IFERROR(INDEX(calculations!$M:$X,44,$P$6)/INDEX(calculations!$M:$X,20,$P$6),0) -> 0 | G69: =IFERROR(INDEX(calculations!$M:$X,45,$P$6)/INDEX(calculations!$M:$X,20,$P$6),0) -> 0.3125 | H69: =IFERROR(INDEX(calculations!$M:$X,244,$P$6)/INDEX(calculations!$M:$X,20,$P$6),0) -> 0 | I69: NO | J69: =IFERROR(INDEX(calculations!$M:$X,246,$P$6),0) -> 1.97645 | K69: =IFERROR(INDEX(calculations!$M:$X,247,$P$6),0) -> 1.66395 | L69: =INDEX(input_data!$L:$L,MATCH("all.in.bnk.stl.drg.---",input_data!$A:$A,0)) -> 0.481 | M69: =INDEX(input_data!$L:$L,MATCH("all.in.dfv.stl.drg.---",input_data!$A:$A,0)) -> 0.5772 | N69: =MAX(K69-L69,0) -> 1.18295 | O69: 7206(D), 7207(D)
A70: Scrap-EAF steel (stl.scr) | B70: t | C70: =IFERROR(INDEX(calculations!$M:$X,69,$P$6)/INDEX(calculations!$M:$X,48,$P$6),0) -> 0.15507 | D70: =IFERROR(INDEX(calculations!$M:$X,70,$P$6)/INDEX(calculations!$M:$X,48,$P$6),0) -> 0 | E70: =IFERROR(INDEX(calculations!$M:$X,71,$P$6)/INDEX(calculations!$M:$X,48,$P$6),0) -> 0 | F70: =IFERROR(INDEX(calculations!$M:$X,72,$P$6)/INDEX(calculations!$M:$X,48,$P$6),0) -> 0 | G70: =IFERROR(INDEX(calculations!$M:$X,73,$P$6)/INDEX(calculations!$M:$X,48,$P$6),0) -> 0.5625 | H70: =IFERROR(INDEX(calculations!$M:$X,249,$P$6)/INDEX(calculations!$M:$X,48,$P$6),0) -> 0 | I70: NO | J70: =IFERROR(INDEX(calculations!$M:$X,251,$P$6),0) -> 0.71757 | K70: =IFERROR(INDEX(calculations!$M:$X,252,$P$6),0) -> 0.15507 | L70: =INDEX(input_data!$L:$L,MATCH("all.in.bnk.stl.scr.---",input_data!$A:$A,0)) -> 0.072 | M70: =INDEX(input_data!$L:$L,MATCH("all.in.dfv.stl.scr.---",input_data!$A:$A,0)) -> 0.0864 | N70: =MAX(K70-L70,0) -> 0.08307 | O70: 7206(E), 7207(E)
A71: BF-BOF steel (stl.bof) | B71: t | C71: =IFERROR(INDEX(calculations!$M:$X,97,$P$6)/INDEX(calculations!$M:$X,76,$P$6),0) -> 0 | D71: =IFERROR(INDEX(calculations!$M:$X,98,$P$6)/INDEX(calculations!$M:$X,76,$P$6),0) -> 0 | E71: =IFERROR(INDEX(calculations!$M:$X,99,$P$6)/INDEX(calculations!$M:$X,76,$P$6),0) -> 0 | F71: =IFERROR(INDEX(calculations!$M:$X,100,$P$6)/INDEX(calculations!$M:$X,76,$P$6),0) -> 0 | G71: =IFERROR(INDEX(calculations!$M:$X,101,$P$6)/INDEX(calculations!$M:$X,76,$P$6),0) -> 0 | H71: =IFERROR(INDEX(calculations!$M:$X,254,$P$6)/INDEX(calculations!$M:$X,76,$P$6),0) -> 0 | I71: NO | J71: =IFERROR(INDEX(calculations!$M:$X,256,$P$6),0) -> 0 | K71: =IFERROR(INDEX(calculations!$M:$X,257,$P$6),0) -> 0 | L71: =INDEX(input_data!$L:$L,MATCH("all.in.bnk.stl.bof.---",input_data!$A:$A,0)) -> 1.37 | M71: =INDEX(input_data!$L:$L,MATCH("all.in.dfv.stl.bof.---",input_data!$A:$A,0)) -> 1.644 | N71: =MAX(K71-L71,0) -> 0 | O71: 7206(C), 7207(C)
A72: Cement (cmt.dry) | B72: t | C72: =IFERROR(INDEX(calculations!$M:$X,125,$P$6)/INDEX(calculations!$M:$X,104,$P$6),0) -> 0.2683 | D72: =IFERROR(INDEX(calculations!$M:$X,126,$P$6)/INDEX(calculations!$M:$X,104,$P$6),0) -> 0 | E72: =IFERROR(INDEX(calculations!$M:$X,127,$P$6)/INDEX(calculations!$M:$X,104,$P$6),0) -> 0.526 | F72: =IFERROR(INDEX(calculations!$M:$X,128,$P$6)/INDEX(calculations!$M:$X,104,$P$6),0) -> 0 | G72: =IFERROR(INDEX(calculations!$M:$X,129,$P$6)/INDEX(calculations!$M:$X,104,$P$6),0) -> 0.05625 | H72: =IFERROR(INDEX(calculations!$M:$X,259,$P$6)/INDEX(calculations!$M:$X,104,$P$6),0) -> 0 | I72: YES | J72: =IFERROR(INDEX(calculations!$M:$X,261,$P$6),0) -> 0.85055 | K72: =IFERROR(INDEX(calculations!$M:$X,262,$P$6),0) -> 0.85055 | L72: =INDEX(input_data!$L:$L,MATCH("all.in.bnk.cmt.dry.---",input_data!$A:$A,0)) -> 0.666 | M72: =INDEX(input_data!$L:$L,MATCH("all.in.dfv.cmt.dry.---",input_data!$A:$A,0)) -> 0.7992 | N72: =MAX(K72-L72,0) -> 0.18455 | O72: 25231000 (A)
A73: Ammonia (frt.amc) | B73: t | C73: =IFERROR(INDEX(calculations!$M:$X,153,$P$6)/INDEX(calculations!$M:$X,132,$P$6),0) -> 0.6732 | D73: =IFERROR(INDEX(calculations!$M:$X,154,$P$6)/INDEX(calculations!$M:$X,132,$P$6),0) -> 1.3464 | E73: =IFERROR(INDEX(calculations!$M:$X,155,$P$6)/INDEX(calculations!$M:$X,132,$P$6),0) -> 0 | F73: =IFERROR(INDEX(calculations!$M:$X,156,$P$6)/INDEX(calculations!$M:$X,132,$P$6),0) -> 0 | G73: =IFERROR(INDEX(calculations!$M:$X,157,$P$6)/INDEX(calculations!$M:$X,132,$P$6),0) -> 0.0375 | H73: =IFERROR(INDEX(calculations!$M:$X,264,$P$6)/INDEX(calculations!$M:$X,132,$P$6),0) -> 0 | I73: YES | J73: =IFERROR(INDEX(calculations!$M:$X,266,$P$6),0) -> 2.0571 | K73: =IFERROR(INDEX(calculations!$M:$X,267,$P$6),0) -> 2.0571 | L73: =INDEX(input_data!$L:$L,MATCH("all.in.bnk.frt.amc.---",input_data!$A:$A,0)) -> 1.522 | M73: =INDEX(input_data!$L:$L,MATCH("all.in.dfv.frt.amc.---",input_data!$A:$A,0)) -> 1.8264 | N73: =MAX(K73-L73,0) -> 0.5351 | O73: 28141000
A74: Urea (frt.ure) | B74: t | C74: =IFERROR(INDEX(calculations!$M:$X,181,$P$6)/INDEX(calculations!$M:$X,160,$P$6),0) -> 0.1683 | D74: =IFERROR(INDEX(calculations!$M:$X,182,$P$6)/INDEX(calculations!$M:$X,160,$P$6),0) -> 0 | E74: =IFERROR(INDEX(calculations!$M:$X,183,$P$6)/INDEX(calculations!$M:$X,160,$P$6),0) -> -0.733 | F74: =IFERROR(INDEX(calculations!$M:$X,184,$P$6)/INDEX(calculations!$M:$X,160,$P$6),0) -> 0 | G74: =IFERROR(INDEX(calculations!$M:$X,185,$P$6)/INDEX(calculations!$M:$X,160,$P$6),0) -> 0.0375 | H74: =IFERROR(INDEX(calculations!$M:$X,269,$P$6)/INDEX(calculations!$M:$X,160,$P$6),0) -> 1.1451132 | I74: YES | J74: =IFERROR(INDEX(calculations!$M:$X,271,$P$6),0) -> 0.6179132 | K74: =IFERROR(INDEX(calculations!$M:$X,272,$P$6),0) -> 0.6179132 | L74: =INDEX(input_data!$L:$L,MATCH("all.in.bnk.frt.ure.---",input_data!$A:$A,0)) -> 0.902 | M74: =INDEX(input_data!$L:$L,MATCH("all.in.dfv.frt.ure.---",input_data!$A:$A,0)) -> 1.0824 | N74: =MAX(K74-L74,0) -> 0 | O74: 31021010
A75: Ammonium nitrate (frt.nit) | B75: t | C75: =IFERROR(INDEX(calculations!$M:$X,209,$P$6)/INDEX(calculations!$M:$X,188,$P$6),0) -> 0.08415 | D75: =IFERROR(INDEX(calculations!$M:$X,210,$P$6)/INDEX(calculations!$M:$X,188,$P$6),0) -> 0 | E75: =IFERROR(INDEX(calculations!$M:$X,211,$P$6)/INDEX(calculations!$M:$X,188,$P$6),0) -> 0 | F75: =IFERROR(INDEX(calculations!$M:$X,212,$P$6)/INDEX(calculations!$M:$X,188,$P$6),0) -> 2.5 | G75: =IFERROR(INDEX(calculations!$M:$X,213,$P$6)/INDEX(calculations!$M:$X,188,$P$6),0) -> 0.0375 | H75: =IFERROR(INDEX(calculations!$M:$X,274,$P$6)/INDEX(calculations!$M:$X,188,$P$6),0) -> 0.4301748 | I75: YES | J75: =IFERROR(INDEX(calculations!$M:$X,276,$P$6),0) -> 3.0518248 | K75: =IFERROR(INDEX(calculations!$M:$X,277,$P$6),0) -> 3.0518248 | L75: =INDEX(input_data!$L:$L,MATCH("all.in.bnk.frt.nit.---",input_data!$A:$A,0)) -> 0.302 | M75: =INDEX(input_data!$L:$L,MATCH("all.in.dfv.frt.nit.---",input_data!$A:$A,0)) -> 0.3624 | N75: =MAX(K75-L75,0) -> 2.7498248 | O75: 31023090
A76: Primary aluminium (alu.prp) | B76: t | C76: =IFERROR(INDEX(calculations!$M:$X,237,$P$6)/INDEX(calculations!$M:$X,216,$P$6),0) -> 0.1122 | D76: =IFERROR(INDEX(calculations!$M:$X,238,$P$6)/INDEX(calculations!$M:$X,216,$P$6),0) -> 0 | E76: =IFERROR(INDEX(calculations!$M:$X,239,$P$6)/INDEX(calculations!$M:$X,216,$P$6),0) -> 1.5 | F76: =IFERROR(INDEX(calculations!$M:$X,240,$P$6)/INDEX(calculations!$M:$X,216,$P$6),0) -> 0.7 | G76: =IFERROR(INDEX(calculations!$M:$X,241,$P$6)/INDEX(calculations!$M:$X,216,$P$6),0) -> 6.5 | H76: =IFERROR(INDEX(calculations!$M:$X,279,$P$6)/INDEX(calculations!$M:$X,216,$P$6),0) -> 0 | I76: NO | J76: =IFERROR(INDEX(calculations!$M:$X,281,$P$6),0) -> 8.8122 | K76: =IFERROR(INDEX(calculations!$M:$X,282,$P$6),0) -> 2.3122 | L76: =INDEX(input_data!$L:$L,MATCH("all.in.bnk.alu.prp.---",input_data!$A:$A,0)) -> 1.423 | M76: =INDEX(input_data!$L:$L,MATCH("all.in.dfv.alu.prp.---",input_data!$A:$A,0)) -> 1.7076 | N76: =MAX(K76-L76,0) -> 0.8892 | O76: 76011000 (K)
A77: Other iron & steel products (stl.oth) | B77: t | C77: =IFERROR(INDEX(calculations!$M:$X,307,$P$6)/INDEX(calculations!$M:$X,286,$P$6),0) -> 0.1722 | D77: =IFERROR(INDEX(calculations!$M:$X,308,$P$6)/INDEX(calculations!$M:$X,286,$P$6),0) -> 0.6727 | E77: =IFERROR(INDEX(calculations!$M:$X,309,$P$6)/INDEX(calculations!$M:$X,286,$P$6),0) -> 0 | F77: =IFERROR(INDEX(calculations!$M:$X,310,$P$6)/INDEX(calculations!$M:$X,286,$P$6),0) -> 0 | G77: =IFERROR(INDEX(calculations!$M:$X,311,$P$6)/INDEX(calculations!$M:$X,286,$P$6),0) -> 0.4375 | H77: =IFERROR(INDEX(calculations!$M:$X,312,$P$6)/INDEX(calculations!$M:$X,286,$P$6),0) -> 0 | I77: NO | J77: =IFERROR(INDEX(calculations!$M:$X,314,$P$6),0) -> 1.2824 | K77: =IFERROR(INDEX(calculations!$M:$X,315,$P$6),0) -> 0.8449 | L77: =INDEX(input_data!$L:$L,MATCH("all.in.bnk.stl.oth.---",input_data!$A:$A,0)) -> 1.222 | M77: =INDEX(input_data!$L:$L,MATCH("all.in.dfv.stl.oth.---",input_data!$A:$A,0)) -> 1.4664 | N77: =MAX(K77-L77,0) -> 0 | O77: 7201, 7202 4/6/7, 7203, 7218
A78: Other nitrogen fertilisers (frt.otn) | B78: t N | C78: =IFERROR(INDEX(calculations!$M:$X,339,$P$6)/INDEX(calculations!$M:$X,318,$P$6),0) -> 0.2805 | D78: =IFERROR(INDEX(calculations!$M:$X,340,$P$6)/INDEX(calculations!$M:$X,318,$P$6),0) -> 0 | E78: =IFERROR(INDEX(calculations!$M:$X,341,$P$6)/INDEX(calculations!$M:$X,318,$P$6),0) -> 0 | F78: =IFERROR(INDEX(calculations!$M:$X,342,$P$6)/INDEX(calculations!$M:$X,318,$P$6),0) -> 0 | G78: =IFERROR(INDEX(calculations!$M:$X,343,$P$6)/INDEX(calculations!$M:$X,318,$P$6),0) -> 0.0375 | H78: =IFERROR(INDEX(calculations!$M:$X,344,$P$6)/INDEX(calculations!$M:$X,318,$P$6),0) -> 0 | I78: YES | J78: =IFERROR(INDEX(calculations!$M:$X,346,$P$6),0) -> 0.318 | K78: =IFERROR(INDEX(calculations!$M:$X,347,$P$6),0) -> 0.318 | L78: =INDEX(input_data!$L:$L,MATCH("all.in.bnk.frt.otn.---",input_data!$A:$A,0)) -> 2.82 | M78: =INDEX(input_data!$L:$L,MATCH("all.in.dfv.frt.otn.---",input_data!$A:$A,0)) -> 3.384 | N78: =MAX(K78-L78,0) -> 0 | O78: 31022100, 31028000, 3105
A80: CBAM-eligible intensity (col 11) = holistic minus S2 × (1-cs2): for iron/steel and aluminium (cs2=0, S2 NOT in scope), CBAM intensity = direct only. For cement and fertilisers (cs2=1, S2 IN scope), CBAM intensity = holistic. Excess (col 14) = MAX(CBAM-eligible − benchmark, 0). Holistic and CBAM intensities respond dynamically to country selector (B5) and detail year (B6). Benchmark and default values are fixed regulatory values (IR 2025/2621 column B). For frt.otn, intensities are in tCO₂e per tonne of N.
A81: Product | B81: View | D81: 2024 | E81: 2025 | F81: 2026 | G81: 2027 | H81: 2028 | I81: 2029 | J81: 2030 | K81: 2031 | L81: 2032 | M81: 2033 | N81: 2034 | O81: 2035
A82: DRI-EAF steel | B82: Holistic | D82: =calculations!M246 -> 2.0181167 | E82: =calculations!N246 -> 2.0111722 | F82: =calculations!O246 -> 2.0042278 | G82: =calculations!P246 -> 1.9972833 | H82: =calculations!Q246 -> 1.9903389 | I82: =calculations!R246 -> 1.9833944 | J82: =calculations!S246 -> 1.97645 | K82: =calculations!T246 -> 1.9695056 | ... O82: =calculations!X246 -> 1.9417278
B83: MRV/CBAM | D83: =calculations!M247 -> 1.66395 | E83: =calculations!N247 -> 1.66395 | F83: =calculations!O247 -> 1.66395 | G83: =calculations!P247 -> 1.66395 | H83: =calculations!Q247 -> 1.66395 | I83: =calculations!R247 -> 1.66395 | J83: =calculations!S247 -> 1.66395 | K83: =calculations!T247 -> 1.66395 | ... O83: =calculations!X247 -> 1.66395
A84: Scrap-EAF steel | B84: Holistic | D84: =calculations!M251 -> 0.79257 | E84: =calculations!N251 -> 0.78007 | F84: =calculations!O251 -> 0.76757 | G84: =calculations!P251 -> 0.75507 | H84: =calculations!Q251 -> 0.74257 | I84: =calculations!R251 -> 0.73007 | J84: =calculations!S251 -> 0.71757 | K84: =calculations!T251 -> 0.70507 | ... O84: =calculations!X251 -> 0.65507
B85: MRV/CBAM | D85: =calculations!M252 -> 0.15507 | E85: =calculations!N252 -> 0.15507 | F85: =calculations!O252 -> 0.15507 | G85: =calculations!P252 -> 0.15507 | H85: =calculations!Q252 -> 0.15507 | I85: =calculations!R252 -> 0.15507 | J85: =calculations!S252 -> 0.15507 | K85: =calculations!T252 -> 0.15507 | ... O85: =calculations!X252 -> 0.15507
A86: BF-BOF steel | B86: Holistic | D86: =calculations!M256 -> 0 | E86: =calculations!N256 -> 0 | F86: =calculations!O256 -> 0 | G86: =calculations!P256 -> 0 | H86: =calculations!Q256 -> 0 | I86: =calculations!R256 -> 0 | J86: =calculations!S256 -> 0 | K86: =calculations!T256 -> 0 | ... O86: =calculations!X256 -> 0
B87: MRV/CBAM | D87: =calculations!M257 -> 0 | E87: =calculations!N257 -> 0 | F87: =calculations!O257 -> 0 | G87: =calculations!P257 -> 0 | H87: =calculations!Q257 -> 0 | I87: =calculations!R257 -> 0 | J87: =calculations!S257 -> 0 | K87: =calculations!T257 -> 0 | ... O87: =calculations!X257 -> 0
A88: Cement | B88: Holistic | D88: =calculations!M261 -> 0.85805 | E88: =calculations!N261 -> 0.8568 | F88: =calculations!O261 -> 0.85555 | G88: =calculations!P261 -> 0.8543 | H88: =calculations!Q261 -> 0.85305 | I88: =calculations!R261 -> 0.8518 | J88: =calculations!S261 -> 0.85055 | K88: =calculations!T261 -> 0.8493 | ... O88: =calculations!X261 -> 0.8443
B89: MRV/CBAM | D89: =calculations!M262 -> 0.85805 | E89: =calculations!N262 -> 0.8568 | F89: =calculations!O262 -> 0.85555 | G89: =calculations!P262 -> 0.8543 | H89: =calculations!Q262 -> 0.85305 | I89: =calculations!R262 -> 0.8518 | J89: =calculations!S262 -> 0.85055 | K89: =calculations!T262 -> 0.8493 | ... O89: =calculations!X262 -> 0.8443
A90: Ammonia | B90: Holistic | D90: =calculations!M266 -> 2.0621 | E90: =calculations!N266 -> 2.0612667 | F90: =calculations!O266 -> 2.0604333 | G90: =calculations!P266 -> 2.0596 | H90: =calculations!Q266 -> 2.0587667 | I90: =calculations!R266 -> 2.0579333 | J90: =calculations!S266 -> 2.0571 | K90: =calculations!T266 -> 2.0562667 | ... O90: =calculations!X266 -> 2.0529333
B91: MRV/CBAM | D91: =calculations!M267 -> 2.0621 | E91: =calculations!N267 -> 2.0612667 | F91: =calculations!O267 -> 2.0604333 | G91: =calculations!P267 -> 2.0596 | H91: =calculations!Q267 -> 2.0587667 | I91: =calculations!R267 -> 2.0579333 | J91: =calculations!S267 -> 2.0571 | K91: =calculations!T267 -> 2.0562667 | ... O91: =calculations!X267 -> 2.0529333
A92: Urea | B92: Holistic | D92: =calculations!M271 -> 0.6229132 | E92: =calculations!N271 -> 0.62207987 | F92: =calculations!O271 -> 0.62124653 | G92: =calculations!P271 -> 0.6204132 | H92: =calculations!Q271 -> 0.61957987 | I92: =calculations!R271 -> 0.61874653 | J92: =calculations!S271 -> 0.6179132 | K92: =calculations!T271 -> 0.61707987 | ... O92: =calculations!X271 -> 0.61374653
B93: MRV/CBAM | D93: =calculations!M272 -> 0.6229132 | E93: =calculations!N272 -> 0.62207987 | F93: =calculations!O272 -> 0.62124653 | G93: =calculations!P272 -> 0.6204132 | H93: =calculations!Q272 -> 0.61957987 | I93: =calculations!R272 -> 0.61874653 | J93: =calculations!S272 -> 0.6179132 | K93: =calculations!T272 -> 0.61707987 | ... O93: =calculations!X272 -> 0.61374653
A94: Ammonium nitrate | B94: Holistic | D94: =calculations!M276 -> 3.0568248 | E94: =calculations!N276 -> 3.0559915 | F94: =calculations!O276 -> 3.0551581 | G94: =calculations!P276 -> 3.0543248 | H94: =calculations!Q276 -> 3.0534915 | I94: =calculations!R276 -> 3.0526581 | J94: =calculations!S276 -> 3.0518248 | K94: =calculations!T276 -> 3.0509915 | ... O94: =calculations!X276 -> 3.0476581
B95: MRV/CBAM | D95: =calculations!M277 -> 3.0568248 | E95: =calculations!N277 -> 3.0559915 | F95: =calculations!O277 -> 3.0551581 | G95: =calculations!P277 -> 3.0543248 | H95: =calculations!Q277 -> 3.0534915 | I95: =calculations!R277 -> 3.0526581 | J95: =calculations!S277 -> 3.0518248 | K95: =calculations!T277 -> 3.0509915 | ... O95: =calculations!X277 -> 3.0476581
A96: Primary aluminium | B96: Holistic | D96: =calculations!M281 -> 9.6788667 | E96: =calculations!N281 -> 9.5344222 | F96: =calculations!O281 -> 9.3899778 | G96: =calculations!P281 -> 9.2455333 | H96: =calculations!Q281 -> 9.1010889 | I96: =calculations!R281 -> 8.9566444 | J96: =calculations!S281 -> 8.8122 | K96: =calculations!T281 -> 8.6677556 | ... O96: =calculations!X281 -> 8.0899778
B97: MRV/CBAM | D97: =calculations!M282 -> 2.3122 | E97: =calculations!N282 -> 2.3122 | F97: =calculations!O282 -> 2.3122 | G97: =calculations!P282 -> 2.3122 | H97: =calculations!Q282 -> 2.3122 | I97: =calculations!R282 -> 2.3122 | J97: =calculations!S282 -> 2.3122 | K97: =calculations!T282 -> 2.3122 | ... O97: =calculations!X282 -> 2.3122
A99: 8. NH₃ CHAIN ACCOUNTING — transparency block (detail year set by B6)
A100: The NH₃ chain accounting cascades ONLY the direct emissions of upstream ammonia to downstream products (urea, AN). Ammonia's own scope-2 (electricity used at the NH₃ plant) is NOT cascaded — that would double-count electricity. Each downstream product accounts for its own scope-2 separately based on its own electricity consumption. Negative S1.np for urea (−0.733 tCO₂/t) represents CO₂ uptake during urea synthesis (which is then re-released when urea is applied as fertiliser — outside the production boundary).
A102: Product | B102: NH₃ factor (t NH₃/t) | C102: NH₃ direct intensity (tCO₂/t NH₃) | D102: NH₃ S2 intensity (tCO₂/t NH₃, NOT cascaded) | E102: Embedded NH₃ direct (tCO₂/t product) | F102: Own S1.fc + S1.fp + S1.np + S1.no (tCO₂/t product) | G102: Own S2 (tCO₂/t product) | H102: Total holistic (tCO₂/t product)
A103: DRI-EAF steel | B103: =INDEX(input_data!$L:$L,MATCH("all.in.nh3.stl.drg.---",input_data!$A:$A,0)) -> 0 | C103: =IFERROR((INDEX(calculations!$M:$X,153,$P$6)+INDEX(calculations!$M:$X,154,$P$6)+INDEX(calculations!$M:$X,155,$P$6)+INDEX(calculations!$M:$X,156,$P$6))/INDEX(calculations!$M:$X,132,$P$6),0) -> 2.0196 | D103: =IFERROR(INDEX(calculations!$M:$X,157,$P$6)/INDEX(calculations!$M:$X,132,$P$6),0) -> 0.0375 | E103: =IFERROR(INDEX(calculations!$M:$X,244,$P$6)/INDEX(calculations!$M:$X,20,$P$6),0) -> 0 | F103: =IFERROR((INDEX(calculations!$M:$X,41,$P$6)+INDEX(calculations!$M:$X,42,$P$6)+INDEX(calculations!$M:$X,43,$P$6)+INDEX(calculations!$M:$X,44,$P$6))/INDEX(calculations!$M:$X,20,$P$6),0) -> 1.66395 | G103: =IFERROR(INDEX(calculations!$M:$X,45,$P$6)/INDEX(calculations!$M:$X,20,$P$6),0) -> 0.3125 | H103: =IFERROR(INDEX(calculations!$M:$X,245,$P$6)/INDEX(calculations!$M:$X,20,$P$6),0) -> 1.97645
A104: Scrap-EAF steel | B104: =INDEX(input_data!$L:$L,MATCH("all.in.nh3.stl.scr.---",input_data!$A:$A,0)) -> 0 | C104: =IFERROR((INDEX(calculations!$M:$X,153,$P$6)+INDEX(calculations!$M:$X,154,$P$6)+INDEX(calculations!$M:$X,155,$P$6)+INDEX(calculations!$M:$X,156,$P$6))/INDEX(calculations!$M:$X,132,$P$6),0) -> 2.0196 | D104: =IFERROR(INDEX(calculations!$M:$X,157,$P$6)/INDEX(calculations!$M:$X,132,$P$6),0) -> 0.0375 | E104: =IFERROR(INDEX(calculations!$M:$X,249,$P$6)/INDEX(calculations!$M:$X,48,$P$6),0) -> 0 | F104: =IFERROR((INDEX(calculations!$M:$X,69,$P$6)+INDEX(calculations!$M:$X,70,$P$6)+INDEX(calculations!$M:$X,71,$P$6)+INDEX(calculations!$M:$X,72,$P$6))/INDEX(calculations!$M:$X,48,$P$6),0) -> 0.15507 | G104: =IFERROR(INDEX(calculations!$M:$X,73,$P$6)/INDEX(calculations!$M:$X,48,$P$6),0) -> 0.5625 | H104: =IFERROR(INDEX(calculations!$M:$X,250,$P$6)/INDEX(calculations!$M:$X,48,$P$6),0) -> 0.71757
A105: BF-BOF steel | B105: =INDEX(input_data!$L:$L,MATCH("all.in.nh3.stl.bof.---",input_data!$A:$A,0)) -> 0 | C105: =IFERROR((INDEX(calculations!$M:$X,153,$P$6)+INDEX(calculations!$M:$X,154,$P$6)+INDEX(calculations!$M:$X,155,$P$6)+INDEX(calculations!$M:$X,156,$P$6))/INDEX(calculations!$M:$X,132,$P$6),0) -> 2.0196 | D105: =IFERROR(INDEX(calculations!$M:$X,157,$P$6)/INDEX(calculations!$M:$X,132,$P$6),0) -> 0.0375 | E105: =IFERROR(INDEX(calculations!$M:$X,254,$P$6)/INDEX(calculations!$M:$X,76,$P$6),0) -> 0 | F105: =IFERROR((INDEX(calculations!$M:$X,97,$P$6)+INDEX(calculations!$M:$X,98,$P$6)+INDEX(calculations!$M:$X,99,$P$6)+INDEX(calculations!$M:$X,100,$P$6))/INDEX(calculations!$M:$X,76,$P$6),0) -> 0 | G105: =IFERROR(INDEX(calculations!$M:$X,101,$P$6)/INDEX(calculations!$M:$X,76,$P$6),0) -> 0 | H105: =IFERROR(INDEX(calculations!$M:$X,255,$P$6)/INDEX(calculations!$M:$X,76,$P$6),0) -> 0
A106: Cement | B106: =INDEX(input_data!$L:$L,MATCH("all.in.nh3.cmt.dry.---",input_data!$A:$A,0)) -> 0 | C106: =IFERROR((INDEX(calculations!$M:$X,153,$P$6)+INDEX(calculations!$M:$X,154,$P$6)+INDEX(calculations!$M:$X,155,$P$6)+INDEX(calculations!$M:$X,156,$P$6))/INDEX(calculations!$M:$X,132,$P$6),0) -> 2.0196 | D106: =IFERROR(INDEX(calculations!$M:$X,157,$P$6)/INDEX(calculations!$M:$X,132,$P$6),0) -> 0.0375 | E106: =IFERROR(INDEX(calculations!$M:$X,259,$P$6)/INDEX(calculations!$M:$X,104,$P$6),0) -> 0 | F106: =IFERROR((INDEX(calculations!$M:$X,125,$P$6)+INDEX(calculations!$M:$X,126,$P$6)+INDEX(calculations!$M:$X,127,$P$6)+INDEX(calculations!$M:$X,128,$P$6))/INDEX(calculations!$M:$X,104,$P$6),0) -> 0.7943 | G106: =IFERROR(INDEX(calculations!$M:$X,129,$P$6)/INDEX(calculations!$M:$X,104,$P$6),0) -> 0.05625 | H106: =IFERROR(INDEX(calculations!$M:$X,260,$P$6)/INDEX(calculations!$M:$X,104,$P$6),0) -> 0.85055
A107: Ammonia | B107: =INDEX(input_data!$L:$L,MATCH("all.in.nh3.frt.amc.---",input_data!$A:$A,0)) -> 0 | C107: =IFERROR((INDEX(calculations!$M:$X,153,$P$6)+INDEX(calculations!$M:$X,154,$P$6)+INDEX(calculations!$M:$X,155,$P$6)+INDEX(calculations!$M:$X,156,$P$6))/INDEX(calculations!$M:$X,132,$P$6),0) -> 2.0196 | D107: =IFERROR(INDEX(calculations!$M:$X,157,$P$6)/INDEX(calculations!$M:$X,132,$P$6),0) -> 0.0375 | E107: =IFERROR(INDEX(calculations!$M:$X,264,$P$6)/INDEX(calculations!$M:$X,132,$P$6),0) -> 0 | F107: =IFERROR((INDEX(calculations!$M:$X,153,$P$6)+INDEX(calculations!$M:$X,154,$P$6)+INDEX(calculations!$M:$X,155,$P$6)+INDEX(calculations!$M:$X,156,$P$6))/INDEX(calculations!$M:$X,132,$P$6),0) -> 2.0196 | G107: =IFERROR(INDEX(calculations!$M:$X,157,$P$6)/INDEX(calculations!$M:$X,132,$P$6),0) -> 0.0375 | H107: =IFERROR(INDEX(calculations!$M:$X,265,$P$6)/INDEX(calculations!$M:$X,132,$P$6),0) -> 2.0571
A108: Urea | B108: =INDEX(input_data!$L:$L,MATCH("all.in.nh3.frt.ure.---",input_data!$A:$A,0)) -> 0.567 | C108: =IFERROR((INDEX(calculations!$M:$X,153,$P$6)+INDEX(calculations!$M:$X,154,$P$6)+INDEX(calculations!$M:$X,155,$P$6)+INDEX(calculations!$M:$X,156,$P$6))/INDEX(calculations!$M:$X,132,$P$6),0) -> 2.0196 | D108: =IFERROR(INDEX(calculations!$M:$X,157,$P$6)/INDEX(calculations!$M:$X,132,$P$6),0) -> 0.0375 | E108: =IFERROR(INDEX(calculations!$M:$X,269,$P$6)/INDEX(calculations!$M:$X,160,$P$6),0) -> 1.1451132 | F108: =IFERROR((INDEX(calculations!$M:$X,181,$P$6)+INDEX(calculations!$M:$X,182,$P$6)+INDEX(calculations!$M:$X,183,$P$6)+INDEX(calculations!$M:$X,184,$P$6))/INDEX(calculations!$M:$X,160,$P$6),0) -> -0.5647 | G108: =IFERROR(INDEX(calculations!$M:$X,185,$P$6)/INDEX(calculations!$M:$X,160,$P$6),0) -> 0.0375 | H108: =IFERROR(INDEX(calculations!$M:$X,270,$P$6)/INDEX(calculations!$M:$X,160,$P$6),0) -> 0.6179132
A109: Ammonium nitrate | B109: =INDEX(input_data!$L:$L,MATCH("all.in.nh3.frt.nit.---",input_data!$A:$A,0)) -> 0.213 | C109: =IFERROR((INDEX(calculations!$M:$X,153,$P$6)+INDEX(calculations!$M:$X,154,$P$6)+INDEX(calculations!$M:$X,155,$P$6)+INDEX(calculations!$M:$X,156,$P$6))/INDEX(calculations!$M:$X,132,$P$6),0) -> 2.0196 | D109: =IFERROR(INDEX(calculations!$M:$X,157,$P$6)/INDEX(calculations!$M:$X,132,$P$6),0) -> 0.0375 | E109: =IFERROR(INDEX(calculations!$M:$X,274,$P$6)/INDEX(calculations!$M:$X,188,$P$6),0) -> 0.4301748 | F109: =IFERROR((INDEX(calculations!$M:$X,209,$P$6)+INDEX(calculations!$M:$X,210,$P$6)+INDEX(calculations!$M:$X,211,$P$6)+INDEX(calculations!$M:$X,212,$P$6))/INDEX(calculations!$M:$X,188,$P$6),0) -> 2.58415 | G109: =IFERROR(INDEX(calculations!$M:$X,213,$P$6)/INDEX(calculations!$M:$X,188,$P$6),0) -> 0.0375 | H109: =IFERROR(INDEX(calculations!$M:$X,275,$P$6)/INDEX(calculations!$M:$X,188,$P$6),0) -> 3.0518248
A110: Primary aluminium | B110: =INDEX(input_data!$L:$L,MATCH("all.in.nh3.alu.prp.---",input_data!$A:$A,0)) -> 0 | C110: =IFERROR((INDEX(calculations!$M:$X,153,$P$6)+INDEX(calculations!$M:$X,154,$P$6)+INDEX(calculations!$M:$X,155,$P$6)+INDEX(calculations!$M:$X,156,$P$6))/INDEX(calculations!$M:$X,132,$P$6),0) -> 2.0196 | D110: =IFERROR(INDEX(calculations!$M:$X,157,$P$6)/INDEX(calculations!$M:$X,132,$P$6),0) -> 0.0375 | E110: =IFERROR(INDEX(calculations!$M:$X,279,$P$6)/INDEX(calculations!$M:$X,216,$P$6),0) -> 0 | F110: =IFERROR((INDEX(calculations!$M:$X,237,$P$6)+INDEX(calculations!$M:$X,238,$P$6)+INDEX(calculations!$M:$X,239,$P$6)+INDEX(calculations!$M:$X,240,$P$6))/INDEX(calculations!$M:$X,216,$P$6),0) -> 2.3122 | G110: =IFERROR(INDEX(calculations!$M:$X,241,$P$6)/INDEX(calculations!$M:$X,216,$P$6),0) -> 6.5 | H110: =IFERROR(INDEX(calculations!$M:$X,280,$P$6)/INDEX(calculations!$M:$X,216,$P$6),0) -> 8.8122
A112: Accounting check: Holistic intensity (col 8) = embedded NH₃ direct + own direct + own S2 = col 5 + col 6 + col 7. For urea/AN, the NH₃ feedstock factor (col 2) is non-zero so col 5 captures the upstream chain. For ammonia itself and others, col 5 is zero (no upstream NH₃). NH₃ S2 (col 4) is shown for reference but is NEVER added to downstream products — only ammonia itself charges that scope.
A114: 9. PRODUCT REFERENCE — CN codes (EU Reg 2023/956 Annex I)
A115: Internal code | B115: Product | C115: CN code | D115: Route indicator | E115: Description (Annex I)
...

Sheet explainer
A1: Pass 8 — Explainer & Legend
A2: What this workbook does, how the levers work, and how to read each sheet.
A4: 1. What this workbook models
B6: Scope | C6: 5 countries (Egypt, Albania, Uzbekistan, Azerbaijan, India) × 8 CBAM-eligible products × 12 years (2024–2035). Tracks production, exports, emissions across 5 scope buckets, EU CBAM obligations, and optimal country-level carbon-pricing responses.
B7: Products | C7: DRI-EAF steel, Scrap-EAF steel, BF-BOF steel, Cement, Ammonia, Urea, Ammonium nitrate, Primary aluminium. Each carries its EU CN code (Combined Nomenclature). See dashboard section 9 for the full product reference card.
B8: Five scope buckets | C8: S1.fc — fuel combustion CO₂. S1.fp — fuel-as-reductant CO₂ (BF coke, DRI shaft NG, SMR reformer NG). S1.np — non-fuel process CO₂ (calcination, urea uptake). S1.no — non-CO₂ GHG (N₂O, PFCs). S2 — electricity.
B9: Coverage flags | C9: Each scope has an independent on/off flag on the dashboard (2a, cells B11–B15). These say what the country's domestic CP is levied on. They do NOT change the regulatory definition of CBAM scope — that's the cs2 flag per product (EU Reg 2023/956 Annex II: cs2=0 for iron/steel and aluminium; cs2=1 for cement, fertilisers).
A11: 2. What's new in Pass 8
B13: Finalised CBAM benchmarks | C13: IR (EU) 2025/2621 adopted 16 Dec 2025. Default-value pathway benchmarks (column B): BF-BOF 1.370 (was 1.530), DRI-EAF 0.481 (was 1.033), Scrap-EAF 0.072 (was 0.288), Cement clinker 0.666 (was 0.693), Aluminium 1.423 (was 1.484). Ammonia, urea, AN unchanged. The scrap drop is the largest in proportional terms and pulls recycled steel firmly into the CBAM net. EU defaults reset to ~20% above the new benchmarks.
B14: Declining grid emission factors | C14: Grid EFs are now 12-year time series, declining linearly from 2024 anchor to 2035 end-point per each country's NDC trajectory. Egypt 0.510 → 0.400; Albania 0.045 → 0.035; Uzbekistan 0.540 → 0.420; Azerbaijan 0.460 → 0.370; India 0.713 → 0.500 tCO₂/MWh. The s2e formula resolves the year-indexed value; everything downstream (intensities, CBAM obligation, optimal CP) responds automatically.
B15: Product CN codes | C15: Each product now carries its EU Combined Nomenclature code from Reg 2023/956 Annex I and the IR 2025/2621 route indicator where applicable: steel CN 7206 with (C) BF-BOF, (D) DRI-EAF, (E) Scrap-EAF; cement clinker CN 25231000 (A) grey; aluminium CN 76011000 (K) primary; ammonia CN 28141000; urea CN 31021010; AN CN 31023090. Visible in dashboard Section 5 (price impact) and Section 6b (EF matrix), with a full reference table in Section 9.
A17: 3. Carried over from Pass 7
B19: India added | C19: Fifth country with realistic 2024 production: ~150 Mt crude steel (110 BF-BOF, 32 DRI-EAF, 8 scrap), 440 Mt cement, 17 Mt NH₃, 30 Mt urea, 4.1 Mt aluminium.
B20: BF-BOF integrated | C20: BF-BOF steel is a regular entity in every country's matrix.
B21: 5-scope coverage flags | C21: Independent on/off flags per scope.
B22: Global MRV per product | C22: Single row B19:I19, one cell per product, applies to all 5 countries.
B23: Exports-only tax toggle | C23: B22: when 1, CP levied only on exports (EU + non-EU).
B24: NH₃ chain transparency | C24: Dashboard Section 8 makes the upstream ammonia chain visible. Only direct emissions of ammonia cascade into urea/AN; S2 of ammonia is shown but NOT cascaded.
B25: EF matrix display | C25: Dashboard Section 6: fuel EFs and per-product calculated intensities.
A27: 4. Key levers — what to move first
B29: B5 — country | C29: Pick from egy/alb/uzb/aze/ind. Everything redraws.
B30: B6 — detail year | C30: Year for Section 5 (price impact) and Section 6b (per-product intensities).
B31: B7 — pass-through θ | C31: Share of wedge passed to buyer prices vs producer margins. Default 0.7.
B32: B11–B15 — coverage flags | C32: Independent on/off for fc, fp, np, no, s2. Whether S2 is credited against CBAM is separately gated by cs2 (row 20).
B33: B19:I19 — MRV per product | C33: 1 if exporter has actual MRV data; 0 to use EU default. Global per product.
B34: B22 — exports-only tax | C34: 0: CP levied on all production. 1: only on exports.
B35: Row 29 — domestic CP | C35: Defaults to optimal CP from row 28. Edit to test sub-optimal or over-shooting pricing.
A37: 5. Sheets in this workbook
B39: dashboard | C39: Inputs and headline outputs (9 sections including the new CN reference card).
B40: explainer | C40: This sheet.
B41: input_data | C41: 1,064 rows keyed by code (cty.dom.par.sec.prc.sub). Universal time series, fuel EFs, per-entity constants, country-level constants (grid EFs now time series), per-country blocks, and Section 7 product CN codes.
B42: calculations | C42: 284 rows. Country-aware. Uniform per-entity block. s2e resolves year-indexed grid EF.
A44: 6. Methodology notes
B46: Two CBAM benchmark columns | C46: EU Reg 2025/2621 specifies separate benchmarks for column A (use with actual measured data) and column B (use with default values). The workbook uses column B uniformly — adequate for first-pass policy analysis. Splitting them is a candidate refinement.
B47: CBAM factor schedule | C47: EU Reg 2025/2620: 2.5% 2026, 5% 2027, 10% 2028, 22.5% 2029, 48.5% 2030, 61% 2031, 73.5% 2032, 86% 2033, 100% 2034.
B48: CBAM scope per product (cs2) | C48: EU Reg 2023/956 Annex II: direct + indirect (S2) for cement, fertilisers, hydrogen. Direct only for iron & steel and aluminium.
B49: NH₃ chain accounting | C49: Urea embeds 0.567 t NH₃/t; AN embeds 0.213 t NH₃/t. Only ammonia direct emissions cascade — S2 is NOT cascaded because each downstream product accounts for its own electricity.
B50: Optimal carbon price | C50: Row 28: country-level CP that captures the CBAM gross as country revenue. Derived as CBAM_gross / (Σ EU_exports × creditable_intensity).
B51: Grid EF trajectories | C51: Linear interpolation between IEA 2024 anchors and 2035 NDC-consistent end-points.
A53: 7. Key regulatory references
B55: EU Reg 2023/956 | C55: CBAM regulation. Annex I lists covered CN codes; Annex II scope (direct vs direct+indirect).
B56: EU IR 2025/2620 | C56: CBAM phase-in schedule; free allocation adjustment rules.
B57: EU IR 2025/2621 | C57: Final CBAM benchmarks (column A vs B) and default values, 16 Dec 2025.
B58: IPCC 2006 Vol. 2 Ch. 2 | C58: Stationary combustion emission factors per fuel.
B59: IEA Emission Factors 2025 | C59: Grid EF 2024 anchors.
B60: Climate Action Tracker 2026 | C60: India 2035 NDC (60% non-fossil capacity).

Sheet benchmarks
B1: CBAM Benchmarks and Default Values — Regulatory Reference Sheet
A3: 1. What benchmarks and default values are, and why they differ
B5: The two pathways | C5: CBAM uses two distinct pathways to determine embedded emissions for the purpose of calculating how many certificates an EU importer must surrender: PATHWAY A — Actual verified data. The non-EU producer provides verified actual embedded emissions, certified by an accredited CBAM verifier under the rules in Implementing Regulation (EU) 2025/2547. This uses the Column A benchmark. PATHWAY B — Default values. Where actual data is not available or not verified, the EU importer uses country-specific and product-specific default values from Implementing Regulation (EU) 2025/2621. This uses the Column B benchmark. The benchmark (BM) enters the formula as a deduction — it represents the quantity of emissions already implicitly allocated for free under the EU ETS. A higher benchmark means more is deducted, so the CBAM cost is lower. Column B benchmarks are set higher than Column A for most products (notably steel), meaning importers using default values face a smaller penalty from the benchmark deduction — but they pay the higher default emission value, which typically more than offsets this.
B6: The CBAM formula (definitive phase, from 2026) | C6: CBAM certificates to surrender = max( SEE − SEFA, 0 ) × CBAM factor Where: SEE = Specific Embedded Emissions (tCO₂e/t), determined by Pathway A or B SEFA = Specific Embedded Free Allocation (tCO₂e/t) = CBAM factor × BM × CSCF CBAM factor = phase-in share of certificates to be purchased (IR 2025/2620 Annex) 2026: 2.5% | 2027: 5.0% | 2028: 10% | 2029: 22.5% 2030: 48.5% | 2031: 61% | 2032: 73.5%| 2033: 86% 2034+: 100% BM = CBAM benchmark (Column A or B depending on pathway) from IR 2025/2621 CSCF = Cross-Sectoral Correction Factor (EU ETS parameter; currently 1.0 for 2026–2030) Certificate price = quarterly average EU ETS price (EUR/tCO₂) Total CBAM cost = certificates × certificate price In this model's simplified form: CBAM/t = max( MRV_intensity − BM × (1 − CBAM_factor), 0 ) × ETS_price × FX × active (The (1 − CBAM_factor) term comes from: SEFA = CBAM_factor × BM, so BM − SEFA = BM × (1 − CBAM_factor))
B7: Credit for carbon prices already paid | C7: Article 9 of Regulation (EU) 2023/956: the number of certificates to be surrendered is reduced by a carbon price effectively paid in the country of origin. The carbon price already paid must be officially established, legally binding, and not reimbursed or compensated in any other way. This is the mechanism by which an exporting country can capture CBAM revenue as domestic fiscal revenue — by levying an equivalent domestic carbon price and having it recognised as creditable. The model calculates the optimal carbon price as the level at which the domestic charge exactly equals the CBAM gross, resulting in zero EU net retention.
B8: Mark-up on default values | C8: Per IR 2025/2621 Recital 15 and Article 3(2): default values carry a mark-up above the country-specific average to incentivise verified actual data reporting. Mark-ups: 2026: +10% | 2027: +20% | 2028 onwards: +30% Exception: fertilisers carry a +1% mark-up only (2026–2028), per Omnibus simplification (Regulation (EU) 2025/2083), citing agricultural price sensitivity and food security. The model currently uses a single EU default value per product (~20% above benchmark) as a simplified proxy for the definitive-phase default pathway. Country-specific default values from IR 2025/2621 Annex I are cited below.
A10: 2. IR (EU) 2025/2620 — CBAM factor schedule (near-verbatim from Annex)
B12: Legal citation | C12: Commission Implementing Regulation (EU) 2025/2620 of 16 December 2025 laying down rules for the application of Regulation (EU) 2023/956 as regards the calculation of the free allocation adjustment to the number of CBAM certificates to be surrendered. OJ L 2025/2620, 22.12.2025.
B13: CBAM factor schedule (Annex, Table 1) | C13: Reporting year | CBAM factor 2026 | 0.025 (2.5%) 2027 | 0.050 (5.0%) 2028 | 0.100 (10.0%) 2029 | 0.225 (22.5%) 2030 | 0.485 (48.5%) 2031 | 0.610 (61.0%) 2032 | 0.735 (73.5%) 2033 | 0.860 (86.0%) 2034+ | 1.000 (100.0%) NOTE: 'Reporting year' is the calendar year of import. Certificates are surrendered by 31 May of the following year (first surrender by 31 May 2027 for 2026 imports).
A15: 3. IR (EU) 2025/2621 — Benchmarks and default values (Annex I, selected)
B17: Legal citation | C17: Commission Implementing Regulation (EU) 2025/2621 of 16 December 2025 laying down rules for the application of Regulation (EU) 2023/956 as regards the establishment of default values. OJ L 2025/2621, 22.12.2025. Applies from 1 January 2026.
B18: Production route indicators (from Annex I introduction) | C18: (A) grey clinker / cement (B) white clinker / cement (C) Carbon Steel based on BF/BOF (D) Carbon Steel based on DRI/EAF (E) Carbon Steel based on Scrap/EAF (F) Low alloy Steel based on BF/BOF (G) Low alloy Steel based on DRI/EAF (H) Low alloy Steel based on Scrap/EAF (J) High alloy Steel (based on EAF) (K) Primary Aluminium (L) Secondary Aluminium Where more than one benchmark value is given for a specific CN code, indicators shown in parentheses identify which production route applies.
B19: Note on Column A vs Column B | C19: Column A (BMg*): Benchmark for use when actual verified emissions are reported. Applies when Pathway A is used. Values marked * are subject to annual update. Column B (BMg): Benchmark for use when default values are applied (Pathway B). Generally higher than Column A for steel (reflecting the higher EU ETS allocation basis for default-value users), and similar or identical for other sectors.
B21: CN code | C21: CN description | D21: Route | E21: Column A (BMg*) tCO₂e/t | F21: Column B (BMg) tCO₂e/t | G21: Model entity | H21: Notes
B22: 25070080 | C22: Kaolinic clays (other than kaolin) | D22: — | E22: 0.666 | F22: 0.666 | G22: cmt.dry (proxy) | H22: Same benchmark as grey clinker
B23: 25231000 | C23: Cement clinkers | D23: (A) | E23: 0.666 | F23: 0.666 | G23: cmt.dry | H23: Grey clinker; (B) white = 0.859
B24: 25231000 | C24: Cement clinkers — white | D24: (B) | E24: 0.859 | F24: 0.859 | G24: — (not modelled) | H24: White clinker benchmark
B25: 25232100 | C25: Portland cement, excl. white, whether or not coloured | D25: (A) | E25: 0.666 | F25: 0.666 | G25: cmt.dry (proxy)
B26: 25232900 | C26: Cement other than Portland | D26: (A) | E26: 0.666 | F26: 0.666 | G26: cmt.dry (proxy)
B27: 7206 | C27: Iron and non-alloy steel, ingots or primary forms | D27: (C) | E27: 1.37 | F27: 1.37 | G27: stl.bof | H27: BF/BOF carbon steel
B28: 7206 | C28: Iron and non-alloy steel, ingots or primary forms | D28: (D) | E28: 0.481 | F28: 0.481 | G28: stl.drg | H28: DRI/EAF carbon steel
B29: 7206 | C29: Iron and non-alloy steel, ingots or primary forms | D29: (E) | E29: 0.072 | F29: 0.072 | G29: stl.scr | H29: Scrap/EAF carbon steel
B30: 7207 | C30: Semi-finished products, iron or non-alloy steel | D30: (C) | E30: 1.37 | F30: 1.37 | G30: stl.bof
B31: 7207 | C31: Semi-finished products, iron or non-alloy steel | D31: (D) | E31: 0.481 | F31: 0.481 | G31: stl.drg
B32: 7207 | C32: Semi-finished products, iron or non-alloy steel | D32: (E) | E32: 0.072 | F32: 0.072 | G32: stl.scr
B33: 7201 | C33: Pig iron and spiegeleisen in pigs, blocks or other primary forms | D33: — | E33: 1.9 | F33: 1.9 | G33: stl.oth (component) | H33: No route split — single benchmark ~1.9 tCO₂/t
B34: 7202 4 | C34: Ferro-manganese (FeMn) | D34: — | E34: 1.44 | F34: 1.44 | G34: stl.oth (component)
B35: 7202 6 | C35: Ferro-chromium (FeCr) | D35: — | E35: 3 | F35: 3 | G35: stl.oth (component) | H35: Approx.; range 3–5 depending on grade
B36: 7202 7 | C36: Ferro-nickel (FeNi) | D36: — | E36: 5.5 | F36: 5.5 | G36: stl.oth (component) | H36: Approx.; range 5–6
B37: 7203 | C37: Ferrous products from direct reduction of iron ore | D37: — | E37: 0.481 | F37: 0.481 | G37: stl.drg / stl.oth | H37: Same benchmark as DRI-EAF steel route
B38: 28141000 | C38: Ammonia, anhydrous | D38: — | E38: 1.522 | F38: 1.522 | G38: frt.amc
B39: 28142000 | C39: Ammonia, in aqueous solution | D39: — | E39: 1.522 | F39: 1.522 | G39: frt.amc (proxy)
B40: 31021010 | C40: Urea, whether or not in aqueous solution, > 45% N | D40: — | E40: 0.053 | F40: 0.902 | G40: frt.ure | H40: Col A very low (CO₂ uptake); Col B used for default
B41: 31023090 | C41: Ammonium nitrate, excl. aqueous solution | D41: — | E41: 0.302 | F41: 0.302 | G41: frt.nit
B42: 31022100 | C42: Ammonium sulphate | D42: — | E42: 0.4 | F42: 0.46 | G42: frt.otn (component) | H42: Approx. from IFA/EFMA; IR 2025/2621 exact value
B43: 31028000 | C43: Urea ammonium nitrate (UAN) solution | D43: — | E43: 0.84 | F43: 0.9 | G43: frt.otn (component) | H43: Approx. blend of urea + AN benchmarks
B44: 3105 | C44: Mixed N fertilisers (NPK/NP, excl. 31056000) | D44: — | E44: 0.45 | F44: 0.5 | G44: frt.otn (component) | H44: Per tonne product; N fraction benchmark ~3 tCO₂/t N
B45: 76011000 | C45: Aluminium, unwrought, not alloyed | D45: (K) | E45: 1.423 | F45: 1.423 | G45: alu.prp | H45: Primary aluminium
B46: 76012000 | C46: Aluminium, unwrought, alloyed | D46: (L) | E46: 0.091 | F46: 0.091 | G46: — (not modelled; zero for recycled) | H46: Secondary aluminium — near-zero benchmark
B47: 76041000 | C47: Bars and rods, of aluminium, not alloyed | D47: (K) | E47: 1.479 | F47: 1.479 | G47: alu.prp (proxy) | H47: Primary + 0.056 forming
B48: 76061100 | C48: Plates and sheets, of aluminium, not alloyed, > 0.2mm | D48: (K) | E48: 1.479 | F48: 1.479 | G48: alu.prp (proxy)
B49: 76071100 | C49: Aluminium foil, not backed, rolled but not further worked | D49: (K) | E49: 1.479 | F49: 1.479 | G49: alu.prp (proxy)
B50: 28041000 | C50: Hydrogen, whether or not compressed | D50: — | E50: 0 | F50: 0 | G50: — (not modelled) | H50: Green H₂ near-zero; grey H₂ ~10 tCO₂/t not covered
B52: Key observations from the benchmark table | C52: 1. The Column A / Column B distinction is consequential only for urea (Col A = 0.053, Col B = 0.902 — a 17× difference reflecting that urea's actual embedded emissions are very low when modern plants are measured, but the default pathway is conservative). 2. For steel, Column A and Column B benchmarks are identical (1.370 / 0.481 / 0.072). The pathway distinction matters only through the embedded emissions (SEE): Pathway A uses actual measured intensities, Pathway B uses conservative country-specific defaults that for high-intensity origins (China, India, Indonesia) are often 2–3× the benchmark. 3. The scrap-EAF benchmark (0.072 tCO₂/t) dropped sharply from the provisional 0.288 in the final IR 2025/2621 regulation. This reflects the principle that scrap steel carries zero embedded emissions from upstream ore processing — the benchmark now reflects only the marginal melting and refining emissions. 4. Ferroalloy benchmarks are approximate in this model. The exact values per CN code and alloy grade are in Annex I of IR 2025/2621, which should be consulted directly for compliance calculations.

Sheet egypt_facilities
B1: Egypt — CBAM-relevant facilities by sector
B2: All facilities in Egypt producing CBAM-eligible goods as of 2024/2025. 'Facility' here corresponds to what the CBAM regulation calls an 'installation' — the production unit whose embedded emissions must be reported. Each row is one facility. Multiple facilities within one corporate group are listed separately. CBAM reporting is at installation level, not company level. Sources: GEM Steel Plant Tracker, Ezz Steel IR, Cemnet.com, Abu Qir/MOPCO/KIMA annual reports, USGS Mineral Yearbooks, IAI, Egyptian Fertilizer Association.
A4: SECTION A — Iron & Steel (CBAM CN 7206/7207 and related)
A5: # | B5: Facility / installation name | C5: Operating company | D5: Location | E5: CBAM entity (model code) | F5: Technology / process route | G5: Annual capacity (Mt/yr crude steel) | H5: Approx. 2024 actual output | I5: EU-relevant exports (indicative) | J5: CBAM intensity estimate tCO₂/t | K5: EU default value tCO₂/t (for origin) | L5: Notes / CBAM status
A6: 1 | B6: EZDK — Al Ezz Dekheila Steel, Alexandria | C6: Ezz Steel (EZDK; 64% Ezz Steel, 20% Egyptian Govt) | D6: Dekheila port, Alexandria | E6: stl.drg | F6: DRI (Midrex, 3 modules, 3.1 Mt/yr) + 4×EAF (80% DRI + 20% scrap) | G6: 3.2 | H6: 3.2 | I6: Exports rebar, wire rod, HRC. EU share ~15–20%. | J6: ~1.5–1.8 (NG-based DRI is efficient; grid adds S2) | K6: ~1.80 (Egypt default; Reg 2025/2621 Annex I) | L6: Largest DRI complex in MENA. 4 EAFs (80MVA×4). CBAM-eligible on EU HRC/rebar exports. Midrex shaft process, natural gas reforming. EZDK listed on EGX (ticker: IRAX).
A7: 2 | B7: Ezz Flat Steel Ain Sokhna (EFS) | C7: Ezz Steel (subsidiary) | D7: Ain Sokhna industrial zone, Suez governorate | E7: stl.drg | F7: DRI mega module (HYL/Danieli) + 2×EAF 185t, 133/160 MVA & 210 MVA | G7: 2 | H7: 1.8 | I7: Flat products (HRC, slabs). EU-oriented export stream. | J7: ~1.6–1.9 | K7: ~1.80 | L7: Opened 2015 with world's largest single DRI module at commissioning. Second EAF commissioned 2023. Produces HRC for export. CBAM obligation on EU HRC exports.
A8: 3 | B8: Ezz Steel Sadat City — rebar | C8: Ezz Steel Co. S.A.E. | D8: Sadat City, Menofia governorate | E8: stl.drg | F8: 1×EAF (80% DRI + 20% scrap) + 2 rolling mills | G8: 1 | H8: 0.9 | I8: Rebar for domestic market; limited EU export. | J8: ~1.5–1.7 | K8: ~1.80 | L8: Ezz Steel's first plant (1994). Primarily serves domestic construction market. CBAM exposure mainly indirect through export of other Ezz entities.
A9: 4 | B9: Suez Steel / Solb Misr — Attaka plant | C9: Solb Misr (part of National Service Products Organisation) | D9: Attaka, Suez governorate | E9: stl.drg | F9: DRI (Energiron / Danieli, 1.95 Mt/yr) + EAF (Danieli, 1.25 Mt/yr) | G9: 2 | H9: 1.5 | I9: Long products (billets, blooms). Some EU exports. | J9: ~1.6–1.9 | K9: ~1.80 | L9: Egypt's second largest steelmaker. DRI plant commissioned 2023. Part of military-affiliated conglomerate. Blooms and round billets sold openly.
A10: 5 | B10: Delta Steel / Beshay Steel | C10: Beshay Steel Group | D10: 10th of Ramadan City, Sharqia governorate | E10: stl.scr | F10: EAF (scrap-based); multiple furnaces | G10: 0.8 | H10: 0.7 | I10: Rebar for domestic use; minimal EU export. | J10: ~0.5–0.7 (scrap EAF) | K10: ~0.72 (Egypt scrap-EAF default) | L10: Scrap-EAF mini-mill. CBAM exposure lower due to scrap route and minimal EU exports.
A11: 6 | B11: National Iron & Steel (Hadisolb) — Helwan | C11: Formerly Egyptian Iron & Steel Co. (state-owned) | D11: Helwan, South Cairo | E11: stl.bof | F11: BF-BOF (integrated blast furnace; in liquidation since Jan 2021) | G11: 0 | H11: 0 | I11: Zero — plant in liquidation. | J11: N/A — not operating | K11: N/A | L11: Historical note only. Hadisolb was Egypt's original integrated steelworks. Entered liquidation January 2021; contributes zero output. Was a BF-BOF route.
A13: SECTION B — Cement (CBAM CN 25231000, 25232100, 25232900)
A14: # | B14: Facility name | C14: Operating company | D14: Location | E14: Type | F14: Capacity (Mt/yr clinker) | G14: 2024 est. output | H14: EU export orientation | I14: Intensity est. tCO₂/t clinker | J14: EU default tCO₂/t | K14: Ownership | L14: Notes
A15: 1 | B15: Lafarge Egypt — Sokhna plant | C15: Lafarge Holcim Egypt (Holcim 80%) | D15: Ain Sokhna, Suez | E15: Dry kiln | F15: 10.6 | G15: 9 | H15: Major exporter — EU, Africa, GCC | I15: ~0.75–0.83 | J15: ~1.58 | K15: Holcim (80%) / Egyptian investors | L15: Largest cement plant in Egypt. 5 production lines. Key CBAM-exposed exporter.
A16: 2 | B16: Cemex Assiut Cement | C16: Cemex Egypt | D16: Assiut, Upper Egypt | E16: Dry kiln | F16: 5.7 | G16: 4.8 | H16: Domestic focus; some exports | I16: ~0.78–0.85 | J16: ~1.58 | K16: Cemex (100%) | L16: Old established plant; partially upgraded. Limited EU exposure.
A17: 3 | B17: Italcementi Suez Cement | C17: Heidelberg Materials Egypt (formerly Italcementi) | D17: Suez | E17: Dry kiln | F17: 4.1 | G17: 3.5 | H17: Export-oriented via Suez Canal | I17: ~0.78–0.84 | J17: ~1.58 | K17: Heidelberg Materials (majority) | L17: Suez location favours export. CBAM relevant.
A18: 4 | B18: Italcementi Tourah Cement | C18: Heidelberg Materials / Tourah Portland | D18: Tourah, Cairo | E18: Dry/wet mix | F18: 3.5 | G18: 2.8 | H18: Mainly domestic | I18: ~0.80–0.88 | J18: ~1.58 | K18: Heidelberg Materials (majority) | L18: Older plant; wet kiln lines remain. Lower efficiency.
A19: 5 | B19: Army Al Arish Cement | C19: National Service Products Organisation (NSPO / Military) | D19: Al Arish, North Sinai | E19: Dry kiln | F19: 3.5 | G19: 3.2 | H19: Domestic + some North Africa exports | I19: ~0.78–0.83 | J19: ~1.58 | K19: Egyptian Military (NSPO) | L19: Military-controlled. Limited export transparency.
A20: 6 | B20: Vicat Sinai Cement | C20: Vicat SA (France, majority) | D20: Ain Sukhna road, Sinai corridor | E20: Dry kiln | F20: 3.3 | G20: 2.9 | H20: Export (EU, Mediterranean) | I20: ~0.77–0.82 | J20: ~1.58 | K20: Vicat SA (~60%) | L20: Modern plant. EU exposure through exports. CBAM directly relevant.
A21: 7 | B21: Misr Beni Suef Cement | C21: ASEC Holding (subsidiary) | D21: Beni Suef, Upper Egypt | E21: Dry kiln | F21: 3.5 | G21: 3 | H21: Mainly domestic | I21: ~0.78–0.84 | J21: ~1.58 | K21: ASEC Holding / Egyptian investors | L21: Under ASEC technical management.
A22: 8 | B22: Misr Cement Qena | C22: ASEC Holding (subsidiary) | D22: Qena, Upper Egypt | E22: Dry kiln | F22: 3 | G22: 2.6 | H22: Mainly domestic | I22: ~0.79–0.85 | J22: ~1.58 | K22: ASEC Holding
A23: 9 | B23: Arabian Cement | C23: Arabian Cement Co (listed EGX) | D23: Ain Sokhna area, Suez | E23: Dry kiln | F23: 2.5 | G23: 2.2 | H23: Exports (EU, Mediterranean, Africa) | I23: ~0.77–0.82 | J23: ~1.58 | K23: Saudi / Egyptian investors (listed)
A24: 10 | B24: Titan Cement Egypt — Alexandria | C24: Titan Cement SA (Greece) | D24: Alexandria | E24: Dry kiln | F24: 1.6 | G24: 1.4 | H24: Mediterranean exports | I24: ~0.76–0.81 | J24: ~1.58 | K24: Titan Cement SA (Greece) | L24: EU parent; good MRV capability.
A25: 11 | B25: Titan Cement Egypt — Beni Suef | C25: Titan Cement SA (Greece) | D25: Beni Suef | E25: Dry kiln | F25: 1.3 | G25: 1.1 | H25: Mainly domestic | I25: ~0.78–0.83 | J25: ~1.58 | K25: Titan Cement SA (Greece)
A26: 12 | B26: El Sewedy Cement | C26: El Sewedy Electric (Egyptian group) | D26: 6th October City, Giza | E26: Dry kiln | F26: 2 | G26: 1.7 | H26: Export (Africa, some EU) | I26: ~0.79–0.84 | J26: ~1.58 | K26: El Sewedy Electric
A27: 13 | B27: South Valley Cement | C27: South Valley Cement Co (listed EGX) | D27: Qena / Sohag area | E27: Dry kiln | F27: 1.6 | G27: 1.3 | H27: Mainly domestic | I27: ~0.79–0.85 | J27: ~1.58 | K27: Egyptian investors (listed)
A28: 14 | B28: ASEC Cement — El Minya | C28: ASEC Holding | D28: Minya, Upper Egypt | E28: Dry kiln | F28: 2 | G28: 1.7 | H28: Mainly domestic | I28: ~0.79–0.85 | J28: ~1.58 | K28: ASEC Holding
A29: 15 | B29: Sinai Cement (White) | C29: ASEC Holding (subsidiary) | D29: North Sinai | E29: Dry kiln (white cement) | F29: 0.6 | G29: 0.5 | H29: Specialty exports | I29: ~0.83–0.90 | J29: ~1.58 | K29: ASEC Holding | L29: White cement specialist. CBAM benchmark (B) = 0.859 for white clinker.
A31: SECTION C — Fertilisers (CBAM CN 28141000, 31021010, 31023090, 31022100)
A32: # | B32: Facility / company | C32: Owner / shareholder | D32: Location | E32: Products | F32: Ammonia capacity (kt/yr) | G32: Urea capacity (kt/yr) | H32: AN/other (kt/yr) | I32: Est. 2024 output | J32: EU export share | K32: CBAM intensity (tCO₂/t product) | L32: Notes / CBAM status
A33: 1 | B33: Abu Qir Fertilizers (AFC) | C33: Abu Dhabi Dev. Holding 21.5%, SEIC 19.8%, EGPC 19.1%, public float | D33: Abu Qir, Alexandria | E33: Ammonia, granular urea, AN, UAN, prilled urea, ammonium sulphate | F33: 600 | G33: 1000 | H33: 300 (AN) + amsul | I33: ~2.2 Mt total (all products, 2023) | J33: ~50% of urea output exported to EU (largest single EU supplier) | K33: NH₃ ~1.4 tCO₂/t; Urea ~1.4 tCO₂/t (Egypt default) | L33: Egypt's largest nitrogen fertiliser producer; ~50% of national N output. 3 ammonia-urea trains plus AN section. CBAM most exposed Egyptian fertiliser facility. December 2024: signed green H₂ and energy efficiency agreements to prepare for CBAM. Abu Qir is listed on EGX (ticker: ABUK). EU export share estimated 40–50% of urea output.
A34: 2 | B34: MOPCO — Misr Fertilizer Production Co. | C34: EBIC 20%, public float 41.5%, Egyptian investors | D34: Damietta / Borg El Arab, Alexandria | E34: Ammonia, granular urea | F34: 390 | G34: 650 | H34: — | I34: ~1.0 Mt urea (est.) | J34: ~20–30% EU / Mediterranean | K34: Urea ~1.4 tCO₂/t (Egypt default) | L34: MOPCO operates two ammonia-urea trains. Listed on EGX (MOPCO.CA). Modern NG-based Haber-Bosch + Stamicarbon urea synthesis.
A35: 3 | B35: Egypt Basic Industries Corp. (EBIC) | C35: SABIC 50%, Fertiglobe 25%, Japanese consortium 25% | D35: Ain Sokhna Industrial Zone, Suez | E35: Ammonia only (exported) | F35: 750 | G35: — | H35: — | I35: ~0.65 Mt ammonia (est.) | J35: ~20% EU (mainly ammonia to European chemical sector) | K35: NH₃ ~1.0–1.3 tCO₂/t (modern plant; lower than Egypt average) | L35: One of Egypt's most efficient ammonia plants. Natural gas feedstock at subsidised rate. CBAM: ammonia is CBAM-eligible (CN 28141000). EU imports of ammonia rising as Algeria/Russia redirect.
A36: 4 | B36: Egyptian Fertilizers Co. (EFC) | C36: Aabar Investments (Abu Dhabi) 55%, Egyptian investors | D36: Ain Sokhna, Suez | E36: Ammonia, granular urea | F36: 330 | G36: 500 | H36: — | I36: ~0.5 Mt urea (est.) | J36: ~30% EU / Mediterranean | K36: Urea ~1.4 tCO₂/t | L36: NG-based ammonia-urea. Part of Fertiglobe group indirectly.
A37: 5 | B37: KIMA — Egyptian Chemical Industries | C37: State-owned (Egyptian state via Ministry of Public Business Sector) | D37: Aswan, Upper Egypt | E37: Ammonium nitrate, nitric acid, some ammonia | F37: 120 | G37: — | H37: 260 (AN) + nitric acid | I37: ~0.25 Mt AN + nitric acid (est.) | J37: Mainly domestic; limited EU export | K37: AN ~0.30 tCO₂/t (direct); older plant using hydro power for electrolysis historically | L37: Egypt's oldest nitrogen fertiliser company. Located at Aswan High Dam — historically used low-cost hydropower for nitrogen fixation. Now NG-based. CBAM: ammonium nitrate (CN 31023090) in scope. Nitric acid (CN 28080000) also CBAM-eligible. Limited EU export; mainly domestic agricultural use.
A38: 6 | B38: HELWAN FERTILIZERS Co. | C38: Egyptian state (Metallurgical Industries Holding) | D38: Helwan, South Cairo | E38: Ammonium nitrate, nitric acid | F38: 150 | G38: — | H38: 200 (AN) | I38: ~0.18 Mt AN (est.) | J38: Mainly domestic | K38: AN ~0.30 tCO₂/t | L38: Part of military-affiliated industrial group. Domestic market focus. CBAM exposure minimal.
A39: 7 | B39: Alexandria Fertilizers (ALEXFERT) | C39: OCI NV (Netherlands) majority shareholder | D39: Alexandria | E39: Ammonia, granular urea | F39: 300 | G39: 500 | H39: — | I39: ~0.45 Mt urea (est.) | J39: ~35% EU | K39: NH₃ ~1.3 tCO₂/t; Urea ~1.4 tCO₂/t | L39: OCI-operated plant (OCI is listed Amsterdam). NG-based, modern. OCI has MRV capability given EU parent company obligations.
A40: 8 | B40: Ain Al Sokhna Phosphatic Fertilizer (NCIC) | C40: National Services Products Organisation (Military) | D40: Ain Al Sokhna, Suez | E40: Ammonia, urea, calcium ammonium nitrate (CAN) | F40: 440 | G40: 380 | H40: 300 (CAN) | I40: ~0.35 Mt urea + 0.30 Mt CAN (est.) | J40: ~15% EU / some Africa | K40: Multi-product; ~1.3–1.5 tCO₂/t urea | L40: Military-controlled. Commissioned 2019. Has ammonia, urea, and CAN (calcium ammonium nitrate). CAN (CN 31026000) is excluded from CBAM scope.
A42: SECTION D — Primary Aluminium (CBAM CN 76011000)
A43: # | B43: Facility | C43: Operator | D43: Location | E43: Technology | F43: Current capacity (kt/yr) | G43: 2024 output (kt/yr) | H43: EU export share | I43: CBAM intensity tCO₂/t (est.) | J43: EU default tCO₂/t | K43: Grid EF | L43: Notes / CBAM status
A44: 1 | B44: Egyptalum — Nag Hammadi smelter (existing) | C44: Egyptian Aluminium Co. (EGAL / Egyptalum); parent: Metallurgical Industries Holding (MIH), state-owned | D44: Nag Hammadi, Qena governorate, Upper Egypt | E44: Hall-Héroult electrolysis (prebaked anodes); anode plant on-site; cast house | F44: 320 | G44: 285 | H44: ~60% of output exported to EU (per company statements) | I44: ~1.8–2.1 tCO₂/t direct (anode + process); S2 excluded per CBAM Annex II | J44: ~1.87 tCO₂/t (India default level; Egypt not separately listed — use 'other countries and territories' ~2.0 estimate) | K44: 0.51 tCO₂/MWh (declining toward 0.40 by 2035) | L44: Egypt's only primary aluminium producer. Largest in North Africa. Nile grid historically (Upper Egypt); 2026 solar PPA (Obelisk/Scatec 500MW) will progressively lower S2 intensity. CBAM exposure: direct emissions only (Annex II); S2 is NOT in CBAM scope for aluminium. May 2026: term sheet signed with Trafigura for +300kt expansion (NewCo JV, $750–900m capex). Expansion targeted at ~2028–2030 commissioning. Expansion will include new 150kt/yr anode plant. EU export share of ~60% is highly significant — this facility is the key Egyptian CBAM aluminium exposure. CBAM obligation 2030 est. (at current intensity, 48.5% factor, €115/t ETS): ~(1.9 − 1.423×0.515) × 115 × 1.10 ≈ USD 155/t direct CBAM cost per exported tonne.
A45: 2 | B45: Egyptalum — proposed expansion (NewCo with Trafigura) | C45: NewCo: Trafigura (minority equity) + Egyptalum + MIH (term sheet May 2026) | D45: Nag Hammadi, Qena governorate, Upper Egypt | E45: Hall-Héroult, new greenfield potline (prebaked, modern anode technology) | F45: 300 | G45: 0 | H45: Expected >60% EU export (Trafigura offtake) | I45: ~1.5–1.7 tCO₂/t (modern greenfield; lower anode consumption; solar power PPA) | J45: ~2.0 (until verified actuals available; default pathway until MRV established) | K45: Target: 0.20–0.30 tCO₂/MWh (dedicated solar + storage PPA) | L45: Not yet operational. Term sheet signed 6 May 2026. EBRD considering $80m loan for solar supply. If solar PPA (Scatec/Obelisk 500MW) fully serves NewCo, S2 intensity approaches zero. Direct emissions (anode + anode effect PFCs) will determine CBAM obligation. Modern prebaked technology targets low PFC emissions. CBAM obligation under solar scenario would be ~(1.5 × 0.515) − 1.423 × 0.515 ≈ near-zero at benchmark. Significant CBAM design consideration for offtake pricing with Trafigura.
B47: CBAM EXPOSURE SUMMARY — EGYPT: Steel: Egypt produces ~10 Mt crude steel, >95% via DRI-EAF route (natural gas Midrex/HYL). Dominant exporters: EZDK and Ezz Flat Steel (Ain Sokhna). EU export share ~15–20% of steel output. CBAM benchmark 0.481 tCO₂/t (DRI-EAF); Egypt's actual intensity ~1.5–1.8 tCO₂/t → material excess. At 2030 conditions (~USD 64/t cement; ~USD 68/t steel), steel CBAM cost is the largest fiscal item. Cement: Egypt has ~70 Mt/yr clinker capacity. Major exporters face CBAM on EU + Mediterranean exports. Turkey and Algeria compete for same EU cement market. Benchmark 0.666 tCO₂/t; Egypt actual ~0.78 tCO₂/t. Fertilisers: Abu Qir Fertilizers is the critical installation — ~50% of Egyptian N fertiliser output, ~40–50% EU-destined. December 2024 sustainability agreements signal active CBAM preparation. Urea benchmark 0.902 tCO₂/t; Egypt default ~1.404 tCO₂/t per IR 2025/2621 → USD ~43/t CBAM cost in 2026. Aluminium: Egyptalum is the sole primary producer. ~60% EU export; direct-only CBAM (Annex II). Benchmark 1.423 tCO₂/t direct; Egyptalum actual direct ~1.8–2.0 tCO₂/t. Planned Trafigura expansion (2028+) with solar power would dramatically lower intensity. Key policy lever: an Egyptian domestic carbon price at ~USD 94/t (optimal CP, 2030) would fully capture the CBAM gross obligation (~USD 376m across all sectors) as Egyptian fiscal revenue.

Sheet input_data
A1: CBAM input data — Pass 7
A2: 5 countries × 8 products × 12 years. All entries keyed by code = cty.dom.par.sec.prc.sub. Yellow cells are inputs; green = formulas.
A3: code | B3: cty | C3: dom | D3: par | E3: sec | F3: prc | G3: sub | H3: variable | I3: unit | J3: description | K3: source | L3: value | M3: 2024 | N3: 2025 | O3: 2026 | P3: 2027 | Q3: 2028 | R3: 2029 | S3: 2030 | T3: 2031 | U3: 2032 | V3: 2033 | W3: 2034 | X3: 2035
A5: 1. Universal time-series parameters
A6: all.in.ets.---.---.--- | B6: all | C6: in | D6: ets | E6: --- | F6: --- | G6: --- | H6: EU ETS allowance price | I6: EUR/tCO2 | J6: Consensus trajectory (consensus ~€126 by 2030). | K6: Analyst consensus | M6: 85 | N6: 90 | O6: 100 | P6: 105 | Q6: 110 | R6: 110 | S6: 115 | T6: 120 | U6: 125 | V6: 130 | W6: 135 | X6: 140
A7: all.in.cbf.---.---.--- | B7: all | C7: in | D7: cbf | E7: --- | F7: --- | G7: --- | H7: CBAM factor (1 − free alloc remaining) | I7: fraction | J7: EU Reg 2025/2620: phase-in 2026→2034. | K7: EU Reg 2025/2620 | M7: 0 | N7: 0 | O7: 0.025 | P7: 0.05 | Q7: 0.1 | R7: 0.225 | S7: 0.485 | T7: 0.61 | U7: 0.735 | V7: 0.86 | W7: 1 | X7: 1
A8: all.in.act.---.---.--- | B8: all | C8: in | D8: act | E8: --- | F8: --- | G8: --- | H8: Active flag (CBAM definitive) | I8: 0/1 | J8: 0 for 2024-25 (reporting only), 1 from 2026. | M8: 0 | N8: 0 | O8: 1 | P8: 1 | Q8: 1 | R8: 1 | S8: 1 | T8: 1 | U8: 1 | V8: 1 | W8: 1 | X8: 1
A9: all.in.fxr.---.---.--- | B9: all | C9: in | D9: fxr | E9: --- | F9: --- | G9: --- | H9: FX rate USD per EUR | I9: USD/EUR | J9: EUR ETS → USD conversion. | M9: 1.1 | N9: 1.1 | O9: 1.1 | P9: 1.1 | Q9: 1.1 | R9: 1.1 | S9: 1.1 | T9: 1.1 | U9: 1.1 | V9: 1.1 | W9: 1.1 | X9: 1.1
A11: 2. Fuel emission factors (kgCO₂/GJ, IPCC 2006 stationary combustion)
A12: all.in.eff.---.---.coa | B12: all | C12: in | D12: eff | E12: --- | F12: --- | G12: coa | H12: Fuel EF — Coal | I12: kgCO2/GJ | J12: IPCC 2006 default for coal. | K12: IPCC 2006 Vol.2 Ch.2 | L12: 96.1
A13: all.in.eff.---.---.nga | B13: all | C13: in | D13: eff | E13: --- | F13: --- | G13: nga | H13: Fuel EF — Natural gas | I13: kgCO2/GJ | J13: IPCC 2006 default for natural gas. | K13: IPCC 2006 Vol.2 Ch.2 | L13: 56.1
A14: all.in.eff.---.---.gso | B14: all | C14: in | D14: eff | E14: --- | F14: --- | G14: gso | H14: Fuel EF — Gasoline | I14: kgCO2/GJ | J14: IPCC 2006 default for gasoline. | K14: IPCC 2006 Vol.2 Ch.2 | L14: 69.3
A15: all.in.eff.---.---.die | B15: all | C15: in | D15: eff | E15: --- | F15: --- | G15: die | H15: Fuel EF — Diesel | I15: kgCO2/GJ | J15: IPCC 2006 default for diesel. | K15: IPCC 2006 Vol.2 Ch.2 | L15: 74.1
A16: all.in.eff.---.---.ker | B16: all | C16: in | D16: eff | E16: --- | F16: --- | G16: ker | H16: Fuel EF — Kerosene | I16: kgCO2/GJ | J16: IPCC 2006 default for kerosene. | K16: IPCC 2006 Vol.2 Ch.2 | L16: 71.9
A17: all.in.eff.---.---.lpg | B17: all | C17: in | D17: eff | E17: --- | F17: --- | G17: lpg | H17: Fuel EF — LPG | I17: kgCO2/GJ | J17: IPCC 2006 default for lpg. | K17: IPCC 2006 Vol.2 Ch.2 | L17: 63.1
A18: all.in.eff.---.---.bio | B18: all | C18: in | D18: eff | E18: --- | F18: --- | G18: bio | H18: Fuel EF — Biomass | I18: kgCO2/GJ | J18: IPCC 2006 default for biomass. | K18: IPCC 2006 Vol.2 Ch.2 | L18: 0
A19: all.in.eff.---.---.ren | B19: all | C19: in | D19: eff | E19: --- | F19: --- | G19: ren | H19: Fuel EF — Self-gen renewables | I19: kgCO2/GJ | J19: IPCC 2006 default for self-gen renewables. | K19: IPCC 2006 Vol.2 Ch.2 | L19: 0
A21: 3. Entity-level constants — benchmark, EU default value, product price, CBAM S2 scope, NH3 chain factor
A22: all.in.bnk.stl.drg.--- | B22: all | C22: in | D22: bnk | E22: stl | F22: drg | G22: --- | H22: CBAM benchmark — DRI-EAF steel | I22: tCO2/t | J22: Final CBAM benchmark (column B, default-value pathway). | K22: EU Reg 2025/2621 (final, 16 Dec 2025) | L22: 0.481
A23: all.in.dfv.stl.drg.--- | B23: all | C23: in | D23: dfv | E23: stl | F23: drg | G23: --- | H23: EU default intensity — DRI-EAF steel | I23: tCO2/t | J23: EU default intensity (~20% above benchmark). | K23: EU Reg 2025/2621 (final, 16 Dec 2025) | L23: 0.5772
A24: all.in.ppx.stl.drg.--- | B24: all | C24: in | D24: ppx | E24: stl | F24: drg | G24: --- | H24: Product price — DRI-EAF steel | I24: USD/t | J24: Pre-policy reference price. | K24: Market data | L24: 750
A25: all.in.cs2.stl.drg.--- | B25: all | C25: in | D25: cs2 | E25: stl | F25: drg | G25: --- | H25: CBAM S2 in scope — DRI-EAF steel | I25: 0/1 | J25: 1 = CBAM covers indirect (S2). 0 = Annex II direct only. | K25: EU Reg 2023/956 Annex II | L25: 0
A26: all.in.nh3.stl.drg.--- | B26: all | C26: in | D26: nh3 | E26: stl | F26: drg | G26: --- | H26: NH₃ feedstock factor — DRI-EAF steel | I26: t NH3/t product | J26: Tonnes ammonia feedstock per tonne of downstream product (urea, AN). 0 otherwise. | K26: IFA / IPCC | L26: 0
A27: all.in.bnk.stl.scr.--- | B27: all | C27: in | D27: bnk | E27: stl | F27: scr | G27: --- | H27: CBAM benchmark — Scrap-EAF steel | I27: tCO2/t | J27: Final CBAM benchmark (column B, default-value pathway). | K27: EU Reg 2025/2621 (final, 16 Dec 2025) | L27: 0.072
A28: all.in.dfv.stl.scr.--- | B28: all | C28: in | D28: dfv | E28: stl | F28: scr | G28: --- | H28: EU default intensity — Scrap-EAF steel | I28: tCO2/t | J28: EU default intensity (~20% above benchmark). | K28: EU Reg 2025/2621 (final, 16 Dec 2025) | L28: 0.0864
A29: all.in.ppx.stl.scr.--- | B29: all | C29: in | D29: ppx | E29: stl | F29: scr | G29: --- | H29: Product price — Scrap-EAF steel | I29: USD/t | J29: Pre-policy reference price. | K29: Market data | L29: 680
A30: all.in.cs2.stl.scr.--- | B30: all | C30: in | D30: cs2 | E30: stl | F30: scr | G30: --- | H30: CBAM S2 in scope — Scrap-EAF steel | I30: 0/1 | J30: 1 = CBAM covers indirect (S2). 0 = Annex II direct only. | K30: EU Reg 2023/956 Annex II | L30: 0
A31: all.in.nh3.stl.scr.--- | B31: all | C31: in | D31: nh3 | E31: stl | F31: scr | G31: --- | H31: NH₃ feedstock factor — Scrap-EAF steel | I31: t NH3/t product | J31: Tonnes ammonia feedstock per tonne of downstream product (urea, AN). 0 otherwise. | K31: IFA / IPCC | L31: 0
A32: all.in.bnk.stl.bof.--- | B32: all | C32: in | D32: bnk | E32: stl | F32: bof | G32: --- | H32: CBAM benchmark — BF-BOF steel | I32: tCO2/t | J32: Final CBAM benchmark (column B, default-value pathway). | K32: EU Reg 2025/2621 (final, 16 Dec 2025) | L32: 1.37
A33: all.in.dfv.stl.bof.--- | B33: all | C33: in | D33: dfv | E33: stl | F33: bof | G33: --- | H33: EU default intensity — BF-BOF steel | I33: tCO2/t | J33: EU default intensity (~20% above benchmark). | K33: EU Reg 2025/2621 (final, 16 Dec 2025) | L33: 1.644
... A61: all.in.nh3.alu.prp.--- | B61: all | C61: in | D61: nh3 | E61: alu | F61: prp | G61: --- | H61: NH₃ feedstock factor — Primary aluminium | I61: t NH3/t product | J61: Tonnes ammonia feedstock per tonne of downstream product (urea, AN). 0 otherwise. | K61: IFA / IPCC | L61: 0
A63: 4. MRV flags per product (global — applies to all countries)
A64: all.in.mrv.stl.drg.--- | B64: all | C64: in | D64: mrv | E64: stl | F64: drg | G64: --- | H64: MRV flag — DRI-EAF steel | I64: 0/1 | J64: 1 = exporter MRV done (EU uses actual). 0 = EU uses default value. Edit on dashboard. | K64: Policy choice | L64: =dashboard!B19 -> 1
A65: all.in.mrv.stl.scr.--- | B65: all | C65: in | D65: mrv | E65: stl | F65: scr | G65: --- | H65: MRV flag — Scrap-EAF steel | I65: 0/1 | J65: 1 = exporter MRV done (EU uses actual). 0 = EU uses default value. Edit on dashboard. | K65: Policy choice | L65: =dashboard!C19 -> 1
A66: all.in.mrv.stl.bof.--- | B66: all | C66: in | D66: mrv | E66: stl | F66: bof | G66: --- | H66: MRV flag — BF-BOF steel | I66: 0/1 | J66: 1 = exporter MRV done (EU uses actual). 0 = EU uses default value. Edit on dashboard. | K66: Policy choice | L66: =dashboard!D19 -> 1
A67: all.in.mrv.cmt.dry.--- | B67: all | C67: in | D67: mrv | E67: cmt | F67: dry | G67: --- | H67: MRV flag — Cement | I67: 0/1 | J67: 1 = exporter MRV done (EU uses actual). 0 = EU uses default value. Edit on dashboard. | K67: Policy choice | L67: =dashboard!E19 -> 1
A68: all.in.mrv.frt.amc.--- | B68: all | C68: in | D68: mrv | E68: frt | F68: amc | G68: --- | H68: MRV flag — Ammonia | I68: 0/1 | J68: 1 = exporter MRV done (EU uses actual). 0 = EU uses default value. Edit on dashboard. | K68: Policy choice | L68: =dashboard!F19 -> 1
A69: all.in.mrv.frt.ure.--- | B69: all | C69: in | D69: mrv | E69: frt | F69: ure | G69: --- | H69: MRV flag — Urea | I69: 0/1 | J69: 1 = exporter MRV done (EU uses actual). 0 = EU uses default value. Edit on dashboard. | K69: Policy choice | L69: =dashboard!G19 -> 1
A70: all.in.mrv.frt.nit.--- | B70: all | C70: in | D70: mrv | E70: frt | F70: nit | G70: --- | H70: MRV flag — Ammonium nitrate | I70: 0/1 | J70: 1 = exporter MRV done (EU uses actual). 0 = EU uses default value. Edit on dashboard. | K70: Policy choice | L70: =dashboard!H19 -> 1
A71: all.in.mrv.alu.prp.--- | B71: all | C71: in | D71: mrv | E71: alu | F71: prp | G71: --- | H71: MRV flag — Primary aluminium | I71: 0/1 | J71: 1 = exporter MRV done (EU uses actual). 0 = EU uses default value. Edit on dashboard. | K71: Policy choice | L71: =dashboard!I19 -> 1
A73: 5. Country-level constants (GDP growth, grid EF)
A74: egy.in.grw.---.---.--- | B74: egy | C74: in | D74: grw | E74: --- | F74: --- | G74: --- | H74: Egypt GDP growth rate | I74: frac/yr | J74: Annual real GDP growth. | K74: IMF WEO 2024 | L74: 0.055
A75: egy.in.gef.---.---.--- | B75: egy | C75: in | D75: gef | E75: --- | F75: --- | G75: --- | H75: Egypt grid emission factor | I75: tCO2/MWh | J75: Grid emission factor, declining trajectory per NDC commitments. 2024 anchor → 2035 end-point. | K75: IEA + national NDCs (linear interpolation) | M75: 0.51 | N75: 0.5 | O75: 0.49 | P75: 0.48 | Q75: 0.47 | R75: 0.46 | S75: 0.45 | T75: 0.44 | U75: 0.43 | V75: 0.42 | W75: 0.41 | X75: 0.4
A76: alb.in.grw.---.---.--- | B76: alb | C76: in | D76: grw | E76: --- | F76: --- | G76: --- | H76: Albania GDP growth rate | I76: frac/yr | J76: Annual real GDP growth. | K76: IMF WEO 2024 | L76: 0.038
A77: alb.in.gef.---.---.--- | B77: alb | C77: in | D77: gef | E77: --- | F77: --- | G77: --- | H77: Albania grid emission factor | I77: tCO2/MWh | J77: Grid emission factor, declining trajectory per NDC commitments. 2024 anchor → 2035 end-point. | K77: IEA + national NDCs (linear interpolation) | M77: 0.045 | N77: 0.0441 | O77: 0.0432 | P77: 0.0423 | Q77: 0.0414 | R77: 0.0405 | S77: 0.0395 | T77: 0.0386 | U77: 0.0377 | V77: 0.0368 | W77: 0.0359 | X77: 0.035
A78: uzb.in.grw.---.---.--- | B78: uzb | C78: in | D78: grw | E78: --- | F78: --- | G78: --- | H78: Uzbekistan GDP growth rate | I78: frac/yr | J78: Annual real GDP growth. | K78: IMF WEO 2024 | L78: 0.055
A79: uzb.in.gef.---.---.--- | B79: uzb | C79: in | D79: gef | E79: --- | F79: --- | G79: --- | H79: Uzbekistan grid emission factor | I79: tCO2/MWh | J79: Grid emission factor, declining trajectory per NDC commitments. 2024 anchor → 2035 end-point. | K79: IEA + national NDCs (linear interpolation) | M79: 0.54 | N79: 0.5291 | O79: 0.5182 | P79: 0.5073 | Q79: 0.4964 | R79: 0.4855 | S79: 0.4745 | T79: 0.4636 | U79: 0.4527 | V79: 0.4418 | W79: 0.4309 | X79: 0.42
A80: aze.in.grw.---.---.--- | B80: aze | C80: in | D80: grw | E80: --- | F80: --- | G80: --- | H80: Azerbaijan GDP growth rate | I80: frac/yr | J80: Annual real GDP growth. | K80: IMF WEO 2024 | L80: 0.025
A81: aze.in.gef.---.---.--- | B81: aze | C81: in | D81: gef | E81: --- | F81: --- | G81: --- | H81: Azerbaijan grid emission factor | I81: tCO2/MWh | J81: Grid emission factor, declining trajectory per NDC commitments. 2024 anchor → 2035 end-point. | K81: IEA + national NDCs (linear interpolation) | M81: 0.46 | N81: 0.4518 | O81: 0.4436 | P81: 0.4355 | Q81: 0.4273 | R81: 0.4191 | S81: 0.4109 | T81: 0.4027 | U81: 0.3945 | V81: 0.3864 | W81: 0.3782 | X81: 0.37
A82: ind.in.grw.---.---.--- | B82: ind | C82: in | D82: grw | E82: --- | F82: --- | G82: --- | H82: India GDP growth rate | I82: frac/yr | J82: Annual real GDP growth. | K82: IMF WEO 2024 | L82: 0.063
A83: ind.in.gef.---.---.--- | B83: ind | C83: in | D83: gef | E83: --- | F83: --- | G83: --- | H83: India grid emission factor | I83: tCO2/MWh | J83: Grid emission factor, declining trajectory per NDC commitments. 2024 anchor → 2035 end-point. | K83: IEA + national NDCs (linear interpolation) | M83: 0.713 | N83: 0.6936 | O83: 0.6743 | P83: 0.6549 | Q83: 0.6355 | R83: 0.6162 | S83: 0.5968 | T83: 0.5775 | U83: 0.5581 | V83: 0.5387 | W83: 0.5194 | X83: 0.5
A85: 6.egy. Egypt — country-specific inputs by entity
A86: egy.in.prb.stl.drg.--- | B86: egy | C86: in | D86: prb | E86: stl | F86: drg | G86: --- | H86: Egypt DRI-EAF steel — base production | I86: Mt | J86: Base year 2024 production of dri-eaf steel. | K86: Worldsteel / industry data | L86: 5.1
A87: egy.in.els.stl.drg.--- | B87: egy | C87: in | D87: els | E87: stl | F87: drg | G87: --- | H87: Egypt DRI-EAF steel — elasticity | I87: pct/pct | J87: Production growth per unit GDP growth. | L87: 1
A88: egy.in.ext.stl.drg.--- | B88: egy | C88: in | D88: ext | E88: stl | F88: drg | G88: --- | H88: Egypt DRI-EAF steel — export share total | I88: frac | J88: Production exported (any destination). | L88: 0.4
A89: egy.in.exe.stl.drg.--- | B89: egy | C89: in | D89: exe | E89: stl | F89: drg | G89: --- | H89: Egypt DRI-EAF steel — EU export share | I89: frac | J89: Share of production exported to EU. | L89: 0.18
A90: egy.in.imp.stl.drg.--- | B90: egy | C90: in | D90: imp | E90: stl | F90: drg | G90: --- | H90: Egypt DRI-EAF steel — import share | I90: frac | J90: Imports as share of (production − exports). | L90: 0.05
A91: egy.in.enc.stl.drg.coa | B91: egy | C91: in | D91: enc | E91: stl | F91: drg | G91: coa | H91: Egypt DRI-EAF steel — Coal (cmb) | I91: GJ/t | J91: Combustion intensity for coal. | K91: IEA/IRENA | L91: 0
A92: egy.in.enc.stl.drg.nga | B92: egy | C92: in | D92: enc | E92: stl | F92: drg | G92: nga | H92: Egypt DRI-EAF steel — Natural gas (cmb) | I92: GJ/t | J92: Combustion intensity for natural gas. | K92: IEA/IRENA | L92: 5
A93: egy.in.enc.stl.drg.gso | B93: egy | C93: in | D93: enc | E93: stl | F93: drg | G93: gso | H93: Egypt DRI-EAF steel — Gasoline (cmb) | I93: GJ/t | J93: Combustion intensity for gasoline. | K93: IEA/IRENA | L93: 0
A94: egy.in.enc.stl.drg.die | B94: egy | C94: in | D94: enc | E94: stl | F94: drg | G94: die | H94: Egypt DRI-EAF steel — Diesel (cmb) | I94: GJ/t | J94: Combustion intensity for diesel. | K94: IEA/IRENA | L94: 0.5
A95: egy.in.enc.stl.drg.ker | B95: egy | C95: in | D95: enc | E95: stl | F95: drg | G95: ker | H95: Egypt DRI-EAF steel — Kerosene (cmb) | I95: GJ/t | J95: Combustion intensity for kerosene. | K95: IEA/IRENA | L95: 0
A96: egy.in.enc.stl.drg.lpg | B96: egy | C96: in | D96: enc | E96: stl | F96: drg | G96: lpg | H96: Egypt DRI-EAF steel — LPG (cmb) | I96: GJ/t | J96: Combustion intensity for lpg. | K96: IEA/IRENA | L96: 0
A97: egy.in.enc.stl.drg.bio | B97: egy | C97: in | D97: enc | E97: stl | F97: drg | G97: bio | H97: Egypt DRI-EAF steel — Biomass (cmb) | I97: GJ/t | J97: Combustion intensity for biomass. | K97: IEA/IRENA | L97: 0
A98: egy.in.enc.stl.drg.ren | B98: egy | C98: in | D98: enc | E98: stl | F98: drg | G98: ren | H98: Egypt DRI-EAF steel — Self-gen renewables (cmb) | I98: GJ/t | J98: Combustion intensity for self-gen renewables. | K98: IEA/IRENA | L98: 0
A99: egy.in.enp.stl.drg.coa | B99: egy | C99: in | D99: enp | E99: stl | F99: drg | G99: coa | H99: Egypt DRI-EAF steel — Coal (prc) | I99: GJ/t | J99: Process/reductant intensity for coal. | K99: IEA/IRENA | L99: 0
A100: egy.in.enp.stl.drg.nga | B100: egy | C100: in | D100: enp | E100: stl | F100: drg | G100: nga | H100: Egypt DRI-EAF steel — Natural gas (prc) | I100: GJ/t | J100: Process/reductant intensity for natural gas. | K100: IEA/IRENA | L100: 24
A101: egy.in.enp.stl.drg.gso | B101: egy | C101: in | D101: enp | E101: stl | F101: drg | G101: gso | H101: Egypt DRI-EAF steel — Gasoline (prc) | I101: GJ/t | J101: Process/reductant intensity for gasoline. | K101: IEA/IRENA | L101: 0
A102: egy.in.enp.stl.drg.die | B102: egy | C102: in | D102: enp | E102: stl | F102: drg | G102: die | H102: Egypt DRI-EAF steel — Diesel (prc) | I102: GJ/t | J102: Process/reductant intensity for diesel. | K102: IEA/IRENA | L102: 0
... A106: egy.in.enp.stl.drg.ren | B106: egy | C106: in | D106: enp | E106: stl | F106: drg | G106: ren | H106: Egypt DRI-EAF steel — Self-gen renewables (prc) | I106: GJ/t | J106: Process/reductant intensity for self-gen renewables. | K106: IEA/IRENA | L106: 0
A107: egy.in.ele.stl.drg.elc | B107: egy | C107: in | D107: ele | E107: stl | F107: drg | G107: elc | H107: Egypt DRI-EAF steel — electricity | I107: GJ/t | J107: Grid electricity intensity. | L107: 2.5
A108: egy.in.efn.stl.drg.--- | B108: egy | C108: in | D108: efn | E108: stl | F108: drg | G108: --- | H108: Egypt DRI-EAF steel — non-fuel process EF | I108: tCO2/t | J108: Direct non-fuel process emissions per tonne of product. Negative for urea (CO2 uptake from atmosphere as feedstock). | K108: IPCC 2006 | L108: 0
A109: egy.in.efo.stl.drg.--- | B109: egy | C109: in | D109: efo | E109: stl | F109: drg | G109: --- | H109: Egypt DRI-EAF steel — non-CO₂ GHG EF | I109: tCO2e/t | J109: Non-CO2 GHG emissions per tonne of product (N2O, PFCs). | K109: IPCC 2006 | L109: 0
A110: egy.in.prb.stl.scr.--- | B110: egy | C110: in | D110: prb | E110: stl | F110: scr | G110: --- | H110: Egypt Scrap-EAF steel — base production | I110: Mt | J110: Base year 2024 production of scrap-eaf steel. | K110: Worldsteel / industry data | L110: 4.58
A111: egy.in.els.stl.scr.--- | B111: egy | C111: in | D111: els | E111: stl | F111: scr | G111: --- | H111: Egypt Scrap-EAF steel — elasticity | I111: pct/pct | J111: Production growth per unit GDP growth. | L111: 0.8
A112: egy.in.ext.stl.scr.--- | B112: egy | C112: in | D112: ext | E112: stl | F112: scr | G112: --- | H112: Egypt Scrap-EAF steel — export share total | I112: frac | J112: Production exported (any destination). | L112: 0.3
A113: egy.in.exe.stl.scr.--- | B113: egy | C113: in | D113: exe | E113: stl | F113: scr | G113: --- | H113: Egypt Scrap-EAF steel — EU export share | I113: frac | J113: Share of production exported to EU. | L113: 0.1
A114: egy.in.imp.stl.scr.--- | B114: egy | C114: in | D114: imp | E114: stl | F114: scr | G114: --- | H114: Egypt Scrap-EAF steel — import share | I114: frac | J114: Imports as share of (production − exports). | L114: 0.1
A115: egy.in.enc.stl.scr.coa | B115: egy | C115: in | D115: enc | E115: stl | F115: scr | G115: coa | H115: Egypt Scrap-EAF steel — Coal (cmb) | I115: GJ/t | J115: Combustion intensity for coal. | K115: IEA/IRENA | L115: 0
A116: egy.in.enc.stl.scr.nga | B116: egy | C116: in | D116: enc | E116: stl | F116: scr | G116: nga | H116: Egypt Scrap-EAF steel — Natural gas (cmb) | I116: GJ/t | J116: Combustion intensity for natural gas. | K116: IEA/IRENA | L116: 2.5
A117: egy.in.enc.stl.scr.gso | B117: egy | C117: in | D117: enc | E117: stl | F117: scr | G117: gso | H117: Egypt Scrap-EAF steel — Gasoline (cmb) | I117: GJ/t | J117: Combustion intensity for gasoline. | K117: IEA/IRENA | L117: 0
A118: egy.in.enc.stl.scr.die | B118: egy | C118: in | D118: enc | E118: stl | F118: scr | G118: die | H118: Egypt Scrap-EAF steel — Diesel (cmb) | I118: GJ/t | J118: Combustion intensity for diesel. | K118: IEA/IRENA | L118: 0.2
A119: egy.in.enc.stl.scr.ker | B119: egy | C119: in | D119: enc | E119: stl | F119: scr | G119: ker | H119: Egypt Scrap-EAF steel — Kerosene (cmb) | I119: GJ/t | J119: Combustion intensity for kerosene. | K119: IEA/IRENA | L119: 0
A120: egy.in.enc.stl.scr.lpg | B120: egy | C120: in | D120: enc | E120: stl | F120: scr | G120: lpg | H120: Egypt Scrap-EAF steel — LPG (cmb) | I120: GJ/t | J120: Combustion intensity for lpg. | K120: IEA/IRENA | L120: 0
A121: egy.in.enc.stl.scr.bio | B121: egy | C121: in | D121: enc | E121: stl | F121: scr | G121: bio | H121: Egypt Scrap-EAF steel — Biomass (cmb) | I121: GJ/t | J121: Combustion intensity for biomass. | K121: IEA/IRENA | L121: 0
A122: egy.in.enc.stl.scr.ren | B122: egy | C122: in | D122: enc | E122: stl | F122: scr | G122: ren | H122: Egypt Scrap-EAF steel — Self-gen renewables (cmb) | I122: GJ/t | J122: Combustion intensity for self-gen renewables. | K122: IEA/IRENA | L122: 0
A123: egy.in.enp.stl.scr.coa | B123: egy | C123: in | D123: enp | E123: stl | F123: scr | G123: coa | H123: Egypt Scrap-EAF steel — Coal (prc) | I123: GJ/t | J123: Process/reductant intensity for coal. | K123: IEA/IRENA | L123: 0
A124: egy.in.enp.stl.scr.nga | B124: egy | C124: in | D124: enp | E124: stl | F124: scr | G124: nga | H124: Egypt Scrap-EAF steel — Natural gas (prc) | I124: GJ/t | J124: Process/reductant intensity for natural gas. | K124: IEA/IRENA | L124: 0
A125: egy.in.enp.stl.scr.gso | B125: egy | C125: in | D125: enp | E125: stl | F125: scr | G125: gso | H125: Egypt Scrap-EAF steel — Gasoline (prc) | I125: GJ/t | J125: Process/reductant intensity for gasoline. | K125: IEA/IRENA | L125: 0
A126: egy.in.enp.stl.scr.die | B126: egy | C126: in | D126: enp | E126: stl | F126: scr | G126: die | H126: Egypt Scrap-EAF steel — Diesel (prc) | I126: GJ/t | J126: Process/reductant intensity for diesel. | K126: IEA/IRENA | L126: 0
... A130: egy.in.enp.stl.scr.ren | B130: egy | C130: in | D130: enp | E130: stl | F130: scr | G130: ren | H130: Egypt Scrap-EAF steel — Self-gen renewables (prc) | I130: GJ/t | J130: Process/reductant intensity for self-gen renewables. | K130: IEA/IRENA | L130: 0
A131: egy.in.ele.stl.scr.elc | B131: egy | C131: in | D131: ele | E131: stl | F131: scr | G131: elc | H131: Egypt Scrap-EAF steel — electricity | I131: GJ/t | J131: Grid electricity intensity. | L131: 4.5
A132: egy.in.efn.stl.scr.--- | B132: egy | C132: in | D132: efn | E132: stl | F132: scr | G132: --- | H132: Egypt Scrap-EAF steel — non-fuel process EF | I132: tCO2/t | J132: Direct non-fuel process emissions per tonne of product. Negative for urea (CO2 uptake from atmosphere as feedstock). | K132: IPCC 2006 | L132: 0
A133: egy.in.efo.stl.scr.--- | B133: egy | C133: in | D133: efo | E133: stl | F133: scr | G133: --- | H133: Egypt Scrap-EAF steel — non-CO₂ GHG EF | I133: tCO2e/t | J133: Non-CO2 GHG emissions per tonne of product (N2O, PFCs). | K133: IPCC 2006 | L133: 0
A134: egy.in.prb.stl.bof.--- | B134: egy | C134: in | D134: prb | E134: stl | F134: bof | G134: --- | H134: Egypt BF-BOF steel — base production | I134: Mt | J134: Base year 2024 production of bf-bof steel. | K134: Worldsteel / industry data | L134: 0
A135: egy.in.els.stl.bof.--- | B135: egy | C135: in | D135: els | E135: stl | F135: bof | G135: --- | H135: Egypt BF-BOF steel — elasticity | I135: pct/pct | J135: Production growth per unit GDP growth. | L135: 1
A136: egy.in.ext.stl.bof.--- | B136: egy | C136: in | D136: ext | E136: stl | F136: bof | G136: --- | H136: Egypt BF-BOF steel — export share total | I136: frac | J136: Production exported (any destination). | L136: 0.2
A137: egy.in.exe.stl.bof.--- | B137: egy | C137: in | D137: exe | E137: stl | F137: bof | G137: --- | H137: Egypt BF-BOF steel — EU export share | I137: frac | J137: Share of production exported to EU. | L137: 0.1
A138: egy.in.imp.stl.bof.--- | B138: egy | C138: in | D138: imp | E138: stl | F138: bof | G138: --- | H138: Egypt BF-BOF steel — import share | I138: frac | J138: Imports as share of (production − exports). | L138: 0.05
A139: egy.in.enc.stl.bof.coa | B139: egy | C139: in | D139: enc | E139: stl | F139: bof | G139: coa | H139: Egypt BF-BOF steel — Coal (cmb) | I139: GJ/t | J139: Combustion intensity for coal. | K139: IEA/IRENA | L139: 4
...

Sheet calculations
A1: CBAM calculations — Pass 7
A2: Country pulled from dashboard!$B$5. All formulas resolve dynamically. Two intensities per entity: holistic (cradle-to-gate) and MRV (CBAM-eligible).
A3: code | B3: cty | C3: dom | D3: par | E3: sec | F3: prc | G3: sub | H3: variable | I3: unit | J3: description | M3: 2024 | N3: 2025 | O3: 2026 | P3: 2027 | Q3: 2028 | R3: 2029 | S3: 2030 | T3: 2031 | U3: 2032 | V3: 2033 | W3: 2034 | X3: 2035
A5: 1. GDP index (compound, base 2024 = 1.00)
A6: =dashboard!$B$5&".pj.grw.---.---.---" -> egy.pj.grw.---.---.--- | B6: =dashboard!$B$5 -> egy | C6: pj | D6: grw | E6: --- | F6: --- | G6: --- | H6: GDP growth rate (lookup) | I6: frac/yr | J6: Pulled from input_data based on selected country. | M6: =INDEX(input_data!$L:$L,MATCH(dashboard!$B$5&".in.grw.---.---.---",input_data!$A:$A,0)) -> 0.055 | N6: =INDEX(input_data!$L:$L,MATCH(dashboard!$B$5&".in.grw.---.---.---",input_data!$A:$A,0)) -> 0.055 | O6: =INDEX(input_data!$L:$L,MATCH(dashboard!$B$5&".in.grw.---.---.---",input_data!$A:$A,0)) -> 0.055 | P6: =INDEX(input_data!$L:$L,MATCH(dashboard!$B$5&".in.grw.---.---.---",input_data!$A:$A,0)) -> 0.055 | Q6: =INDEX(input_data!$L:$L,MATCH(dashboard!$B$5&".in.grw.---.---.---",input_data!$A:$A,0)) -> 0.055 | R6: =INDEX(input_data!$L:$L,MATCH(dashboard!$B$5&".in.grw.---.---.---",input_data!$A:$A,0)) -> 0.055 | S6: =INDEX(input_data!$L:$L,MATCH(dashboard!$B$5&".in.grw.---.---.---",input_data!$A:$A,0)) -> 0.055 | T6: =INDEX(input_data!$L:$L,MATCH(dashboard!$B$5&".in.grw.---.---.---",input_data!$A:$A,0)) -> 0.055 | ... X6: =INDEX(input_data!$L:$L,MATCH(dashboard!$B$5&".in.grw.---.---.---",input_data!$A:$A,0)) -> 0.055
A7: =dashboard!$B$5&".pj.idx.---.---.---" -> egy.pj.idx.---.---.--- | B7: =dashboard!$B$5 -> egy | C7: pj | D7: idx | E7: --- | F7: --- | G7: --- | H7: GDP index (cumulative, 2024 base) | I7: index | J7: Compounded from 2024 base year using growth rate. | M7: =1 -> 1 | N7: =M7*(1+N6) -> 1.055 | O7: =N7*(1+O6) -> 1.113025 | P7: =O7*(1+P6) -> 1.1742414 | Q7: =P7*(1+Q6) -> 1.2388247 | R7: =Q7*(1+R6) -> 1.30696 | S7: =R7*(1+S6) -> 1.3788428 | T7: =S7*(1+T6) -> 1.4546792 | U7: =T7*(1+U6) -> 1.5346865 | ... X7: =W7*(1+X6) -> 1.8020924
A9: 2. Fuel EF helper block (kgCO2/GJ, pulled from input_data)
A10: =dashboard!$B$5&".ef.eff.---.---.coa" -> egy.ef.eff.---.---.coa | B10: =dashboard!$B$5 -> egy | C10: ef | D10: eff | E10: --- | F10: --- | G10: coa | H10: Fuel EF — Coal | I10: kgCO2/GJ | J10: Pulled from input_data section 2. | M10: =INDEX(input_data!$L:$L,MATCH("all.in.eff.---.---.coa",input_data!$A:$A,0)) -> 96.1 | N10: =INDEX(input_data!$L:$L,MATCH("all.in.eff.---.---.coa",input_data!$A:$A,0)) -> 96.1 | O10: =INDEX(input_data!$L:$L,MATCH("all.in.eff.---.---.coa",input_data!$A:$A,0)) -> 96.1 | P10: =INDEX(input_data!$L:$L,MATCH("all.in.eff.---.---.coa",input_data!$A:$A,0)) -> 96.1 | Q10: =INDEX(input_data!$L:$L,MATCH("all.in.eff.---.---.coa",input_data!$A:$A,0)) -> 96.1 | R10: =INDEX(input_data!$L:$L,MATCH("all.in.eff.---.---.coa",input_data!$A:$A,0)) -> 96.1 | S10: =INDEX(input_data!$L:$L,MATCH("all.in.eff.---.---.coa",input_data!$A:$A,0)) -> 96.1 | T10: =INDEX(input_data!$L:$L,MATCH("all.in.eff.---.---.coa",input_data!$A:$A,0)) -> 96.1 | ... X10: =INDEX(input_data!$L:$L,MATCH("all.in.eff.---.---.coa",input_data!$A:$A,0)) -> 96.1
A11: =dashboard!$B$5&".ef.eff.---.---.nga" -> egy.ef.eff.---.---.nga | B11: =dashboard!$B$5 -> egy | C11: ef | D11: eff | E11: --- | F11: --- | G11: nga | H11: Fuel EF — Natural gas | I11: kgCO2/GJ | J11: Pulled from input_data section 2. | M11: =INDEX(input_data!$L:$L,MATCH("all.in.eff.---.---.nga",input_data!$A:$A,0)) -> 56.1 | N11: =INDEX(input_data!$L:$L,MATCH("all.in.eff.---.---.nga",input_data!$A:$A,0)) -> 56.1 | O11: =INDEX(input_data!$L:$L,MATCH("all.in.eff.---.---.nga",input_data!$A:$A,0)) -> 56.1 | P11: =INDEX(input_data!$L:$L,MATCH("all.in.eff.---.---.nga",input_data!$A:$A,0)) -> 56.1 | Q11: =INDEX(input_data!$L:$L,MATCH("all.in.eff.---.---.nga",input_data!$A:$A,0)) -> 56.1 | R11: =INDEX(input_data!$L:$L,MATCH("all.in.eff.---.---.nga",input_data!$A:$A,0)) -> 56.1 | S11: =INDEX(input_data!$L:$L,MATCH("all.in.eff.---.---.nga",input_data!$A:$A,0)) -> 56.1 | T11: =INDEX(input_data!$L:$L,MATCH("all.in.eff.---.---.nga",input_data!$A:$A,0)) -> 56.1 | ... X11: =INDEX(input_data!$L:$L,MATCH("all.in.eff.---.---.nga",input_data!$A:$A,0)) -> 56.1
A12: =dashboard!$B$5&".ef.eff.---.---.gso" -> egy.ef.eff.---.---.gso | B12: =dashboard!$B$5 -> egy | C12: ef | D12: eff | E12: --- | F12: --- | G12: gso | H12: Fuel EF — Gasoline | I12: kgCO2/GJ | J12: Pulled from input_data section 2. | M12: =INDEX(input_data!$L:$L,MATCH("all.in.eff.---.---.gso",input_data!$A:$A,0)) -> 69.3 | N12: =INDEX(input_data!$L:$L,MATCH("all.in.eff.---.---.gso",input_data!$A:$A,0)) -> 69.3 | O12: =INDEX(input_data!$L:$L,MATCH("all.in.eff.---.---.gso",input_data!$A:$A,0)) -> 69.3 | P12: =INDEX(input_data!$L:$L,MATCH("all.in.eff.---.---.gso",input_data!$A:$A,0)) -> 69.3 | Q12: =INDEX(input_data!$L:$L,MATCH("all.in.eff.---.---.gso",input_data!$A:$A,0)) -> 69.3 | R12: =INDEX(input_data!$L:$L,MATCH("all.in.eff.---.---.gso",input_data!$A:$A,0)) -> 69.3 | S12: =INDEX(input_data!$L:$L,MATCH("all.in.eff.---.---.gso",input_data!$A:$A,0)) -> 69.3 | T12: =INDEX(input_data!$L:$L,MATCH("all.in.eff.---.---.gso",input_data!$A:$A,0)) -> 69.3 | ... X12: =INDEX(input_data!$L:$L,MATCH("all.in.eff.---.---.gso",input_data!$A:$A,0)) -> 69.3
A13: =dashboard!$B$5&".ef.eff.---.---.die" -> egy.ef.eff.---.---.die | B13: =dashboard!$B$5 -> egy | C13: ef | D13: eff | E13: --- | F13: --- | G13: die | H13: Fuel EF — Diesel | I13: kgCO2/GJ | J13: Pulled from input_data section 2. | M13: =INDEX(input_data!$L:$L,MATCH("all.in.eff.---.---.die",input_data!$A:$A,0)) -> 74.1 | N13: =INDEX(input_data!$L:$L,MATCH("all.in.eff.---.---.die",input_data!$A:$A,0)) -> 74.1 | O13: =INDEX(input_data!$L:$L,MATCH("all.in.eff.---.---.die",input_data!$A:$A,0)) -> 74.1 | P13: =INDEX(input_data!$L:$L,MATCH("all.in.eff.---.---.die",input_data!$A:$A,0)) -> 74.1 | Q13: =INDEX(input_data!$L:$L,MATCH("all.in.eff.---.---.die",input_data!$A:$A,0)) -> 74.1 | R13: =INDEX(input_data!$L:$L,MATCH("all.in.eff.---.---.die",input_data!$A:$A,0)) -> 74.1 | S13: =INDEX(input_data!$L:$L,MATCH("all.in.eff.---.---.die",input_data!$A:$A,0)) -> 74.1 | T13: =INDEX(input_data!$L:$L,MATCH("all.in.eff.---.---.die",input_data!$A:$A,0)) -> 74.1 | ... X13: =INDEX(input_data!$L:$L,MATCH("all.in.eff.---.---.die",input_data!$A:$A,0)) -> 74.1
A14: =dashboard!$B$5&".ef.eff.---.---.ker" -> egy.ef.eff.---.---.ker | B14: =dashboard!$B$5 -> egy | C14: ef | D14: eff | E14: --- | F14: --- | G14: ker | H14: Fuel EF — Kerosene | I14: kgCO2/GJ | J14: Pulled from input_data section 2. | M14: =INDEX(input_data!$L:$L,MATCH("all.in.eff.---.---.ker",input_data!$A:$A,0)) -> 71.9 | N14: =INDEX(input_data!$L:$L,MATCH("all.in.eff.---.---.ker",input_data!$A:$A,0)) -> 71.9 | O14: =INDEX(input_data!$L:$L,MATCH("all.in.eff.---.---.ker",input_data!$A:$A,0)) -> 71.9 | P14: =INDEX(input_data!$L:$L,MATCH("all.in.eff.---.---.ker",input_data!$A:$A,0)) -> 71.9 | Q14: =INDEX(input_data!$L:$L,MATCH("all.in.eff.---.---.ker",input_data!$A:$A,0)) -> 71.9 | R14: =INDEX(input_data!$L:$L,MATCH("all.in.eff.---.---.ker",input_data!$A:$A,0)) -> 71.9 | S14: =INDEX(input_data!$L:$L,MATCH("all.in.eff.---.---.ker",input_data!$A:$A,0)) -> 71.9 | T14: =INDEX(input_data!$L:$L,MATCH("all.in.eff.---.---.ker",input_data!$A:$A,0)) -> 71.9 | ... X14: =INDEX(input_data!$L:$L,MATCH("all.in.eff.---.---.ker",input_data!$A:$A,0)) -> 71.9
A15: =dashboard!$B$5&".ef.eff.---.---.lpg" -> egy.ef.eff.---.---.lpg | B15: =dashboard!$B$5 -> egy | C15: ef | D15: eff | E15: --- | F15: --- | G15: lpg | H15: Fuel EF — LPG | I15: kgCO2/GJ | J15: Pulled from input_data section 2. | M15: =INDEX(input_data!$L:$L,MATCH("all.in.eff.---.---.lpg",input_data!$A:$A,0)) -> 63.1 | N15: =INDEX(input_data!$L:$L,MATCH("all.in.eff.---.---.lpg",input_data!$A:$A,0)) -> 63.1 | O15: =INDEX(input_data!$L:$L,MATCH("all.in.eff.---.---.lpg",input_data!$A:$A,0)) -> 63.1 | P15: =INDEX(input_data!$L:$L,MATCH("all.in.eff.---.---.lpg",input_data!$A:$A,0)) -> 63.1 | Q15: =INDEX(input_data!$L:$L,MATCH("all.in.eff.---.---.lpg",input_data!$A:$A,0)) -> 63.1 | R15: =INDEX(input_data!$L:$L,MATCH("all.in.eff.---.---.lpg",input_data!$A:$A,0)) -> 63.1 | S15: =INDEX(input_data!$L:$L,MATCH("all.in.eff.---.---.lpg",input_data!$A:$A,0)) -> 63.1 | T15: =INDEX(input_data!$L:$L,MATCH("all.in.eff.---.---.lpg",input_data!$A:$A,0)) -> 63.1 | ... X15: =INDEX(input_data!$L:$L,MATCH("all.in.eff.---.---.lpg",input_data!$A:$A,0)) -> 63.1
A16: =dashboard!$B$5&".ef.eff.---.---.bio" -> egy.ef.eff.---.---.bio | B16: =dashboard!$B$5 -> egy | C16: ef | D16: eff | E16: --- | F16: --- | G16: bio | H16: Fuel EF — Biomass | I16: kgCO2/GJ | J16: Pulled from input_data section 2. | M16: =INDEX(input_data!$L:$L,MATCH("all.in.eff.---.---.bio",input_data!$A:$A,0)) -> 0 | N16: =INDEX(input_data!$L:$L,MATCH("all.in.eff.---.---.bio",input_data!$A:$A,0)) -> 0 | O16: =INDEX(input_data!$L:$L,MATCH("all.in.eff.---.---.bio",input_data!$A:$A,0)) -> 0 | P16: =INDEX(input_data!$L:$L,MATCH("all.in.eff.---.---.bio",input_data!$A:$A,0)) -> 0 | Q16: =INDEX(input_data!$L:$L,MATCH("all.in.eff.---.---.bio",input_data!$A:$A,0)) -> 0 | R16: =INDEX(input_data!$L:$L,MATCH("all.in.eff.---.---.bio",input_data!$A:$A,0)) -> 0 | S16: =INDEX(input_data!$L:$L,MATCH("all.in.eff.---.---.bio",input_data!$A:$A,0)) -> 0 | T16: =INDEX(input_data!$L:$L,MATCH("all.in.eff.---.---.bio",input_data!$A:$A,0)) -> 0 | ... X16: =INDEX(input_data!$L:$L,MATCH("all.in.eff.---.---.bio",input_data!$A:$A,0)) -> 0
A17: =dashboard!$B$5&".ef.eff.---.---.ren" -> egy.ef.eff.---.---.ren | B17: =dashboard!$B$5 -> egy | C17: ef | D17: eff | E17: --- | F17: --- | G17: ren | H17: Fuel EF — Self-gen renewables | I17: kgCO2/GJ | J17: Pulled from input_data section 2. | M17: =INDEX(input_data!$L:$L,MATCH("all.in.eff.---.---.ren",input_data!$A:$A,0)) -> 0 | N17: =INDEX(input_data!$L:$L,MATCH("all.in.eff.---.---.ren",input_data!$A:$A,0)) -> 0 | O17: =INDEX(input_data!$L:$L,MATCH("all.in.eff.---.---.ren",input_data!$A:$A,0)) -> 0 | P17: =INDEX(input_data!$L:$L,MATCH("all.in.eff.---.---.ren",input_data!$A:$A,0)) -> 0 | Q17: =INDEX(input_data!$L:$L,MATCH("all.in.eff.---.---.ren",input_data!$A:$A,0)) -> 0 | R17: =INDEX(input_data!$L:$L,MATCH("all.in.eff.---.---.ren",input_data!$A:$A,0)) -> 0 | S17: =INDEX(input_data!$L:$L,MATCH("all.in.eff.---.---.ren",input_data!$A:$A,0)) -> 0 | T17: =INDEX(input_data!$L:$L,MATCH("all.in.eff.---.---.ren",input_data!$A:$A,0)) -> 0 | ... X17: =INDEX(input_data!$L:$L,MATCH("all.in.eff.---.---.ren",input_data!$A:$A,0)) -> 0
A19: 3.stl.drg. DRI-EAF steel — calculations
