Workbook

Sheet Dashboard
A1: CES Energy Demand Model with TECP
A2: Unified policy interface: same inputs drive both dynamic simulation and TECP
A4: POLICY INSTRUMENTS | D4: (Zero)
B5: Level | C5: Unit | D5: Intro year | E5: Target year
A6: Economy-wide carbon tax | B6: 50 | C6: $/tCO2 | D6: 2025 | E6: 2028
A7: Road Transport feebate | B7: 20 | C7: $/tCO2 | D7: 2026 | E7: 2030
A8: Electricity Gen. feebate | B8: 15 | C8: $/tCO2 | D8: 2026 | E8: 2030
A10: FUEL EXCISES ($/GJ) — by sector | D10: (Zero)
A11: Fuel | B11: RT excise ($/GJ) | C11: EG excise ($/GJ) | D11: Intro year | E11: Target year
A12: Coal | B12: 0 | C12: 0 | D12: 2025 | E12: 2028
A13: Natural gas | B13: 0 | C13: 0 | D13: 2025 | E13: 2028
A14: Gasoline | B14: 5 | C14: 0 | D14: 2025 | E14: 2028
A15: Diesel | B15: 4 | C15: 0 | D15: 2025 | E15: 2028
A16: Electricity | B16: 0 | C16: 0 | D16: 2025 | E16: 2028
A17: RE generation | B17: 0 | C17: 0 | D17: 2025 | E17: 2028
A19: COMPUTED POLICY TRAJECTORIES
B20: 2024 | C20: 2025 | D20: 2026 | E20: 2027 | F20: 2028 | G20: 2029 | H20: 2030 | I20: 2031 | J20: 2032 | K20: 2033 | L20: 2034 | M20: 2035
A21: Carbon tax ($/tCO2) | B21: =IF(2024<=$D$6,0,IF(2024>=$E$6,$B$6,$B$6*(2024-$D$6)/($E$6-$D$6))) -> 0 | C21: =IF(2025<=$D$6,0,IF(2025>=$E$6,$B$6,$B$6*(2025-$D$6)/($E$6-$D$6))) -> 0 | D21: =IF(2026<=$D$6,0,IF(2026>=$E$6,$B$6,$B$6*(2026-$D$6)/($E$6-$D$6))) -> 16.666667 | E21: =IF(2027<=$D$6,0,IF(2027>=$E$6,$B$6,$B$6*(2027-$D$6)/($E$6-$D$6))) -> 33.333333 | F21: =IF(2028<=$D$6,0,IF(2028>=$E$6,$B$6,$B$6*(2028-$D$6)/($E$6-$D$6))) -> 50 | G21: =IF(2029<=$D$6,0,IF(2029>=$E$6,$B$6,$B$6*(2029-$D$6)/($E$6-$D$6))) -> 50 | H21: =IF(2030<=$D$6,0,IF(2030>=$E$6,$B$6,$B$6*(2030-$D$6)/($E$6-$D$6))) -> 50 | I21: =IF(2031<=$D$6,0,IF(2031>=$E$6,$B$6,$B$6*(2031-$D$6)/($E$6-$D$6))) -> 50 | J21: =IF(2032<=$D$6,0,IF(2032>=$E$6,$B$6,$B$6*(2032-$D$6)/($E$6-$D$6))) -> 50 | K21: =IF(2033<=$D$6,0,IF(2033>=$E$6,$B$6,$B$6*(2033-$D$6)/($E$6-$D$6))) -> 50 | L21: =IF(2034<=$D$6,0,IF(2034>=$E$6,$B$6,$B$6*(2034-$D$6)/($E$6-$D$6))) -> 50 | M21: =IF(2035<=$D$6,0,IF(2035>=$E$6,$B$6,$B$6*(2035-$D$6)/($E$6-$D$6))) -> 50
A22: RT feebate ($/tCO2) | B22: =IF(2024<=$D$7,0,IF(2024>=$E$7,$B$7,$B$7*(2024-$D$7)/($E$7-$D$7))) -> 0 | C22: =IF(2025<=$D$7,0,IF(2025>=$E$7,$B$7,$B$7*(2025-$D$7)/($E$7-$D$7))) -> 0 | D22: =IF(2026<=$D$7,0,IF(2026>=$E$7,$B$7,$B$7*(2026-$D$7)/($E$7-$D$7))) -> 0 | E22: =IF(2027<=$D$7,0,IF(2027>=$E$7,$B$7,$B$7*(2027-$D$7)/($E$7-$D$7))) -> 5 | F22: =IF(2028<=$D$7,0,IF(2028>=$E$7,$B$7,$B$7*(2028-$D$7)/($E$7-$D$7))) -> 10 | G22: =IF(2029<=$D$7,0,IF(2029>=$E$7,$B$7,$B$7*(2029-$D$7)/($E$7-$D$7))) -> 15 | H22: =IF(2030<=$D$7,0,IF(2030>=$E$7,$B$7,$B$7*(2030-$D$7)/($E$7-$D$7))) -> 20 | I22: =IF(2031<=$D$7,0,IF(2031>=$E$7,$B$7,$B$7*(2031-$D$7)/($E$7-$D$7))) -> 20 | J22: =IF(2032<=$D$7,0,IF(2032>=$E$7,$B$7,$B$7*(2032-$D$7)/($E$7-$D$7))) -> 20 | K22: =IF(2033<=$D$7,0,IF(2033>=$E$7,$B$7,$B$7*(2033-$D$7)/($E$7-$D$7))) -> 20 | L22: =IF(2034<=$D$7,0,IF(2034>=$E$7,$B$7,$B$7*(2034-$D$7)/($E$7-$D$7))) -> 20 | M22: =IF(2035<=$D$7,0,IF(2035>=$E$7,$B$7,$B$7*(2035-$D$7)/($E$7-$D$7))) -> 20
A23: EG feebate ($/tCO2) | B23: =IF(2024<=$D$8,0,IF(2024>=$E$8,$B$8,$B$8*(2024-$D$8)/($E$8-$D$8))) -> 0 | C23: =IF(2025<=$D$8,0,IF(2025>=$E$8,$B$8,$B$8*(2025-$D$8)/($E$8-$D$8))) -> 0 | D23: =IF(2026<=$D$8,0,IF(2026>=$E$8,$B$8,$B$8*(2026-$D$8)/($E$8-$D$8))) -> 0 | E23: =IF(2027<=$D$8,0,IF(2027>=$E$8,$B$8,$B$8*(2027-$D$8)/($E$8-$D$8))) -> 3.75 | F23: =IF(2028<=$D$8,0,IF(2028>=$E$8,$B$8,$B$8*(2028-$D$8)/($E$8-$D$8))) -> 7.5 | G23: =IF(2029<=$D$8,0,IF(2029>=$E$8,$B$8,$B$8*(2029-$D$8)/($E$8-$D$8))) -> 11.25 | H23: =IF(2030<=$D$8,0,IF(2030>=$E$8,$B$8,$B$8*(2030-$D$8)/($E$8-$D$8))) -> 15 | I23: =IF(2031<=$D$8,0,IF(2031>=$E$8,$B$8,$B$8*(2031-$D$8)/($E$8-$D$8))) -> 15 | J23: =IF(2032<=$D$8,0,IF(2032>=$E$8,$B$8,$B$8*(2032-$D$8)/($E$8-$D$8))) -> 15 | K23: =IF(2033<=$D$8,0,IF(2033>=$E$8,$B$8,$B$8*(2033-$D$8)/($E$8-$D$8))) -> 15 | L23: =IF(2034<=$D$8,0,IF(2034>=$E$8,$B$8,$B$8*(2034-$D$8)/($E$8-$D$8))) -> 15 | M23: =IF(2035<=$D$8,0,IF(2035>=$E$8,$B$8,$B$8*(2035-$D$8)/($E$8-$D$8))) -> 15
A24: RT excises ($/GJ) by fuel:
A25: Coal | B25: =IF(2024<=$D$12,0,IF(2024>=$E$12,$B$12,$B$12*(2024-$D$12)/($E$12-$D$12))) -> 0 | C25: =IF(2025<=$D$12,0,IF(2025>=$E$12,$B$12,$B$12*(2025-$D$12)/($E$12-$D$12))) -> 0 | D25: =IF(2026<=$D$12,0,IF(2026>=$E$12,$B$12,$B$12*(2026-$D$12)/($E$12-$D$12))) -> 0 | E25: =IF(2027<=$D$12,0,IF(2027>=$E$12,$B$12,$B$12*(2027-$D$12)/($E$12-$D$12))) -> 0 | F25: =IF(2028<=$D$12,0,IF(2028>=$E$12,$B$12,$B$12*(2028-$D$12)/($E$12-$D$12))) -> 0 | G25: =IF(2029<=$D$12,0,IF(2029>=$E$12,$B$12,$B$12*(2029-$D$12)/($E$12-$D$12))) -> 0 | H25: =IF(2030<=$D$12,0,IF(2030>=$E$12,$B$12,$B$12*(2030-$D$12)/($E$12-$D$12))) -> 0 | I25: =IF(2031<=$D$12,0,IF(2031>=$E$12,$B$12,$B$12*(2031-$D$12)/($E$12-$D$12))) -> 0 | J25: =IF(2032<=$D$12,0,IF(2032>=$E$12,$B$12,$B$12*(2032-$D$12)/($E$12-$D$12))) -> 0 | K25: =IF(2033<=$D$12,0,IF(2033>=$E$12,$B$12,$B$12*(2033-$D$12)/($E$12-$D$12))) -> 0 | L25: =IF(2034<=$D$12,0,IF(2034>=$E$12,$B$12,$B$12*(2034-$D$12)/($E$12-$D$12))) -> 0 | M25: =IF(2035<=$D$12,0,IF(2035>=$E$12,$B$12,$B$12*(2035-$D$12)/($E$12-$D$12))) -> 0
A26: Natural gas | B26: =IF(2024<=$D$13,0,IF(2024>=$E$13,$B$13,$B$13*(2024-$D$13)/($E$13-$D$13))) -> 0 | C26: =IF(2025<=$D$13,0,IF(2025>=$E$13,$B$13,$B$13*(2025-$D$13)/($E$13-$D$13))) -> 0 | D26: =IF(2026<=$D$13,0,IF(2026>=$E$13,$B$13,$B$13*(2026-$D$13)/($E$13-$D$13))) -> 0 | E26: =IF(2027<=$D$13,0,IF(2027>=$E$13,$B$13,$B$13*(2027-$D$13)/($E$13-$D$13))) -> 0 | F26: =IF(2028<=$D$13,0,IF(2028>=$E$13,$B$13,$B$13*(2028-$D$13)/($E$13-$D$13))) -> 0 | G26: =IF(2029<=$D$13,0,IF(2029>=$E$13,$B$13,$B$13*(2029-$D$13)/($E$13-$D$13))) -> 0 | H26: =IF(2030<=$D$13,0,IF(2030>=$E$13,$B$13,$B$13*(2030-$D$13)/($E$13-$D$13))) -> 0 | I26: =IF(2031<=$D$13,0,IF(2031>=$E$13,$B$13,$B$13*(2031-$D$13)/($E$13-$D$13))) -> 0 | J26: =IF(2032<=$D$13,0,IF(2032>=$E$13,$B$13,$B$13*(2032-$D$13)/($E$13-$D$13))) -> 0 | K26: =IF(2033<=$D$13,0,IF(2033>=$E$13,$B$13,$B$13*(2033-$D$13)/($E$13-$D$13))) -> 0 | L26: =IF(2034<=$D$13,0,IF(2034>=$E$13,$B$13,$B$13*(2034-$D$13)/($E$13-$D$13))) -> 0 | M26: =IF(2035<=$D$13,0,IF(2035>=$E$13,$B$13,$B$13*(2035-$D$13)/($E$13-$D$13))) -> 0
A27: Gasoline | B27: =IF(2024<=$D$14,0,IF(2024>=$E$14,$B$14,$B$14*(2024-$D$14)/($E$14-$D$14))) -> 0 | C27: =IF(2025<=$D$14,0,IF(2025>=$E$14,$B$14,$B$14*(2025-$D$14)/($E$14-$D$14))) -> 0 | D27: =IF(2026<=$D$14,0,IF(2026>=$E$14,$B$14,$B$14*(2026-$D$14)/($E$14-$D$14))) -> 1.6666667 | E27: =IF(2027<=$D$14,0,IF(2027>=$E$14,$B$14,$B$14*(2027-$D$14)/($E$14-$D$14))) -> 3.3333333 | F27: =IF(2028<=$D$14,0,IF(2028>=$E$14,$B$14,$B$14*(2028-$D$14)/($E$14-$D$14))) -> 5 | G27: =IF(2029<=$D$14,0,IF(2029>=$E$14,$B$14,$B$14*(2029-$D$14)/($E$14-$D$14))) -> 5 | H27: =IF(2030<=$D$14,0,IF(2030>=$E$14,$B$14,$B$14*(2030-$D$14)/($E$14-$D$14))) -> 5 | I27: =IF(2031<=$D$14,0,IF(2031>=$E$14,$B$14,$B$14*(2031-$D$14)/($E$14-$D$14))) -> 5 | J27: =IF(2032<=$D$14,0,IF(2032>=$E$14,$B$14,$B$14*(2032-$D$14)/($E$14-$D$14))) -> 5 | K27: =IF(2033<=$D$14,0,IF(2033>=$E$14,$B$14,$B$14*(2033-$D$14)/($E$14-$D$14))) -> 5 | L27: =IF(2034<=$D$14,0,IF(2034>=$E$14,$B$14,$B$14*(2034-$D$14)/($E$14-$D$14))) -> 5 | M27: =IF(2035<=$D$14,0,IF(2035>=$E$14,$B$14,$B$14*(2035-$D$14)/($E$14-$D$14))) -> 5
A28: Diesel | B28: =IF(2024<=$D$15,0,IF(2024>=$E$15,$B$15,$B$15*(2024-$D$15)/($E$15-$D$15))) -> 0 | C28: =IF(2025<=$D$15,0,IF(2025>=$E$15,$B$15,$B$15*(2025-$D$15)/($E$15-$D$15))) -> 0 | D28: =IF(2026<=$D$15,0,IF(2026>=$E$15,$B$15,$B$15*(2026-$D$15)/($E$15-$D$15))) -> 1.3333333 | E28: =IF(2027<=$D$15,0,IF(2027>=$E$15,$B$15,$B$15*(2027-$D$15)/($E$15-$D$15))) -> 2.6666667 | F28: =IF(2028<=$D$15,0,IF(2028>=$E$15,$B$15,$B$15*(2028-$D$15)/($E$15-$D$15))) -> 4 | G28: =IF(2029<=$D$15,0,IF(2029>=$E$15,$B$15,$B$15*(2029-$D$15)/($E$15-$D$15))) -> 4 | H28: =IF(2030<=$D$15,0,IF(2030>=$E$15,$B$15,$B$15*(2030-$D$15)/($E$15-$D$15))) -> 4 | I28: =IF(2031<=$D$15,0,IF(2031>=$E$15,$B$15,$B$15*(2031-$D$15)/($E$15-$D$15))) -> 4 | J28: =IF(2032<=$D$15,0,IF(2032>=$E$15,$B$15,$B$15*(2032-$D$15)/($E$15-$D$15))) -> 4 | K28: =IF(2033<=$D$15,0,IF(2033>=$E$15,$B$15,$B$15*(2033-$D$15)/($E$15-$D$15))) -> 4 | L28: =IF(2034<=$D$15,0,IF(2034>=$E$15,$B$15,$B$15*(2034-$D$15)/($E$15-$D$15))) -> 4 | M28: =IF(2035<=$D$15,0,IF(2035>=$E$15,$B$15,$B$15*(2035-$D$15)/($E$15-$D$15))) -> 4
A29: Electricity | B29: =IF(2024<=$D$16,0,IF(2024>=$E$16,$B$16,$B$16*(2024-$D$16)/($E$16-$D$16))) -> 0 | C29: =IF(2025<=$D$16,0,IF(2025>=$E$16,$B$16,$B$16*(2025-$D$16)/($E$16-$D$16))) -> 0 | D29: =IF(2026<=$D$16,0,IF(2026>=$E$16,$B$16,$B$16*(2026-$D$16)/($E$16-$D$16))) -> 0 | E29: =IF(2027<=$D$16,0,IF(2027>=$E$16,$B$16,$B$16*(2027-$D$16)/($E$16-$D$16))) -> 0 | F29: =IF(2028<=$D$16,0,IF(2028>=$E$16,$B$16,$B$16*(2028-$D$16)/($E$16-$D$16))) -> 0 | G29: =IF(2029<=$D$16,0,IF(2029>=$E$16,$B$16,$B$16*(2029-$D$16)/($E$16-$D$16))) -> 0 | H29: =IF(2030<=$D$16,0,IF(2030>=$E$16,$B$16,$B$16*(2030-$D$16)/($E$16-$D$16))) -> 0 | I29: =IF(2031<=$D$16,0,IF(2031>=$E$16,$B$16,$B$16*(2031-$D$16)/($E$16-$D$16))) -> 0 | J29: =IF(2032<=$D$16,0,IF(2032>=$E$16,$B$16,$B$16*(2032-$D$16)/($E$16-$D$16))) -> 0 | K29: =IF(2033<=$D$16,0,IF(2033>=$E$16,$B$16,$B$16*(2033-$D$16)/($E$16-$D$16))) -> 0 | L29: =IF(2034<=$D$16,0,IF(2034>=$E$16,$B$16,$B$16*(2034-$D$16)/($E$16-$D$16))) -> 0 | M29: =IF(2035<=$D$16,0,IF(2035>=$E$16,$B$16,$B$16*(2035-$D$16)/($E$16-$D$16))) -> 0
A30: RE generation | B30: =IF(2024<=$D$17,0,IF(2024>=$E$17,$B$17,$B$17*(2024-$D$17)/($E$17-$D$17))) -> 0 | C30: =IF(2025<=$D$17,0,IF(2025>=$E$17,$B$17,$B$17*(2025-$D$17)/($E$17-$D$17))) -> 0 | D30: =IF(2026<=$D$17,0,IF(2026>=$E$17,$B$17,$B$17*(2026-$D$17)/($E$17-$D$17))) -> 0 | E30: =IF(2027<=$D$17,0,IF(2027>=$E$17,$B$17,$B$17*(2027-$D$17)/($E$17-$D$17))) -> 0 | F30: =IF(2028<=$D$17,0,IF(2028>=$E$17,$B$17,$B$17*(2028-$D$17)/($E$17-$D$17))) -> 0 | G30: =IF(2029<=$D$17,0,IF(2029>=$E$17,$B$17,$B$17*(2029-$D$17)/($E$17-$D$17))) -> 0 | H30: =IF(2030<=$D$17,0,IF(2030>=$E$17,$B$17,$B$17*(2030-$D$17)/($E$17-$D$17))) -> 0 | I30: =IF(2031<=$D$17,0,IF(2031>=$E$17,$B$17,$B$17*(2031-$D$17)/($E$17-$D$17))) -> 0 | J30: =IF(2032<=$D$17,0,IF(2032>=$E$17,$B$17,$B$17*(2032-$D$17)/($E$17-$D$17))) -> 0 | K30: =IF(2033<=$D$17,0,IF(2033>=$E$17,$B$17,$B$17*(2033-$D$17)/($E$17-$D$17))) -> 0 | L30: =IF(2034<=$D$17,0,IF(2034>=$E$17,$B$17,$B$17*(2034-$D$17)/($E$17-$D$17))) -> 0 | M30: =IF(2035<=$D$17,0,IF(2035>=$E$17,$B$17,$B$17*(2035-$D$17)/($E$17-$D$17))) -> 0
A31: EG excises ($/GJ) by fuel:
A32: Coal | B32: =IF(2024<=$D$12,0,IF(2024>=$E$12,$C$12,$C$12*(2024-$D$12)/($E$12-$D$12))) -> 0 | C32: =IF(2025<=$D$12,0,IF(2025>=$E$12,$C$12,$C$12*(2025-$D$12)/($E$12-$D$12))) -> 0 | D32: =IF(2026<=$D$12,0,IF(2026>=$E$12,$C$12,$C$12*(2026-$D$12)/($E$12-$D$12))) -> 0 | E32: =IF(2027<=$D$12,0,IF(2027>=$E$12,$C$12,$C$12*(2027-$D$12)/($E$12-$D$12))) -> 0 | F32: =IF(2028<=$D$12,0,IF(2028>=$E$12,$C$12,$C$12*(2028-$D$12)/($E$12-$D$12))) -> 0 | G32: =IF(2029<=$D$12,0,IF(2029>=$E$12,$C$12,$C$12*(2029-$D$12)/($E$12-$D$12))) -> 0 | H32: =IF(2030<=$D$12,0,IF(2030>=$E$12,$C$12,$C$12*(2030-$D$12)/($E$12-$D$12))) -> 0 | I32: =IF(2031<=$D$12,0,IF(2031>=$E$12,$C$12,$C$12*(2031-$D$12)/($E$12-$D$12))) -> 0 | J32: =IF(2032<=$D$12,0,IF(2032>=$E$12,$C$12,$C$12*(2032-$D$12)/($E$12-$D$12))) -> 0 | K32: =IF(2033<=$D$12,0,IF(2033>=$E$12,$C$12,$C$12*(2033-$D$12)/($E$12-$D$12))) -> 0 | L32: =IF(2034<=$D$12,0,IF(2034>=$E$12,$C$12,$C$12*(2034-$D$12)/($E$12-$D$12))) -> 0 | M32: =IF(2035<=$D$12,0,IF(2035>=$E$12,$C$12,$C$12*(2035-$D$12)/($E$12-$D$12))) -> 0
A33: Natural gas | B33: =IF(2024<=$D$13,0,IF(2024>=$E$13,$C$13,$C$13*(2024-$D$13)/($E$13-$D$13))) -> 0 | C33: =IF(2025<=$D$13,0,IF(2025>=$E$13,$C$13,$C$13*(2025-$D$13)/($E$13-$D$13))) -> 0 | D33: =IF(2026<=$D$13,0,IF(2026>=$E$13,$C$13,$C$13*(2026-$D$13)/($E$13-$D$13))) -> 0 | E33: =IF(2027<=$D$13,0,IF(2027>=$E$13,$C$13,$C$13*(2027-$D$13)/($E$13-$D$13))) -> 0 | F33: =IF(2028<=$D$13,0,IF(2028>=$E$13,$C$13,$C$13*(2028-$D$13)/($E$13-$D$13))) -> 0 | G33: =IF(2029<=$D$13,0,IF(2029>=$E$13,$C$13,$C$13*(2029-$D$13)/($E$13-$D$13))) -> 0 | H33: =IF(2030<=$D$13,0,IF(2030>=$E$13,$C$13,$C$13*(2030-$D$13)/($E$13-$D$13))) -> 0 | I33: =IF(2031<=$D$13,0,IF(2031>=$E$13,$C$13,$C$13*(2031-$D$13)/($E$13-$D$13))) -> 0 | J33: =IF(2032<=$D$13,0,IF(2032>=$E$13,$C$13,$C$13*(2032-$D$13)/($E$13-$D$13))) -> 0 | K33: =IF(2033<=$D$13,0,IF(2033>=$E$13,$C$13,$C$13*(2033-$D$13)/($E$13-$D$13))) -> 0 | L33: =IF(2034<=$D$13,0,IF(2034>=$E$13,$C$13,$C$13*(2034-$D$13)/($E$13-$D$13))) -> 0 | M33: =IF(2035<=$D$13,0,IF(2035>=$E$13,$C$13,$C$13*(2035-$D$13)/($E$13-$D$13))) -> 0
A34: Gasoline | B34: =IF(2024<=$D$14,0,IF(2024>=$E$14,$C$14,$C$14*(2024-$D$14)/($E$14-$D$14))) -> 0 | C34: =IF(2025<=$D$14,0,IF(2025>=$E$14,$C$14,$C$14*(2025-$D$14)/($E$14-$D$14))) -> 0 | D34: =IF(2026<=$D$14,0,IF(2026>=$E$14,$C$14,$C$14*(2026-$D$14)/($E$14-$D$14))) -> 0 | E34: =IF(2027<=$D$14,0,IF(2027>=$E$14,$C$14,$C$14*(2027-$D$14)/($E$14-$D$14))) -> 0 | F34: =IF(2028<=$D$14,0,IF(2028>=$E$14,$C$14,$C$14*(2028-$D$14)/($E$14-$D$14))) -> 0 | G34: =IF(2029<=$D$14,0,IF(2029>=$E$14,$C$14,$C$14*(2029-$D$14)/($E$14-$D$14))) -> 0 | H34: =IF(2030<=$D$14,0,IF(2030>=$E$14,$C$14,$C$14*(2030-$D$14)/($E$14-$D$14))) -> 0 | I34: =IF(2031<=$D$14,0,IF(2031>=$E$14,$C$14,$C$14*(2031-$D$14)/($E$14-$D$14))) -> 0 | J34: =IF(2032<=$D$14,0,IF(2032>=$E$14,$C$14,$C$14*(2032-$D$14)/($E$14-$D$14))) -> 0 | K34: =IF(2033<=$D$14,0,IF(2033>=$E$14,$C$14,$C$14*(2033-$D$14)/($E$14-$D$14))) -> 0 | L34: =IF(2034<=$D$14,0,IF(2034>=$E$14,$C$14,$C$14*(2034-$D$14)/($E$14-$D$14))) -> 0 | M34: =IF(2035<=$D$14,0,IF(2035>=$E$14,$C$14,$C$14*(2035-$D$14)/($E$14-$D$14))) -> 0
A35: Diesel | B35: =IF(2024<=$D$15,0,IF(2024>=$E$15,$C$15,$C$15*(2024-$D$15)/($E$15-$D$15))) -> 0 | C35: =IF(2025<=$D$15,0,IF(2025>=$E$15,$C$15,$C$15*(2025-$D$15)/($E$15-$D$15))) -> 0 | D35: =IF(2026<=$D$15,0,IF(2026>=$E$15,$C$15,$C$15*(2026-$D$15)/($E$15-$D$15))) -> 0 | E35: =IF(2027<=$D$15,0,IF(2027>=$E$15,$C$15,$C$15*(2027-$D$15)/($E$15-$D$15))) -> 0 | F35: =IF(2028<=$D$15,0,IF(2028>=$E$15,$C$15,$C$15*(2028-$D$15)/($E$15-$D$15))) -> 0 | G35: =IF(2029<=$D$15,0,IF(2029>=$E$15,$C$15,$C$15*(2029-$D$15)/($E$15-$D$15))) -> 0 | H35: =IF(2030<=$D$15,0,IF(2030>=$E$15,$C$15,$C$15*(2030-$D$15)/($E$15-$D$15))) -> 0 | I35: =IF(2031<=$D$15,0,IF(2031>=$E$15,$C$15,$C$15*(2031-$D$15)/($E$15-$D$15))) -> 0 | J35: =IF(2032<=$D$15,0,IF(2032>=$E$15,$C$15,$C$15*(2032-$D$15)/($E$15-$D$15))) -> 0 | K35: =IF(2033<=$D$15,0,IF(2033>=$E$15,$C$15,$C$15*(2033-$D$15)/($E$15-$D$15))) -> 0 | L35: =IF(2034<=$D$15,0,IF(2034>=$E$15,$C$15,$C$15*(2034-$D$15)/($E$15-$D$15))) -> 0 | M35: =IF(2035<=$D$15,0,IF(2035>=$E$15,$C$15,$C$15*(2035-$D$15)/($E$15-$D$15))) -> 0
A36: Electricity | B36: =IF(2024<=$D$16,0,IF(2024>=$E$16,$C$16,$C$16*(2024-$D$16)/($E$16-$D$16))) -> 0 | C36: =IF(2025<=$D$16,0,IF(2025>=$E$16,$C$16,$C$16*(2025-$D$16)/($E$16-$D$16))) -> 0 | D36: =IF(2026<=$D$16,0,IF(2026>=$E$16,$C$16,$C$16*(2026-$D$16)/($E$16-$D$16))) -> 0 | E36: =IF(2027<=$D$16,0,IF(2027>=$E$16,$C$16,$C$16*(2027-$D$16)/($E$16-$D$16))) -> 0 | F36: =IF(2028<=$D$16,0,IF(2028>=$E$16,$C$16,$C$16*(2028-$D$16)/($E$16-$D$16))) -> 0 | G36: =IF(2029<=$D$16,0,IF(2029>=$E$16,$C$16,$C$16*(2029-$D$16)/($E$16-$D$16))) -> 0 | H36: =IF(2030<=$D$16,0,IF(2030>=$E$16,$C$16,$C$16*(2030-$D$16)/($E$16-$D$16))) -> 0 | I36: =IF(2031<=$D$16,0,IF(2031>=$E$16,$C$16,$C$16*(2031-$D$16)/($E$16-$D$16))) -> 0 | J36: =IF(2032<=$D$16,0,IF(2032>=$E$16,$C$16,$C$16*(2032-$D$16)/($E$16-$D$16))) -> 0 | K36: =IF(2033<=$D$16,0,IF(2033>=$E$16,$C$16,$C$16*(2033-$D$16)/($E$16-$D$16))) -> 0 | L36: =IF(2034<=$D$16,0,IF(2034>=$E$16,$C$16,$C$16*(2034-$D$16)/($E$16-$D$16))) -> 0 | M36: =IF(2035<=$D$16,0,IF(2035>=$E$16,$C$16,$C$16*(2035-$D$16)/($E$16-$D$16))) -> 0
A37: RE generation | B37: =IF(2024<=$D$17,0,IF(2024>=$E$17,$C$17,$C$17*(2024-$D$17)/($E$17-$D$17))) -> 0 | C37: =IF(2025<=$D$17,0,IF(2025>=$E$17,$C$17,$C$17*(2025-$D$17)/($E$17-$D$17))) -> 0 | D37: =IF(2026<=$D$17,0,IF(2026>=$E$17,$C$17,$C$17*(2026-$D$17)/($E$17-$D$17))) -> 0 | E37: =IF(2027<=$D$17,0,IF(2027>=$E$17,$C$17,$C$17*(2027-$D$17)/($E$17-$D$17))) -> 0 | F37: =IF(2028<=$D$17,0,IF(2028>=$E$17,$C$17,$C$17*(2028-$D$17)/($E$17-$D$17))) -> 0 | G37: =IF(2029<=$D$17,0,IF(2029>=$E$17,$C$17,$C$17*(2029-$D$17)/($E$17-$D$17))) -> 0 | H37: =IF(2030<=$D$17,0,IF(2030>=$E$17,$C$17,$C$17*(2030-$D$17)/($E$17-$D$17))) -> 0 | I37: =IF(2031<=$D$17,0,IF(2031>=$E$17,$C$17,$C$17*(2031-$D$17)/($E$17-$D$17))) -> 0 | J37: =IF(2032<=$D$17,0,IF(2032>=$E$17,$C$17,$C$17*(2032-$D$17)/($E$17-$D$17))) -> 0 | K37: =IF(2033<=$D$17,0,IF(2033>=$E$17,$C$17,$C$17*(2033-$D$17)/($E$17-$D$17))) -> 0 | L37: =IF(2034<=$D$17,0,IF(2034>=$E$17,$C$17,$C$17*(2034-$D$17)/($E$17-$D$17))) -> 0 | M37: =IF(2035<=$D$17,0,IF(2035>=$E$17,$C$17,$C$17*(2035-$D$17)/($E$17-$D$17))) -> 0
A40: TOTAL EFFECTIVE CARBON PRICE
A41: TECP at target year | B41: ='TECP Calcs'!B28 -> 61.859332 | C41: $/tCO2
A43: Decomposition:
A44: Intensive margin | B44: ='TECP Calcs'!B31 -> 41.973925
A45: Extensive margin | B45: ='TECP Calcs'!B32 -> 19.885407
A47: Sector breakdown:
A48: Road Transport | B48: ='TECP Calcs'!B35 -> 10.967041
A49: Electricity Generation | B49: ='TECP Calcs'!B36 -> 50.892291
A51: Reference carbon tax
A53: TECP / Carbon tax ratio | B53: ='TECP Calcs'!B39 -> 1.2371866
A57: Partial Adjustment — Emissions Comparison
B59: Unit | C59: 2024 | D59: 2025 | E59: 2026 | F59: 2027 | G59: 2028 | H59: 2029 | I59: 2030 | J59: 2031 | K59: 2032 | L59: 2033 | M59: 2034 | N59: 2035
A60: Baseline emissions | B60: MtCO2 | C60: =Baseline!C115 -> 243.71 | D60: =Baseline!D115 -> 243.71 | E60: =Baseline!E115 -> 243.71 | F60: =Baseline!F115 -> 243.71 | G60: =Baseline!G115 -> 243.71 | H60: =Baseline!H115 -> 243.71 | I60: =Baseline!I115 -> 243.71 | J60: =Baseline!J115 -> 243.71 | ... N60: =Baseline!N115 -> 243.71
A61: Policy emissions | B61: MtCO2 | C61: =Policy!C115 -> 243.71 | D61: =Policy!D115 -> 243.71 | E61: =Policy!E115 -> 241.59681 | F61: =Policy!F115 -> 239.87332 | G61: =Policy!G115 -> 238.47625 | H61: =Policy!H115 -> 238.31612 | I61: =Policy!I115 -> 238.1434 | J61: =Policy!J115 -> 238.1434 | ... N61: =Policy!N115 -> 238.1434
A62: Emissions reduction | B62: MtCO2 | C62: =C60-C61 -> 0 | D62: =D60-D61 -> 0 | E62: =E60-E61 -> 2.1131858 | F62: =F60-F61 -> 3.8366781 | G62: =G60-G61 -> 5.2337472 | H62: =H60-H61 -> 5.3938803 | I62: =I60-I61 -> 5.5665995 | J62: =J60-J61 -> 5.5665995 | ... N62: =N60-N61 -> 5.5665995
A63: % reduction | B63: % | C63: =IF(C60=0,0,C62/C60) -> 0 | D63: =IF(D60=0,0,D62/D60) -> 0 | E63: =IF(E60=0,0,E62/E60) -> 0.0086709031 | F63: =IF(F60=0,0,F62/F60) -> 0.015742801 | G63: =IF(G60=0,0,G62/G60) -> 0.021475308 | H63: =IF(H60=0,0,H62/H60) -> 0.022132372 | I63: =IF(I60=0,0,I62/I60) -> 0.02284108 | J63: =IF(J60=0,0,J62/J60) -> 0.02284108 | ... N63: =IF(N60=0,0,N62/N60) -> 0.02284108
A65: Carbon tax ($/tCO2) | C65: =Dashboard!B21 -> 0 | D65: =Dashboard!C21 -> 0 | E65: =Dashboard!D21 -> 16.666667 | F65: =Dashboard!E21 -> 33.333333 | G65: =Dashboard!F21 -> 50 | H65: =Dashboard!G21 -> 50 | I65: =Dashboard!H21 -> 50 | J65: =Dashboard!I21 -> 50 | ... N65: =Dashboard!M21 -> 50

Sheet Tech Parameters
A1: Technical Parameters
A3: CES Elasticities
B4: Road Transport | C4: Electricity Gen.
A5: Substitution elasticity (sigma) | B5: 1.5 | C5: 0.8
A6: Demand elasticity (eta) | B6: -0.3 | C6: -0.15
A7: Adjustment speed (lambda) | B7: 0.15 | C7: 0.08
A9: Road Transport — Fuel Parameters
A10: Fuel | B10: Base price ($/GJ) | C10: Emission factor (tCO2/GJ) | D10: Base quantity (PJ) | E10: Efficiency (phi) | F10: Effective price ($/GJ svc) | G10: Effective EF (tCO2/GJ svc) | H10: Energy share (w) | I10: Service share (w_hat) | J10: Cost share (s)
A11: Coal | B11: 0 | C11: 0.095 | D11: 0 | E11: 0 | F11: =IF(E11=0,0,B11/E11) -> 0 | G11: =IF(E11=0,0,C11/E11) -> 0 | H11: =IF(SUM($D$11:$D$16)=0,0,D11/SUM($D$11:$D$16)) -> 0 | I11: =IF(SUMPRODUCT($D$11:$D$16,$E$11:$E$16)=0,0,D11*E11/SUMPRODUCT($D$11:$D$16,$E$11:$E$16)) -> 0 | J11: =IF(SUMPRODUCT($B$11:$B$16,$D$11:$D$16)=0,0,B11*D11/SUMPRODUCT($B$11:$B$16,$D$11:$D$16)) -> 0
A12: Natural gas | B12: 8 | C12: 0.056 | D12: 15 | E12: 0.25 | F12: =IF(E12=0,0,B12/E12) -> 32 | G12: =IF(E12=0,0,C12/E12) -> 0.224 | H12: =IF(SUM($D$11:$D$16)=0,0,D12/SUM($D$11:$D$16)) -> 0.012244898 | I12: =IF(SUMPRODUCT($D$11:$D$16,$E$11:$E$16)=0,0,D12*E12/SUMPRODUCT($D$11:$D$16,$E$11:$E$16)) -> 0.010211028 | J12: =IF(SUMPRODUCT($B$11:$B$16,$D$11:$D$16)=0,0,B12*D12/SUMPRODUCT($B$11:$B$16,$D$11:$D$16)) -> 0.0055452865
A13: Gasoline | B13: 18 | C13: 0.069 | D13: 650 | E13: 0.25 | F13: =IF(E13=0,0,B13/E13) -> 72 | G13: =IF(E13=0,0,C13/E13) -> 0.276 | H13: =IF(SUM($D$11:$D$16)=0,0,D13/SUM($D$11:$D$16)) -> 0.53061224 | I13: =IF(SUMPRODUCT($D$11:$D$16,$E$11:$E$16)=0,0,D13*E13/SUMPRODUCT($D$11:$D$16,$E$11:$E$16)) -> 0.44247788 | J13: =IF(SUMPRODUCT($B$11:$B$16,$D$11:$D$16)=0,0,B13*D13/SUMPRODUCT($B$11:$B$16,$D$11:$D$16)) -> 0.54066543
A14: Diesel | B14: 17 | C14: 0.074 | D14: 500 | E14: 0.3 | F14: =IF(E14=0,0,B14/E14) -> 56.666667 | G14: =IF(E14=0,0,C14/E14) -> 0.24666667 | H14: =IF(SUM($D$11:$D$16)=0,0,D14/SUM($D$11:$D$16)) -> 0.40816327 | I14: =IF(SUMPRODUCT($D$11:$D$16,$E$11:$E$16)=0,0,D14*E14/SUMPRODUCT($D$11:$D$16,$E$11:$E$16)) -> 0.40844112 | J14: =IF(SUMPRODUCT($B$11:$B$16,$D$11:$D$16)=0,0,B14*D14/SUMPRODUCT($B$11:$B$16,$D$11:$D$16)) -> 0.39279113
A15: Electricity | B15: 22 | C15: 0 | D15: 60 | E15: 0.85 | F15: =IF(E15=0,0,B15/E15) -> 25.882353 | G15: =IF(E15=0,0,C15/E15) -> 0 | H15: =IF(SUM($D$11:$D$16)=0,0,D15/SUM($D$11:$D$16)) -> 0.048979592 | I15: =IF(SUMPRODUCT($D$11:$D$16,$E$11:$E$16)=0,0,D15*E15/SUMPRODUCT($D$11:$D$16,$E$11:$E$16)) -> 0.13886998 | J15: =IF(SUMPRODUCT($B$11:$B$16,$D$11:$D$16)=0,0,B15*D15/SUMPRODUCT($B$11:$B$16,$D$11:$D$16)) -> 0.060998152
A16: RE generation | B16: 0 | C16: 0 | D16: 0 | E16: 0 | F16: =IF(E16=0,0,B16/E16) -> 0 | G16: =IF(E16=0,0,C16/E16) -> 0 | H16: =IF(SUM($D$11:$D$16)=0,0,D16/SUM($D$11:$D$16)) -> 0 | I16: =IF(SUMPRODUCT($D$11:$D$16,$E$11:$E$16)=0,0,D16*E16/SUMPRODUCT($D$11:$D$16,$E$11:$E$16)) -> 0 | J16: =IF(SUMPRODUCT($B$11:$B$16,$D$11:$D$16)=0,0,B16*D16/SUMPRODUCT($B$11:$B$16,$D$11:$D$16)) -> 0
A17: TOTALS | D17: =SUM(D11:D16) -> 1225
A18: Mean eff. EF (svc-wtd) | B18: =SUMPRODUCT(I11:I16,G11:G16) -> 0.22515997
A19: Total emissions (MtCO2) | B19: =SUMPRODUCT(D11:D16,C11:C16) -> 82.69
A22: Electricity Generation — Fuel Parameters
A23: Fuel | B23: Base price ($/GJ) | C23: Emission factor (tCO2/GJ) | D23: Base quantity (PJ) | E23: Efficiency (phi) | F23: Effective price ($/GJ svc) | G23: Effective EF (tCO2/GJ svc) | H23: Energy share (w) | I23: Service share (w_hat) | J23: Cost share (s)
A24: Coal | B24: 3 | C24: 0.095 | D24: 1200 | E24: 0.38 | F24: =IF(E24=0,0,B24/E24) -> 7.8947368 | G24: =IF(E24=0,0,C24/E24) -> 0.25 | H24: =IF(SUM($D$24:$D$29)=0,0,D24/SUM($D$24:$D$29)) -> 0.49382716 | I24: =IF(SUMPRODUCT($D$24:$D$29,$E$24:$E$29)=0,0,D24*E24/SUMPRODUCT($D$24:$D$29,$E$24:$E$29)) -> 0.36004737 | J24: =IF(SUMPRODUCT($B$24:$B$29,$D$24:$D$29)=0,0,B24*D24/SUMPRODUCT($B$24:$B$29,$D$24:$D$29)) -> 0.37422037
A25: Natural gas | B25: 6 | C25: 0.056 | D25: 800 | E25: 0.5 | F25: =IF(E25=0,0,B25/E25) -> 12 | G25: =IF(E25=0,0,C25/E25) -> 0.112 | H25: =IF(SUM($D$24:$D$29)=0,0,D25/SUM($D$24:$D$29)) -> 0.32921811 | I25: =IF(SUMPRODUCT($D$24:$D$29,$E$24:$E$29)=0,0,D25*E25/SUMPRODUCT($D$24:$D$29,$E$24:$E$29)) -> 0.31583103 | J25: =IF(SUMPRODUCT($B$24:$B$29,$D$24:$D$29)=0,0,B25*D25/SUMPRODUCT($B$24:$B$29,$D$24:$D$29)) -> 0.4989605
A26: Gasoline | B26: 0 | C26: 0.069 | D26: 0 | E26: 0 | F26: =IF(E26=0,0,B26/E26) -> 0 | G26: =IF(E26=0,0,C26/E26) -> 0 | H26: =IF(SUM($D$24:$D$29)=0,0,D26/SUM($D$24:$D$29)) -> 0 | I26: =IF(SUMPRODUCT($D$24:$D$29,$E$24:$E$29)=0,0,D26*E26/SUMPRODUCT($D$24:$D$29,$E$24:$E$29)) -> 0 | J26: =IF(SUMPRODUCT($B$24:$B$29,$D$24:$D$29)=0,0,B26*D26/SUMPRODUCT($B$24:$B$29,$D$24:$D$29)) -> 0
A27: Diesel | B27: 14 | C27: 0.074 | D27: 30 | E27: 0.35 | F27: =IF(E27=0,0,B27/E27) -> 40 | G27: =IF(E27=0,0,C27/E27) -> 0.21142857 | H27: =IF(SUM($D$24:$D$29)=0,0,D27/SUM($D$24:$D$29)) -> 0.012345679 | I27: =IF(SUMPRODUCT($D$24:$D$29,$E$24:$E$29)=0,0,D27*E27/SUMPRODUCT($D$24:$D$29,$E$24:$E$29)) -> 0.0082905645 | J27: =IF(SUMPRODUCT($B$24:$B$29,$D$24:$D$29)=0,0,B27*D27/SUMPRODUCT($B$24:$B$29,$D$24:$D$29)) -> 0.043659044
A28: Electricity | B28: 0 | C28: 0 | D28: 0 | E28: 0 | F28: =IF(E28=0,0,B28/E28) -> 0 | G28: =IF(E28=0,0,C28/E28) -> 0 | H28: =IF(SUM($D$24:$D$29)=0,0,D28/SUM($D$24:$D$29)) -> 0 | I28: =IF(SUMPRODUCT($D$24:$D$29,$E$24:$E$29)=0,0,D28*E28/SUMPRODUCT($D$24:$D$29,$E$24:$E$29)) -> 0 | J28: =IF(SUMPRODUCT($B$24:$B$29,$D$24:$D$29)=0,0,B28*D28/SUMPRODUCT($B$24:$B$29,$D$24:$D$29)) -> 0
A29: RE generation | B29: 2 | C29: 0 | D29: 400 | E29: 1 | F29: =IF(E29=0,0,B29/E29) -> 2 | G29: =IF(E29=0,0,C29/E29) -> 0 | H29: =IF(SUM($D$24:$D$29)=0,0,D29/SUM($D$24:$D$29)) -> 0.16460905 | I29: =IF(SUMPRODUCT($D$24:$D$29,$E$24:$E$29)=0,0,D29*E29/SUMPRODUCT($D$24:$D$29,$E$24:$E$29)) -> 0.31583103 | J29: =IF(SUMPRODUCT($B$24:$B$29,$D$24:$D$29)=0,0,B29*D29/SUMPRODUCT($B$24:$B$29,$D$24:$D$29)) -> 0.083160083
A30: TOTALS | D30: =SUM(D24:D29) -> 2430
A31: Mean eff. EF (svc-wtd) | B31: =SUMPRODUCT(I24:I29,G24:G29) -> 0.12713778
A32: Total emissions (MtCO2) | B32: =SUMPRODUCT(D24:D29,C24:C29) -> 161.02

Sheet TECP Calcs
A1: Total Effective Carbon Price (TECP)
A2: Static long-run equilibrium. Elasticities derived from CES, applied in isoelastic form.
A4: ROAD TRANSPORT
A5: Fuel | B5: E_fs (MtCO2) | C5: w_hat (svc share) | D5: e/phi (tCO2/GJ svc) | E5: mean e/phi | F5: p/phi ($/GJ svc) | G5: C_s ($/GJ svc) | H5: eps_int (isoelastic) | I5: eps_ext (isoelastic) | J5: eps_int_tilde (semi-elast) | K5: eps_ext_tilde (semi-elast) | L5: tau_int ($/tCO2) | M5: tau_ext ($/tCO2) | N5: Omega_int | O5: Omega_ext | P5: Dp_eff ($/GJ svc) | Q5: mean_Dp_eff ($/GJ svc)
A6: ='Tech Parameters'!A11 -> Coal | B6: ='Tech Parameters'!D11*'Tech Parameters'!C11 -> 0 | C6: ='Tech Parameters'!I11 -> 0 | D6: ='Tech Parameters'!G11 -> 0 | E6: ='Tech Parameters'!B18 -> 0.22515997 | F6: ='Tech Parameters'!F11 -> 0 | G6: =('Tech Parameters'!J11*IF('Tech Parameters'!F11=0,0,'Tech Parameters'!F11^(1-'Tech Parameters'!$B$5))+'Tech Parameters'!J12*IF('Tech Parameters'!F12=0,0,'Tech Parameters'!F12^(1-'Tech Parameters'!$B$5))+'Tech Parameters'!J13*IF('Tech Parameters'!F13=0,0,'Tech Parameters'!F13^(1-'Tech Parameters'!$B$5))+'Tech Parameters'!J14*IF('Tech Parameters'!F14=0,0,'Tech Parameters'!F14^(1-'Tech Parameters'!$B$5))+'Tech Parameters'!J15*IF('Tech Parameters'!F15=0,0,'Tech Parameters'!F15^(1-'Tech Parameters'!$B$5))+'Tech Parameters'!J16*IF('Tech Parameters'!F16=0,0,'Tech Parameters'!F16^(1-'Tech Parameters'!$B$5)))^(1/(1-'Tech Parameters'!$B$5)) -> 60.216236 | H6: =IF(C6=0,0,-'Tech Parameters'!$B$5*(1-C6)) -> 0 | I6: ='Tech Parameters'!$B$6 -> -0.3 | J6: =IF(F6=0,0,'Tech Parameters'!$B$5*(1-C6)*(D6-E6)/F6) -> 0 | K6: =IF(G6=0,0,ABS('Tech Parameters'!$B$6)*E6/G6) -> 0.0011217571 | L6: =IF(ABS(D6-E6)<0.00001,0,(P6-Q6)/(D6-E6)) -> 113.49014 | M6: =IF(E6=0,0,Q6/E6) -> 113.49014 | N6: =B6*J6 -> 0 | O6: =B6*K6 -> 0 | P6: =IF('Tech Parameters'!E11=0,0,(Dashboard!$B$6*'Tech Parameters'!C11+Dashboard!$B$7*('Tech Parameters'!C11-('Tech Parameters'!H11*'Tech Parameters'!C11+'Tech Parameters'!H12*'Tech Parameters'!C12+'Tech Parameters'!H13*'Tech Parameters'!C13+'Tech Parameters'!H14*'Tech Parameters'!C14+'Tech Parameters'!H15*'Tech Parameters'!C15+'Tech Parameters'!H16*'Tech Parameters'!C16))+Dashboard!$B$12)/'Tech Parameters'!E11) -> 0 | Q6: =SUMPRODUCT($C$6:$C$11,$P$6:$P$11) -> 25.553438
A7: ='Tech Parameters'!A12 -> Natural gas | B7: ='Tech Parameters'!D12*'Tech Parameters'!C12 -> 0.84 | C7: ='Tech Parameters'!I12 -> 0.010211028 | D7: ='Tech Parameters'!G12 -> 0.224 | E7: ='Tech Parameters'!B18 -> 0.22515997 | F7: ='Tech Parameters'!F12 -> 32 | G7: =$G$6 -> 60.216236 | H7: =IF(C7=0,0,-'Tech Parameters'!$B$5*(1-C7)) -> -1.4846835 | I7: ='Tech Parameters'!$B$6 -> -0.3 | J7: =IF(F7=0,0,'Tech Parameters'!$B$5*(1-C7)*(D7-E7)/F7) -> -5.3818512e-05 | K7: =IF(G7=0,0,ABS('Tech Parameters'!$B$6)*E7/G7) -> 0.0011217571 | L7: =IF(ABS(D7-E7)<0.00001,0,(P7-Q7)/(D7-E7)) -> 13167.206 | M7: =IF(E7=0,0,Q7/E7) -> 113.49014 | N7: =B7*J7 -> -4.520755e-05 | O7: =B7*K7 -> 0.00094227599 | P7: =IF('Tech Parameters'!E12=0,0,(Dashboard!$B$6*'Tech Parameters'!C12+Dashboard!$B$7*('Tech Parameters'!C12-('Tech Parameters'!H11*'Tech Parameters'!C11+'Tech Parameters'!H12*'Tech Parameters'!C12+'Tech Parameters'!H13*'Tech Parameters'!C13+'Tech Parameters'!H14*'Tech Parameters'!C14+'Tech Parameters'!H15*'Tech Parameters'!C15+'Tech Parameters'!H16*'Tech Parameters'!C16))+Dashboard!$B$13)/'Tech Parameters'!E12) -> 10.279837 | Q7: =SUMPRODUCT($C$6:$C$11,$P$6:$P$11) -> 25.553438
A8: ='Tech Parameters'!A13 -> Gasoline | B8: ='Tech Parameters'!D13*'Tech Parameters'!C13 -> 44.85 | C8: ='Tech Parameters'!I13 -> 0.44247788 | D8: ='Tech Parameters'!G13 -> 0.276 | E8: ='Tech Parameters'!B18 -> 0.22515997 | F8: ='Tech Parameters'!F13 -> 72 | G8: =$G$6 -> 60.216236 | H8: =IF(C8=0,0,-'Tech Parameters'!$B$5*(1-C8)) -> -0.83628319 | I8: ='Tech Parameters'!$B$6 -> -0.3 | J8: =IF(F8=0,0,'Tech Parameters'!$B$5*(1-C8)*(D8-E8)/F8) -> 0.00059050917 | K8: =IF(G8=0,0,ABS('Tech Parameters'!$B$6)*E8/G8) -> 0.0011217571 | L8: =IF(ABS(D8-E8)<0.00001,0,(P8-Q8)/(D8-E8)) -> 164.56323 | M8: =IF(E8=0,0,Q8/E8) -> 113.49014 | N8: =B8*J8 -> 0.026484336 | O8: =B8*K8 -> 0.050310807 | P8: =IF('Tech Parameters'!E13=0,0,(Dashboard!$B$6*'Tech Parameters'!C13+Dashboard!$B$7*('Tech Parameters'!C13-('Tech Parameters'!H11*'Tech Parameters'!C11+'Tech Parameters'!H12*'Tech Parameters'!C12+'Tech Parameters'!H13*'Tech Parameters'!C13+'Tech Parameters'!H14*'Tech Parameters'!C14+'Tech Parameters'!H15*'Tech Parameters'!C15+'Tech Parameters'!H16*'Tech Parameters'!C16))+Dashboard!$B$14)/'Tech Parameters'!E13) -> 33.919837 | Q8: =SUMPRODUCT($C$6:$C$11,$P$6:$P$11) -> 25.553438
A9: ='Tech Parameters'!A14 -> Diesel | B9: ='Tech Parameters'!D14*'Tech Parameters'!C14 -> 37 | C9: ='Tech Parameters'!I14 -> 0.40844112 | D9: ='Tech Parameters'!G14 -> 0.24666667 | E9: ='Tech Parameters'!B18 -> 0.22515997 | F9: ='Tech Parameters'!F14 -> 56.666667 | G9: =$G$6 -> 60.216236 | H9: =IF(C9=0,0,-'Tech Parameters'!$B$5*(1-C9)) -> -0.88733833 | I9: ='Tech Parameters'!$B$6 -> -0.3 | J9: =IF(F9=0,0,'Tech Parameters'!$B$5*(1-C9)*(D9-E9)/F9) -> 0.00033677142 | K9: =IF(G9=0,0,ABS('Tech Parameters'!$B$6)*E9/G9) -> 0.0011217571 | L9: =IF(ABS(D9-E9)<0.00001,0,(P9-Q9)/(D9-E9)) -> 25.407263 | M9: =IF(E9=0,0,Q9/E9) -> 113.49014 | N9: =B9*J9 -> 0.012460543 | O9: =B9*K9 -> 0.041505014 | P9: =IF('Tech Parameters'!E14=0,0,(Dashboard!$B$6*'Tech Parameters'!C14+Dashboard!$B$7*('Tech Parameters'!C14-('Tech Parameters'!H11*'Tech Parameters'!C11+'Tech Parameters'!H12*'Tech Parameters'!C12+'Tech Parameters'!H13*'Tech Parameters'!C13+'Tech Parameters'!H14*'Tech Parameters'!C14+'Tech Parameters'!H15*'Tech Parameters'!C15+'Tech Parameters'!H16*'Tech Parameters'!C16))+Dashboard!$B$15)/'Tech Parameters'!E14) -> 26.099864 | Q9: =SUMPRODUCT($C$6:$C$11,$P$6:$P$11) -> 25.553438
A10: ='Tech Parameters'!A15 -> Electricity | B10: ='Tech Parameters'!D15*'Tech Parameters'!C15 -> 0 | C10: ='Tech Parameters'!I15 -> 0.13886998 | D10: ='Tech Parameters'!G15 -> 0 | E10: ='Tech Parameters'!B18 -> 0.22515997 | F10: ='Tech Parameters'!F15 -> 25.882353 | G10: =$G$6 -> 60.216236 | H10: =IF(C10=0,0,-'Tech Parameters'!$B$5*(1-C10)) -> -1.291695 | I10: ='Tech Parameters'!$B$6 -> -0.3 | J10: =IF(F10=0,0,'Tech Parameters'!$B$5*(1-C10)*(D10-E10)/F10) -> -0.011236923 | K10: =IF(G10=0,0,ABS('Tech Parameters'!$B$6)*E10/G10) -> 0.0011217571 | L10: =IF(ABS(D10-E10)<0.00001,0,(P10-Q10)/(D10-E10)) -> 120.54417 | M10: =IF(E10=0,0,Q10/E10) -> 113.49014 | N10: =B10*J10 -> 0 | O10: =B10*K10 -> 0 | P10: =IF('Tech Parameters'!E15=0,0,(Dashboard!$B$6*'Tech Parameters'!C15+Dashboard!$B$7*('Tech Parameters'!C15-('Tech Parameters'!H11*'Tech Parameters'!C11+'Tech Parameters'!H12*'Tech Parameters'!C12+'Tech Parameters'!H13*'Tech Parameters'!C13+'Tech Parameters'!H14*'Tech Parameters'!C14+'Tech Parameters'!H15*'Tech Parameters'!C15+'Tech Parameters'!H16*'Tech Parameters'!C16))+Dashboard!$B$16)/'Tech Parameters'!E15) -> -1.5882833 | Q10: =SUMPRODUCT($C$6:$C$11,$P$6:$P$11) -> 25.553438
A11: ='Tech Parameters'!A16 -> RE generation | B11: ='Tech Parameters'!D16*'Tech Parameters'!C16 -> 0 | C11: ='Tech Parameters'!I16 -> 0 | D11: ='Tech Parameters'!G16 -> 0 | E11: ='Tech Parameters'!B18 -> 0.22515997 | F11: ='Tech Parameters'!F16 -> 0 | G11: =$G$6 -> 60.216236 | H11: =IF(C11=0,0,-'Tech Parameters'!$B$5*(1-C11)) -> 0 | I11: ='Tech Parameters'!$B$6 -> -0.3 | J11: =IF(F11=0,0,'Tech Parameters'!$B$5*(1-C11)*(D11-E11)/F11) -> 0 | K11: =IF(G11=0,0,ABS('Tech Parameters'!$B$6)*E11/G11) -> 0.0011217571 | L11: =IF(ABS(D11-E11)<0.00001,0,(P11-Q11)/(D11-E11)) -> 113.49014 | M11: =IF(E11=0,0,Q11/E11) -> 113.49014 | N11: =B11*J11 -> 0 | O11: =B11*K11 -> 0 | P11: =IF('Tech Parameters'!E16=0,0,(Dashboard!$B$6*'Tech Parameters'!C16+Dashboard!$B$7*('Tech Parameters'!C16-('Tech Parameters'!H11*'Tech Parameters'!C11+'Tech Parameters'!H12*'Tech Parameters'!C12+'Tech Parameters'!H13*'Tech Parameters'!C13+'Tech Parameters'!H14*'Tech Parameters'!C14+'Tech Parameters'!H15*'Tech Parameters'!C15+'Tech Parameters'!H16*'Tech Parameters'!C16))+Dashboard!$B$17)/'Tech Parameters'!E16) -> 0 | Q11: =SUMPRODUCT($C$6:$C$11,$P$6:$P$11) -> 25.553438
A14: ELECTRICITY GENERATION
A15: Fuel | B15: E_fs (MtCO2) | C15: w_hat (svc share) | D15: e/phi (tCO2/GJ svc) | E15: mean e/phi | F15: p/phi ($/GJ svc) | G15: C_s ($/GJ svc) | H15: eps_int (isoelastic) | I15: eps_ext (isoelastic) | J15: eps_int_tilde (semi-elast) | K15: eps_ext_tilde (semi-elast) | L15: tau_int ($/tCO2) | M15: tau_ext ($/tCO2) | N15: Omega_int | O15: Omega_ext | P15: Dp_eff ($/GJ svc) | Q15: mean_Dp_eff ($/GJ svc)
A16: ='Tech Parameters'!A24 -> Coal | B16: ='Tech Parameters'!D24*'Tech Parameters'!C24 -> 114 | C16: ='Tech Parameters'!I24 -> 0.36004737 | D16: ='Tech Parameters'!G24 -> 0.25 | E16: ='Tech Parameters'!B31 -> 0.12713778 | F16: ='Tech Parameters'!F24 -> 7.8947368 | G16: =('Tech Parameters'!J24*IF('Tech Parameters'!F24=0,0,'Tech Parameters'!F24^(1-'Tech Parameters'!$C$5))+'Tech Parameters'!J25*IF('Tech Parameters'!F25=0,0,'Tech Parameters'!F25^(1-'Tech Parameters'!$C$5))+'Tech Parameters'!J26*IF('Tech Parameters'!F26=0,0,'Tech Parameters'!F26^(1-'Tech Parameters'!$C$5))+'Tech Parameters'!J27*IF('Tech Parameters'!F27=0,0,'Tech Parameters'!F27^(1-'Tech Parameters'!$C$5))+'Tech Parameters'!J28*IF('Tech Parameters'!F28=0,0,'Tech Parameters'!F28^(1-'Tech Parameters'!$C$5))+'Tech Parameters'!J29*IF('Tech Parameters'!F29=0,0,'Tech Parameters'!F29^(1-'Tech Parameters'!$C$5)))^(1/(1-'Tech Parameters'!$C$5)) -> 9.6214419 | H16: =IF(C16=0,0,-'Tech Parameters'!$C$5*(1-C16)) -> -0.5119621 | I16: ='Tech Parameters'!$C$6 -> -0.15 | J16: =IF(F16=0,0,'Tech Parameters'!$C$5*(1-C16)*(D16-E16)/F16) -> 0.0079674346 | K16: =IF(G16=0,0,ABS('Tech Parameters'!$C$6)*E16/G16) -> 0.0019821008 | L16: =IF(ABS(D16-E16)<0.00001,0,(P16-Q16)/(D16-E16)) -> 59.232622 | M16: =IF(E16=0,0,Q16/E16) -> 50 | N16: =B16*J16 -> 0.90828755 | O16: =B16*K16 -> 0.22595949 | P16: =IF('Tech Parameters'!E24=0,0,(Dashboard!$B$6*'Tech Parameters'!C24+Dashboard!$B$8*('Tech Parameters'!C24-('Tech Parameters'!H24*'Tech Parameters'!C24+'Tech Parameters'!H25*'Tech Parameters'!C25+'Tech Parameters'!H26*'Tech Parameters'!C26+'Tech Parameters'!H27*'Tech Parameters'!C27+'Tech Parameters'!H28*'Tech Parameters'!C28+'Tech Parameters'!H29*'Tech Parameters'!C29))+Dashboard!$C$12)/'Tech Parameters'!E24) -> 13.63434 | Q16: =SUMPRODUCT($C$16:$C$21,$P$16:$P$21) -> 6.3568891
A17: ='Tech Parameters'!A25 -> Natural gas | B17: ='Tech Parameters'!D25*'Tech Parameters'!C25 -> 44.8 | C17: ='Tech Parameters'!I25 -> 0.31583103 | D17: ='Tech Parameters'!G25 -> 0.112 | E17: ='Tech Parameters'!B31 -> 0.12713778 | F17: ='Tech Parameters'!F25 -> 12 | G17: =$G$16 -> 9.6214419 | H17: =IF(C17=0,0,-'Tech Parameters'!$C$5*(1-C17)) -> -0.54733518 | I17: ='Tech Parameters'!$C$6 -> -0.15 | J17: =IF(F17=0,0,'Tech Parameters'!$C$5*(1-C17)*(D17-E17)/F17) -> -0.00069045335 | K17: =IF(G17=0,0,ABS('Tech Parameters'!$C$6)*E17/G17) -> 0.0019821008 | L17: =IF(ABS(D17-E17)<0.00001,0,(P17-Q17)/(D17-E17)) -> 70.339918 | M17: =IF(E17=0,0,Q17/E17) -> 50 | N17: =B17*J17 -> -0.03093231 | O17: =B17*K17 -> 0.088798114 | P17: =IF('Tech Parameters'!E25=0,0,(Dashboard!$B$6*'Tech Parameters'!C25+Dashboard!$B$8*('Tech Parameters'!C25-('Tech Parameters'!H24*'Tech Parameters'!C24+'Tech Parameters'!H25*'Tech Parameters'!C25+'Tech Parameters'!H26*'Tech Parameters'!C26+'Tech Parameters'!H27*'Tech Parameters'!C27+'Tech Parameters'!H28*'Tech Parameters'!C28+'Tech Parameters'!H29*'Tech Parameters'!C29))+Dashboard!$C$13)/'Tech Parameters'!E25) -> 5.2920988 | Q17: =SUMPRODUCT($C$16:$C$21,$P$16:$P$21) -> 6.3568891
A18: ='Tech Parameters'!A26 -> Gasoline | B18: ='Tech Parameters'!D26*'Tech Parameters'!C26 -> 0 | C18: ='Tech Parameters'!I26 -> 0 | D18: ='Tech Parameters'!G26 -> 0 | E18: ='Tech Parameters'!B31 -> 0.12713778 | F18: ='Tech Parameters'!F26 -> 0 | G18: =$G$16 -> 9.6214419 | H18: =IF(C18=0,0,-'Tech Parameters'!$C$5*(1-C18)) -> 0 | I18: ='Tech Parameters'!$C$6 -> -0.15 | J18: =IF(F18=0,0,'Tech Parameters'!$C$5*(1-C18)*(D18-E18)/F18) -> 0 | K18: =IF(G18=0,0,ABS('Tech Parameters'!$C$6)*E18/G18) -> 0.0019821008 | L18: =IF(ABS(D18-E18)<0.00001,0,(P18-Q18)/(D18-E18)) -> 50 | M18: =IF(E18=0,0,Q18/E18) -> 50 | N18: =B18*J18 -> 0 | O18: =B18*K18 -> 0 | P18: =IF('Tech Parameters'!E26=0,0,(Dashboard!$B$6*'Tech Parameters'!C26+Dashboard!$B$8*('Tech Parameters'!C26-('Tech Parameters'!H24*'Tech Parameters'!C24+'Tech Parameters'!H25*'Tech Parameters'!C25+'Tech Parameters'!H26*'Tech Parameters'!C26+'Tech Parameters'!H27*'Tech Parameters'!C27+'Tech Parameters'!H28*'Tech Parameters'!C28+'Tech Parameters'!H29*'Tech Parameters'!C29))+Dashboard!$C$14)/'Tech Parameters'!E26) -> 0 | Q18: =SUMPRODUCT($C$16:$C$21,$P$16:$P$21) -> 6.3568891
A19: ='Tech Parameters'!A27 -> Diesel | B19: ='Tech Parameters'!D27*'Tech Parameters'!C27 -> 2.22 | C19: ='Tech Parameters'!I27 -> 0.0082905645 | D19: ='Tech Parameters'!G27 -> 0.21142857 | E19: ='Tech Parameters'!B31 -> 0.12713778 | F19: ='Tech Parameters'!F27 -> 40 | G19: =$G$16 -> 9.6214419 | H19: =IF(C19=0,0,-'Tech Parameters'!$C$5*(1-C19)) -> -0.79336755 | I19: ='Tech Parameters'!$C$6 -> -0.15 | J19: =IF(F19=0,0,'Tech Parameters'!$C$5*(1-C19)*(D19-E19)/F19) -> 0.0016718394 | K19: =IF(G19=0,0,ABS('Tech Parameters'!$C$6)*E19/G19) -> 0.0019821008 | L19: =IF(ABS(D19-E19)<0.00001,0,(P19-Q19)/(D19-E19)) -> 53.93364 | M19: =IF(E19=0,0,Q19/E19) -> 50 | N19: =B19*J19 -> 0.0037114836 | O19: =B19*K19 -> 0.0044002637 | P19: =IF('Tech Parameters'!E27=0,0,(Dashboard!$B$6*'Tech Parameters'!C27+Dashboard!$B$8*('Tech Parameters'!C27-('Tech Parameters'!H24*'Tech Parameters'!C24+'Tech Parameters'!H25*'Tech Parameters'!C25+'Tech Parameters'!H26*'Tech Parameters'!C26+'Tech Parameters'!H27*'Tech Parameters'!C27+'Tech Parameters'!H28*'Tech Parameters'!C28+'Tech Parameters'!H29*'Tech Parameters'!C29))+Dashboard!$C$15)/'Tech Parameters'!E27) -> 10.902998 | Q19: =SUMPRODUCT($C$16:$C$21,$P$16:$P$21) -> 6.3568891
A20: ='Tech Parameters'!A28 -> Electricity | B20: ='Tech Parameters'!D28*'Tech Parameters'!C28 -> 0 | C20: ='Tech Parameters'!I28 -> 0 | D20: ='Tech Parameters'!G28 -> 0 | E20: ='Tech Parameters'!B31 -> 0.12713778 | F20: ='Tech Parameters'!F28 -> 0 | G20: =$G$16 -> 9.6214419 | H20: =IF(C20=0,0,-'Tech Parameters'!$C$5*(1-C20)) -> 0 | I20: ='Tech Parameters'!$C$6 -> -0.15 | J20: =IF(F20=0,0,'Tech Parameters'!$C$5*(1-C20)*(D20-E20)/F20) -> 0 | K20: =IF(G20=0,0,ABS('Tech Parameters'!$C$6)*E20/G20) -> 0.0019821008 | L20: =IF(ABS(D20-E20)<0.00001,0,(P20-Q20)/(D20-E20)) -> 50 | M20: =IF(E20=0,0,Q20/E20) -> 50 | N20: =B20*J20 -> 0 | O20: =B20*K20 -> 0 | P20: =IF('Tech Parameters'!E28=0,0,(Dashboard!$B$6*'Tech Parameters'!C28+Dashboard!$B$8*('Tech Parameters'!C28-('Tech Parameters'!H24*'Tech Parameters'!C24+'Tech Parameters'!H25*'Tech Parameters'!C25+'Tech Parameters'!H26*'Tech Parameters'!C26+'Tech Parameters'!H27*'Tech Parameters'!C27+'Tech Parameters'!H28*'Tech Parameters'!C28+'Tech Parameters'!H29*'Tech Parameters'!C29))+Dashboard!$C$16)/'Tech Parameters'!E28) -> 0 | Q20: =SUMPRODUCT($C$16:$C$21,$P$16:$P$21) -> 6.3568891
A21: ='Tech Parameters'!A29 -> RE generation | B21: ='Tech Parameters'!D29*'Tech Parameters'!C29 -> 0 | C21: ='Tech Parameters'!I29 -> 0.31583103 | D21: ='Tech Parameters'!G29 -> 0 | E21: ='Tech Parameters'!B31 -> 0.12713778 | F21: ='Tech Parameters'!F29 -> 2 | G21: =$G$16 -> 9.6214419 | H21: =IF(C21=0,0,-'Tech Parameters'!$C$5*(1-C21)) -> -0.54733518 | I21: ='Tech Parameters'!$C$6 -> -0.15 | J21: =IF(F21=0,0,'Tech Parameters'!$C$5*(1-C21)*(D21-E21)/F21) -> -0.03479349 | K21: =IF(G21=0,0,ABS('Tech Parameters'!$C$6)*E21/G21) -> 0.0019821008 | L21: =IF(ABS(D21-E21)<0.00001,0,(P21-Q21)/(D21-E21)) -> 57.817901 | M21: =IF(E21=0,0,Q21/E21) -> 50 | N21: =B21*J21 -> 0 | O21: =B21*K21 -> 0 | P21: =IF('Tech Parameters'!E29=0,0,(Dashboard!$B$6*'Tech Parameters'!C29+Dashboard!$B$8*('Tech Parameters'!C29-('Tech Parameters'!H24*'Tech Parameters'!C24+'Tech Parameters'!H25*'Tech Parameters'!C25+'Tech Parameters'!H26*'Tech Parameters'!C26+'Tech Parameters'!H27*'Tech Parameters'!C27+'Tech Parameters'!H28*'Tech Parameters'!C28+'Tech Parameters'!H29*'Tech Parameters'!C29))+Dashboard!$C$17)/'Tech Parameters'!E29) -> -0.99395062 | Q21: =SUMPRODUCT($C$16:$C$21,$P$16:$P$21) -> 6.3568891
A24: TECP CALCULATION
A25: Lambda (normalisation) | B25: =SUM(N6:N11)+SUM(O6:O11)+SUM(N16:N21)+SUM(O16:O21) -> 1.3318824
A26: Numerator (policy reduction) | B26: =SUMPRODUCT(N6:N11,L6:L11)+SUMPRODUCT(O6:O11,M6:M11)+SUMPRODUCT(N16:N21,L16:L21)+SUMPRODUCT(O16:O21,M16:M21) -> 82.389353
A28: TOTAL EFFECTIVE CARBON PRICE | B28: =$B$26/$B$25 -> 61.859332 | C28: $/tCO2
A30: Decomposition:
A31: Intensive margin | B31: =(SUMPRODUCT(N6:N11,L6:L11)+SUMPRODUCT(N16:N21,L16:L21))/$B$25 -> 41.973925
A32: Extensive margin | B32: =(SUMPRODUCT(O6:O11,M6:M11)+SUMPRODUCT(O16:O21,M16:M21))/$B$25 -> 19.885407
A34: Sector breakdown:
A35: Road Transport | B35: =(SUMPRODUCT(N6:N11,L6:L11)+SUMPRODUCT(O6:O11,M6:M11))/$B$25 -> 10.967041
A36: Electricity Generation | B36: =(SUMPRODUCT(N16:N21,L16:L21)+SUMPRODUCT(O16:O21,M16:M21))/$B$25 -> 50.892291
A38: Carbon tax (reference) | B38: =Dashboard!$B$6 -> 50
A39: TECP / Carbon tax ratio | B39: =IF(Dashboard!$B$6=0,0,$B$28/Dashboard!$B$6) -> 1.2371866
A41: Note: Isoelastic elasticities (cols H-I) derived from CES. Semi-elasticities (cols J-K) = isoelastic / price.
A42: Feebate input in $/tCO2: converted to $/GJ per fuel via feebate*(ef - e_bar), making it revenue-neutral.

Sheet Baseline
A1: Partial Adjustment Model — Baseline
B3: Unit | C3: 2024 | D3: 2025 | E3: 2026 | F3: 2027 | G3: 2028 | H3: 2029 | I3: 2030 | J3: 2031 | K3: 2032 | L3: 2033 | M3: 2034 | N3: 2035
A4: ROAD TRANSPORT — Fuel Prices ($/GJ)
A5: Coal | B5: $/GJ | C5: ='Tech Parameters'!B11 -> 0 | D5: ='Tech Parameters'!B11 -> 0 | E5: ='Tech Parameters'!B11 -> 0 | F5: ='Tech Parameters'!B11 -> 0 | G5: ='Tech Parameters'!B11 -> 0 | H5: ='Tech Parameters'!B11 -> 0 | I5: ='Tech Parameters'!B11 -> 0 | J5: ='Tech Parameters'!B11 -> 0 | K5: ='Tech Parameters'!B11 -> 0 | L5: ='Tech Parameters'!B11 -> 0 | M5: ='Tech Parameters'!B11 -> 0 | N5: ='Tech Parameters'!B11 -> 0
A6: Natural gas | B6: $/GJ | C6: ='Tech Parameters'!B12 -> 8 | D6: ='Tech Parameters'!B12 -> 8 | E6: ='Tech Parameters'!B12 -> 8 | F6: ='Tech Parameters'!B12 -> 8 | G6: ='Tech Parameters'!B12 -> 8 | H6: ='Tech Parameters'!B12 -> 8 | I6: ='Tech Parameters'!B12 -> 8 | J6: ='Tech Parameters'!B12 -> 8 | K6: ='Tech Parameters'!B12 -> 8 | L6: ='Tech Parameters'!B12 -> 8 | M6: ='Tech Parameters'!B12 -> 8 | N6: ='Tech Parameters'!B12 -> 8
A7: Gasoline | B7: $/GJ | C7: ='Tech Parameters'!B13 -> 18 | D7: ='Tech Parameters'!B13 -> 18 | E7: ='Tech Parameters'!B13 -> 18 | F7: ='Tech Parameters'!B13 -> 18 | G7: ='Tech Parameters'!B13 -> 18 | H7: ='Tech Parameters'!B13 -> 18 | I7: ='Tech Parameters'!B13 -> 18 | J7: ='Tech Parameters'!B13 -> 18 | K7: ='Tech Parameters'!B13 -> 18 | L7: ='Tech Parameters'!B13 -> 18 | M7: ='Tech Parameters'!B13 -> 18 | N7: ='Tech Parameters'!B13 -> 18
A8: Diesel | B8: $/GJ | C8: ='Tech Parameters'!B14 -> 17 | D8: ='Tech Parameters'!B14 -> 17 | E8: ='Tech Parameters'!B14 -> 17 | F8: ='Tech Parameters'!B14 -> 17 | G8: ='Tech Parameters'!B14 -> 17 | H8: ='Tech Parameters'!B14 -> 17 | I8: ='Tech Parameters'!B14 -> 17 | J8: ='Tech Parameters'!B14 -> 17 | K8: ='Tech Parameters'!B14 -> 17 | L8: ='Tech Parameters'!B14 -> 17 | M8: ='Tech Parameters'!B14 -> 17 | N8: ='Tech Parameters'!B14 -> 17
A9: Electricity | B9: $/GJ | C9: ='Tech Parameters'!B15 -> 22 | D9: ='Tech Parameters'!B15 -> 22 | E9: ='Tech Parameters'!B15 -> 22 | F9: ='Tech Parameters'!B15 -> 22 | G9: ='Tech Parameters'!B15 -> 22 | H9: ='Tech Parameters'!B15 -> 22 | I9: ='Tech Parameters'!B15 -> 22 | J9: ='Tech Parameters'!B15 -> 22 | K9: ='Tech Parameters'!B15 -> 22 | L9: ='Tech Parameters'!B15 -> 22 | M9: ='Tech Parameters'!B15 -> 22 | N9: ='Tech Parameters'!B15 -> 22
A10: RE generation | B10: $/GJ | C10: ='Tech Parameters'!B16 -> 0 | D10: ='Tech Parameters'!B16 -> 0 | E10: ='Tech Parameters'!B16 -> 0 | F10: ='Tech Parameters'!B16 -> 0 | G10: ='Tech Parameters'!B16 -> 0 | H10: ='Tech Parameters'!B16 -> 0 | I10: ='Tech Parameters'!B16 -> 0 | J10: ='Tech Parameters'!B16 -> 0 | K10: ='Tech Parameters'!B16 -> 0 | L10: ='Tech Parameters'!B16 -> 0 | M10: ='Tech Parameters'!B16 -> 0 | N10: ='Tech Parameters'!B16 -> 0
A12: ROAD TRANSPORT — Effective Prices ($/GJ svc)
A13: Coal | B13: $/GJ svc | C13: =IF('Tech Parameters'!E11=0,0,C5/'Tech Parameters'!E11) -> 0 | D13: =IF('Tech Parameters'!E11=0,0,D5/'Tech Parameters'!E11) -> 0 | E13: =IF('Tech Parameters'!E11=0,0,E5/'Tech Parameters'!E11) -> 0 | F13: =IF('Tech Parameters'!E11=0,0,F5/'Tech Parameters'!E11) -> 0 | G13: =IF('Tech Parameters'!E11=0,0,G5/'Tech Parameters'!E11) -> 0 | H13: =IF('Tech Parameters'!E11=0,0,H5/'Tech Parameters'!E11) -> 0 | I13: =IF('Tech Parameters'!E11=0,0,I5/'Tech Parameters'!E11) -> 0 | J13: =IF('Tech Parameters'!E11=0,0,J5/'Tech Parameters'!E11) -> 0 | K13: =IF('Tech Parameters'!E11=0,0,K5/'Tech Parameters'!E11) -> 0 | L13: =IF('Tech Parameters'!E11=0,0,L5/'Tech Parameters'!E11) -> 0 | M13: =IF('Tech Parameters'!E11=0,0,M5/'Tech Parameters'!E11) -> 0 | N13: =IF('Tech Parameters'!E11=0,0,N5/'Tech Parameters'!E11) -> 0
A14: Natural gas | B14: $/GJ svc | C14: =IF('Tech Parameters'!E12=0,0,C6/'Tech Parameters'!E12) -> 32 | D14: =IF('Tech Parameters'!E12=0,0,D6/'Tech Parameters'!E12) -> 32 | E14: =IF('Tech Parameters'!E12=0,0,E6/'Tech Parameters'!E12) -> 32 | F14: =IF('Tech Parameters'!E12=0,0,F6/'Tech Parameters'!E12) -> 32 | G14: =IF('Tech Parameters'!E12=0,0,G6/'Tech Parameters'!E12) -> 32 | H14: =IF('Tech Parameters'!E12=0,0,H6/'Tech Parameters'!E12) -> 32 | I14: =IF('Tech Parameters'!E12=0,0,I6/'Tech Parameters'!E12) -> 32 | J14: =IF('Tech Parameters'!E12=0,0,J6/'Tech Parameters'!E12) -> 32 | K14: =IF('Tech Parameters'!E12=0,0,K6/'Tech Parameters'!E12) -> 32 | L14: =IF('Tech Parameters'!E12=0,0,L6/'Tech Parameters'!E12) -> 32 | M14: =IF('Tech Parameters'!E12=0,0,M6/'Tech Parameters'!E12) -> 32 | N14: =IF('Tech Parameters'!E12=0,0,N6/'Tech Parameters'!E12) -> 32
A15: Gasoline | B15: $/GJ svc | C15: =IF('Tech Parameters'!E13=0,0,C7/'Tech Parameters'!E13) -> 72 | D15: =IF('Tech Parameters'!E13=0,0,D7/'Tech Parameters'!E13) -> 72 | E15: =IF('Tech Parameters'!E13=0,0,E7/'Tech Parameters'!E13) -> 72 | F15: =IF('Tech Parameters'!E13=0,0,F7/'Tech Parameters'!E13) -> 72 | G15: =IF('Tech Parameters'!E13=0,0,G7/'Tech Parameters'!E13) -> 72 | H15: =IF('Tech Parameters'!E13=0,0,H7/'Tech Parameters'!E13) -> 72 | I15: =IF('Tech Parameters'!E13=0,0,I7/'Tech Parameters'!E13) -> 72 | J15: =IF('Tech Parameters'!E13=0,0,J7/'Tech Parameters'!E13) -> 72 | K15: =IF('Tech Parameters'!E13=0,0,K7/'Tech Parameters'!E13) -> 72 | L15: =IF('Tech Parameters'!E13=0,0,L7/'Tech Parameters'!E13) -> 72 | M15: =IF('Tech Parameters'!E13=0,0,M7/'Tech Parameters'!E13) -> 72 | N15: =IF('Tech Parameters'!E13=0,0,N7/'Tech Parameters'!E13) -> 72
A16: Diesel | B16: $/GJ svc | C16: =IF('Tech Parameters'!E14=0,0,C8/'Tech Parameters'!E14) -> 56.666667 | D16: =IF('Tech Parameters'!E14=0,0,D8/'Tech Parameters'!E14) -> 56.666667 | E16: =IF('Tech Parameters'!E14=0,0,E8/'Tech Parameters'!E14) -> 56.666667 | F16: =IF('Tech Parameters'!E14=0,0,F8/'Tech Parameters'!E14) -> 56.666667 | G16: =IF('Tech Parameters'!E14=0,0,G8/'Tech Parameters'!E14) -> 56.666667 | H16: =IF('Tech Parameters'!E14=0,0,H8/'Tech Parameters'!E14) -> 56.666667 | I16: =IF('Tech Parameters'!E14=0,0,I8/'Tech Parameters'!E14) -> 56.666667 | J16: =IF('Tech Parameters'!E14=0,0,J8/'Tech Parameters'!E14) -> 56.666667 | K16: =IF('Tech Parameters'!E14=0,0,K8/'Tech Parameters'!E14) -> 56.666667 | L16: =IF('Tech Parameters'!E14=0,0,L8/'Tech Parameters'!E14) -> 56.666667 | M16: =IF('Tech Parameters'!E14=0,0,M8/'Tech Parameters'!E14) -> 56.666667 | N16: =IF('Tech Parameters'!E14=0,0,N8/'Tech Parameters'!E14) -> 56.666667
A17: Electricity | B17: $/GJ svc | C17: =IF('Tech Parameters'!E15=0,0,C9/'Tech Parameters'!E15) -> 25.882353 | D17: =IF('Tech Parameters'!E15=0,0,D9/'Tech Parameters'!E15) -> 25.882353 | E17: =IF('Tech Parameters'!E15=0,0,E9/'Tech Parameters'!E15) -> 25.882353 | F17: =IF('Tech Parameters'!E15=0,0,F9/'Tech Parameters'!E15) -> 25.882353 | G17: =IF('Tech Parameters'!E15=0,0,G9/'Tech Parameters'!E15) -> 25.882353 | H17: =IF('Tech Parameters'!E15=0,0,H9/'Tech Parameters'!E15) -> 25.882353 | I17: =IF('Tech Parameters'!E15=0,0,I9/'Tech Parameters'!E15) -> 25.882353 | J17: =IF('Tech Parameters'!E15=0,0,J9/'Tech Parameters'!E15) -> 25.882353 | K17: =IF('Tech Parameters'!E15=0,0,K9/'Tech Parameters'!E15) -> 25.882353 | L17: =IF('Tech Parameters'!E15=0,0,L9/'Tech Parameters'!E15) -> 25.882353 | M17: =IF('Tech Parameters'!E15=0,0,M9/'Tech Parameters'!E15) -> 25.882353 | N17: =IF('Tech Parameters'!E15=0,0,N9/'Tech Parameters'!E15) -> 25.882353
A18: RE generation | B18: $/GJ svc | C18: =IF('Tech Parameters'!E16=0,0,C10/'Tech Parameters'!E16) -> 0 | D18: =IF('Tech Parameters'!E16=0,0,D10/'Tech Parameters'!E16) -> 0 | E18: =IF('Tech Parameters'!E16=0,0,E10/'Tech Parameters'!E16) -> 0 | F18: =IF('Tech Parameters'!E16=0,0,F10/'Tech Parameters'!E16) -> 0 | G18: =IF('Tech Parameters'!E16=0,0,G10/'Tech Parameters'!E16) -> 0 | H18: =IF('Tech Parameters'!E16=0,0,H10/'Tech Parameters'!E16) -> 0 | I18: =IF('Tech Parameters'!E16=0,0,I10/'Tech Parameters'!E16) -> 0 | J18: =IF('Tech Parameters'!E16=0,0,J10/'Tech Parameters'!E16) -> 0 | K18: =IF('Tech Parameters'!E16=0,0,K10/'Tech Parameters'!E16) -> 0 | L18: =IF('Tech Parameters'!E16=0,0,L10/'Tech Parameters'!E16) -> 0 | M18: =IF('Tech Parameters'!E16=0,0,M10/'Tech Parameters'!E16) -> 0 | N18: =IF('Tech Parameters'!E16=0,0,N10/'Tech Parameters'!E16) -> 0
A20: ROAD TRANSPORT — CES Cost Index
C22: =IF(C13=0,0,C13^(1-'Tech Parameters'!$B$5)) -> 0 | D22: =IF(D13=0,0,D13^(1-'Tech Parameters'!$B$5)) -> 0 | E22: =IF(E13=0,0,E13^(1-'Tech Parameters'!$B$5)) -> 0 | F22: =IF(F13=0,0,F13^(1-'Tech Parameters'!$B$5)) -> 0 | G22: =IF(G13=0,0,G13^(1-'Tech Parameters'!$B$5)) -> 0 | H22: =IF(H13=0,0,H13^(1-'Tech Parameters'!$B$5)) -> 0 | I22: =IF(I13=0,0,I13^(1-'Tech Parameters'!$B$5)) -> 0 | J22: =IF(J13=0,0,J13^(1-'Tech Parameters'!$B$5)) -> 0 | ... N22: =IF(N13=0,0,N13^(1-'Tech Parameters'!$B$5)) -> 0
C23: =IF(C14=0,0,C14^(1-'Tech Parameters'!$B$5)) -> 0.1767767 | D23: =IF(D14=0,0,D14^(1-'Tech Parameters'!$B$5)) -> 0.1767767 | E23: =IF(E14=0,0,E14^(1-'Tech Parameters'!$B$5)) -> 0.1767767 | F23: =IF(F14=0,0,F14^(1-'Tech Parameters'!$B$5)) -> 0.1767767 | G23: =IF(G14=0,0,G14^(1-'Tech Parameters'!$B$5)) -> 0.1767767 | H23: =IF(H14=0,0,H14^(1-'Tech Parameters'!$B$5)) -> 0.1767767 | I23: =IF(I14=0,0,I14^(1-'Tech Parameters'!$B$5)) -> 0.1767767 | J23: =IF(J14=0,0,J14^(1-'Tech Parameters'!$B$5)) -> 0.1767767 | ... N23: =IF(N14=0,0,N14^(1-'Tech Parameters'!$B$5)) -> 0.1767767
C24: =IF(C15=0,0,C15^(1-'Tech Parameters'!$B$5)) -> 0.11785113 | D24: =IF(D15=0,0,D15^(1-'Tech Parameters'!$B$5)) -> 0.11785113 | E24: =IF(E15=0,0,E15^(1-'Tech Parameters'!$B$5)) -> 0.11785113 | F24: =IF(F15=0,0,F15^(1-'Tech Parameters'!$B$5)) -> 0.11785113 | G24: =IF(G15=0,0,G15^(1-'Tech Parameters'!$B$5)) -> 0.11785113 | H24: =IF(H15=0,0,H15^(1-'Tech Parameters'!$B$5)) -> 0.11785113 | I24: =IF(I15=0,0,I15^(1-'Tech Parameters'!$B$5)) -> 0.11785113 | J24: =IF(J15=0,0,J15^(1-'Tech Parameters'!$B$5)) -> 0.11785113 | ... N24: =IF(N15=0,0,N15^(1-'Tech Parameters'!$B$5)) -> 0.11785113
C25: =IF(C16=0,0,C16^(1-'Tech Parameters'!$B$5)) -> 0.13284223 | D25: =IF(D16=0,0,D16^(1-'Tech Parameters'!$B$5)) -> 0.13284223 | E25: =IF(E16=0,0,E16^(1-'Tech Parameters'!$B$5)) -> 0.13284223 | F25: =IF(F16=0,0,F16^(1-'Tech Parameters'!$B$5)) -> 0.13284223 | G25: =IF(G16=0,0,G16^(1-'Tech Parameters'!$B$5)) -> 0.13284223 | H25: =IF(H16=0,0,H16^(1-'Tech Parameters'!$B$5)) -> 0.13284223 | I25: =IF(I16=0,0,I16^(1-'Tech Parameters'!$B$5)) -> 0.13284223 | J25: =IF(J16=0,0,J16^(1-'Tech Parameters'!$B$5)) -> 0.13284223 | ... N25: =IF(N16=0,0,N16^(1-'Tech Parameters'!$B$5)) -> 0.13284223
C26: =IF(C17=0,0,C17^(1-'Tech Parameters'!$B$5)) -> 0.19656135 | D26: =IF(D17=0,0,D17^(1-'Tech Parameters'!$B$5)) -> 0.19656135 | E26: =IF(E17=0,0,E17^(1-'Tech Parameters'!$B$5)) -> 0.19656135 | F26: =IF(F17=0,0,F17^(1-'Tech Parameters'!$B$5)) -> 0.19656135 | G26: =IF(G17=0,0,G17^(1-'Tech Parameters'!$B$5)) -> 0.19656135 | H26: =IF(H17=0,0,H17^(1-'Tech Parameters'!$B$5)) -> 0.19656135 | I26: =IF(I17=0,0,I17^(1-'Tech Parameters'!$B$5)) -> 0.19656135 | J26: =IF(J17=0,0,J17^(1-'Tech Parameters'!$B$5)) -> 0.19656135 | ... N26: =IF(N17=0,0,N17^(1-'Tech Parameters'!$B$5)) -> 0.19656135
C27: =IF(C18=0,0,C18^(1-'Tech Parameters'!$B$5)) -> 0 | D27: =IF(D18=0,0,D18^(1-'Tech Parameters'!$B$5)) -> 0 | E27: =IF(E18=0,0,E18^(1-'Tech Parameters'!$B$5)) -> 0 | F27: =IF(F18=0,0,F18^(1-'Tech Parameters'!$B$5)) -> 0 | G27: =IF(G18=0,0,G18^(1-'Tech Parameters'!$B$5)) -> 0 | H27: =IF(H18=0,0,H18^(1-'Tech Parameters'!$B$5)) -> 0 | I27: =IF(I18=0,0,I18^(1-'Tech Parameters'!$B$5)) -> 0 | J27: =IF(J18=0,0,J18^(1-'Tech Parameters'!$B$5)) -> 0 | ... N27: =IF(N18=0,0,N18^(1-'Tech Parameters'!$B$5)) -> 0
C28: ='Tech Parameters'!J11 -> 0 | D28: ='Tech Parameters'!J12 -> 0.0055452865 | E28: ='Tech Parameters'!J13 -> 0.54066543 | F28: ='Tech Parameters'!J14 -> 0.39279113 | G28: ='Tech Parameters'!J15 -> 0.060998152 | H28: ='Tech Parameters'!J16 -> 0
A29: C(t) | B29: $/GJ svc | C29: =(C28*C22+D28*C23+E28*C24+F28*C25+G28*C26+H28*C27)^(1/(1-'Tech Parameters'!$B$5)) -> 60.216236 | D29: =(C28*D22+D28*D23+E28*D24+F28*D25+G28*D26+H28*D27)^(1/(1-'Tech Parameters'!$B$5)) -> 60.216236 | E29: =(C28*E22+D28*E23+E28*E24+F28*E25+G28*E26+H28*E27)^(1/(1-'Tech Parameters'!$B$5)) -> 60.216236 | F29: =(C28*F22+D28*F23+E28*F24+F28*F25+G28*F26+H28*F27)^(1/(1-'Tech Parameters'!$B$5)) -> 60.216236 | G29: =(C28*G22+D28*G23+E28*G24+F28*G25+G28*G26+H28*G27)^(1/(1-'Tech Parameters'!$B$5)) -> 60.216236 | H29: =(C28*H22+D28*H23+E28*H24+F28*H25+G28*H26+H28*H27)^(1/(1-'Tech Parameters'!$B$5)) -> 60.216236 | I29: =(C28*I22+D28*I23+E28*I24+F28*I25+G28*I26+H28*I27)^(1/(1-'Tech Parameters'!$B$5)) -> 60.216236 | J29: =(C28*J22+D28*J23+E28*J24+F28*J25+G28*J26+H28*J27)^(1/(1-'Tech Parameters'!$B$5)) -> 60.216236 | K29: =(C28*K22+D28*K23+E28*K24+F28*K25+G28*K26+H28*K27)^(1/(1-'Tech Parameters'!$B$5)) -> 60.216236 | L29: =(C28*L22+D28*L23+E28*L24+F28*L25+G28*L26+H28*L27)^(1/(1-'Tech Parameters'!$B$5)) -> 60.216236 | M29: =(C28*M22+D28*M23+E28*M24+F28*M25+G28*M26+H28*M27)^(1/(1-'Tech Parameters'!$B$5)) -> 60.216236 | N29: =(C28*N22+D28*N23+E28*N24+F28*N25+G28*N26+H28*N27)^(1/(1-'Tech Parameters'!$B$5)) -> 60.216236
A31: ROAD TRANSPORT — Equilibrium Quantities (PJ)
A32: Coal | B32: PJ | C32: ='Tech Parameters'!D11 -> 0 | D32: =IF(OR(D13=0,C13=0),C41,C41*(D13/C13)^(-'Tech Parameters'!$B$5)*(D29/C29)^('Tech Parameters'!$B$5+'Tech Parameters'!$B$6)) -> 0 | E32: =IF(OR(E13=0,D13=0),D41,D41*(E13/D13)^(-'Tech Parameters'!$B$5)*(E29/D29)^('Tech Parameters'!$B$5+'Tech Parameters'!$B$6)) -> 0 | F32: =IF(OR(F13=0,E13=0),E41,E41*(F13/E13)^(-'Tech Parameters'!$B$5)*(F29/E29)^('Tech Parameters'!$B$5+'Tech Parameters'!$B$6)) -> 0 | G32: =IF(OR(G13=0,F13=0),F41,F41*(G13/F13)^(-'Tech Parameters'!$B$5)*(G29/F29)^('Tech Parameters'!$B$5+'Tech Parameters'!$B$6)) -> 0 | H32: =IF(OR(H13=0,G13=0),G41,G41*(H13/G13)^(-'Tech Parameters'!$B$5)*(H29/G29)^('Tech Parameters'!$B$5+'Tech Parameters'!$B$6)) -> 0 | I32: =IF(OR(I13=0,H13=0),H41,H41*(I13/H13)^(-'Tech Parameters'!$B$5)*(I29/H29)^('Tech Parameters'!$B$5+'Tech Parameters'!$B$6)) -> 0 | J32: =IF(OR(J13=0,I13=0),I41,I41*(J13/I13)^(-'Tech Parameters'!$B$5)*(J29/I29)^('Tech Parameters'!$B$5+'Tech Parameters'!$B$6)) -> 0 | K32: =IF(OR(K13=0,J13=0),J41,J41*(K13/J13)^(-'Tech Parameters'!$B$5)*(K29/J29)^('Tech Parameters'!$B$5+'Tech Parameters'!$B$6)) -> 0 | ... N32: =IF(OR(N13=0,M13=0),M41,M41*(N13/M13)^(-'Tech Parameters'!$B$5)*(N29/M29)^('Tech Parameters'!$B$5+'Tech Parameters'!$B$6)) -> 0
A33: Natural gas | B33: PJ | C33: ='Tech Parameters'!D12 -> 15 | D33: =IF(OR(D14=0,C14=0),C42,C42*(D14/C14)^(-'Tech Parameters'!$B$5)*(D29/C29)^('Tech Parameters'!$B$5+'Tech Parameters'!$B$6)) -> 15 | E33: =IF(OR(E14=0,D14=0),D42,D42*(E14/D14)^(-'Tech Parameters'!$B$5)*(E29/D29)^('Tech Parameters'!$B$5+'Tech Parameters'!$B$6)) -> 15 | F33: =IF(OR(F14=0,E14=0),E42,E42*(F14/E14)^(-'Tech Parameters'!$B$5)*(F29/E29)^('Tech Parameters'!$B$5+'Tech Parameters'!$B$6)) -> 15 | G33: =IF(OR(G14=0,F14=0),F42,F42*(G14/F14)^(-'Tech Parameters'!$B$5)*(G29/F29)^('Tech Parameters'!$B$5+'Tech Parameters'!$B$6)) -> 15 | H33: =IF(OR(H14=0,G14=0),G42,G42*(H14/G14)^(-'Tech Parameters'!$B$5)*(H29/G29)^('Tech Parameters'!$B$5+'Tech Parameters'!$B$6)) -> 15 | I33: =IF(OR(I14=0,H14=0),H42,H42*(I14/H14)^(-'Tech Parameters'!$B$5)*(I29/H29)^('Tech Parameters'!$B$5+'Tech Parameters'!$B$6)) -> 15 | J33: =IF(OR(J14=0,I14=0),I42,I42*(J14/I14)^(-'Tech Parameters'!$B$5)*(J29/I29)^('Tech Parameters'!$B$5+'Tech Parameters'!$B$6)) -> 15 | K33: =IF(OR(K14=0,J14=0),J42,J42*(K14/J14)^(-'Tech Parameters'!$B$5)*(K29/J29)^('Tech Parameters'!$B$5+'Tech Parameters'!$B$6)) -> 15 | ... N33: =IF(OR(N14=0,M14=0),M42,M42*(N14/M14)^(-'Tech Parameters'!$B$5)*(N29/M29)^('Tech Parameters'!$B$5+'Tech Parameters'!$B$6)) -> 15
A34: Gasoline | B34: PJ | C34: ='Tech Parameters'!D13 -> 650 | D34: =IF(OR(D15=0,C15=0),C43,C43*(D15/C15)^(-'Tech Parameters'!$B$5)*(D29/C29)^('Tech Parameters'!$B$5+'Tech Parameters'!$B$6)) -> 650 | E34: =IF(OR(E15=0,D15=0),D43,D43*(E15/D15)^(-'Tech Parameters'!$B$5)*(E29/D29)^('Tech Parameters'!$B$5+'Tech Parameters'!$B$6)) -> 650 | F34: =IF(OR(F15=0,E15=0),E43,E43*(F15/E15)^(-'Tech Parameters'!$B$5)*(F29/E29)^('Tech Parameters'!$B$5+'Tech Parameters'!$B$6)) -> 650 | G34: =IF(OR(G15=0,F15=0),F43,F43*(G15/F15)^(-'Tech Parameters'!$B$5)*(G29/F29)^('Tech Parameters'!$B$5+'Tech Parameters'!$B$6)) -> 650 | H34: =IF(OR(H15=0,G15=0),G43,G43*(H15/G15)^(-'Tech Parameters'!$B$5)*(H29/G29)^('Tech Parameters'!$B$5+'Tech Parameters'!$B$6)) -> 650 | I34: =IF(OR(I15=0,H15=0),H43,H43*(I15/H15)^(-'Tech Parameters'!$B$5)*(I29/H29)^('Tech Parameters'!$B$5+'Tech Parameters'!$B$6)) -> 650 | J34: =IF(OR(J15=0,I15=0),I43,I43*(J15/I15)^(-'Tech Parameters'!$B$5)*(J29/I29)^('Tech Parameters'!$B$5+'Tech Parameters'!$B$6)) -> 650 | K34: =IF(OR(K15=0,J15=0),J43,J43*(K15/J15)^(-'Tech Parameters'!$B$5)*(K29/J29)^('Tech Parameters'!$B$5+'Tech Parameters'!$B$6)) -> 650 | ... N34: =IF(OR(N15=0,M15=0),M43,M43*(N15/M15)^(-'Tech Parameters'!$B$5)*(N29/M29)^('Tech Parameters'!$B$5+'Tech Parameters'!$B$6)) -> 650
A35: Diesel | B35: PJ | C35: ='Tech Parameters'!D14 -> 500 | D35: =IF(OR(D16=0,C16=0),C44,C44*(D16/C16)^(-'Tech Parameters'!$B$5)*(D29/C29)^('Tech Parameters'!$B$5+'Tech Parameters'!$B$6)) -> 500 | E35: =IF(OR(E16=0,D16=0),D44,D44*(E16/D16)^(-'Tech Parameters'!$B$5)*(E29/D29)^('Tech Parameters'!$B$5+'Tech Parameters'!$B$6)) -> 500 | F35: =IF(OR(F16=0,E16=0),E44,E44*(F16/E16)^(-'Tech Parameters'!$B$5)*(F29/E29)^('Tech Parameters'!$B$5+'Tech Parameters'!$B$6)) -> 500 | G35: =IF(OR(G16=0,F16=0),F44,F44*(G16/F16)^(-'Tech Parameters'!$B$5)*(G29/F29)^('Tech Parameters'!$B$5+'Tech Parameters'!$B$6)) -> 500 | H35: =IF(OR(H16=0,G16=0),G44,G44*(H16/G16)^(-'Tech Parameters'!$B$5)*(H29/G29)^('Tech Parameters'!$B$5+'Tech Parameters'!$B$6)) -> 500 | I35: =IF(OR(I16=0,H16=0),H44,H44*(I16/H16)^(-'Tech Parameters'!$B$5)*(I29/H29)^('Tech Parameters'!$B$5+'Tech Parameters'!$B$6)) -> 500 | J35: =IF(OR(J16=0,I16=0),I44,I44*(J16/I16)^(-'Tech Parameters'!$B$5)*(J29/I29)^('Tech Parameters'!$B$5+'Tech Parameters'!$B$6)) -> 500 | K35: =IF(OR(K16=0,J16=0),J44,J44*(K16/J16)^(-'Tech Parameters'!$B$5)*(K29/J29)^('Tech Parameters'!$B$5+'Tech Parameters'!$B$6)) -> 500 | ... N35: =IF(OR(N16=0,M16=0),M44,M44*(N16/M16)^(-'Tech Parameters'!$B$5)*(N29/M29)^('Tech Parameters'!$B$5+'Tech Parameters'!$B$6)) -> 500
A36: Electricity | B36: PJ | C36: ='Tech Parameters'!D15 -> 60 | D36: =IF(OR(D17=0,C17=0),C45,C45*(D17/C17)^(-'Tech Parameters'!$B$5)*(D29/C29)^('Tech Parameters'!$B$5+'Tech Parameters'!$B$6)) -> 60 | E36: =IF(OR(E17=0,D17=0),D45,D45*(E17/D17)^(-'Tech Parameters'!$B$5)*(E29/D29)^('Tech Parameters'!$B$5+'Tech Parameters'!$B$6)) -> 60 | F36: =IF(OR(F17=0,E17=0),E45,E45*(F17/E17)^(-'Tech Parameters'!$B$5)*(F29/E29)^('Tech Parameters'!$B$5+'Tech Parameters'!$B$6)) -> 60 | G36: =IF(OR(G17=0,F17=0),F45,F45*(G17/F17)^(-'Tech Parameters'!$B$5)*(G29/F29)^('Tech Parameters'!$B$5+'Tech Parameters'!$B$6)) -> 60 | H36: =IF(OR(H17=0,G17=0),G45,G45*(H17/G17)^(-'Tech Parameters'!$B$5)*(H29/G29)^('Tech Parameters'!$B$5+'Tech Parameters'!$B$6)) -> 60 | I36: =IF(OR(I17=0,H17=0),H45,H45*(I17/H17)^(-'Tech Parameters'!$B$5)*(I29/H29)^('Tech Parameters'!$B$5+'Tech Parameters'!$B$6)) -> 60 | J36: =IF(OR(J17=0,I17=0),I45,I45*(J17/I17)^(-'Tech Parameters'!$B$5)*(J29/I29)^('Tech Parameters'!$B$5+'Tech Parameters'!$B$6)) -> 60 | K36: =IF(OR(K17=0,J17=0),J45,J45*(K17/J17)^(-'Tech Parameters'!$B$5)*(K29/J29)^('Tech Parameters'!$B$5+'Tech Parameters'!$B$6)) -> 60 | ... N36: =IF(OR(N17=0,M17=0),M45,M45*(N17/M17)^(-'Tech Parameters'!$B$5)*(N29/M29)^('Tech Parameters'!$B$5+'Tech Parameters'!$B$6)) -> 60
A37: RE generation | B37: PJ | C37: ='Tech Parameters'!D16 -> 0 | D37: =IF(OR(D18=0,C18=0),C46,C46*(D18/C18)^(-'Tech Parameters'!$B$5)*(D29/C29)^('Tech Parameters'!$B$5+'Tech Parameters'!$B$6)) -> 0 | E37: =IF(OR(E18=0,D18=0),D46,D46*(E18/D18)^(-'Tech Parameters'!$B$5)*(E29/D29)^('Tech Parameters'!$B$5+'Tech Parameters'!$B$6)) -> 0 | F37: =IF(OR(F18=0,E18=0),E46,E46*(F18/E18)^(-'Tech Parameters'!$B$5)*(F29/E29)^('Tech Parameters'!$B$5+'Tech Parameters'!$B$6)) -> 0 | G37: =IF(OR(G18=0,F18=0),F46,F46*(G18/F18)^(-'Tech Parameters'!$B$5)*(G29/F29)^('Tech Parameters'!$B$5+'Tech Parameters'!$B$6)) -> 0 | H37: =IF(OR(H18=0,G18=0),G46,G46*(H18/G18)^(-'Tech Parameters'!$B$5)*(H29/G29)^('Tech Parameters'!$B$5+'Tech Parameters'!$B$6)) -> 0 | I37: =IF(OR(I18=0,H18=0),H46,H46*(I18/H18)^(-'Tech Parameters'!$B$5)*(I29/H29)^('Tech Parameters'!$B$5+'Tech Parameters'!$B$6)) -> 0 | J37: =IF(OR(J18=0,I18=0),I46,I46*(J18/I18)^(-'Tech Parameters'!$B$5)*(J29/I29)^('Tech Parameters'!$B$5+'Tech Parameters'!$B$6)) -> 0 | K37: =IF(OR(K18=0,J18=0),J46,J46*(K18/J18)^(-'Tech Parameters'!$B$5)*(K29/J29)^('Tech Parameters'!$B$5+'Tech Parameters'!$B$6)) -> 0 | ... N37: =IF(OR(N18=0,M18=0),M46,M46*(N18/M18)^(-'Tech Parameters'!$B$5)*(N29/M29)^('Tech Parameters'!$B$5+'Tech Parameters'!$B$6)) -> 0
A39: ROAD TRANSPORT — Actual Quantities (PJ)
A41: Coal | B41: PJ | C41: =C32 -> 0 | D41: =C41+'Tech Parameters'!$B$7*(D32-C41) -> 0 | E41: =D41+'Tech Parameters'!$B$7*(E32-D41) -> 0 | F41: =E41+'Tech Parameters'!$B$7*(F32-E41) -> 0 | G41: =F41+'Tech Parameters'!$B$7*(G32-F41) -> 0 | H41: =G41+'Tech Parameters'!$B$7*(H32-G41) -> 0 | I41: =H41+'Tech Parameters'!$B$7*(I32-H41) -> 0 | J41: =I41+'Tech Parameters'!$B$7*(J32-I41) -> 0 | K41: =J41+'Tech Parameters'!$B$7*(K32-J41) -> 0 | ... N41: =M41+'Tech Parameters'!$B$7*(N32-M41) -> 0
A42: Natural gas | B42: PJ | C42: =C33 -> 15 | D42: =C42+'Tech Parameters'!$B$7*(D33-C42) -> 15 | E42: =D42+'Tech Parameters'!$B$7*(E33-D42) -> 15 | F42: =E42+'Tech Parameters'!$B$7*(F33-E42) -> 15 | G42: =F42+'Tech Parameters'!$B$7*(G33-F42) -> 15 | H42: =G42+'Tech Parameters'!$B$7*(H33-G42) -> 15 | I42: =H42+'Tech Parameters'!$B$7*(I33-H42) -> 15 | J42: =I42+'Tech Parameters'!$B$7*(J33-I42) -> 15 | K42: =J42+'Tech Parameters'!$B$7*(K33-J42) -> 15 | ... N42: =M42+'Tech Parameters'!$B$7*(N33-M42) -> 15
A43: Gasoline | B43: PJ | C43: =C34 -> 650 | D43: =C43+'Tech Parameters'!$B$7*(D34-C43) -> 650 | E43: =D43+'Tech Parameters'!$B$7*(E34-D43) -> 650 | F43: =E43+'Tech Parameters'!$B$7*(F34-E43) -> 650 | G43: =F43+'Tech Parameters'!$B$7*(G34-F43) -> 650 | H43: =G43+'Tech Parameters'!$B$7*(H34-G43) -> 650 | I43: =H43+'Tech Parameters'!$B$7*(I34-H43) -> 650 | J43: =I43+'Tech Parameters'!$B$7*(J34-I43) -> 650 | K43: =J43+'Tech Parameters'!$B$7*(K34-J43) -> 650 | ... N43: =M43+'Tech Parameters'!$B$7*(N34-M43) -> 650
A44: Diesel | B44: PJ | C44: =C35 -> 500 | D44: =C44+'Tech Parameters'!$B$7*(D35-C44) -> 500 | E44: =D44+'Tech Parameters'!$B$7*(E35-D44) -> 500 | F44: =E44+'Tech Parameters'!$B$7*(F35-E44) -> 500 | G44: =F44+'Tech Parameters'!$B$7*(G35-F44) -> 500 | H44: =G44+'Tech Parameters'!$B$7*(H35-G44) -> 500 | I44: =H44+'Tech Parameters'!$B$7*(I35-H44) -> 500 | J44: =I44+'Tech Parameters'!$B$7*(J35-I44) -> 500 | K44: =J44+'Tech Parameters'!$B$7*(K35-J44) -> 500 | ... N44: =M44+'Tech Parameters'!$B$7*(N35-M44) -> 500
A45: Electricity | B45: PJ | C45: =C36 -> 60 | D45: =C45+'Tech Parameters'!$B$7*(D36-C45) -> 60 | E45: =D45+'Tech Parameters'!$B$7*(E36-D45) -> 60 | F45: =E45+'Tech Parameters'!$B$7*(F36-E45) -> 60 | G45: =F45+'Tech Parameters'!$B$7*(G36-F45) -> 60 | H45: =G45+'Tech Parameters'!$B$7*(H36-G45) -> 60 | I45: =H45+'Tech Parameters'!$B$7*(I36-H45) -> 60 | J45: =I45+'Tech Parameters'!$B$7*(J36-I45) -> 60 | K45: =J45+'Tech Parameters'!$B$7*(K36-J45) -> 60 | ... N45: =M45+'Tech Parameters'!$B$7*(N36-M45) -> 60
A46: RE generation | B46: PJ | C46: =C37 -> 0 | D46: =C46+'Tech Parameters'!$B$7*(D37-C46) -> 0 | E46: =D46+'Tech Parameters'!$B$7*(E37-D46) -> 0 | F46: =E46+'Tech Parameters'!$B$7*(F37-E46) -> 0 | G46: =F46+'Tech Parameters'!$B$7*(G37-F46) -> 0 | H46: =G46+'Tech Parameters'!$B$7*(H37-G46) -> 0 | I46: =H46+'Tech Parameters'!$B$7*(I37-H46) -> 0 | J46: =I46+'Tech Parameters'!$B$7*(J37-I46) -> 0 | K46: =J46+'Tech Parameters'!$B$7*(K37-J46) -> 0 | ... N46: =M46+'Tech Parameters'!$B$7*(N37-M46) -> 0
A48: ROAD TRANSPORT — Emissions (MtCO2)
A49: Coal | B49: MtCO2 | C49: =C41*'Tech Parameters'!C11 -> 0 | D49: =D41*'Tech Parameters'!C11 -> 0 | E49: =E41*'Tech Parameters'!C11 -> 0 | F49: =F41*'Tech Parameters'!C11 -> 0 | G49: =G41*'Tech Parameters'!C11 -> 0 | H49: =H41*'Tech Parameters'!C11 -> 0 | I49: =I41*'Tech Parameters'!C11 -> 0 | J49: =J41*'Tech Parameters'!C11 -> 0 | K49: =K41*'Tech Parameters'!C11 -> 0 | L49: =L41*'Tech Parameters'!C11 -> 0 | M49: =M41*'Tech Parameters'!C11 -> 0 | N49: =N41*'Tech Parameters'!C11 -> 0
A50: Natural gas | B50: MtCO2 | C50: =C42*'Tech Parameters'!C12 -> 0.84 | D50: =D42*'Tech Parameters'!C12 -> 0.84 | E50: =E42*'Tech Parameters'!C12 -> 0.84 | F50: =F42*'Tech Parameters'!C12 -> 0.84 | G50: =G42*'Tech Parameters'!C12 -> 0.84 | H50: =H42*'Tech Parameters'!C12 -> 0.84 | I50: =I42*'Tech Parameters'!C12 -> 0.84 | J50: =J42*'Tech Parameters'!C12 -> 0.84 | K50: =K42*'Tech Parameters'!C12 -> 0.84 | L50: =L42*'Tech Parameters'!C12 -> 0.84 | M50: =M42*'Tech Parameters'!C12 -> 0.84 | N50: =N42*'Tech Parameters'!C12 -> 0.84
A51: Gasoline | B51: MtCO2 | C51: =C43*'Tech Parameters'!C13 -> 44.85 | D51: =D43*'Tech Parameters'!C13 -> 44.85 | E51: =E43*'Tech Parameters'!C13 -> 44.85 | F51: =F43*'Tech Parameters'!C13 -> 44.85 | G51: =G43*'Tech Parameters'!C13 -> 44.85 | H51: =H43*'Tech Parameters'!C13 -> 44.85 | I51: =I43*'Tech Parameters'!C13 -> 44.85 | J51: =J43*'Tech Parameters'!C13 -> 44.85 | K51: =K43*'Tech Parameters'!C13 -> 44.85 | L51: =L43*'Tech Parameters'!C13 -> 44.85 | M51: =M43*'Tech Parameters'!C13 -> 44.85 | N51: =N43*'Tech Parameters'!C13 -> 44.85
A52: Diesel | B52: MtCO2 | C52: =C44*'Tech Parameters'!C14 -> 37 | D52: =D44*'Tech Parameters'!C14 -> 37 | E52: =E44*'Tech Parameters'!C14 -> 37 | F52: =F44*'Tech Parameters'!C14 -> 37 | G52: =G44*'Tech Parameters'!C14 -> 37 | H52: =H44*'Tech Parameters'!C14 -> 37 | I52: =I44*'Tech Parameters'!C14 -> 37 | J52: =J44*'Tech Parameters'!C14 -> 37 | K52: =K44*'Tech Parameters'!C14 -> 37 | L52: =L44*'Tech Parameters'!C14 -> 37 | M52: =M44*'Tech Parameters'!C14 -> 37 | N52: =N44*'Tech Parameters'!C14 -> 37
A53: Electricity | B53: MtCO2 | C53: =C45*'Tech Parameters'!C15 -> 0 | D53: =D45*'Tech Parameters'!C15 -> 0 | E53: =E45*'Tech Parameters'!C15 -> 0 | F53: =F45*'Tech Parameters'!C15 -> 0 | G53: =G45*'Tech Parameters'!C15 -> 0 | H53: =H45*'Tech Parameters'!C15 -> 0 | I53: =I45*'Tech Parameters'!C15 -> 0 | J53: =J45*'Tech Parameters'!C15 -> 0 | K53: =K45*'Tech Parameters'!C15 -> 0 | L53: =L45*'Tech Parameters'!C15 -> 0 | M53: =M45*'Tech Parameters'!C15 -> 0 | N53: =N45*'Tech Parameters'!C15 -> 0
A54: RE generation | B54: MtCO2 | C54: =C46*'Tech Parameters'!C16 -> 0 | D54: =D46*'Tech Parameters'!C16 -> 0 | E54: =E46*'Tech Parameters'!C16 -> 0 | F54: =F46*'Tech Parameters'!C16 -> 0 | G54: =G46*'Tech Parameters'!C16 -> 0 | H54: =H46*'Tech Parameters'!C16 -> 0 | I54: =I46*'Tech Parameters'!C16 -> 0 | J54: =J46*'Tech Parameters'!C16 -> 0 | K54: =K46*'Tech Parameters'!C16 -> 0 | L54: =L46*'Tech Parameters'!C16 -> 0 | M54: =M46*'Tech Parameters'!C16 -> 0 | N54: =N46*'Tech Parameters'!C16 -> 0
A55: TOTAL ROAD TRANSPORT EMISSIONS | B55: MtCO2 | C55: =SUM(C49:C54) -> 82.69 | D55: =SUM(D49:D54) -> 82.69 | E55: =SUM(E49:E54) -> 82.69 | F55: =SUM(F49:F54) -> 82.69 | G55: =SUM(G49:G54) -> 82.69 | H55: =SUM(H49:H54) -> 82.69 | I55: =SUM(I49:I54) -> 82.69 | J55: =SUM(J49:J54) -> 82.69 | ... N55: =SUM(N49:N54) -> 82.69
A56: TOTAL ROAD TRANSPORT ENERGY | B56: PJ | C56: =SUM(C41:C46) -> 1225 | D56: =SUM(D41:D46) -> 1225 | E56: =SUM(E41:E46) -> 1225 | F56: =SUM(F41:F46) -> 1225 | G56: =SUM(G41:G46) -> 1225 | H56: =SUM(H41:H46) -> 1225 | I56: =SUM(I41:I46) -> 1225 | J56: =SUM(J41:J46) -> 1225 | ... N56: =SUM(N41:N46) -> 1225
A59: ELECTRICITY GEN. — Fuel Prices ($/GJ)
A60: Coal | B60: $/GJ | C60: ='Tech Parameters'!B24 -> 3 | D60: ='Tech Parameters'!B24 -> 3 | E60: ='Tech Parameters'!B24 -> 3 | F60: ='Tech Parameters'!B24 -> 3 | G60: ='Tech Parameters'!B24 -> 3 | H60: ='Tech Parameters'!B24 -> 3 | I60: ='Tech Parameters'!B24 -> 3 | J60: ='Tech Parameters'!B24 -> 3 | K60: ='Tech Parameters'!B24 -> 3 | L60: ='Tech Parameters'!B24 -> 3 | M60: ='Tech Parameters'!B24 -> 3 | N60: ='Tech Parameters'!B24 -> 3
A61: Natural gas | B61: $/GJ | C61: ='Tech Parameters'!B25 -> 6 | D61: ='Tech Parameters'!B25 -> 6 | E61: ='Tech Parameters'!B25 -> 6 | F61: ='Tech Parameters'!B25 -> 6 | G61: ='Tech Parameters'!B25 -> 6 | H61: ='Tech Parameters'!B25 -> 6 | I61: ='Tech Parameters'!B25 -> 6 | J61: ='Tech Parameters'!B25 -> 6 | K61: ='Tech Parameters'!B25 -> 6 | L61: ='Tech Parameters'!B25 -> 6 | M61: ='Tech Parameters'!B25 -> 6 | N61: ='Tech Parameters'!B25 -> 6
A62: Gasoline | B62: $/GJ | C62: ='Tech Parameters'!B26 -> 0 | D62: ='Tech Parameters'!B26 -> 0 | E62: ='Tech Parameters'!B26 -> 0 | F62: ='Tech Parameters'!B26 -> 0 | G62: ='Tech Parameters'!B26 -> 0 | H62: ='Tech Parameters'!B26 -> 0 | I62: ='Tech Parameters'!B26 -> 0 | J62: ='Tech Parameters'!B26 -> 0 | K62: ='Tech Parameters'!B26 -> 0 | L62: ='Tech Parameters'!B26 -> 0 | M62: ='Tech Parameters'!B26 -> 0 | N62: ='Tech Parameters'!B26 -> 0
A63: Diesel | B63: $/GJ | C63: ='Tech Parameters'!B27 -> 14 | D63: ='Tech Parameters'!B27 -> 14 | E63: ='Tech Parameters'!B27 -> 14 | F63: ='Tech Parameters'!B27 -> 14 | G63: ='Tech Parameters'!B27 -> 14 | H63: ='Tech Parameters'!B27 -> 14 | I63: ='Tech Parameters'!B27 -> 14 | J63: ='Tech Parameters'!B27 -> 14 | K63: ='Tech Parameters'!B27 -> 14 | L63: ='Tech Parameters'!B27 -> 14 | M63: ='Tech Parameters'!B27 -> 14 | N63: ='Tech Parameters'!B27 -> 14
A64: Electricity | B64: $/GJ | C64: ='Tech Parameters'!B28 -> 0 | D64: ='Tech Parameters'!B28 -> 0 | E64: ='Tech Parameters'!B28 -> 0 | F64: ='Tech Parameters'!B28 -> 0 | G64: ='Tech Parameters'!B28 -> 0 | H64: ='Tech Parameters'!B28 -> 0 | I64: ='Tech Parameters'!B28 -> 0 | J64: ='Tech Parameters'!B28 -> 0 | K64: ='Tech Parameters'!B28 -> 0 | L64: ='Tech Parameters'!B28 -> 0 | M64: ='Tech Parameters'!B28 -> 0 | N64: ='Tech Parameters'!B28 -> 0
A65: RE generation | B65: $/GJ | C65: ='Tech Parameters'!B29 -> 2 | D65: ='Tech Parameters'!B29 -> 2 | E65: ='Tech Parameters'!B29 -> 2 | F65: ='Tech Parameters'!B29 -> 2 | G65: ='Tech Parameters'!B29 -> 2 | H65: ='Tech Parameters'!B29 -> 2 | I65: ='Tech Parameters'!B29 -> 2 | J65: ='Tech Parameters'!B29 -> 2 | K65: ='Tech Parameters'!B29 -> 2 | L65: ='Tech Parameters'!B29 -> 2 | M65: ='Tech Parameters'!B29 -> 2 | N65: ='Tech Parameters'!B29 -> 2
A67: ELECTRICITY GEN. — Effective Prices ($/GJ svc)
A68: Coal | B68: $/GJ svc | C68: =IF('Tech Parameters'!E24=0,0,C60/'Tech Parameters'!E24) -> 7.8947368 | D68: =IF('Tech Parameters'!E24=0,0,D60/'Tech Parameters'!E24) -> 7.8947368 | E68: =IF('Tech Parameters'!E24=0,0,E60/'Tech Parameters'!E24) -> 7.8947368 | F68: =IF('Tech Parameters'!E24=0,0,F60/'Tech Parameters'!E24) -> 7.8947368 | G68: =IF('Tech Parameters'!E24=0,0,G60/'Tech Parameters'!E24) -> 7.8947368 | H68: =IF('Tech Parameters'!E24=0,0,H60/'Tech Parameters'!E24) -> 7.8947368 | I68: =IF('Tech Parameters'!E24=0,0,I60/'Tech Parameters'!E24) -> 7.8947368 | J68: =IF('Tech Parameters'!E24=0,0,J60/'Tech Parameters'!E24) -> 7.8947368 | K68: =IF('Tech Parameters'!E24=0,0,K60/'Tech Parameters'!E24) -> 7.8947368 | L68: =IF('Tech Parameters'!E24=0,0,L60/'Tech Parameters'!E24) -> 7.8947368 | M68: =IF('Tech Parameters'!E24=0,0,M60/'Tech Parameters'!E24) -> 7.8947368 | N68: =IF('Tech Parameters'!E24=0,0,N60/'Tech Parameters'!E24) -> 7.8947368
A69: Natural gas | B69: $/GJ svc | C69: =IF('Tech Parameters'!E25=0,0,C61/'Tech Parameters'!E25) -> 12 | D69: =IF('Tech Parameters'!E25=0,0,D61/'Tech Parameters'!E25) -> 12 | E69: =IF('Tech Parameters'!E25=0,0,E61/'Tech Parameters'!E25) -> 12 | F69: =IF('Tech Parameters'!E25=0,0,F61/'Tech Parameters'!E25) -> 12 | G69: =IF('Tech Parameters'!E25=0,0,G61/'Tech Parameters'!E25) -> 12 | H69: =IF('Tech Parameters'!E25=0,0,H61/'Tech Parameters'!E25) -> 12 | I69: =IF('Tech Parameters'!E25=0,0,I61/'Tech Parameters'!E25) -> 12 | J69: =IF('Tech Parameters'!E25=0,0,J61/'Tech Parameters'!E25) -> 12 | K69: =IF('Tech Parameters'!E25=0,0,K61/'Tech Parameters'!E25) -> 12 | L69: =IF('Tech Parameters'!E25=0,0,L61/'Tech Parameters'!E25) -> 12 | M69: =IF('Tech Parameters'!E25=0,0,M61/'Tech Parameters'!E25) -> 12 | N69: =IF('Tech Parameters'!E25=0,0,N61/'Tech Parameters'!E25) -> 12
A70: Gasoline | B70: $/GJ svc | C70: =IF('Tech Parameters'!E26=0,0,C62/'Tech Parameters'!E26) -> 0 | D70: =IF('Tech Parameters'!E26=0,0,D62/'Tech Parameters'!E26) -> 0 | E70: =IF('Tech Parameters'!E26=0,0,E62/'Tech Parameters'!E26) -> 0 | F70: =IF('Tech Parameters'!E26=0,0,F62/'Tech Parameters'!E26) -> 0 | G70: =IF('Tech Parameters'!E26=0,0,G62/'Tech Parameters'!E26) -> 0 | H70: =IF('Tech Parameters'!E26=0,0,H62/'Tech Parameters'!E26) -> 0 | I70: =IF('Tech Parameters'!E26=0,0,I62/'Tech Parameters'!E26) -> 0 | J70: =IF('Tech Parameters'!E26=0,0,J62/'Tech Parameters'!E26) -> 0 | K70: =IF('Tech Parameters'!E26=0,0,K62/'Tech Parameters'!E26) -> 0 | L70: =IF('Tech Parameters'!E26=0,0,L62/'Tech Parameters'!E26) -> 0 | M70: =IF('Tech Parameters'!E26=0,0,M62/'Tech Parameters'!E26) -> 0 | N70: =IF('Tech Parameters'!E26=0,0,N62/'Tech Parameters'!E26) -> 0
A71: Diesel | B71: $/GJ svc | C71: =IF('Tech Parameters'!E27=0,0,C63/'Tech Parameters'!E27) -> 40 | D71: =IF('Tech Parameters'!E27=0,0,D63/'Tech Parameters'!E27) -> 40 | E71: =IF('Tech Parameters'!E27=0,0,E63/'Tech Parameters'!E27) -> 40 | F71: =IF('Tech Parameters'!E27=0,0,F63/'Tech Parameters'!E27) -> 40 | G71: =IF('Tech Parameters'!E27=0,0,G63/'Tech Parameters'!E27) -> 40 | H71: =IF('Tech Parameters'!E27=0,0,H63/'Tech Parameters'!E27) -> 40 | I71: =IF('Tech Parameters'!E27=0,0,I63/'Tech Parameters'!E27) -> 40 | J71: =IF('Tech Parameters'!E27=0,0,J63/'Tech Parameters'!E27) -> 40 | K71: =IF('Tech Parameters'!E27=0,0,K63/'Tech Parameters'!E27) -> 40 | L71: =IF('Tech Parameters'!E27=0,0,L63/'Tech Parameters'!E27) -> 40 | M71: =IF('Tech Parameters'!E27=0,0,M63/'Tech Parameters'!E27) -> 40 | N71: =IF('Tech Parameters'!E27=0,0,N63/'Tech Parameters'!E27) -> 40
A72: Electricity | B72: $/GJ svc | C72: =IF('Tech Parameters'!E28=0,0,C64/'Tech Parameters'!E28) -> 0 | D72: =IF('Tech Parameters'!E28=0,0,D64/'Tech Parameters'!E28) -> 0 | E72: =IF('Tech Parameters'!E28=0,0,E64/'Tech Parameters'!E28) -> 0 | F72: =IF('Tech Parameters'!E28=0,0,F64/'Tech Parameters'!E28) -> 0 | G72: =IF('Tech Parameters'!E28=0,0,G64/'Tech Parameters'!E28) -> 0 | H72: =IF('Tech Parameters'!E28=0,0,H64/'Tech Parameters'!E28) -> 0 | I72: =IF('Tech Parameters'!E28=0,0,I64/'Tech Parameters'!E28) -> 0 | J72: =IF('Tech Parameters'!E28=0,0,J64/'Tech Parameters'!E28) -> 0 | K72: =IF('Tech Parameters'!E28=0,0,K64/'Tech Parameters'!E28) -> 0 | L72: =IF('Tech Parameters'!E28=0,0,L64/'Tech Parameters'!E28) -> 0 | M72: =IF('Tech Parameters'!E28=0,0,M64/'Tech Parameters'!E28) -> 0 | N72: =IF('Tech Parameters'!E28=0,0,N64/'Tech Parameters'!E28) -> 0
A73: RE generation | B73: $/GJ svc | C73: =IF('Tech Parameters'!E29=0,0,C65/'Tech Parameters'!E29) -> 2 | D73: =IF('Tech Parameters'!E29=0,0,D65/'Tech Parameters'!E29) -> 2 | E73: =IF('Tech Parameters'!E29=0,0,E65/'Tech Parameters'!E29) -> 2 | F73: =IF('Tech Parameters'!E29=0,0,F65/'Tech Parameters'!E29) -> 2 | G73: =IF('Tech Parameters'!E29=0,0,G65/'Tech Parameters'!E29) -> 2 | H73: =IF('Tech Parameters'!E29=0,0,H65/'Tech Parameters'!E29) -> 2 | I73: =IF('Tech Parameters'!E29=0,0,I65/'Tech Parameters'!E29) -> 2 | J73: =IF('Tech Parameters'!E29=0,0,J65/'Tech Parameters'!E29) -> 2 | K73: =IF('Tech Parameters'!E29=0,0,K65/'Tech Parameters'!E29) -> 2 | L73: =IF('Tech Parameters'!E29=0,0,L65/'Tech Parameters'!E29) -> 2 | M73: =IF('Tech Parameters'!E29=0,0,M65/'Tech Parameters'!E29) -> 2 | N73: =IF('Tech Parameters'!E29=0,0,N65/'Tech Parameters'!E29) -> 2
A75: ELECTRICITY GEN. — CES Cost Index
C77: =IF(C68=0,0,C68^(1-'Tech Parameters'!$C$5)) -> 1.5117067 | D77: =IF(D68=0,0,D68^(1-'Tech Parameters'!$C$5)) -> 1.5117067 | E77: =IF(E68=0,0,E68^(1-'Tech Parameters'!$C$5)) -> 1.5117067 | F77: =IF(F68=0,0,F68^(1-'Tech Parameters'!$C$5)) -> 1.5117067 | G77: =IF(G68=0,0,G68^(1-'Tech Parameters'!$C$5)) -> 1.5117067 | H77: =IF(H68=0,0,H68^(1-'Tech Parameters'!$C$5)) -> 1.5117067 | I77: =IF(I68=0,0,I68^(1-'Tech Parameters'!$C$5)) -> 1.5117067 | J77: =IF(J68=0,0,J68^(1-'Tech Parameters'!$C$5)) -> 1.5117067 | ... N77: =IF(N68=0,0,N68^(1-'Tech Parameters'!$C$5)) -> 1.5117067
C78: =IF(C69=0,0,C69^(1-'Tech Parameters'!$C$5)) -> 1.6437518 | D78: =IF(D69=0,0,D69^(1-'Tech Parameters'!$C$5)) -> 1.6437518 | E78: =IF(E69=0,0,E69^(1-'Tech Parameters'!$C$5)) -> 1.6437518 | F78: =IF(F69=0,0,F69^(1-'Tech Parameters'!$C$5)) -> 1.6437518 | G78: =IF(G69=0,0,G69^(1-'Tech Parameters'!$C$5)) -> 1.6437518 | H78: =IF(H69=0,0,H69^(1-'Tech Parameters'!$C$5)) -> 1.6437518 | I78: =IF(I69=0,0,I69^(1-'Tech Parameters'!$C$5)) -> 1.6437518 | J78: =IF(J69=0,0,J69^(1-'Tech Parameters'!$C$5)) -> 1.6437518 | ... N78: =IF(N69=0,0,N69^(1-'Tech Parameters'!$C$5)) -> 1.6437518
C79: =IF(C70=0,0,C70^(1-'Tech Parameters'!$C$5)) -> 0 | D79: =IF(D70=0,0,D70^(1-'Tech Parameters'!$C$5)) -> 0 | E79: =IF(E70=0,0,E70^(1-'Tech Parameters'!$C$5)) -> 0 | F79: =IF(F70=0,0,F70^(1-'Tech Parameters'!$C$5)) -> 0 | G79: =IF(G70=0,0,G70^(1-'Tech Parameters'!$C$5)) -> 0 | H79: =IF(H70=0,0,H70^(1-'Tech Parameters'!$C$5)) -> 0 | I79: =IF(I70=0,0,I70^(1-'Tech Parameters'!$C$5)) -> 0 | J79: =IF(J70=0,0,J70^(1-'Tech Parameters'!$C$5)) -> 0 | ... N79: =IF(N70=0,0,N70^(1-'Tech Parameters'!$C$5)) -> 0
C80: =IF(C71=0,0,C71^(1-'Tech Parameters'!$C$5)) -> 2.0912791 | D80: =IF(D71=0,0,D71^(1-'Tech Parameters'!$C$5)) -> 2.0912791 | E80: =IF(E71=0,0,E71^(1-'Tech Parameters'!$C$5)) -> 2.0912791 | F80: =IF(F71=0,0,F71^(1-'Tech Parameters'!$C$5)) -> 2.0912791 | G80: =IF(G71=0,0,G71^(1-'Tech Parameters'!$C$5)) -> 2.0912791 | H80: =IF(H71=0,0,H71^(1-'Tech Parameters'!$C$5)) -> 2.0912791 | I80: =IF(I71=0,0,I71^(1-'Tech Parameters'!$C$5)) -> 2.0912791 | J80: =IF(J71=0,0,J71^(1-'Tech Parameters'!$C$5)) -> 2.0912791 | ... N80: =IF(N71=0,0,N71^(1-'Tech Parameters'!$C$5)) -> 2.0912791
C81: =IF(C72=0,0,C72^(1-'Tech Parameters'!$C$5)) -> 0 | D81: =IF(D72=0,0,D72^(1-'Tech Parameters'!$C$5)) -> 0 | E81: =IF(E72=0,0,E72^(1-'Tech Parameters'!$C$5)) -> 0 | F81: =IF(F72=0,0,F72^(1-'Tech Parameters'!$C$5)) -> 0 | G81: =IF(G72=0,0,G72^(1-'Tech Parameters'!$C$5)) -> 0 | H81: =IF(H72=0,0,H72^(1-'Tech Parameters'!$C$5)) -> 0 | I81: =IF(I72=0,0,I72^(1-'Tech Parameters'!$C$5)) -> 0 | J81: =IF(J72=0,0,J72^(1-'Tech Parameters'!$C$5)) -> 0 | ... N81: =IF(N72=0,0,N72^(1-'Tech Parameters'!$C$5)) -> 0
C82: =IF(C73=0,0,C73^(1-'Tech Parameters'!$C$5)) -> 1.1486984 | D82: =IF(D73=0,0,D73^(1-'Tech Parameters'!$C$5)) -> 1.1486984 | E82: =IF(E73=0,0,E73^(1-'Tech Parameters'!$C$5)) -> 1.1486984 | F82: =IF(F73=0,0,F73^(1-'Tech Parameters'!$C$5)) -> 1.1486984 | G82: =IF(G73=0,0,G73^(1-'Tech Parameters'!$C$5)) -> 1.1486984 | H82: =IF(H73=0,0,H73^(1-'Tech Parameters'!$C$5)) -> 1.1486984 | I82: =IF(I73=0,0,I73^(1-'Tech Parameters'!$C$5)) -> 1.1486984 | J82: =IF(J73=0,0,J73^(1-'Tech Parameters'!$C$5)) -> 1.1486984 | ... N82: =IF(N73=0,0,N73^(1-'Tech Parameters'!$C$5)) -> 1.1486984
C83: ='Tech Parameters'!J24 -> 0.37422037 | D83: ='Tech Parameters'!J25 -> 0.4989605 | E83: ='Tech Parameters'!J26 -> 0 | F83: ='Tech Parameters'!J27 -> 0.043659044 | G83: ='Tech Parameters'!J28 -> 0 | H83: ='Tech Parameters'!J29 -> 0.083160083
A84: C(t) | B84: $/GJ svc | C84: =(C83*C77+D83*C78+E83*C79+F83*C80+G83*C81+H83*C82)^(1/(1-'Tech Parameters'!$C$5)) -> 9.6214419 | D84: =(C83*D77+D83*D78+E83*D79+F83*D80+G83*D81+H83*D82)^(1/(1-'Tech Parameters'!$C$5)) -> 9.6214419 | E84: =(C83*E77+D83*E78+E83*E79+F83*E80+G83*E81+H83*E82)^(1/(1-'Tech Parameters'!$C$5)) -> 9.6214419 | F84: =(C83*F77+D83*F78+E83*F79+F83*F80+G83*F81+H83*F82)^(1/(1-'Tech Parameters'!$C$5)) -> 9.6214419 | G84: =(C83*G77+D83*G78+E83*G79+F83*G80+G83*G81+H83*G82)^(1/(1-'Tech Parameters'!$C$5)) -> 9.6214419 | H84: =(C83*H77+D83*H78+E83*H79+F83*H80+G83*H81+H83*H82)^(1/(1-'Tech Parameters'!$C$5)) -> 9.6214419 | I84: =(C83*I77+D83*I78+E83*I79+F83*I80+G83*I81+H83*I82)^(1/(1-'Tech Parameters'!$C$5)) -> 9.6214419 | J84: =(C83*J77+D83*J78+E83*J79+F83*J80+G83*J81+H83*J82)^(1/(1-'Tech Parameters'!$C$5)) -> 9.6214419 | K84: =(C83*K77+D83*K78+E83*K79+F83*K80+G83*K81+H83*K82)^(1/(1-'Tech Parameters'!$C$5)) -> 9.6214419 | L84: =(C83*L77+D83*L78+E83*L79+F83*L80+G83*L81+H83*L82)^(1/(1-'Tech Parameters'!$C$5)) -> 9.6214419 | M84: =(C83*M77+D83*M78+E83*M79+F83*M80+G83*M81+H83*M82)^(1/(1-'Tech Parameters'!$C$5)) -> 9.6214419 | N84: =(C83*N77+D83*N78+E83*N79+F83*N80+G83*N81+H83*N82)^(1/(1-'Tech Parameters'!$C$5)) -> 9.6214419
A86: ELECTRICITY GEN. — Equilibrium Quantities (PJ)
A87: Coal | B87: PJ | C87: ='Tech Parameters'!D24 -> 1200 | D87: =IF(OR(D68=0,C68=0),C96,C96*(D68/C68)^(-'Tech Parameters'!$C$5)*(D84/C84)^('Tech Parameters'!$C$5+'Tech Parameters'!$C$6)) -> 1200 | E87: =IF(OR(E68=0,D68=0),D96,D96*(E68/D68)^(-'Tech Parameters'!$C$5)*(E84/D84)^('Tech Parameters'!$C$5+'Tech Parameters'!$C$6)) -> 1200 | F87: =IF(OR(F68=0,E68=0),E96,E96*(F68/E68)^(-'Tech Parameters'!$C$5)*(F84/E84)^('Tech Parameters'!$C$5+'Tech Parameters'!$C$6)) -> 1200 | G87: =IF(OR(G68=0,F68=0),F96,F96*(G68/F68)^(-'Tech Parameters'!$C$5)*(G84/F84)^('Tech Parameters'!$C$5+'Tech Parameters'!$C$6)) -> 1200 | H87: =IF(OR(H68=0,G68=0),G96,G96*(H68/G68)^(-'Tech Parameters'!$C$5)*(H84/G84)^('Tech Parameters'!$C$5+'Tech Parameters'!$C$6)) -> 1200 | I87: =IF(OR(I68=0,H68=0),H96,H96*(I68/H68)^(-'Tech Parameters'!$C$5)*(I84/H84)^('Tech Parameters'!$C$5+'Tech Parameters'!$C$6)) -> 1200 | J87: =IF(OR(J68=0,I68=0),I96,I96*(J68/I68)^(-'Tech Parameters'!$C$5)*(J84/I84)^('Tech Parameters'!$C$5+'Tech Parameters'!$C$6)) -> 1200 | K87: =IF(OR(K68=0,J68=0),J96,J96*(K68/J68)^(-'Tech Parameters'!$C$5)*(K84/J84)^('Tech Parameters'!$C$5+'Tech Parameters'!$C$6)) -> 1200 | ... N87: =IF(OR(N68=0,M68=0),M96,M96*(N68/M68)^(-'Tech Parameters'!$C$5)*(N84/M84)^('Tech Parameters'!$C$5+'Tech Parameters'!$C$6)) -> 1200
A88: Natural gas | B88: PJ | C88: ='Tech Parameters'!D25 -> 800 | D88: =IF(OR(D69=0,C69=0),C97,C97*(D69/C69)^(-'Tech Parameters'!$C$5)*(D84/C84)^('Tech Parameters'!$C$5+'Tech Parameters'!$C$6)) -> 800 | E88: =IF(OR(E69=0,D69=0),D97,D97*(E69/D69)^(-'Tech Parameters'!$C$5)*(E84/D84)^('Tech Parameters'!$C$5+'Tech Parameters'!$C$6)) -> 800 | F88: =IF(OR(F69=0,E69=0),E97,E97*(F69/E69)^(-'Tech Parameters'!$C$5)*(F84/E84)^('Tech Parameters'!$C$5+'Tech Parameters'!$C$6)) -> 800 | G88: =IF(OR(G69=0,F69=0),F97,F97*(G69/F69)^(-'Tech Parameters'!$C$5)*(G84/F84)^('Tech Parameters'!$C$5+'Tech Parameters'!$C$6)) -> 800 | H88: =IF(OR(H69=0,G69=0),G97,G97*(H69/G69)^(-'Tech Parameters'!$C$5)*(H84/G84)^('Tech Parameters'!$C$5+'Tech Parameters'!$C$6)) -> 800 | I88: =IF(OR(I69=0,H69=0),H97,H97*(I69/H69)^(-'Tech Parameters'!$C$5)*(I84/H84)^('Tech Parameters'!$C$5+'Tech Parameters'!$C$6)) -> 800 | J88: =IF(OR(J69=0,I69=0),I97,I97*(J69/I69)^(-'Tech Parameters'!$C$5)*(J84/I84)^('Tech Parameters'!$C$5+'Tech Parameters'!$C$6)) -> 800 | K88: =IF(OR(K69=0,J69=0),J97,J97*(K69/J69)^(-'Tech Parameters'!$C$5)*(K84/J84)^('Tech Parameters'!$C$5+'Tech Parameters'!$C$6)) -> 800 | ... N88: =IF(OR(N69=0,M69=0),M97,M97*(N69/M69)^(-'Tech Parameters'!$C$5)*(N84/M84)^('Tech Parameters'!$C$5+'Tech Parameters'!$C$6)) -> 800
A89: Gasoline | B89: PJ | C89: ='Tech Parameters'!D26 -> 0 | D89: =IF(OR(D70=0,C70=0),C98,C98*(D70/C70)^(-'Tech Parameters'!$C$5)*(D84/C84)^('Tech Parameters'!$C$5+'Tech Parameters'!$C$6)) -> 0 | E89: =IF(OR(E70=0,D70=0),D98,D98*(E70/D70)^(-'Tech Parameters'!$C$5)*(E84/D84)^('Tech Parameters'!$C$5+'Tech Parameters'!$C$6)) -> 0 | F89: =IF(OR(F70=0,E70=0),E98,E98*(F70/E70)^(-'Tech Parameters'!$C$5)*(F84/E84)^('Tech Parameters'!$C$5+'Tech Parameters'!$C$6)) -> 0 | G89: =IF(OR(G70=0,F70=0),F98,F98*(G70/F70)^(-'Tech Parameters'!$C$5)*(G84/F84)^('Tech Parameters'!$C$5+'Tech Parameters'!$C$6)) -> 0 | H89: =IF(OR(H70=0,G70=0),G98,G98*(H70/G70)^(-'Tech Parameters'!$C$5)*(H84/G84)^('Tech Parameters'!$C$5+'Tech Parameters'!$C$6)) -> 0 | I89: =IF(OR(I70=0,H70=0),H98,H98*(I70/H70)^(-'Tech Parameters'!$C$5)*(I84/H84)^('Tech Parameters'!$C$5+'Tech Parameters'!$C$6)) -> 0 | J89: =IF(OR(J70=0,I70=0),I98,I98*(J70/I70)^(-'Tech Parameters'!$C$5)*(J84/I84)^('Tech Parameters'!$C$5+'Tech Parameters'!$C$6)) -> 0 | K89: =IF(OR(K70=0,J70=0),J98,J98*(K70/J70)^(-'Tech Parameters'!$C$5)*(K84/J84)^('Tech Parameters'!$C$5+'Tech Parameters'!$C$6)) -> 0 | ... N89: =IF(OR(N70=0,M70=0),M98,M98*(N70/M70)^(-'Tech Parameters'!$C$5)*(N84/M84)^('Tech Parameters'!$C$5+'Tech Parameters'!$C$6)) -> 0
A90: Diesel | B90: PJ | C90: ='Tech Parameters'!D27 -> 30 | D90: =IF(OR(D71=0,C71=0),C99,C99*(D71/C71)^(-'Tech Parameters'!$C$5)*(D84/C84)^('Tech Parameters'!$C$5+'Tech Parameters'!$C$6)) -> 30 | E90: =IF(OR(E71=0,D71=0),D99,D99*(E71/D71)^(-'Tech Parameters'!$C$5)*(E84/D84)^('Tech Parameters'!$C$5+'Tech Parameters'!$C$6)) -> 30 | F90: =IF(OR(F71=0,E71=0),E99,E99*(F71/E71)^(-'Tech Parameters'!$C$5)*(F84/E84)^('Tech Parameters'!$C$5+'Tech Parameters'!$C$6)) -> 30 | G90: =IF(OR(G71=0,F71=0),F99,F99*(G71/F71)^(-'Tech Parameters'!$C$5)*(G84/F84)^('Tech Parameters'!$C$5+'Tech Parameters'!$C$6)) -> 30 | H90: =IF(OR(H71=0,G71=0),G99,G99*(H71/G71)^(-'Tech Parameters'!$C$5)*(H84/G84)^('Tech Parameters'!$C$5+'Tech Parameters'!$C$6)) -> 30 | I90: =IF(OR(I71=0,H71=0),H99,H99*(I71/H71)^(-'Tech Parameters'!$C$5)*(I84/H84)^('Tech Parameters'!$C$5+'Tech Parameters'!$C$6)) -> 30 | J90: =IF(OR(J71=0,I71=0),I99,I99*(J71/I71)^(-'Tech Parameters'!$C$5)*(J84/I84)^('Tech Parameters'!$C$5+'Tech Parameters'!$C$6)) -> 30 | K90: =IF(OR(K71=0,J71=0),J99,J99*(K71/J71)^(-'Tech Parameters'!$C$5)*(K84/J84)^('Tech Parameters'!$C$5+'Tech Parameters'!$C$6)) -> 30 | ... N90: =IF(OR(N71=0,M71=0),M99,M99*(N71/M71)^(-'Tech Parameters'!$C$5)*(N84/M84)^('Tech Parameters'!$C$5+'Tech Parameters'!$C$6)) -> 30
A91: Electricity | B91: PJ | C91: ='Tech Parameters'!D28 -> 0 | D91: =IF(OR(D72=0,C72=0),C100,C100*(D72/C72)^(-'Tech Parameters'!$C$5)*(D84/C84)^('Tech Parameters'!$C$5+'Tech Parameters'!$C$6)) -> 0 | E91: =IF(OR(E72=0,D72=0),D100,D100*(E72/D72)^(-'Tech Parameters'!$C$5)*(E84/D84)^('Tech Parameters'!$C$5+'Tech Parameters'!$C$6)) -> 0 | F91: =IF(OR(F72=0,E72=0),E100,E100*(F72/E72)^(-'Tech Parameters'!$C$5)*(F84/E84)^('Tech Parameters'!$C$5+'Tech Parameters'!$C$6)) -> 0 | G91: =IF(OR(G72=0,F72=0),F100,F100*(G72/F72)^(-'Tech Parameters'!$C$5)*(G84/F84)^('Tech Parameters'!$C$5+'Tech Parameters'!$C$6)) -> 0 | H91: =IF(OR(H72=0,G72=0),G100,G100*(H72/G72)^(-'Tech Parameters'!$C$5)*(H84/G84)^('Tech Parameters'!$C$5+'Tech Parameters'!$C$6)) -> 0 | I91: =IF(OR(I72=0,H72=0),H100,H100*(I72/H72)^(-'Tech Parameters'!$C$5)*(I84/H84)^('Tech Parameters'!$C$5+'Tech Parameters'!$C$6)) -> 0 | J91: =IF(OR(J72=0,I72=0),I100,I100*(J72/I72)^(-'Tech Parameters'!$C$5)*(J84/I84)^('Tech Parameters'!$C$5+'Tech Parameters'!$C$6)) -> 0 | K91: =IF(OR(K72=0,J72=0),J100,J100*(K72/J72)^(-'Tech Parameters'!$C$5)*(K84/J84)^('Tech Parameters'!$C$5+'Tech Parameters'!$C$6)) -> 0 | ... N91: =IF(OR(N72=0,M72=0),M100,M100*(N72/M72)^(-'Tech Parameters'!$C$5)*(N84/M84)^('Tech Parameters'!$C$5+'Tech Parameters'!$C$6)) -> 0
A92: RE generation | B92: PJ | C92: ='Tech Parameters'!D29 -> 400 | D92: =IF(OR(D73=0,C73=0),C101,C101*(D73/C73)^(-'Tech Parameters'!$C$5)*(D84/C84)^('Tech Parameters'!$C$5+'Tech Parameters'!$C$6)) -> 400 | E92: =IF(OR(E73=0,D73=0),D101,D101*(E73/D73)^(-'Tech Parameters'!$C$5)*(E84/D84)^('Tech Parameters'!$C$5+'Tech Parameters'!$C$6)) -> 400 | F92: =IF(OR(F73=0,E73=0),E101,E101*(F73/E73)^(-'Tech Parameters'!$C$5)*(F84/E84)^('Tech Parameters'!$C$5+'Tech Parameters'!$C$6)) -> 400 | G92: =IF(OR(G73=0,F73=0),F101,F101*(G73/F73)^(-'Tech Parameters'!$C$5)*(G84/F84)^('Tech Parameters'!$C$5+'Tech Parameters'!$C$6)) -> 400 | H92: =IF(OR(H73=0,G73=0),G101,G101*(H73/G73)^(-'Tech Parameters'!$C$5)*(H84/G84)^('Tech Parameters'!$C$5+'Tech Parameters'!$C$6)) -> 400 | I92: =IF(OR(I73=0,H73=0),H101,H101*(I73/H73)^(-'Tech Parameters'!$C$5)*(I84/H84)^('Tech Parameters'!$C$5+'Tech Parameters'!$C$6)) -> 400 | J92: =IF(OR(J73=0,I73=0),I101,I101*(J73/I73)^(-'Tech Parameters'!$C$5)*(J84/I84)^('Tech Parameters'!$C$5+'Tech Parameters'!$C$6)) -> 400 | K92: =IF(OR(K73=0,J73=0),J101,J101*(K73/J73)^(-'Tech Parameters'!$C$5)*(K84/J84)^('Tech Parameters'!$C$5+'Tech Parameters'!$C$6)) -> 400 | ... N92: =IF(OR(N73=0,M73=0),M101,M101*(N73/M73)^(-'Tech Parameters'!$C$5)*(N84/M84)^('Tech Parameters'!$C$5+'Tech Parameters'!$C$6)) -> 400
A94: ELECTRICITY GEN. — Actual Quantities (PJ)
A96: Coal | B96: PJ | C96: =C87 -> 1200 | D96: =C96+'Tech Parameters'!$C$7*(D87-C96) -> 1200 | E96: =D96+'Tech Parameters'!$C$7*(E87-D96) -> 1200 | F96: =E96+'Tech Parameters'!$C$7*(F87-E96) -> 1200 | G96: =F96+'Tech Parameters'!$C$7*(G87-F96) -> 1200 | H96: =G96+'Tech Parameters'!$C$7*(H87-G96) -> 1200 | I96: =H96+'Tech Parameters'!$C$7*(I87-H96) -> 1200 | J96: =I96+'Tech Parameters'!$C$7*(J87-I96) -> 1200 | K96: =J96+'Tech Parameters'!$C$7*(K87-J96) -> 1200 | ... N96: =M96+'Tech Parameters'!$C$7*(N87-M96) -> 1200
A97: Natural gas | B97: PJ | C97: =C88 -> 800 | D97: =C97+'Tech Parameters'!$C$7*(D88-C97) -> 800 | E97: =D97+'Tech Parameters'!$C$7*(E88-D97) -> 800 | F97: =E97+'Tech Parameters'!$C$7*(F88-E97) -> 800 | G97: =F97+'Tech Parameters'!$C$7*(G88-F97) -> 800 | H97: =G97+'Tech Parameters'!$C$7*(H88-G97) -> 800 | I97: =H97+'Tech Parameters'!$C$7*(I88-H97) -> 800 | J97: =I97+'Tech Parameters'!$C$7*(J88-I97) -> 800 | K97: =J97+'Tech Parameters'!$C$7*(K88-J97) -> 800 | ... N97: =M97+'Tech Parameters'!$C$7*(N88-M97) -> 800
A98: Gasoline | B98: PJ | C98: =C89 -> 0 | D98: =C98+'Tech Parameters'!$C$7*(D89-C98) -> 0 | E98: =D98+'Tech Parameters'!$C$7*(E89-D98) -> 0 | F98: =E98+'Tech Parameters'!$C$7*(F89-E98) -> 0 | G98: =F98+'Tech Parameters'!$C$7*(G89-F98) -> 0 | H98: =G98+'Tech Parameters'!$C$7*(H89-G98) -> 0 | I98: =H98+'Tech Parameters'!$C$7*(I89-H98) -> 0 | J98: =I98+'Tech Parameters'!$C$7*(J89-I98) -> 0 | K98: =J98+'Tech Parameters'!$C$7*(K89-J98) -> 0 | ... N98: =M98+'Tech Parameters'!$C$7*(N89-M98) -> 0
A99: Diesel | B99: PJ | C99: =C90 -> 30 | D99: =C99+'Tech Parameters'!$C$7*(D90-C99) -> 30 | E99: =D99+'Tech Parameters'!$C$7*(E90-D99) -> 30 | F99: =E99+'Tech Parameters'!$C$7*(F90-E99) -> 30 | G99: =F99+'Tech Parameters'!$C$7*(G90-F99) -> 30 | H99: =G99+'Tech Parameters'!$C$7*(H90-G99) -> 30 | I99: =H99+'Tech Parameters'!$C$7*(I90-H99) -> 30 | J99: =I99+'Tech Parameters'!$C$7*(J90-I99) -> 30 | K99: =J99+'Tech Parameters'!$C$7*(K90-J99) -> 30 | ... N99: =M99+'Tech Parameters'!$C$7*(N90-M99) -> 30
A100: Electricity | B100: PJ | C100: =C91 -> 0 | D100: =C100+'Tech Parameters'!$C$7*(D91-C100) -> 0 | E100: =D100+'Tech Parameters'!$C$7*(E91-D100) -> 0 | F100: =E100+'Tech Parameters'!$C$7*(F91-E100) -> 0 | G100: =F100+'Tech Parameters'!$C$7*(G91-F100) -> 0 | H100: =G100+'Tech Parameters'!$C$7*(H91-G100) -> 0 | I100: =H100+'Tech Parameters'!$C$7*(I91-H100) -> 0 | J100: =I100+'Tech Parameters'!$C$7*(J91-I100) -> 0 | K100: =J100+'Tech Parameters'!$C$7*(K91-J100) -> 0 | ... N100: =M100+'Tech Parameters'!$C$7*(N91-M100) -> 0
A101: RE generation | B101: PJ | C101: =C92 -> 400 | D101: =C101+'Tech Parameters'!$C$7*(D92-C101) -> 400 | E101: =D101+'Tech Parameters'!$C$7*(E92-D101) -> 400 | F101: =E101+'Tech Parameters'!$C$7*(F92-E101) -> 400 | G101: =F101+'Tech Parameters'!$C$7*(G92-F101) -> 400 | H101: =G101+'Tech Parameters'!$C$7*(H92-G101) -> 400 | I101: =H101+'Tech Parameters'!$C$7*(I92-H101) -> 400 | J101: =I101+'Tech Parameters'!$C$7*(J92-I101) -> 400 | K101: =J101+'Tech Parameters'!$C$7*(K92-J101) -> 400 | ... N101: =M101+'Tech Parameters'!$C$7*(N92-M101) -> 400
A103: ELECTRICITY GEN. — Emissions (MtCO2)
A104: Coal | B104: MtCO2 | C104: =C96*'Tech Parameters'!C24 -> 114 | D104: =D96*'Tech Parameters'!C24 -> 114 | E104: =E96*'Tech Parameters'!C24 -> 114 | F104: =F96*'Tech Parameters'!C24 -> 114 | G104: =G96*'Tech Parameters'!C24 -> 114 | H104: =H96*'Tech Parameters'!C24 -> 114 | I104: =I96*'Tech Parameters'!C24 -> 114 | J104: =J96*'Tech Parameters'!C24 -> 114 | K104: =K96*'Tech Parameters'!C24 -> 114 | L104: =L96*'Tech Parameters'!C24 -> 114 | M104: =M96*'Tech Parameters'!C24 -> 114 | N104: =N96*'Tech Parameters'!C24 -> 114
A105: Natural gas | B105: MtCO2 | C105: =C97*'Tech Parameters'!C25 -> 44.8 | D105: =D97*'Tech Parameters'!C25 -> 44.8 | E105: =E97*'Tech Parameters'!C25 -> 44.8 | F105: =F97*'Tech Parameters'!C25 -> 44.8 | G105: =G97*'Tech Parameters'!C25 -> 44.8 | H105: =H97*'Tech Parameters'!C25 -> 44.8 | I105: =I97*'Tech Parameters'!C25 -> 44.8 | J105: =J97*'Tech Parameters'!C25 -> 44.8 | K105: =K97*'Tech Parameters'!C25 -> 44.8 | L105: =L97*'Tech Parameters'!C25 -> 44.8 | M105: =M97*'Tech Parameters'!C25 -> 44.8 | N105: =N97*'Tech Parameters'!C25 -> 44.8
A106: Gasoline | B106: MtCO2 | C106: =C98*'Tech Parameters'!C26 -> 0 | D106: =D98*'Tech Parameters'!C26 -> 0 | E106: =E98*'Tech Parameters'!C26 -> 0 | F106: =F98*'Tech Parameters'!C26 -> 0 | G106: =G98*'Tech Parameters'!C26 -> 0 | H106: =H98*'Tech Parameters'!C26 -> 0 | I106: =I98*'Tech Parameters'!C26 -> 0 | J106: =J98*'Tech Parameters'!C26 -> 0 | K106: =K98*'Tech Parameters'!C26 -> 0 | L106: =L98*'Tech Parameters'!C26 -> 0 | M106: =M98*'Tech Parameters'!C26 -> 0 | N106: =N98*'Tech Parameters'!C26 -> 0
A107: Diesel | B107: MtCO2 | C107: =C99*'Tech Parameters'!C27 -> 2.22 | D107: =D99*'Tech Parameters'!C27 -> 2.22 | E107: =E99*'Tech Parameters'!C27 -> 2.22 | F107: =F99*'Tech Parameters'!C27 -> 2.22 | G107: =G99*'Tech Parameters'!C27 -> 2.22 | H107: =H99*'Tech Parameters'!C27 -> 2.22 | I107: =I99*'Tech Parameters'!C27 -> 2.22 | J107: =J99*'Tech Parameters'!C27 -> 2.22 | K107: =K99*'Tech Parameters'!C27 -> 2.22 | L107: =L99*'Tech Parameters'!C27 -> 2.22 | M107: =M99*'Tech Parameters'!C27 -> 2.22 | N107: =N99*'Tech Parameters'!C27 -> 2.22
A108: Electricity | B108: MtCO2 | C108: =C100*'Tech Parameters'!C28 -> 0 | D108: =D100*'Tech Parameters'!C28 -> 0 | E108: =E100*'Tech Parameters'!C28 -> 0 | F108: =F100*'Tech Parameters'!C28 -> 0 | G108: =G100*'Tech Parameters'!C28 -> 0 | H108: =H100*'Tech Parameters'!C28 -> 0 | I108: =I100*'Tech Parameters'!C28 -> 0 | J108: =J100*'Tech Parameters'!C28 -> 0 | K108: =K100*'Tech Parameters'!C28 -> 0 | L108: =L100*'Tech Parameters'!C28 -> 0 | M108: =M100*'Tech Parameters'!C28 -> 0 | N108: =N100*'Tech Parameters'!C28 -> 0
A109: RE generation | B109: MtCO2 | C109: =C101*'Tech Parameters'!C29 -> 0 | D109: =D101*'Tech Parameters'!C29 -> 0 | E109: =E101*'Tech Parameters'!C29 -> 0 | F109: =F101*'Tech Parameters'!C29 -> 0 | G109: =G101*'Tech Parameters'!C29 -> 0 | H109: =H101*'Tech Parameters'!C29 -> 0 | I109: =I101*'Tech Parameters'!C29 -> 0 | J109: =J101*'Tech Parameters'!C29 -> 0 | K109: =K101*'Tech Parameters'!C29 -> 0 | L109: =L101*'Tech Parameters'!C29 -> 0 | M109: =M101*'Tech Parameters'!C29 -> 0 | N109: =N101*'Tech Parameters'!C29 -> 0
A110: TOTAL ELECTRICITY GEN. EMISSIONS | B110: MtCO2 | C110: =SUM(C104:C109) -> 161.02 | D110: =SUM(D104:D109) -> 161.02 | E110: =SUM(E104:E109) -> 161.02 | F110: =SUM(F104:F109) -> 161.02 | G110: =SUM(G104:G109) -> 161.02 | H110: =SUM(H104:H109) -> 161.02 | I110: =SUM(I104:I109) -> 161.02 | J110: =SUM(J104:J109) -> 161.02 | ... N110: =SUM(N104:N109) -> 161.02
A111: TOTAL ELECTRICITY GEN. ENERGY | B111: PJ | C111: =SUM(C96:C101) -> 2430 | D111: =SUM(D96:D101) -> 2430 | E111: =SUM(E96:E101) -> 2430 | F111: =SUM(F96:F101) -> 2430 | G111: =SUM(G96:G101) -> 2430 | H111: =SUM(H96:H101) -> 2430 | I111: =SUM(I96:I101) -> 2430 | J111: =SUM(J96:J101) -> 2430 | ... N111: =SUM(N96:N101) -> 2430
A114: ECONOMY-WIDE TOTALS
A115: Total emissions | B115: MtCO2 | C115: =C55+C110 -> 243.71 | D115: =D55+D110 -> 243.71 | E115: =E55+E110 -> 243.71 | F115: =F55+F110 -> 243.71 | G115: =G55+G110 -> 243.71 | H115: =H55+H110 -> 243.71 | I115: =I55+I110 -> 243.71 | J115: =J55+J110 -> 243.71 | ... N115: =N55+N110 -> 243.71
A116: Total energy | B116: PJ | C116: =C56+C111 -> 3655 | D116: =D56+D111 -> 3655 | E116: =E56+E111 -> 3655 | F116: =F56+F111 -> 3655 | G116: =G56+G111 -> 3655 | H116: =H56+H111 -> 3655 | I116: =I56+I111 -> 3655 | J116: =J56+J111 -> 3655 | ... N116: =N56+N111 -> 3655

Sheet Policy
A1: Partial Adjustment Model — Policy
B3: Unit | C3: 2024 | D3: 2025 | E3: 2026 | F3: 2027 | G3: 2028 | H3: 2029 | I3: 2030 | J3: 2031 | K3: 2032 | L3: 2033 | M3: 2034 | N3: 2035
A4: ROAD TRANSPORT — Fuel Prices ($/GJ)
A5: Coal | B5: $/GJ | C5: =Baseline!C5+Dashboard!B21*'Tech Parameters'!C11+Dashboard!B22*('Tech Parameters'!C11-('Tech Parameters'!H11*'Tech Parameters'!C11+'Tech Parameters'!H12*'Tech Parameters'!C12+'Tech Parameters'!H13*'Tech Parameters'!C13+'Tech Parameters'!H14*'Tech Parameters'!C14+'Tech Parameters'!H15*'Tech Parameters'!C15+'Tech Parameters'!H16*'Tech Parameters'!C16))+Dashboard!B25 -> 0 | D5: =Baseline!D5+Dashboard!C21*'Tech Parameters'!C11+Dashboard!C22*('Tech Parameters'!C11-('Tech Parameters'!H11*'Tech Parameters'!C11+'Tech Parameters'!H12*'Tech Parameters'!C12+'Tech Parameters'!H13*'Tech Parameters'!C13+'Tech Parameters'!H14*'Tech Parameters'!C14+'Tech Parameters'!H15*'Tech Parameters'!C15+'Tech Parameters'!H16*'Tech Parameters'!C16))+Dashboard!C25 -> 0 | E5: =Baseline!E5+Dashboard!D21*'Tech Parameters'!C11+Dashboard!D22*('Tech Parameters'!C11-('Tech Parameters'!H11*'Tech Parameters'!C11+'Tech Parameters'!H12*'Tech Parameters'!C12+'Tech Parameters'!H13*'Tech Parameters'!C13+'Tech Parameters'!H14*'Tech Parameters'!C14+'Tech Parameters'!H15*'Tech Parameters'!C15+'Tech Parameters'!H16*'Tech Parameters'!C16))+Dashboard!D25 -> 1.5833333 | F5: =Baseline!F5+Dashboard!E21*'Tech Parameters'!C11+Dashboard!E22*('Tech Parameters'!C11-('Tech Parameters'!H11*'Tech Parameters'!C11+'Tech Parameters'!H12*'Tech Parameters'!C12+'Tech Parameters'!H13*'Tech Parameters'!C13+'Tech Parameters'!H14*'Tech Parameters'!C14+'Tech Parameters'!H15*'Tech Parameters'!C15+'Tech Parameters'!H16*'Tech Parameters'!C16))+Dashboard!E25 -> 3.3041565 | G5: =Baseline!G5+Dashboard!F21*'Tech Parameters'!C11+Dashboard!F22*('Tech Parameters'!C11-('Tech Parameters'!H11*'Tech Parameters'!C11+'Tech Parameters'!H12*'Tech Parameters'!C12+'Tech Parameters'!H13*'Tech Parameters'!C13+'Tech Parameters'!H14*'Tech Parameters'!C14+'Tech Parameters'!H15*'Tech Parameters'!C15+'Tech Parameters'!H16*'Tech Parameters'!C16))+Dashboard!F25 -> 5.0249796 | H5: =Baseline!H5+Dashboard!G21*'Tech Parameters'!C11+Dashboard!G22*('Tech Parameters'!C11-('Tech Parameters'!H11*'Tech Parameters'!C11+'Tech Parameters'!H12*'Tech Parameters'!C12+'Tech Parameters'!H13*'Tech Parameters'!C13+'Tech Parameters'!H14*'Tech Parameters'!C14+'Tech Parameters'!H15*'Tech Parameters'!C15+'Tech Parameters'!H16*'Tech Parameters'!C16))+Dashboard!G25 -> 5.1624694 | I5: =Baseline!I5+Dashboard!H21*'Tech Parameters'!C11+Dashboard!H22*('Tech Parameters'!C11-('Tech Parameters'!H11*'Tech Parameters'!C11+'Tech Parameters'!H12*'Tech Parameters'!C12+'Tech Parameters'!H13*'Tech Parameters'!C13+'Tech Parameters'!H14*'Tech Parameters'!C14+'Tech Parameters'!H15*'Tech Parameters'!C15+'Tech Parameters'!H16*'Tech Parameters'!C16))+Dashboard!H25 -> 5.2999592 | J5: =Baseline!J5+Dashboard!I21*'Tech Parameters'!C11+Dashboard!I22*('Tech Parameters'!C11-('Tech Parameters'!H11*'Tech Parameters'!C11+'Tech Parameters'!H12*'Tech Parameters'!C12+'Tech Parameters'!H13*'Tech Parameters'!C13+'Tech Parameters'!H14*'Tech Parameters'!C14+'Tech Parameters'!H15*'Tech Parameters'!C15+'Tech Parameters'!H16*'Tech Parameters'!C16))+Dashboard!I25 -> 5.2999592 | K5: =Baseline!K5+Dashboard!J21*'Tech Parameters'!C11+Dashboard!J22*('Tech Parameters'!C11-('Tech Parameters'!H11*'Tech Parameters'!C11+'Tech Parameters'!H12*'Tech Parameters'!C12+'Tech Parameters'!H13*'Tech Parameters'!C13+'Tech Parameters'!H14*'Tech Parameters'!C14+'Tech Parameters'!H15*'Tech Parameters'!C15+'Tech Parameters'!H16*'Tech Parameters'!C16))+Dashboard!J25 -> 5.2999592 | L5: =Baseline!L5+Dashboard!K21*'Tech Parameters'!C11+Dashboard!K22*('Tech Parameters'!C11-('Tech Parameters'!H11*'Tech Parameters'!C11+'Tech Parameters'!H12*'Tech Parameters'!C12+'Tech Parameters'!H13*'Tech Parameters'!C13+'Tech Parameters'!H14*'Tech Parameters'!C14+'Tech Parameters'!H15*'Tech Parameters'!C15+'Tech Parameters'!H16*'Tech Parameters'!C16))+Dashboard!K25 -> 5.2999592 | M5: =Baseline!M5+Dashboard!L21*'Tech Parameters'!C11+Dashboard!L22*('Tech Parameters'!C11-('Tech Parameters'!H11*'Tech Parameters'!C11+'Tech Parameters'!H12*'Tech Parameters'!C12+'Tech Parameters'!H13*'Tech Parameters'!C13+'Tech Parameters'!H14*'Tech Parameters'!C14+'Tech Parameters'!H15*'Tech Parameters'!C15+'Tech Parameters'!H16*'Tech Parameters'!C16))+Dashboard!L25 -> 5.2999592 | N5: =Baseline!N5+Dashboard!M21*'Tech Parameters'!C11+Dashboard!M22*('Tech Parameters'!C11-('Tech Parameters'!H11*'Tech Parameters'!C11+'Tech Parameters'!H12*'Tech Parameters'!C12+'Tech Parameters'!H13*'Tech Parameters'!C13+'Tech Parameters'!H14*'Tech Parameters'!C14+'Tech Parameters'!H15*'Tech Parameters'!C15+'Tech Parameters'!H16*'Tech Parameters'!C16))+Dashboard!M25 -> 5.2999592
A6: Natural gas | B6: $/GJ | C6: =Baseline!C6+Dashboard!B21*'Tech Parameters'!C12+Dashboard!B22*('Tech Parameters'!C12-('Tech Parameters'!H11*'Tech Parameters'!C11+'Tech Parameters'!H12*'Tech Parameters'!C12+'Tech Parameters'!H13*'Tech Parameters'!C13+'Tech Parameters'!H14*'Tech Parameters'!C14+'Tech Parameters'!H15*'Tech Parameters'!C15+'Tech Parameters'!H16*'Tech Parameters'!C16))+Dashboard!B26 -> 8 | D6: =Baseline!D6+Dashboard!C21*'Tech Parameters'!C12+Dashboard!C22*('Tech Parameters'!C12-('Tech Parameters'!H11*'Tech Parameters'!C11+'Tech Parameters'!H12*'Tech Parameters'!C12+'Tech Parameters'!H13*'Tech Parameters'!C13+'Tech Parameters'!H14*'Tech Parameters'!C14+'Tech Parameters'!H15*'Tech Parameters'!C15+'Tech Parameters'!H16*'Tech Parameters'!C16))+Dashboard!C26 -> 8 | E6: =Baseline!E6+Dashboard!D21*'Tech Parameters'!C12+Dashboard!D22*('Tech Parameters'!C12-('Tech Parameters'!H11*'Tech Parameters'!C11+'Tech Parameters'!H12*'Tech Parameters'!C12+'Tech Parameters'!H13*'Tech Parameters'!C13+'Tech Parameters'!H14*'Tech Parameters'!C14+'Tech Parameters'!H15*'Tech Parameters'!C15+'Tech Parameters'!H16*'Tech Parameters'!C16))+Dashboard!D26 -> 8.9333333 | F6: =Baseline!F6+Dashboard!E21*'Tech Parameters'!C12+Dashboard!E22*('Tech Parameters'!C12-('Tech Parameters'!H11*'Tech Parameters'!C11+'Tech Parameters'!H12*'Tech Parameters'!C12+'Tech Parameters'!H13*'Tech Parameters'!C13+'Tech Parameters'!H14*'Tech Parameters'!C14+'Tech Parameters'!H15*'Tech Parameters'!C15+'Tech Parameters'!H16*'Tech Parameters'!C16))+Dashboard!E26 -> 9.8091565 | G6: =Baseline!G6+Dashboard!F21*'Tech Parameters'!C12+Dashboard!F22*('Tech Parameters'!C12-('Tech Parameters'!H11*'Tech Parameters'!C11+'Tech Parameters'!H12*'Tech Parameters'!C12+'Tech Parameters'!H13*'Tech Parameters'!C13+'Tech Parameters'!H14*'Tech Parameters'!C14+'Tech Parameters'!H15*'Tech Parameters'!C15+'Tech Parameters'!H16*'Tech Parameters'!C16))+Dashboard!F26 -> 10.68498 | H6: =Baseline!H6+Dashboard!G21*'Tech Parameters'!C12+Dashboard!G22*('Tech Parameters'!C12-('Tech Parameters'!H11*'Tech Parameters'!C11+'Tech Parameters'!H12*'Tech Parameters'!C12+'Tech Parameters'!H13*'Tech Parameters'!C13+'Tech Parameters'!H14*'Tech Parameters'!C14+'Tech Parameters'!H15*'Tech Parameters'!C15+'Tech Parameters'!H16*'Tech Parameters'!C16))+Dashboard!G26 -> 10.627469 | I6: =Baseline!I6+Dashboard!H21*'Tech Parameters'!C12+Dashboard!H22*('Tech Parameters'!C12-('Tech Parameters'!H11*'Tech Parameters'!C11+'Tech Parameters'!H12*'Tech Parameters'!C12+'Tech Parameters'!H13*'Tech Parameters'!C13+'Tech Parameters'!H14*'Tech Parameters'!C14+'Tech Parameters'!H15*'Tech Parameters'!C15+'Tech Parameters'!H16*'Tech Parameters'!C16))+Dashboard!H26 -> 10.569959 | J6: =Baseline!J6+Dashboard!I21*'Tech Parameters'!C12+Dashboard!I22*('Tech Parameters'!C12-('Tech Parameters'!H11*'Tech Parameters'!C11+'Tech Parameters'!H12*'Tech Parameters'!C12+'Tech Parameters'!H13*'Tech Parameters'!C13+'Tech Parameters'!H14*'Tech Parameters'!C14+'Tech Parameters'!H15*'Tech Parameters'!C15+'Tech Parameters'!H16*'Tech Parameters'!C16))+Dashboard!I26 -> 10.569959 | K6: =Baseline!K6+Dashboard!J21*'Tech Parameters'!C12+Dashboard!J22*('Tech Parameters'!C12-('Tech Parameters'!H11*'Tech Parameters'!C11+'Tech Parameters'!H12*'Tech Parameters'!C12+'Tech Parameters'!H13*'Tech Parameters'!C13+'Tech Parameters'!H14*'Tech Parameters'!C14+'Tech Parameters'!H15*'Tech Parameters'!C15+'Tech Parameters'!H16*'Tech Parameters'!C16))+Dashboard!J26 -> 10.569959 | L6: =Baseline!L6+Dashboard!K21*'Tech Parameters'!C12+Dashboard!K22*('Tech Parameters'!C12-('Tech Parameters'!H11*'Tech Parameters'!C11+'Tech Parameters'!H12*'Tech Parameters'!C12+'Tech Parameters'!H13*'Tech Parameters'!C13+'Tech Parameters'!H14*'Tech Parameters'!C14+'Tech Parameters'!H15*'Tech Parameters'!C15+'Tech Parameters'!H16*'Tech Parameters'!C16))+Dashboard!K26 -> 10.569959 | M6: =Baseline!M6+Dashboard!L21*'Tech Parameters'!C12+Dashboard!L22*('Tech Parameters'!C12-('Tech Parameters'!H11*'Tech Parameters'!C11+'Tech Parameters'!H12*'Tech Parameters'!C12+'Tech Parameters'!H13*'Tech Parameters'!C13+'Tech Parameters'!H14*'Tech Parameters'!C14+'Tech Parameters'!H15*'Tech Parameters'!C15+'Tech Parameters'!H16*'Tech Parameters'!C16))+Dashboard!L26 -> 10.569959 | N6: =Baseline!N6+Dashboard!M21*'Tech Parameters'!C12+Dashboard!M22*('Tech Parameters'!C12-('Tech Parameters'!H11*'Tech Parameters'!C11+'Tech Parameters'!H12*'Tech Parameters'!C12+'Tech Parameters'!H13*'Tech Parameters'!C13+'Tech Parameters'!H14*'Tech Parameters'!C14+'Tech Parameters'!H15*'Tech Parameters'!C15+'Tech Parameters'!H16*'Tech Parameters'!C16))+Dashboard!M26 -> 10.569959
A7: Gasoline | B7: $/GJ | C7: =Baseline!C7+Dashboard!B21*'Tech Parameters'!C13+Dashboard!B22*('Tech Parameters'!C13-('Tech Parameters'!H11*'Tech Parameters'!C11+'Tech Parameters'!H12*'Tech Parameters'!C12+'Tech Parameters'!H13*'Tech Parameters'!C13+'Tech Parameters'!H14*'Tech Parameters'!C14+'Tech Parameters'!H15*'Tech Parameters'!C15+'Tech Parameters'!H16*'Tech Parameters'!C16))+Dashboard!B27 -> 18 | D7: =Baseline!D7+Dashboard!C21*'Tech Parameters'!C13+Dashboard!C22*('Tech Parameters'!C13-('Tech Parameters'!H11*'Tech Parameters'!C11+'Tech Parameters'!H12*'Tech Parameters'!C12+'Tech Parameters'!H13*'Tech Parameters'!C13+'Tech Parameters'!H14*'Tech Parameters'!C14+'Tech Parameters'!H15*'Tech Parameters'!C15+'Tech Parameters'!H16*'Tech Parameters'!C16))+Dashboard!C27 -> 18 | E7: =Baseline!E7+Dashboard!D21*'Tech Parameters'!C13+Dashboard!D22*('Tech Parameters'!C13-('Tech Parameters'!H11*'Tech Parameters'!C11+'Tech Parameters'!H12*'Tech Parameters'!C12+'Tech Parameters'!H13*'Tech Parameters'!C13+'Tech Parameters'!H14*'Tech Parameters'!C14+'Tech Parameters'!H15*'Tech Parameters'!C15+'Tech Parameters'!H16*'Tech Parameters'!C16))+Dashboard!D27 -> 20.816667 | F7: =Baseline!F7+Dashboard!E21*'Tech Parameters'!C13+Dashboard!E22*('Tech Parameters'!C13-('Tech Parameters'!H11*'Tech Parameters'!C11+'Tech Parameters'!H12*'Tech Parameters'!C12+'Tech Parameters'!H13*'Tech Parameters'!C13+'Tech Parameters'!H14*'Tech Parameters'!C14+'Tech Parameters'!H15*'Tech Parameters'!C15+'Tech Parameters'!H16*'Tech Parameters'!C16))+Dashboard!E27 -> 23.640823 | G7: =Baseline!G7+Dashboard!F21*'Tech Parameters'!C13+Dashboard!F22*('Tech Parameters'!C13-('Tech Parameters'!H11*'Tech Parameters'!C11+'Tech Parameters'!H12*'Tech Parameters'!C12+'Tech Parameters'!H13*'Tech Parameters'!C13+'Tech Parameters'!H14*'Tech Parameters'!C14+'Tech Parameters'!H15*'Tech Parameters'!C15+'Tech Parameters'!H16*'Tech Parameters'!C16))+Dashboard!F27 -> 26.46498 | H7: =Baseline!H7+Dashboard!G21*'Tech Parameters'!C13+Dashboard!G22*('Tech Parameters'!C13-('Tech Parameters'!H11*'Tech Parameters'!C11+'Tech Parameters'!H12*'Tech Parameters'!C12+'Tech Parameters'!H13*'Tech Parameters'!C13+'Tech Parameters'!H14*'Tech Parameters'!C14+'Tech Parameters'!H15*'Tech Parameters'!C15+'Tech Parameters'!H16*'Tech Parameters'!C16))+Dashboard!G27 -> 26.472469 | I7: =Baseline!I7+Dashboard!H21*'Tech Parameters'!C13+Dashboard!H22*('Tech Parameters'!C13-('Tech Parameters'!H11*'Tech Parameters'!C11+'Tech Parameters'!H12*'Tech Parameters'!C12+'Tech Parameters'!H13*'Tech Parameters'!C13+'Tech Parameters'!H14*'Tech Parameters'!C14+'Tech Parameters'!H15*'Tech Parameters'!C15+'Tech Parameters'!H16*'Tech Parameters'!C16))+Dashboard!H27 -> 26.479959 | J7: =Baseline!J7+Dashboard!I21*'Tech Parameters'!C13+Dashboard!I22*('Tech Parameters'!C13-('Tech Parameters'!H11*'Tech Parameters'!C11+'Tech Parameters'!H12*'Tech Parameters'!C12+'Tech Parameters'!H13*'Tech Parameters'!C13+'Tech Parameters'!H14*'Tech Parameters'!C14+'Tech Parameters'!H15*'Tech Parameters'!C15+'Tech Parameters'!H16*'Tech Parameters'!C16))+Dashboard!I27 -> 26.479959 | K7: =Baseline!K7+Dashboard!J21*'Tech Parameters'!C13+Dashboard!J22*('Tech Parameters'!C13-('Tech Parameters'!H11*'Tech Parameters'!C11+'Tech Parameters'!H12*'Tech Parameters'!C12+'Tech Parameters'!H13*'Tech Parameters'!C13+'Tech Parameters'!H14*'Tech Parameters'!C14+'Tech Parameters'!H15*'Tech Parameters'!C15+'Tech Parameters'!H16*'Tech Parameters'!C16))+Dashboard!J27 -> 26.479959 | L7: =Baseline!L7+Dashboard!K21*'Tech Parameters'!C13+Dashboard!K22*('Tech Parameters'!C13-('Tech Parameters'!H11*'Tech Parameters'!C11+'Tech Parameters'!H12*'Tech Parameters'!C12+'Tech Parameters'!H13*'Tech Parameters'!C13+'Tech Parameters'!H14*'Tech Parameters'!C14+'Tech Parameters'!H15*'Tech Parameters'!C15+'Tech Parameters'!H16*'Tech Parameters'!C16))+Dashboard!K27 -> 26.479959 | M7: =Baseline!M7+Dashboard!L21*'Tech Parameters'!C13+Dashboard!L22*('Tech Parameters'!C13-('Tech Parameters'!H11*'Tech Parameters'!C11+'Tech Parameters'!H12*'Tech Parameters'!C12+'Tech Parameters'!H13*'Tech Parameters'!C13+'Tech Parameters'!H14*'Tech Parameters'!C14+'Tech Parameters'!H15*'Tech Parameters'!C15+'Tech Parameters'!H16*'Tech Parameters'!C16))+Dashboard!L27 -> 26.479959 | N7: =Baseline!N7+Dashboard!M21*'Tech Parameters'!C13+Dashboard!M22*('Tech Parameters'!C13-('Tech Parameters'!H11*'Tech Parameters'!C11+'Tech Parameters'!H12*'Tech Parameters'!C12+'Tech Parameters'!H13*'Tech Parameters'!C13+'Tech Parameters'!H14*'Tech Parameters'!C14+'Tech Parameters'!H15*'Tech Parameters'!C15+'Tech Parameters'!H16*'Tech Parameters'!C16))+Dashboard!M27 -> 26.479959
A8: Diesel | B8: $/GJ | C8: =Baseline!C8+Dashboard!B21*'Tech Parameters'!C14+Dashboard!B22*('Tech Parameters'!C14-('Tech Parameters'!H11*'Tech Parameters'!C11+'Tech Parameters'!H12*'Tech Parameters'!C12+'Tech Parameters'!H13*'Tech Parameters'!C13+'Tech Parameters'!H14*'Tech Parameters'!C14+'Tech Parameters'!H15*'Tech Parameters'!C15+'Tech Parameters'!H16*'Tech Parameters'!C16))+Dashboard!B28 -> 17 | D8: =Baseline!D8+Dashboard!C21*'Tech Parameters'!C14+Dashboard!C22*('Tech Parameters'!C14-('Tech Parameters'!H11*'Tech Parameters'!C11+'Tech Parameters'!H12*'Tech Parameters'!C12+'Tech Parameters'!H13*'Tech Parameters'!C13+'Tech Parameters'!H14*'Tech Parameters'!C14+'Tech Parameters'!H15*'Tech Parameters'!C15+'Tech Parameters'!H16*'Tech Parameters'!C16))+Dashboard!C28 -> 17 | E8: =Baseline!E8+Dashboard!D21*'Tech Parameters'!C14+Dashboard!D22*('Tech Parameters'!C14-('Tech Parameters'!H11*'Tech Parameters'!C11+'Tech Parameters'!H12*'Tech Parameters'!C12+'Tech Parameters'!H13*'Tech Parameters'!C13+'Tech Parameters'!H14*'Tech Parameters'!C14+'Tech Parameters'!H15*'Tech Parameters'!C15+'Tech Parameters'!H16*'Tech Parameters'!C16))+Dashboard!D28 -> 19.566667 | F8: =Baseline!F8+Dashboard!E21*'Tech Parameters'!C14+Dashboard!E22*('Tech Parameters'!C14-('Tech Parameters'!H11*'Tech Parameters'!C11+'Tech Parameters'!H12*'Tech Parameters'!C12+'Tech Parameters'!H13*'Tech Parameters'!C13+'Tech Parameters'!H14*'Tech Parameters'!C14+'Tech Parameters'!H15*'Tech Parameters'!C15+'Tech Parameters'!H16*'Tech Parameters'!C16))+Dashboard!E28 -> 22.165823 | G8: =Baseline!G8+Dashboard!F21*'Tech Parameters'!C14+Dashboard!F22*('Tech Parameters'!C14-('Tech Parameters'!H11*'Tech Parameters'!C11+'Tech Parameters'!H12*'Tech Parameters'!C12+'Tech Parameters'!H13*'Tech Parameters'!C13+'Tech Parameters'!H14*'Tech Parameters'!C14+'Tech Parameters'!H15*'Tech Parameters'!C15+'Tech Parameters'!H16*'Tech Parameters'!C16))+Dashboard!F28 -> 24.76498 | H8: =Baseline!H8+Dashboard!G21*'Tech Parameters'!C14+Dashboard!G22*('Tech Parameters'!C14-('Tech Parameters'!H11*'Tech Parameters'!C11+'Tech Parameters'!H12*'Tech Parameters'!C12+'Tech Parameters'!H13*'Tech Parameters'!C13+'Tech Parameters'!H14*'Tech Parameters'!C14+'Tech Parameters'!H15*'Tech Parameters'!C15+'Tech Parameters'!H16*'Tech Parameters'!C16))+Dashboard!G28 -> 24.797469 | I8: =Baseline!I8+Dashboard!H21*'Tech Parameters'!C14+Dashboard!H22*('Tech Parameters'!C14-('Tech Parameters'!H11*'Tech Parameters'!C11+'Tech Parameters'!H12*'Tech Parameters'!C12+'Tech Parameters'!H13*'Tech Parameters'!C13+'Tech Parameters'!H14*'Tech Parameters'!C14+'Tech Parameters'!H15*'Tech Parameters'!C15+'Tech Parameters'!H16*'Tech Parameters'!C16))+Dashboard!H28 -> 24.829959 | J8: =Baseline!J8+Dashboard!I21*'Tech Parameters'!C14+Dashboard!I22*('Tech Parameters'!C14-('Tech Parameters'!H11*'Tech Parameters'!C11+'Tech Parameters'!H12*'Tech Parameters'!C12+'Tech Parameters'!H13*'Tech Parameters'!C13+'Tech Parameters'!H14*'Tech Parameters'!C14+'Tech Parameters'!H15*'Tech Parameters'!C15+'Tech Parameters'!H16*'Tech Parameters'!C16))+Dashboard!I28 -> 24.829959 | K8: =Baseline!K8+Dashboard!J21*'Tech Parameters'!C14+Dashboard!J22*('Tech Parameters'!C14-('Tech Parameters'!H11*'Tech Parameters'!C11+'Tech Parameters'!H12*'Tech Parameters'!C12+'Tech Parameters'!H13*'Tech Parameters'!C13+'Tech Parameters'!H14*'Tech Parameters'!C14+'Tech Parameters'!H15*'Tech Parameters'!C15+'Tech Parameters'!H16*'Tech Parameters'!C16))+Dashboard!J28 -> 24.829959 | L8: =Baseline!L8+Dashboard!K21*'Tech Parameters'!C14+Dashboard!K22*('Tech Parameters'!C14-('Tech Parameters'!H11*'Tech Parameters'!C11+'Tech Parameters'!H12*'Tech Parameters'!C12+'Tech Parameters'!H13*'Tech Parameters'!C13+'Tech Parameters'!H14*'Tech Parameters'!C14+'Tech Parameters'!H15*'Tech Parameters'!C15+'Tech Parameters'!H16*'Tech Parameters'!C16))+Dashboard!K28 -> 24.829959 | M8: =Baseline!M8+Dashboard!L21*'Tech Parameters'!C14+Dashboard!L22*('Tech Parameters'!C14-('Tech Parameters'!H11*'Tech Parameters'!C11+'Tech Parameters'!H12*'Tech Parameters'!C12+'Tech Parameters'!H13*'Tech Parameters'!C13+'Tech Parameters'!H14*'Tech Parameters'!C14+'Tech Parameters'!H15*'Tech Parameters'!C15+'Tech Parameters'!H16*'Tech Parameters'!C16))+Dashboard!L28 -> 24.829959 | N8: =Baseline!N8+Dashboard!M21*'Tech Parameters'!C14+Dashboard!M22*('Tech Parameters'!C14-('Tech Parameters'!H11*'Tech Parameters'!C11+'Tech Parameters'!H12*'Tech Parameters'!C12+'Tech Parameters'!H13*'Tech Parameters'!C13+'Tech Parameters'!H14*'Tech Parameters'!C14+'Tech Parameters'!H15*'Tech Parameters'!C15+'Tech Parameters'!H16*'Tech Parameters'!C16))+Dashboard!M28 -> 24.829959
A9: Electricity | B9: $/GJ | C9: =Baseline!C9+Dashboard!B21*'Tech Parameters'!C15+Dashboard!B22*('Tech Parameters'!C15-('Tech Parameters'!H11*'Tech Parameters'!C11+'Tech Parameters'!H12*'Tech Parameters'!C12+'Tech Parameters'!H13*'Tech Parameters'!C13+'Tech Parameters'!H14*'Tech Parameters'!C14+'Tech Parameters'!H15*'Tech Parameters'!C15+'Tech Parameters'!H16*'Tech Parameters'!C16))+Dashboard!B29 -> 22 | D9: =Baseline!D9+Dashboard!C21*'Tech Parameters'!C15+Dashboard!C22*('Tech Parameters'!C15-('Tech Parameters'!H11*'Tech Parameters'!C11+'Tech Parameters'!H12*'Tech Parameters'!C12+'Tech Parameters'!H13*'Tech Parameters'!C13+'Tech Parameters'!H14*'Tech Parameters'!C14+'Tech Parameters'!H15*'Tech Parameters'!C15+'Tech Parameters'!H16*'Tech Parameters'!C16))+Dashboard!C29 -> 22 | E9: =Baseline!E9+Dashboard!D21*'Tech Parameters'!C15+Dashboard!D22*('Tech Parameters'!C15-('Tech Parameters'!H11*'Tech Parameters'!C11+'Tech Parameters'!H12*'Tech Parameters'!C12+'Tech Parameters'!H13*'Tech Parameters'!C13+'Tech Parameters'!H14*'Tech Parameters'!C14+'Tech Parameters'!H15*'Tech Parameters'!C15+'Tech Parameters'!H16*'Tech Parameters'!C16))+Dashboard!D29 -> 22 | F9: =Baseline!F9+Dashboard!E21*'Tech Parameters'!C15+Dashboard!E22*('Tech Parameters'!C15-('Tech Parameters'!H11*'Tech Parameters'!C11+'Tech Parameters'!H12*'Tech Parameters'!C12+'Tech Parameters'!H13*'Tech Parameters'!C13+'Tech Parameters'!H14*'Tech Parameters'!C14+'Tech Parameters'!H15*'Tech Parameters'!C15+'Tech Parameters'!H16*'Tech Parameters'!C16))+Dashboard!E29 -> 21.66249 | G9: =Baseline!G9+Dashboard!F21*'Tech Parameters'!C15+Dashboard!F22*('Tech Parameters'!C15-('Tech Parameters'!H11*'Tech Parameters'!C11+'Tech Parameters'!H12*'Tech Parameters'!C12+'Tech Parameters'!H13*'Tech Parameters'!C13+'Tech Parameters'!H14*'Tech Parameters'!C14+'Tech Parameters'!H15*'Tech Parameters'!C15+'Tech Parameters'!H16*'Tech Parameters'!C16))+Dashboard!F29 -> 21.32498 | H9: =Baseline!H9+Dashboard!G21*'Tech Parameters'!C15+Dashboard!G22*('Tech Parameters'!C15-('Tech Parameters'!H11*'Tech Parameters'!C11+'Tech Parameters'!H12*'Tech Parameters'!C12+'Tech Parameters'!H13*'Tech Parameters'!C13+'Tech Parameters'!H14*'Tech Parameters'!C14+'Tech Parameters'!H15*'Tech Parameters'!C15+'Tech Parameters'!H16*'Tech Parameters'!C16))+Dashboard!G29 -> 20.987469 | I9: =Baseline!I9+Dashboard!H21*'Tech Parameters'!C15+Dashboard!H22*('Tech Parameters'!C15-('Tech Parameters'!H11*'Tech Parameters'!C11+'Tech Parameters'!H12*'Tech Parameters'!C12+'Tech Parameters'!H13*'Tech Parameters'!C13+'Tech Parameters'!H14*'Tech Parameters'!C14+'Tech Parameters'!H15*'Tech Parameters'!C15+'Tech Parameters'!H16*'Tech Parameters'!C16))+Dashboard!H29 -> 20.649959 | J9: =Baseline!J9+Dashboard!I21*'Tech Parameters'!C15+Dashboard!I22*('Tech Parameters'!C15-('Tech Parameters'!H11*'Tech Parameters'!C11+'Tech Parameters'!H12*'Tech Parameters'!C12+'Tech Parameters'!H13*'Tech Parameters'!C13+'Tech Parameters'!H14*'Tech Parameters'!C14+'Tech Parameters'!H15*'Tech Parameters'!C15+'Tech Parameters'!H16*'Tech Parameters'!C16))+Dashboard!I29 -> 20.649959 | K9: =Baseline!K9+Dashboard!J21*'Tech Parameters'!C15+Dashboard!J22*('Tech Parameters'!C15-('Tech Parameters'!H11*'Tech Parameters'!C11+'Tech Parameters'!H12*'Tech Parameters'!C12+'Tech Parameters'!H13*'Tech Parameters'!C13+'Tech Parameters'!H14*'Tech Parameters'!C14+'Tech Parameters'!H15*'Tech Parameters'!C15+'Tech Parameters'!H16*'Tech Parameters'!C16))+Dashboard!J29 -> 20.649959 | L9: =Baseline!L9+Dashboard!K21*'Tech Parameters'!C15+Dashboard!K22*('Tech Parameters'!C15-('Tech Parameters'!H11*'Tech Parameters'!C11+'Tech Parameters'!H12*'Tech Parameters'!C12+'Tech Parameters'!H13*'Tech Parameters'!C13+'Tech Parameters'!H14*'Tech Parameters'!C14+'Tech Parameters'!H15*'Tech Parameters'!C15+'Tech Parameters'!H16*'Tech Parameters'!C16))+Dashboard!K29 -> 20.649959 | M9: =Baseline!M9+Dashboard!L21*'Tech Parameters'!C15+Dashboard!L22*('Tech Parameters'!C15-('Tech Parameters'!H11*'Tech Parameters'!C11+'Tech Parameters'!H12*'Tech Parameters'!C12+'Tech Parameters'!H13*'Tech Parameters'!C13+'Tech Parameters'!H14*'Tech Parameters'!C14+'Tech Parameters'!H15*'Tech Parameters'!C15+'Tech Parameters'!H16*'Tech Parameters'!C16))+Dashboard!L29 -> 20.649959 | N9: =Baseline!N9+Dashboard!M21*'Tech Parameters'!C15+Dashboard!M22*('Tech Parameters'!C15-('Tech Parameters'!H11*'Tech Parameters'!C11+'Tech Parameters'!H12*'Tech Parameters'!C12+'Tech Parameters'!H13*'Tech Parameters'!C13+'Tech Parameters'!H14*'Tech Parameters'!C14+'Tech Parameters'!H15*'Tech Parameters'!C15+'Tech Parameters'!H16*'Tech Parameters'!C16))+Dashboard!M29 -> 20.649959
A10: RE generation | B10: $/GJ | C10: =Baseline!C10+Dashboard!B21*'Tech Parameters'!C16+Dashboard!B22*('Tech Parameters'!C16-('Tech Parameters'!H11*'Tech Parameters'!C11+'Tech Parameters'!H12*'Tech Parameters'!C12+'Tech Parameters'!H13*'Tech Parameters'!C13+'Tech Parameters'!H14*'Tech Parameters'!C14+'Tech Parameters'!H15*'Tech Parameters'!C15+'Tech Parameters'!H16*'Tech Parameters'!C16))+Dashboard!B30 -> 0 | D10: =Baseline!D10+Dashboard!C21*'Tech Parameters'!C16+Dashboard!C22*('Tech Parameters'!C16-('Tech Parameters'!H11*'Tech Parameters'!C11+'Tech Parameters'!H12*'Tech Parameters'!C12+'Tech Parameters'!H13*'Tech Parameters'!C13+'Tech Parameters'!H14*'Tech Parameters'!C14+'Tech Parameters'!H15*'Tech Parameters'!C15+'Tech Parameters'!H16*'Tech Parameters'!C16))+Dashboard!C30 -> 0 | E10: =Baseline!E10+Dashboard!D21*'Tech Parameters'!C16+Dashboard!D22*('Tech Parameters'!C16-('Tech Parameters'!H11*'Tech Parameters'!C11+'Tech Parameters'!H12*'Tech Parameters'!C12+'Tech Parameters'!H13*'Tech Parameters'!C13+'Tech Parameters'!H14*'Tech Parameters'!C14+'Tech Parameters'!H15*'Tech Parameters'!C15+'Tech Parameters'!H16*'Tech Parameters'!C16))+Dashboard!D30 -> 0 | F10: =Baseline!F10+Dashboard!E21*'Tech Parameters'!C16+Dashboard!E22*('Tech Parameters'!C16-('Tech Parameters'!H11*'Tech Parameters'!C11+'Tech Parameters'!H12*'Tech Parameters'!C12+'Tech Parameters'!H13*'Tech Parameters'!C13+'Tech Parameters'!H14*'Tech Parameters'!C14+'Tech Parameters'!H15*'Tech Parameters'!C15+'Tech Parameters'!H16*'Tech Parameters'!C16))+Dashboard!E30 -> -0.3375102 | G10: =Baseline!G10+Dashboard!F21*'Tech Parameters'!C16+Dashboard!F22*('Tech Parameters'!C16-('Tech Parameters'!H11*'Tech Parameters'!C11+'Tech Parameters'!H12*'Tech Parameters'!C12+'Tech Parameters'!H13*'Tech Parameters'!C13+'Tech Parameters'!H14*'Tech Parameters'!C14+'Tech Parameters'!H15*'Tech Parameters'!C15+'Tech Parameters'!H16*'Tech Parameters'!C16))+Dashboard!F30 -> -0.67502041 | H10: =Baseline!H10+Dashboard!G21*'Tech Parameters'!C16+Dashboard!G22*('Tech Parameters'!C16-('Tech Parameters'!H11*'Tech Parameters'!C11+'Tech Parameters'!H12*'Tech Parameters'!C12+'Tech Parameters'!H13*'Tech Parameters'!C13+'Tech Parameters'!H14*'Tech Parameters'!C14+'Tech Parameters'!H15*'Tech Parameters'!C15+'Tech Parameters'!H16*'Tech Parameters'!C16))+Dashboard!G30 -> -1.0125306 | I10: =Baseline!I10+Dashboard!H21*'Tech Parameters'!C16+Dashboard!H22*('Tech Parameters'!C16-('Tech Parameters'!H11*'Tech Parameters'!C11+'Tech Parameters'!H12*'Tech Parameters'!C12+'Tech Parameters'!H13*'Tech Parameters'!C13+'Tech Parameters'!H14*'Tech Parameters'!C14+'Tech Parameters'!H15*'Tech Parameters'!C15+'Tech Parameters'!H16*'Tech Parameters'!C16))+Dashboard!H30 -> -1.3500408 | J10: =Baseline!J10+Dashboard!I21*'Tech Parameters'!C16+Dashboard!I22*('Tech Parameters'!C16-('Tech Parameters'!H11*'Tech Parameters'!C11+'Tech Parameters'!H12*'Tech Parameters'!C12+'Tech Parameters'!H13*'Tech Parameters'!C13+'Tech Parameters'!H14*'Tech Parameters'!C14+'Tech Parameters'!H15*'Tech Parameters'!C15+'Tech Parameters'!H16*'Tech Parameters'!C16))+Dashboard!I30 -> -1.3500408 | K10: =Baseline!K10+Dashboard!J21*'Tech Parameters'!C16+Dashboard!J22*('Tech Parameters'!C16-('Tech Parameters'!H11*'Tech Parameters'!C11+'Tech Parameters'!H12*'Tech Parameters'!C12+'Tech Parameters'!H13*'Tech Parameters'!C13+'Tech Parameters'!H14*'Tech Parameters'!C14+'Tech Parameters'!H15*'Tech Parameters'!C15+'Tech Parameters'!H16*'Tech Parameters'!C16))+Dashboard!J30 -> -1.3500408 | L10: =Baseline!L10+Dashboard!K21*'Tech Parameters'!C16+Dashboard!K22*('Tech Parameters'!C16-('Tech Parameters'!H11*'Tech Parameters'!C11+'Tech Parameters'!H12*'Tech Parameters'!C12+'Tech Parameters'!H13*'Tech Parameters'!C13+'Tech Parameters'!H14*'Tech Parameters'!C14+'Tech Parameters'!H15*'Tech Parameters'!C15+'Tech Parameters'!H16*'Tech Parameters'!C16))+Dashboard!K30 -> -1.3500408 | M10: =Baseline!M10+Dashboard!L21*'Tech Parameters'!C16+Dashboard!L22*('Tech Parameters'!C16-('Tech Parameters'!H11*'Tech Parameters'!C11+'Tech Parameters'!H12*'Tech Parameters'!C12+'Tech Parameters'!H13*'Tech Parameters'!C13+'Tech Parameters'!H14*'Tech Parameters'!C14+'Tech Parameters'!H15*'Tech Parameters'!C15+'Tech Parameters'!H16*'Tech Parameters'!C16))+Dashboard!L30 -> -1.3500408 | N10: =Baseline!N10+Dashboard!M21*'Tech Parameters'!C16+Dashboard!M22*('Tech Parameters'!C16-('Tech Parameters'!H11*'Tech Parameters'!C11+'Tech Parameters'!H12*'Tech Parameters'!C12+'Tech Parameters'!H13*'Tech Parameters'!C13+'Tech Parameters'!H14*'Tech Parameters'!C14+'Tech Parameters'!H15*'Tech Parameters'!C15+'Tech Parameters'!H16*'Tech Parameters'!C16))+Dashboard!M30 -> -1.3500408
A12: ROAD TRANSPORT — Effective Prices ($/GJ svc)
A13: Coal | B13: $/GJ svc | C13: =IF('Tech Parameters'!E11=0,0,C5/'Tech Parameters'!E11) -> 0 | D13: =IF('Tech Parameters'!E11=0,0,D5/'Tech Parameters'!E11) -> 0 | E13: =IF('Tech Parameters'!E11=0,0,E5/'Tech Parameters'!E11) -> 0 | F13: =IF('Tech Parameters'!E11=0,0,F5/'Tech Parameters'!E11) -> 0 | G13: =IF('Tech Parameters'!E11=0,0,G5/'Tech Parameters'!E11) -> 0 | H13: =IF('Tech Parameters'!E11=0,0,H5/'Tech Parameters'!E11) -> 0 | I13: =IF('Tech Parameters'!E11=0,0,I5/'Tech Parameters'!E11) -> 0 | J13: =IF('Tech Parameters'!E11=0,0,J5/'Tech Parameters'!E11) -> 0 | K13: =IF('Tech Parameters'!E11=0,0,K5/'Tech Parameters'!E11) -> 0 | L13: =IF('Tech Parameters'!E11=0,0,L5/'Tech Parameters'!E11) -> 0 | M13: =IF('Tech Parameters'!E11=0,0,M5/'Tech Parameters'!E11) -> 0 | N13: =IF('Tech Parameters'!E11=0,0,N5/'Tech Parameters'!E11) -> 0
A14: Natural gas | B14: $/GJ svc | C14: =IF('Tech Parameters'!E12=0,0,C6/'Tech Parameters'!E12) -> 32 | D14: =IF('Tech Parameters'!E12=0,0,D6/'Tech Parameters'!E12) -> 32 | E14: =IF('Tech Parameters'!E12=0,0,E6/'Tech Parameters'!E12) -> 35.733333 | F14: =IF('Tech Parameters'!E12=0,0,F6/'Tech Parameters'!E12) -> 39.236626 | G14: =IF('Tech Parameters'!E12=0,0,G6/'Tech Parameters'!E12) -> 42.739918 | H14: =IF('Tech Parameters'!E12=0,0,H6/'Tech Parameters'!E12) -> 42.509878 | I14: =IF('Tech Parameters'!E12=0,0,I6/'Tech Parameters'!E12) -> 42.279837 | J14: =IF('Tech Parameters'!E12=0,0,J6/'Tech Parameters'!E12) -> 42.279837 | K14: =IF('Tech Parameters'!E12=0,0,K6/'Tech Parameters'!E12) -> 42.279837 | L14: =IF('Tech Parameters'!E12=0,0,L6/'Tech Parameters'!E12) -> 42.279837 | M14: =IF('Tech Parameters'!E12=0,0,M6/'Tech Parameters'!E12) -> 42.279837 | N14: =IF('Tech Parameters'!E12=0,0,N6/'Tech Parameters'!E12) -> 42.279837
A15: Gasoline | B15: $/GJ svc | C15: =IF('Tech Parameters'!E13=0,0,C7/'Tech Parameters'!E13) -> 72 | D15: =IF('Tech Parameters'!E13=0,0,D7/'Tech Parameters'!E13) -> 72 | E15: =IF('Tech Parameters'!E13=0,0,E7/'Tech Parameters'!E13) -> 83.266667 | F15: =IF('Tech Parameters'!E13=0,0,F7/'Tech Parameters'!E13) -> 94.563293 | G15: =IF('Tech Parameters'!E13=0,0,G7/'Tech Parameters'!E13) -> 105.85992 | H15: =IF('Tech Parameters'!E13=0,0,H7/'Tech Parameters'!E13) -> 105.88988 | I15: =IF('Tech Parameters'!E13=0,0,I7/'Tech Parameters'!E13) -> 105.91984 | J15: =IF('Tech Parameters'!E13=0,0,J7/'Tech Parameters'!E13) -> 105.91984 | K15: =IF('Tech Parameters'!E13=0,0,K7/'Tech Parameters'!E13) -> 105.91984 | L15: =IF('Tech Parameters'!E13=0,0,L7/'Tech Parameters'!E13) -> 105.91984 | M15: =IF('Tech Parameters'!E13=0,0,M7/'Tech Parameters'!E13) -> 105.91984 | N15: =IF('Tech Parameters'!E13=0,0,N7/'Tech Parameters'!E13) -> 105.91984
A16: Diesel | B16: $/GJ svc | C16: =IF('Tech Parameters'!E14=0,0,C8/'Tech Parameters'!E14) -> 56.666667 | D16: =IF('Tech Parameters'!E14=0,0,D8/'Tech Parameters'!E14) -> 56.666667 | E16: =IF('Tech Parameters'!E14=0,0,E8/'Tech Parameters'!E14) -> 65.222222 | F16: =IF('Tech Parameters'!E14=0,0,F8/'Tech Parameters'!E14) -> 73.886077 | G16: =IF('Tech Parameters'!E14=0,0,G8/'Tech Parameters'!E14) -> 82.549932 | H16: =IF('Tech Parameters'!E14=0,0,H8/'Tech Parameters'!E14) -> 82.658231 | I16: =IF('Tech Parameters'!E14=0,0,I8/'Tech Parameters'!E14) -> 82.766531 | J16: =IF('Tech Parameters'!E14=0,0,J8/'Tech Parameters'!E14) -> 82.766531 | K16: =IF('Tech Parameters'!E14=0,0,K8/'Tech Parameters'!E14) -> 82.766531 | L16: =IF('Tech Parameters'!E14=0,0,L8/'Tech Parameters'!E14) -> 82.766531 | M16: =IF('Tech Parameters'!E14=0,0,M8/'Tech Parameters'!E14) -> 82.766531 | N16: =IF('Tech Parameters'!E14=0,0,N8/'Tech Parameters'!E14) -> 82.766531
A17: Electricity | B17: $/GJ svc | C17: =IF('Tech Parameters'!E15=0,0,C9/'Tech Parameters'!E15) -> 25.882353 | D17: =IF('Tech Parameters'!E15=0,0,D9/'Tech Parameters'!E15) -> 25.882353 | E17: =IF('Tech Parameters'!E15=0,0,E9/'Tech Parameters'!E15) -> 25.882353 | F17: =IF('Tech Parameters'!E15=0,0,F9/'Tech Parameters'!E15) -> 25.485282 | G17: =IF('Tech Parameters'!E15=0,0,G9/'Tech Parameters'!E15) -> 25.088211 | H17: =IF('Tech Parameters'!E15=0,0,H9/'Tech Parameters'!E15) -> 24.69114 | I17: =IF('Tech Parameters'!E15=0,0,I9/'Tech Parameters'!E15) -> 24.29407 | J17: =IF('Tech Parameters'!E15=0,0,J9/'Tech Parameters'!E15) -> 24.29407 | K17: =IF('Tech Parameters'!E15=0,0,K9/'Tech Parameters'!E15) -> 24.29407 | L17: =IF('Tech Parameters'!E15=0,0,L9/'Tech Parameters'!E15) -> 24.29407 | M17: =IF('Tech Parameters'!E15=0,0,M9/'Tech Parameters'!E15) -> 24.29407 | N17: =IF('Tech Parameters'!E15=0,0,N9/'Tech Parameters'!E15) -> 24.29407
A18: RE generation | B18: $/GJ svc | C18: =IF('Tech Parameters'!E16=0,0,C10/'Tech Parameters'!E16) -> 0 | D18: =IF('Tech Parameters'!E16=0,0,D10/'Tech Parameters'!E16) -> 0 | E18: =IF('Tech Parameters'!E16=0,0,E10/'Tech Parameters'!E16) -> 0 | F18: =IF('Tech Parameters'!E16=0,0,F10/'Tech Parameters'!E16) -> 0 | G18: =IF('Tech Parameters'!E16=0,0,G10/'Tech Parameters'!E16) -> 0 | H18: =IF('Tech Parameters'!E16=0,0,H10/'Tech Parameters'!E16) -> 0 | I18: =IF('Tech Parameters'!E16=0,0,I10/'Tech Parameters'!E16) -> 0 | J18: =IF('Tech Parameters'!E16=0,0,J10/'Tech Parameters'!E16) -> 0 | K18: =IF('Tech Parameters'!E16=0,0,K10/'Tech Parameters'!E16) -> 0 | L18: =IF('Tech Parameters'!E16=0,0,L10/'Tech Parameters'!E16) -> 0 | M18: =IF('Tech Parameters'!E16=0,0,M10/'Tech Parameters'!E16) -> 0 | N18: =IF('Tech Parameters'!E16=0,0,N10/'Tech Parameters'!E16) -> 0
A20: ROAD TRANSPORT — CES Cost Index
C22: =IF(C13=0,0,C13^(1-'Tech Parameters'!$B$5)) -> 0 | D22: =IF(D13=0,0,D13^(1-'Tech Parameters'!$B$5)) -> 0 | E22: =IF(E13=0,0,E13^(1-'Tech Parameters'!$B$5)) -> 0 | F22: =IF(F13=0,0,F13^(1-'Tech Parameters'!$B$5)) -> 0 | G22: =IF(G13=0,0,G13^(1-'Tech Parameters'!$B$5)) -> 0 | H22: =IF(H13=0,0,H13^(1-'Tech Parameters'!$B$5)) -> 0 | I22: =IF(I13=0,0,I13^(1-'Tech Parameters'!$B$5)) -> 0 | J22: =IF(J13=0,0,J13^(1-'Tech Parameters'!$B$5)) -> 0 | ... N22: =IF(N13=0,0,N13^(1-'Tech Parameters'!$B$5)) -> 0
C23: =IF(C14=0,0,C14^(1-'Tech Parameters'!$B$5)) -> 0.1767767 | D23: =IF(D14=0,0,D14^(1-'Tech Parameters'!$B$5)) -> 0.1767767 | E23: =IF(E14=0,0,E14^(1-'Tech Parameters'!$B$5)) -> 0.1672874 | F23: =IF(F14=0,0,F14^(1-'Tech Parameters'!$B$5)) -> 0.15964458 | G23: =IF(G14=0,0,G14^(1-'Tech Parameters'!$B$5)) -> 0.15296186 | H23: =IF(H14=0,0,H14^(1-'Tech Parameters'!$B$5)) -> 0.15337518 | I23: =IF(I14=0,0,I14^(1-'Tech Parameters'!$B$5)) -> 0.15379186 | J23: =IF(J14=0,0,J14^(1-'Tech Parameters'!$B$5)) -> 0.15379186 | ... N23: =IF(N14=0,0,N14^(1-'Tech Parameters'!$B$5)) -> 0.15379186
C24: =IF(C15=0,0,C15^(1-'Tech Parameters'!$B$5)) -> 0.11785113 | D24: =IF(D15=0,0,D15^(1-'Tech Parameters'!$B$5)) -> 0.11785113 | E24: =IF(E15=0,0,E15^(1-'Tech Parameters'!$B$5)) -> 0.10958836 | F24: =IF(F15=0,0,F15^(1-'Tech Parameters'!$B$5)) -> 0.10283447 | G24: =IF(G15=0,0,G15^(1-'Tech Parameters'!$B$5)) -> 0.097192829 | H24: =IF(H15=0,0,H15^(1-'Tech Parameters'!$B$5)) -> 0.097179079 | I24: =IF(I15=0,0,I15^(1-'Tech Parameters'!$B$5)) -> 0.097165334 | J24: =IF(J15=0,0,J15^(1-'Tech Parameters'!$B$5)) -> 0.097165334 | ... N24: =IF(N15=0,0,N15^(1-'Tech Parameters'!$B$5)) -> 0.097165334
C25: =IF(C16=0,0,C16^(1-'Tech Parameters'!$B$5)) -> 0.13284223 | D25: =IF(D16=0,0,D16^(1-'Tech Parameters'!$B$5)) -> 0.13284223 | E25: =IF(E16=0,0,E16^(1-'Tech Parameters'!$B$5)) -> 0.12382325 | F25: =IF(F16=0,0,F16^(1-'Tech Parameters'!$B$5)) -> 0.11633722 | G25: =IF(G16=0,0,G16^(1-'Tech Parameters'!$B$5)) -> 0.11006307 | H25: =IF(H16=0,0,H16^(1-'Tech Parameters'!$B$5)) -> 0.10999095 | I25: =IF(I16=0,0,I16^(1-'Tech Parameters'!$B$5)) -> 0.10991896 | J25: =IF(J16=0,0,J16^(1-'Tech Parameters'!$B$5)) -> 0.10991896 | ... N25: =IF(N16=0,0,N16^(1-'Tech Parameters'!$B$5)) -> 0.10991896
C26: =IF(C17=0,0,C17^(1-'Tech Parameters'!$B$5)) -> 0.19656135 | D26: =IF(D17=0,0,D17^(1-'Tech Parameters'!$B$5)) -> 0.19656135 | E26: =IF(E17=0,0,E17^(1-'Tech Parameters'!$B$5)) -> 0.19656135 | F26: =IF(F17=0,0,F17^(1-'Tech Parameters'!$B$5)) -> 0.19808668 | G26: =IF(G17=0,0,G17^(1-'Tech Parameters'!$B$5)) -> 0.19964809 | H26: =IF(H17=0,0,H17^(1-'Tech Parameters'!$B$5)) -> 0.201247 | I26: =IF(I17=0,0,I17^(1-'Tech Parameters'!$B$5)) -> 0.20288496 | J26: =IF(J17=0,0,J17^(1-'Tech Parameters'!$B$5)) -> 0.20288496 | ... N26: =IF(N17=0,0,N17^(1-'Tech Parameters'!$B$5)) -> 0.20288496
C27: =IF(C18=0,0,C18^(1-'Tech Parameters'!$B$5)) -> 0 | D27: =IF(D18=0,0,D18^(1-'Tech Parameters'!$B$5)) -> 0 | E27: =IF(E18=0,0,E18^(1-'Tech Parameters'!$B$5)) -> 0 | F27: =IF(F18=0,0,F18^(1-'Tech Parameters'!$B$5)) -> 0 | G27: =IF(G18=0,0,G18^(1-'Tech Parameters'!$B$5)) -> 0 | H27: =IF(H18=0,0,H18^(1-'Tech Parameters'!$B$5)) -> 0 | I27: =IF(I18=0,0,I18^(1-'Tech Parameters'!$B$5)) -> 0 | J27: =IF(J18=0,0,J18^(1-'Tech Parameters'!$B$5)) -> 0 | ... N27: =IF(N18=0,0,N18^(1-'Tech Parameters'!$B$5)) -> 0
C28: ='Tech Parameters'!J11 -> 0 | D28: ='Tech Parameters'!J12 -> 0.0055452865 | E28: ='Tech Parameters'!J13 -> 0.54066543 | F28: ='Tech Parameters'!J14 -> 0.39279113 | G28: ='Tech Parameters'!J15 -> 0.060998152 | H28: ='Tech Parameters'!J16 -> 0
A29: C(t) | B29: $/GJ svc | C29: =(C28*C22+D28*C23+E28*C24+F28*C25+G28*C26+H28*C27)^(1/(1-'Tech Parameters'!$B$5)) -> 60.216236 | D29: =(C28*D22+D28*D23+E28*D24+F28*D25+G28*D26+H28*D27)^(1/(1-'Tech Parameters'!$B$5)) -> 60.216236 | E29: =(C28*E22+D28*E23+E28*E24+F28*E25+G28*E26+H28*E27)^(1/(1-'Tech Parameters'!$B$5)) -> 68.522198 | F29: =(C28*F22+D28*F23+E28*F24+F28*F25+G28*F26+H28*F27)^(1/(1-'Tech Parameters'!$B$5)) -> 76.592315 | G29: =(C28*G22+D28*G23+E28*G24+F28*G25+G28*G26+H28*G27)^(1/(1-'Tech Parameters'!$B$5)) -> 84.466881 | H29: =(C28*H22+D28*H23+E28*H24+F28*H25+G28*H26+H28*H27)^(1/(1-'Tech Parameters'!$B$5)) -> 84.367512 | I29: =(C28*I22+D28*I23+E28*I24+F28*I25+G28*I26+H28*I27)^(1/(1-'Tech Parameters'!$B$5)) -> 84.264514 | J29: =(C28*J22+D28*J23+E28*J24+F28*J25+G28*J26+H28*J27)^(1/(1-'Tech Parameters'!$B$5)) -> 84.264514 | K29: =(C28*K22+D28*K23+E28*K24+F28*K25+G28*K26+H28*K27)^(1/(1-'Tech Parameters'!$B$5)) -> 84.264514 | L29: =(C28*L22+D28*L23+E28*L24+F28*L25+G28*L26+H28*L27)^(1/(1-'Tech Parameters'!$B$5)) -> 84.264514 | M29: =(C28*M22+D28*M23+E28*M24+F28*M25+G28*M26+H28*M27)^(1/(1-'Tech Parameters'!$B$5)) -> 84.264514 | N29: =(C28*N22+D28*N23+E28*N24+F28*N25+G28*N26+H28*N27)^(1/(1-'Tech Parameters'!$B$5)) -> 84.264514
A31: ROAD TRANSPORT — Equilibrium Quantities (PJ)
A32: Coal | B32: PJ | C32: ='Tech Parameters'!D11 -> 0 | D32: =IF(OR(D13=0,C13=0),C41,C41*(D13/C13)^(-'Tech Parameters'!$B$5)*(D29/C29)^('Tech Parameters'!$B$5+'Tech Parameters'!$B$6)) -> 0 | E32: =IF(OR(E13=0,D13=0),D41,D41*(E13/D13)^(-'Tech Parameters'!$B$5)*(E29/D29)^('Tech Parameters'!$B$5+'Tech Parameters'!$B$6)) -> 0 | F32: =IF(OR(F13=0,E13=0),E41,E41*(F13/E13)^(-'Tech Parameters'!$B$5)*(F29/E29)^('Tech Parameters'!$B$5+'Tech Parameters'!$B$6)) -> 0 | G32: =IF(OR(G13=0,F13=0),F41,F41*(G13/F13)^(-'Tech Parameters'!$B$5)*(G29/F29)^('Tech Parameters'!$B$5+'Tech Parameters'!$B$6)) -> 0 | H32: =IF(OR(H13=0,G13=0),G41,G41*(H13/G13)^(-'Tech Parameters'!$B$5)*(H29/G29)^('Tech Parameters'!$B$5+'Tech Parameters'!$B$6)) -> 0 | I32: =IF(OR(I13=0,H13=0),H41,H41*(I13/H13)^(-'Tech Parameters'!$B$5)*(I29/H29)^('Tech Parameters'!$B$5+'Tech Parameters'!$B$6)) -> 0 | J32: =IF(OR(J13=0,I13=0),I41,I41*(J13/I13)^(-'Tech Parameters'!$B$5)*(J29/I29)^('Tech Parameters'!$B$5+'Tech Parameters'!$B$6)) -> 0 | K32: =IF(OR(K13=0,J13=0),J41,J41*(K13/J13)^(-'Tech Parameters'!$B$5)*(K29/J29)^('Tech Parameters'!$B$5+'Tech Parameters'!$B$6)) -> 0 | ... N32: =IF(OR(N13=0,M13=0),M41,M41*(N13/M13)^(-'Tech Parameters'!$B$5)*(N29/M29)^('Tech Parameters'!$B$5+'Tech Parameters'!$B$6)) -> 0
A33: Natural gas | B33: PJ | C33: ='Tech Parameters'!D12 -> 15 | D33: =IF(OR(D14=0,C14=0),C42,C42*(D14/C14)^(-'Tech Parameters'!$B$5)*(D29/C29)^('Tech Parameters'!$B$5+'Tech Parameters'!$B$6)) -> 15 | E33: =IF(OR(E14=0,D14=0),D42,D42*(E14/D14)^(-'Tech Parameters'!$B$5)*(E29/D29)^('Tech Parameters'!$B$5+'Tech Parameters'!$B$6)) -> 14.84387 | F33: =IF(OR(F14=0,E14=0),E42,E42*(F14/E14)^(-'Tech Parameters'!$B$5)*(F29/E29)^('Tech Parameters'!$B$5+'Tech Parameters'!$B$6)) -> 14.876822 | G33: =IF(OR(G14=0,F14=0),F42,F42*(G14/F14)^(-'Tech Parameters'!$B$5)*(G29/F29)^('Tech Parameters'!$B$5+'Tech Parameters'!$B$6)) -> 14.80018 | H33: =IF(OR(H14=0,G14=0),G42,G42*(H14/G14)^(-'Tech Parameters'!$B$5)*(H29/G29)^('Tech Parameters'!$B$5+'Tech Parameters'!$B$6)) -> 15.037559 | I33: =IF(OR(I14=0,H14=0),H42,H42*(I14/H14)^(-'Tech Parameters'!$B$5)*(I29/H29)^('Tech Parameters'!$B$5+'Tech Parameters'!$B$6)) -> 15.052541 | J33: =IF(OR(J14=0,I14=0),I42,I42*(J14/I14)^(-'Tech Parameters'!$B$5)*(J29/I29)^('Tech Parameters'!$B$5+'Tech Parameters'!$B$6)) -> 14.967442 | K33: =IF(OR(K14=0,J14=0),J42,J42*(K14/J14)^(-'Tech Parameters'!$B$5)*(K29/J29)^('Tech Parameters'!$B$5+'Tech Parameters'!$B$6)) -> 14.967442 | ... N33: =IF(OR(N14=0,M14=0),M42,M42*(N14/M14)^(-'Tech Parameters'!$B$5)*(N29/M29)^('Tech Parameters'!$B$5+'Tech Parameters'!$B$6)) -> 14.967442
A34: Gasoline | B34: PJ | C34: ='Tech Parameters'!D13 -> 650 | D34: =IF(OR(D15=0,C15=0),C43,C43*(D15/C15)^(-'Tech Parameters'!$B$5)*(D29/C29)^('Tech Parameters'!$B$5+'Tech Parameters'!$B$6)) -> 650 | E34: =IF(OR(E15=0,D15=0),D43,D43*(E15/D15)^(-'Tech Parameters'!$B$5)*(E29/D29)^('Tech Parameters'!$B$5+'Tech Parameters'!$B$6)) -> 610.30448 | F34: =IF(OR(F15=0,E15=0),E43,E43*(F15/E15)^(-'Tech Parameters'!$B$5)*(F29/E29)^('Tech Parameters'!$B$5+'Tech Parameters'!$B$6)) -> 608.22497 | G34: =IF(OR(G15=0,F15=0),F43,F43*(G15/F15)^(-'Tech Parameters'!$B$5)*(G29/F29)^('Tech Parameters'!$B$5+'Tech Parameters'!$B$6)) -> 606.40995 | H34: =IF(OR(H15=0,G15=0),G43,G43*(H15/G15)^(-'Tech Parameters'!$B$5)*(H29/G29)^('Tech Parameters'!$B$5+'Tech Parameters'!$B$6)) -> 632.6699 | I34: =IF(OR(I15=0,H15=0),H43,H43*(I15/H15)^(-'Tech Parameters'!$B$5)*(I29/H29)^('Tech Parameters'!$B$5+'Tech Parameters'!$B$6)) -> 632.46206 | J34: =IF(OR(J15=0,I15=0),I43,I43*(J15/I15)^(-'Tech Parameters'!$B$5)*(J29/I29)^('Tech Parameters'!$B$5+'Tech Parameters'!$B$6)) -> 633.47919 | K34: =IF(OR(K15=0,J15=0),J43,J43*(K15/J15)^(-'Tech Parameters'!$B$5)*(K29/J29)^('Tech Parameters'!$B$5+'Tech Parameters'!$B$6)) -> 633.47919 | ... N34: =IF(OR(N15=0,M15=0),M43,M43*(N15/M15)^(-'Tech Parameters'!$B$5)*(N29/M29)^('Tech Parameters'!$B$5+'Tech Parameters'!$B$6)) -> 633.47919
A35: Diesel | B35: PJ | C35: ='Tech Parameters'!D14 -> 500 | D35: =IF(OR(D16=0,C16=0),C44,C44*(D16/C16)^(-'Tech Parameters'!$B$5)*(D29/C29)^('Tech Parameters'!$B$5+'Tech Parameters'!$B$6)) -> 500 | E35: =IF(OR(E16=0,D16=0),D44,D44*(E16/D16)^(-'Tech Parameters'!$B$5)*(E29/D29)^('Tech Parameters'!$B$5+'Tech Parameters'!$B$6)) -> 472.8347 | F35: =IF(OR(F16=0,E16=0),E44,E44*(F16/E16)^(-'Tech Parameters'!$B$5)*(F29/E29)^('Tech Parameters'!$B$5+'Tech Parameters'!$B$6)) -> 470.1001 | G35: =IF(OR(G16=0,F16=0),F44,F44*(G16/F16)^(-'Tech Parameters'!$B$5)*(G29/F29)^('Tech Parameters'!$B$5+'Tech Parameters'!$B$6)) -> 468.57688 | H35: =IF(OR(H16=0,G16=0),G44,G44*(H16/G16)^(-'Tech Parameters'!$B$5)*(H29/G29)^('Tech Parameters'!$B$5+'Tech Parameters'!$B$6)) -> 486.88223 | I35: =IF(OR(I16=0,H16=0),H44,H44*(I16/H16)^(-'Tech Parameters'!$B$5)*(I29/H29)^('Tech Parameters'!$B$5+'Tech Parameters'!$B$6)) -> 486.61115 | J35: =IF(OR(J16=0,I16=0),I44,I44*(J16/I16)^(-'Tech Parameters'!$B$5)*(J29/I29)^('Tech Parameters'!$B$5+'Tech Parameters'!$B$6)) -> 488.03227 | K35: =IF(OR(K16=0,J16=0),J44,J44*(K16/J16)^(-'Tech Parameters'!$B$5)*(K29/J29)^('Tech Parameters'!$B$5+'Tech Parameters'!$B$6)) -> 488.03227 | ... N35: =IF(OR(N16=0,M16=0),M44,M44*(N16/M16)^(-'Tech Parameters'!$B$5)*(N29/M29)^('Tech Parameters'!$B$5+'Tech Parameters'!$B$6)) -> 488.03227
A36: Electricity | B36: PJ | C36: ='Tech Parameters'!D15 -> 60 | D36: =IF(OR(D17=0,C17=0),C45,C45*(D17/C17)^(-'Tech Parameters'!$B$5)*(D29/C29)^('Tech Parameters'!$B$5+'Tech Parameters'!$B$6)) -> 60 | E36: =IF(OR(E17=0,D17=0),D45,D45*(E17/D17)^(-'Tech Parameters'!$B$5)*(E29/D29)^('Tech Parameters'!$B$5+'Tech Parameters'!$B$6)) -> 70.063604 | F36: =IF(OR(F17=0,E17=0),E45,E45*(F17/E17)^(-'Tech Parameters'!$B$5)*(F29/E29)^('Tech Parameters'!$B$5+'Tech Parameters'!$B$6)) -> 71.951299 | G36: =IF(OR(G17=0,F17=0),F45,F45*(G17/F17)^(-'Tech Parameters'!$B$5)*(G29/F29)^('Tech Parameters'!$B$5+'Tech Parameters'!$B$6)) -> 72.626302 | H36: =IF(OR(H17=0,G17=0),G45,G45*(H17/G17)^(-'Tech Parameters'!$B$5)*(H29/G29)^('Tech Parameters'!$B$5+'Tech Parameters'!$B$6)) -> 65.977445 | I36: =IF(OR(I17=0,H17=0),H45,H45*(I17/H17)^(-'Tech Parameters'!$B$5)*(I29/H29)^('Tech Parameters'!$B$5+'Tech Parameters'!$B$6)) -> 66.22498 | J36: =IF(OR(J17=0,I17=0),I45,I45*(J17/I17)^(-'Tech Parameters'!$B$5)*(J29/I29)^('Tech Parameters'!$B$5+'Tech Parameters'!$B$6)) -> 64.953175 | K36: =IF(OR(K17=0,J17=0),J45,J45*(K17/J17)^(-'Tech Parameters'!$B$5)*(K29/J29)^('Tech Parameters'!$B$5+'Tech Parameters'!$B$6)) -> 64.953175 | ... N36: =IF(OR(N17=0,M17=0),M45,M45*(N17/M17)^(-'Tech Parameters'!$B$5)*(N29/M29)^('Tech Parameters'!$B$5+'Tech Parameters'!$B$6)) -> 64.953175
A37: RE generation | B37: PJ | C37: ='Tech Parameters'!D16 -> 0 | D37: =IF(OR(D18=0,C18=0),C46,C46*(D18/C18)^(-'Tech Parameters'!$B$5)*(D29/C29)^('Tech Parameters'!$B$5+'Tech Parameters'!$B$6)) -> 0 | E37: =IF(OR(E18=0,D18=0),D46,D46*(E18/D18)^(-'Tech Parameters'!$B$5)*(E29/D29)^('Tech Parameters'!$B$5+'Tech Parameters'!$B$6)) -> 0 | F37: =IF(OR(F18=0,E18=0),E46,E46*(F18/E18)^(-'Tech Parameters'!$B$5)*(F29/E29)^('Tech Parameters'!$B$5+'Tech Parameters'!$B$6)) -> 0 | G37: =IF(OR(G18=0,F18=0),F46,F46*(G18/F18)^(-'Tech Parameters'!$B$5)*(G29/F29)^('Tech Parameters'!$B$5+'Tech Parameters'!$B$6)) -> 0 | H37: =IF(OR(H18=0,G18=0),G46,G46*(H18/G18)^(-'Tech Parameters'!$B$5)*(H29/G29)^('Tech Parameters'!$B$5+'Tech Parameters'!$B$6)) -> 0 | I37: =IF(OR(I18=0,H18=0),H46,H46*(I18/H18)^(-'Tech Parameters'!$B$5)*(I29/H29)^('Tech Parameters'!$B$5+'Tech Parameters'!$B$6)) -> 0 | J37: =IF(OR(J18=0,I18=0),I46,I46*(J18/I18)^(-'Tech Parameters'!$B$5)*(J29/I29)^('Tech Parameters'!$B$5+'Tech Parameters'!$B$6)) -> 0 | K37: =IF(OR(K18=0,J18=0),J46,J46*(K18/J18)^(-'Tech Parameters'!$B$5)*(K29/J29)^('Tech Parameters'!$B$5+'Tech Parameters'!$B$6)) -> 0 | ... N37: =IF(OR(N18=0,M18=0),M46,M46*(N18/M18)^(-'Tech Parameters'!$B$5)*(N29/M29)^('Tech Parameters'!$B$5+'Tech Parameters'!$B$6)) -> 0
A39: ROAD TRANSPORT — Actual Quantities (PJ)
A41: Coal | B41: PJ | C41: =C32 -> 0 | D41: =C41+'Tech Parameters'!$B$7*(D32-C41) -> 0 | E41: =D41+'Tech Parameters'!$B$7*(E32-D41) -> 0 | F41: =E41+'Tech Parameters'!$B$7*(F32-E41) -> 0 | G41: =F41+'Tech Parameters'!$B$7*(G32-F41) -> 0 | H41: =G41+'Tech Parameters'!$B$7*(H32-G41) -> 0 | I41: =H41+'Tech Parameters'!$B$7*(I32-H41) -> 0 | J41: =I41+'Tech Parameters'!$B$7*(J32-I41) -> 0 | K41: =J41+'Tech Parameters'!$B$7*(K32-J41) -> 0 | ... N41: =M41+'Tech Parameters'!$B$7*(N32-M41) -> 0
A42: Natural gas | B42: PJ | C42: =C33 -> 15 | D42: =C42+'Tech Parameters'!$B$7*(D33-C42) -> 15 | E42: =D42+'Tech Parameters'!$B$7*(E33-D42) -> 14.976581 | F42: =E42+'Tech Parameters'!$B$7*(F33-E42) -> 14.961617 | G42: =F42+'Tech Parameters'!$B$7*(G33-F42) -> 14.937401 | H42: =G42+'Tech Parameters'!$B$7*(H33-G42) -> 14.952425 | I42: =H42+'Tech Parameters'!$B$7*(I33-H42) -> 14.967442 | J42: =I42+'Tech Parameters'!$B$7*(J33-I42) -> 14.967442 | K42: =J42+'Tech Parameters'!$B$7*(K33-J42) -> 14.967442 | ... N42: =M42+'Tech Parameters'!$B$7*(N33-M42) -> 14.967442
A43: Gasoline | B43: PJ | C43: =C34 -> 650 | D43: =C43+'Tech Parameters'!$B$7*(D34-C43) -> 650 | E43: =D43+'Tech Parameters'!$B$7*(E34-D43) -> 644.04567 | F43: =E43+'Tech Parameters'!$B$7*(F34-E43) -> 638.67257 | G43: =F43+'Tech Parameters'!$B$7*(G34-F43) -> 633.83317 | H43: =G43+'Tech Parameters'!$B$7*(H34-G43) -> 633.65868 | I43: =H43+'Tech Parameters'!$B$7*(I34-H43) -> 633.47919 | J43: =I43+'Tech Parameters'!$B$7*(J34-I43) -> 633.47919 | K43: =J43+'Tech Parameters'!$B$7*(K34-J43) -> 633.47919 | ... N43: =M43+'Tech Parameters'!$B$7*(N34-M43) -> 633.47919
A44: Diesel | B44: PJ | C44: =C35 -> 500 | D44: =C44+'Tech Parameters'!$B$7*(D35-C44) -> 500 | E44: =D44+'Tech Parameters'!$B$7*(E35-D44) -> 495.9252 | F44: =E44+'Tech Parameters'!$B$7*(F35-E44) -> 492.05144 | G44: =F44+'Tech Parameters'!$B$7*(G35-F44) -> 488.53026 | H44: =G44+'Tech Parameters'!$B$7*(H35-G44) -> 488.28305 | I44: =H44+'Tech Parameters'!$B$7*(I35-H44) -> 488.03227 | J44: =I44+'Tech Parameters'!$B$7*(J35-I44) -> 488.03227 | K44: =J44+'Tech Parameters'!$B$7*(K35-J44) -> 488.03227 | ... N44: =M44+'Tech Parameters'!$B$7*(N35-M44) -> 488.03227
A45: Electricity | B45: PJ | C45: =C36 -> 60 | D45: =C45+'Tech Parameters'!$B$7*(D36-C45) -> 60 | E45: =D45+'Tech Parameters'!$B$7*(E36-D45) -> 61.509541 | F45: =E45+'Tech Parameters'!$B$7*(F36-E45) -> 63.075804 | G45: =F45+'Tech Parameters'!$B$7*(G36-F45) -> 64.508379 | H45: =G45+'Tech Parameters'!$B$7*(H36-G45) -> 64.728739 | I45: =H45+'Tech Parameters'!$B$7*(I36-H45) -> 64.953175 | J45: =I45+'Tech Parameters'!$B$7*(J36-I45) -> 64.953175 | K45: =J45+'Tech Parameters'!$B$7*(K36-J45) -> 64.953175 | ... N45: =M45+'Tech Parameters'!$B$7*(N36-M45) -> 64.953175
A46: RE generation | B46: PJ | C46: =C37 -> 0 | D46: =C46+'Tech Parameters'!$B$7*(D37-C46) -> 0 | E46: =D46+'Tech Parameters'!$B$7*(E37-D46) -> 0 | F46: =E46+'Tech Parameters'!$B$7*(F37-E46) -> 0 | G46: =F46+'Tech Parameters'!$B$7*(G37-F46) -> 0 | H46: =G46+'Tech Parameters'!$B$7*(H37-G46) -> 0 | I46: =H46+'Tech Parameters'!$B$7*(I37-H46) -> 0 | J46: =I46+'Tech Parameters'!$B$7*(J37-I46) -> 0 | K46: =J46+'Tech Parameters'!$B$7*(K37-J46) -> 0 | ... N46: =M46+'Tech Parameters'!$B$7*(N37-M46) -> 0
A48: ROAD TRANSPORT — Emissions (MtCO2)
A49: Coal | B49: MtCO2 | C49: =C41*'Tech Parameters'!C11 -> 0 | D49: =D41*'Tech Parameters'!C11 -> 0 | E49: =E41*'Tech Parameters'!C11 -> 0 | F49: =F41*'Tech Parameters'!C11 -> 0 | G49: =G41*'Tech Parameters'!C11 -> 0 | H49: =H41*'Tech Parameters'!C11 -> 0 | I49: =I41*'Tech Parameters'!C11 -> 0 | J49: =J41*'Tech Parameters'!C11 -> 0 | K49: =K41*'Tech Parameters'!C11 -> 0 | L49: =L41*'Tech Parameters'!C11 -> 0 | M49: =M41*'Tech Parameters'!C11 -> 0 | N49: =N41*'Tech Parameters'!C11 -> 0
A50: Natural gas | B50: MtCO2 | C50: =C42*'Tech Parameters'!C12 -> 0.84 | D50: =D42*'Tech Parameters'!C12 -> 0.84 | E50: =E42*'Tech Parameters'!C12 -> 0.83868851 | F50: =F42*'Tech Parameters'!C12 -> 0.83785054 | G50: =G42*'Tech Parameters'!C12 -> 0.83649447 | H50: =H42*'Tech Parameters'!C12 -> 0.83733579 | I50: =I42*'Tech Parameters'!C12 -> 0.83817677 | J50: =J42*'Tech Parameters'!C12 -> 0.83817677 | K50: =K42*'Tech Parameters'!C12 -> 0.83817677 | L50: =L42*'Tech Parameters'!C12 -> 0.83817677 | M50: =M42*'Tech Parameters'!C12 -> 0.83817677 | N50: =N42*'Tech Parameters'!C12 -> 0.83817677
A51: Gasoline | B51: MtCO2 | C51: =C43*'Tech Parameters'!C13 -> 44.85 | D51: =D43*'Tech Parameters'!C13 -> 44.85 | E51: =E43*'Tech Parameters'!C13 -> 44.439151 | F51: =F43*'Tech Parameters'!C13 -> 44.068407 | G51: =G43*'Tech Parameters'!C13 -> 43.734489 | H51: =H43*'Tech Parameters'!C13 -> 43.722449 | I51: =I43*'Tech Parameters'!C13 -> 43.710064 | J51: =J43*'Tech Parameters'!C13 -> 43.710064 | K51: =K43*'Tech Parameters'!C13 -> 43.710064 | L51: =L43*'Tech Parameters'!C13 -> 43.710064 | M51: =M43*'Tech Parameters'!C13 -> 43.710064 | N51: =N43*'Tech Parameters'!C13 -> 43.710064
A52: Diesel | B52: MtCO2 | C52: =C44*'Tech Parameters'!C14 -> 37 | D52: =D44*'Tech Parameters'!C14 -> 37 | E52: =E44*'Tech Parameters'!C14 -> 36.698465 | F52: =F44*'Tech Parameters'!C14 -> 36.411807 | G52: =G44*'Tech Parameters'!C14 -> 36.151239 | H52: =H44*'Tech Parameters'!C14 -> 36.132946 | I52: =I44*'Tech Parameters'!C14 -> 36.114388 | J52: =J44*'Tech Parameters'!C14 -> 36.114388 | K52: =K44*'Tech Parameters'!C14 -> 36.114388 | L52: =L44*'Tech Parameters'!C14 -> 36.114388 | M52: =M44*'Tech Parameters'!C14 -> 36.114388 | N52: =N44*'Tech Parameters'!C14 -> 36.114388
A53: Electricity | B53: MtCO2 | C53: =C45*'Tech Parameters'!C15 -> 0 | D53: =D45*'Tech Parameters'!C15 -> 0 | E53: =E45*'Tech Parameters'!C15 -> 0 | F53: =F45*'Tech Parameters'!C15 -> 0 | G53: =G45*'Tech Parameters'!C15 -> 0 | H53: =H45*'Tech Parameters'!C15 -> 0 | I53: =I45*'Tech Parameters'!C15 -> 0 | J53: =J45*'Tech Parameters'!C15 -> 0 | K53: =K45*'Tech Parameters'!C15 -> 0 | L53: =L45*'Tech Parameters'!C15 -> 0 | M53: =M45*'Tech Parameters'!C15 -> 0 | N53: =N45*'Tech Parameters'!C15 -> 0
A54: RE generation | B54: MtCO2 | C54: =C46*'Tech Parameters'!C16 -> 0 | D54: =D46*'Tech Parameters'!C16 -> 0 | E54: =E46*'Tech Parameters'!C16 -> 0 | F54: =F46*'Tech Parameters'!C16 -> 0 | G54: =G46*'Tech Parameters'!C16 -> 0 | H54: =H46*'Tech Parameters'!C16 -> 0 | I54: =I46*'Tech Parameters'!C16 -> 0 | J54: =J46*'Tech Parameters'!C16 -> 0 | K54: =K46*'Tech Parameters'!C16 -> 0 | L54: =L46*'Tech Parameters'!C16 -> 0 | M54: =M46*'Tech Parameters'!C16 -> 0 | N54: =N46*'Tech Parameters'!C16 -> 0
A55: TOTAL ROAD TRANSPORT EMISSIONS | B55: MtCO2 | C55: =SUM(C49:C54) -> 82.69 | D55: =SUM(D49:D54) -> 82.69 | E55: =SUM(E49:E54) -> 81.976305 | F55: =SUM(F49:F54) -> 81.318064 | G55: =SUM(G49:G54) -> 80.722222 | H55: =SUM(H49:H54) -> 80.692731 | I55: =SUM(I49:I54) -> 80.662629 | J55: =SUM(J49:J54) -> 80.662629 | ... N55: =SUM(N49:N54) -> 80.662629
A56: TOTAL ROAD TRANSPORT ENERGY | B56: PJ | C56: =SUM(C41:C46) -> 1225 | D56: =SUM(D41:D46) -> 1225 | E56: =SUM(E41:E46) -> 1216.457 | F56: =SUM(F41:F46) -> 1208.7614 | G56: =SUM(G41:G46) -> 1201.8092 | H56: =SUM(H41:H46) -> 1201.6229 | I56: =SUM(I41:I46) -> 1201.4321 | J56: =SUM(J41:J46) -> 1201.4321 | ... N56: =SUM(N41:N46) -> 1201.4321
A59: ELECTRICITY GEN. — Fuel Prices ($/GJ)
A60: Coal | B60: $/GJ | C60: =Baseline!C60+Dashboard!B21*'Tech Parameters'!C24+Dashboard!B23*('Tech Parameters'!C24-('Tech Parameters'!H24*'Tech Parameters'!C24+'Tech Parameters'!H25*'Tech Parameters'!C25+'Tech Parameters'!H26*'Tech Parameters'!C26+'Tech Parameters'!H27*'Tech Parameters'!C27+'Tech Parameters'!H28*'Tech Parameters'!C28+'Tech Parameters'!H29*'Tech Parameters'!C29))+Dashboard!B32 -> 3 | D60: =Baseline!D60+Dashboard!C21*'Tech Parameters'!C24+Dashboard!C23*('Tech Parameters'!C24-('Tech Parameters'!H24*'Tech Parameters'!C24+'Tech Parameters'!H25*'Tech Parameters'!C25+'Tech Parameters'!H26*'Tech Parameters'!C26+'Tech Parameters'!H27*'Tech Parameters'!C27+'Tech Parameters'!H28*'Tech Parameters'!C28+'Tech Parameters'!H29*'Tech Parameters'!C29))+Dashboard!C32 -> 3 | E60: =Baseline!E60+Dashboard!D21*'Tech Parameters'!C24+Dashboard!D23*('Tech Parameters'!C24-('Tech Parameters'!H24*'Tech Parameters'!C24+'Tech Parameters'!H25*'Tech Parameters'!C25+'Tech Parameters'!H26*'Tech Parameters'!C26+'Tech Parameters'!H27*'Tech Parameters'!C27+'Tech Parameters'!H28*'Tech Parameters'!C28+'Tech Parameters'!H29*'Tech Parameters'!C29))+Dashboard!D32 -> 4.5833333 | F60: =Baseline!F60+Dashboard!E21*'Tech Parameters'!C24+Dashboard!E23*('Tech Parameters'!C24-('Tech Parameters'!H24*'Tech Parameters'!C24+'Tech Parameters'!H25*'Tech Parameters'!C25+'Tech Parameters'!H26*'Tech Parameters'!C26+'Tech Parameters'!H27*'Tech Parameters'!C27+'Tech Parameters'!H28*'Tech Parameters'!C28+'Tech Parameters'!H29*'Tech Parameters'!C29))+Dashboard!E32 -> 6.274429 | G60: =Baseline!G60+Dashboard!F21*'Tech Parameters'!C24+Dashboard!F23*('Tech Parameters'!C24-('Tech Parameters'!H24*'Tech Parameters'!C24+'Tech Parameters'!H25*'Tech Parameters'!C25+'Tech Parameters'!H26*'Tech Parameters'!C26+'Tech Parameters'!H27*'Tech Parameters'!C27+'Tech Parameters'!H28*'Tech Parameters'!C28+'Tech Parameters'!H29*'Tech Parameters'!C29))+Dashboard!F32 -> 7.9655247 | H60: =Baseline!H60+Dashboard!G21*'Tech Parameters'!C24+Dashboard!G23*('Tech Parameters'!C24-('Tech Parameters'!H24*'Tech Parameters'!C24+'Tech Parameters'!H25*'Tech Parameters'!C25+'Tech Parameters'!H26*'Tech Parameters'!C26+'Tech Parameters'!H27*'Tech Parameters'!C27+'Tech Parameters'!H28*'Tech Parameters'!C28+'Tech Parameters'!H29*'Tech Parameters'!C29))+Dashboard!G32 -> 8.073287 | I60: =Baseline!I60+Dashboard!H21*'Tech Parameters'!C24+Dashboard!H23*('Tech Parameters'!C24-('Tech Parameters'!H24*'Tech Parameters'!C24+'Tech Parameters'!H25*'Tech Parameters'!C25+'Tech Parameters'!H26*'Tech Parameters'!C26+'Tech Parameters'!H27*'Tech Parameters'!C27+'Tech Parameters'!H28*'Tech Parameters'!C28+'Tech Parameters'!H29*'Tech Parameters'!C29))+Dashboard!H32 -> 8.1810494 | J60: =Baseline!J60+Dashboard!I21*'Tech Parameters'!C24+Dashboard!I23*('Tech Parameters'!C24-('Tech Parameters'!H24*'Tech Parameters'!C24+'Tech Parameters'!H25*'Tech Parameters'!C25+'Tech Parameters'!H26*'Tech Parameters'!C26+'Tech Parameters'!H27*'Tech Parameters'!C27+'Tech Parameters'!H28*'Tech Parameters'!C28+'Tech Parameters'!H29*'Tech Parameters'!C29))+Dashboard!I32 -> 8.1810494 | K60: =Baseline!K60+Dashboard!J21*'Tech Parameters'!C24+Dashboard!J23*('Tech Parameters'!C24-('Tech Parameters'!H24*'Tech Parameters'!C24+'Tech Parameters'!H25*'Tech Parameters'!C25+'Tech Parameters'!H26*'Tech Parameters'!C26+'Tech Parameters'!H27*'Tech Parameters'!C27+'Tech Parameters'!H28*'Tech Parameters'!C28+'Tech Parameters'!H29*'Tech Parameters'!C29))+Dashboard!J32 -> 8.1810494 | L60: =Baseline!L60+Dashboard!K21*'Tech Parameters'!C24+Dashboard!K23*('Tech Parameters'!C24-('Tech Parameters'!H24*'Tech Parameters'!C24+'Tech Parameters'!H25*'Tech Parameters'!C25+'Tech Parameters'!H26*'Tech Parameters'!C26+'Tech Parameters'!H27*'Tech Parameters'!C27+'Tech Parameters'!H28*'Tech Parameters'!C28+'Tech Parameters'!H29*'Tech Parameters'!C29))+Dashboard!K32 -> 8.1810494 | M60: =Baseline!M60+Dashboard!L21*'Tech Parameters'!C24+Dashboard!L23*('Tech Parameters'!C24-('Tech Parameters'!H24*'Tech Parameters'!C24+'Tech Parameters'!H25*'Tech Parameters'!C25+'Tech Parameters'!H26*'Tech Parameters'!C26+'Tech Parameters'!H27*'Tech Parameters'!C27+'Tech Parameters'!H28*'Tech Parameters'!C28+'Tech Parameters'!H29*'Tech Parameters'!C29))+Dashboard!L32 -> 8.1810494 | N60: =Baseline!N60+Dashboard!M21*'Tech Parameters'!C24+Dashboard!M23*('Tech Parameters'!C24-('Tech Parameters'!H24*'Tech Parameters'!C24+'Tech Parameters'!H25*'Tech Parameters'!C25+'Tech Parameters'!H26*'Tech Parameters'!C26+'Tech Parameters'!H27*'Tech Parameters'!C27+'Tech Parameters'!H28*'Tech Parameters'!C28+'Tech Parameters'!H29*'Tech Parameters'!C29))+Dashboard!M32 -> 8.1810494
A61: Natural gas | B61: $/GJ | C61: =Baseline!C61+Dashboard!B21*'Tech Parameters'!C25+Dashboard!B23*('Tech Parameters'!C25-('Tech Parameters'!H24*'Tech Parameters'!C24+'Tech Parameters'!H25*'Tech Parameters'!C25+'Tech Parameters'!H26*'Tech Parameters'!C26+'Tech Parameters'!H27*'Tech Parameters'!C27+'Tech Parameters'!H28*'Tech Parameters'!C28+'Tech Parameters'!H29*'Tech Parameters'!C29))+Dashboard!B33 -> 6 | D61: =Baseline!D61+Dashboard!C21*'Tech Parameters'!C25+Dashboard!C23*('Tech Parameters'!C25-('Tech Parameters'!H24*'Tech Parameters'!C24+'Tech Parameters'!H25*'Tech Parameters'!C25+'Tech Parameters'!H26*'Tech Parameters'!C26+'Tech Parameters'!H27*'Tech Parameters'!C27+'Tech Parameters'!H28*'Tech Parameters'!C28+'Tech Parameters'!H29*'Tech Parameters'!C29))+Dashboard!C33 -> 6 | E61: =Baseline!E61+Dashboard!D21*'Tech Parameters'!C25+Dashboard!D23*('Tech Parameters'!C25-('Tech Parameters'!H24*'Tech Parameters'!C24+'Tech Parameters'!H25*'Tech Parameters'!C25+'Tech Parameters'!H26*'Tech Parameters'!C26+'Tech Parameters'!H27*'Tech Parameters'!C27+'Tech Parameters'!H28*'Tech Parameters'!C28+'Tech Parameters'!H29*'Tech Parameters'!C29))+Dashboard!D33 -> 6.9333333 | F61: =Baseline!F61+Dashboard!E21*'Tech Parameters'!C25+Dashboard!E23*('Tech Parameters'!C25-('Tech Parameters'!H24*'Tech Parameters'!C24+'Tech Parameters'!H25*'Tech Parameters'!C25+'Tech Parameters'!H26*'Tech Parameters'!C26+'Tech Parameters'!H27*'Tech Parameters'!C27+'Tech Parameters'!H28*'Tech Parameters'!C28+'Tech Parameters'!H29*'Tech Parameters'!C29))+Dashboard!E33 -> 7.828179 | G61: =Baseline!G61+Dashboard!F21*'Tech Parameters'!C25+Dashboard!F23*('Tech Parameters'!C25-('Tech Parameters'!H24*'Tech Parameters'!C24+'Tech Parameters'!H25*'Tech Parameters'!C25+'Tech Parameters'!H26*'Tech Parameters'!C26+'Tech Parameters'!H27*'Tech Parameters'!C27+'Tech Parameters'!H28*'Tech Parameters'!C28+'Tech Parameters'!H29*'Tech Parameters'!C29))+Dashboard!F33 -> 8.7230247 | H61: =Baseline!H61+Dashboard!G21*'Tech Parameters'!C25+Dashboard!G23*('Tech Parameters'!C25-('Tech Parameters'!H24*'Tech Parameters'!C24+'Tech Parameters'!H25*'Tech Parameters'!C25+'Tech Parameters'!H26*'Tech Parameters'!C26+'Tech Parameters'!H27*'Tech Parameters'!C27+'Tech Parameters'!H28*'Tech Parameters'!C28+'Tech Parameters'!H29*'Tech Parameters'!C29))+Dashboard!G33 -> 8.684537 | I61: =Baseline!I61+Dashboard!H21*'Tech Parameters'!C25+Dashboard!H23*('Tech Parameters'!C25-('Tech Parameters'!H24*'Tech Parameters'!C24+'Tech Parameters'!H25*'Tech Parameters'!C25+'Tech Parameters'!H26*'Tech Parameters'!C26+'Tech Parameters'!H27*'Tech Parameters'!C27+'Tech Parameters'!H28*'Tech Parameters'!C28+'Tech Parameters'!H29*'Tech Parameters'!C29))+Dashboard!H33 -> 8.6460494 | J61: =Baseline!J61+Dashboard!I21*'Tech Parameters'!C25+Dashboard!I23*('Tech Parameters'!C25-('Tech Parameters'!H24*'Tech Parameters'!C24+'Tech Parameters'!H25*'Tech Parameters'!C25+'Tech Parameters'!H26*'Tech Parameters'!C26+'Tech Parameters'!H27*'Tech Parameters'!C27+'Tech Parameters'!H28*'Tech Parameters'!C28+'Tech Parameters'!H29*'Tech Parameters'!C29))+Dashboard!I33 -> 8.6460494 | K61: =Baseline!K61+Dashboard!J21*'Tech Parameters'!C25+Dashboard!J23*('Tech Parameters'!C25-('Tech Parameters'!H24*'Tech Parameters'!C24+'Tech Parameters'!H25*'Tech Parameters'!C25+'Tech Parameters'!H26*'Tech Parameters'!C26+'Tech Parameters'!H27*'Tech Parameters'!C27+'Tech Parameters'!H28*'Tech Parameters'!C28+'Tech Parameters'!H29*'Tech Parameters'!C29))+Dashboard!J33 -> 8.6460494 | L61: =Baseline!L61+Dashboard!K21*'Tech Parameters'!C25+Dashboard!K23*('Tech Parameters'!C25-('Tech Parameters'!H24*'Tech Parameters'!C24+'Tech Parameters'!H25*'Tech Parameters'!C25+'Tech Parameters'!H26*'Tech Parameters'!C26+'Tech Parameters'!H27*'Tech Parameters'!C27+'Tech Parameters'!H28*'Tech Parameters'!C28+'Tech Parameters'!H29*'Tech Parameters'!C29))+Dashboard!K33 -> 8.6460494 | M61: =Baseline!M61+Dashboard!L21*'Tech Parameters'!C25+Dashboard!L23*('Tech Parameters'!C25-('Tech Parameters'!H24*'Tech Parameters'!C24+'Tech Parameters'!H25*'Tech Parameters'!C25+'Tech Parameters'!H26*'Tech Parameters'!C26+'Tech Parameters'!H27*'Tech Parameters'!C27+'Tech Parameters'!H28*'Tech Parameters'!C28+'Tech Parameters'!H29*'Tech Parameters'!C29))+Dashboard!L33 -> 8.6460494 | N61: =Baseline!N61+Dashboard!M21*'Tech Parameters'!C25+Dashboard!M23*('Tech Parameters'!C25-('Tech Parameters'!H24*'Tech Parameters'!C24+'Tech Parameters'!H25*'Tech Parameters'!C25+'Tech Parameters'!H26*'Tech Parameters'!C26+'Tech Parameters'!H27*'Tech Parameters'!C27+'Tech Parameters'!H28*'Tech Parameters'!C28+'Tech Parameters'!H29*'Tech Parameters'!C29))+Dashboard!M33 -> 8.6460494
A62: Gasoline | B62: $/GJ | C62: =Baseline!C62+Dashboard!B21*'Tech Parameters'!C26+Dashboard!B23*('Tech Parameters'!C26-('Tech Parameters'!H24*'Tech Parameters'!C24+'Tech Parameters'!H25*'Tech Parameters'!C25+'Tech Parameters'!H26*'Tech Parameters'!C26+'Tech Parameters'!H27*'Tech Parameters'!C27+'Tech Parameters'!H28*'Tech Parameters'!C28+'Tech Parameters'!H29*'Tech Parameters'!C29))+Dashboard!B34 -> 0 | D62: =Baseline!D62+Dashboard!C21*'Tech Parameters'!C26+Dashboard!C23*('Tech Parameters'!C26-('Tech Parameters'!H24*'Tech Parameters'!C24+'Tech Parameters'!H25*'Tech Parameters'!C25+'Tech Parameters'!H26*'Tech Parameters'!C26+'Tech Parameters'!H27*'Tech Parameters'!C27+'Tech Parameters'!H28*'Tech Parameters'!C28+'Tech Parameters'!H29*'Tech Parameters'!C29))+Dashboard!C34 -> 0 | E62: =Baseline!E62+Dashboard!D21*'Tech Parameters'!C26+Dashboard!D23*('Tech Parameters'!C26-('Tech Parameters'!H24*'Tech Parameters'!C24+'Tech Parameters'!H25*'Tech Parameters'!C25+'Tech Parameters'!H26*'Tech Parameters'!C26+'Tech Parameters'!H27*'Tech Parameters'!C27+'Tech Parameters'!H28*'Tech Parameters'!C28+'Tech Parameters'!H29*'Tech Parameters'!C29))+Dashboard!D34 -> 1.15 | F62: =Baseline!F62+Dashboard!E21*'Tech Parameters'!C26+Dashboard!E23*('Tech Parameters'!C26-('Tech Parameters'!H24*'Tech Parameters'!C24+'Tech Parameters'!H25*'Tech Parameters'!C25+'Tech Parameters'!H26*'Tech Parameters'!C26+'Tech Parameters'!H27*'Tech Parameters'!C27+'Tech Parameters'!H28*'Tech Parameters'!C28+'Tech Parameters'!H29*'Tech Parameters'!C29))+Dashboard!E34 -> 2.3102623 | G62: =Baseline!G62+Dashboard!F21*'Tech Parameters'!C26+Dashboard!F23*('Tech Parameters'!C26-('Tech Parameters'!H24*'Tech Parameters'!C24+'Tech Parameters'!H25*'Tech Parameters'!C25+'Tech Parameters'!H26*'Tech Parameters'!C26+'Tech Parameters'!H27*'Tech Parameters'!C27+'Tech Parameters'!H28*'Tech Parameters'!C28+'Tech Parameters'!H29*'Tech Parameters'!C29))+Dashboard!F34 -> 3.4705247 | H62: =Baseline!H62+Dashboard!G21*'Tech Parameters'!C26+Dashboard!G23*('Tech Parameters'!C26-('Tech Parameters'!H24*'Tech Parameters'!C24+'Tech Parameters'!H25*'Tech Parameters'!C25+'Tech Parameters'!H26*'Tech Parameters'!C26+'Tech Parameters'!H27*'Tech Parameters'!C27+'Tech Parameters'!H28*'Tech Parameters'!C28+'Tech Parameters'!H29*'Tech Parameters'!C29))+Dashboard!G34 -> 3.480787 | I62: =Baseline!I62+Dashboard!H21*'Tech Parameters'!C26+Dashboard!H23*('Tech Parameters'!C26-('Tech Parameters'!H24*'Tech Parameters'!C24+'Tech Parameters'!H25*'Tech Parameters'!C25+'Tech Parameters'!H26*'Tech Parameters'!C26+'Tech Parameters'!H27*'Tech Parameters'!C27+'Tech Parameters'!H28*'Tech Parameters'!C28+'Tech Parameters'!H29*'Tech Parameters'!C29))+Dashboard!H34 -> 3.4910494 | J62: =Baseline!J62+Dashboard!I21*'Tech Parameters'!C26+Dashboard!I23*('Tech Parameters'!C26-('Tech Parameters'!H24*'Tech Parameters'!C24+'Tech Parameters'!H25*'Tech Parameters'!C25+'Tech Parameters'!H26*'Tech Parameters'!C26+'Tech Parameters'!H27*'Tech Parameters'!C27+'Tech Parameters'!H28*'Tech Parameters'!C28+'Tech Parameters'!H29*'Tech Parameters'!C29))+Dashboard!I34 -> 3.4910494 | K62: =Baseline!K62+Dashboard!J21*'Tech Parameters'!C26+Dashboard!J23*('Tech Parameters'!C26-('Tech Parameters'!H24*'Tech Parameters'!C24+'Tech Parameters'!H25*'Tech Parameters'!C25+'Tech Parameters'!H26*'Tech Parameters'!C26+'Tech Parameters'!H27*'Tech Parameters'!C27+'Tech Parameters'!H28*'Tech Parameters'!C28+'Tech Parameters'!H29*'Tech Parameters'!C29))+Dashboard!J34 -> 3.4910494 | L62: =Baseline!L62+Dashboard!K21*'Tech Parameters'!C26+Dashboard!K23*('Tech Parameters'!C26-('Tech Parameters'!H24*'Tech Parameters'!C24+'Tech Parameters'!H25*'Tech Parameters'!C25+'Tech Parameters'!H26*'Tech Parameters'!C26+'Tech Parameters'!H27*'Tech Parameters'!C27+'Tech Parameters'!H28*'Tech Parameters'!C28+'Tech Parameters'!H29*'Tech Parameters'!C29))+Dashboard!K34 -> 3.4910494 | M62: =Baseline!M62+Dashboard!L21*'Tech Parameters'!C26+Dashboard!L23*('Tech Parameters'!C26-('Tech Parameters'!H24*'Tech Parameters'!C24+'Tech Parameters'!H25*'Tech Parameters'!C25+'Tech Parameters'!H26*'Tech Parameters'!C26+'Tech Parameters'!H27*'Tech Parameters'!C27+'Tech Parameters'!H28*'Tech Parameters'!C28+'Tech Parameters'!H29*'Tech Parameters'!C29))+Dashboard!L34 -> 3.4910494 | N62: =Baseline!N62+Dashboard!M21*'Tech Parameters'!C26+Dashboard!M23*('Tech Parameters'!C26-('Tech Parameters'!H24*'Tech Parameters'!C24+'Tech Parameters'!H25*'Tech Parameters'!C25+'Tech Parameters'!H26*'Tech Parameters'!C26+'Tech Parameters'!H27*'Tech Parameters'!C27+'Tech Parameters'!H28*'Tech Parameters'!C28+'Tech Parameters'!H29*'Tech Parameters'!C29))+Dashboard!M34 -> 3.4910494
A63: Diesel | B63: $/GJ | C63: =Baseline!C63+Dashboard!B21*'Tech Parameters'!C27+Dashboard!B23*('Tech Parameters'!C27-('Tech Parameters'!H24*'Tech Parameters'!C24+'Tech Parameters'!H25*'Tech Parameters'!C25+'Tech Parameters'!H26*'Tech Parameters'!C26+'Tech Parameters'!H27*'Tech Parameters'!C27+'Tech Parameters'!H28*'Tech Parameters'!C28+'Tech Parameters'!H29*'Tech Parameters'!C29))+Dashboard!B35 -> 14 | D63: =Baseline!D63+Dashboard!C21*'Tech Parameters'!C27+Dashboard!C23*('Tech Parameters'!C27-('Tech Parameters'!H24*'Tech Parameters'!C24+'Tech Parameters'!H25*'Tech Parameters'!C25+'Tech Parameters'!H26*'Tech Parameters'!C26+'Tech Parameters'!H27*'Tech Parameters'!C27+'Tech Parameters'!H28*'Tech Parameters'!C28+'Tech Parameters'!H29*'Tech Parameters'!C29))+Dashboard!C35 -> 14 | E63: =Baseline!E63+Dashboard!D21*'Tech Parameters'!C27+Dashboard!D23*('Tech Parameters'!C27-('Tech Parameters'!H24*'Tech Parameters'!C24+'Tech Parameters'!H25*'Tech Parameters'!C25+'Tech Parameters'!H26*'Tech Parameters'!C26+'Tech Parameters'!H27*'Tech Parameters'!C27+'Tech Parameters'!H28*'Tech Parameters'!C28+'Tech Parameters'!H29*'Tech Parameters'!C29))+Dashboard!D35 -> 15.233333 | F63: =Baseline!F63+Dashboard!E21*'Tech Parameters'!C27+Dashboard!E23*('Tech Parameters'!C27-('Tech Parameters'!H24*'Tech Parameters'!C24+'Tech Parameters'!H25*'Tech Parameters'!C25+'Tech Parameters'!H26*'Tech Parameters'!C26+'Tech Parameters'!H27*'Tech Parameters'!C27+'Tech Parameters'!H28*'Tech Parameters'!C28+'Tech Parameters'!H29*'Tech Parameters'!C29))+Dashboard!E35 -> 16.495679 | G63: =Baseline!G63+Dashboard!F21*'Tech Parameters'!C27+Dashboard!F23*('Tech Parameters'!C27-('Tech Parameters'!H24*'Tech Parameters'!C24+'Tech Parameters'!H25*'Tech Parameters'!C25+'Tech Parameters'!H26*'Tech Parameters'!C26+'Tech Parameters'!H27*'Tech Parameters'!C27+'Tech Parameters'!H28*'Tech Parameters'!C28+'Tech Parameters'!H29*'Tech Parameters'!C29))+Dashboard!F35 -> 17.758025 | H63: =Baseline!H63+Dashboard!G21*'Tech Parameters'!C27+Dashboard!G23*('Tech Parameters'!C27-('Tech Parameters'!H24*'Tech Parameters'!C24+'Tech Parameters'!H25*'Tech Parameters'!C25+'Tech Parameters'!H26*'Tech Parameters'!C26+'Tech Parameters'!H27*'Tech Parameters'!C27+'Tech Parameters'!H28*'Tech Parameters'!C28+'Tech Parameters'!H29*'Tech Parameters'!C29))+Dashboard!G35 -> 17.787037 | I63: =Baseline!I63+Dashboard!H21*'Tech Parameters'!C27+Dashboard!H23*('Tech Parameters'!C27-('Tech Parameters'!H24*'Tech Parameters'!C24+'Tech Parameters'!H25*'Tech Parameters'!C25+'Tech Parameters'!H26*'Tech Parameters'!C26+'Tech Parameters'!H27*'Tech Parameters'!C27+'Tech Parameters'!H28*'Tech Parameters'!C28+'Tech Parameters'!H29*'Tech Parameters'!C29))+Dashboard!H35 -> 17.816049 | J63: =Baseline!J63+Dashboard!I21*'Tech Parameters'!C27+Dashboard!I23*('Tech Parameters'!C27-('Tech Parameters'!H24*'Tech Parameters'!C24+'Tech Parameters'!H25*'Tech Parameters'!C25+'Tech Parameters'!H26*'Tech Parameters'!C26+'Tech Parameters'!H27*'Tech Parameters'!C27+'Tech Parameters'!H28*'Tech Parameters'!C28+'Tech Parameters'!H29*'Tech Parameters'!C29))+Dashboard!I35 -> 17.816049 | K63: =Baseline!K63+Dashboard!J21*'Tech Parameters'!C27+Dashboard!J23*('Tech Parameters'!C27-('Tech Parameters'!H24*'Tech Parameters'!C24+'Tech Parameters'!H25*'Tech Parameters'!C25+'Tech Parameters'!H26*'Tech Parameters'!C26+'Tech Parameters'!H27*'Tech Parameters'!C27+'Tech Parameters'!H28*'Tech Parameters'!C28+'Tech Parameters'!H29*'Tech Parameters'!C29))+Dashboard!J35 -> 17.816049 | L63: =Baseline!L63+Dashboard!K21*'Tech Parameters'!C27+Dashboard!K23*('Tech Parameters'!C27-('Tech Parameters'!H24*'Tech Parameters'!C24+'Tech Parameters'!H25*'Tech Parameters'!C25+'Tech Parameters'!H26*'Tech Parameters'!C26+'Tech Parameters'!H27*'Tech Parameters'!C27+'Tech Parameters'!H28*'Tech Parameters'!C28+'Tech Parameters'!H29*'Tech Parameters'!C29))+Dashboard!K35 -> 17.816049 | M63: =Baseline!M63+Dashboard!L21*'Tech Parameters'!C27+Dashboard!L23*('Tech Parameters'!C27-('Tech Parameters'!H24*'Tech Parameters'!C24+'Tech Parameters'!H25*'Tech Parameters'!C25+'Tech Parameters'!H26*'Tech Parameters'!C26+'Tech Parameters'!H27*'Tech Parameters'!C27+'Tech Parameters'!H28*'Tech Parameters'!C28+'Tech Parameters'!H29*'Tech Parameters'!C29))+Dashboard!L35 -> 17.816049 | N63: =Baseline!N63+Dashboard!M21*'Tech Parameters'!C27+Dashboard!M23*('Tech Parameters'!C27-('Tech Parameters'!H24*'Tech Parameters'!C24+'Tech Parameters'!H25*'Tech Parameters'!C25+'Tech Parameters'!H26*'Tech Parameters'!C26+'Tech Parameters'!H27*'Tech Parameters'!C27+'Tech Parameters'!H28*'Tech Parameters'!C28+'Tech Parameters'!H29*'Tech Parameters'!C29))+Dashboard!M35 -> 17.816049
A64: Electricity | B64: $/GJ | C64: =Baseline!C64+Dashboard!B21*'Tech Parameters'!C28+Dashboard!B23*('Tech Parameters'!C28-('Tech Parameters'!H24*'Tech Parameters'!C24+'Tech Parameters'!H25*'Tech Parameters'!C25+'Tech Parameters'!H26*'Tech Parameters'!C26+'Tech Parameters'!H27*'Tech Parameters'!C27+'Tech Parameters'!H28*'Tech Parameters'!C28+'Tech Parameters'!H29*'Tech Parameters'!C29))+Dashboard!B36 -> 0 | D64: =Baseline!D64+Dashboard!C21*'Tech Parameters'!C28+Dashboard!C23*('Tech Parameters'!C28-('Tech Parameters'!H24*'Tech Parameters'!C24+'Tech Parameters'!H25*'Tech Parameters'!C25+'Tech Parameters'!H26*'Tech Parameters'!C26+'Tech Parameters'!H27*'Tech Parameters'!C27+'Tech Parameters'!H28*'Tech Parameters'!C28+'Tech Parameters'!H29*'Tech Parameters'!C29))+Dashboard!C36 -> 0 | E64: =Baseline!E64+Dashboard!D21*'Tech Parameters'!C28+Dashboard!D23*('Tech Parameters'!C28-('Tech Parameters'!H24*'Tech Parameters'!C24+'Tech Parameters'!H25*'Tech Parameters'!C25+'Tech Parameters'!H26*'Tech Parameters'!C26+'Tech Parameters'!H27*'Tech Parameters'!C27+'Tech Parameters'!H28*'Tech Parameters'!C28+'Tech Parameters'!H29*'Tech Parameters'!C29))+Dashboard!D36 -> 0 | F64: =Baseline!F64+Dashboard!E21*'Tech Parameters'!C28+Dashboard!E23*('Tech Parameters'!C28-('Tech Parameters'!H24*'Tech Parameters'!C24+'Tech Parameters'!H25*'Tech Parameters'!C25+'Tech Parameters'!H26*'Tech Parameters'!C26+'Tech Parameters'!H27*'Tech Parameters'!C27+'Tech Parameters'!H28*'Tech Parameters'!C28+'Tech Parameters'!H29*'Tech Parameters'!C29))+Dashboard!E36 -> -0.24848765 | G64: =Baseline!G64+Dashboard!F21*'Tech Parameters'!C28+Dashboard!F23*('Tech Parameters'!C28-('Tech Parameters'!H24*'Tech Parameters'!C24+'Tech Parameters'!H25*'Tech Parameters'!C25+'Tech Parameters'!H26*'Tech Parameters'!C26+'Tech Parameters'!H27*'Tech Parameters'!C27+'Tech Parameters'!H28*'Tech Parameters'!C28+'Tech Parameters'!H29*'Tech Parameters'!C29))+Dashboard!F36 -> -0.49697531 | H64: =Baseline!H64+Dashboard!G21*'Tech Parameters'!C28+Dashboard!G23*('Tech Parameters'!C28-('Tech Parameters'!H24*'Tech Parameters'!C24+'Tech Parameters'!H25*'Tech Parameters'!C25+'Tech Parameters'!H26*'Tech Parameters'!C26+'Tech Parameters'!H27*'Tech Parameters'!C27+'Tech Parameters'!H28*'Tech Parameters'!C28+'Tech Parameters'!H29*'Tech Parameters'!C29))+Dashboard!G36 -> -0.74546296 | I64: =Baseline!I64+Dashboard!H21*'Tech Parameters'!C28+Dashboard!H23*('Tech Parameters'!C28-('Tech Parameters'!H24*'Tech Parameters'!C24+'Tech Parameters'!H25*'Tech Parameters'!C25+'Tech Parameters'!H26*'Tech Parameters'!C26+'Tech Parameters'!H27*'Tech Parameters'!C27+'Tech Parameters'!H28*'Tech Parameters'!C28+'Tech Parameters'!H29*'Tech Parameters'!C29))+Dashboard!H36 -> -0.99395062 | J64: =Baseline!J64+Dashboard!I21*'Tech Parameters'!C28+Dashboard!I23*('Tech Parameters'!C28-('Tech Parameters'!H24*'Tech Parameters'!C24+'Tech Parameters'!H25*'Tech Parameters'!C25+'Tech Parameters'!H26*'Tech Parameters'!C26+'Tech Parameters'!H27*'Tech Parameters'!C27+'Tech Parameters'!H28*'Tech Parameters'!C28+'Tech Parameters'!H29*'Tech Parameters'!C29))+Dashboard!I36 -> -0.99395062 | K64: =Baseline!K64+Dashboard!J21*'Tech Parameters'!C28+Dashboard!J23*('Tech Parameters'!C28-('Tech Parameters'!H24*'Tech Parameters'!C24+'Tech Parameters'!H25*'Tech Parameters'!C25+'Tech Parameters'!H26*'Tech Parameters'!C26+'Tech Parameters'!H27*'Tech Parameters'!C27+'Tech Parameters'!H28*'Tech Parameters'!C28+'Tech Parameters'!H29*'Tech Parameters'!C29))+Dashboard!J36 -> -0.99395062 | L64: =Baseline!L64+Dashboard!K21*'Tech Parameters'!C28+Dashboard!K23*('Tech Parameters'!C28-('Tech Parameters'!H24*'Tech Parameters'!C24+'Tech Parameters'!H25*'Tech Parameters'!C25+'Tech Parameters'!H26*'Tech Parameters'!C26+'Tech Parameters'!H27*'Tech Parameters'!C27+'Tech Parameters'!H28*'Tech Parameters'!C28+'Tech Parameters'!H29*'Tech Parameters'!C29))+Dashboard!K36 -> -0.99395062 | M64: =Baseline!M64+Dashboard!L21*'Tech Parameters'!C28+Dashboard!L23*('Tech Parameters'!C28-('Tech Parameters'!H24*'Tech Parameters'!C24+'Tech Parameters'!H25*'Tech Parameters'!C25+'Tech Parameters'!H26*'Tech Parameters'!C26+'Tech Parameters'!H27*'Tech Parameters'!C27+'Tech Parameters'!H28*'Tech Parameters'!C28+'Tech Parameters'!H29*'Tech Parameters'!C29))+Dashboard!L36 -> -0.99395062 | N64: =Baseline!N64+Dashboard!M21*'Tech Parameters'!C28+Dashboard!M23*('Tech Parameters'!C28-('Tech Parameters'!H24*'Tech Parameters'!C24+'Tech Parameters'!H25*'Tech Parameters'!C25+'Tech Parameters'!H26*'Tech Parameters'!C26+'Tech Parameters'!H27*'Tech Parameters'!C27+'Tech Parameters'!H28*'Tech Parameters'!C28+'Tech Parameters'!H29*'Tech Parameters'!C29))+Dashboard!M36 -> -0.99395062
A65: RE generation | B65: $/GJ | C65: =Baseline!C65+Dashboard!B21*'Tech Parameters'!C29+Dashboard!B23*('Tech Parameters'!C29-('Tech Parameters'!H24*'Tech Parameters'!C24+'Tech Parameters'!H25*'Tech Parameters'!C25+'Tech Parameters'!H26*'Tech Parameters'!C26+'Tech Parameters'!H27*'Tech Parameters'!C27+'Tech Parameters'!H28*'Tech Parameters'!C28+'Tech Parameters'!H29*'Tech Parameters'!C29))+Dashboard!B37 -> 2 | D65: =Baseline!D65+Dashboard!C21*'Tech Parameters'!C29+Dashboard!C23*('Tech Parameters'!C29-('Tech Parameters'!H24*'Tech Parameters'!C24+'Tech Parameters'!H25*'Tech Parameters'!C25+'Tech Parameters'!H26*'Tech Parameters'!C26+'Tech Parameters'!H27*'Tech Parameters'!C27+'Tech Parameters'!H28*'Tech Parameters'!C28+'Tech Parameters'!H29*'Tech Parameters'!C29))+Dashboard!C37 -> 2 | E65: =Baseline!E65+Dashboard!D21*'Tech Parameters'!C29+Dashboard!D23*('Tech Parameters'!C29-('Tech Parameters'!H24*'Tech Parameters'!C24+'Tech Parameters'!H25*'Tech Parameters'!C25+'Tech Parameters'!H26*'Tech Parameters'!C26+'Tech Parameters'!H27*'Tech Parameters'!C27+'Tech Parameters'!H28*'Tech Parameters'!C28+'Tech Parameters'!H29*'Tech Parameters'!C29))+Dashboard!D37 -> 2 | F65: =Baseline!F65+Dashboard!E21*'Tech Parameters'!C29+Dashboard!E23*('Tech Parameters'!C29-('Tech Parameters'!H24*'Tech Parameters'!C24+'Tech Parameters'!H25*'Tech Parameters'!C25+'Tech Parameters'!H26*'Tech Parameters'!C26+'Tech Parameters'!H27*'Tech Parameters'!C27+'Tech Parameters'!H28*'Tech Parameters'!C28+'Tech Parameters'!H29*'Tech Parameters'!C29))+Dashboard!E37 -> 1.7515123 | G65: =Baseline!G65+Dashboard!F21*'Tech Parameters'!C29+Dashboard!F23*('Tech Parameters'!C29-('Tech Parameters'!H24*'Tech Parameters'!C24+'Tech Parameters'!H25*'Tech Parameters'!C25+'Tech Parameters'!H26*'Tech Parameters'!C26+'Tech Parameters'!H27*'Tech Parameters'!C27+'Tech Parameters'!H28*'Tech Parameters'!C28+'Tech Parameters'!H29*'Tech Parameters'!C29))+Dashboard!F37 -> 1.5030247 | H65: =Baseline!H65+Dashboard!G21*'Tech Parameters'!C29+Dashboard!G23*('Tech Parameters'!C29-('Tech Parameters'!H24*'Tech Parameters'!C24+'Tech Parameters'!H25*'Tech Parameters'!C25+'Tech Parameters'!H26*'Tech Parameters'!C26+'Tech Parameters'!H27*'Tech Parameters'!C27+'Tech Parameters'!H28*'Tech Parameters'!C28+'Tech Parameters'!H29*'Tech Parameters'!C29))+Dashboard!G37 -> 1.254537 | I65: =Baseline!I65+Dashboard!H21*'Tech Parameters'!C29+Dashboard!H23*('Tech Parameters'!C29-('Tech Parameters'!H24*'Tech Parameters'!C24+'Tech Parameters'!H25*'Tech Parameters'!C25+'Tech Parameters'!H26*'Tech Parameters'!C26+'Tech Parameters'!H27*'Tech Parameters'!C27+'Tech Parameters'!H28*'Tech Parameters'!C28+'Tech Parameters'!H29*'Tech Parameters'!C29))+Dashboard!H37 -> 1.0060494 | J65: =Baseline!J65+Dashboard!I21*'Tech Parameters'!C29+Dashboard!I23*('Tech Parameters'!C29-('Tech Parameters'!H24*'Tech Parameters'!C24+'Tech Parameters'!H25*'Tech Parameters'!C25+'Tech Parameters'!H26*'Tech Parameters'!C26+'Tech Parameters'!H27*'Tech Parameters'!C27+'Tech Parameters'!H28*'Tech Parameters'!C28+'Tech Parameters'!H29*'Tech Parameters'!C29))+Dashboard!I37 -> 1.0060494 | K65: =Baseline!K65+Dashboard!J21*'Tech Parameters'!C29+Dashboard!J23*('Tech Parameters'!C29-('Tech Parameters'!H24*'Tech Parameters'!C24+'Tech Parameters'!H25*'Tech Parameters'!C25+'Tech Parameters'!H26*'Tech Parameters'!C26+'Tech Parameters'!H27*'Tech Parameters'!C27+'Tech Parameters'!H28*'Tech Parameters'!C28+'Tech Parameters'!H29*'Tech Parameters'!C29))+Dashboard!J37 -> 1.0060494 | L65: =Baseline!L65+Dashboard!K21*'Tech Parameters'!C29+Dashboard!K23*('Tech Parameters'!C29-('Tech Parameters'!H24*'Tech Parameters'!C24+'Tech Parameters'!H25*'Tech Parameters'!C25+'Tech Parameters'!H26*'Tech Parameters'!C26+'Tech Parameters'!H27*'Tech Parameters'!C27+'Tech Parameters'!H28*'Tech Parameters'!C28+'Tech Parameters'!H29*'Tech Parameters'!C29))+Dashboard!K37 -> 1.0060494 | M65: =Baseline!M65+Dashboard!L21*'Tech Parameters'!C29+Dashboard!L23*('Tech Parameters'!C29-('Tech Parameters'!H24*'Tech Parameters'!C24+'Tech Parameters'!H25*'Tech Parameters'!C25+'Tech Parameters'!H26*'Tech Parameters'!C26+'Tech Parameters'!H27*'Tech Parameters'!C27+'Tech Parameters'!H28*'Tech Parameters'!C28+'Tech Parameters'!H29*'Tech Parameters'!C29))+Dashboard!L37 -> 1.0060494 | N65: =Baseline!N65+Dashboard!M21*'Tech Parameters'!C29+Dashboard!M23*('Tech Parameters'!C29-('Tech Parameters'!H24*'Tech Parameters'!C24+'Tech Parameters'!H25*'Tech Parameters'!C25+'Tech Parameters'!H26*'Tech Parameters'!C26+'Tech Parameters'!H27*'Tech Parameters'!C27+'Tech Parameters'!H28*'Tech Parameters'!C28+'Tech Parameters'!H29*'Tech Parameters'!C29))+Dashboard!M37 -> 1.0060494
A67: ELECTRICITY GEN. — Effective Prices ($/GJ svc)
A68: Coal | B68: $/GJ svc | C68: =IF('Tech Parameters'!E24=0,0,C60/'Tech Parameters'!E24) -> 7.8947368 | D68: =IF('Tech Parameters'!E24=0,0,D60/'Tech Parameters'!E24) -> 7.8947368 | E68: =IF('Tech Parameters'!E24=0,0,E60/'Tech Parameters'!E24) -> 12.061404 | F68: =IF('Tech Parameters'!E24=0,0,F60/'Tech Parameters'!E24) -> 16.511655 | G68: =IF('Tech Parameters'!E24=0,0,G60/'Tech Parameters'!E24) -> 20.961907 | H68: =IF('Tech Parameters'!E24=0,0,H60/'Tech Parameters'!E24) -> 21.245492 | I68: =IF('Tech Parameters'!E24=0,0,I60/'Tech Parameters'!E24) -> 21.529077 | J68: =IF('Tech Parameters'!E24=0,0,J60/'Tech Parameters'!E24) -> 21.529077 | K68: =IF('Tech Parameters'!E24=0,0,K60/'Tech Parameters'!E24) -> 21.529077 | L68: =IF('Tech Parameters'!E24=0,0,L60/'Tech Parameters'!E24) -> 21.529077 | M68: =IF('Tech Parameters'!E24=0,0,M60/'Tech Parameters'!E24) -> 21.529077 | N68: =IF('Tech Parameters'!E24=0,0,N60/'Tech Parameters'!E24) -> 21.529077
A69: Natural gas | B69: $/GJ svc | C69: =IF('Tech Parameters'!E25=0,0,C61/'Tech Parameters'!E25) -> 12 | D69: =IF('Tech Parameters'!E25=0,0,D61/'Tech Parameters'!E25) -> 12 | E69: =IF('Tech Parameters'!E25=0,0,E61/'Tech Parameters'!E25) -> 13.866667 | F69: =IF('Tech Parameters'!E25=0,0,F61/'Tech Parameters'!E25) -> 15.656358 | G69: =IF('Tech Parameters'!E25=0,0,G61/'Tech Parameters'!E25) -> 17.446049 | H69: =IF('Tech Parameters'!E25=0,0,H61/'Tech Parameters'!E25) -> 17.369074 | I69: =IF('Tech Parameters'!E25=0,0,I61/'Tech Parameters'!E25) -> 17.292099 | J69: =IF('Tech Parameters'!E25=0,0,J61/'Tech Parameters'!E25) -> 17.292099 | K69: =IF('Tech Parameters'!E25=0,0,K61/'Tech Parameters'!E25) -> 17.292099 | L69: =IF('Tech Parameters'!E25=0,0,L61/'Tech Parameters'!E25) -> 17.292099 | M69: =IF('Tech Parameters'!E25=0,0,M61/'Tech Parameters'!E25) -> 17.292099 | N69: =IF('Tech Parameters'!E25=0,0,N61/'Tech Parameters'!E25) -> 17.292099
A70: Gasoline | B70: $/GJ svc | C70: =IF('Tech Parameters'!E26=0,0,C62/'Tech Parameters'!E26) -> 0 | D70: =IF('Tech Parameters'!E26=0,0,D62/'Tech Parameters'!E26) -> 0 | E70: =IF('Tech Parameters'!E26=0,0,E62/'Tech Parameters'!E26) -> 0 | F70: =IF('Tech Parameters'!E26=0,0,F62/'Tech Parameters'!E26) -> 0 | G70: =IF('Tech Parameters'!E26=0,0,G62/'Tech Parameters'!E26) -> 0 | H70: =IF('Tech Parameters'!E26=0,0,H62/'Tech Parameters'!E26) -> 0 | I70: =IF('Tech Parameters'!E26=0,0,I62/'Tech Parameters'!E26) -> 0 | J70: =IF('Tech Parameters'!E26=0,0,J62/'Tech Parameters'!E26) -> 0 | K70: =IF('Tech Parameters'!E26=0,0,K62/'Tech Parameters'!E26) -> 0 | L70: =IF('Tech Parameters'!E26=0,0,L62/'Tech Parameters'!E26) -> 0 | M70: =IF('Tech Parameters'!E26=0,0,M62/'Tech Parameters'!E26) -> 0 | N70: =IF('Tech Parameters'!E26=0,0,N62/'Tech Parameters'!E26) -> 0
A71: Diesel | B71: $/GJ svc | C71: =IF('Tech Parameters'!E27=0,0,C63/'Tech Parameters'!E27) -> 40 | D71: =IF('Tech Parameters'!E27=0,0,D63/'Tech Parameters'!E27) -> 40 | E71: =IF('Tech Parameters'!E27=0,0,E63/'Tech Parameters'!E27) -> 43.52381 | F71: =IF('Tech Parameters'!E27=0,0,F63/'Tech Parameters'!E27) -> 47.130511 | G71: =IF('Tech Parameters'!E27=0,0,G63/'Tech Parameters'!E27) -> 50.737213 | H71: =IF('Tech Parameters'!E27=0,0,H63/'Tech Parameters'!E27) -> 50.820106 | I71: =IF('Tech Parameters'!E27=0,0,I63/'Tech Parameters'!E27) -> 50.902998 | J71: =IF('Tech Parameters'!E27=0,0,J63/'Tech Parameters'!E27) -> 50.902998 | K71: =IF('Tech Parameters'!E27=0,0,K63/'Tech Parameters'!E27) -> 50.902998 | L71: =IF('Tech Parameters'!E27=0,0,L63/'Tech Parameters'!E27) -> 50.902998 | M71: =IF('Tech Parameters'!E27=0,0,M63/'Tech Parameters'!E27) -> 50.902998 | N71: =IF('Tech Parameters'!E27=0,0,N63/'Tech Parameters'!E27) -> 50.902998
A72: Electricity | B72: $/GJ svc | C72: =IF('Tech Parameters'!E28=0,0,C64/'Tech Parameters'!E28) -> 0 | D72: =IF('Tech Parameters'!E28=0,0,D64/'Tech Parameters'!E28) -> 0 | E72: =IF('Tech Parameters'!E28=0,0,E64/'Tech Parameters'!E28) -> 0 | F72: =IF('Tech Parameters'!E28=0,0,F64/'Tech Parameters'!E28) -> 0 | G72: =IF('Tech Parameters'!E28=0,0,G64/'Tech Parameters'!E28) -> 0 | H72: =IF('Tech Parameters'!E28=0,0,H64/'Tech Parameters'!E28) -> 0 | I72: =IF('Tech Parameters'!E28=0,0,I64/'Tech Parameters'!E28) -> 0 | J72: =IF('Tech Parameters'!E28=0,0,J64/'Tech Parameters'!E28) -> 0 | K72: =IF('Tech Parameters'!E28=0,0,K64/'Tech Parameters'!E28) -> 0 | L72: =IF('Tech Parameters'!E28=0,0,L64/'Tech Parameters'!E28) -> 0 | M72: =IF('Tech Parameters'!E28=0,0,M64/'Tech Parameters'!E28) -> 0 | N72: =IF('Tech Parameters'!E28=0,0,N64/'Tech Parameters'!E28) -> 0
A73: RE generation | B73: $/GJ svc | C73: =IF('Tech Parameters'!E29=0,0,C65/'Tech Parameters'!E29) -> 2 | D73: =IF('Tech Parameters'!E29=0,0,D65/'Tech Parameters'!E29) -> 2 | E73: =IF('Tech Parameters'!E29=0,0,E65/'Tech Parameters'!E29) -> 2 | F73: =IF('Tech Parameters'!E29=0,0,F65/'Tech Parameters'!E29) -> 1.7515123 | G73: =IF('Tech Parameters'!E29=0,0,G65/'Tech Parameters'!E29) -> 1.5030247 | H73: =IF('Tech Parameters'!E29=0,0,H65/'Tech Parameters'!E29) -> 1.254537 | I73: =IF('Tech Parameters'!E29=0,0,I65/'Tech Parameters'!E29) -> 1.0060494 | J73: =IF('Tech Parameters'!E29=0,0,J65/'Tech Parameters'!E29) -> 1.0060494 | K73: =IF('Tech Parameters'!E29=0,0,K65/'Tech Parameters'!E29) -> 1.0060494 | L73: =IF('Tech Parameters'!E29=0,0,L65/'Tech Parameters'!E29) -> 1.0060494 | M73: =IF('Tech Parameters'!E29=0,0,M65/'Tech Parameters'!E29) -> 1.0060494 | N73: =IF('Tech Parameters'!E29=0,0,N65/'Tech Parameters'!E29) -> 1.0060494
A75: ELECTRICITY GEN. — CES Cost Index
C77: =IF(C68=0,0,C68^(1-'Tech Parameters'!$C$5)) -> 1.5117067 | D77: =IF(D68=0,0,D68^(1-'Tech Parameters'!$C$5)) -> 1.5117067 | E77: =IF(E68=0,0,E68^(1-'Tech Parameters'!$C$5)) -> 1.6454306 | F77: =IF(F68=0,0,F68^(1-'Tech Parameters'!$C$5)) -> 1.7520969 | G77: =IF(G68=0,0,G68^(1-'Tech Parameters'!$C$5)) -> 1.8377488 | H77: =IF(H68=0,0,H68^(1-'Tech Parameters'!$C$5)) -> 1.8426946 | I77: =IF(I68=0,0,I68^(1-'Tech Parameters'!$C$5)) -> 1.8475878 | J77: =IF(J68=0,0,J68^(1-'Tech Parameters'!$C$5)) -> 1.8475878 | ... N77: =IF(N68=0,0,N68^(1-'Tech Parameters'!$C$5)) -> 1.8475878
C78: =IF(C69=0,0,C69^(1-'Tech Parameters'!$C$5)) -> 1.6437518 | D78: =IF(D69=0,0,D69^(1-'Tech Parameters'!$C$5)) -> 1.6437518 | E78: =IF(E69=0,0,E69^(1-'Tech Parameters'!$C$5)) -> 1.6919768 | F78: =IF(F69=0,0,F69^(1-'Tech Parameters'!$C$5)) -> 1.7335571 | G78: =IF(G69=0,0,G69^(1-'Tech Parameters'!$C$5)) -> 1.7714929 | H78: =IF(H69=0,0,H69^(1-'Tech Parameters'!$C$5)) -> 1.7699269 | I78: =IF(I69=0,0,I69^(1-'Tech Parameters'!$C$5)) -> 1.7683554 | J78: =IF(J69=0,0,J69^(1-'Tech Parameters'!$C$5)) -> 1.7683554 | ... N78: =IF(N69=0,0,N69^(1-'Tech Parameters'!$C$5)) -> 1.7683554
C79: =IF(C70=0,0,C70^(1-'Tech Parameters'!$C$5)) -> 0 | D79: =IF(D70=0,0,D70^(1-'Tech Parameters'!$C$5)) -> 0 | E79: =IF(E70=0,0,E70^(1-'Tech Parameters'!$C$5)) -> 0 | F79: =IF(F70=0,0,F70^(1-'Tech Parameters'!$C$5)) -> 0 | G79: =IF(G70=0,0,G70^(1-'Tech Parameters'!$C$5)) -> 0 | H79: =IF(H70=0,0,H70^(1-'Tech Parameters'!$C$5)) -> 0 | I79: =IF(I70=0,0,I70^(1-'Tech Parameters'!$C$5)) -> 0 | J79: =IF(J70=0,0,J70^(1-'Tech Parameters'!$C$5)) -> 0 | ... N79: =IF(N70=0,0,N70^(1-'Tech Parameters'!$C$5)) -> 0
C80: =IF(C71=0,0,C71^(1-'Tech Parameters'!$C$5)) -> 2.0912791 | D80: =IF(D71=0,0,D71^(1-'Tech Parameters'!$C$5)) -> 2.0912791 | E80: =IF(E71=0,0,E71^(1-'Tech Parameters'!$C$5)) -> 2.1268917 | F80: =IF(F71=0,0,F71^(1-'Tech Parameters'!$C$5)) -> 2.1610282 | G80: =IF(G71=0,0,G71^(1-'Tech Parameters'!$C$5)) -> 2.1931348 | H80: =IF(H71=0,0,H71^(1-'Tech Parameters'!$C$5)) -> 2.1938509 | I80: =IF(I71=0,0,I71^(1-'Tech Parameters'!$C$5)) -> 2.1945661 | J80: =IF(J71=0,0,J71^(1-'Tech Parameters'!$C$5)) -> 2.1945661 | ... N80: =IF(N71=0,0,N71^(1-'Tech Parameters'!$C$5)) -> 2.1945661
C81: =IF(C72=0,0,C72^(1-'Tech Parameters'!$C$5)) -> 0 | D81: =IF(D72=0,0,D72^(1-'Tech Parameters'!$C$5)) -> 0 | E81: =IF(E72=0,0,E72^(1-'Tech Parameters'!$C$5)) -> 0 | F81: =IF(F72=0,0,F72^(1-'Tech Parameters'!$C$5)) -> 0 | G81: =IF(G72=0,0,G72^(1-'Tech Parameters'!$C$5)) -> 0 | H81: =IF(H72=0,0,H72^(1-'Tech Parameters'!$C$5)) -> 0 | I81: =IF(I72=0,0,I72^(1-'Tech Parameters'!$C$5)) -> 0 | J81: =IF(J72=0,0,J72^(1-'Tech Parameters'!$C$5)) -> 0 | ... N81: =IF(N72=0,0,N72^(1-'Tech Parameters'!$C$5)) -> 0
C82: =IF(C73=0,0,C73^(1-'Tech Parameters'!$C$5)) -> 1.1486984 | D82: =IF(D73=0,0,D73^(1-'Tech Parameters'!$C$5)) -> 1.1486984 | E82: =IF(E73=0,0,E73^(1-'Tech Parameters'!$C$5)) -> 1.1486984 | F82: =IF(F73=0,0,F73^(1-'Tech Parameters'!$C$5)) -> 1.1186202 | G82: =IF(G73=0,0,G73^(1-'Tech Parameters'!$C$5)) -> 1.0849088 | H82: =IF(H73=0,0,H73^(1-'Tech Parameters'!$C$5)) -> 1.0463975 | I82: =IF(I73=0,0,I73^(1-'Tech Parameters'!$C$5)) -> 1.001207 | J82: =IF(J73=0,0,J73^(1-'Tech Parameters'!$C$5)) -> 1.001207 | ... N82: =IF(N73=0,0,N73^(1-'Tech Parameters'!$C$5)) -> 1.001207
C83: ='Tech Parameters'!J24 -> 0.37422037 | D83: ='Tech Parameters'!J25 -> 0.4989605 | E83: ='Tech Parameters'!J26 -> 0 | F83: ='Tech Parameters'!J27 -> 0.043659044 | G83: ='Tech Parameters'!J28 -> 0 | H83: ='Tech Parameters'!J29 -> 0.083160083
A84: C(t) | B84: $/GJ svc | C84: =(C83*C77+D83*C78+E83*C79+F83*C80+G83*C81+H83*C82)^(1/(1-'Tech Parameters'!$C$5)) -> 9.6214419 | D84: =(C83*D77+D83*D78+E83*D79+F83*D80+G83*D81+H83*D82)^(1/(1-'Tech Parameters'!$C$5)) -> 9.6214419 | E84: =(C83*E77+D83*E78+E83*E79+F83*E80+G83*E81+H83*E82)^(1/(1-'Tech Parameters'!$C$5)) -> 12.169417 | F84: =(C83*F77+D83*F78+E83*F79+F83*F80+G83*F81+H83*F82)^(1/(1-'Tech Parameters'!$C$5)) -> 14.536657 | G84: =(C83*G77+D83*G78+E83*G79+F83*G80+G83*G81+H83*G82)^(1/(1-'Tech Parameters'!$C$5)) -> 16.772561 | H84: =(C83*H77+D83*H78+E83*H79+F83*H80+G83*H81+H83*H82)^(1/(1-'Tech Parameters'!$C$5)) -> 16.672509 | I84: =(C83*I77+D83*I78+E83*I79+F83*I80+G83*I81+H83*I82)^(1/(1-'Tech Parameters'!$C$5)) -> 16.545641 | J84: =(C83*J77+D83*J78+E83*J79+F83*J80+G83*J81+H83*J82)^(1/(1-'Tech Parameters'!$C$5)) -> 16.545641 | K84: =(C83*K77+D83*K78+E83*K79+F83*K80+G83*K81+H83*K82)^(1/(1-'Tech Parameters'!$C$5)) -> 16.545641 | L84: =(C83*L77+D83*L78+E83*L79+F83*L80+G83*L81+H83*L82)^(1/(1-'Tech Parameters'!$C$5)) -> 16.545641 | M84: =(C83*M77+D83*M78+E83*M79+F83*M80+G83*M81+H83*M82)^(1/(1-'Tech Parameters'!$C$5)) -> 16.545641 | N84: =(C83*N77+D83*N78+E83*N79+F83*N80+G83*N81+H83*N82)^(1/(1-'Tech Parameters'!$C$5)) -> 16.545641
A86: ELECTRICITY GEN. — Equilibrium Quantities (PJ)
A87: Coal | B87: PJ | C87: ='Tech Parameters'!D24 -> 1200 | D87: =IF(OR(D68=0,C68=0),C96,C96*(D68/C68)^(-'Tech Parameters'!$C$5)*(D84/C84)^('Tech Parameters'!$C$5+'Tech Parameters'!$C$6)) -> 1200 | E87: =IF(OR(E68=0,D68=0),D96,D96*(E68/D68)^(-'Tech Parameters'!$C$5)*(E84/D84)^('Tech Parameters'!$C$5+'Tech Parameters'!$C$6)) -> 995.98398 | F87: =IF(OR(F68=0,E68=0),E96,E96*(F68/E68)^(-'Tech Parameters'!$C$5)*(F84/E84)^('Tech Parameters'!$C$5+'Tech Parameters'!$C$6)) -> 1033.4661 | G87: =IF(OR(G68=0,F68=0),F96,F96*(G68/F68)^(-'Tech Parameters'!$C$5)*(G84/F84)^('Tech Parameters'!$C$5+'Tech Parameters'!$C$6)) -> 1062.3747 | H87: =IF(OR(H68=0,G68=0),G96,G96*(H68/G68)^(-'Tech Parameters'!$C$5)*(H84/G84)^('Tech Parameters'!$C$5+'Tech Parameters'!$C$6)) -> 1146.0184 | I87: =IF(OR(I68=0,H68=0),H96,H96*(I68/H68)^(-'Tech Parameters'!$C$5)*(I84/H84)^('Tech Parameters'!$C$5+'Tech Parameters'!$C$6)) -> 1143.618 | J87: =IF(OR(J68=0,I68=0),I96,I96*(J68/I68)^(-'Tech Parameters'!$C$5)*(J84/I84)^('Tech Parameters'!$C$5+'Tech Parameters'!$C$6)) -> 1160.1308 | K87: =IF(OR(K68=0,J68=0),J96,J96*(K68/J68)^(-'Tech Parameters'!$C$5)*(K84/J84)^('Tech Parameters'!$C$5+'Tech Parameters'!$C$6)) -> 1160.1308 | ... N87: =IF(OR(N68=0,M68=0),M96,M96*(N68/M68)^(-'Tech Parameters'!$C$5)*(N84/M84)^('Tech Parameters'!$C$5+'Tech Parameters'!$C$6)) -> 1160.1308
A88: Natural gas | B88: PJ | C88: ='Tech Parameters'!D25 -> 800 | D88: =IF(OR(D69=0,C69=0),C97,C97*(D69/C69)^(-'Tech Parameters'!$C$5)*(D84/C84)^('Tech Parameters'!$C$5+'Tech Parameters'!$C$6)) -> 800 | E88: =IF(OR(E69=0,D69=0),D97,D97*(E69/D69)^(-'Tech Parameters'!$C$5)*(E84/D84)^('Tech Parameters'!$C$5+'Tech Parameters'!$C$6)) -> 830.18825 | F88: =IF(OR(F69=0,E69=0),E97,E97*(F69/E69)^(-'Tech Parameters'!$C$5)*(F84/E84)^('Tech Parameters'!$C$5+'Tech Parameters'!$C$6)) -> 817.3362 | G88: =IF(OR(G69=0,F69=0),F97,F97*(G69/F69)^(-'Tech Parameters'!$C$5)*(G84/F84)^('Tech Parameters'!$C$5+'Tech Parameters'!$C$6)) -> 808.77405 | H88: =IF(OR(H69=0,G69=0),G97,G97*(H69/G69)^(-'Tech Parameters'!$C$5)*(H84/G84)^('Tech Parameters'!$C$5+'Tech Parameters'!$C$6)) -> 803.73947 | I88: =IF(OR(I69=0,H69=0),H97,H97*(I69/H69)^(-'Tech Parameters'!$C$5)*(I84/H84)^('Tech Parameters'!$C$5+'Tech Parameters'!$C$6)) -> 802.86512 | J88: =IF(OR(J69=0,I69=0),I97,I97*(J69/I69)^(-'Tech Parameters'!$C$5)*(J84/I84)^('Tech Parameters'!$C$5+'Tech Parameters'!$C$6)) -> 803.90863 | K88: =IF(OR(K69=0,J69=0),J97,J97*(K69/J69)^(-'Tech Parameters'!$C$5)*(K84/J84)^('Tech Parameters'!$C$5+'Tech Parameters'!$C$6)) -> 803.90863 | ... N88: =IF(OR(N69=0,M69=0),M97,M97*(N69/M69)^(-'Tech Parameters'!$C$5)*(N84/M84)^('Tech Parameters'!$C$5+'Tech Parameters'!$C$6)) -> 803.90863
A89: Gasoline | B89: PJ | C89: ='Tech Parameters'!D26 -> 0 | D89: =IF(OR(D70=0,C70=0),C98,C98*(D70/C70)^(-'Tech Parameters'!$C$5)*(D84/C84)^('Tech Parameters'!$C$5+'Tech Parameters'!$C$6)) -> 0 | E89: =IF(OR(E70=0,D70=0),D98,D98*(E70/D70)^(-'Tech Parameters'!$C$5)*(E84/D84)^('Tech Parameters'!$C$5+'Tech Parameters'!$C$6)) -> 0 | F89: =IF(OR(F70=0,E70=0),E98,E98*(F70/E70)^(-'Tech Parameters'!$C$5)*(F84/E84)^('Tech Parameters'!$C$5+'Tech Parameters'!$C$6)) -> 0 | G89: =IF(OR(G70=0,F70=0),F98,F98*(G70/F70)^(-'Tech Parameters'!$C$5)*(G84/F84)^('Tech Parameters'!$C$5+'Tech Parameters'!$C$6)) -> 0 | H89: =IF(OR(H70=0,G70=0),G98,G98*(H70/G70)^(-'Tech Parameters'!$C$5)*(H84/G84)^('Tech Parameters'!$C$5+'Tech Parameters'!$C$6)) -> 0 | I89: =IF(OR(I70=0,H70=0),H98,H98*(I70/H70)^(-'Tech Parameters'!$C$5)*(I84/H84)^('Tech Parameters'!$C$5+'Tech Parameters'!$C$6)) -> 0 | J89: =IF(OR(J70=0,I70=0),I98,I98*(J70/I70)^(-'Tech Parameters'!$C$5)*(J84/I84)^('Tech Parameters'!$C$5+'Tech Parameters'!$C$6)) -> 0 | K89: =IF(OR(K70=0,J70=0),J98,J98*(K70/J70)^(-'Tech Parameters'!$C$5)*(K84/J84)^('Tech Parameters'!$C$5+'Tech Parameters'!$C$6)) -> 0 | ... N89: =IF(OR(N70=0,M70=0),M98,M98*(N70/M70)^(-'Tech Parameters'!$C$5)*(N84/M84)^('Tech Parameters'!$C$5+'Tech Parameters'!$C$6)) -> 0
A90: Diesel | B90: PJ | C90: ='Tech Parameters'!D27 -> 30 | D90: =IF(OR(D71=0,C71=0),C99,C99*(D71/C71)^(-'Tech Parameters'!$C$5)*(D84/C84)^('Tech Parameters'!$C$5+'Tech Parameters'!$C$6)) -> 30 | E90: =IF(OR(E71=0,D71=0),D99,D99*(E71/D71)^(-'Tech Parameters'!$C$5)*(E84/D84)^('Tech Parameters'!$C$5+'Tech Parameters'!$C$6)) -> 32.666829 | F90: =IF(OR(F71=0,E71=0),E99,E99*(F71/E71)^(-'Tech Parameters'!$C$5)*(F84/E84)^('Tech Parameters'!$C$5+'Tech Parameters'!$C$6)) -> 31.821103 | G90: =IF(OR(G71=0,F71=0),F99,F99*(G71/F71)^(-'Tech Parameters'!$C$5)*(G84/F84)^('Tech Parameters'!$C$5+'Tech Parameters'!$C$6)) -> 31.391481 | H90: =IF(OR(H71=0,G71=0),G99,G99*(H71/G71)^(-'Tech Parameters'!$C$5)*(H84/G84)^('Tech Parameters'!$C$5+'Tech Parameters'!$C$6)) -> 30.268277 | I90: =IF(OR(I71=0,H71=0),H99,H99*(I71/H71)^(-'Tech Parameters'!$C$5)*(I84/H84)^('Tech Parameters'!$C$5+'Tech Parameters'!$C$6)) -> 30.223256 | J90: =IF(OR(J71=0,I71=0),I99,I99*(J71/I71)^(-'Tech Parameters'!$C$5)*(J84/I84)^('Tech Parameters'!$C$5+'Tech Parameters'!$C$6)) -> 30.398111 | K90: =IF(OR(K71=0,J71=0),J99,J99*(K71/J71)^(-'Tech Parameters'!$C$5)*(K84/J84)^('Tech Parameters'!$C$5+'Tech Parameters'!$C$6)) -> 30.398111 | ... N90: =IF(OR(N71=0,M71=0),M99,M99*(N71/M71)^(-'Tech Parameters'!$C$5)*(N84/M84)^('Tech Parameters'!$C$5+'Tech Parameters'!$C$6)) -> 30.398111
A91: Electricity | B91: PJ | C91: ='Tech Parameters'!D28 -> 0 | D91: =IF(OR(D72=0,C72=0),C100,C100*(D72/C72)^(-'Tech Parameters'!$C$5)*(D84/C84)^('Tech Parameters'!$C$5+'Tech Parameters'!$C$6)) -> 0 | E91: =IF(OR(E72=0,D72=0),D100,D100*(E72/D72)^(-'Tech Parameters'!$C$5)*(E84/D84)^('Tech Parameters'!$C$5+'Tech Parameters'!$C$6)) -> 0 | F91: =IF(OR(F72=0,E72=0),E100,E100*(F72/E72)^(-'Tech Parameters'!$C$5)*(F84/E84)^('Tech Parameters'!$C$5+'Tech Parameters'!$C$6)) -> 0 | G91: =IF(OR(G72=0,F72=0),F100,F100*(G72/F72)^(-'Tech Parameters'!$C$5)*(G84/F84)^('Tech Parameters'!$C$5+'Tech Parameters'!$C$6)) -> 0 | H91: =IF(OR(H72=0,G72=0),G100,G100*(H72/G72)^(-'Tech Parameters'!$C$5)*(H84/G84)^('Tech Parameters'!$C$5+'Tech Parameters'!$C$6)) -> 0 | I91: =IF(OR(I72=0,H72=0),H100,H100*(I72/H72)^(-'Tech Parameters'!$C$5)*(I84/H84)^('Tech Parameters'!$C$5+'Tech Parameters'!$C$6)) -> 0 | J91: =IF(OR(J72=0,I72=0),I100,I100*(J72/I72)^(-'Tech Parameters'!$C$5)*(J84/I84)^('Tech Parameters'!$C$5+'Tech Parameters'!$C$6)) -> 0 | K91: =IF(OR(K72=0,J72=0),J100,J100*(K72/J72)^(-'Tech Parameters'!$C$5)*(K84/J84)^('Tech Parameters'!$C$5+'Tech Parameters'!$C$6)) -> 0 | ... N91: =IF(OR(N72=0,M72=0),M100,M100*(N72/M72)^(-'Tech Parameters'!$C$5)*(N84/M84)^('Tech Parameters'!$C$5+'Tech Parameters'!$C$6)) -> 0
A92: RE generation | B92: PJ | C92: ='Tech Parameters'!D29 -> 400 | D92: =IF(OR(D73=0,C73=0),C101,C101*(D73/C73)^(-'Tech Parameters'!$C$5)*(D84/C84)^('Tech Parameters'!$C$5+'Tech Parameters'!$C$6)) -> 400 | E92: =IF(OR(E73=0,D73=0),D101,D101*(E73/D73)^(-'Tech Parameters'!$C$5)*(E84/D84)^('Tech Parameters'!$C$5+'Tech Parameters'!$C$6)) -> 465.99285 | F92: =IF(OR(F73=0,E73=0),E101,E101*(F73/E73)^(-'Tech Parameters'!$C$5)*(F84/E84)^('Tech Parameters'!$C$5+'Tech Parameters'!$C$6)) -> 505.85331 | G92: =IF(OR(G73=0,F73=0),F101,F101*(G73/F73)^(-'Tech Parameters'!$C$5)*(G84/F84)^('Tech Parameters'!$C$5+'Tech Parameters'!$C$6)) -> 512.66933 | H92: =IF(OR(H73=0,G73=0),G101,G101*(H73/G73)^(-'Tech Parameters'!$C$5)*(H84/G84)^('Tech Parameters'!$C$5+'Tech Parameters'!$C$6)) -> 484.90941 | I92: =IF(OR(I73=0,H73=0),H101,H101*(I73/H73)^(-'Tech Parameters'!$C$5)*(I84/H84)^('Tech Parameters'!$C$5+'Tech Parameters'!$C$6)) -> 506.1921 | J92: =IF(OR(J73=0,I73=0),I101,I101*(J73/I73)^(-'Tech Parameters'!$C$5)*(J84/I84)^('Tech Parameters'!$C$5+'Tech Parameters'!$C$6)) -> 432.75005 | K92: =IF(OR(K73=0,J73=0),J101,J101*(K73/J73)^(-'Tech Parameters'!$C$5)*(K84/J84)^('Tech Parameters'!$C$5+'Tech Parameters'!$C$6)) -> 432.75005 | ... N92: =IF(OR(N73=0,M73=0),M101,M101*(N73/M73)^(-'Tech Parameters'!$C$5)*(N84/M84)^('Tech Parameters'!$C$5+'Tech Parameters'!$C$6)) -> 432.75005
A94: ELECTRICITY GEN. — Actual Quantities (PJ)
A96: Coal | B96: PJ | C96: =C87 -> 1200 | D96: =C96+'Tech Parameters'!$C$7*(D87-C96) -> 1200 | E96: =D96+'Tech Parameters'!$C$7*(E87-D96) -> 1183.6787 | F96: =E96+'Tech Parameters'!$C$7*(F87-E96) -> 1171.6617 | G96: =F96+'Tech Parameters'!$C$7*(G87-F96) -> 1162.9187 | H96: =G96+'Tech Parameters'!$C$7*(H87-G96) -> 1161.5667 | I96: =H96+'Tech Parameters'!$C$7*(I87-H96) -> 1160.1308 | J96: =I96+'Tech Parameters'!$C$7*(J87-I96) -> 1160.1308 | K96: =J96+'Tech Parameters'!$C$7*(K87-J96) -> 1160.1308 | ... N96: =M96+'Tech Parameters'!$C$7*(N87-M96) -> 1160.1308
