Workbook
Name CountrySelector: CBAM!$B$5
Name CovS1fc: CBAM!$B$11
Name CovS1fp: CBAM!$B$12
Name CovS1no: CBAM!$B$14
Name CovS1np: CBAM!$B$13
Name CovS2: CBAM!$B$15
Name DetailYear: CBAM!$B$6
Name ExportsOnly: CBAM!$B$22
Name MRVmaster: CBAM!$B$19
Name Theta: CBAM!$B$7
Name Version: version!$A$3
Name YearIdx: CBAM!$P$6

Sheet Guide
A1: Pass 8 — Explainer & Legend
A2: What this workbook does, how the levers work, and how to read each sheet.
A4: 1. What this workbook models
B6: Scope | C6: 5 countries (Egypt, Albania, Uzbekistan, Azerbaijan, India) × 8 CBAM-eligible products × 12 years (2024–2035). Tracks production, exports, emissions across 5 scope buckets, EU CBAM obligations, and optimal country-level carbon-pricing responses.
B7: Products | C7: DRI-EAF steel, Scrap-EAF steel, BF-BOF steel, Cement, Ammonia, Urea, Ammonium nitrate, Primary aluminium. BF-BOF appears in all countries' production matrices; only India has non-zero base BF-BOF capacity at this stage.
B8: Five scope buckets | C8: S1.fc — fuel combustion CO₂ (boilers, kilns, heat). S1.fp — fuel-as-reductant CO₂ (BF coke + PCI, DRI shaft NG, SMR reformer NG). S1.np — non-fuel process CO₂ (cement calcination, anode oxidation, urea CO₂ uptake). S1.no — non-CO₂ GHG in CO₂e (N₂O from HNO₃, PFCs from Hall-Héroult cells). S2 — electricity (indirect via grid).
B9: Coverage flags | C9: Each scope has an independent on/off flag on the dashboard (2a, cells B11–B15). These say what the country's domestic CP is levied on. They do NOT change the regulatory definition of CBAM scope — that's controlled by the cs2 flag per product (EU Reg 2023/956 Annex II: cs2=0 for iron/steel and aluminium; cs2=1 for cement and fertilisers).
A11: 2. What's new in Pass 8
B13: Finalised CBAM benchmarks | C13: Implementing Regulation (EU) 2025/2621 adopted 16 Dec 2025. Benchmarks for the default-value pathway (column B): BF-BOF 1.370 (was 1.530), DRI-EAF 0.481 (was 1.033), Scrap-EAF 0.072 (was 0.288), Cement clinker 0.666 (was 0.693), Ammonia 1.522 (unchanged), Urea 0.902 (unchanged), Aluminium 1.423 (was 1.484). The scrap benchmark drop is the largest in proportional terms and ratchets recycled steel firmly into the CBAM net even at low actual intensities. EU default values reset to ~20% above the new benchmark.
B14: Declining grid emission factors | C14: Grid EFs are now 12-year time series rather than constants, declining linearly in line with each country's NDC trajectory. Egypt 0.510 → 0.400 (NDC 42% RE by 2030); Albania 0.045 → 0.035 (already low from hydro); Uzbekistan 0.540 → 0.420 (40% RE by 2035); Azerbaijan 0.460 → 0.370 (30% RE by 2030); India 0.713 → 0.500 (60% non-fossil by 2035 NDC). The s2e formula now resolves the year-indexed value; everything downstream — intensities, CBAM obligation, optimal CP — responds automatically.
A16: 3. Carried over from Pass 7
B18: India added | C18: Fifth country with realistic 2024 production: ~150 Mt crude steel (110 BF-BOF, 32 DRI-EAF, 8 scrap), 440 Mt cement, 17 Mt NH₃, 30 Mt urea, 4.1 Mt aluminium.
B19: BF-BOF integrated | C19: BF-BOF steel is a regular entity in every country's matrix (energy intensity rows, emissions rows, intensity matrix). India is currently the only country with non-zero BF-BOF base capacity; structure exists for all.
B20: 5-scope coverage flags | C20: Independent on/off flags per scope (2a on dashboard). Replaces the previous A/B/C aggregation.
B21: Global MRV per product | C21: Single row B19:I19 on dashboard, one cell per product. Applies to all 5 countries. MRV=0 falls back to the EU default value.
B22: Exports-only tax toggle | C22: B22: when 1, the country's CP is levied only on exports (EU + non-EU). Useful for politically-constrained pricing.
B23: NH₃ chain transparency | C23: Section 8 of dashboard makes the upstream ammonia chain visible. Only direct emissions of ammonia cascade into urea/AN; S2 of ammonia is shown but NOT cascaded — each downstream product accounts for its own electricity.
B24: EF matrix display | C24: Section 6: fuel emission factors (IPCC 2006) and per-product calculated intensities for the selected country, alongside EU benchmarks and default values.
A26: 4. Key levers — what to move first
B28: B5 — country | C28: Pick from egy/alb/uzb/aze/ind. Everything redraws.
B29: B6 — detail year | C29: Year for Section 5 (price impact) and Section 6b (per-product intensities). Other sections show full 12-year series.
B30: B7 — pass-through θ | C30: Share of wedge passed to buyer prices vs absorbed by producer margins. Default 0.7.
B31: B11–B15 — coverage flags | C31: Independent on/off for fc, fp, np, no, s2. Whether S2 is credited against CBAM is separately gated by the cs2 regulatory flag per product (row 20).
B32: B19:I19 — MRV per product | C32: 1 if exporter has actual MRV data; 0 to use EU default. Global per product.
B33: B22 — exports-only tax | C33: 0: CP levied on all production. 1: only on exports.
B34: Row 29 — domestic CP | C34: Defaults to optimal CP from row 28 (the level that exactly captures the CBAM gross). Edit to test sub-optimal or over-shooting pricing.
A36: 5. Sheets in this workbook
B38: dashboard | C38: Inputs and headline outputs. Sections 1-4 are the policy control panel; Sections 5-8 are diagnostic views of the selected country at the detail year.
B39: explainer | C39: This sheet — overview, lever guide, and methodology notes.
B40: input_data | C40: 1,053 rows keyed by code (cty.dom.par.sec.prc.sub). Universal time series, fuel EFs, per-entity constants (now with finalised benchmarks), country-level constants (grid EFs now time series), 5 country × 8 product blocks.
B41: calculations | C41: 284 rows. Country-aware (pulls from CBAM!B5). Uniform per-entity block. s2e formula now resolves year-indexed grid EF.
A43: 6. Methodology notes
B45: Two CBAM benchmark columns | C45: EU Reg 2025/2621 specifies separate benchmarks for column A (use with actual measured data) and column B (use with default values). The workbook uses column B for the default-value pathway when MRV=0 and treats the same benchmark consistently when MRV=1 — a simplification but adequate for first-pass policy analysis.
B46: CBAM factor schedule | C46: EU Reg 2025/2620: 2.5% 2026, 5% 2027, 10% 2028, 22.5% 2029, 48.5% 2030, 61% 2031, 73.5% 2032, 86% 2033, 100% 2034. The factor is the share of certificates that must be purchased (= 1 minus free allocation share).
B47: CBAM scope per product (cs2) | C47: EU Reg 2023/956 Annex II: direct + indirect (S2) for cement, fertilisers, hydrogen. Direct only for iron & steel and aluminium. The cs2 row in section 2b shows the regulatory scope; it gates whether S2 contributes to creditability against CBAM.
B48: NH₃ chain accounting | C48: Upstream ammonia feedstock embedded in urea (0.567 t NH₃/t) and AN (0.213 t NH₃/t). Only ammonia's direct emissions cascade — S2 is NOT cascaded because each downstream product accounts for its own electricity via its own S2 row. This avoids double-counting.
B49: Optimal carbon price | C49: Row 28: country-level CP that exactly captures the CBAM gross as country revenue. Derived analytically as CBAM_gross / (Σ EU_exports × creditable_intensity), where creditable intensity sums the scopes that are BOTH covered by the CP AND in CBAM scope.
B50: Revenue accounting | C50: Country revenue = (CP × covered_intensity) × (EU + non-EU exports + domestic × (1−exports_only)). CBAM credit = (CP × creditable_intensity × EU exports). EU net = MAX(CBAM_gross − credit, 0). Total pool = country revenue + EU net.
B51: Grid EF trajectories | C51: Linear interpolation between 2024 anchors (IEA Emission Factors 2025) and 2035 end-points consistent with NDC commitments. Egypt and Uzbekistan trajectories reflect modest decarbonisation; India's reflects its accelerating non-fossil capacity build-out.
A53: 7. Key regulatory references
B55: EU Reg 2023/956 | C55: CBAM regulation. Annex II lists covered products and scope.
B56: EU IR 2025/2620 | C56: CBAM phase-in schedule + free allocation adjustment rules.
B57: EU IR 2025/2621 | C57: Final CBAM benchmarks and default values (16 Dec 2025).
B58: IPCC 2006 Vol. 2 Ch. 2 | C58: Stationary combustion emission factors per fuel.
B59: GEM 2024 Steel Brief | C59: India steel data — BF-BOF dominance, capacity by route.
B60: IEA Emission Factors 2025 | C60: Grid EF base year anchors.
B61: Climate Action Tracker 2026 | C61: India 2035 NDC analysis (60% non-fossil capacity).

Sheet CBAM
A1: ="CPAT Policy Dashboard — "&Version -> CPAT Policy Dashboard — v1.6
A2: 5 countries × 8 products × 12 years. 5-scope coverage flags, global MRV per product, exports-only tax option, BF-BOF integrated, NH₃ chain explicitly accounted, EF matrix included.
A4: 1. COUNTRY & VIEW SETTINGS
A5: Country selector | B5: egy | C5: → | D5: Choose from: egy, alb, uzb, aze, ind.
A6: Detail year (for price-impact table) | B6: 2030 | C6: → | D6: Year for the price-impact section. | P6: =MATCH(TEXT($B$6,"0"),input_data!$M$3:$X$3,0) -> 7
A7: Pass-through θ (share of wedge to buyer prices) | B7: 0.7 | C7: → | D7: Share of carbon wedge passed to buyers (rest hits producer margins).
A9: 2. POLICY CHOICES
A10: 2a. Coverage flags — what the domestic CP is levied on (1 = covered, 0 = not)
A11: Coverage S1.fc (Scope 1 — Fuel combustion CO₂) | B11: 1 | C11: → | D11: Combustion fuels (heat, steam).
A12: Coverage S1.fp (Scope 1 — Fuel-as-reductant CO₂) | B12: 1 | C12: → | D12: Fuel-as-reductant (BF coke + PCI, DRI shaft NG, SMR reformer NG).
A13: Coverage S1.np (Scope 1 — Non-fuel process CO₂) | B13: 1 | C13: → | D13: Calcination CO₂ (cement, anode), urea CO₂ uptake (negative for urea).
A14: Coverage S1.no (Scope 1 — Non-CO₂ GHG (CO₂e)) | B14: 1 | C14: → | D14: N₂O from HNO₃, PFCs from Hall-Héroult.
A15: Coverage S2 (Scope 2 — Electricity (indirect)) | B15: 1 | C15: → | D15: Indirect electricity emissions.
A17: 2b. MRV per product (global — applies to all countries; 1 = MRV verified, EU uses actual)
A18: Product → | B18: DRI | C18: Scrap | D18: BF-BOF | E18: Cement | F18: NH₃ | G18: Urea | H18: AN | I18: Al
A19: MRV flag (edit here): | B19: 1 | C19: 1 | D19: 1 | E19: 1 | F19: 1 | G19: 1 | H19: 1 | I19: 1
A20: CBAM S2 scope (reg., Annex II = 0): | B20: =INDEX(input_data!$L:$L,MATCH("all.in.cs2.stl.drg.---",input_data!$A:$A,0)) -> 0 | C20: =INDEX(input_data!$L:$L,MATCH("all.in.cs2.stl.scr.---",input_data!$A:$A,0)) -> 0 | D20: =INDEX(input_data!$L:$L,MATCH("all.in.cs2.stl.bof.---",input_data!$A:$A,0)) -> 0 | E20: =INDEX(input_data!$L:$L,MATCH("all.in.cs2.cmt.dry.---",input_data!$A:$A,0)) -> 1 | F20: =INDEX(input_data!$L:$L,MATCH("all.in.cs2.frt.amc.---",input_data!$A:$A,0)) -> 1 | G20: =INDEX(input_data!$L:$L,MATCH("all.in.cs2.frt.ure.---",input_data!$A:$A,0)) -> 1 | H20: =INDEX(input_data!$L:$L,MATCH("all.in.cs2.frt.nit.---",input_data!$A:$A,0)) -> 1 | I20: =INDEX(input_data!$L:$L,MATCH("all.in.cs2.alu.prp.---",input_data!$A:$A,0)) -> 0
A22: 2c. Tax only exports? (1 = yes — no domestic CP on home consumption; 0 = no) | B22: 0 | C22: → | D22: When 1, the country's CP is levied only on EU + non-EU exports (not on domestic-consumed product). Useful for politically-constrained pricing.
A24: 3. CARBON PRICE TIME SERIES
A25: row | B25: unit | D25: 2024 | E25: 2025 | F25: 2026 | G25: 2027 | H25: 2028 | I25: 2029 | J25: 2030 | K25: 2031 | L25: 2032 | M25: 2033 | N25: 2034 | O25: 2035
A26: EU ETS price | B26: EUR/tCO2 | D26: =INDEX(input_data!$M:$X,MATCH("all.in.ets.---.---.---",input_data!$A:$A,0),1) -> 85 | E26: =INDEX(input_data!$M:$X,MATCH("all.in.ets.---.---.---",input_data!$A:$A,0),2) -> 90 | F26: =INDEX(input_data!$M:$X,MATCH("all.in.ets.---.---.---",input_data!$A:$A,0),3) -> 100 | G26: =INDEX(input_data!$M:$X,MATCH("all.in.ets.---.---.---",input_data!$A:$A,0),4) -> 105 | H26: =INDEX(input_data!$M:$X,MATCH("all.in.ets.---.---.---",input_data!$A:$A,0),5) -> 110 | I26: =INDEX(input_data!$M:$X,MATCH("all.in.ets.---.---.---",input_data!$A:$A,0),6) -> 110 | J26: =INDEX(input_data!$M:$X,MATCH("all.in.ets.---.---.---",input_data!$A:$A,0),7) -> 115 | K26: =INDEX(input_data!$M:$X,MATCH("all.in.ets.---.---.---",input_data!$A:$A,0),8) -> 120 | L26: =INDEX(input_data!$M:$X,MATCH("all.in.ets.---.---.---",input_data!$A:$A,0),9) -> 125 | M26: =INDEX(input_data!$M:$X,MATCH("all.in.ets.---.---.---",input_data!$A:$A,0),10) -> 130 | N26: =INDEX(input_data!$M:$X,MATCH("all.in.ets.---.---.---",input_data!$A:$A,0),11) -> 135 | O26: =INDEX(input_data!$M:$X,MATCH("all.in.ets.---.---.---",input_data!$A:$A,0),12) -> 140
A27: CBAM factor | B27: fraction | D27: =INDEX(input_data!$M:$X,MATCH("all.in.cbf.---.---.---",input_data!$A:$A,0),1) -> 0 | E27: =INDEX(input_data!$M:$X,MATCH("all.in.cbf.---.---.---",input_data!$A:$A,0),2) -> 0 | F27: =INDEX(input_data!$M:$X,MATCH("all.in.cbf.---.---.---",input_data!$A:$A,0),3) -> 0.025 | G27: =INDEX(input_data!$M:$X,MATCH("all.in.cbf.---.---.---",input_data!$A:$A,0),4) -> 0.05 | H27: =INDEX(input_data!$M:$X,MATCH("all.in.cbf.---.---.---",input_data!$A:$A,0),5) -> 0.1 | I27: =INDEX(input_data!$M:$X,MATCH("all.in.cbf.---.---.---",input_data!$A:$A,0),6) -> 0.225 | J27: =INDEX(input_data!$M:$X,MATCH("all.in.cbf.---.---.---",input_data!$A:$A,0),7) -> 0.485 | K27: =INDEX(input_data!$M:$X,MATCH("all.in.cbf.---.---.---",input_data!$A:$A,0),8) -> 0.61 | L27: =INDEX(input_data!$M:$X,MATCH("all.in.cbf.---.---.---",input_data!$A:$A,0),9) -> 0.735 | M27: =INDEX(input_data!$M:$X,MATCH("all.in.cbf.---.---.---",input_data!$A:$A,0),10) -> 0.86 | N27: =INDEX(input_data!$M:$X,MATCH("all.in.cbf.---.---.---",input_data!$A:$A,0),11) -> 1 | O27: =INDEX(input_data!$M:$X,MATCH("all.in.cbf.---.---.---",input_data!$A:$A,0),12) -> 1
A28: ↓ OPTIMAL CP (captures full CBAM as country revenue) | B28: USD/tCO2 | D28: =IFERROR((IFERROR(calculations!M21*calculations!M248,0)+IFERROR(calculations!M49*calculations!M253,0)+IFERROR(calculations!M77*calculations!M258,0)+IFERROR(calculations!M105*calculations!M263,0)+IFERROR(calculations!M133*calculations!M268,0)+IFERROR(calculations!M161*calculations!M273,0)+IFERROR(calculations!M189*calculations!M278,0)+IFERROR(calculations!M217*calculations!M283,0)+IFERROR(calculations!M287*calculations!M316,0)+IFERROR(calculations!M319*calculations!M348,0))/(IFERROR(calculations!M21/calculations!M20*((calculations!M41+calculations!M244)*$B$11+calculations!M42*$B$12+calculations!M43*$B$13+calculations!M44*$B$14+calculations!M45*$B$15*INDEX(input_data!$L:$L,MATCH("all.in.cs2.stl.drg.---",input_data!$A:$A,0))),0)+IFERROR(calculations!M49/calculations!M48*((calculations!M69+calculations!M249)*$B$11+calculations!M70*$B$12+calculations!M71*$B$13+calculations!M72*$B$14+calculations!M73*$B$15*INDEX(input_data!$L:$L,MATCH("all.in.cs2.stl.scr.---",input_data!$A:$A,0))),0)+IFERROR(calculations!M77/calculations!M76*((calculations!M97+calculations!M254)*$B$11+calculations!M98*$B$12+calculations!M99*$B$13+calculations!M100*$B$14+calculations!M101*$B$15*INDEX(input_data!$L:$L,MATCH("all.in.cs2.stl.bof.---",input_data!$A:$A,0))),0)+IFERROR(calculations!M105/calculations!M104*((calculations!M125+calculations!M259)*$B$11+calculations!M126*$B$12+calculations!M127*$B$13+calculations!M128*$B$14+calculations!M129*$B$15*INDEX(input_data!$L:$L,MATCH("all.in.cs2.cmt.dry.---",input_data!$A:$A,0))),0)+IFERROR(calculations!M133/calculations!M132*((calculations!M153+calculations!M264)*$B$11+calculations!M154*$B$12+calculations!M155*$B$13+calculations!M156*$B$14+calculations!M157*$B$15*INDEX(input_data!$L:$L,MATCH("all.in.cs2.frt.amc.---",input_data!$A:$A,0))),0)+IFERROR(calculations!M161/calculations!M160*((calculations!M181+calculations!M269)*$B$11+calculations!M182*$B$12+calculations!M183*$B$13+calculations!M184*$B$14+calculations!M185*$B$15*INDEX(input_data!$L:$L,MATCH("all.in.cs2.frt.ure.---",input_data!$A:$A,0))),0)+IFERROR(calculations!M189/calculations!M188*((calculations!M209+calculations!M274)*$B$11+calculations!M210*$B$12+calculations!M211*$B$13+calculations!M212*$B$14+calculations!M213*$B$15*INDEX(input_data!$L:$L,MATCH("all.in.cs2.frt.nit.---",input_data!$A:$A,0))),0)+IFERROR(calculations!M217/calculations!M216*((calculations!M237+calculations!M279)*$B$11+calculations!M238*$B$12+calculations!M239*$B$13+calculations!M240*$B$14+calculations!M241*$B$15*INDEX(input_data!$L:$L,MATCH("all.in.cs2.alu.prp.---",input_data!$A:$A,0))),0)+IFERROR(calculations!M287/calculations!M286*((calculations!M307+calculations!M312)*$B$11+calculations!M308*$B$12+calculations!M309*$B$13+calculations!M310*$B$14+calculations!M311*$B$15*INDEX(input_data!$L:$L,MATCH("all.in.cs2.stl.oth.---",input_data!$A:$A,0))),0)+IFERROR(calculations!M319/calculations!M318*((calculations!M339+calculations!M344)*$B$11+calculations!M340*$B$12+calculations!M341*$B$13+calculations!M342*$B$14+calculations!M343*$B$15*INDEX(input_data!$L:$L,MATCH("all.in.cs2.frt.otn.---",input_data!$A:$A,0))),0)),0) -> 0 | E28: =IFERROR((IFERROR(calculations!N21*calculations!N248,0)+IFERROR(calculations!N49*calculations!N253,0)+IFERROR(calculations!N77*calculations!N258,0)+IFERROR(calculations!N105*calculations!N263,0)+IFERROR(calculations!N133*calculations!N268,0)+IFERROR(calculations!N161*calculations!N273,0)+IFERROR(calculations!N189*calculations!N278,0)+IFERROR(calculations!N217*calculations!N283,0)+IFERROR(calculations!N287*calculations!N316,0)+IFERROR(calculations!N319*calculations!N348,0))/(IFERROR(calculations!N21/calculations!N20*((calculations!N41+calculations!N244)*$B$11+calculations!N42*$B$12+calculations!N43*$B$13+calculations!N44*$B$14+calculations!N45*$B$15*INDEX(input_data!$L:$L,MATCH("all.in.cs2.stl.drg.---",input_data!$A:$A,0))),0)+IFERROR(calculations!N49/calculations!N48*((calculations!N69+calculations!N249)*$B$11+calculations!N70*$B$12+calculations!N71*$B$13+calculations!N72*$B$14+calculations!N73*$B$15*INDEX(input_data!$L:$L,MATCH("all.in.cs2.stl.scr.---",input_data!$A:$A,0))),0)+IFERROR(calculations!N77/calculations!N76*((calculations!N97+calculations!N254)*$B$11+calculations!N98*$B$12+calculations!N99*$B$13+calculations!N100*$B$14+calculations!N101*$B$15*INDEX(input_data!$L:$L,MATCH("all.in.cs2.stl.bof.---",input_data!$A:$A,0))),0)+IFERROR(calculations!N105/calculations!N104*((calculations!N125+calculations!N259)*$B$11+calculations!N126*$B$12+calculations!N127*$B$13+calculations!N128*$B$14+calculations!N129*$B$15*INDEX(input_data!$L:$L,MATCH("all.in.cs2.cmt.dry.---",input_data!$A:$A,0))),0)+IFERROR(calculations!N133/calculations!N132*((calculations!N153+calculations!N264)*$B$11+calculations!N154*$B$12+calculations!N155*$B$13+calculations!N156*$B$14+calculations!N157*$B$15*INDEX(input_data!$L:$L,MATCH("all.in.cs2.frt.amc.---",input_data!$A:$A,0))),0)+IFERROR(calculations!N161/calculations!N160*((calculations!N181+calculations!N269)*$B$11+calculations!N182*$B$12+calculations!N183*$B$13+calculations!N184*$B$14+calculations!N185*$B$15*INDEX(input_data!$L:$L,MATCH("all.in.cs2.frt.ure.---",input_data!$A:$A,0))),0)+IFERROR(calculations!N189/calculations!N188*((calculations!N209+calculations!N274)*$B$11+calculations!N210*$B$12+calculations!N211*$B$13+calculations!N212*$B$14+calculations!N213*$B$15*INDEX(input_data!$L:$L,MATCH("all.in.cs2.frt.nit.---",input_data!$A:$A,0))),0)+IFERROR(calculations!N217/calculations!N216*((calculations!N237+calculations!N279)*$B$11+calculations!N238*$B$12+calculations!N239*$B$13+calculations!N240*$B$14+calculations!N241*$B$15*INDEX(input_data!$L:$L,MATCH("all.in.cs2.alu.prp.---",input_data!$A:$A,0))),0)+IFERROR(calculations!N287/calculations!N286*((calculations!N307+calculations!N312)*$B$11+calculations!N308*$B$12+calculations!N309*$B$13+calculations!N310*$B$14+calculations!N311*$B$15*INDEX(input_data!$L:$L,MATCH("all.in.cs2.stl.oth.---",input_data!$A:$A,0))),0)+IFERROR(calculations!N319/calculations!N318*((calculations!N339+calculations!N344)*$B$11+calculations!N340*$B$12+calculations!N341*$B$13+calculations!N342*$B$14+calculations!N343*$B$15*INDEX(input_data!$L:$L,MATCH("all.in.cs2.frt.otn.---",input_data!$A:$A,0))),0)),0) -> 0 | F28: =IFERROR((IFERROR(calculations!O21*calculations!O248,0)+IFERROR(calculations!O49*calculations!O253,0)+IFERROR(calculations!O77*calculations!O258,0)+IFERROR(calculations!O105*calculations!O263,0)+IFERROR(calculations!O133*calculations!O268,0)+IFERROR(calculations!O161*calculations!O273,0)+IFERROR(calculations!O189*calculations!O278,0)+IFERROR(calculations!O217*calculations!O283,0)+IFERROR(calculations!O287*calculations!O316,0)+IFERROR(calculations!O319*calculations!O348,0))/(IFERROR(calculations!O21/calculations!O20*((calculations!O41+calculations!O244)*$B$11+calculations!O42*$B$12+calculations!O43*$B$13+calculations!O44*$B$14+calculations!O45*$B$15*INDEX(input_data!$L:$L,MATCH("all.in.cs2.stl.drg.---",input_data!$A:$A,0))),0)+IFERROR(calculations!O49/calculations!O48*((calculations!O69+calculations!O249)*$B$11+calculations!O70*$B$12+calculations!O71*$B$13+calculations!O72*$B$14+calculations!O73*$B$15*INDEX(input_data!$L:$L,MATCH("all.in.cs2.stl.scr.---",input_data!$A:$A,0))),0)+IFERROR(calculations!O77/calculations!O76*((calculations!O97+calculations!O254)*$B$11+calculations!O98*$B$12+calculations!O99*$B$13+calculations!O100*$B$14+calculations!O101*$B$15*INDEX(input_data!$L:$L,MATCH("all.in.cs2.stl.bof.---",input_data!$A:$A,0))),0)+IFERROR(calculations!O105/calculations!O104*((calculations!O125+calculations!O259)*$B$11+calculations!O126*$B$12+calculations!O127*$B$13+calculations!O128*$B$14+calculations!O129*$B$15*INDEX(input_data!$L:$L,MATCH("all.in.cs2.cmt.dry.---",input_data!$A:$A,0))),0)+IFERROR(calculations!O133/calculations!O132*((calculations!O153+calculations!O264)*$B$11+calculations!O154*$B$12+calculations!O155*$B$13+calculations!O156*$B$14+calculations!O157*$B$15*INDEX(input_data!$L:$L,MATCH("all.in.cs2.frt.amc.---",input_data!$A:$A,0))),0)+IFERROR(calculations!O161/calculations!O160*((calculations!O181+calculations!O269)*$B$11+calculations!O182*$B$12+calculations!O183*$B$13+calculations!O184*$B$14+calculations!O185*$B$15*INDEX(input_data!$L:$L,MATCH("all.in.cs2.frt.ure.---",input_data!$A:$A,0))),0)+IFERROR(calculations!O189/calculations!O188*((calculations!O209+calculations!O274)*$B$11+calculations!O210*$B$12+calculations!O211*$B$13+calculations!O212*$B$14+calculations!O213*$B$15*INDEX(input_data!$L:$L,MATCH("all.in.cs2.frt.nit.---",input_data!$A:$A,0))),0)+IFERROR(calculations!O217/calculations!O216*((calculations!O237+calculations!O279)*$B$11+calculations!O238*$B$12+calculations!O239*$B$13+calculations!O240*$B$14+calculations!O241*$B$15*INDEX(input_data!$L:$L,MATCH("all.in.cs2.alu.prp.---",input_data!$A:$A,0))),0)+IFERROR(calculations!O287/calculations!O286*((calculations!O307+calculations!O312)*$B$11+calculations!O308*$B$12+calculations!O309*$B$13+calculations!O310*$B$14+calculations!O311*$B$15*INDEX(input_data!$L:$L,MATCH("all.in.cs2.stl.oth.---",input_data!$A:$A,0))),0)+IFERROR(calculations!O319/calculations!O318*((calculations!O339+calculations!O344)*$B$11+calculations!O340*$B$12+calculations!O341*$B$13+calculations!O342*$B$14+calculations!O343*$B$15*INDEX(input_data!$L:$L,MATCH("all.in.cs2.frt.otn.---",input_data!$A:$A,0))),0)),0) -> 34.6168 | G28: =IFERROR((IFERROR(calculations!P21*calculations!P248,0)+IFERROR(calculations!P49*calculations!P253,0)+IFERROR(calculations!P77*calculations!P258,0)+IFERROR(calculations!P105*calculations!P263,0)+IFERROR(calculations!P133*calculations!P268,0)+IFERROR(calculations!P161*calculations!P273,0)+IFERROR(calculations!P189*calculations!P278,0)+IFERROR(calculations!P217*calculations!P283,0)+IFERROR(calculations!P287*calculations!P316,0)+IFERROR(calculations!P319*calculations!P348,0))/(IFERROR(calculations!P21/calculations!P20*((calculations!P41+calculations!P244)*$B$11+calculations!P42*$B$12+calculations!P43*$B$13+calculations!P44*$B$14+calculations!P45*$B$15*INDEX(input_data!$L:$L,MATCH("all.in.cs2.stl.drg.---",input_data!$A:$A,0))),0)+IFERROR(calculations!P49/calculations!P48*((calculations!P69+calculations!P249)*$B$11+calculations!P70*$B$12+calculations!P71*$B$13+calculations!P72*$B$14+calculations!P73*$B$15*INDEX(input_data!$L:$L,MATCH("all.in.cs2.stl.scr.---",input_data!$A:$A,0))),0)+IFERROR(calculations!P77/calculations!P76*((calculations!P97+calculations!P254)*$B$11+calculations!P98*$B$12+calculations!P99*$B$13+calculations!P100*$B$14+calculations!P101*$B$15*INDEX(input_data!$L:$L,MATCH("all.in.cs2.stl.bof.---",input_data!$A:$A,0))),0)+IFERROR(calculations!P105/calculations!P104*((calculations!P125+calculations!P259)*$B$11+calculations!P126*$B$12+calculations!P127*$B$13+calculations!P128*$B$14+calculations!P129*$B$15*INDEX(input_data!$L:$L,MATCH("all.in.cs2.cmt.dry.---",input_data!$A:$A,0))),0)+IFERROR(calculations!P133/calculations!P132*((calculations!P153+calculations!P264)*$B$11+calculations!P154*$B$12+calculations!P155*$B$13+calculations!P156*$B$14+calculations!P157*$B$15*INDEX(input_data!$L:$L,MATCH("all.in.cs2.frt.amc.---",input_data!$A:$A,0))),0)+IFERROR(calculations!P161/calculations!P160*((calculations!P181+calculations!P269)*$B$11+calculations!P182*$B$12+calculations!P183*$B$13+calculations!P184*$B$14+calculations!P185*$B$15*INDEX(input_data!$L:$L,MATCH("all.in.cs2.frt.ure.---",input_data!$A:$A,0))),0)+IFERROR(calculations!P189/calculations!P188*((calculations!P209+calculations!P274)*$B$11+calculations!P210*$B$12+calculations!P211*$B$13+calculations!P212*$B$14+calculations!P213*$B$15*INDEX(input_data!$L:$L,MATCH("all.in.cs2.frt.nit.---",input_data!$A:$A,0))),0)+IFERROR(calculations!P217/calculations!P216*((calculations!P237+calculations!P279)*$B$11+calculations!P238*$B$12+calculations!P239*$B$13+calculations!P240*$B$14+calculations!P241*$B$15*INDEX(input_data!$L:$L,MATCH("all.in.cs2.alu.prp.---",input_data!$A:$A,0))),0)+IFERROR(calculations!P287/calculations!P286*((calculations!P307+calculations!P312)*$B$11+calculations!P308*$B$12+calculations!P309*$B$13+calculations!P310*$B$14+calculations!P311*$B$15*INDEX(input_data!$L:$L,MATCH("all.in.cs2.stl.oth.---",input_data!$A:$A,0))),0)+IFERROR(calculations!P319/calculations!P318*((calculations!P339+calculations!P344)*$B$11+calculations!P340*$B$12+calculations!P341*$B$13+calculations!P342*$B$14+calculations!P343*$B$15*INDEX(input_data!$L:$L,MATCH("all.in.cs2.frt.otn.---",input_data!$A:$A,0))),0)),0) -> 38.153867 | H28: =IFERROR((IFERROR(calculations!Q21*calculations!Q248,0)+IFERROR(calculations!Q49*calculations!Q253,0)+IFERROR(calculations!Q77*calculations!Q258,0)+IFERROR(calculations!Q105*calculations!Q263,0)+IFERROR(calculations!Q133*calculations!Q268,0)+IFERROR(calculations!Q161*calculations!Q273,0)+IFERROR(calculations!Q189*calculations!Q278,0)+IFERROR(calculations!Q217*calculations!Q283,0)+IFERROR(calculations!Q287*calculations!Q316,0)+IFERROR(calculations!Q319*calculations!Q348,0))/(IFERROR(calculations!Q21/calculations!Q20*((calculations!Q41+calculations!Q244)*$B$11+calculations!Q42*$B$12+calculations!Q43*$B$13+calculations!Q44*$B$14+calculations!Q45*$B$15*INDEX(input_data!$L:$L,MATCH("all.in.cs2.stl.drg.---",input_data!$A:$A,0))),0)+IFERROR(calculations!Q49/calculations!Q48*((calculations!Q69+calculations!Q249)*$B$11+calculations!Q70*$B$12+calculations!Q71*$B$13+calculations!Q72*$B$14+calculations!Q73*$B$15*INDEX(input_data!$L:$L,MATCH("all.in.cs2.stl.scr.---",input_data!$A:$A,0))),0)+IFERROR(calculations!Q77/calculations!Q76*((calculations!Q97+calculations!Q254)*$B$11+calculations!Q98*$B$12+calculations!Q99*$B$13+calculations!Q100*$B$14+calculations!Q101*$B$15*INDEX(input_data!$L:$L,MATCH("all.in.cs2.stl.bof.---",input_data!$A:$A,0))),0)+IFERROR(calculations!Q105/calculations!Q104*((calculations!Q125+calculations!Q259)*$B$11+calculations!Q126*$B$12+calculations!Q127*$B$13+calculations!Q128*$B$14+calculations!Q129*$B$15*INDEX(input_data!$L:$L,MATCH("all.in.cs2.cmt.dry.---",input_data!$A:$A,0))),0)+IFERROR(calculations!Q133/calculations!Q132*((calculations!Q153+calculations!Q264)*$B$11+calculations!Q154*$B$12+calculations!Q155*$B$13+calculations!Q156*$B$14+calculations!Q157*$B$15*INDEX(input_data!$L:$L,MATCH("all.in.cs2.frt.amc.---",input_data!$A:$A,0))),0)+IFERROR(calculations!Q161/calculations!Q160*((calculations!Q181+calculations!Q269)*$B$11+calculations!Q182*$B$12+calculations!Q183*$B$13+calculations!Q184*$B$14+calculations!Q185*$B$15*INDEX(input_data!$L:$L,MATCH("all.in.cs2.frt.ure.---",input_data!$A:$A,0))),0)+IFERROR(calculations!Q189/calculations!Q188*((calculations!Q209+calculations!Q274)*$B$11+calculations!Q210*$B$12+calculations!Q211*$B$13+calculations!Q212*$B$14+calculations!Q213*$B$15*INDEX(input_data!$L:$L,MATCH("all.in.cs2.frt.nit.---",input_data!$A:$A,0))),0)+IFERROR(calculations!Q217/calculations!Q216*((calculations!Q237+calculations!Q279)*$B$11+calculations!Q238*$B$12+calculations!Q239*$B$13+calculations!Q240*$B$14+calculations!Q241*$B$15*INDEX(input_data!$L:$L,MATCH("all.in.cs2.alu.prp.---",input_data!$A:$A,0))),0)+IFERROR(calculations!Q287/calculations!Q286*((calculations!Q307+calculations!Q312)*$B$11+calculations!Q308*$B$12+calculations!Q309*$B$13+calculations!Q310*$B$14+calculations!Q311*$B$15*INDEX(input_data!$L:$L,MATCH("all.in.cs2.stl.oth.---",input_data!$A:$A,0))),0)+IFERROR(calculations!Q319/calculations!Q318*((calculations!Q339+calculations!Q344)*$B$11+calculations!Q340*$B$12+calculations!Q341*$B$13+calculations!Q342*$B$14+calculations!Q343*$B$15*INDEX(input_data!$L:$L,MATCH("all.in.cs2.frt.otn.---",input_data!$A:$A,0))),0)),0) -> 43.768314 | I28: =IFERROR((IFERROR(calculations!R21*calculations!R248,0)+IFERROR(calculations!R49*calculations!R253,0)+IFERROR(calculations!R77*calculations!R258,0)+IFERROR(calculations!R105*calculations!R263,0)+IFERROR(calculations!R133*calculations!R268,0)+IFERROR(calculations!R161*calculations!R273,0)+IFERROR(calculations!R189*calculations!R278,0)+IFERROR(calculations!R217*calculations!R283,0)+IFERROR(calculations!R287*calculations!R316,0)+IFERROR(calculations!R319*calculations!R348,0))/(IFERROR(calculations!R21/calculations!R20*((calculations!R41+calculations!R244)*$B$11+calculations!R42*$B$12+calculations!R43*$B$13+calculations!R44*$B$14+calculations!R45*$B$15*INDEX(input_data!$L:$L,MATCH("all.in.cs2.stl.drg.---",input_data!$A:$A,0))),0)+IFERROR(calculations!R49/calculations!R48*((calculations!R69+calculations!R249)*$B$11+calculations!R70*$B$12+calculations!R71*$B$13+calculations!R72*$B$14+calculations!R73*$B$15*INDEX(input_data!$L:$L,MATCH("all.in.cs2.stl.scr.---",input_data!$A:$A,0))),0)+IFERROR(calculations!R77/calculations!R76*((calculations!R97+calculations!R254)*$B$11+calculations!R98*$B$12+calculations!R99*$B$13+calculations!R100*$B$14+calculations!R101*$B$15*INDEX(input_data!$L:$L,MATCH("all.in.cs2.stl.bof.---",input_data!$A:$A,0))),0)+IFERROR(calculations!R105/calculations!R104*((calculations!R125+calculations!R259)*$B$11+calculations!R126*$B$12+calculations!R127*$B$13+calculations!R128*$B$14+calculations!R129*$B$15*INDEX(input_data!$L:$L,MATCH("all.in.cs2.cmt.dry.---",input_data!$A:$A,0))),0)+IFERROR(calculations!R133/calculations!R132*((calculations!R153+calculations!R264)*$B$11+calculations!R154*$B$12+calculations!R155*$B$13+calculations!R156*$B$14+calculations!R157*$B$15*INDEX(input_data!$L:$L,MATCH("all.in.cs2.frt.amc.---",input_data!$A:$A,0))),0)+IFERROR(calculations!R161/calculations!R160*((calculations!R181+calculations!R269)*$B$11+calculations!R182*$B$12+calculations!R183*$B$13+calculations!R184*$B$14+calculations!R185*$B$15*INDEX(input_data!$L:$L,MATCH("all.in.cs2.frt.ure.---",input_data!$A:$A,0))),0)+IFERROR(calculations!R189/calculations!R188*((calculations!R209+calculations!R274)*$B$11+calculations!R210*$B$12+calculations!R211*$B$13+calculations!R212*$B$14+calculations!R213*$B$15*INDEX(input_data!$L:$L,MATCH("all.in.cs2.frt.nit.---",input_data!$A:$A,0))),0)+IFERROR(calculations!R217/calculations!R216*((calculations!R237+calculations!R279)*$B$11+calculations!R238*$B$12+calculations!R239*$B$13+calculations!R240*$B$14+calculations!R241*$B$15*INDEX(input_data!$L:$L,MATCH("all.in.cs2.alu.prp.---",input_data!$A:$A,0))),0)+IFERROR(calculations!R287/calculations!R286*((calculations!R307+calculations!R312)*$B$11+calculations!R308*$B$12+calculations!R309*$B$13+calculations!R310*$B$14+calculations!R311*$B$15*INDEX(input_data!$L:$L,MATCH("all.in.cs2.stl.oth.---",input_data!$A:$A,0))),0)+IFERROR(calculations!R319/calculations!R318*((calculations!R339+calculations!R344)*$B$11+calculations!R340*$B$12+calculations!R341*$B$13+calculations!R342*$B$14+calculations!R343*$B$15*INDEX(input_data!$L:$L,MATCH("all.in.cs2.frt.otn.---",input_data!$A:$A,0))),0)),0) -> 53.28536 | J28: =IFERROR((IFERROR(calculations!S21*calculations!S248,0)+IFERROR(calculations!S49*calculations!S253,0)+IFERROR(calculations!S77*calculations!S258,0)+IFERROR(calculations!S105*calculations!S263,0)+IFERROR(calculations!S133*calculations!S268,0)+IFERROR(calculations!S161*calculations!S273,0)+IFERROR(calculations!S189*calculations!S278,0)+IFERROR(calculations!S217*calculations!S283,0)+IFERROR(calculations!S287*calculations!S316,0)+IFERROR(calculations!S319*calculations!S348,0))/(IFERROR(calculations!S21/calculations!S20*((calculations!S41+calculations!S244)*$B$11+calculations!S42*$B$12+calculations!S43*$B$13+calculations!S44*$B$14+calculations!S45*$B$15*INDEX(input_data!$L:$L,MATCH("all.in.cs2.stl.drg.---",input_data!$A:$A,0))),0)+IFERROR(calculations!S49/calculations!S48*((calculations!S69+calculations!S249)*$B$11+calculations!S70*$B$12+calculations!S71*$B$13+calculations!S72*$B$14+calculations!S73*$B$15*INDEX(input_data!$L:$L,MATCH("all.in.cs2.stl.scr.---",input_data!$A:$A,0))),0)+IFERROR(calculations!S77/calculations!S76*((calculations!S97+calculations!S254)*$B$11+calculations!S98*$B$12+calculations!S99*$B$13+calculations!S100*$B$14+calculations!S101*$B$15*INDEX(input_data!$L:$L,MATCH("all.in.cs2.stl.bof.---",input_data!$A:$A,0))),0)+IFERROR(calculations!S105/calculations!S104*((calculations!S125+calculations!S259)*$B$11+calculations!S126*$B$12+calculations!S127*$B$13+calculations!S128*$B$14+calculations!S129*$B$15*INDEX(input_data!$L:$L,MATCH("all.in.cs2.cmt.dry.---",input_data!$A:$A,0))),0)+IFERROR(calculations!S133/calculations!S132*((calculations!S153+calculations!S264)*$B$11+calculations!S154*$B$12+calculations!S155*$B$13+calculations!S156*$B$14+calculations!S157*$B$15*INDEX(input_data!$L:$L,MATCH("all.in.cs2.frt.amc.---",input_data!$A:$A,0))),0)+IFERROR(calculations!S161/calculations!S160*((calculations!S181+calculations!S269)*$B$11+calculations!S182*$B$12+calculations!S183*$B$13+calculations!S184*$B$14+calculations!S185*$B$15*INDEX(input_data!$L:$L,MATCH("all.in.cs2.frt.ure.---",input_data!$A:$A,0))),0)+IFERROR(calculations!S189/calculations!S188*((calculations!S209+calculations!S274)*$B$11+calculations!S210*$B$12+calculations!S211*$B$13+calculations!S212*$B$14+calculations!S213*$B$15*INDEX(input_data!$L:$L,MATCH("all.in.cs2.frt.nit.---",input_data!$A:$A,0))),0)+IFERROR(calculations!S217/calculations!S216*((calculations!S237+calculations!S279)*$B$11+calculations!S238*$B$12+calculations!S239*$B$13+calculations!S240*$B$14+calculations!S241*$B$15*INDEX(input_data!$L:$L,MATCH("all.in.cs2.alu.prp.---",input_data!$A:$A,0))),0)+IFERROR(calculations!S287/calculations!S286*((calculations!S307+calculations!S312)*$B$11+calculations!S308*$B$12+calculations!S309*$B$13+calculations!S310*$B$14+calculations!S311*$B$15*INDEX(input_data!$L:$L,MATCH("all.in.cs2.stl.oth.---",input_data!$A:$A,0))),0)+IFERROR(calculations!S319/calculations!S318*((calculations!S339+calculations!S344)*$B$11+calculations!S340*$B$12+calculations!S341*$B$13+calculations!S342*$B$14+calculations!S343*$B$15*INDEX(input_data!$L:$L,MATCH("all.in.cs2.frt.otn.---",input_data!$A:$A,0))),0)),0) -> 76.914135 | K28: =IFERROR((IFERROR(calculations!T21*calculations!T248,0)+IFERROR(calculations!T49*calculations!T253,0)+IFERROR(calculations!T77*calculations!T258,0)+IFERROR(calculations!T105*calculations!T263,0)+IFERROR(calculations!T133*calculations!T268,0)+IFERROR(calculations!T161*calculations!T273,0)+IFERROR(calculations!T189*calculations!T278,0)+IFERROR(calculations!T217*calculations!T283,0)+IFERROR(calculations!T287*calculations!T316,0)+IFERROR(calculations!T319*calculations!T348,0))/(IFERROR(calculations!T21/calculations!T20*((calculations!T41+calculations!T244)*$B$11+calculations!T42*$B$12+calculations!T43*$B$13+calculations!T44*$B$14+calculations!T45*$B$15*INDEX(input_data!$L:$L,MATCH("all.in.cs2.stl.drg.---",input_data!$A:$A,0))),0)+IFERROR(calculations!T49/calculations!T48*((calculations!T69+calculations!T249)*$B$11+calculations!T70*$B$12+calculations!T71*$B$13+calculations!T72*$B$14+calculations!T73*$B$15*INDEX(input_data!$L:$L,MATCH("all.in.cs2.stl.scr.---",input_data!$A:$A,0))),0)+IFERROR(calculations!T77/calculations!T76*((calculations!T97+calculations!T254)*$B$11+calculations!T98*$B$12+calculations!T99*$B$13+calculations!T100*$B$14+calculations!T101*$B$15*INDEX(input_data!$L:$L,MATCH("all.in.cs2.stl.bof.---",input_data!$A:$A,0))),0)+IFERROR(calculations!T105/calculations!T104*((calculations!T125+calculations!T259)*$B$11+calculations!T126*$B$12+calculations!T127*$B$13+calculations!T128*$B$14+calculations!T129*$B$15*INDEX(input_data!$L:$L,MATCH("all.in.cs2.cmt.dry.---",input_data!$A:$A,0))),0)+IFERROR(calculations!T133/calculations!T132*((calculations!T153+calculations!T264)*$B$11+calculations!T154*$B$12+calculations!T155*$B$13+calculations!T156*$B$14+calculations!T157*$B$15*INDEX(input_data!$L:$L,MATCH("all.in.cs2.frt.amc.---",input_data!$A:$A,0))),0)+IFERROR(calculations!T161/calculations!T160*((calculations!T181+calculations!T269)*$B$11+calculations!T182*$B$12+calculations!T183*$B$13+calculations!T184*$B$14+calculations!T185*$B$15*INDEX(input_data!$L:$L,MATCH("all.in.cs2.frt.ure.---",input_data!$A:$A,0))),0)+IFERROR(calculations!T189/calculations!T188*((calculations!T209+calculations!T274)*$B$11+calculations!T210*$B$12+calculations!T211*$B$13+calculations!T212*$B$14+calculations!T213*$B$15*INDEX(input_data!$L:$L,MATCH("all.in.cs2.frt.nit.---",input_data!$A:$A,0))),0)+IFERROR(calculations!T217/calculations!T216*((calculations!T237+calculations!T279)*$B$11+calculations!T238*$B$12+calculations!T239*$B$13+calculations!T240*$B$14+calculations!T241*$B$15*INDEX(input_data!$L:$L,MATCH("all.in.cs2.alu.prp.---",input_data!$A:$A,0))),0)+IFERROR(calculations!T287/calculations!T286*((calculations!T307+calculations!T312)*$B$11+calculations!T308*$B$12+calculations!T309*$B$13+calculations!T310*$B$14+calculations!T311*$B$15*INDEX(input_data!$L:$L,MATCH("all.in.cs2.stl.oth.---",input_data!$A:$A,0))),0)+IFERROR(calculations!T319/calculations!T318*((calculations!T339+calculations!T344)*$B$11+calculations!T340*$B$12+calculations!T341*$B$13+calculations!T342*$B$14+calculations!T343*$B$15*INDEX(input_data!$L:$L,MATCH("all.in.cs2.frt.otn.---",input_data!$A:$A,0))),0)),0) -> 92.786248 | ... O28: =IFERROR((IFERROR(calculations!X21*calculations!X248,0)+IFERROR(calculations!X49*calculations!X253,0)+IFERROR(calculations!X77*calculations!X258,0)+IFERROR(calculations!X105*calculations!X263,0)+IFERROR(calculations!X133*calculations!X268,0)+IFERROR(calculations!X161*calculations!X273,0)+IFERROR(calculations!X189*calculations!X278,0)+IFERROR(calculations!X217*calculations!X283,0)+IFERROR(calculations!X287*calculations!X316,0)+IFERROR(calculations!X319*calculations!X348,0))/(IFERROR(calculations!X21/calculations!X20*((calculations!X41+calculations!X244)*$B$11+calculations!X42*$B$12+calculations!X43*$B$13+calculations!X44*$B$14+calculations!X45*$B$15*INDEX(input_data!$L:$L,MATCH("all.in.cs2.stl.drg.---",input_data!$A:$A,0))),0)+IFERROR(calculations!X49/calculations!X48*((calculations!X69+calculations!X249)*$B$11+calculations!X70*$B$12+calculations!X71*$B$13+calculations!X72*$B$14+calculations!X73*$B$15*INDEX(input_data!$L:$L,MATCH("all.in.cs2.stl.scr.---",input_data!$A:$A,0))),0)+IFERROR(calculations!X77/calculations!X76*((calculations!X97+calculations!X254)*$B$11+calculations!X98*$B$12+calculations!X99*$B$13+calculations!X100*$B$14+calculations!X101*$B$15*INDEX(input_data!$L:$L,MATCH("all.in.cs2.stl.bof.---",input_data!$A:$A,0))),0)+IFERROR(calculations!X105/calculations!X104*((calculations!X125+calculations!X259)*$B$11+calculations!X126*$B$12+calculations!X127*$B$13+calculations!X128*$B$14+calculations!X129*$B$15*INDEX(input_data!$L:$L,MATCH("all.in.cs2.cmt.dry.---",input_data!$A:$A,0))),0)+IFERROR(calculations!X133/calculations!X132*((calculations!X153+calculations!X264)*$B$11+calculations!X154*$B$12+calculations!X155*$B$13+calculations!X156*$B$14+calculations!X157*$B$15*INDEX(input_data!$L:$L,MATCH("all.in.cs2.frt.amc.---",input_data!$A:$A,0))),0)+IFERROR(calculations!X161/calculations!X160*((calculations!X181+calculations!X269)*$B$11+calculations!X182*$B$12+calculations!X183*$B$13+calculations!X184*$B$14+calculations!X185*$B$15*INDEX(input_data!$L:$L,MATCH("all.in.cs2.frt.ure.---",input_data!$A:$A,0))),0)+IFERROR(calculations!X189/calculations!X188*((calculations!X209+calculations!X274)*$B$11+calculations!X210*$B$12+calculations!X211*$B$13+calculations!X212*$B$14+calculations!X213*$B$15*INDEX(input_data!$L:$L,MATCH("all.in.cs2.frt.nit.---",input_data!$A:$A,0))),0)+IFERROR(calculations!X217/calculations!X216*((calculations!X237+calculations!X279)*$B$11+calculations!X238*$B$12+calculations!X239*$B$13+calculations!X240*$B$14+calculations!X241*$B$15*INDEX(input_data!$L:$L,MATCH("all.in.cs2.alu.prp.---",input_data!$A:$A,0))),0)+IFERROR(calculations!X287/calculations!X286*((calculations!X307+calculations!X312)*$B$11+calculations!X308*$B$12+calculations!X309*$B$13+calculations!X310*$B$14+calculations!X311*$B$15*INDEX(input_data!$L:$L,MATCH("all.in.cs2.stl.oth.---",input_data!$A:$A,0))),0)+IFERROR(calculations!X319/calculations!X318*((calculations!X339+calculations!X344)*$B$11+calculations!X340*$B$12+calculations!X341*$B$13+calculations!X342*$B$14+calculations!X343*$B$15*INDEX(input_data!$L:$L,MATCH("all.in.cs2.frt.otn.---",input_data!$A:$A,0))),0)),0) -> 154
A29: ↓ DOMESTIC CARBON PRICE (editable, default = optimal) | B29: USD/tCO2 | D29: =D28 -> 0 | E29: =E28 -> 0 | F29: =F28 -> 34.6168 | G29: =G28 -> 38.153867 | H29: =H28 -> 43.768314 | I29: =I28 -> 53.28536 | J29: =J28 -> 76.914135 | K29: =K28 -> 92.786248 | ... O29: =O28 -> 154
A31: 4. HEADLINE REVENUES (USD millions)
A32: row | B32: unit | D32: 2024 | E32: 2025 | F32: 2026 | G32: 2027 | H32: 2028 | I32: 2029 | J32: 2030 | K32: 2031 | L32: 2032 | M32: 2033 | N32: 2034 | O32: 2035
A33: EU CBAM obligation gross | B33: USD m | D33: =IFERROR(calculations!M21*calculations!M248,0)+IFERROR(calculations!M49*calculations!M253,0)+IFERROR(calculations!M77*calculations!M258,0)+IFERROR(calculations!M105*calculations!M263,0)+IFERROR(calculations!M133*calculations!M268,0)+IFERROR(calculations!M161*calculations!M273,0)+IFERROR(calculations!M189*calculations!M278,0)+IFERROR(calculations!M217*calculations!M283,0)+IFERROR(calculations!M287*calculations!M316,0)+IFERROR(calculations!M319*calculations!M348,0) -> 0 | E33: =IFERROR(calculations!N21*calculations!N248,0)+IFERROR(calculations!N49*calculations!N253,0)+IFERROR(calculations!N77*calculations!N258,0)+IFERROR(calculations!N105*calculations!N263,0)+IFERROR(calculations!N133*calculations!N268,0)+IFERROR(calculations!N161*calculations!N273,0)+IFERROR(calculations!N189*calculations!N278,0)+IFERROR(calculations!N217*calculations!N283,0)+IFERROR(calculations!N287*calculations!N316,0)+IFERROR(calculations!N319*calculations!N348,0) -> 0 | F33: =IFERROR(calculations!O21*calculations!O248,0)+IFERROR(calculations!O49*calculations!O253,0)+IFERROR(calculations!O77*calculations!O258,0)+IFERROR(calculations!O105*calculations!O263,0)+IFERROR(calculations!O133*calculations!O268,0)+IFERROR(calculations!O161*calculations!O273,0)+IFERROR(calculations!O189*calculations!O278,0)+IFERROR(calculations!O217*calculations!O283,0)+IFERROR(calculations!O287*calculations!O316,0)+IFERROR(calculations!O319*calculations!O348,0) -> 76.689832 | G33: =IFERROR(calculations!P21*calculations!P248,0)+IFERROR(calculations!P49*calculations!P253,0)+IFERROR(calculations!P77*calculations!P258,0)+IFERROR(calculations!P105*calculations!P263,0)+IFERROR(calculations!P133*calculations!P268,0)+IFERROR(calculations!P161*calculations!P273,0)+IFERROR(calculations!P189*calculations!P278,0)+IFERROR(calculations!P217*calculations!P283,0)+IFERROR(calculations!P287*calculations!P316,0)+IFERROR(calculations!P319*calculations!P348,0) -> 88.082977 | H33: =IFERROR(calculations!Q21*calculations!Q248,0)+IFERROR(calculations!Q49*calculations!Q253,0)+IFERROR(calculations!Q77*calculations!Q258,0)+IFERROR(calculations!Q105*calculations!Q263,0)+IFERROR(calculations!Q133*calculations!Q268,0)+IFERROR(calculations!Q161*calculations!Q273,0)+IFERROR(calculations!Q189*calculations!Q278,0)+IFERROR(calculations!Q217*calculations!Q283,0)+IFERROR(calculations!Q287*calculations!Q316,0)+IFERROR(calculations!Q319*calculations!Q348,0) -> 105.31264 | I33: =IFERROR(calculations!R21*calculations!R248,0)+IFERROR(calculations!R49*calculations!R253,0)+IFERROR(calculations!R77*calculations!R258,0)+IFERROR(calculations!R105*calculations!R263,0)+IFERROR(calculations!R133*calculations!R268,0)+IFERROR(calculations!R161*calculations!R273,0)+IFERROR(calculations!R189*calculations!R278,0)+IFERROR(calculations!R217*calculations!R283,0)+IFERROR(calculations!R287*calculations!R316,0)+IFERROR(calculations!R319*calculations!R348,0) -> 133.6473 | J33: =IFERROR(calculations!S21*calculations!S248,0)+IFERROR(calculations!S49*calculations!S253,0)+IFERROR(calculations!S77*calculations!S258,0)+IFERROR(calculations!S105*calculations!S263,0)+IFERROR(calculations!S133*calculations!S268,0)+IFERROR(calculations!S161*calculations!S273,0)+IFERROR(calculations!S189*calculations!S278,0)+IFERROR(calculations!S217*calculations!S283,0)+IFERROR(calculations!S287*calculations!S316,0)+IFERROR(calculations!S319*calculations!S348,0) -> 201.1194 | K33: =IFERROR(calculations!T21*calculations!T248,0)+IFERROR(calculations!T49*calculations!T253,0)+IFERROR(calculations!T77*calculations!T258,0)+IFERROR(calculations!T105*calculations!T263,0)+IFERROR(calculations!T133*calculations!T268,0)+IFERROR(calculations!T161*calculations!T273,0)+IFERROR(calculations!T189*calculations!T278,0)+IFERROR(calculations!T217*calculations!T283,0)+IFERROR(calculations!T287*calculations!T316,0)+IFERROR(calculations!T319*calculations!T348,0) -> 252.9825 | ... O33: =IFERROR(calculations!X21*calculations!X248,0)+IFERROR(calculations!X49*calculations!X253,0)+IFERROR(calculations!X77*calculations!X258,0)+IFERROR(calculations!X105*calculations!X263,0)+IFERROR(calculations!X133*calculations!X268,0)+IFERROR(calculations!X161*calculations!X273,0)+IFERROR(calculations!X189*calculations!X278,0)+IFERROR(calculations!X217*calculations!X283,0)+IFERROR(calculations!X287*calculations!X316,0)+IFERROR(calculations!X319*calculations!X348,0) -> 497.03882
A34: ● Country revenue on EU exports (total covered) | B34: USD m | D34: =IFERROR((calculations!M21/calculations!M20)*((calculations!M41+calculations!M244)*$B$11+calculations!M42*$B$12+calculations!M43*$B$13+calculations!M44*$B$14+calculations!M45*$B$15)*D29,0)+IFERROR((calculations!M49/calculations!M48)*((calculations!M69+calculations!M249)*$B$11+calculations!M70*$B$12+calculations!M71*$B$13+calculations!M72*$B$14+calculations!M73*$B$15)*D29,0)+IFERROR((calculations!M77/calculations!M76)*((calculations!M97+calculations!M254)*$B$11+calculations!M98*$B$12+calculations!M99*$B$13+calculations!M100*$B$14+calculations!M101*$B$15)*D29,0)+IFERROR((calculations!M105/calculations!M104)*((calculations!M125+calculations!M259)*$B$11+calculations!M126*$B$12+calculations!M127*$B$13+calculations!M128*$B$14+calculations!M129*$B$15)*D29,0)+IFERROR((calculations!M133/calculations!M132)*((calculations!M153+calculations!M264)*$B$11+calculations!M154*$B$12+calculations!M155*$B$13+calculations!M156*$B$14+calculations!M157*$B$15)*D29,0)+IFERROR((calculations!M161/calculations!M160)*((calculations!M181+calculations!M269)*$B$11+calculations!M182*$B$12+calculations!M183*$B$13+calculations!M184*$B$14+calculations!M185*$B$15)*D29,0)+IFERROR((calculations!M189/calculations!M188)*((calculations!M209+calculations!M274)*$B$11+calculations!M210*$B$12+calculations!M211*$B$13+calculations!M212*$B$14+calculations!M213*$B$15)*D29,0)+IFERROR((calculations!M217/calculations!M216)*((calculations!M237+calculations!M279)*$B$11+calculations!M238*$B$12+calculations!M239*$B$13+calculations!M240*$B$14+calculations!M241*$B$15)*D29,0)+IFERROR((calculations!M287/calculations!M286)*((calculations!M307+calculations!M312)*$B$11+calculations!M308*$B$12+calculations!M309*$B$13+calculations!M310*$B$14+calculations!M311*$B$15)*D29,0)+IFERROR((calculations!M319/calculations!M318)*((calculations!M339+calculations!M344)*$B$11+calculations!M340*$B$12+calculations!M341*$B$13+calculations!M342*$B$14+calculations!M343*$B$15)*D29,0) -> 0 | E34: =IFERROR((calculations!N21/calculations!N20)*((calculations!N41+calculations!N244)*$B$11+calculations!N42*$B$12+calculations!N43*$B$13+calculations!N44*$B$14+calculations!N45*$B$15)*E29,0)+IFERROR((calculations!N49/calculations!N48)*((calculations!N69+calculations!N249)*$B$11+calculations!N70*$B$12+calculations!N71*$B$13+calculations!N72*$B$14+calculations!N73*$B$15)*E29,0)+IFERROR((calculations!N77/calculations!N76)*((calculations!N97+calculations!N254)*$B$11+calculations!N98*$B$12+calculations!N99*$B$13+calculations!N100*$B$14+calculations!N101*$B$15)*E29,0)+IFERROR((calculations!N105/calculations!N104)*((calculations!N125+calculations!N259)*$B$11+calculations!N126*$B$12+calculations!N127*$B$13+calculations!N128*$B$14+calculations!N129*$B$15)*E29,0)+IFERROR((calculations!N133/calculations!N132)*((calculations!N153+calculations!N264)*$B$11+calculations!N154*$B$12+calculations!N155*$B$13+calculations!N156*$B$14+calculations!N157*$B$15)*E29,0)+IFERROR((calculations!N161/calculations!N160)*((calculations!N181+calculations!N269)*$B$11+calculations!N182*$B$12+calculations!N183*$B$13+calculations!N184*$B$14+calculations!N185*$B$15)*E29,0)+IFERROR((calculations!N189/calculations!N188)*((calculations!N209+calculations!N274)*$B$11+calculations!N210*$B$12+calculations!N211*$B$13+calculations!N212*$B$14+calculations!N213*$B$15)*E29,0)+IFERROR((calculations!N217/calculations!N216)*((calculations!N237+calculations!N279)*$B$11+calculations!N238*$B$12+calculations!N239*$B$13+calculations!N240*$B$14+calculations!N241*$B$15)*E29,0)+IFERROR((calculations!N287/calculations!N286)*((calculations!N307+calculations!N312)*$B$11+calculations!N308*$B$12+calculations!N309*$B$13+calculations!N310*$B$14+calculations!N311*$B$15)*E29,0)+IFERROR((calculations!N319/calculations!N318)*((calculations!N339+calculations!N344)*$B$11+calculations!N340*$B$12+calculations!N341*$B$13+calculations!N342*$B$14+calculations!N343*$B$15)*E29,0) -> 0 | F34: =IFERROR((calculations!O21/calculations!O20)*((calculations!O41+calculations!O244)*$B$11+calculations!O42*$B$12+calculations!O43*$B$13+calculations!O44*$B$14+calculations!O45*$B$15)*F29,0)+IFERROR((calculations!O49/calculations!O48)*((calculations!O69+calculations!O249)*$B$11+calculations!O70*$B$12+calculations!O71*$B$13+calculations!O72*$B$14+calculations!O73*$B$15)*F29,0)+IFERROR((calculations!O77/calculations!O76)*((calculations!O97+calculations!O254)*$B$11+calculations!O98*$B$12+calculations!O99*$B$13+calculations!O100*$B$14+calculations!O101*$B$15)*F29,0)+IFERROR((calculations!O105/calculations!O104)*((calculations!O125+calculations!O259)*$B$11+calculations!O126*$B$12+calculations!O127*$B$13+calculations!O128*$B$14+calculations!O129*$B$15)*F29,0)+IFERROR((calculations!O133/calculations!O132)*((calculations!O153+calculations!O264)*$B$11+calculations!O154*$B$12+calculations!O155*$B$13+calculations!O156*$B$14+calculations!O157*$B$15)*F29,0)+IFERROR((calculations!O161/calculations!O160)*((calculations!O181+calculations!O269)*$B$11+calculations!O182*$B$12+calculations!O183*$B$13+calculations!O184*$B$14+calculations!O185*$B$15)*F29,0)+IFERROR((calculations!O189/calculations!O188)*((calculations!O209+calculations!O274)*$B$11+calculations!O210*$B$12+calculations!O211*$B$13+calculations!O212*$B$14+calculations!O213*$B$15)*F29,0)+IFERROR((calculations!O217/calculations!O216)*((calculations!O237+calculations!O279)*$B$11+calculations!O238*$B$12+calculations!O239*$B$13+calculations!O240*$B$14+calculations!O241*$B$15)*F29,0)+IFERROR((calculations!O287/calculations!O286)*((calculations!O307+calculations!O312)*$B$11+calculations!O308*$B$12+calculations!O309*$B$13+calculations!O310*$B$14+calculations!O311*$B$15)*F29,0)+IFERROR((calculations!O319/calculations!O318)*((calculations!O339+calculations!O344)*$B$11+calculations!O340*$B$12+calculations!O341*$B$13+calculations!O342*$B$14+calculations!O343*$B$15)*F29,0) -> 105.56305 | G34: =IFERROR((calculations!P21/calculations!P20)*((calculations!P41+calculations!P244)*$B$11+calculations!P42*$B$12+calculations!P43*$B$13+calculations!P44*$B$14+calculations!P45*$B$15)*G29,0)+IFERROR((calculations!P49/calculations!P48)*((calculations!P69+calculations!P249)*$B$11+calculations!P70*$B$12+calculations!P71*$B$13+calculations!P72*$B$14+calculations!P73*$B$15)*G29,0)+IFERROR((calculations!P77/calculations!P76)*((calculations!P97+calculations!P254)*$B$11+calculations!P98*$B$12+calculations!P99*$B$13+calculations!P100*$B$14+calculations!P101*$B$15)*G29,0)+IFERROR((calculations!P105/calculations!P104)*((calculations!P125+calculations!P259)*$B$11+calculations!P126*$B$12+calculations!P127*$B$13+calculations!P128*$B$14+calculations!P129*$B$15)*G29,0)+IFERROR((calculations!P133/calculations!P132)*((calculations!P153+calculations!P264)*$B$11+calculations!P154*$B$12+calculations!P155*$B$13+calculations!P156*$B$14+calculations!P157*$B$15)*G29,0)+IFERROR((calculations!P161/calculations!P160)*((calculations!P181+calculations!P269)*$B$11+calculations!P182*$B$12+calculations!P183*$B$13+calculations!P184*$B$14+calculations!P185*$B$15)*G29,0)+IFERROR((calculations!P189/calculations!P188)*((calculations!P209+calculations!P274)*$B$11+calculations!P210*$B$12+calculations!P211*$B$13+calculations!P212*$B$14+calculations!P213*$B$15)*G29,0)+IFERROR((calculations!P217/calculations!P216)*((calculations!P237+calculations!P279)*$B$11+calculations!P238*$B$12+calculations!P239*$B$13+calculations!P240*$B$14+calculations!P241*$B$15)*G29,0)+IFERROR((calculations!P287/calculations!P286)*((calculations!P307+calculations!P312)*$B$11+calculations!P308*$B$12+calculations!P309*$B$13+calculations!P310*$B$14+calculations!P311*$B$15)*G29,0)+IFERROR((calculations!P319/calculations!P318)*((calculations!P339+calculations!P344)*$B$11+calculations!P340*$B$12+calculations!P341*$B$13+calculations!P342*$B$14+calculations!P343*$B$15)*G29,0) -> 120.73892 | H34: =IFERROR((calculations!Q21/calculations!Q20)*((calculations!Q41+calculations!Q244)*$B$11+calculations!Q42*$B$12+calculations!Q43*$B$13+calculations!Q44*$B$14+calculations!Q45*$B$15)*H29,0)+IFERROR((calculations!Q49/calculations!Q48)*((calculations!Q69+calculations!Q249)*$B$11+calculations!Q70*$B$12+calculations!Q71*$B$13+calculations!Q72*$B$14+calculations!Q73*$B$15)*H29,0)+IFERROR((calculations!Q77/calculations!Q76)*((calculations!Q97+calculations!Q254)*$B$11+calculations!Q98*$B$12+calculations!Q99*$B$13+calculations!Q100*$B$14+calculations!Q101*$B$15)*H29,0)+IFERROR((calculations!Q105/calculations!Q104)*((calculations!Q125+calculations!Q259)*$B$11+calculations!Q126*$B$12+calculations!Q127*$B$13+calculations!Q128*$B$14+calculations!Q129*$B$15)*H29,0)+IFERROR((calculations!Q133/calculations!Q132)*((calculations!Q153+calculations!Q264)*$B$11+calculations!Q154*$B$12+calculations!Q155*$B$13+calculations!Q156*$B$14+calculations!Q157*$B$15)*H29,0)+IFERROR((calculations!Q161/calculations!Q160)*((calculations!Q181+calculations!Q269)*$B$11+calculations!Q182*$B$12+calculations!Q183*$B$13+calculations!Q184*$B$14+calculations!Q185*$B$15)*H29,0)+IFERROR((calculations!Q189/calculations!Q188)*((calculations!Q209+calculations!Q274)*$B$11+calculations!Q210*$B$12+calculations!Q211*$B$13+calculations!Q212*$B$14+calculations!Q213*$B$15)*H29,0)+IFERROR((calculations!Q217/calculations!Q216)*((calculations!Q237+calculations!Q279)*$B$11+calculations!Q238*$B$12+calculations!Q239*$B$13+calculations!Q240*$B$14+calculations!Q241*$B$15)*H29,0)+IFERROR((calculations!Q287/calculations!Q286)*((calculations!Q307+calculations!Q312)*$B$11+calculations!Q308*$B$12+calculations!Q309*$B$13+calculations!Q310*$B$14+calculations!Q311*$B$15)*H29,0)+IFERROR((calculations!Q319/calculations!Q318)*((calculations!Q339+calculations!Q344)*$B$11+calculations!Q340*$B$12+calculations!Q341*$B$13+calculations!Q342*$B$14+calculations!Q343*$B$15)*H29,0) -> 143.7383 | I34: =IFERROR((calculations!R21/calculations!R20)*((calculations!R41+calculations!R244)*$B$11+calculations!R42*$B$12+calculations!R43*$B$13+calculations!R44*$B$14+calculations!R45*$B$15)*I29,0)+IFERROR((calculations!R49/calculations!R48)*((calculations!R69+calculations!R249)*$B$11+calculations!R70*$B$12+calculations!R71*$B$13+calculations!R72*$B$14+calculations!R73*$B$15)*I29,0)+IFERROR((calculations!R77/calculations!R76)*((calculations!R97+calculations!R254)*$B$11+calculations!R98*$B$12+calculations!R99*$B$13+calculations!R100*$B$14+calculations!R101*$B$15)*I29,0)+IFERROR((calculations!R105/calculations!R104)*((calculations!R125+calculations!R259)*$B$11+calculations!R126*$B$12+calculations!R127*$B$13+calculations!R128*$B$14+calculations!R129*$B$15)*I29,0)+IFERROR((calculations!R133/calculations!R132)*((calculations!R153+calculations!R264)*$B$11+calculations!R154*$B$12+calculations!R155*$B$13+calculations!R156*$B$14+calculations!R157*$B$15)*I29,0)+IFERROR((calculations!R161/calculations!R160)*((calculations!R181+calculations!R269)*$B$11+calculations!R182*$B$12+calculations!R183*$B$13+calculations!R184*$B$14+calculations!R185*$B$15)*I29,0)+IFERROR((calculations!R189/calculations!R188)*((calculations!R209+calculations!R274)*$B$11+calculations!R210*$B$12+calculations!R211*$B$13+calculations!R212*$B$14+calculations!R213*$B$15)*I29,0)+IFERROR((calculations!R217/calculations!R216)*((calculations!R237+calculations!R279)*$B$11+calculations!R238*$B$12+calculations!R239*$B$13+calculations!R240*$B$14+calculations!R241*$B$15)*I29,0)+IFERROR((calculations!R287/calculations!R286)*((calculations!R307+calculations!R312)*$B$11+calculations!R308*$B$12+calculations!R309*$B$13+calculations!R310*$B$14+calculations!R311*$B$15)*I29,0)+IFERROR((calculations!R319/calculations!R318)*((calculations!R339+calculations!R344)*$B$11+calculations!R340*$B$12+calculations!R341*$B$13+calculations!R342*$B$14+calculations!R343*$B$15)*I29,0) -> 181.61202 | J34: =IFERROR((calculations!S21/calculations!S20)*((calculations!S41+calculations!S244)*$B$11+calculations!S42*$B$12+calculations!S43*$B$13+calculations!S44*$B$14+calculations!S45*$B$15)*J29,0)+IFERROR((calculations!S49/calculations!S48)*((calculations!S69+calculations!S249)*$B$11+calculations!S70*$B$12+calculations!S71*$B$13+calculations!S72*$B$14+calculations!S73*$B$15)*J29,0)+IFERROR((calculations!S77/calculations!S76)*((calculations!S97+calculations!S254)*$B$11+calculations!S98*$B$12+calculations!S99*$B$13+calculations!S100*$B$14+calculations!S101*$B$15)*J29,0)+IFERROR((calculations!S105/calculations!S104)*((calculations!S125+calculations!S259)*$B$11+calculations!S126*$B$12+calculations!S127*$B$13+calculations!S128*$B$14+calculations!S129*$B$15)*J29,0)+IFERROR((calculations!S133/calculations!S132)*((calculations!S153+calculations!S264)*$B$11+calculations!S154*$B$12+calculations!S155*$B$13+calculations!S156*$B$14+calculations!S157*$B$15)*J29,0)+IFERROR((calculations!S161/calculations!S160)*((calculations!S181+calculations!S269)*$B$11+calculations!S182*$B$12+calculations!S183*$B$13+calculations!S184*$B$14+calculations!S185*$B$15)*J29,0)+IFERROR((calculations!S189/calculations!S188)*((calculations!S209+calculations!S274)*$B$11+calculations!S210*$B$12+calculations!S211*$B$13+calculations!S212*$B$14+calculations!S213*$B$15)*J29,0)+IFERROR((calculations!S217/calculations!S216)*((calculations!S237+calculations!S279)*$B$11+calculations!S238*$B$12+calculations!S239*$B$13+calculations!S240*$B$14+calculations!S241*$B$15)*J29,0)+IFERROR((calculations!S287/calculations!S286)*((calculations!S307+calculations!S312)*$B$11+calculations!S308*$B$12+calculations!S309*$B$13+calculations!S310*$B$14+calculations!S311*$B$15)*J29,0)+IFERROR((calculations!S319/calculations!S318)*((calculations!S339+calculations!S344)*$B$11+calculations!S340*$B$12+calculations!S341*$B$13+calculations!S342*$B$14+calculations!S343*$B$15)*J29,0) -> 272.07369 | K34: =IFERROR((calculations!T21/calculations!T20)*((calculations!T41+calculations!T244)*$B$11+calculations!T42*$B$12+calculations!T43*$B$13+calculations!T44*$B$14+calculations!T45*$B$15)*K29,0)+IFERROR((calculations!T49/calculations!T48)*((calculations!T69+calculations!T249)*$B$11+calculations!T70*$B$12+calculations!T71*$B$13+calculations!T72*$B$14+calculations!T73*$B$15)*K29,0)+IFERROR((calculations!T77/calculations!T76)*((calculations!T97+calculations!T254)*$B$11+calculations!T98*$B$12+calculations!T99*$B$13+calculations!T100*$B$14+calculations!T101*$B$15)*K29,0)+IFERROR((calculations!T105/calculations!T104)*((calculations!T125+calculations!T259)*$B$11+calculations!T126*$B$12+calculations!T127*$B$13+calculations!T128*$B$14+calculations!T129*$B$15)*K29,0)+IFERROR((calculations!T133/calculations!T132)*((calculations!T153+calculations!T264)*$B$11+calculations!T154*$B$12+calculations!T155*$B$13+calculations!T156*$B$14+calculations!T157*$B$15)*K29,0)+IFERROR((calculations!T161/calculations!T160)*((calculations!T181+calculations!T269)*$B$11+calculations!T182*$B$12+calculations!T183*$B$13+calculations!T184*$B$14+calculations!T185*$B$15)*K29,0)+IFERROR((calculations!T189/calculations!T188)*((calculations!T209+calculations!T274)*$B$11+calculations!T210*$B$12+calculations!T211*$B$13+calculations!T212*$B$14+calculations!T213*$B$15)*K29,0)+IFERROR((calculations!T217/calculations!T216)*((calculations!T237+calculations!T279)*$B$11+calculations!T238*$B$12+calculations!T239*$B$13+calculations!T240*$B$14+calculations!T241*$B$15)*K29,0)+IFERROR((calculations!T287/calculations!T286)*((calculations!T307+calculations!T312)*$B$11+calculations!T308*$B$12+calculations!T309*$B$13+calculations!T310*$B$14+calculations!T311*$B$15)*K29,0)+IFERROR((calculations!T319/calculations!T318)*((calculations!T339+calculations!T344)*$B$11+calculations!T340*$B$12+calculations!T341*$B$13+calculations!T342*$B$14+calculations!T343*$B$15)*K29,0) -> 340.66466 | ... O34: =IFERROR((calculations!X21/calculations!X20)*((calculations!X41+calculations!X244)*$B$11+calculations!X42*$B$12+calculations!X43*$B$13+calculations!X44*$B$14+calculations!X45*$B$15)*O29,0)+IFERROR((calculations!X49/calculations!X48)*((calculations!X69+calculations!X249)*$B$11+calculations!X70*$B$12+calculations!X71*$B$13+calculations!X72*$B$14+calculations!X73*$B$15)*O29,0)+IFERROR((calculations!X77/calculations!X76)*((calculations!X97+calculations!X254)*$B$11+calculations!X98*$B$12+calculations!X99*$B$13+calculations!X100*$B$14+calculations!X101*$B$15)*O29,0)+IFERROR((calculations!X105/calculations!X104)*((calculations!X125+calculations!X259)*$B$11+calculations!X126*$B$12+calculations!X127*$B$13+calculations!X128*$B$14+calculations!X129*$B$15)*O29,0)+IFERROR((calculations!X133/calculations!X132)*((calculations!X153+calculations!X264)*$B$11+calculations!X154*$B$12+calculations!X155*$B$13+calculations!X156*$B$14+calculations!X157*$B$15)*O29,0)+IFERROR((calculations!X161/calculations!X160)*((calculations!X181+calculations!X269)*$B$11+calculations!X182*$B$12+calculations!X183*$B$13+calculations!X184*$B$14+calculations!X185*$B$15)*O29,0)+IFERROR((calculations!X189/calculations!X188)*((calculations!X209+calculations!X274)*$B$11+calculations!X210*$B$12+calculations!X211*$B$13+calculations!X212*$B$14+calculations!X213*$B$15)*O29,0)+IFERROR((calculations!X217/calculations!X216)*((calculations!X237+calculations!X279)*$B$11+calculations!X238*$B$12+calculations!X239*$B$13+calculations!X240*$B$14+calculations!X241*$B$15)*O29,0)+IFERROR((calculations!X287/calculations!X286)*((calculations!X307+calculations!X312)*$B$11+calculations!X308*$B$12+calculations!X309*$B$13+calculations!X310*$B$14+calculations!X311*$B$15)*O29,0)+IFERROR((calculations!X319/calculations!X318)*((calculations!X339+calculations!X344)*$B$11+calculations!X340*$B$12+calculations!X341*$B$13+calculations!X342*$B$14+calculations!X343*$B$15)*O29,0) -> 656.45376
A35: of which creditable against CBAM | B35: USD m | D35: =IFERROR((calculations!M21/calculations!M20)*((calculations!M41+calculations!M244)*$B$11+calculations!M42*$B$12+calculations!M43*$B$13+calculations!M44*$B$14+calculations!M45*$B$15*INDEX(input_data!$L:$L,MATCH("all.in.cs2.stl.drg.---",input_data!$A:$A,0)))*D29,0)+IFERROR((calculations!M49/calculations!M48)*((calculations!M69+calculations!M249)*$B$11+calculations!M70*$B$12+calculations!M71*$B$13+calculations!M72*$B$14+calculations!M73*$B$15*INDEX(input_data!$L:$L,MATCH("all.in.cs2.stl.scr.---",input_data!$A:$A,0)))*D29,0)+IFERROR((calculations!M77/calculations!M76)*((calculations!M97+calculations!M254)*$B$11+calculations!M98*$B$12+calculations!M99*$B$13+calculations!M100*$B$14+calculations!M101*$B$15*INDEX(input_data!$L:$L,MATCH("all.in.cs2.stl.bof.---",input_data!$A:$A,0)))*D29,0)+IFERROR((calculations!M105/calculations!M104)*((calculations!M125+calculations!M259)*$B$11+calculations!M126*$B$12+calculations!M127*$B$13+calculations!M128*$B$14+calculations!M129*$B$15*INDEX(input_data!$L:$L,MATCH("all.in.cs2.cmt.dry.---",input_data!$A:$A,0)))*D29,0)+IFERROR((calculations!M133/calculations!M132)*((calculations!M153+calculations!M264)*$B$11+calculations!M154*$B$12+calculations!M155*$B$13+calculations!M156*$B$14+calculations!M157*$B$15*INDEX(input_data!$L:$L,MATCH("all.in.cs2.frt.amc.---",input_data!$A:$A,0)))*D29,0)+IFERROR((calculations!M161/calculations!M160)*((calculations!M181+calculations!M269)*$B$11+calculations!M182*$B$12+calculations!M183*$B$13+calculations!M184*$B$14+calculations!M185*$B$15*INDEX(input_data!$L:$L,MATCH("all.in.cs2.frt.ure.---",input_data!$A:$A,0)))*D29,0)+IFERROR((calculations!M189/calculations!M188)*((calculations!M209+calculations!M274)*$B$11+calculations!M210*$B$12+calculations!M211*$B$13+calculations!M212*$B$14+calculations!M213*$B$15*INDEX(input_data!$L:$L,MATCH("all.in.cs2.frt.nit.---",input_data!$A:$A,0)))*D29,0)+IFERROR((calculations!M217/calculations!M216)*((calculations!M237+calculations!M279)*$B$11+calculations!M238*$B$12+calculations!M239*$B$13+calculations!M240*$B$14+calculations!M241*$B$15*INDEX(input_data!$L:$L,MATCH("all.in.cs2.alu.prp.---",input_data!$A:$A,0)))*D29,0)+IFERROR((calculations!M287/calculations!M286)*((calculations!M307+calculations!M312)*$B$11+calculations!M308*$B$12+calculations!M309*$B$13+calculations!M310*$B$14+calculations!M311*$B$15*INDEX(input_data!$L:$L,MATCH("all.in.cs2.stl.oth.---",input_data!$A:$A,0)))*D29,0)+IFERROR((calculations!M319/calculations!M318)*((calculations!M339+calculations!M344)*$B$11+calculations!M340*$B$12+calculations!M341*$B$13+calculations!M342*$B$14+calculations!M343*$B$15*INDEX(input_data!$L:$L,MATCH("all.in.cs2.frt.otn.---",input_data!$A:$A,0)))*D29,0) -> 0 | E35: =IFERROR((calculations!N21/calculations!N20)*((calculations!N41+calculations!N244)*$B$11+calculations!N42*$B$12+calculations!N43*$B$13+calculations!N44*$B$14+calculations!N45*$B$15*INDEX(input_data!$L:$L,MATCH("all.in.cs2.stl.drg.---",input_data!$A:$A,0)))*E29,0)+IFERROR((calculations!N49/calculations!N48)*((calculations!N69+calculations!N249)*$B$11+calculations!N70*$B$12+calculations!N71*$B$13+calculations!N72*$B$14+calculations!N73*$B$15*INDEX(input_data!$L:$L,MATCH("all.in.cs2.stl.scr.---",input_data!$A:$A,0)))*E29,0)+IFERROR((calculations!N77/calculations!N76)*((calculations!N97+calculations!N254)*$B$11+calculations!N98*$B$12+calculations!N99*$B$13+calculations!N100*$B$14+calculations!N101*$B$15*INDEX(input_data!$L:$L,MATCH("all.in.cs2.stl.bof.---",input_data!$A:$A,0)))*E29,0)+IFERROR((calculations!N105/calculations!N104)*((calculations!N125+calculations!N259)*$B$11+calculations!N126*$B$12+calculations!N127*$B$13+calculations!N128*$B$14+calculations!N129*$B$15*INDEX(input_data!$L:$L,MATCH("all.in.cs2.cmt.dry.---",input_data!$A:$A,0)))*E29,0)+IFERROR((calculations!N133/calculations!N132)*((calculations!N153+calculations!N264)*$B$11+calculations!N154*$B$12+calculations!N155*$B$13+calculations!N156*$B$14+calculations!N157*$B$15*INDEX(input_data!$L:$L,MATCH("all.in.cs2.frt.amc.---",input_data!$A:$A,0)))*E29,0)+IFERROR((calculations!N161/calculations!N160)*((calculations!N181+calculations!N269)*$B$11+calculations!N182*$B$12+calculations!N183*$B$13+calculations!N184*$B$14+calculations!N185*$B$15*INDEX(input_data!$L:$L,MATCH("all.in.cs2.frt.ure.---",input_data!$A:$A,0)))*E29,0)+IFERROR((calculations!N189/calculations!N188)*((calculations!N209+calculations!N274)*$B$11+calculations!N210*$B$12+calculations!N211*$B$13+calculations!N212*$B$14+calculations!N213*$B$15*INDEX(input_data!$L:$L,MATCH("all.in.cs2.frt.nit.---",input_data!$A:$A,0)))*E29,0)+IFERROR((calculations!N217/calculations!N216)*((calculations!N237+calculations!N279)*$B$11+calculations!N238*$B$12+calculations!N239*$B$13+calculations!N240*$B$14+calculations!N241*$B$15*INDEX(input_data!$L:$L,MATCH("all.in.cs2.alu.prp.---",input_data!$A:$A,0)))*E29,0)+IFERROR((calculations!N287/calculations!N286)*((calculations!N307+calculations!N312)*$B$11+calculations!N308*$B$12+calculations!N309*$B$13+calculations!N310*$B$14+calculations!N311*$B$15*INDEX(input_data!$L:$L,MATCH("all.in.cs2.stl.oth.---",input_data!$A:$A,0)))*E29,0)+IFERROR((calculations!N319/calculations!N318)*((calculations!N339+calculations!N344)*$B$11+calculations!N340*$B$12+calculations!N341*$B$13+calculations!N342*$B$14+calculations!N343*$B$15*INDEX(input_data!$L:$L,MATCH("all.in.cs2.frt.otn.---",input_data!$A:$A,0)))*E29,0) -> 0 | F35: =IFERROR((calculations!O21/calculations!O20)*((calculations!O41+calculations!O244)*$B$11+calculations!O42*$B$12+calculations!O43*$B$13+calculations!O44*$B$14+calculations!O45*$B$15*INDEX(input_data!$L:$L,MATCH("all.in.cs2.stl.drg.---",input_data!$A:$A,0)))*F29,0)+IFERROR((calculations!O49/calculations!O48)*((calculations!O69+calculations!O249)*$B$11+calculations!O70*$B$12+calculations!O71*$B$13+calculations!O72*$B$14+calculations!O73*$B$15*INDEX(input_data!$L:$L,MATCH("all.in.cs2.stl.scr.---",input_data!$A:$A,0)))*F29,0)+IFERROR((calculations!O77/calculations!O76)*((calculations!O97+calculations!O254)*$B$11+calculations!O98*$B$12+calculations!O99*$B$13+calculations!O100*$B$14+calculations!O101*$B$15*INDEX(input_data!$L:$L,MATCH("all.in.cs2.stl.bof.---",input_data!$A:$A,0)))*F29,0)+IFERROR((calculations!O105/calculations!O104)*((calculations!O125+calculations!O259)*$B$11+calculations!O126*$B$12+calculations!O127*$B$13+calculations!O128*$B$14+calculations!O129*$B$15*INDEX(input_data!$L:$L,MATCH("all.in.cs2.cmt.dry.---",input_data!$A:$A,0)))*F29,0)+IFERROR((calculations!O133/calculations!O132)*((calculations!O153+calculations!O264)*$B$11+calculations!O154*$B$12+calculations!O155*$B$13+calculations!O156*$B$14+calculations!O157*$B$15*INDEX(input_data!$L:$L,MATCH("all.in.cs2.frt.amc.---",input_data!$A:$A,0)))*F29,0)+IFERROR((calculations!O161/calculations!O160)*((calculations!O181+calculations!O269)*$B$11+calculations!O182*$B$12+calculations!O183*$B$13+calculations!O184*$B$14+calculations!O185*$B$15*INDEX(input_data!$L:$L,MATCH("all.in.cs2.frt.ure.---",input_data!$A:$A,0)))*F29,0)+IFERROR((calculations!O189/calculations!O188)*((calculations!O209+calculations!O274)*$B$11+calculations!O210*$B$12+calculations!O211*$B$13+calculations!O212*$B$14+calculations!O213*$B$15*INDEX(input_data!$L:$L,MATCH("all.in.cs2.frt.nit.---",input_data!$A:$A,0)))*F29,0)+IFERROR((calculations!O217/calculations!O216)*((calculations!O237+calculations!O279)*$B$11+calculations!O238*$B$12+calculations!O239*$B$13+calculations!O240*$B$14+calculations!O241*$B$15*INDEX(input_data!$L:$L,MATCH("all.in.cs2.alu.prp.---",input_data!$A:$A,0)))*F29,0)+IFERROR((calculations!O287/calculations!O286)*((calculations!O307+calculations!O312)*$B$11+calculations!O308*$B$12+calculations!O309*$B$13+calculations!O310*$B$14+calculations!O311*$B$15*INDEX(input_data!$L:$L,MATCH("all.in.cs2.stl.oth.---",input_data!$A:$A,0)))*F29,0)+IFERROR((calculations!O319/calculations!O318)*((calculations!O339+calculations!O344)*$B$11+calculations!O340*$B$12+calculations!O341*$B$13+calculations!O342*$B$14+calculations!O343*$B$15*INDEX(input_data!$L:$L,MATCH("all.in.cs2.frt.otn.---",input_data!$A:$A,0)))*F29,0) -> 76.689832 | G35: =IFERROR((calculations!P21/calculations!P20)*((calculations!P41+calculations!P244)*$B$11+calculations!P42*$B$12+calculations!P43*$B$13+calculations!P44*$B$14+calculations!P45*$B$15*INDEX(input_data!$L:$L,MATCH("all.in.cs2.stl.drg.---",input_data!$A:$A,0)))*G29,0)+IFERROR((calculations!P49/calculations!P48)*((calculations!P69+calculations!P249)*$B$11+calculations!P70*$B$12+calculations!P71*$B$13+calculations!P72*$B$14+calculations!P73*$B$15*INDEX(input_data!$L:$L,MATCH("all.in.cs2.stl.scr.---",input_data!$A:$A,0)))*G29,0)+IFERROR((calculations!P77/calculations!P76)*((calculations!P97+calculations!P254)*$B$11+calculations!P98*$B$12+calculations!P99*$B$13+calculations!P100*$B$14+calculations!P101*$B$15*INDEX(input_data!$L:$L,MATCH("all.in.cs2.stl.bof.---",input_data!$A:$A,0)))*G29,0)+IFERROR((calculations!P105/calculations!P104)*((calculations!P125+calculations!P259)*$B$11+calculations!P126*$B$12+calculations!P127*$B$13+calculations!P128*$B$14+calculations!P129*$B$15*INDEX(input_data!$L:$L,MATCH("all.in.cs2.cmt.dry.---",input_data!$A:$A,0)))*G29,0)+IFERROR((calculations!P133/calculations!P132)*((calculations!P153+calculations!P264)*$B$11+calculations!P154*$B$12+calculations!P155*$B$13+calculations!P156*$B$14+calculations!P157*$B$15*INDEX(input_data!$L:$L,MATCH("all.in.cs2.frt.amc.---",input_data!$A:$A,0)))*G29,0)+IFERROR((calculations!P161/calculations!P160)*((calculations!P181+calculations!P269)*$B$11+calculations!P182*$B$12+calculations!P183*$B$13+calculations!P184*$B$14+calculations!P185*$B$15*INDEX(input_data!$L:$L,MATCH("all.in.cs2.frt.ure.---",input_data!$A:$A,0)))*G29,0)+IFERROR((calculations!P189/calculations!P188)*((calculations!P209+calculations!P274)*$B$11+calculations!P210*$B$12+calculations!P211*$B$13+calculations!P212*$B$14+calculations!P213*$B$15*INDEX(input_data!$L:$L,MATCH("all.in.cs2.frt.nit.---",input_data!$A:$A,0)))*G29,0)+IFERROR((calculations!P217/calculations!P216)*((calculations!P237+calculations!P279)*$B$11+calculations!P238*$B$12+calculations!P239*$B$13+calculations!P240*$B$14+calculations!P241*$B$15*INDEX(input_data!$L:$L,MATCH("all.in.cs2.alu.prp.---",input_data!$A:$A,0)))*G29,0)+IFERROR((calculations!P287/calculations!P286)*((calculations!P307+calculations!P312)*$B$11+calculations!P308*$B$12+calculations!P309*$B$13+calculations!P310*$B$14+calculations!P311*$B$15*INDEX(input_data!$L:$L,MATCH("all.in.cs2.stl.oth.---",input_data!$A:$A,0)))*G29,0)+IFERROR((calculations!P319/calculations!P318)*((calculations!P339+calculations!P344)*$B$11+calculations!P340*$B$12+calculations!P341*$B$13+calculations!P342*$B$14+calculations!P343*$B$15*INDEX(input_data!$L:$L,MATCH("all.in.cs2.frt.otn.---",input_data!$A:$A,0)))*G29,0) -> 88.082977 | H35: =IFERROR((calculations!Q21/calculations!Q20)*((calculations!Q41+calculations!Q244)*$B$11+calculations!Q42*$B$12+calculations!Q43*$B$13+calculations!Q44*$B$14+calculations!Q45*$B$15*INDEX(input_data!$L:$L,MATCH("all.in.cs2.stl.drg.---",input_data!$A:$A,0)))*H29,0)+IFERROR((calculations!Q49/calculations!Q48)*((calculations!Q69+calculations!Q249)*$B$11+calculations!Q70*$B$12+calculations!Q71*$B$13+calculations!Q72*$B$14+calculations!Q73*$B$15*INDEX(input_data!$L:$L,MATCH("all.in.cs2.stl.scr.---",input_data!$A:$A,0)))*H29,0)+IFERROR((calculations!Q77/calculations!Q76)*((calculations!Q97+calculations!Q254)*$B$11+calculations!Q98*$B$12+calculations!Q99*$B$13+calculations!Q100*$B$14+calculations!Q101*$B$15*INDEX(input_data!$L:$L,MATCH("all.in.cs2.stl.bof.---",input_data!$A:$A,0)))*H29,0)+IFERROR((calculations!Q105/calculations!Q104)*((calculations!Q125+calculations!Q259)*$B$11+calculations!Q126*$B$12+calculations!Q127*$B$13+calculations!Q128*$B$14+calculations!Q129*$B$15*INDEX(input_data!$L:$L,MATCH("all.in.cs2.cmt.dry.---",input_data!$A:$A,0)))*H29,0)+IFERROR((calculations!Q133/calculations!Q132)*((calculations!Q153+calculations!Q264)*$B$11+calculations!Q154*$B$12+calculations!Q155*$B$13+calculations!Q156*$B$14+calculations!Q157*$B$15*INDEX(input_data!$L:$L,MATCH("all.in.cs2.frt.amc.---",input_data!$A:$A,0)))*H29,0)+IFERROR((calculations!Q161/calculations!Q160)*((calculations!Q181+calculations!Q269)*$B$11+calculations!Q182*$B$12+calculations!Q183*$B$13+calculations!Q184*$B$14+calculations!Q185*$B$15*INDEX(input_data!$L:$L,MATCH("all.in.cs2.frt.ure.---",input_data!$A:$A,0)))*H29,0)+IFERROR((calculations!Q189/calculations!Q188)*((calculations!Q209+calculations!Q274)*$B$11+calculations!Q210*$B$12+calculations!Q211*$B$13+calculations!Q212*$B$14+calculations!Q213*$B$15*INDEX(input_data!$L:$L,MATCH("all.in.cs2.frt.nit.---",input_data!$A:$A,0)))*H29,0)+IFERROR((calculations!Q217/calculations!Q216)*((calculations!Q237+calculations!Q279)*$B$11+calculations!Q238*$B$12+calculations!Q239*$B$13+calculations!Q240*$B$14+calculations!Q241*$B$15*INDEX(input_data!$L:$L,MATCH("all.in.cs2.alu.prp.---",input_data!$A:$A,0)))*H29,0)+IFERROR((calculations!Q287/calculations!Q286)*((calculations!Q307+calculations!Q312)*$B$11+calculations!Q308*$B$12+calculations!Q309*$B$13+calculations!Q310*$B$14+calculations!Q311*$B$15*INDEX(input_data!$L:$L,MATCH("all.in.cs2.stl.oth.---",input_data!$A:$A,0)))*H29,0)+IFERROR((calculations!Q319/calculations!Q318)*((calculations!Q339+calculations!Q344)*$B$11+calculations!Q340*$B$12+calculations!Q341*$B$13+calculations!Q342*$B$14+calculations!Q343*$B$15*INDEX(input_data!$L:$L,MATCH("all.in.cs2.frt.otn.---",input_data!$A:$A,0)))*H29,0) -> 105.31264 | I35: =IFERROR((calculations!R21/calculations!R20)*((calculations!R41+calculations!R244)*$B$11+calculations!R42*$B$12+calculations!R43*$B$13+calculations!R44*$B$14+calculations!R45*$B$15*INDEX(input_data!$L:$L,MATCH("all.in.cs2.stl.drg.---",input_data!$A:$A,0)))*I29,0)+IFERROR((calculations!R49/calculations!R48)*((calculations!R69+calculations!R249)*$B$11+calculations!R70*$B$12+calculations!R71*$B$13+calculations!R72*$B$14+calculations!R73*$B$15*INDEX(input_data!$L:$L,MATCH("all.in.cs2.stl.scr.---",input_data!$A:$A,0)))*I29,0)+IFERROR((calculations!R77/calculations!R76)*((calculations!R97+calculations!R254)*$B$11+calculations!R98*$B$12+calculations!R99*$B$13+calculations!R100*$B$14+calculations!R101*$B$15*INDEX(input_data!$L:$L,MATCH("all.in.cs2.stl.bof.---",input_data!$A:$A,0)))*I29,0)+IFERROR((calculations!R105/calculations!R104)*((calculations!R125+calculations!R259)*$B$11+calculations!R126*$B$12+calculations!R127*$B$13+calculations!R128*$B$14+calculations!R129*$B$15*INDEX(input_data!$L:$L,MATCH("all.in.cs2.cmt.dry.---",input_data!$A:$A,0)))*I29,0)+IFERROR((calculations!R133/calculations!R132)*((calculations!R153+calculations!R264)*$B$11+calculations!R154*$B$12+calculations!R155*$B$13+calculations!R156*$B$14+calculations!R157*$B$15*INDEX(input_data!$L:$L,MATCH("all.in.cs2.frt.amc.---",input_data!$A:$A,0)))*I29,0)+IFERROR((calculations!R161/calculations!R160)*((calculations!R181+calculations!R269)*$B$11+calculations!R182*$B$12+calculations!R183*$B$13+calculations!R184*$B$14+calculations!R185*$B$15*INDEX(input_data!$L:$L,MATCH("all.in.cs2.frt.ure.---",input_data!$A:$A,0)))*I29,0)+IFERROR((calculations!R189/calculations!R188)*((calculations!R209+calculations!R274)*$B$11+calculations!R210*$B$12+calculations!R211*$B$13+calculations!R212*$B$14+calculations!R213*$B$15*INDEX(input_data!$L:$L,MATCH("all.in.cs2.frt.nit.---",input_data!$A:$A,0)))*I29,0)+IFERROR((calculations!R217/calculations!R216)*((calculations!R237+calculations!R279)*$B$11+calculations!R238*$B$12+calculations!R239*$B$13+calculations!R240*$B$14+calculations!R241*$B$15*INDEX(input_data!$L:$L,MATCH("all.in.cs2.alu.prp.---",input_data!$A:$A,0)))*I29,0)+IFERROR((calculations!R287/calculations!R286)*((calculations!R307+calculations!R312)*$B$11+calculations!R308*$B$12+calculations!R309*$B$13+calculations!R310*$B$14+calculations!R311*$B$15*INDEX(input_data!$L:$L,MATCH("all.in.cs2.stl.oth.---",input_data!$A:$A,0)))*I29,0)+IFERROR((calculations!R319/calculations!R318)*((calculations!R339+calculations!R344)*$B$11+calculations!R340*$B$12+calculations!R341*$B$13+calculations!R342*$B$14+calculations!R343*$B$15*INDEX(input_data!$L:$L,MATCH("all.in.cs2.frt.otn.---",input_data!$A:$A,0)))*I29,0) -> 133.6473 | J35: =IFERROR((calculations!S21/calculations!S20)*((calculations!S41+calculations!S244)*$B$11+calculations!S42*$B$12+calculations!S43*$B$13+calculations!S44*$B$14+calculations!S45*$B$15*INDEX(input_data!$L:$L,MATCH("all.in.cs2.stl.drg.---",input_data!$A:$A,0)))*J29,0)+IFERROR((calculations!S49/calculations!S48)*((calculations!S69+calculations!S249)*$B$11+calculations!S70*$B$12+calculations!S71*$B$13+calculations!S72*$B$14+calculations!S73*$B$15*INDEX(input_data!$L:$L,MATCH("all.in.cs2.stl.scr.---",input_data!$A:$A,0)))*J29,0)+IFERROR((calculations!S77/calculations!S76)*((calculations!S97+calculations!S254)*$B$11+calculations!S98*$B$12+calculations!S99*$B$13+calculations!S100*$B$14+calculations!S101*$B$15*INDEX(input_data!$L:$L,MATCH("all.in.cs2.stl.bof.---",input_data!$A:$A,0)))*J29,0)+IFERROR((calculations!S105/calculations!S104)*((calculations!S125+calculations!S259)*$B$11+calculations!S126*$B$12+calculations!S127*$B$13+calculations!S128*$B$14+calculations!S129*$B$15*INDEX(input_data!$L:$L,MATCH("all.in.cs2.cmt.dry.---",input_data!$A:$A,0)))*J29,0)+IFERROR((calculations!S133/calculations!S132)*((calculations!S153+calculations!S264)*$B$11+calculations!S154*$B$12+calculations!S155*$B$13+calculations!S156*$B$14+calculations!S157*$B$15*INDEX(input_data!$L:$L,MATCH("all.in.cs2.frt.amc.---",input_data!$A:$A,0)))*J29,0)+IFERROR((calculations!S161/calculations!S160)*((calculations!S181+calculations!S269)*$B$11+calculations!S182*$B$12+calculations!S183*$B$13+calculations!S184*$B$14+calculations!S185*$B$15*INDEX(input_data!$L:$L,MATCH("all.in.cs2.frt.ure.---",input_data!$A:$A,0)))*J29,0)+IFERROR((calculations!S189/calculations!S188)*((calculations!S209+calculations!S274)*$B$11+calculations!S210*$B$12+calculations!S211*$B$13+calculations!S212*$B$14+calculations!S213*$B$15*INDEX(input_data!$L:$L,MATCH("all.in.cs2.frt.nit.---",input_data!$A:$A,0)))*J29,0)+IFERROR((calculations!S217/calculations!S216)*((calculations!S237+calculations!S279)*$B$11+calculations!S238*$B$12+calculations!S239*$B$13+calculations!S240*$B$14+calculations!S241*$B$15*INDEX(input_data!$L:$L,MATCH("all.in.cs2.alu.prp.---",input_data!$A:$A,0)))*J29,0)+IFERROR((calculations!S287/calculations!S286)*((calculations!S307+calculations!S312)*$B$11+calculations!S308*$B$12+calculations!S309*$B$13+calculations!S310*$B$14+calculations!S311*$B$15*INDEX(input_data!$L:$L,MATCH("all.in.cs2.stl.oth.---",input_data!$A:$A,0)))*J29,0)+IFERROR((calculations!S319/calculations!S318)*((calculations!S339+calculations!S344)*$B$11+calculations!S340*$B$12+calculations!S341*$B$13+calculations!S342*$B$14+calculations!S343*$B$15*INDEX(input_data!$L:$L,MATCH("all.in.cs2.frt.otn.---",input_data!$A:$A,0)))*J29,0) -> 201.1194 | K35: =IFERROR((calculations!T21/calculations!T20)*((calculations!T41+calculations!T244)*$B$11+calculations!T42*$B$12+calculations!T43*$B$13+calculations!T44*$B$14+calculations!T45*$B$15*INDEX(input_data!$L:$L,MATCH("all.in.cs2.stl.drg.---",input_data!$A:$A,0)))*K29,0)+IFERROR((calculations!T49/calculations!T48)*((calculations!T69+calculations!T249)*$B$11+calculations!T70*$B$12+calculations!T71*$B$13+calculations!T72*$B$14+calculations!T73*$B$15*INDEX(input_data!$L:$L,MATCH("all.in.cs2.stl.scr.---",input_data!$A:$A,0)))*K29,0)+IFERROR((calculations!T77/calculations!T76)*((calculations!T97+calculations!T254)*$B$11+calculations!T98*$B$12+calculations!T99*$B$13+calculations!T100*$B$14+calculations!T101*$B$15*INDEX(input_data!$L:$L,MATCH("all.in.cs2.stl.bof.---",input_data!$A:$A,0)))*K29,0)+IFERROR((calculations!T105/calculations!T104)*((calculations!T125+calculations!T259)*$B$11+calculations!T126*$B$12+calculations!T127*$B$13+calculations!T128*$B$14+calculations!T129*$B$15*INDEX(input_data!$L:$L,MATCH("all.in.cs2.cmt.dry.---",input_data!$A:$A,0)))*K29,0)+IFERROR((calculations!T133/calculations!T132)*((calculations!T153+calculations!T264)*$B$11+calculations!T154*$B$12+calculations!T155*$B$13+calculations!T156*$B$14+calculations!T157*$B$15*INDEX(input_data!$L:$L,MATCH("all.in.cs2.frt.amc.---",input_data!$A:$A,0)))*K29,0)+IFERROR((calculations!T161/calculations!T160)*((calculations!T181+calculations!T269)*$B$11+calculations!T182*$B$12+calculations!T183*$B$13+calculations!T184*$B$14+calculations!T185*$B$15*INDEX(input_data!$L:$L,MATCH("all.in.cs2.frt.ure.---",input_data!$A:$A,0)))*K29,0)+IFERROR((calculations!T189/calculations!T188)*((calculations!T209+calculations!T274)*$B$11+calculations!T210*$B$12+calculations!T211*$B$13+calculations!T212*$B$14+calculations!T213*$B$15*INDEX(input_data!$L:$L,MATCH("all.in.cs2.frt.nit.---",input_data!$A:$A,0)))*K29,0)+IFERROR((calculations!T217/calculations!T216)*((calculations!T237+calculations!T279)*$B$11+calculations!T238*$B$12+calculations!T239*$B$13+calculations!T240*$B$14+calculations!T241*$B$15*INDEX(input_data!$L:$L,MATCH("all.in.cs2.alu.prp.---",input_data!$A:$A,0)))*K29,0)+IFERROR((calculations!T287/calculations!T286)*((calculations!T307+calculations!T312)*$B$11+calculations!T308*$B$12+calculations!T309*$B$13+calculations!T310*$B$14+calculations!T311*$B$15*INDEX(input_data!$L:$L,MATCH("all.in.cs2.stl.oth.---",input_data!$A:$A,0)))*K29,0)+IFERROR((calculations!T319/calculations!T318)*((calculations!T339+calculations!T344)*$B$11+calculations!T340*$B$12+calculations!T341*$B$13+calculations!T342*$B$14+calculations!T343*$B$15*INDEX(input_data!$L:$L,MATCH("all.in.cs2.frt.otn.---",input_data!$A:$A,0)))*K29,0) -> 252.9825 | ... O35: =IFERROR((calculations!X21/calculations!X20)*((calculations!X41+calculations!X244)*$B$11+calculations!X42*$B$12+calculations!X43*$B$13+calculations!X44*$B$14+calculations!X45*$B$15*INDEX(input_data!$L:$L,MATCH("all.in.cs2.stl.drg.---",input_data!$A:$A,0)))*O29,0)+IFERROR((calculations!X49/calculations!X48)*((calculations!X69+calculations!X249)*$B$11+calculations!X70*$B$12+calculations!X71*$B$13+calculations!X72*$B$14+calculations!X73*$B$15*INDEX(input_data!$L:$L,MATCH("all.in.cs2.stl.scr.---",input_data!$A:$A,0)))*O29,0)+IFERROR((calculations!X77/calculations!X76)*((calculations!X97+calculations!X254)*$B$11+calculations!X98*$B$12+calculations!X99*$B$13+calculations!X100*$B$14+calculations!X101*$B$15*INDEX(input_data!$L:$L,MATCH("all.in.cs2.stl.bof.---",input_data!$A:$A,0)))*O29,0)+IFERROR((calculations!X105/calculations!X104)*((calculations!X125+calculations!X259)*$B$11+calculations!X126*$B$12+calculations!X127*$B$13+calculations!X128*$B$14+calculations!X129*$B$15*INDEX(input_data!$L:$L,MATCH("all.in.cs2.cmt.dry.---",input_data!$A:$A,0)))*O29,0)+IFERROR((calculations!X133/calculations!X132)*((calculations!X153+calculations!X264)*$B$11+calculations!X154*$B$12+calculations!X155*$B$13+calculations!X156*$B$14+calculations!X157*$B$15*INDEX(input_data!$L:$L,MATCH("all.in.cs2.frt.amc.---",input_data!$A:$A,0)))*O29,0)+IFERROR((calculations!X161/calculations!X160)*((calculations!X181+calculations!X269)*$B$11+calculations!X182*$B$12+calculations!X183*$B$13+calculations!X184*$B$14+calculations!X185*$B$15*INDEX(input_data!$L:$L,MATCH("all.in.cs2.frt.ure.---",input_data!$A:$A,0)))*O29,0)+IFERROR((calculations!X189/calculations!X188)*((calculations!X209+calculations!X274)*$B$11+calculations!X210*$B$12+calculations!X211*$B$13+calculations!X212*$B$14+calculations!X213*$B$15*INDEX(input_data!$L:$L,MATCH("all.in.cs2.frt.nit.---",input_data!$A:$A,0)))*O29,0)+IFERROR((calculations!X217/calculations!X216)*((calculations!X237+calculations!X279)*$B$11+calculations!X238*$B$12+calculations!X239*$B$13+calculations!X240*$B$14+calculations!X241*$B$15*INDEX(input_data!$L:$L,MATCH("all.in.cs2.alu.prp.---",input_data!$A:$A,0)))*O29,0)+IFERROR((calculations!X287/calculations!X286)*((calculations!X307+calculations!X312)*$B$11+calculations!X308*$B$12+calculations!X309*$B$13+calculations!X310*$B$14+calculations!X311*$B$15*INDEX(input_data!$L:$L,MATCH("all.in.cs2.stl.oth.---",input_data!$A:$A,0)))*O29,0)+IFERROR((calculations!X319/calculations!X318)*((calculations!X339+calculations!X344)*$B$11+calculations!X340*$B$12+calculations!X341*$B$13+calculations!X342*$B$14+calculations!X343*$B$15*INDEX(input_data!$L:$L,MATCH("all.in.cs2.frt.otn.---",input_data!$A:$A,0)))*O29,0) -> 497.03882
A36: ● EU CBAM retained = MAX(gross − creditable, 0) | B36: USD m | D36: =MAX(D33-D35,0) -> 0 | E36: =MAX(E33-E35,0) -> 0 | F36: =MAX(F33-F35,0) -> 0 | G36: =MAX(G33-G35,0) -> 0 | H36: =MAX(H33-H35,0) -> 0 | I36: =MAX(I33-I35,0) -> 0 | J36: =MAX(J33-J35,0) -> 2.8421709e-14 | K36: =MAX(K33-K35,0) -> 2.8421709e-14 | ... O36: =MAX(O33-O35,0) -> 5.6843419e-14
A37: ● Country revenue on non-EU exports | B37: USD m | D37: =IFERROR((calculations!M22/calculations!M20)*((calculations!M41+calculations!M244)*$B$11+calculations!M42*$B$12+calculations!M43*$B$13+calculations!M44*$B$14+calculations!M45*$B$15)*D29,0)+IFERROR((calculations!M50/calculations!M48)*((calculations!M69+calculations!M249)*$B$11+calculations!M70*$B$12+calculations!M71*$B$13+calculations!M72*$B$14+calculations!M73*$B$15)*D29,0)+IFERROR((calculations!M78/calculations!M76)*((calculations!M97+calculations!M254)*$B$11+calculations!M98*$B$12+calculations!M99*$B$13+calculations!M100*$B$14+calculations!M101*$B$15)*D29,0)+IFERROR((calculations!M106/calculations!M104)*((calculations!M125+calculations!M259)*$B$11+calculations!M126*$B$12+calculations!M127*$B$13+calculations!M128*$B$14+calculations!M129*$B$15)*D29,0)+IFERROR((calculations!M134/calculations!M132)*((calculations!M153+calculations!M264)*$B$11+calculations!M154*$B$12+calculations!M155*$B$13+calculations!M156*$B$14+calculations!M157*$B$15)*D29,0)+IFERROR((calculations!M162/calculations!M160)*((calculations!M181+calculations!M269)*$B$11+calculations!M182*$B$12+calculations!M183*$B$13+calculations!M184*$B$14+calculations!M185*$B$15)*D29,0)+IFERROR((calculations!M190/calculations!M188)*((calculations!M209+calculations!M274)*$B$11+calculations!M210*$B$12+calculations!M211*$B$13+calculations!M212*$B$14+calculations!M213*$B$15)*D29,0)+IFERROR((calculations!M218/calculations!M216)*((calculations!M237+calculations!M279)*$B$11+calculations!M238*$B$12+calculations!M239*$B$13+calculations!M240*$B$14+calculations!M241*$B$15)*D29,0)+IFERROR((calculations!M288/calculations!M286)*((calculations!M307+calculations!M312)*$B$11+calculations!M308*$B$12+calculations!M309*$B$13+calculations!M310*$B$14+calculations!M311*$B$15)*D29,0)+IFERROR((calculations!M320/calculations!M318)*((calculations!M339+calculations!M344)*$B$11+calculations!M340*$B$12+calculations!M341*$B$13+calculations!M342*$B$14+calculations!M343*$B$15)*D29,0) -> 0 | E37: =IFERROR((calculations!N22/calculations!N20)*((calculations!N41+calculations!N244)*$B$11+calculations!N42*$B$12+calculations!N43*$B$13+calculations!N44*$B$14+calculations!N45*$B$15)*E29,0)+IFERROR((calculations!N50/calculations!N48)*((calculations!N69+calculations!N249)*$B$11+calculations!N70*$B$12+calculations!N71*$B$13+calculations!N72*$B$14+calculations!N73*$B$15)*E29,0)+IFERROR((calculations!N78/calculations!N76)*((calculations!N97+calculations!N254)*$B$11+calculations!N98*$B$12+calculations!N99*$B$13+calculations!N100*$B$14+calculations!N101*$B$15)*E29,0)+IFERROR((calculations!N106/calculations!N104)*((calculations!N125+calculations!N259)*$B$11+calculations!N126*$B$12+calculations!N127*$B$13+calculations!N128*$B$14+calculations!N129*$B$15)*E29,0)+IFERROR((calculations!N134/calculations!N132)*((calculations!N153+calculations!N264)*$B$11+calculations!N154*$B$12+calculations!N155*$B$13+calculations!N156*$B$14+calculations!N157*$B$15)*E29,0)+IFERROR((calculations!N162/calculations!N160)*((calculations!N181+calculations!N269)*$B$11+calculations!N182*$B$12+calculations!N183*$B$13+calculations!N184*$B$14+calculations!N185*$B$15)*E29,0)+IFERROR((calculations!N190/calculations!N188)*((calculations!N209+calculations!N274)*$B$11+calculations!N210*$B$12+calculations!N211*$B$13+calculations!N212*$B$14+calculations!N213*$B$15)*E29,0)+IFERROR((calculations!N218/calculations!N216)*((calculations!N237+calculations!N279)*$B$11+calculations!N238*$B$12+calculations!N239*$B$13+calculations!N240*$B$14+calculations!N241*$B$15)*E29,0)+IFERROR((calculations!N288/calculations!N286)*((calculations!N307+calculations!N312)*$B$11+calculations!N308*$B$12+calculations!N309*$B$13+calculations!N310*$B$14+calculations!N311*$B$15)*E29,0)+IFERROR((calculations!N320/calculations!N318)*((calculations!N339+calculations!N344)*$B$11+calculations!N340*$B$12+calculations!N341*$B$13+calculations!N342*$B$14+calculations!N343*$B$15)*E29,0) -> 0 | F37: =IFERROR((calculations!O22/calculations!O20)*((calculations!O41+calculations!O244)*$B$11+calculations!O42*$B$12+calculations!O43*$B$13+calculations!O44*$B$14+calculations!O45*$B$15)*F29,0)+IFERROR((calculations!O50/calculations!O48)*((calculations!O69+calculations!O249)*$B$11+calculations!O70*$B$12+calculations!O71*$B$13+calculations!O72*$B$14+calculations!O73*$B$15)*F29,0)+IFERROR((calculations!O78/calculations!O76)*((calculations!O97+calculations!O254)*$B$11+calculations!O98*$B$12+calculations!O99*$B$13+calculations!O100*$B$14+calculations!O101*$B$15)*F29,0)+IFERROR((calculations!O106/calculations!O104)*((calculations!O125+calculations!O259)*$B$11+calculations!O126*$B$12+calculations!O127*$B$13+calculations!O128*$B$14+calculations!O129*$B$15)*F29,0)+IFERROR((calculations!O134/calculations!O132)*((calculations!O153+calculations!O264)*$B$11+calculations!O154*$B$12+calculations!O155*$B$13+calculations!O156*$B$14+calculations!O157*$B$15)*F29,0)+IFERROR((calculations!O162/calculations!O160)*((calculations!O181+calculations!O269)*$B$11+calculations!O182*$B$12+calculations!O183*$B$13+calculations!O184*$B$14+calculations!O185*$B$15)*F29,0)+IFERROR((calculations!O190/calculations!O188)*((calculations!O209+calculations!O274)*$B$11+calculations!O210*$B$12+calculations!O211*$B$13+calculations!O212*$B$14+calculations!O213*$B$15)*F29,0)+IFERROR((calculations!O218/calculations!O216)*((calculations!O237+calculations!O279)*$B$11+calculations!O238*$B$12+calculations!O239*$B$13+calculations!O240*$B$14+calculations!O241*$B$15)*F29,0)+IFERROR((calculations!O288/calculations!O286)*((calculations!O307+calculations!O312)*$B$11+calculations!O308*$B$12+calculations!O309*$B$13+calculations!O310*$B$14+calculations!O311*$B$15)*F29,0)+IFERROR((calculations!O320/calculations!O318)*((calculations!O339+calculations!O344)*$B$11+calculations!O340*$B$12+calculations!O341*$B$13+calculations!O342*$B$14+calculations!O343*$B$15)*F29,0) -> 168.89424 | G37: =IFERROR((calculations!P22/calculations!P20)*((calculations!P41+calculations!P244)*$B$11+calculations!P42*$B$12+calculations!P43*$B$13+calculations!P44*$B$14+calculations!P45*$B$15)*G29,0)+IFERROR((calculations!P50/calculations!P48)*((calculations!P69+calculations!P249)*$B$11+calculations!P70*$B$12+calculations!P71*$B$13+calculations!P72*$B$14+calculations!P73*$B$15)*G29,0)+IFERROR((calculations!P78/calculations!P76)*((calculations!P97+calculations!P254)*$B$11+calculations!P98*$B$12+calculations!P99*$B$13+calculations!P100*$B$14+calculations!P101*$B$15)*G29,0)+IFERROR((calculations!P106/calculations!P104)*((calculations!P125+calculations!P259)*$B$11+calculations!P126*$B$12+calculations!P127*$B$13+calculations!P128*$B$14+calculations!P129*$B$15)*G29,0)+IFERROR((calculations!P134/calculations!P132)*((calculations!P153+calculations!P264)*$B$11+calculations!P154*$B$12+calculations!P155*$B$13+calculations!P156*$B$14+calculations!P157*$B$15)*G29,0)+IFERROR((calculations!P162/calculations!P160)*((calculations!P181+calculations!P269)*$B$11+calculations!P182*$B$12+calculations!P183*$B$13+calculations!P184*$B$14+calculations!P185*$B$15)*G29,0)+IFERROR((calculations!P190/calculations!P188)*((calculations!P209+calculations!P274)*$B$11+calculations!P210*$B$12+calculations!P211*$B$13+calculations!P212*$B$14+calculations!P213*$B$15)*G29,0)+IFERROR((calculations!P218/calculations!P216)*((calculations!P237+calculations!P279)*$B$11+calculations!P238*$B$12+calculations!P239*$B$13+calculations!P240*$B$14+calculations!P241*$B$15)*G29,0)+IFERROR((calculations!P288/calculations!P286)*((calculations!P307+calculations!P312)*$B$11+calculations!P308*$B$12+calculations!P309*$B$13+calculations!P310*$B$14+calculations!P311*$B$15)*G29,0)+IFERROR((calculations!P320/calculations!P318)*((calculations!P339+calculations!P344)*$B$11+calculations!P340*$B$12+calculations!P341*$B$13+calculations!P342*$B$14+calculations!P343*$B$15)*G29,0) -> 193.79979 | H37: =IFERROR((calculations!Q22/calculations!Q20)*((calculations!Q41+calculations!Q244)*$B$11+calculations!Q42*$B$12+calculations!Q43*$B$13+calculations!Q44*$B$14+calculations!Q45*$B$15)*H29,0)+IFERROR((calculations!Q50/calculations!Q48)*((calculations!Q69+calculations!Q249)*$B$11+calculations!Q70*$B$12+calculations!Q71*$B$13+calculations!Q72*$B$14+calculations!Q73*$B$15)*H29,0)+IFERROR((calculations!Q78/calculations!Q76)*((calculations!Q97+calculations!Q254)*$B$11+calculations!Q98*$B$12+calculations!Q99*$B$13+calculations!Q100*$B$14+calculations!Q101*$B$15)*H29,0)+IFERROR((calculations!Q106/calculations!Q104)*((calculations!Q125+calculations!Q259)*$B$11+calculations!Q126*$B$12+calculations!Q127*$B$13+calculations!Q128*$B$14+calculations!Q129*$B$15)*H29,0)+IFERROR((calculations!Q134/calculations!Q132)*((calculations!Q153+calculations!Q264)*$B$11+calculations!Q154*$B$12+calculations!Q155*$B$13+calculations!Q156*$B$14+calculations!Q157*$B$15)*H29,0)+IFERROR((calculations!Q162/calculations!Q160)*((calculations!Q181+calculations!Q269)*$B$11+calculations!Q182*$B$12+calculations!Q183*$B$13+calculations!Q184*$B$14+calculations!Q185*$B$15)*H29,0)+IFERROR((calculations!Q190/calculations!Q188)*((calculations!Q209+calculations!Q274)*$B$11+calculations!Q210*$B$12+calculations!Q211*$B$13+calculations!Q212*$B$14+calculations!Q213*$B$15)*H29,0)+IFERROR((calculations!Q218/calculations!Q216)*((calculations!Q237+calculations!Q279)*$B$11+calculations!Q238*$B$12+calculations!Q239*$B$13+calculations!Q240*$B$14+calculations!Q241*$B$15)*H29,0)+IFERROR((calculations!Q288/calculations!Q286)*((calculations!Q307+calculations!Q312)*$B$11+calculations!Q308*$B$12+calculations!Q309*$B$13+calculations!Q310*$B$14+calculations!Q311*$B$15)*H29,0)+IFERROR((calculations!Q320/calculations!Q318)*((calculations!Q339+calculations!Q344)*$B$11+calculations!Q340*$B$12+calculations!Q341*$B$13+calculations!Q342*$B$14+calculations!Q343*$B$15)*H29,0) -> 231.46268 | I37: =IFERROR((calculations!R22/calculations!R20)*((calculations!R41+calculations!R244)*$B$11+calculations!R42*$B$12+calculations!R43*$B$13+calculations!R44*$B$14+calculations!R45*$B$15)*I29,0)+IFERROR((calculations!R50/calculations!R48)*((calculations!R69+calculations!R249)*$B$11+calculations!R70*$B$12+calculations!R71*$B$13+calculations!R72*$B$14+calculations!R73*$B$15)*I29,0)+IFERROR((calculations!R78/calculations!R76)*((calculations!R97+calculations!R254)*$B$11+calculations!R98*$B$12+calculations!R99*$B$13+calculations!R100*$B$14+calculations!R101*$B$15)*I29,0)+IFERROR((calculations!R106/calculations!R104)*((calculations!R125+calculations!R259)*$B$11+calculations!R126*$B$12+calculations!R127*$B$13+calculations!R128*$B$14+calculations!R129*$B$15)*I29,0)+IFERROR((calculations!R134/calculations!R132)*((calculations!R153+calculations!R264)*$B$11+calculations!R154*$B$12+calculations!R155*$B$13+calculations!R156*$B$14+calculations!R157*$B$15)*I29,0)+IFERROR((calculations!R162/calculations!R160)*((calculations!R181+calculations!R269)*$B$11+calculations!R182*$B$12+calculations!R183*$B$13+calculations!R184*$B$14+calculations!R185*$B$15)*I29,0)+IFERROR((calculations!R190/calculations!R188)*((calculations!R209+calculations!R274)*$B$11+calculations!R210*$B$12+calculations!R211*$B$13+calculations!R212*$B$14+calculations!R213*$B$15)*I29,0)+IFERROR((calculations!R218/calculations!R216)*((calculations!R237+calculations!R279)*$B$11+calculations!R238*$B$12+calculations!R239*$B$13+calculations!R240*$B$14+calculations!R241*$B$15)*I29,0)+IFERROR((calculations!R288/calculations!R286)*((calculations!R307+calculations!R312)*$B$11+calculations!R308*$B$12+calculations!R309*$B$13+calculations!R310*$B$14+calculations!R311*$B$15)*I29,0)+IFERROR((calculations!R320/calculations!R318)*((calculations!R339+calculations!R344)*$B$11+calculations!R340*$B$12+calculations!R341*$B$13+calculations!R342*$B$14+calculations!R343*$B$15)*I29,0) -> 293.3964 | J37: =IFERROR((calculations!S22/calculations!S20)*((calculations!S41+calculations!S244)*$B$11+calculations!S42*$B$12+calculations!S43*$B$13+calculations!S44*$B$14+calculations!S45*$B$15)*J29,0)+IFERROR((calculations!S50/calculations!S48)*((calculations!S69+calculations!S249)*$B$11+calculations!S70*$B$12+calculations!S71*$B$13+calculations!S72*$B$14+calculations!S73*$B$15)*J29,0)+IFERROR((calculations!S78/calculations!S76)*((calculations!S97+calculations!S254)*$B$11+calculations!S98*$B$12+calculations!S99*$B$13+calculations!S100*$B$14+calculations!S101*$B$15)*J29,0)+IFERROR((calculations!S106/calculations!S104)*((calculations!S125+calculations!S259)*$B$11+calculations!S126*$B$12+calculations!S127*$B$13+calculations!S128*$B$14+calculations!S129*$B$15)*J29,0)+IFERROR((calculations!S134/calculations!S132)*((calculations!S153+calculations!S264)*$B$11+calculations!S154*$B$12+calculations!S155*$B$13+calculations!S156*$B$14+calculations!S157*$B$15)*J29,0)+IFERROR((calculations!S162/calculations!S160)*((calculations!S181+calculations!S269)*$B$11+calculations!S182*$B$12+calculations!S183*$B$13+calculations!S184*$B$14+calculations!S185*$B$15)*J29,0)+IFERROR((calculations!S190/calculations!S188)*((calculations!S209+calculations!S274)*$B$11+calculations!S210*$B$12+calculations!S211*$B$13+calculations!S212*$B$14+calculations!S213*$B$15)*J29,0)+IFERROR((calculations!S218/calculations!S216)*((calculations!S237+calculations!S279)*$B$11+calculations!S238*$B$12+calculations!S239*$B$13+calculations!S240*$B$14+calculations!S241*$B$15)*J29,0)+IFERROR((calculations!S288/calculations!S286)*((calculations!S307+calculations!S312)*$B$11+calculations!S308*$B$12+calculations!S309*$B$13+calculations!S310*$B$14+calculations!S311*$B$15)*J29,0)+IFERROR((calculations!S320/calculations!S318)*((calculations!S339+calculations!S344)*$B$11+calculations!S340*$B$12+calculations!S341*$B$13+calculations!S342*$B$14+calculations!S343*$B$15)*J29,0) -> 440.95854 | K37: =IFERROR((calculations!T22/calculations!T20)*((calculations!T41+calculations!T244)*$B$11+calculations!T42*$B$12+calculations!T43*$B$13+calculations!T44*$B$14+calculations!T45*$B$15)*K29,0)+IFERROR((calculations!T50/calculations!T48)*((calculations!T69+calculations!T249)*$B$11+calculations!T70*$B$12+calculations!T71*$B$13+calculations!T72*$B$14+calculations!T73*$B$15)*K29,0)+IFERROR((calculations!T78/calculations!T76)*((calculations!T97+calculations!T254)*$B$11+calculations!T98*$B$12+calculations!T99*$B$13+calculations!T100*$B$14+calculations!T101*$B$15)*K29,0)+IFERROR((calculations!T106/calculations!T104)*((calculations!T125+calculations!T259)*$B$11+calculations!T126*$B$12+calculations!T127*$B$13+calculations!T128*$B$14+calculations!T129*$B$15)*K29,0)+IFERROR((calculations!T134/calculations!T132)*((calculations!T153+calculations!T264)*$B$11+calculations!T154*$B$12+calculations!T155*$B$13+calculations!T156*$B$14+calculations!T157*$B$15)*K29,0)+IFERROR((calculations!T162/calculations!T160)*((calculations!T181+calculations!T269)*$B$11+calculations!T182*$B$12+calculations!T183*$B$13+calculations!T184*$B$14+calculations!T185*$B$15)*K29,0)+IFERROR((calculations!T190/calculations!T188)*((calculations!T209+calculations!T274)*$B$11+calculations!T210*$B$12+calculations!T211*$B$13+calculations!T212*$B$14+calculations!T213*$B$15)*K29,0)+IFERROR((calculations!T218/calculations!T216)*((calculations!T237+calculations!T279)*$B$11+calculations!T238*$B$12+calculations!T239*$B$13+calculations!T240*$B$14+calculations!T241*$B$15)*K29,0)+IFERROR((calculations!T288/calculations!T286)*((calculations!T307+calculations!T312)*$B$11+calculations!T308*$B$12+calculations!T309*$B$13+calculations!T310*$B$14+calculations!T311*$B$15)*K29,0)+IFERROR((calculations!T320/calculations!T318)*((calculations!T339+calculations!T344)*$B$11+calculations!T340*$B$12+calculations!T341*$B$13+calculations!T342*$B$14+calculations!T343*$B$15)*K29,0) -> 553.90929 | ... O37: =IFERROR((calculations!X22/calculations!X20)*((calculations!X41+calculations!X244)*$B$11+calculations!X42*$B$12+calculations!X43*$B$13+calculations!X44*$B$14+calculations!X45*$B$15)*O29,0)+IFERROR((calculations!X50/calculations!X48)*((calculations!X69+calculations!X249)*$B$11+calculations!X70*$B$12+calculations!X71*$B$13+calculations!X72*$B$14+calculations!X73*$B$15)*O29,0)+IFERROR((calculations!X78/calculations!X76)*((calculations!X97+calculations!X254)*$B$11+calculations!X98*$B$12+calculations!X99*$B$13+calculations!X100*$B$14+calculations!X101*$B$15)*O29,0)+IFERROR((calculations!X106/calculations!X104)*((calculations!X125+calculations!X259)*$B$11+calculations!X126*$B$12+calculations!X127*$B$13+calculations!X128*$B$14+calculations!X129*$B$15)*O29,0)+IFERROR((calculations!X134/calculations!X132)*((calculations!X153+calculations!X264)*$B$11+calculations!X154*$B$12+calculations!X155*$B$13+calculations!X156*$B$14+calculations!X157*$B$15)*O29,0)+IFERROR((calculations!X162/calculations!X160)*((calculations!X181+calculations!X269)*$B$11+calculations!X182*$B$12+calculations!X183*$B$13+calculations!X184*$B$14+calculations!X185*$B$15)*O29,0)+IFERROR((calculations!X190/calculations!X188)*((calculations!X209+calculations!X274)*$B$11+calculations!X210*$B$12+calculations!X211*$B$13+calculations!X212*$B$14+calculations!X213*$B$15)*O29,0)+IFERROR((calculations!X218/calculations!X216)*((calculations!X237+calculations!X279)*$B$11+calculations!X238*$B$12+calculations!X239*$B$13+calculations!X240*$B$14+calculations!X241*$B$15)*O29,0)+IFERROR((calculations!X288/calculations!X286)*((calculations!X307+calculations!X312)*$B$11+calculations!X308*$B$12+calculations!X309*$B$13+calculations!X310*$B$14+calculations!X311*$B$15)*O29,0)+IFERROR((calculations!X320/calculations!X318)*((calculations!X339+calculations!X344)*$B$11+calculations!X340*$B$12+calculations!X341*$B$13+calculations!X342*$B$14+calculations!X343*$B$15)*O29,0) -> 1081.2116
A38: ● Country revenue on domestic consumption (zero if 2c=1) | B38: USD m | D38: =IFERROR((1-$B$22)*(calculations!M23/calculations!M20)*((calculations!M41+calculations!M244)*$B$11+calculations!M42*$B$12+calculations!M43*$B$13+calculations!M44*$B$14+calculations!M45*$B$15)*D29,0)+IFERROR((1-$B$22)*(calculations!M51/calculations!M48)*((calculations!M69+calculations!M249)*$B$11+calculations!M70*$B$12+calculations!M71*$B$13+calculations!M72*$B$14+calculations!M73*$B$15)*D29,0)+IFERROR((1-$B$22)*(calculations!M79/calculations!M76)*((calculations!M97+calculations!M254)*$B$11+calculations!M98*$B$12+calculations!M99*$B$13+calculations!M100*$B$14+calculations!M101*$B$15)*D29,0)+IFERROR((1-$B$22)*(calculations!M107/calculations!M104)*((calculations!M125+calculations!M259)*$B$11+calculations!M126*$B$12+calculations!M127*$B$13+calculations!M128*$B$14+calculations!M129*$B$15)*D29,0)+IFERROR((1-$B$22)*(calculations!M135/calculations!M132)*((calculations!M153+calculations!M264)*$B$11+calculations!M154*$B$12+calculations!M155*$B$13+calculations!M156*$B$14+calculations!M157*$B$15)*D29,0)+IFERROR((1-$B$22)*(calculations!M163/calculations!M160)*((calculations!M181+calculations!M269)*$B$11+calculations!M182*$B$12+calculations!M183*$B$13+calculations!M184*$B$14+calculations!M185*$B$15)*D29,0)+IFERROR((1-$B$22)*(calculations!M191/calculations!M188)*((calculations!M209+calculations!M274)*$B$11+calculations!M210*$B$12+calculations!M211*$B$13+calculations!M212*$B$14+calculations!M213*$B$15)*D29,0)+IFERROR((1-$B$22)*(calculations!M219/calculations!M216)*((calculations!M237+calculations!M279)*$B$11+calculations!M238*$B$12+calculations!M239*$B$13+calculations!M240*$B$14+calculations!M241*$B$15)*D29,0)+IFERROR((1-$B$22)*(calculations!M289/calculations!M286)*((calculations!M307+calculations!M312)*$B$11+calculations!M308*$B$12+calculations!M309*$B$13+calculations!M310*$B$14+calculations!M311*$B$15)*D29,0)+IFERROR((1-$B$22)*(calculations!M321/calculations!M318)*((calculations!M339+calculations!M344)*$B$11+calculations!M340*$B$12+calculations!M341*$B$13+calculations!M342*$B$14+calculations!M343*$B$15)*D29,0) -> 0 | E38: =IFERROR((1-$B$22)*(calculations!N23/calculations!N20)*((calculations!N41+calculations!N244)*$B$11+calculations!N42*$B$12+calculations!N43*$B$13+calculations!N44*$B$14+calculations!N45*$B$15)*E29,0)+IFERROR((1-$B$22)*(calculations!N51/calculations!N48)*((calculations!N69+calculations!N249)*$B$11+calculations!N70*$B$12+calculations!N71*$B$13+calculations!N72*$B$14+calculations!N73*$B$15)*E29,0)+IFERROR((1-$B$22)*(calculations!N79/calculations!N76)*((calculations!N97+calculations!N254)*$B$11+calculations!N98*$B$12+calculations!N99*$B$13+calculations!N100*$B$14+calculations!N101*$B$15)*E29,0)+IFERROR((1-$B$22)*(calculations!N107/calculations!N104)*((calculations!N125+calculations!N259)*$B$11+calculations!N126*$B$12+calculations!N127*$B$13+calculations!N128*$B$14+calculations!N129*$B$15)*E29,0)+IFERROR((1-$B$22)*(calculations!N135/calculations!N132)*((calculations!N153+calculations!N264)*$B$11+calculations!N154*$B$12+calculations!N155*$B$13+calculations!N156*$B$14+calculations!N157*$B$15)*E29,0)+IFERROR((1-$B$22)*(calculations!N163/calculations!N160)*((calculations!N181+calculations!N269)*$B$11+calculations!N182*$B$12+calculations!N183*$B$13+calculations!N184*$B$14+calculations!N185*$B$15)*E29,0)+IFERROR((1-$B$22)*(calculations!N191/calculations!N188)*((calculations!N209+calculations!N274)*$B$11+calculations!N210*$B$12+calculations!N211*$B$13+calculations!N212*$B$14+calculations!N213*$B$15)*E29,0)+IFERROR((1-$B$22)*(calculations!N219/calculations!N216)*((calculations!N237+calculations!N279)*$B$11+calculations!N238*$B$12+calculations!N239*$B$13+calculations!N240*$B$14+calculations!N241*$B$15)*E29,0)+IFERROR((1-$B$22)*(calculations!N289/calculations!N286)*((calculations!N307+calculations!N312)*$B$11+calculations!N308*$B$12+calculations!N309*$B$13+calculations!N310*$B$14+calculations!N311*$B$15)*E29,0)+IFERROR((1-$B$22)*(calculations!N321/calculations!N318)*((calculations!N339+calculations!N344)*$B$11+calculations!N340*$B$12+calculations!N341*$B$13+calculations!N342*$B$14+calculations!N343*$B$15)*E29,0) -> 0 | F38: =IFERROR((1-$B$22)*(calculations!O23/calculations!O20)*((calculations!O41+calculations!O244)*$B$11+calculations!O42*$B$12+calculations!O43*$B$13+calculations!O44*$B$14+calculations!O45*$B$15)*F29,0)+IFERROR((1-$B$22)*(calculations!O51/calculations!O48)*((calculations!O69+calculations!O249)*$B$11+calculations!O70*$B$12+calculations!O71*$B$13+calculations!O72*$B$14+calculations!O73*$B$15)*F29,0)+IFERROR((1-$B$22)*(calculations!O79/calculations!O76)*((calculations!O97+calculations!O254)*$B$11+calculations!O98*$B$12+calculations!O99*$B$13+calculations!O100*$B$14+calculations!O101*$B$15)*F29,0)+IFERROR((1-$B$22)*(calculations!O107/calculations!O104)*((calculations!O125+calculations!O259)*$B$11+calculations!O126*$B$12+calculations!O127*$B$13+calculations!O128*$B$14+calculations!O129*$B$15)*F29,0)+IFERROR((1-$B$22)*(calculations!O135/calculations!O132)*((calculations!O153+calculations!O264)*$B$11+calculations!O154*$B$12+calculations!O155*$B$13+calculations!O156*$B$14+calculations!O157*$B$15)*F29,0)+IFERROR((1-$B$22)*(calculations!O163/calculations!O160)*((calculations!O181+calculations!O269)*$B$11+calculations!O182*$B$12+calculations!O183*$B$13+calculations!O184*$B$14+calculations!O185*$B$15)*F29,0)+IFERROR((1-$B$22)*(calculations!O191/calculations!O188)*((calculations!O209+calculations!O274)*$B$11+calculations!O210*$B$12+calculations!O211*$B$13+calculations!O212*$B$14+calculations!O213*$B$15)*F29,0)+IFERROR((1-$B$22)*(calculations!O219/calculations!O216)*((calculations!O237+calculations!O279)*$B$11+calculations!O238*$B$12+calculations!O239*$B$13+calculations!O240*$B$14+calculations!O241*$B$15)*F29,0)+IFERROR((1-$B$22)*(calculations!O289/calculations!O286)*((calculations!O307+calculations!O312)*$B$11+calculations!O308*$B$12+calculations!O309*$B$13+calculations!O310*$B$14+calculations!O311*$B$15)*F29,0)+IFERROR((1-$B$22)*(calculations!O321/calculations!O318)*((calculations!O339+calculations!O344)*$B$11+calculations!O340*$B$12+calculations!O341*$B$13+calculations!O342*$B$14+calculations!O343*$B$15)*F29,0) -> 1974.7121 | G38: =IFERROR((1-$B$22)*(calculations!P23/calculations!P20)*((calculations!P41+calculations!P244)*$B$11+calculations!P42*$B$12+calculations!P43*$B$13+calculations!P44*$B$14+calculations!P45*$B$15)*G29,0)+IFERROR((1-$B$22)*(calculations!P51/calculations!P48)*((calculations!P69+calculations!P249)*$B$11+calculations!P70*$B$12+calculations!P71*$B$13+calculations!P72*$B$14+calculations!P73*$B$15)*G29,0)+IFERROR((1-$B$22)*(calculations!P79/calculations!P76)*((calculations!P97+calculations!P254)*$B$11+calculations!P98*$B$12+calculations!P99*$B$13+calculations!P100*$B$14+calculations!P101*$B$15)*G29,0)+IFERROR((1-$B$22)*(calculations!P107/calculations!P104)*((calculations!P125+calculations!P259)*$B$11+calculations!P126*$B$12+calculations!P127*$B$13+calculations!P128*$B$14+calculations!P129*$B$15)*G29,0)+IFERROR((1-$B$22)*(calculations!P135/calculations!P132)*((calculations!P153+calculations!P264)*$B$11+calculations!P154*$B$12+calculations!P155*$B$13+calculations!P156*$B$14+calculations!P157*$B$15)*G29,0)+IFERROR((1-$B$22)*(calculations!P163/calculations!P160)*((calculations!P181+calculations!P269)*$B$11+calculations!P182*$B$12+calculations!P183*$B$13+calculations!P184*$B$14+calculations!P185*$B$15)*G29,0)+IFERROR((1-$B$22)*(calculations!P191/calculations!P188)*((calculations!P209+calculations!P274)*$B$11+calculations!P210*$B$12+calculations!P211*$B$13+calculations!P212*$B$14+calculations!P213*$B$15)*G29,0)+IFERROR((1-$B$22)*(calculations!P219/calculations!P216)*((calculations!P237+calculations!P279)*$B$11+calculations!P238*$B$12+calculations!P239*$B$13+calculations!P240*$B$14+calculations!P241*$B$15)*G29,0)+IFERROR((1-$B$22)*(calculations!P289/calculations!P286)*((calculations!P307+calculations!P312)*$B$11+calculations!P308*$B$12+calculations!P309*$B$13+calculations!P310*$B$14+calculations!P311*$B$15)*G29,0)+IFERROR((1-$B$22)*(calculations!P321/calculations!P318)*((calculations!P339+calculations!P344)*$B$11+calculations!P340*$B$12+calculations!P341*$B$13+calculations!P342*$B$14+calculations!P343*$B$15)*G29,0) -> 2275.7791 | H38: =IFERROR((1-$B$22)*(calculations!Q23/calculations!Q20)*((calculations!Q41+calculations!Q244)*$B$11+calculations!Q42*$B$12+calculations!Q43*$B$13+calculations!Q44*$B$14+calculations!Q45*$B$15)*H29,0)+IFERROR((1-$B$22)*(calculations!Q51/calculations!Q48)*((calculations!Q69+calculations!Q249)*$B$11+calculations!Q70*$B$12+calculations!Q71*$B$13+calculations!Q72*$B$14+calculations!Q73*$B$15)*H29,0)+IFERROR((1-$B$22)*(calculations!Q79/calculations!Q76)*((calculations!Q97+calculations!Q254)*$B$11+calculations!Q98*$B$12+calculations!Q99*$B$13+calculations!Q100*$B$14+calculations!Q101*$B$15)*H29,0)+IFERROR((1-$B$22)*(calculations!Q107/calculations!Q104)*((calculations!Q125+calculations!Q259)*$B$11+calculations!Q126*$B$12+calculations!Q127*$B$13+calculations!Q128*$B$14+calculations!Q129*$B$15)*H29,0)+IFERROR((1-$B$22)*(calculations!Q135/calculations!Q132)*((calculations!Q153+calculations!Q264)*$B$11+calculations!Q154*$B$12+calculations!Q155*$B$13+calculations!Q156*$B$14+calculations!Q157*$B$15)*H29,0)+IFERROR((1-$B$22)*(calculations!Q163/calculations!Q160)*((calculations!Q181+calculations!Q269)*$B$11+calculations!Q182*$B$12+calculations!Q183*$B$13+calculations!Q184*$B$14+calculations!Q185*$B$15)*H29,0)+IFERROR((1-$B$22)*(calculations!Q191/calculations!Q188)*((calculations!Q209+calculations!Q274)*$B$11+calculations!Q210*$B$12+calculations!Q211*$B$13+calculations!Q212*$B$14+calculations!Q213*$B$15)*H29,0)+IFERROR((1-$B$22)*(calculations!Q219/calculations!Q216)*((calculations!Q237+calculations!Q279)*$B$11+calculations!Q238*$B$12+calculations!Q239*$B$13+calculations!Q240*$B$14+calculations!Q241*$B$15)*H29,0)+IFERROR((1-$B$22)*(calculations!Q289/calculations!Q286)*((calculations!Q307+calculations!Q312)*$B$11+calculations!Q308*$B$12+calculations!Q309*$B$13+calculations!Q310*$B$14+calculations!Q311*$B$15)*H29,0)+IFERROR((1-$B$22)*(calculations!Q321/calculations!Q318)*((calculations!Q339+calculations!Q344)*$B$11+calculations!Q340*$B$12+calculations!Q341*$B$13+calculations!Q342*$B$14+calculations!Q343*$B$15)*H29,0) -> 2729.83 | I38: =IFERROR((1-$B$22)*(calculations!R23/calculations!R20)*((calculations!R41+calculations!R244)*$B$11+calculations!R42*$B$12+calculations!R43*$B$13+calculations!R44*$B$14+calculations!R45*$B$15)*I29,0)+IFERROR((1-$B$22)*(calculations!R51/calculations!R48)*((calculations!R69+calculations!R249)*$B$11+calculations!R70*$B$12+calculations!R71*$B$13+calculations!R72*$B$14+calculations!R73*$B$15)*I29,0)+IFERROR((1-$B$22)*(calculations!R79/calculations!R76)*((calculations!R97+calculations!R254)*$B$11+calculations!R98*$B$12+calculations!R99*$B$13+calculations!R100*$B$14+calculations!R101*$B$15)*I29,0)+IFERROR((1-$B$22)*(calculations!R107/calculations!R104)*((calculations!R125+calculations!R259)*$B$11+calculations!R126*$B$12+calculations!R127*$B$13+calculations!R128*$B$14+calculations!R129*$B$15)*I29,0)+IFERROR((1-$B$22)*(calculations!R135/calculations!R132)*((calculations!R153+calculations!R264)*$B$11+calculations!R154*$B$12+calculations!R155*$B$13+calculations!R156*$B$14+calculations!R157*$B$15)*I29,0)+IFERROR((1-$B$22)*(calculations!R163/calculations!R160)*((calculations!R181+calculations!R269)*$B$11+calculations!R182*$B$12+calculations!R183*$B$13+calculations!R184*$B$14+calculations!R185*$B$15)*I29,0)+IFERROR((1-$B$22)*(calculations!R191/calculations!R188)*((calculations!R209+calculations!R274)*$B$11+calculations!R210*$B$12+calculations!R211*$B$13+calculations!R212*$B$14+calculations!R213*$B$15)*I29,0)+IFERROR((1-$B$22)*(calculations!R219/calculations!R216)*((calculations!R237+calculations!R279)*$B$11+calculations!R238*$B$12+calculations!R239*$B$13+calculations!R240*$B$14+calculations!R241*$B$15)*I29,0)+IFERROR((1-$B$22)*(calculations!R289/calculations!R286)*((calculations!R307+calculations!R312)*$B$11+calculations!R308*$B$12+calculations!R309*$B$13+calculations!R310*$B$14+calculations!R311*$B$15)*I29,0)+IFERROR((1-$B$22)*(calculations!R321/calculations!R318)*((calculations!R339+calculations!R344)*$B$11+calculations!R340*$B$12+calculations!R341*$B$13+calculations!R342*$B$14+calculations!R343*$B$15)*I29,0) -> 3475.1802 | J38: =IFERROR((1-$B$22)*(calculations!S23/calculations!S20)*((calculations!S41+calculations!S244)*$B$11+calculations!S42*$B$12+calculations!S43*$B$13+calculations!S44*$B$14+calculations!S45*$B$15)*J29,0)+IFERROR((1-$B$22)*(calculations!S51/calculations!S48)*((calculations!S69+calculations!S249)*$B$11+calculations!S70*$B$12+calculations!S71*$B$13+calculations!S72*$B$14+calculations!S73*$B$15)*J29,0)+IFERROR((1-$B$22)*(calculations!S79/calculations!S76)*((calculations!S97+calculations!S254)*$B$11+calculations!S98*$B$12+calculations!S99*$B$13+calculations!S100*$B$14+calculations!S101*$B$15)*J29,0)+IFERROR((1-$B$22)*(calculations!S107/calculations!S104)*((calculations!S125+calculations!S259)*$B$11+calculations!S126*$B$12+calculations!S127*$B$13+calculations!S128*$B$14+calculations!S129*$B$15)*J29,0)+IFERROR((1-$B$22)*(calculations!S135/calculations!S132)*((calculations!S153+calculations!S264)*$B$11+calculations!S154*$B$12+calculations!S155*$B$13+calculations!S156*$B$14+calculations!S157*$B$15)*J29,0)+IFERROR((1-$B$22)*(calculations!S163/calculations!S160)*((calculations!S181+calculations!S269)*$B$11+calculations!S182*$B$12+calculations!S183*$B$13+calculations!S184*$B$14+calculations!S185*$B$15)*J29,0)+IFERROR((1-$B$22)*(calculations!S191/calculations!S188)*((calculations!S209+calculations!S274)*$B$11+calculations!S210*$B$12+calculations!S211*$B$13+calculations!S212*$B$14+calculations!S213*$B$15)*J29,0)+IFERROR((1-$B$22)*(calculations!S219/calculations!S216)*((calculations!S237+calculations!S279)*$B$11+calculations!S238*$B$12+calculations!S239*$B$13+calculations!S240*$B$14+calculations!S241*$B$15)*J29,0)+IFERROR((1-$B$22)*(calculations!S289/calculations!S286)*((calculations!S307+calculations!S312)*$B$11+calculations!S308*$B$12+calculations!S309*$B$13+calculations!S310*$B$14+calculations!S311*$B$15)*J29,0)+IFERROR((1-$B$22)*(calculations!S321/calculations!S318)*((calculations!S339+calculations!S344)*$B$11+calculations!S340*$B$12+calculations!S341*$B$13+calculations!S342*$B$14+calculations!S343*$B$15)*J29,0) -> 5245.3979 | K38: =IFERROR((1-$B$22)*(calculations!T23/calculations!T20)*((calculations!T41+calculations!T244)*$B$11+calculations!T42*$B$12+calculations!T43*$B$13+calculations!T44*$B$14+calculations!T45*$B$15)*K29,0)+IFERROR((1-$B$22)*(calculations!T51/calculations!T48)*((calculations!T69+calculations!T249)*$B$11+calculations!T70*$B$12+calculations!T71*$B$13+calculations!T72*$B$14+calculations!T73*$B$15)*K29,0)+IFERROR((1-$B$22)*(calculations!T79/calculations!T76)*((calculations!T97+calculations!T254)*$B$11+calculations!T98*$B$12+calculations!T99*$B$13+calculations!T100*$B$14+calculations!T101*$B$15)*K29,0)+IFERROR((1-$B$22)*(calculations!T107/calculations!T104)*((calculations!T125+calculations!T259)*$B$11+calculations!T126*$B$12+calculations!T127*$B$13+calculations!T128*$B$14+calculations!T129*$B$15)*K29,0)+IFERROR((1-$B$22)*(calculations!T135/calculations!T132)*((calculations!T153+calculations!T264)*$B$11+calculations!T154*$B$12+calculations!T155*$B$13+calculations!T156*$B$14+calculations!T157*$B$15)*K29,0)+IFERROR((1-$B$22)*(calculations!T163/calculations!T160)*((calculations!T181+calculations!T269)*$B$11+calculations!T182*$B$12+calculations!T183*$B$13+calculations!T184*$B$14+calculations!T185*$B$15)*K29,0)+IFERROR((1-$B$22)*(calculations!T191/calculations!T188)*((calculations!T209+calculations!T274)*$B$11+calculations!T210*$B$12+calculations!T211*$B$13+calculations!T212*$B$14+calculations!T213*$B$15)*K29,0)+IFERROR((1-$B$22)*(calculations!T219/calculations!T216)*((calculations!T237+calculations!T279)*$B$11+calculations!T238*$B$12+calculations!T239*$B$13+calculations!T240*$B$14+calculations!T241*$B$15)*K29,0)+IFERROR((1-$B$22)*(calculations!T289/calculations!T286)*((calculations!T307+calculations!T312)*$B$11+calculations!T308*$B$12+calculations!T309*$B$13+calculations!T310*$B$14+calculations!T311*$B$15)*K29,0)+IFERROR((1-$B$22)*(calculations!T321/calculations!T318)*((calculations!T339+calculations!T344)*$B$11+calculations!T340*$B$12+calculations!T341*$B$13+calculations!T342*$B$14+calculations!T343*$B$15)*K29,0) -> 6617.101 | ... O38: =IFERROR((1-$B$22)*(calculations!X23/calculations!X20)*((calculations!X41+calculations!X244)*$B$11+calculations!X42*$B$12+calculations!X43*$B$13+calculations!X44*$B$14+calculations!X45*$B$15)*O29,0)+IFERROR((1-$B$22)*(calculations!X51/calculations!X48)*((calculations!X69+calculations!X249)*$B$11+calculations!X70*$B$12+calculations!X71*$B$13+calculations!X72*$B$14+calculations!X73*$B$15)*O29,0)+IFERROR((1-$B$22)*(calculations!X79/calculations!X76)*((calculations!X97+calculations!X254)*$B$11+calculations!X98*$B$12+calculations!X99*$B$13+calculations!X100*$B$14+calculations!X101*$B$15)*O29,0)+IFERROR((1-$B$22)*(calculations!X107/calculations!X104)*((calculations!X125+calculations!X259)*$B$11+calculations!X126*$B$12+calculations!X127*$B$13+calculations!X128*$B$14+calculations!X129*$B$15)*O29,0)+IFERROR((1-$B$22)*(calculations!X135/calculations!X132)*((calculations!X153+calculations!X264)*$B$11+calculations!X154*$B$12+calculations!X155*$B$13+calculations!X156*$B$14+calculations!X157*$B$15)*O29,0)+IFERROR((1-$B$22)*(calculations!X163/calculations!X160)*((calculations!X181+calculations!X269)*$B$11+calculations!X182*$B$12+calculations!X183*$B$13+calculations!X184*$B$14+calculations!X185*$B$15)*O29,0)+IFERROR((1-$B$22)*(calculations!X191/calculations!X188)*((calculations!X209+calculations!X274)*$B$11+calculations!X210*$B$12+calculations!X211*$B$13+calculations!X212*$B$14+calculations!X213*$B$15)*O29,0)+IFERROR((1-$B$22)*(calculations!X219/calculations!X216)*((calculations!X237+calculations!X279)*$B$11+calculations!X238*$B$12+calculations!X239*$B$13+calculations!X240*$B$14+calculations!X241*$B$15)*O29,0)+IFERROR((1-$B$22)*(calculations!X289/calculations!X286)*((calculations!X307+calculations!X312)*$B$11+calculations!X308*$B$12+calculations!X309*$B$13+calculations!X310*$B$14+calculations!X311*$B$15)*O29,0)+IFERROR((1-$B$22)*(calculations!X321/calculations!X318)*((calculations!X339+calculations!X344)*$B$11+calculations!X340*$B$12+calculations!X341*$B$13+calculations!X342*$B$14+calculations!X343*$B$15)*O29,0) -> 13135.274
A39: TOTAL COUNTRY REVENUE | B39: USD m | D39: =D34+D37+D38 -> 0 | E39: =E34+E37+E38 -> 0 | F39: =F34+F37+F38 -> 2249.1694 | G39: =G34+G37+G38 -> 2590.3178 | H39: =H34+H37+H38 -> 3105.031 | I39: =I34+I37+I38 -> 3950.1887 | J39: =J34+J37+J38 -> 5958.4301 | K39: =K34+K37+K38 -> 7511.6749 | ... O39: =O34+O37+O38 -> 14872.939
A40: TOTAL POOL (country + EU) | B40: USD m | D40: =D39+D36 -> 0 | E40: =E39+E36 -> 0 | F40: =F39+F36 -> 2249.1694 | G40: =G39+G36 -> 2590.3178 | H40: =H39+H36 -> 3105.031 | I40: =I39+I36 -> 3950.1887 | J40: =J39+J36 -> 5958.4301 | K40: =K39+K36 -> 7511.6749 | ... O40: =O39+O36 -> 14872.939
A42: 5. PRICE IMPACT BY PRODUCT (detail year set by B6)
A43: Product | B43: Pre-policy price (USD/t) | C43: EU wedge — CBAM/t | D43: Domestic wedge — CP × covered int | E43: Stack on EU exports | F43: Stack on non-EU exports | G43: Stack on domestic | H43: Buyer price ↑ EU | I43: Buyer price ↑ non-EU | J43: Producer margin hit EU | K43: Producer margin hit non-EU
A44: DRI-EAF steel (CN 7206 (D)) | B44: =INDEX(input_data!$M:$X,MATCH("all.in.ppx.stl.drg.---",input_data!$A:$A,0),$P$6) -> 0 | C44: =INDEX(calculations!$M:$X,248,$P$6) -> 61.012848 | D44: =IFERROR(((INDEX(calculations!$M:$X,41,$P$6)+INDEX(calculations!$M:$X,244,$P$6))*$B$11+INDEX(calculations!$M:$X,42,$P$6)*$B$12+INDEX(calculations!$M:$X,43,$P$6)*$B$13+INDEX(calculations!$M:$X,44,$P$6)*$B$14+INDEX(calculations!$M:$X,45,$P$6)*$B$15)/INDEX(calculations!$M:$X,20,$P$6),0)*INDEX($D$29:$O$29,$P$6) -> 75.37816 | E44: =MAX(C44,D44) -> 75.37816 | F44: =D44 -> 75.37816 | G44: =(1-$B$22)*D44 -> 75.37816 | H44: =$B$7*E44 -> 52.764712 | I44: =$B$7*F44 -> 52.764712 | J44: =(1-$B$7)*E44 -> 22.613448 | K44: =(1-$B$7)*F44 -> 22.613448
A45: Scrap-EAF steel (CN 7206 (E)) | B45: =INDEX(input_data!$M:$X,MATCH("all.in.ppx.stl.scr.---",input_data!$A:$A,0),$P$6) -> 0 | C45: =INDEX(calculations!$M:$X,253,$P$6) -> 14.948505 | D45: =IFERROR(((INDEX(calculations!$M:$X,69,$P$6)+INDEX(calculations!$M:$X,249,$P$6))*$B$11+INDEX(calculations!$M:$X,70,$P$6)*$B$12+INDEX(calculations!$M:$X,71,$P$6)*$B$13+INDEX(calculations!$M:$X,72,$P$6)*$B$14+INDEX(calculations!$M:$X,73,$P$6)*$B$15)/INDEX(calculations!$M:$X,48,$P$6),0)*INDEX($D$29:$O$29,$P$6) -> 31.169453 | E45: =MAX(C45,D45) -> 31.169453 | F45: =D45 -> 31.169453 | G45: =(1-$B$22)*D45 -> 31.169453 | H45: =$B$7*E45 -> 21.818617 | I45: =$B$7*F45 -> 21.818617 | J45: =(1-$B$7)*E45 -> 9.350836 | K45: =(1-$B$7)*F45 -> 9.350836
A46: BF-BOF steel (CN 7206 (C)) | B46: =INDEX(input_data!$M:$X,MATCH("all.in.ppx.stl.bof.---",input_data!$A:$A,0),$P$6) -> 0 | C46: =INDEX(calculations!$M:$X,258,$P$6) -> 185.50592 | D46: =IFERROR(((INDEX(calculations!$M:$X,97,$P$6)+INDEX(calculations!$M:$X,254,$P$6))*$B$11+INDEX(calculations!$M:$X,98,$P$6)*$B$12+INDEX(calculations!$M:$X,99,$P$6)*$B$13+INDEX(calculations!$M:$X,100,$P$6)*$B$14+INDEX(calculations!$M:$X,101,$P$6)*$B$15)/INDEX(calculations!$M:$X,76,$P$6),0)*INDEX($D$29:$O$29,$P$6) -> 0 | E46: =MAX(C46,D46) -> 185.50592 | F46: =D46 -> 0 | G46: =(1-$B$22)*D46 -> 0 | H46: =$B$7*E46 -> 129.85415 | I46: =$B$7*F46 -> 0 | J46: =(1-$B$7)*E46 -> 55.651777 | K46: =(1-$B$7)*F46 -> 0
A47: Cement (CN 25231000 (A)) | B47: =INDEX(input_data!$M:$X,MATCH("all.in.ppx.cmt.dry.---",input_data!$A:$A,0),$P$6) -> 0 | C47: =INDEX(calculations!$M:$X,263,$P$6) -> 66.73634 | D47: =IFERROR(((INDEX(calculations!$M:$X,125,$P$6)+INDEX(calculations!$M:$X,259,$P$6))*$B$11+INDEX(calculations!$M:$X,126,$P$6)*$B$12+INDEX(calculations!$M:$X,127,$P$6)*$B$13+INDEX(calculations!$M:$X,128,$P$6)*$B$14+INDEX(calculations!$M:$X,129,$P$6)*$B$15)/INDEX(calculations!$M:$X,104,$P$6),0)*INDEX($D$29:$O$29,$P$6) -> 66.9576 | E47: =MAX(C47,D47) -> 66.9576 | F47: =D47 -> 66.9576 | G47: =(1-$B$22)*D47 -> 66.9576 | H47: =$B$7*E47 -> 46.87032 | I47: =$B$7*F47 -> 46.87032 | J47: =(1-$B$7)*E47 -> 20.08728 | K47: =(1-$B$7)*F47 -> 20.08728
A48: Ammonia (CN 28141000) | B48: =INDEX(input_data!$M:$X,MATCH("all.in.ppx.frt.amc.---",input_data!$A:$A,0),$P$6) -> 0 | C48: =INDEX(calculations!$M:$X,268,$P$6) -> 139.77871 | D48: =IFERROR(((INDEX(calculations!$M:$X,153,$P$6)+INDEX(calculations!$M:$X,264,$P$6))*$B$11+INDEX(calculations!$M:$X,154,$P$6)*$B$12+INDEX(calculations!$M:$X,155,$P$6)*$B$13+INDEX(calculations!$M:$X,156,$P$6)*$B$14+INDEX(calculations!$M:$X,157,$P$6)*$B$15)/INDEX(calculations!$M:$X,132,$P$6),0)*INDEX($D$29:$O$29,$P$6) -> 145.27542 | E48: =MAX(C48,D48) -> 145.27542 | F48: =D48 -> 145.27542 | G48: =(1-$B$22)*D48 -> 145.27542 | H48: =$B$7*E48 -> 101.69279 | I48: =$B$7*F48 -> 101.69279 | J48: =(1-$B$7)*E48 -> 43.582626 | K48: =(1-$B$7)*F48 -> 43.582626
A49: Urea (CN 31021010) | B49: =INDEX(input_data!$M:$X,MATCH("all.in.ppx.frt.ure.---",input_data!$A:$A,0),$P$6) -> 0 | C49: =INDEX(calculations!$M:$X,273,$P$6) -> 2.9246294 | D49: =IFERROR(((INDEX(calculations!$M:$X,181,$P$6)+INDEX(calculations!$M:$X,269,$P$6))*$B$11+INDEX(calculations!$M:$X,182,$P$6)*$B$12+INDEX(calculations!$M:$X,183,$P$6)*$B$13+INDEX(calculations!$M:$X,184,$P$6)*$B$14+INDEX(calculations!$M:$X,185,$P$6)*$B$15)/INDEX(calculations!$M:$X,160,$P$6),0)*INDEX($D$29:$O$29,$P$6) -> 37.507147 | E49: =MAX(C49,D49) -> 37.507147 | F49: =D49 -> 37.507147 | G49: =(1-$B$22)*D49 -> 37.507147 | H49: =$B$7*E49 -> 26.255003 | I49: =$B$7*F49 -> 26.255003 | J49: =(1-$B$7)*E49 -> 11.252144 | K49: =(1-$B$7)*F49 -> 11.252144
A50: Ammonium nitrate (CN 31023090) | B50: =INDEX(input_data!$M:$X,MATCH("all.in.ppx.frt.nit.---",input_data!$A:$A,0),$P$6) -> 0 | C50: =INDEX(calculations!$M:$X,278,$P$6) -> 173.6509 | D50: =IFERROR(((INDEX(calculations!$M:$X,209,$P$6)+INDEX(calculations!$M:$X,274,$P$6))*$B$11+INDEX(calculations!$M:$X,210,$P$6)*$B$12+INDEX(calculations!$M:$X,211,$P$6)*$B$13+INDEX(calculations!$M:$X,212,$P$6)*$B$14+INDEX(calculations!$M:$X,213,$P$6)*$B$15)/INDEX(calculations!$M:$X,188,$P$6),0)*INDEX($D$29:$O$29,$P$6) -> 117.54513 | E50: =MAX(C50,D50) -> 173.6509 | F50: =D50 -> 117.54513 | G50: =(1-$B$22)*D50 -> 117.54513 | H50: =$B$7*E50 -> 121.55563 | I50: =$B$7*F50 -> 82.281594 | J50: =(1-$B$7)*E50 -> 52.09527 | K50: =(1-$B$7)*F50 -> 35.26354
A51: Primary aluminium (CN 76011000 (K)) | B51: =INDEX(input_data!$M:$X,MATCH("all.in.ppx.alu.prp.---",input_data!$A:$A,0),$P$6) -> 0 | C51: =INDEX(calculations!$M:$X,283,$P$6) -> 223.31741 | D51: =IFERROR(((INDEX(calculations!$M:$X,237,$P$6)+INDEX(calculations!$M:$X,279,$P$6))*$B$11+INDEX(calculations!$M:$X,238,$P$6)*$B$12+INDEX(calculations!$M:$X,239,$P$6)*$B$13+INDEX(calculations!$M:$X,240,$P$6)*$B$14+INDEX(calculations!$M:$X,241,$P$6)*$B$15)/INDEX(calculations!$M:$X,216,$P$6),0)*INDEX($D$29:$O$29,$P$6) -> 711.31731 | E51: =MAX(C51,D51) -> 711.31731 | F51: =D51 -> 711.31731 | G51: =(1-$B$22)*D51 -> 711.31731 | H51: =$B$7*E51 -> 497.92211 | I51: =$B$7*F51 -> 497.92211 | J51: =(1-$B$7)*E51 -> 213.39519 | K51: =(1-$B$7)*F51 -> 213.39519
A53: EU wedge = CBAM/t (uses CBAM-eligible intensity, Annex II respected). Domestic wedge = CP × covered_intensity (covers whatever scopes 2a flags say). Stack on EU = max(EU wedge, dom wedge) — producer pays whichever is higher. Stack on domestic = 0 when exports-only toggle (2c) is on. θ (B7) splits each wedge between buyer prices and producer margins.
A55: 6. EMISSION INTENSITY MATRIX — country (B5), detail year (B6). Fuel EF reference in ef_benchmarks sheet.
A56: 6a. Fuel emission factors (kgCO₂/GJ, IPCC 2006 stationary combustion defaults). Global constants — same for all countries and entities.
A57: These IPCC 2006 defaults live in input_data under code all.in.eff.---.---.[fuel]. They are constant across years (IPCC physical constants). Column A of each row below holds the lookup code; column C formula reads from input_data via MATCH($A{row},...). To add or change an EF: update input_data row; formula here auto-updates.
A58: Code in input_data (col A → MATCH) | B58: Fuel | C58: EF (kgCO₂/GJ) from input_data | D58: IPCC 2006 reference
A59: all.in.eff.---.---.coa | B59: Coal | C59: =INDEX(input_data!$L:$L,MATCH("all.in.eff.---.---.coa",input_data!$A:$A,0)) -> 96.1 | D59: Coal — 96.1 kgCO₂/GJ (IPCC 2006 T2.2; bituminous default)
A60: all.in.eff.---.---.nga | B60: Natural gas | C60: =INDEX(input_data!$L:$L,MATCH("all.in.eff.---.---.nga",input_data!$A:$A,0)) -> 56.1 | D60: Natural gas — 56.1 kgCO₂/GJ (IPCC 2006 T2.2)
A61: all.in.eff.---.---.gso | B61: Gasoline | C61: =INDEX(input_data!$L:$L,MATCH("all.in.eff.---.---.gso",input_data!$A:$A,0)) -> 69.3 | D61: Gasoline — 69.3 kgCO₂/GJ
A62: all.in.eff.---.---.die | B62: Diesel | C62: =INDEX(input_data!$L:$L,MATCH("all.in.eff.---.---.die",input_data!$A:$A,0)) -> 74.1 | D62: Diesel — 74.1 kgCO₂/GJ
A63: all.in.eff.---.---.ker | B63: Kerosene | C63: =INDEX(input_data!$L:$L,MATCH("all.in.eff.---.---.ker",input_data!$A:$A,0)) -> 71.9 | D63: Kerosene — 71.9 kgCO₂/GJ
A64: all.in.eff.---.---.lpg | B64: LPG | C64: =INDEX(input_data!$L:$L,MATCH("all.in.eff.---.---.lpg",input_data!$A:$A,0)) -> 63.1 | D64: LPG — 63.1 kgCO₂/GJ
A65: all.in.eff.---.---.bio | B65: Biomass | C65: =INDEX(input_data!$L:$L,MATCH("all.in.eff.---.---.bio",input_data!$A:$A,0)) -> 0 | D65: Biomass — 0 (biogenic, not counted under IPCC GHG inventory rules)
A66: all.in.eff.---.---.ren | B66: Self-gen renewables | C66: =INDEX(input_data!$L:$L,MATCH("all.in.eff.---.---.ren",input_data!$A:$A,0)) -> 0 | D66: Self-gen renewables — 0 (zero direct emission)
A68: 6b. Weighted-average fuel emission factor per entity × application [= Σ(energy_GJ × fuel_EF) / Σ(energy_GJ), kgCO₂/GJ]
A69: This converts the multi-fuel energy mix into a single combined EF for (a) combustion and (b) process/reduction. It answers: 'what is the effective kgCO₂/GJ for this entity's fuel blend?' Formula: =SUMPRODUCT(enc_rows, ef_rows) / SUM(enc_rows), where enc_rows are the annual energy consumption rows from the calculations sheet for the current country (B5) and detail year (YEAR_IDX). Code column (A) is self-generated from entity code. Zero denominator → IFERROR returns 0. These are per-tonne intensities expressed as kgCO₂/GJ — multiply by GJ/t intensity to get tCO₂/t.
A70: Code (self-generated) | B70: Entity | C70: Unit | D70: Wtd-avg EF COMBUSTION (kgCO₂/GJ) | E70: Wtd-avg EF PROCESS/RED. (kgCO₂/GJ) | F70: Total combustion energy (PJ) [for weighting] | G70: Total process energy (PJ) [for weighting] | H70: Formula note
A71: =CBAM!$B$5&".wef.stl.drg.---" -> egy.wef.stl.drg.--- | B71: DRI-EAF steel (stl.drg) | C71: t | D71: =IFERROR((INDEX(calculations!$M:$X,24,CBAM!$P$6)*INDEX(calculations!$M:$X,10,CBAM!$P$6)+INDEX(calculations!$M:$X,25,CBAM!$P$6)*INDEX(calculations!$M:$X,11,CBAM!$P$6)+INDEX(calculations!$M:$X,26,CBAM!$P$6)*INDEX(calculations!$M:$X,12,CBAM!$P$6)+INDEX(calculations!$M:$X,27,CBAM!$P$6)*INDEX(calculations!$M:$X,13,CBAM!$P$6)+INDEX(calculations!$M:$X,28,CBAM!$P$6)*INDEX(calculations!$M:$X,14,CBAM!$P$6)+INDEX(calculations!$M:$X,29,CBAM!$P$6)*INDEX(calculations!$M:$X,15,CBAM!$P$6)+INDEX(calculations!$M:$X,30,CBAM!$P$6)*INDEX(calculations!$M:$X,16,CBAM!$P$6)+INDEX(calculations!$M:$X,31,CBAM!$P$6)*INDEX(calculations!$M:$X,17,CBAM!$P$6))/(INDEX(calculations!$M:$X,24,CBAM!$P$6)+INDEX(calculations!$M:$X,25,CBAM!$P$6)+INDEX(calculations!$M:$X,26,CBAM!$P$6)+INDEX(calculations!$M:$X,27,CBAM!$P$6)+INDEX(calculations!$M:$X,28,CBAM!$P$6)+INDEX(calculations!$M:$X,29,CBAM!$P$6)+INDEX(calculations!$M:$X,30,CBAM!$P$6)+INDEX(calculations!$M:$X,31,CBAM!$P$6)),0) -> 56.1 | E71: =IFERROR((INDEX(calculations!$M:$X,32,CBAM!$P$6)*INDEX(calculations!$M:$X,10,CBAM!$P$6)+INDEX(calculations!$M:$X,33,CBAM!$P$6)*INDEX(calculations!$M:$X,11,CBAM!$P$6)+INDEX(calculations!$M:$X,34,CBAM!$P$6)*INDEX(calculations!$M:$X,12,CBAM!$P$6)+INDEX(calculations!$M:$X,35,CBAM!$P$6)*INDEX(calculations!$M:$X,13,CBAM!$P$6)+INDEX(calculations!$M:$X,36,CBAM!$P$6)*INDEX(calculations!$M:$X,14,CBAM!$P$6)+INDEX(calculations!$M:$X,37,CBAM!$P$6)*INDEX(calculations!$M:$X,15,CBAM!$P$6)+INDEX(calculations!$M:$X,38,CBAM!$P$6)*INDEX(calculations!$M:$X,16,CBAM!$P$6)+INDEX(calculations!$M:$X,39,CBAM!$P$6)*INDEX(calculations!$M:$X,17,CBAM!$P$6))/(INDEX(calculations!$M:$X,32,CBAM!$P$6)+INDEX(calculations!$M:$X,33,CBAM!$P$6)+INDEX(calculations!$M:$X,34,CBAM!$P$6)+INDEX(calculations!$M:$X,35,CBAM!$P$6)+INDEX(calculations!$M:$X,36,CBAM!$P$6)+INDEX(calculations!$M:$X,37,CBAM!$P$6)+INDEX(calculations!$M:$X,38,CBAM!$P$6)+INDEX(calculations!$M:$X,39,CBAM!$P$6)),0) -> 56.1 | F71: =IFERROR(INDEX(calculations!$M:$X,24,CBAM!$P$6)+INDEX(calculations!$M:$X,25,CBAM!$P$6)+INDEX(calculations!$M:$X,26,CBAM!$P$6)+INDEX(calculations!$M:$X,27,CBAM!$P$6)+INDEX(calculations!$M:$X,28,CBAM!$P$6)+INDEX(calculations!$M:$X,29,CBAM!$P$6)+INDEX(calculations!$M:$X,30,CBAM!$P$6)+INDEX(calculations!$M:$X,31,CBAM!$P$6),0) -> 16.173826 | G71: =IFERROR(INDEX(calculations!$M:$X,32,CBAM!$P$6)+INDEX(calculations!$M:$X,33,CBAM!$P$6)+INDEX(calculations!$M:$X,34,CBAM!$P$6)+INDEX(calculations!$M:$X,35,CBAM!$P$6)+INDEX(calculations!$M:$X,36,CBAM!$P$6)+INDEX(calculations!$M:$X,37,CBAM!$P$6)+INDEX(calculations!$M:$X,38,CBAM!$P$6)+INDEX(calculations!$M:$X,39,CBAM!$P$6),0) -> 70.320983 | H71: cmb: SUMPRODUCT(enc rows 24–31, ef rows 10–17) / SUM(enc). prc: same with enp rows 32–39
A72: =CBAM!$B$5&".wef.stl.scr.---" -> egy.wef.stl.scr.--- | B72: Scrap-EAF steel (stl.scr) | C72: t | D72: =IFERROR((INDEX(calculations!$M:$X,52,CBAM!$P$6)*INDEX(calculations!$M:$X,10,CBAM!$P$6)+INDEX(calculations!$M:$X,53,CBAM!$P$6)*INDEX(calculations!$M:$X,11,CBAM!$P$6)+INDEX(calculations!$M:$X,54,CBAM!$P$6)*INDEX(calculations!$M:$X,12,CBAM!$P$6)+INDEX(calculations!$M:$X,55,CBAM!$P$6)*INDEX(calculations!$M:$X,13,CBAM!$P$6)+INDEX(calculations!$M:$X,56,CBAM!$P$6)*INDEX(calculations!$M:$X,14,CBAM!$P$6)+INDEX(calculations!$M:$X,57,CBAM!$P$6)*INDEX(calculations!$M:$X,15,CBAM!$P$6)+INDEX(calculations!$M:$X,58,CBAM!$P$6)*INDEX(calculations!$M:$X,16,CBAM!$P$6)+INDEX(calculations!$M:$X,59,CBAM!$P$6)*INDEX(calculations!$M:$X,17,CBAM!$P$6))/(INDEX(calculations!$M:$X,52,CBAM!$P$6)+INDEX(calculations!$M:$X,53,CBAM!$P$6)+INDEX(calculations!$M:$X,54,CBAM!$P$6)+INDEX(calculations!$M:$X,55,CBAM!$P$6)+INDEX(calculations!$M:$X,56,CBAM!$P$6)+INDEX(calculations!$M:$X,57,CBAM!$P$6)+INDEX(calculations!$M:$X,58,CBAM!$P$6)+INDEX(calculations!$M:$X,59,CBAM!$P$6)),0) -> 56.1 | E72: =IFERROR((INDEX(calculations!$M:$X,60,CBAM!$P$6)*INDEX(calculations!$M:$X,10,CBAM!$P$6)+INDEX(calculations!$M:$X,61,CBAM!$P$6)*INDEX(calculations!$M:$X,11,CBAM!$P$6)+INDEX(calculations!$M:$X,62,CBAM!$P$6)*INDEX(calculations!$M:$X,12,CBAM!$P$6)+INDEX(calculations!$M:$X,63,CBAM!$P$6)*INDEX(calculations!$M:$X,13,CBAM!$P$6)+INDEX(calculations!$M:$X,64,CBAM!$P$6)*INDEX(calculations!$M:$X,14,CBAM!$P$6)+INDEX(calculations!$M:$X,65,CBAM!$P$6)*INDEX(calculations!$M:$X,15,CBAM!$P$6)+INDEX(calculations!$M:$X,66,CBAM!$P$6)*INDEX(calculations!$M:$X,16,CBAM!$P$6)+INDEX(calculations!$M:$X,67,CBAM!$P$6)*INDEX(calculations!$M:$X,17,CBAM!$P$6))/(INDEX(calculations!$M:$X,60,CBAM!$P$6)+INDEX(calculations!$M:$X,61,CBAM!$P$6)+INDEX(calculations!$M:$X,62,CBAM!$P$6)+INDEX(calculations!$M:$X,63,CBAM!$P$6)+INDEX(calculations!$M:$X,64,CBAM!$P$6)+INDEX(calculations!$M:$X,65,CBAM!$P$6)+INDEX(calculations!$M:$X,66,CBAM!$P$6)+INDEX(calculations!$M:$X,67,CBAM!$P$6)),0) -> 0 | F72: =IFERROR(INDEX(calculations!$M:$X,52,CBAM!$P$6)+INDEX(calculations!$M:$X,53,CBAM!$P$6)+INDEX(calculations!$M:$X,54,CBAM!$P$6)+INDEX(calculations!$M:$X,55,CBAM!$P$6)+INDEX(calculations!$M:$X,56,CBAM!$P$6)+INDEX(calculations!$M:$X,57,CBAM!$P$6)+INDEX(calculations!$M:$X,58,CBAM!$P$6)+INDEX(calculations!$M:$X,59,CBAM!$P$6),0) -> 14.805303 | G72: =IFERROR(INDEX(calculations!$M:$X,60,CBAM!$P$6)+INDEX(calculations!$M:$X,61,CBAM!$P$6)+INDEX(calculations!$M:$X,62,CBAM!$P$6)+INDEX(calculations!$M:$X,63,CBAM!$P$6)+INDEX(calculations!$M:$X,64,CBAM!$P$6)+INDEX(calculations!$M:$X,65,CBAM!$P$6)+INDEX(calculations!$M:$X,66,CBAM!$P$6)+INDEX(calculations!$M:$X,67,CBAM!$P$6),0) -> 0 | H72: cmb: SUMPRODUCT(enc rows 52–59, ef rows 10–17) / SUM(enc). prc: same with enp rows 60–67
A73: =CBAM!$B$5&".wef.stl.bof.---" -> egy.wef.stl.bof.--- | B73: BF-BOF steel (stl.bof) | C73: t | D73: =IFERROR((INDEX(calculations!$M:$X,80,CBAM!$P$6)*INDEX(calculations!$M:$X,10,CBAM!$P$6)+INDEX(calculations!$M:$X,81,CBAM!$P$6)*INDEX(calculations!$M:$X,11,CBAM!$P$6)+INDEX(calculations!$M:$X,82,CBAM!$P$6)*INDEX(calculations!$M:$X,12,CBAM!$P$6)+INDEX(calculations!$M:$X,83,CBAM!$P$6)*INDEX(calculations!$M:$X,13,CBAM!$P$6)+INDEX(calculations!$M:$X,84,CBAM!$P$6)*INDEX(calculations!$M:$X,14,CBAM!$P$6)+INDEX(calculations!$M:$X,85,CBAM!$P$6)*INDEX(calculations!$M:$X,15,CBAM!$P$6)+INDEX(calculations!$M:$X,86,CBAM!$P$6)*INDEX(calculations!$M:$X,16,CBAM!$P$6)+INDEX(calculations!$M:$X,87,CBAM!$P$6)*INDEX(calculations!$M:$X,17,CBAM!$P$6))/(INDEX(calculations!$M:$X,80,CBAM!$P$6)+INDEX(calculations!$M:$X,81,CBAM!$P$6)+INDEX(calculations!$M:$X,82,CBAM!$P$6)+INDEX(calculations!$M:$X,83,CBAM!$P$6)+INDEX(calculations!$M:$X,84,CBAM!$P$6)+INDEX(calculations!$M:$X,85,CBAM!$P$6)+INDEX(calculations!$M:$X,86,CBAM!$P$6)+INDEX(calculations!$M:$X,87,CBAM!$P$6)),0) -> 0 | E73: =IFERROR((INDEX(calculations!$M:$X,88,CBAM!$P$6)*INDEX(calculations!$M:$X,10,CBAM!$P$6)+INDEX(calculations!$M:$X,89,CBAM!$P$6)*INDEX(calculations!$M:$X,11,CBAM!$P$6)+INDEX(calculations!$M:$X,90,CBAM!$P$6)*INDEX(calculations!$M:$X,12,CBAM!$P$6)+INDEX(calculations!$M:$X,91,CBAM!$P$6)*INDEX(calculations!$M:$X,13,CBAM!$P$6)+INDEX(calculations!$M:$X,92,CBAM!$P$6)*INDEX(calculations!$M:$X,14,CBAM!$P$6)+INDEX(calculations!$M:$X,93,CBAM!$P$6)*INDEX(calculations!$M:$X,15,CBAM!$P$6)+INDEX(calculations!$M:$X,94,CBAM!$P$6)*INDEX(calculations!$M:$X,16,CBAM!$P$6)+INDEX(calculations!$M:$X,95,CBAM!$P$6)*INDEX(calculations!$M:$X,17,CBAM!$P$6))/(INDEX(calculations!$M:$X,88,CBAM!$P$6)+INDEX(calculations!$M:$X,89,CBAM!$P$6)+INDEX(calculations!$M:$X,90,CBAM!$P$6)+INDEX(calculations!$M:$X,91,CBAM!$P$6)+INDEX(calculations!$M:$X,92,CBAM!$P$6)+INDEX(calculations!$M:$X,93,CBAM!$P$6)+INDEX(calculations!$M:$X,94,CBAM!$P$6)+INDEX(calculations!$M:$X,95,CBAM!$P$6)),0) -> 0 | F73: =IFERROR(INDEX(calculations!$M:$X,80,CBAM!$P$6)+INDEX(calculations!$M:$X,81,CBAM!$P$6)+INDEX(calculations!$M:$X,82,CBAM!$P$6)+INDEX(calculations!$M:$X,83,CBAM!$P$6)+INDEX(calculations!$M:$X,84,CBAM!$P$6)+INDEX(calculations!$M:$X,85,CBAM!$P$6)+INDEX(calculations!$M:$X,86,CBAM!$P$6)+INDEX(calculations!$M:$X,87,CBAM!$P$6),0) -> 0 | G73: =IFERROR(INDEX(calculations!$M:$X,88,CBAM!$P$6)+INDEX(calculations!$M:$X,89,CBAM!$P$6)+INDEX(calculations!$M:$X,90,CBAM!$P$6)+INDEX(calculations!$M:$X,91,CBAM!$P$6)+INDEX(calculations!$M:$X,92,CBAM!$P$6)+INDEX(calculations!$M:$X,93,CBAM!$P$6)+INDEX(calculations!$M:$X,94,CBAM!$P$6)+INDEX(calculations!$M:$X,95,CBAM!$P$6),0) -> 0 | H73: cmb: SUMPRODUCT(enc rows 80–87, ef rows 10–17) / SUM(enc). prc: same with enp rows 88–95
A74: =CBAM!$B$5&".wef.cmt.dry.---" -> egy.wef.cmt.dry.--- | B74: Cement (cmt.dry) | C74: t | D74: =IFERROR((INDEX(calculations!$M:$X,108,CBAM!$P$6)*INDEX(calculations!$M:$X,10,CBAM!$P$6)+INDEX(calculations!$M:$X,109,CBAM!$P$6)*INDEX(calculations!$M:$X,11,CBAM!$P$6)+INDEX(calculations!$M:$X,110,CBAM!$P$6)*INDEX(calculations!$M:$X,12,CBAM!$P$6)+INDEX(calculations!$M:$X,111,CBAM!$P$6)*INDEX(calculations!$M:$X,13,CBAM!$P$6)+INDEX(calculations!$M:$X,112,CBAM!$P$6)*INDEX(calculations!$M:$X,14,CBAM!$P$6)+INDEX(calculations!$M:$X,113,CBAM!$P$6)*INDEX(calculations!$M:$X,15,CBAM!$P$6)+INDEX(calculations!$M:$X,114,CBAM!$P$6)*INDEX(calculations!$M:$X,16,CBAM!$P$6)+INDEX(calculations!$M:$X,115,CBAM!$P$6)*INDEX(calculations!$M:$X,17,CBAM!$P$6))/(INDEX(calculations!$M:$X,108,CBAM!$P$6)+INDEX(calculations!$M:$X,109,CBAM!$P$6)+INDEX(calculations!$M:$X,110,CBAM!$P$6)+INDEX(calculations!$M:$X,111,CBAM!$P$6)+INDEX(calculations!$M:$X,112,CBAM!$P$6)+INDEX(calculations!$M:$X,113,CBAM!$P$6)+INDEX(calculations!$M:$X,114,CBAM!$P$6)+INDEX(calculations!$M:$X,115,CBAM!$P$6)),0) -> 96.1 | E74: =IFERROR((INDEX(calculations!$M:$X,116,CBAM!$P$6)*INDEX(calculations!$M:$X,10,CBAM!$P$6)+INDEX(calculations!$M:$X,117,CBAM!$P$6)*INDEX(calculations!$M:$X,11,CBAM!$P$6)+INDEX(calculations!$M:$X,118,CBAM!$P$6)*INDEX(calculations!$M:$X,12,CBAM!$P$6)+INDEX(calculations!$M:$X,119,CBAM!$P$6)*INDEX(calculations!$M:$X,13,CBAM!$P$6)+INDEX(calculations!$M:$X,120,CBAM!$P$6)*INDEX(calculations!$M:$X,14,CBAM!$P$6)+INDEX(calculations!$M:$X,121,CBAM!$P$6)*INDEX(calculations!$M:$X,15,CBAM!$P$6)+INDEX(calculations!$M:$X,122,CBAM!$P$6)*INDEX(calculations!$M:$X,16,CBAM!$P$6)+INDEX(calculations!$M:$X,123,CBAM!$P$6)*INDEX(calculations!$M:$X,17,CBAM!$P$6))/(INDEX(calculations!$M:$X,116,CBAM!$P$6)+INDEX(calculations!$M:$X,117,CBAM!$P$6)+INDEX(calculations!$M:$X,118,CBAM!$P$6)+INDEX(calculations!$M:$X,119,CBAM!$P$6)+INDEX(calculations!$M:$X,120,CBAM!$P$6)+INDEX(calculations!$M:$X,121,CBAM!$P$6)+INDEX(calculations!$M:$X,122,CBAM!$P$6)+INDEX(calculations!$M:$X,123,CBAM!$P$6)),0) -> 0 | F74: =IFERROR(INDEX(calculations!$M:$X,108,CBAM!$P$6)+INDEX(calculations!$M:$X,109,CBAM!$P$6)+INDEX(calculations!$M:$X,110,CBAM!$P$6)+INDEX(calculations!$M:$X,111,CBAM!$P$6)+INDEX(calculations!$M:$X,112,CBAM!$P$6)+INDEX(calculations!$M:$X,113,CBAM!$P$6)+INDEX(calculations!$M:$X,114,CBAM!$P$6)+INDEX(calculations!$M:$X,115,CBAM!$P$6),0) -> 200.28782 | G74: =IFERROR(INDEX(calculations!$M:$X,116,CBAM!$P$6)+INDEX(calculations!$M:$X,117,CBAM!$P$6)+INDEX(calculations!$M:$X,118,CBAM!$P$6)+INDEX(calculations!$M:$X,119,CBAM!$P$6)+INDEX(calculations!$M:$X,120,CBAM!$P$6)+INDEX(calculations!$M:$X,121,CBAM!$P$6)+INDEX(calculations!$M:$X,122,CBAM!$P$6)+INDEX(calculations!$M:$X,123,CBAM!$P$6),0) -> 0 | H74: cmb: SUMPRODUCT(enc rows 108–115, ef rows 10–17) / SUM(enc). prc: same with enp rows 116–123
A75: =CBAM!$B$5&".wef.frt.amc.---" -> egy.wef.frt.amc.--- | B75: Ammonia (frt.amc) | C75: t | D75: =IFERROR((INDEX(calculations!$M:$X,136,CBAM!$P$6)*INDEX(calculations!$M:$X,10,CBAM!$P$6)+INDEX(calculations!$M:$X,137,CBAM!$P$6)*INDEX(calculations!$M:$X,11,CBAM!$P$6)+INDEX(calculations!$M:$X,138,CBAM!$P$6)*INDEX(calculations!$M:$X,12,CBAM!$P$6)+INDEX(calculations!$M:$X,139,CBAM!$P$6)*INDEX(calculations!$M:$X,13,CBAM!$P$6)+INDEX(calculations!$M:$X,140,CBAM!$P$6)*INDEX(calculations!$M:$X,14,CBAM!$P$6)+INDEX(calculations!$M:$X,141,CBAM!$P$6)*INDEX(calculations!$M:$X,15,CBAM!$P$6)+INDEX(calculations!$M:$X,142,CBAM!$P$6)*INDEX(calculations!$M:$X,16,CBAM!$P$6)+INDEX(calculations!$M:$X,143,CBAM!$P$6)*INDEX(calculations!$M:$X,17,CBAM!$P$6))/(INDEX(calculations!$M:$X,136,CBAM!$P$6)+INDEX(calculations!$M:$X,137,CBAM!$P$6)+INDEX(calculations!$M:$X,138,CBAM!$P$6)+INDEX(calculations!$M:$X,139,CBAM!$P$6)+INDEX(calculations!$M:$X,140,CBAM!$P$6)+INDEX(calculations!$M:$X,141,CBAM!$P$6)+INDEX(calculations!$M:$X,142,CBAM!$P$6)+INDEX(calculations!$M:$X,143,CBAM!$P$6)),0) -> 56.1 | E75: =IFERROR((INDEX(calculations!$M:$X,144,CBAM!$P$6)*INDEX(calculations!$M:$X,10,CBAM!$P$6)+INDEX(calculations!$M:$X,145,CBAM!$P$6)*INDEX(calculations!$M:$X,11,CBAM!$P$6)+INDEX(calculations!$M:$X,146,CBAM!$P$6)*INDEX(calculations!$M:$X,12,CBAM!$P$6)+INDEX(calculations!$M:$X,147,CBAM!$P$6)*INDEX(calculations!$M:$X,13,CBAM!$P$6)+INDEX(calculations!$M:$X,148,CBAM!$P$6)*INDEX(calculations!$M:$X,14,CBAM!$P$6)+INDEX(calculations!$M:$X,149,CBAM!$P$6)*INDEX(calculations!$M:$X,15,CBAM!$P$6)+INDEX(calculations!$M:$X,150,CBAM!$P$6)*INDEX(calculations!$M:$X,16,CBAM!$P$6)+INDEX(calculations!$M:$X,151,CBAM!$P$6)*INDEX(calculations!$M:$X,17,CBAM!$P$6))/(INDEX(calculations!$M:$X,144,CBAM!$P$6)+INDEX(calculations!$M:$X,145,CBAM!$P$6)+INDEX(calculations!$M:$X,146,CBAM!$P$6)+INDEX(calculations!$M:$X,147,CBAM!$P$6)+INDEX(calculations!$M:$X,148,CBAM!$P$6)+INDEX(calculations!$M:$X,149,CBAM!$P$6)+INDEX(calculations!$M:$X,150,CBAM!$P$6)+INDEX(calculations!$M:$X,151,CBAM!$P$6)),0) -> 56.1 | F75: =IFERROR(INDEX(calculations!$M:$X,136,CBAM!$P$6)+INDEX(calculations!$M:$X,137,CBAM!$P$6)+INDEX(calculations!$M:$X,138,CBAM!$P$6)+INDEX(calculations!$M:$X,139,CBAM!$P$6)+INDEX(calculations!$M:$X,140,CBAM!$P$6)+INDEX(calculations!$M:$X,141,CBAM!$P$6)+INDEX(calculations!$M:$X,142,CBAM!$P$6)+INDEX(calculations!$M:$X,143,CBAM!$P$6),0) -> 9.8636275 | G75: =IFERROR(INDEX(calculations!$M:$X,144,CBAM!$P$6)+INDEX(calculations!$M:$X,145,CBAM!$P$6)+INDEX(calculations!$M:$X,146,CBAM!$P$6)+INDEX(calculations!$M:$X,147,CBAM!$P$6)+INDEX(calculations!$M:$X,148,CBAM!$P$6)+INDEX(calculations!$M:$X,149,CBAM!$P$6)+INDEX(calculations!$M:$X,150,CBAM!$P$6)+INDEX(calculations!$M:$X,151,CBAM!$P$6),0) -> 36.636331 | H75: cmb: SUMPRODUCT(enc rows 136–143, ef rows 10–17) / SUM(enc). prc: same with enp rows 144–151
A76: =CBAM!$B$5&".wef.frt.ure.---" -> egy.wef.frt.ure.--- | B76: Urea (frt.ure) | C76: t | D76: =IFERROR((INDEX(calculations!$M:$X,164,CBAM!$P$6)*INDEX(calculations!$M:$X,10,CBAM!$P$6)+INDEX(calculations!$M:$X,165,CBAM!$P$6)*INDEX(calculations!$M:$X,11,CBAM!$P$6)+INDEX(calculations!$M:$X,166,CBAM!$P$6)*INDEX(calculations!$M:$X,12,CBAM!$P$6)+INDEX(calculations!$M:$X,167,CBAM!$P$6)*INDEX(calculations!$M:$X,13,CBAM!$P$6)+INDEX(calculations!$M:$X,168,CBAM!$P$6)*INDEX(calculations!$M:$X,14,CBAM!$P$6)+INDEX(calculations!$M:$X,169,CBAM!$P$6)*INDEX(calculations!$M:$X,15,CBAM!$P$6)+INDEX(calculations!$M:$X,170,CBAM!$P$6)*INDEX(calculations!$M:$X,16,CBAM!$P$6)+INDEX(calculations!$M:$X,171,CBAM!$P$6)*INDEX(calculations!$M:$X,17,CBAM!$P$6))/(INDEX(calculations!$M:$X,164,CBAM!$P$6)+INDEX(calculations!$M:$X,165,CBAM!$P$6)+INDEX(calculations!$M:$X,166,CBAM!$P$6)+INDEX(calculations!$M:$X,167,CBAM!$P$6)+INDEX(calculations!$M:$X,168,CBAM!$P$6)+INDEX(calculations!$M:$X,169,CBAM!$P$6)+INDEX(calculations!$M:$X,170,CBAM!$P$6)+INDEX(calculations!$M:$X,171,CBAM!$P$6)),0) -> 56.1 | E76: =IFERROR((INDEX(calculations!$M:$X,172,CBAM!$P$6)*INDEX(calculations!$M:$X,10,CBAM!$P$6)+INDEX(calculations!$M:$X,173,CBAM!$P$6)*INDEX(calculations!$M:$X,11,CBAM!$P$6)+INDEX(calculations!$M:$X,174,CBAM!$P$6)*INDEX(calculations!$M:$X,12,CBAM!$P$6)+INDEX(calculations!$M:$X,175,CBAM!$P$6)*INDEX(calculations!$M:$X,13,CBAM!$P$6)+INDEX(calculations!$M:$X,176,CBAM!$P$6)*INDEX(calculations!$M:$X,14,CBAM!$P$6)+INDEX(calculations!$M:$X,177,CBAM!$P$6)*INDEX(calculations!$M:$X,15,CBAM!$P$6)+INDEX(calculations!$M:$X,178,CBAM!$P$6)*INDEX(calculations!$M:$X,16,CBAM!$P$6)+INDEX(calculations!$M:$X,179,CBAM!$P$6)*INDEX(calculations!$M:$X,17,CBAM!$P$6))/(INDEX(calculations!$M:$X,172,CBAM!$P$6)+INDEX(calculations!$M:$X,173,CBAM!$P$6)+INDEX(calculations!$M:$X,174,CBAM!$P$6)+INDEX(calculations!$M:$X,175,CBAM!$P$6)+INDEX(calculations!$M:$X,176,CBAM!$P$6)+INDEX(calculations!$M:$X,177,CBAM!$P$6)+INDEX(calculations!$M:$X,178,CBAM!$P$6)+INDEX(calculations!$M:$X,179,CBAM!$P$6)),0) -> 0 | F76: =IFERROR(INDEX(calculations!$M:$X,164,CBAM!$P$6)+INDEX(calculations!$M:$X,165,CBAM!$P$6)+INDEX(calculations!$M:$X,166,CBAM!$P$6)+INDEX(calculations!$M:$X,167,CBAM!$P$6)+INDEX(calculations!$M:$X,168,CBAM!$P$6)+INDEX(calculations!$M:$X,169,CBAM!$P$6)+INDEX(calculations!$M:$X,170,CBAM!$P$6)+INDEX(calculations!$M:$X,171,CBAM!$P$6),0) -> 3.2878758 | G76: =IFERROR(INDEX(calculations!$M:$X,172,CBAM!$P$6)+INDEX(calculations!$M:$X,173,CBAM!$P$6)+INDEX(calculations!$M:$X,174,CBAM!$P$6)+INDEX(calculations!$M:$X,175,CBAM!$P$6)+INDEX(calculations!$M:$X,176,CBAM!$P$6)+INDEX(calculations!$M:$X,177,CBAM!$P$6)+INDEX(calculations!$M:$X,178,CBAM!$P$6)+INDEX(calculations!$M:$X,179,CBAM!$P$6),0) -> 0 | H76: cmb: SUMPRODUCT(enc rows 164–171, ef rows 10–17) / SUM(enc). prc: same with enp rows 172–179
A77: =CBAM!$B$5&".wef.frt.nit.---" -> egy.wef.frt.nit.--- | B77: Ammonium nitrate (frt.nit) | C77: t | D77: =IFERROR((INDEX(calculations!$M:$X,192,CBAM!$P$6)*INDEX(calculations!$M:$X,10,CBAM!$P$6)+INDEX(calculations!$M:$X,193,CBAM!$P$6)*INDEX(calculations!$M:$X,11,CBAM!$P$6)+INDEX(calculations!$M:$X,194,CBAM!$P$6)*INDEX(calculations!$M:$X,12,CBAM!$P$6)+INDEX(calculations!$M:$X,195,CBAM!$P$6)*INDEX(calculations!$M:$X,13,CBAM!$P$6)+INDEX(calculations!$M:$X,196,CBAM!$P$6)*INDEX(calculations!$M:$X,14,CBAM!$P$6)+INDEX(calculations!$M:$X,197,CBAM!$P$6)*INDEX(calculations!$M:$X,15,CBAM!$P$6)+INDEX(calculations!$M:$X,198,CBAM!$P$6)*INDEX(calculations!$M:$X,16,CBAM!$P$6)+INDEX(calculations!$M:$X,199,CBAM!$P$6)*INDEX(calculations!$M:$X,17,CBAM!$P$6))/(INDEX(calculations!$M:$X,192,CBAM!$P$6)+INDEX(calculations!$M:$X,193,CBAM!$P$6)+INDEX(calculations!$M:$X,194,CBAM!$P$6)+INDEX(calculations!$M:$X,195,CBAM!$P$6)+INDEX(calculations!$M:$X,196,CBAM!$P$6)+INDEX(calculations!$M:$X,197,CBAM!$P$6)+INDEX(calculations!$M:$X,198,CBAM!$P$6)+INDEX(calculations!$M:$X,199,CBAM!$P$6)),0) -> 56.1 | E77: =IFERROR((INDEX(calculations!$M:$X,200,CBAM!$P$6)*INDEX(calculations!$M:$X,10,CBAM!$P$6)+INDEX(calculations!$M:$X,201,CBAM!$P$6)*INDEX(calculations!$M:$X,11,CBAM!$P$6)+INDEX(calculations!$M:$X,202,CBAM!$P$6)*INDEX(calculations!$M:$X,12,CBAM!$P$6)+INDEX(calculations!$M:$X,203,CBAM!$P$6)*INDEX(calculations!$M:$X,13,CBAM!$P$6)+INDEX(calculations!$M:$X,204,CBAM!$P$6)*INDEX(calculations!$M:$X,14,CBAM!$P$6)+INDEX(calculations!$M:$X,205,CBAM!$P$6)*INDEX(calculations!$M:$X,15,CBAM!$P$6)+INDEX(calculations!$M:$X,206,CBAM!$P$6)*INDEX(calculations!$M:$X,16,CBAM!$P$6)+INDEX(calculations!$M:$X,207,CBAM!$P$6)*INDEX(calculations!$M:$X,17,CBAM!$P$6))/(INDEX(calculations!$M:$X,200,CBAM!$P$6)+INDEX(calculations!$M:$X,201,CBAM!$P$6)+INDEX(calculations!$M:$X,202,CBAM!$P$6)+INDEX(calculations!$M:$X,203,CBAM!$P$6)+INDEX(calculations!$M:$X,204,CBAM!$P$6)+INDEX(calculations!$M:$X,205,CBAM!$P$6)+INDEX(calculations!$M:$X,206,CBAM!$P$6)+INDEX(calculations!$M:$X,207,CBAM!$P$6)),0) -> 0 | F77: =IFERROR(INDEX(calculations!$M:$X,192,CBAM!$P$6)+INDEX(calculations!$M:$X,193,CBAM!$P$6)+INDEX(calculations!$M:$X,194,CBAM!$P$6)+INDEX(calculations!$M:$X,195,CBAM!$P$6)+INDEX(calculations!$M:$X,196,CBAM!$P$6)+INDEX(calculations!$M:$X,197,CBAM!$P$6)+INDEX(calculations!$M:$X,198,CBAM!$P$6)+INDEX(calculations!$M:$X,199,CBAM!$P$6),0) -> 1.137119 | G77: =IFERROR(INDEX(calculations!$M:$X,200,CBAM!$P$6)+INDEX(calculations!$M:$X,201,CBAM!$P$6)+INDEX(calculations!$M:$X,202,CBAM!$P$6)+INDEX(calculations!$M:$X,203,CBAM!$P$6)+INDEX(calculations!$M:$X,204,CBAM!$P$6)+INDEX(calculations!$M:$X,205,CBAM!$P$6)+INDEX(calculations!$M:$X,206,CBAM!$P$6)+INDEX(calculations!$M:$X,207,CBAM!$P$6),0) -> 0 | H77: cmb: SUMPRODUCT(enc rows 192–199, ef rows 10–17) / SUM(enc). prc: same with enp rows 200–207
A78: =CBAM!$B$5&".wef.alu.prp.---" -> egy.wef.alu.prp.--- | B78: Primary aluminium (alu.prp) | C78: t | D78: =IFERROR((INDEX(calculations!$M:$X,220,CBAM!$P$6)*INDEX(calculations!$M:$X,10,CBAM!$P$6)+INDEX(calculations!$M:$X,221,CBAM!$P$6)*INDEX(calculations!$M:$X,11,CBAM!$P$6)+INDEX(calculations!$M:$X,222,CBAM!$P$6)*INDEX(calculations!$M:$X,12,CBAM!$P$6)+INDEX(calculations!$M:$X,223,CBAM!$P$6)*INDEX(calculations!$M:$X,13,CBAM!$P$6)+INDEX(calculations!$M:$X,224,CBAM!$P$6)*INDEX(calculations!$M:$X,14,CBAM!$P$6)+INDEX(calculations!$M:$X,225,CBAM!$P$6)*INDEX(calculations!$M:$X,15,CBAM!$P$6)+INDEX(calculations!$M:$X,226,CBAM!$P$6)*INDEX(calculations!$M:$X,16,CBAM!$P$6)+INDEX(calculations!$M:$X,227,CBAM!$P$6)*INDEX(calculations!$M:$X,17,CBAM!$P$6))/(INDEX(calculations!$M:$X,220,CBAM!$P$6)+INDEX(calculations!$M:$X,221,CBAM!$P$6)+INDEX(calculations!$M:$X,222,CBAM!$P$6)+INDEX(calculations!$M:$X,223,CBAM!$P$6)+INDEX(calculations!$M:$X,224,CBAM!$P$6)+INDEX(calculations!$M:$X,225,CBAM!$P$6)+INDEX(calculations!$M:$X,226,CBAM!$P$6)+INDEX(calculations!$M:$X,227,CBAM!$P$6)),0) -> 74.1 | E78: =IFERROR((INDEX(calculations!$M:$X,228,CBAM!$P$6)*INDEX(calculations!$M:$X,10,CBAM!$P$6)+INDEX(calculations!$M:$X,229,CBAM!$P$6)*INDEX(calculations!$M:$X,11,CBAM!$P$6)+INDEX(calculations!$M:$X,230,CBAM!$P$6)*INDEX(calculations!$M:$X,12,CBAM!$P$6)+INDEX(calculations!$M:$X,231,CBAM!$P$6)*INDEX(calculations!$M:$X,13,CBAM!$P$6)+INDEX(calculations!$M:$X,232,CBAM!$P$6)*INDEX(calculations!$M:$X,14,CBAM!$P$6)+INDEX(calculations!$M:$X,233,CBAM!$P$6)*INDEX(calculations!$M:$X,15,CBAM!$P$6)+INDEX(calculations!$M:$X,234,CBAM!$P$6)*INDEX(calculations!$M:$X,16,CBAM!$P$6)+INDEX(calculations!$M:$X,235,CBAM!$P$6)*INDEX(calculations!$M:$X,17,CBAM!$P$6))/(INDEX(calculations!$M:$X,228,CBAM!$P$6)+INDEX(calculations!$M:$X,229,CBAM!$P$6)+INDEX(calculations!$M:$X,230,CBAM!$P$6)+INDEX(calculations!$M:$X,231,CBAM!$P$6)+INDEX(calculations!$M:$X,232,CBAM!$P$6)+INDEX(calculations!$M:$X,233,CBAM!$P$6)+INDEX(calculations!$M:$X,234,CBAM!$P$6)+INDEX(calculations!$M:$X,235,CBAM!$P$6)),0) -> 0 | F78: =IFERROR(INDEX(calculations!$M:$X,220,CBAM!$P$6)+INDEX(calculations!$M:$X,221,CBAM!$P$6)+INDEX(calculations!$M:$X,222,CBAM!$P$6)+INDEX(calculations!$M:$X,223,CBAM!$P$6)+INDEX(calculations!$M:$X,224,CBAM!$P$6)+INDEX(calculations!$M:$X,225,CBAM!$P$6)+INDEX(calculations!$M:$X,226,CBAM!$P$6)+INDEX(calculations!$M:$X,227,CBAM!$P$6),0) -> 0.74996293 | G78: =IFERROR(INDEX(calculations!$M:$X,228,CBAM!$P$6)+INDEX(calculations!$M:$X,229,CBAM!$P$6)+INDEX(calculations!$M:$X,230,CBAM!$P$6)+INDEX(calculations!$M:$X,231,CBAM!$P$6)+INDEX(calculations!$M:$X,232,CBAM!$P$6)+INDEX(calculations!$M:$X,233,CBAM!$P$6)+INDEX(calculations!$M:$X,234,CBAM!$P$6)+INDEX(calculations!$M:$X,235,CBAM!$P$6),0) -> 0 | H78: cmb: SUMPRODUCT(enc rows 220–227, ef rows 10–17) / SUM(enc). prc: same with enp rows 228–235
A79: =CBAM!$B$5&".wef.stl.oth.---" -> egy.wef.stl.oth.--- | B79: Other iron & steel (stl.oth) | C79: t | D79: =IFERROR((INDEX(calculations!$M:$X,290,CBAM!$P$6)*INDEX(calculations!$M:$X,10,CBAM!$P$6)+INDEX(calculations!$M:$X,291,CBAM!$P$6)*INDEX(calculations!$M:$X,11,CBAM!$P$6)+INDEX(calculations!$M:$X,292,CBAM!$P$6)*INDEX(calculations!$M:$X,12,CBAM!$P$6)+INDEX(calculations!$M:$X,293,CBAM!$P$6)*INDEX(calculations!$M:$X,13,CBAM!$P$6)+INDEX(calculations!$M:$X,294,CBAM!$P$6)*INDEX(calculations!$M:$X,14,CBAM!$P$6)+INDEX(calculations!$M:$X,295,CBAM!$P$6)*INDEX(calculations!$M:$X,15,CBAM!$P$6)+INDEX(calculations!$M:$X,296,CBAM!$P$6)*INDEX(calculations!$M:$X,16,CBAM!$P$6)+INDEX(calculations!$M:$X,297,CBAM!$P$6)*INDEX(calculations!$M:$X,17,CBAM!$P$6))/(INDEX(calculations!$M:$X,290,CBAM!$P$6)+INDEX(calculations!$M:$X,291,CBAM!$P$6)+INDEX(calculations!$M:$X,292,CBAM!$P$6)+INDEX(calculations!$M:$X,293,CBAM!$P$6)+INDEX(calculations!$M:$X,294,CBAM!$P$6)+INDEX(calculations!$M:$X,295,CBAM!$P$6)+INDEX(calculations!$M:$X,296,CBAM!$P$6)+INDEX(calculations!$M:$X,297,CBAM!$P$6)),0) -> 86.1 | E79: =IFERROR((INDEX(calculations!$M:$X,298,CBAM!$P$6)*INDEX(calculations!$M:$X,10,CBAM!$P$6)+INDEX(calculations!$M:$X,299,CBAM!$P$6)*INDEX(calculations!$M:$X,11,CBAM!$P$6)+INDEX(calculations!$M:$X,300,CBAM!$P$6)*INDEX(calculations!$M:$X,12,CBAM!$P$6)+INDEX(calculations!$M:$X,301,CBAM!$P$6)*INDEX(calculations!$M:$X,13,CBAM!$P$6)+INDEX(calculations!$M:$X,302,CBAM!$P$6)*INDEX(calculations!$M:$X,14,CBAM!$P$6)+INDEX(calculations!$M:$X,303,CBAM!$P$6)*INDEX(calculations!$M:$X,15,CBAM!$P$6)+INDEX(calculations!$M:$X,304,CBAM!$P$6)*INDEX(calculations!$M:$X,16,CBAM!$P$6)+INDEX(calculations!$M:$X,305,CBAM!$P$6)*INDEX(calculations!$M:$X,17,CBAM!$P$6))/(INDEX(calculations!$M:$X,298,CBAM!$P$6)+INDEX(calculations!$M:$X,299,CBAM!$P$6)+INDEX(calculations!$M:$X,300,CBAM!$P$6)+INDEX(calculations!$M:$X,301,CBAM!$P$6)+INDEX(calculations!$M:$X,302,CBAM!$P$6)+INDEX(calculations!$M:$X,303,CBAM!$P$6)+INDEX(calculations!$M:$X,304,CBAM!$P$6)+INDEX(calculations!$M:$X,305,CBAM!$P$6)),0) -> 96.1 | F79: =IFERROR(INDEX(calculations!$M:$X,290,CBAM!$P$6)+INDEX(calculations!$M:$X,291,CBAM!$P$6)+INDEX(calculations!$M:$X,292,CBAM!$P$6)+INDEX(calculations!$M:$X,293,CBAM!$P$6)+INDEX(calculations!$M:$X,294,CBAM!$P$6)+INDEX(calculations!$M:$X,295,CBAM!$P$6)+INDEX(calculations!$M:$X,296,CBAM!$P$6)+INDEX(calculations!$M:$X,297,CBAM!$P$6),0) -> 0.55153712 | G79: =IFERROR(INDEX(calculations!$M:$X,298,CBAM!$P$6)+INDEX(calculations!$M:$X,299,CBAM!$P$6)+INDEX(calculations!$M:$X,300,CBAM!$P$6)+INDEX(calculations!$M:$X,301,CBAM!$P$6)+INDEX(calculations!$M:$X,302,CBAM!$P$6)+INDEX(calculations!$M:$X,303,CBAM!$P$6)+INDEX(calculations!$M:$X,304,CBAM!$P$6)+INDEX(calculations!$M:$X,305,CBAM!$P$6),0) -> 1.9303799 | H79: cmb: SUMPRODUCT(enc rows 290–297, ef rows 10–17) / SUM(enc). prc: same with enp rows 298–305
A80: =CBAM!$B$5&".wef.frt.otn.---" -> egy.wef.frt.otn.--- | B80: Other nitrogen fertilisers (frt.otn) | C80: t N | D80: =IFERROR((INDEX(calculations!$M:$X,322,CBAM!$P$6)*INDEX(calculations!$M:$X,10,CBAM!$P$6)+INDEX(calculations!$M:$X,323,CBAM!$P$6)*INDEX(calculations!$M:$X,11,CBAM!$P$6)+INDEX(calculations!$M:$X,324,CBAM!$P$6)*INDEX(calculations!$M:$X,12,CBAM!$P$6)+INDEX(calculations!$M:$X,325,CBAM!$P$6)*INDEX(calculations!$M:$X,13,CBAM!$P$6)+INDEX(calculations!$M:$X,326,CBAM!$P$6)*INDEX(calculations!$M:$X,14,CBAM!$P$6)+INDEX(calculations!$M:$X,327,CBAM!$P$6)*INDEX(calculations!$M:$X,15,CBAM!$P$6)+INDEX(calculations!$M:$X,328,CBAM!$P$6)*INDEX(calculations!$M:$X,16,CBAM!$P$6)+INDEX(calculations!$M:$X,329,CBAM!$P$6)*INDEX(calculations!$M:$X,17,CBAM!$P$6))/(INDEX(calculations!$M:$X,322,CBAM!$P$6)+INDEX(calculations!$M:$X,323,CBAM!$P$6)+INDEX(calculations!$M:$X,324,CBAM!$P$6)+INDEX(calculations!$M:$X,325,CBAM!$P$6)+INDEX(calculations!$M:$X,326,CBAM!$P$6)+INDEX(calculations!$M:$X,327,CBAM!$P$6)+INDEX(calculations!$M:$X,328,CBAM!$P$6)+INDEX(calculations!$M:$X,329,CBAM!$P$6)),0) -> 56.1 | E80: =IFERROR((INDEX(calculations!$M:$X,330,CBAM!$P$6)*INDEX(calculations!$M:$X,10,CBAM!$P$6)+INDEX(calculations!$M:$X,331,CBAM!$P$6)*INDEX(calculations!$M:$X,11,CBAM!$P$6)+INDEX(calculations!$M:$X,332,CBAM!$P$6)*INDEX(calculations!$M:$X,12,CBAM!$P$6)+INDEX(calculations!$M:$X,333,CBAM!$P$6)*INDEX(calculations!$M:$X,13,CBAM!$P$6)+INDEX(calculations!$M:$X,334,CBAM!$P$6)*INDEX(calculations!$M:$X,14,CBAM!$P$6)+INDEX(calculations!$M:$X,335,CBAM!$P$6)*INDEX(calculations!$M:$X,15,CBAM!$P$6)+INDEX(calculations!$M:$X,336,CBAM!$P$6)*INDEX(calculations!$M:$X,16,CBAM!$P$6)+INDEX(calculations!$M:$X,337,CBAM!$P$6)*INDEX(calculations!$M:$X,17,CBAM!$P$6))/(INDEX(calculations!$M:$X,330,CBAM!$P$6)+INDEX(calculations!$M:$X,331,CBAM!$P$6)+INDEX(calculations!$M:$X,332,CBAM!$P$6)+INDEX(calculations!$M:$X,333,CBAM!$P$6)+INDEX(calculations!$M:$X,334,CBAM!$P$6)+INDEX(calculations!$M:$X,335,CBAM!$P$6)+INDEX(calculations!$M:$X,336,CBAM!$P$6)+INDEX(calculations!$M:$X,337,CBAM!$P$6)),0) -> 0 | F80: =IFERROR(INDEX(calculations!$M:$X,322,CBAM!$P$6)+INDEX(calculations!$M:$X,323,CBAM!$P$6)+INDEX(calculations!$M:$X,324,CBAM!$P$6)+INDEX(calculations!$M:$X,325,CBAM!$P$6)+INDEX(calculations!$M:$X,326,CBAM!$P$6)+INDEX(calculations!$M:$X,327,CBAM!$P$6)+INDEX(calculations!$M:$X,328,CBAM!$P$6)+INDEX(calculations!$M:$X,329,CBAM!$P$6),0) -> 0.46969655 | G80: =IFERROR(INDEX(calculations!$M:$X,330,CBAM!$P$6)+INDEX(calculations!$M:$X,331,CBAM!$P$6)+INDEX(calculations!$M:$X,332,CBAM!$P$6)+INDEX(calculations!$M:$X,333,CBAM!$P$6)+INDEX(calculations!$M:$X,334,CBAM!$P$6)+INDEX(calculations!$M:$X,335,CBAM!$P$6)+INDEX(calculations!$M:$X,336,CBAM!$P$6)+INDEX(calculations!$M:$X,337,CBAM!$P$6),0) -> 0 | H80: cmb: SUMPRODUCT(enc rows 322–329, ef rows 10–17) / SUM(enc). prc: same with enp rows 330–337
A82: 6a. Emission intensity decomposition — all 10 entities, detail year (B6), country (B5). Column order: direct scope 1 (combustion, process, non-fuel, non-CO₂) THEN scope 2, THEN chain.
A83: S1.np (non-fuel process CO₂) and S1.no (non-CO₂ GHG: N₂O, PFCs) are SCOPE 1 direct emissions — they appear here BEFORE S2 (indirect/electricity). All values = MtCO₂e ÷ Mt production = tCO₂e/t (or tCO₂e/t N for frt.otn). Scope-2-in-CBAM column: green=YES (cement and fertilisers per Annex II of Reg 2023/956), orange=NO (steel and aluminium — direct emissions only for CBAM). Benchmark and EU default from input_data (IR 2025/2620 and IR 2025/2621). Excess = MAX(CBAM-eligible − benchmark, 0).
A84: Code (col A) | B84: Entity | C84: Unit | D84: S1.fc combustion tCO₂/t | E84: S1.fp process fuel tCO₂/t | F84: S1.np non-fuel process CO₂/t | G84: S1.no N₂O/PFCs tCO₂e/t | H84: S2 electricity tCO₂/t | I84: NH₃ chain tCO₂/t | J84: S2 in CBAM scope? | K84: Holistic tCO₂e/t | L84: CBAM-eligible (MRV) tCO₂e/t | M84: EU default (IR 2025/2621) SEE | N84: Free alloc. equivalent (IR 2025/2620) | O84: Excess over benchmark | P84: CN codes (CBAM Annex I)
A85: =CBAM!$B$5&".em.int.stl.drg.---" -> egy.em.int.stl.drg.--- | B85: DRI-EAF steel (stl.drg) | C85: t | D85: =IFERROR(INDEX(calculations!$M:$X,41,CBAM!$P$6)/INDEX(calculations!$M:$X,20,CBAM!$P$6),0) -> 0.12903 | E85: =IFERROR(INDEX(calculations!$M:$X,42,CBAM!$P$6)/INDEX(calculations!$M:$X,20,CBAM!$P$6),0) -> 0.561 | F85: =IFERROR(INDEX(calculations!$M:$X,43,CBAM!$P$6)/INDEX(calculations!$M:$X,20,CBAM!$P$6),0) -> 0.04 | G85: =IFERROR(INDEX(calculations!$M:$X,44,CBAM!$P$6)/INDEX(calculations!$M:$X,20,CBAM!$P$6),0) -> 0 | H85: =IFERROR(INDEX(calculations!$M:$X,45,CBAM!$P$6)/INDEX(calculations!$M:$X,20,CBAM!$P$6),0) -> 0.25 | I85: =IFERROR(INDEX(calculations!$M:$X,244,CBAM!$P$6)/INDEX(calculations!$M:$X,20,CBAM!$P$6),0) -> 0 | J85: =IF(INDEX(input_data!$L:$L,MATCH("all.in.cs2.stl.drg.---",input_data!$A:$A,0))=1,"YES","NO") -> NO | K85: =IFERROR(INDEX(calculations!$M:$X,246,CBAM!$P$6),0) -> 0.98003 | L85: =IFERROR(INDEX(calculations!$M:$X,247,CBAM!$P$6),0) -> 0.73003 | M85: =INDEX(input_data!$L:$L,MATCH("all.in.dfv.stl.drg.---",input_data!$A:$A,0)) -> 1.82 | N85: =INDEX(input_data!$L:$L,MATCH("all.in.bnk.stl.drg.---",input_data!$A:$A,0)) -> 0.481 | O85: =MAX(L85-N85,0) -> 0.24903 | P85: 7206(D), 7207(D)
A86: =CBAM!$B$5&".em.int.stl.scr.---" -> egy.em.int.stl.scr.--- | B86: Scrap-EAF steel (stl.scr) | C86: t | D86: =IFERROR(INDEX(calculations!$M:$X,69,CBAM!$P$6)/INDEX(calculations!$M:$X,48,CBAM!$P$6),0) -> 0.14025 | E86: =IFERROR(INDEX(calculations!$M:$X,70,CBAM!$P$6)/INDEX(calculations!$M:$X,48,CBAM!$P$6),0) -> 0 | F86: =IFERROR(INDEX(calculations!$M:$X,71,CBAM!$P$6)/INDEX(calculations!$M:$X,48,CBAM!$P$6),0) -> 0.015 | G86: =IFERROR(INDEX(calculations!$M:$X,72,CBAM!$P$6)/INDEX(calculations!$M:$X,48,CBAM!$P$6),0) -> 0 | H86: =IFERROR(INDEX(calculations!$M:$X,73,CBAM!$P$6)/INDEX(calculations!$M:$X,48,CBAM!$P$6),0) -> 0.25 | I86: =IFERROR(INDEX(calculations!$M:$X,249,CBAM!$P$6)/INDEX(calculations!$M:$X,48,CBAM!$P$6),0) -> 0 | J86: =IF(INDEX(input_data!$L:$L,MATCH("all.in.cs2.stl.scr.---",input_data!$A:$A,0))=1,"YES","NO") -> NO | K86: =IFERROR(INDEX(calculations!$M:$X,251,CBAM!$P$6),0) -> 0.40525 | L86: =IFERROR(INDEX(calculations!$M:$X,252,CBAM!$P$6),0) -> 0.15525 | M86: =INDEX(input_data!$L:$L,MATCH("all.in.dfv.stl.scr.---",input_data!$A:$A,0)) -> 0.72 | N86: =INDEX(input_data!$L:$L,MATCH("all.in.bnk.stl.scr.---",input_data!$A:$A,0)) -> 0.072 | O86: =MAX(L86-N86,0) -> 0.08325 | P86: 7206(E), 7207(E)
A87: =CBAM!$B$5&".em.int.stl.bof.---" -> egy.em.int.stl.bof.--- | B87: BF-BOF steel (stl.bof) | C87: t | D87: =IFERROR(INDEX(calculations!$M:$X,97,CBAM!$P$6)/INDEX(calculations!$M:$X,76,CBAM!$P$6),0) -> 0 | E87: =IFERROR(INDEX(calculations!$M:$X,98,CBAM!$P$6)/INDEX(calculations!$M:$X,76,CBAM!$P$6),0) -> 0 | F87: =IFERROR(INDEX(calculations!$M:$X,99,CBAM!$P$6)/INDEX(calculations!$M:$X,76,CBAM!$P$6),0) -> 0 | G87: =IFERROR(INDEX(calculations!$M:$X,100,CBAM!$P$6)/INDEX(calculations!$M:$X,76,CBAM!$P$6),0) -> 0 | H87: =IFERROR(INDEX(calculations!$M:$X,101,CBAM!$P$6)/INDEX(calculations!$M:$X,76,CBAM!$P$6),0) -> 0 | I87: =IFERROR(INDEX(calculations!$M:$X,254,CBAM!$P$6)/INDEX(calculations!$M:$X,76,CBAM!$P$6),0) -> 0 | J87: =IF(INDEX(input_data!$L:$L,MATCH("all.in.cs2.stl.bof.---",input_data!$A:$A,0))=1,"YES","NO") -> NO | K87: =IFERROR(INDEX(calculations!$M:$X,256,CBAM!$P$6),0) -> 2.3595 | L87: =IFERROR(INDEX(calculations!$M:$X,257,CBAM!$P$6),0) -> 2.172 | M87: =INDEX(input_data!$L:$L,MATCH("all.in.dfv.stl.bof.---",input_data!$A:$A,0)) -> 2.8 | N87: =INDEX(input_data!$L:$L,MATCH("all.in.bnk.stl.bof.---",input_data!$A:$A,0)) -> 1.37 | O87: =MAX(L87-N87,0) -> 0.802 | P87: 7206(C), 7207(C)
A88: =CBAM!$B$5&".em.int.cmt.dry.---" -> egy.em.int.cmt.dry.--- | B88: Cement (cmt.dry) | C88: t | D88: =IFERROR(INDEX(calculations!$M:$X,125,CBAM!$P$6)/INDEX(calculations!$M:$X,104,CBAM!$P$6),0) -> 0.2883 | E88: =IFERROR(INDEX(calculations!$M:$X,126,CBAM!$P$6)/INDEX(calculations!$M:$X,104,CBAM!$P$6),0) -> 0 | F88: =IFERROR(INDEX(calculations!$M:$X,127,CBAM!$P$6)/INDEX(calculations!$M:$X,104,CBAM!$P$6),0) -> 0.526 | G88: =IFERROR(INDEX(calculations!$M:$X,128,CBAM!$P$6)/INDEX(calculations!$M:$X,104,CBAM!$P$6),0) -> 0 | H88: =IFERROR(INDEX(calculations!$M:$X,129,CBAM!$P$6)/INDEX(calculations!$M:$X,104,CBAM!$P$6),0) -> 0.05625 | I88: =IFERROR(INDEX(calculations!$M:$X,259,CBAM!$P$6)/INDEX(calculations!$M:$X,104,CBAM!$P$6),0) -> 0 | J88: =IF(INDEX(input_data!$L:$L,MATCH("all.in.cs2.cmt.dry.---",input_data!$A:$A,0))=1,"YES","NO") -> YES | K88: =IFERROR(INDEX(calculations!$M:$X,261,CBAM!$P$6),0) -> 0.87055 | L88: =IFERROR(INDEX(calculations!$M:$X,262,CBAM!$P$6),0) -> 0.87055 | M88: =INDEX(input_data!$L:$L,MATCH("all.in.dfv.cmt.dry.---",input_data!$A:$A,0)) -> 1.58 | N88: =INDEX(input_data!$L:$L,MATCH("all.in.bnk.cmt.dry.---",input_data!$A:$A,0)) -> 0.666 | O88: =MAX(L88-N88,0) -> 0.20455 | P88: 25231000(A)
A89: =CBAM!$B$5&".em.int.frt.amc.---" -> egy.em.int.frt.amc.--- | B89: Ammonia (frt.amc) | C89: t | D89: =IFERROR(INDEX(calculations!$M:$X,153,CBAM!$P$6)/INDEX(calculations!$M:$X,132,CBAM!$P$6),0) -> 0.3927 | E89: =IFERROR(INDEX(calculations!$M:$X,154,CBAM!$P$6)/INDEX(calculations!$M:$X,132,CBAM!$P$6),0) -> 1.4586 | F89: =IFERROR(INDEX(calculations!$M:$X,155,CBAM!$P$6)/INDEX(calculations!$M:$X,132,CBAM!$P$6),0) -> 0 | G89: =IFERROR(INDEX(calculations!$M:$X,156,CBAM!$P$6)/INDEX(calculations!$M:$X,132,CBAM!$P$6),0) -> 0 | H89: =IFERROR(INDEX(calculations!$M:$X,157,CBAM!$P$6)/INDEX(calculations!$M:$X,132,CBAM!$P$6),0) -> 0.0375 | I89: =IFERROR(INDEX(calculations!$M:$X,264,CBAM!$P$6)/INDEX(calculations!$M:$X,132,CBAM!$P$6),0) -> 0 | J89: =IF(INDEX(input_data!$L:$L,MATCH("all.in.cs2.frt.amc.---",input_data!$A:$A,0))=1,"YES","NO") -> YES | K89: =IFERROR(INDEX(calculations!$M:$X,266,CBAM!$P$6),0) -> 1.8888 | L89: =IFERROR(INDEX(calculations!$M:$X,267,CBAM!$P$6),0) -> 1.8888 | M89: =INDEX(input_data!$L:$L,MATCH("all.in.dfv.frt.amc.---",input_data!$A:$A,0)) -> 1.826 | N89: =INDEX(input_data!$L:$L,MATCH("all.in.bnk.frt.amc.---",input_data!$A:$A,0)) -> 1.522 | O89: =MAX(L89-N89,0) -> 0.3668 | P89: 28141000
A90: =CBAM!$B$5&".em.int.frt.ure.---" -> egy.em.int.frt.ure.--- | B90: Urea (frt.ure) | C90: t | D90: =IFERROR(INDEX(calculations!$M:$X,181,CBAM!$P$6)/INDEX(calculations!$M:$X,160,CBAM!$P$6),0) -> 0.1122 | E90: =IFERROR(INDEX(calculations!$M:$X,182,CBAM!$P$6)/INDEX(calculations!$M:$X,160,CBAM!$P$6),0) -> 0 | F90: =IFERROR(INDEX(calculations!$M:$X,183,CBAM!$P$6)/INDEX(calculations!$M:$X,160,CBAM!$P$6),0) -> -0.733 | G90: =IFERROR(INDEX(calculations!$M:$X,184,CBAM!$P$6)/INDEX(calculations!$M:$X,160,CBAM!$P$6),0) -> 0 | H90: =IFERROR(INDEX(calculations!$M:$X,185,CBAM!$P$6)/INDEX(calculations!$M:$X,160,CBAM!$P$6),0) -> 0.0375 | I90: =IFERROR(INDEX(calculations!$M:$X,269,CBAM!$P$6)/INDEX(calculations!$M:$X,160,CBAM!$P$6),0) -> 1.0709496 | J90: =IF(INDEX(input_data!$L:$L,MATCH("all.in.cs2.frt.ure.---",input_data!$A:$A,0))=1,"YES","NO") -> YES | K90: =IFERROR(INDEX(calculations!$M:$X,271,CBAM!$P$6),0) -> 0.4876496 | L90: =IFERROR(INDEX(calculations!$M:$X,272,CBAM!$P$6),0) -> 0.4876496 | M90: =INDEX(input_data!$L:$L,MATCH("all.in.dfv.frt.ure.---",input_data!$A:$A,0)) -> 1.88 | N90: =INDEX(input_data!$L:$L,MATCH("all.in.bnk.frt.ure.---",input_data!$A:$A,0)) -> 0.902 | O90: =MAX(L90-N90,0) -> 0 | P90: 31021010
A91: =CBAM!$B$5&".em.int.frt.nit.---" -> egy.em.int.frt.nit.--- | B91: Ammonium nitrate (frt.nit) | C91: t | D91: =IFERROR(INDEX(calculations!$M:$X,209,CBAM!$P$6)/INDEX(calculations!$M:$X,188,CBAM!$P$6),0) -> 0.1122 | E91: =IFERROR(INDEX(calculations!$M:$X,210,CBAM!$P$6)/INDEX(calculations!$M:$X,188,CBAM!$P$6),0) -> 0 | F91: =IFERROR(INDEX(calculations!$M:$X,211,CBAM!$P$6)/INDEX(calculations!$M:$X,188,CBAM!$P$6),0) -> 0 | G91: =IFERROR(INDEX(calculations!$M:$X,212,CBAM!$P$6)/INDEX(calculations!$M:$X,188,CBAM!$P$6),0) -> 0.97 | H91: =IFERROR(INDEX(calculations!$M:$X,213,CBAM!$P$6)/INDEX(calculations!$M:$X,188,CBAM!$P$6),0) -> 0.04375 | I91: =IFERROR(INDEX(calculations!$M:$X,274,CBAM!$P$6)/INDEX(calculations!$M:$X,188,CBAM!$P$6),0) -> 0.4023144 | J91: =IF(INDEX(input_data!$L:$L,MATCH("all.in.cs2.frt.nit.---",input_data!$A:$A,0))=1,"YES","NO") -> YES | K91: =IFERROR(INDEX(calculations!$M:$X,276,CBAM!$P$6),0) -> 1.5282644 | L91: =IFERROR(INDEX(calculations!$M:$X,277,CBAM!$P$6),0) -> 1.5282644 | M91: =INDEX(input_data!$L:$L,MATCH("all.in.dfv.frt.nit.---",input_data!$A:$A,0)) -> 0.97 | N91: =INDEX(input_data!$L:$L,MATCH("all.in.bnk.frt.nit.---",input_data!$A:$A,0)) -> 0.302 | O91: =MAX(L91-N91,0) -> 1.2262644 | P91: 31023090
A92: =CBAM!$B$5&".em.int.alu.prp.---" -> egy.em.int.alu.prp.--- | B92: Primary aluminium (alu.prp) | C92: t | D92: =IFERROR(INDEX(calculations!$M:$X,237,CBAM!$P$6)/INDEX(calculations!$M:$X,216,CBAM!$P$6),0) -> 0.1482 | E92: =IFERROR(INDEX(calculations!$M:$X,238,CBAM!$P$6)/INDEX(calculations!$M:$X,216,CBAM!$P$6),0) -> 0 | F92: =IFERROR(INDEX(calculations!$M:$X,239,CBAM!$P$6)/INDEX(calculations!$M:$X,216,CBAM!$P$6),0) -> 1.5 | G92: =IFERROR(INDEX(calculations!$M:$X,240,CBAM!$P$6)/INDEX(calculations!$M:$X,216,CBAM!$P$6),0) -> 0.85 | H92: =IFERROR(INDEX(calculations!$M:$X,241,CBAM!$P$6)/INDEX(calculations!$M:$X,216,CBAM!$P$6),0) -> 6.75 | I92: =IFERROR(INDEX(calculations!$M:$X,279,CBAM!$P$6)/INDEX(calculations!$M:$X,216,CBAM!$P$6),0) -> 0 | J92: =IF(INDEX(input_data!$L:$L,MATCH("all.in.cs2.alu.prp.---",input_data!$A:$A,0))=1,"YES","NO") -> NO | K92: =IFERROR(INDEX(calculations!$M:$X,281,CBAM!$P$6),0) -> 9.2482 | L92: =IFERROR(INDEX(calculations!$M:$X,282,CBAM!$P$6),0) -> 2.4982 | M92: =INDEX(input_data!$L:$L,MATCH("all.in.dfv.alu.prp.---",input_data!$A:$A,0)) -> 2.06 | N92: =INDEX(input_data!$L:$L,MATCH("all.in.bnk.alu.prp.---",input_data!$A:$A,0)) -> 1.423 | O92: =MAX(L92-N92,0) -> 1.0752 | P92: 76011000(K)
A93: =CBAM!$B$5&".em.int.stl.oth.---" -> egy.em.int.stl.oth.--- | B93: Other iron & steel (stl.oth) | C93: t | D93: =IFERROR(INDEX(calculations!$M:$X,307,CBAM!$P$6)/INDEX(calculations!$M:$X,286,CBAM!$P$6),0) -> 0.1722 | E93: =IFERROR(INDEX(calculations!$M:$X,308,CBAM!$P$6)/INDEX(calculations!$M:$X,286,CBAM!$P$6),0) -> 0.6727 | F93: =IFERROR(INDEX(calculations!$M:$X,309,CBAM!$P$6)/INDEX(calculations!$M:$X,286,CBAM!$P$6),0) -> 0 | G93: =IFERROR(INDEX(calculations!$M:$X,310,CBAM!$P$6)/INDEX(calculations!$M:$X,286,CBAM!$P$6),0) -> 0 | H93: =IFERROR(INDEX(calculations!$M:$X,311,CBAM!$P$6)/INDEX(calculations!$M:$X,286,CBAM!$P$6),0) -> 0.4375 | I93: =IFERROR(INDEX(calculations!$M:$X,312,CBAM!$P$6)/INDEX(calculations!$M:$X,286,CBAM!$P$6),0) -> 0 | J93: =IF(INDEX(input_data!$L:$L,MATCH("all.in.cs2.stl.oth.---",input_data!$A:$A,0))=1,"YES","NO") -> NO | K93: =IFERROR(INDEX(calculations!$M:$X,314,CBAM!$P$6),0) -> 1.2824 | L93: =IFERROR(INDEX(calculations!$M:$X,315,CBAM!$P$6),0) -> 0.8449 | M93: =INDEX(input_data!$L:$L,MATCH("all.in.dfv.stl.oth.---",input_data!$A:$A,0)) -> 1.466 | N93: =INDEX(input_data!$L:$L,MATCH("all.in.bnk.stl.oth.---",input_data!$A:$A,0)) -> 1.222 | O93: =MAX(L93-N93,0) -> 0 | P93: 7201/7202 4,6,7/7203
A94: =CBAM!$B$5&".em.int.frt.otn.---" -> egy.em.int.frt.otn.--- | B94: Other nitrogen fertilisers (frt.otn) | C94: t N | D94: =IFERROR(INDEX(calculations!$M:$X,339,CBAM!$P$6)/INDEX(calculations!$M:$X,318,CBAM!$P$6),0) -> 0.2805 | E94: =IFERROR(INDEX(calculations!$M:$X,340,CBAM!$P$6)/INDEX(calculations!$M:$X,318,CBAM!$P$6),0) -> 0 | F94: =IFERROR(INDEX(calculations!$M:$X,341,CBAM!$P$6)/INDEX(calculations!$M:$X,318,CBAM!$P$6),0) -> 0 | G94: =IFERROR(INDEX(calculations!$M:$X,342,CBAM!$P$6)/INDEX(calculations!$M:$X,318,CBAM!$P$6),0) -> 0 | H94: =IFERROR(INDEX(calculations!$M:$X,343,CBAM!$P$6)/INDEX(calculations!$M:$X,318,CBAM!$P$6),0) -> 0.0375 | I94: =IFERROR(INDEX(calculations!$M:$X,344,CBAM!$P$6)/INDEX(calculations!$M:$X,318,CBAM!$P$6),0) -> 0 | J94: =IF(INDEX(input_data!$L:$L,MATCH("all.in.cs2.frt.otn.---",input_data!$A:$A,0))=1,"YES","NO") -> YES | K94: =IFERROR(INDEX(calculations!$M:$X,346,CBAM!$P$6),0) -> 0.318 | L94: =IFERROR(INDEX(calculations!$M:$X,347,CBAM!$P$6),0) -> 0.318 | M94: =INDEX(input_data!$L:$L,MATCH("all.in.dfv.frt.otn.---",input_data!$A:$A,0)) -> 3.384 | N94: =INDEX(input_data!$L:$L,MATCH("all.in.bnk.frt.otn.---",input_data!$A:$A,0)) -> 2.82 | O94: =MAX(L94-N94,0) -> 0 | P94: 31022100/31028000/3105
A95: CBAM-eligible (col 12) = Holistic − S2×(1−cs2): for steel and aluminium (S2 NOT in CBAM scope), CBAM intensity = S1 direct only. For cement and fertilisers (S2 IN scope), CBAM intensity = S1 + S2. EU default (col 14) = SEE before 10% markup, from IR 2025/2621. Benchmarks from IR 2025/2620. Both regulations dated 16 December 2025.
A97: 6b. EF comparison: model computed intensities vs IR 2025/2621 reference default values. Country (B5), detail year (B6). Reference values from ref_data sheet.
A98: REGULATORY GUIDANCE IN USE: Commission Implementing Regulation (EU) 2025/2621 of 16 December 2025 (OJ L 2025/2621, 22.12.2025). Legally binding from 1 January 2026. XLS file published February 2026. No revision as of May 2026; next mandatory review by December 2027 (Recital 15, IR 2025/2621). Default values = country-specific average embedded emission intensity + mark-up (+10% in 2026, +20% in 2027, +30% from 2028; fertilisers +1% only per Reg 2025/2083 Omnibus simplification). This table shows the PRE-MARKUP default (= country average) vs model holistic intensity. The benchmark (EU ETS) is a separate concept — it is the free-allocation equivalent used to compute the deduction in the certificate formula. Model EFs respond to country selector (B5) and are compared against the corresponding IR 2025/2621 country-specific SEE value.
A99: Code (self-generated) | B99: Entity | C99: Unit | D99: Model S1.fc tCO₂/t | E99: Ref S1.fc (from ref_data GJ/t × EF) | F99: Model S1.fp tCO₂/t | G99: Ref S1.fp (from ref_data) | H99: Model efn S1.np tCO₂/t | I99: Ref efn (IPCC 2006 tCO₂/t) | J99: Model efo S1.no tCO₂e/t | K99: Ref efo (IPCC AR6 tCO₂e/t) | L99: Model S2 tCO₂/t | M99: Model holistic tCO₂e/t | N99: IR 2025/2621 SEE total (pre-markup) | O99: Model/ SEE ratio | P99: Note
A100: =CBAM!$B$5&".cmp.ef.stl.drg.---" -> egy.cmp.ef.stl.drg.--- | B100: DRI-EAF steel | C100: t | D100: =IFERROR(INDEX(calculations!$M:$X,41,CBAM!$P$6)/INDEX(calculations!$M:$X,20,CBAM!$P$6),0) -> 0.12903 | E100: =IFERROR((IFERROR(INDEX(ref_data!$D:$D,MATCH(CBAM!$B$5&".ref.ei.stl.drg.---",ref_data!$A:$A,0)),0)*96.1+IFERROR(INDEX(ref_data!$E:$E,MATCH(CBAM!$B$5&".ref.ei.stl.drg.---",ref_data!$A:$A,0)),0)*56.1+IFERROR(INDEX(ref_data!$F:$F,MATCH(CBAM!$B$5&".ref.ei.stl.drg.---",ref_data!$A:$A,0)),0)*69.3+IFERROR(INDEX(ref_data!$G:$G,MATCH(CBAM!$B$5&".ref.ei.stl.drg.---",ref_data!$A:$A,0)),0)*74.1+IFERROR(INDEX(ref_data!$H:$H,MATCH(CBAM!$B$5&".ref.ei.stl.drg.---",ref_data!$A:$A,0)),0)*71.9+IFERROR(INDEX(ref_data!$I:$I,MATCH(CBAM!$B$5&".ref.ei.stl.drg.---",ref_data!$A:$A,0)),0)*63.1+IFERROR(INDEX(ref_data!$J:$J,MATCH(CBAM!$B$5&".ref.ei.stl.drg.---",ref_data!$A:$A,0)),0)*0+IFERROR(INDEX(ref_data!$K:$K,MATCH(CBAM!$B$5&".ref.ei.stl.drg.---",ref_data!$A:$A,0)),0)*0)/1000,0) -> 0.31755 | F100: =IFERROR(INDEX(calculations!$M:$X,42,CBAM!$P$6)/INDEX(calculations!$M:$X,20,CBAM!$P$6),0) -> 0.561 | G100: =IFERROR((IFERROR(INDEX(ref_data!$L:$L,MATCH(CBAM!$B$5&".ref.ei.stl.drg.---",ref_data!$A:$A,0)),0)*96.1+IFERROR(INDEX(ref_data!$M:$M,MATCH(CBAM!$B$5&".ref.ei.stl.drg.---",ref_data!$A:$A,0)),0)*56.1+IFERROR(INDEX(ref_data!$N:$N,MATCH(CBAM!$B$5&".ref.ei.stl.drg.---",ref_data!$A:$A,0)),0)*69.3+IFERROR(INDEX(ref_data!$O:$O,MATCH(CBAM!$B$5&".ref.ei.stl.drg.---",ref_data!$A:$A,0)),0)*74.1+IFERROR(INDEX(ref_data!$P:$P,MATCH(CBAM!$B$5&".ref.ei.stl.drg.---",ref_data!$A:$A,0)),0)*71.9+IFERROR(INDEX(ref_data!$Q:$Q,MATCH(CBAM!$B$5&".ref.ei.stl.drg.---",ref_data!$A:$A,0)),0)*63.1+IFERROR(INDEX(ref_data!$R:$R,MATCH(CBAM!$B$5&".ref.ei.stl.drg.---",ref_data!$A:$A,0)),0)*0+IFERROR(INDEX(ref_data!$S:$S,MATCH(CBAM!$B$5&".ref.ei.stl.drg.---",ref_data!$A:$A,0)),0)*0)/1000,0) -> 1.3464 | H100: =IFERROR(INDEX(calculations!$M:$X,43,CBAM!$P$6)/INDEX(calculations!$M:$X,20,CBAM!$P$6),0) -> 0.04 | I100: =IFERROR(INDEX(ref_data!$U:$U,MATCH("egy.ref.ei.stl.drg.---",ref_data!$A:$A,0)),0) -> 0.1 | J100: =IFERROR(INDEX(calculations!$M:$X,44,CBAM!$P$6)/INDEX(calculations!$M:$X,20,CBAM!$P$6),0) -> 0 | K100: =IFERROR(INDEX(ref_data!$V:$V,MATCH("egy.ref.ei.stl.drg.---",ref_data!$A:$A,0)),0) -> 0 | L100: =IFERROR(INDEX(calculations!$M:$X,45,CBAM!$P$6)/INDEX(calculations!$M:$X,20,CBAM!$P$6),0) -> 0.25 | M100: =IFERROR(INDEX(calculations!$M:$X,246,CBAM!$P$6),0) -> 0.98003 | N100: =IFERROR(INDEX(ref_data!$F:$F,MATCH(CBAM!$B$5&".ref.dv.stl.drg.---",ref_data!$A:$A,0)),"—") -> 1.404 | O100: =IFERROR(M100/N100,"—") -> 0.69802707 | P100: DRI: model S1.fp (NG reduction) vs ref. Ratio >1 if model includes more process scope.
A101: =CBAM!$B$5&".cmp.ef.stl.scr.---" -> egy.cmp.ef.stl.scr.--- | B101: Scrap-EAF steel | C101: t | D101: =IFERROR(INDEX(calculations!$M:$X,69,CBAM!$P$6)/INDEX(calculations!$M:$X,48,CBAM!$P$6),0) -> 0.14025 | E101: =IFERROR((IFERROR(INDEX(ref_data!$D:$D,MATCH(CBAM!$B$5&".ref.ei.stl.scr.---",ref_data!$A:$A,0)),0)*96.1+IFERROR(INDEX(ref_data!$E:$E,MATCH(CBAM!$B$5&".ref.ei.stl.scr.---",ref_data!$A:$A,0)),0)*56.1+IFERROR(INDEX(ref_data!$F:$F,MATCH(CBAM!$B$5&".ref.ei.stl.scr.---",ref_data!$A:$A,0)),0)*69.3+IFERROR(INDEX(ref_data!$G:$G,MATCH(CBAM!$B$5&".ref.ei.stl.scr.---",ref_data!$A:$A,0)),0)*74.1+IFERROR(INDEX(ref_data!$H:$H,MATCH(CBAM!$B$5&".ref.ei.stl.scr.---",ref_data!$A:$A,0)),0)*71.9+IFERROR(INDEX(ref_data!$I:$I,MATCH(CBAM!$B$5&".ref.ei.stl.scr.---",ref_data!$A:$A,0)),0)*63.1+IFERROR(INDEX(ref_data!$J:$J,MATCH(CBAM!$B$5&".ref.ei.stl.scr.---",ref_data!$A:$A,0)),0)*0+IFERROR(INDEX(ref_data!$K:$K,MATCH(CBAM!$B$5&".ref.ei.stl.scr.---",ref_data!$A:$A,0)),0)*0)/1000,0) -> 0.15507 | F101: =IFERROR(INDEX(calculations!$M:$X,70,CBAM!$P$6)/INDEX(calculations!$M:$X,48,CBAM!$P$6),0) -> 0 | G101: =IFERROR((IFERROR(INDEX(ref_data!$L:$L,MATCH(CBAM!$B$5&".ref.ei.stl.scr.---",ref_data!$A:$A,0)),0)*96.1+IFERROR(INDEX(ref_data!$M:$M,MATCH(CBAM!$B$5&".ref.ei.stl.scr.---",ref_data!$A:$A,0)),0)*56.1+IFERROR(INDEX(ref_data!$N:$N,MATCH(CBAM!$B$5&".ref.ei.stl.scr.---",ref_data!$A:$A,0)),0)*69.3+IFERROR(INDEX(ref_data!$O:$O,MATCH(CBAM!$B$5&".ref.ei.stl.scr.---",ref_data!$A:$A,0)),0)*74.1+IFERROR(INDEX(ref_data!$P:$P,MATCH(CBAM!$B$5&".ref.ei.stl.scr.---",ref_data!$A:$A,0)),0)*71.9+IFERROR(INDEX(ref_data!$Q:$Q,MATCH(CBAM!$B$5&".ref.ei.stl.scr.---",ref_data!$A:$A,0)),0)*63.1+IFERROR(INDEX(ref_data!$R:$R,MATCH(CBAM!$B$5&".ref.ei.stl.scr.---",ref_data!$A:$A,0)),0)*0+IFERROR(INDEX(ref_data!$S:$S,MATCH(CBAM!$B$5&".ref.ei.stl.scr.---",ref_data!$A:$A,0)),0)*0)/1000,0) -> 0 | H101: =IFERROR(INDEX(calculations!$M:$X,71,CBAM!$P$6)/INDEX(calculations!$M:$X,48,CBAM!$P$6),0) -> 0.015 | I101: =IFERROR(INDEX(ref_data!$U:$U,MATCH("egy.ref.ei.stl.scr.---",ref_data!$A:$A,0)),0) -> 0 | J101: =IFERROR(INDEX(calculations!$M:$X,72,CBAM!$P$6)/INDEX(calculations!$M:$X,48,CBAM!$P$6),0) -> 0 | K101: =IFERROR(INDEX(ref_data!$V:$V,MATCH("egy.ref.ei.stl.scr.---",ref_data!$A:$A,0)),0) -> 0 | L101: =IFERROR(INDEX(calculations!$M:$X,73,CBAM!$P$6)/INDEX(calculations!$M:$X,48,CBAM!$P$6),0) -> 0.25 | M101: =IFERROR(INDEX(calculations!$M:$X,251,CBAM!$P$6),0) -> 0.40525 | N101: =IFERROR(INDEX(ref_data!$F:$F,MATCH(CBAM!$B$5&".ref.dv.stl.scr.---",ref_data!$A:$A,0)),"—") -> 0.72 | O101: =IFERROR(M101/N101,"—") -> 0.56284722 | P101: Scrap-EAF: low direct intensity; S2 large but excluded from CBAM for steel.
A102: =CBAM!$B$5&".cmp.ef.stl.bof.---" -> egy.cmp.ef.stl.bof.--- | B102: BF-BOF steel | C102: t | D102: =IFERROR(INDEX(calculations!$M:$X,97,CBAM!$P$6)/INDEX(calculations!$M:$X,76,CBAM!$P$6),0) -> 0 | E102: =IFERROR((IFERROR(INDEX(ref_data!$D:$D,MATCH(CBAM!$B$5&".ref.ei.stl.bof.---",ref_data!$A:$A,0)),0)*96.1+IFERROR(INDEX(ref_data!$E:$E,MATCH(CBAM!$B$5&".ref.ei.stl.bof.---",ref_data!$A:$A,0)),0)*56.1+IFERROR(INDEX(ref_data!$F:$F,MATCH(CBAM!$B$5&".ref.ei.stl.bof.---",ref_data!$A:$A,0)),0)*69.3+IFERROR(INDEX(ref_data!$G:$G,MATCH(CBAM!$B$5&".ref.ei.stl.bof.---",ref_data!$A:$A,0)),0)*74.1+IFERROR(INDEX(ref_data!$H:$H,MATCH(CBAM!$B$5&".ref.ei.stl.bof.---",ref_data!$A:$A,0)),0)*71.9+IFERROR(INDEX(ref_data!$I:$I,MATCH(CBAM!$B$5&".ref.ei.stl.bof.---",ref_data!$A:$A,0)),0)*63.1+IFERROR(INDEX(ref_data!$J:$J,MATCH(CBAM!$B$5&".ref.ei.stl.bof.---",ref_data!$A:$A,0)),0)*0+IFERROR(INDEX(ref_data!$K:$K,MATCH(CBAM!$B$5&".ref.ei.stl.bof.---",ref_data!$A:$A,0)),0)*0)/1000,0) -> 0.40727 | F102: =IFERROR(INDEX(calculations!$M:$X,98,CBAM!$P$6)/INDEX(calculations!$M:$X,76,CBAM!$P$6),0) -> 0 | G102: =IFERROR((IFERROR(INDEX(ref_data!$L:$L,MATCH(CBAM!$B$5&".ref.ei.stl.bof.---",ref_data!$A:$A,0)),0)*96.1+IFERROR(INDEX(ref_data!$M:$M,MATCH(CBAM!$B$5&".ref.ei.stl.bof.---",ref_data!$A:$A,0)),0)*56.1+IFERROR(INDEX(ref_data!$N:$N,MATCH(CBAM!$B$5&".ref.ei.stl.bof.---",ref_data!$A:$A,0)),0)*69.3+IFERROR(INDEX(ref_data!$O:$O,MATCH(CBAM!$B$5&".ref.ei.stl.bof.---",ref_data!$A:$A,0)),0)*74.1+IFERROR(INDEX(ref_data!$P:$P,MATCH(CBAM!$B$5&".ref.ei.stl.bof.---",ref_data!$A:$A,0)),0)*71.9+IFERROR(INDEX(ref_data!$Q:$Q,MATCH(CBAM!$B$5&".ref.ei.stl.bof.---",ref_data!$A:$A,0)),0)*63.1+IFERROR(INDEX(ref_data!$R:$R,MATCH(CBAM!$B$5&".ref.ei.stl.bof.---",ref_data!$A:$A,0)),0)*0+IFERROR(INDEX(ref_data!$S:$S,MATCH(CBAM!$B$5&".ref.ei.stl.bof.---",ref_data!$A:$A,0)),0)*0)/1000,0) -> 1.4976 | H102: =IFERROR(INDEX(calculations!$M:$X,99,CBAM!$P$6)/INDEX(calculations!$M:$X,76,CBAM!$P$6),0) -> 0 | I102: =IFERROR(INDEX(ref_data!$U:$U,MATCH("egy.ref.ei.stl.bof.---",ref_data!$A:$A,0)),0) -> 0.25 | J102: =IFERROR(INDEX(calculations!$M:$X,100,CBAM!$P$6)/INDEX(calculations!$M:$X,76,CBAM!$P$6),0) -> 0 | K102: =IFERROR(INDEX(ref_data!$V:$V,MATCH("egy.ref.ei.stl.bof.---",ref_data!$A:$A,0)),0) -> 0 | L102: =IFERROR(INDEX(calculations!$M:$X,101,CBAM!$P$6)/INDEX(calculations!$M:$X,76,CBAM!$P$6),0) -> 0 | M102: =IFERROR(INDEX(calculations!$M:$X,256,CBAM!$P$6),0) -> 2.3595 | N102: =IFERROR(INDEX(ref_data!$F:$F,MATCH(CBAM!$B$5&".ref.dv.stl.bof.---",ref_data!$A:$A,0)),"—") -> — | O102: =IFERROR(M102/N102,"—") -> — | P102: BF-BOF: coal-intensive; ref S1.fp (coke reduction) should dominate.
A103: =CBAM!$B$5&".cmp.ef.cmt.dry.---" -> egy.cmp.ef.cmt.dry.--- | B103: Cement | C103: t | D103: =IFERROR(INDEX(calculations!$M:$X,125,CBAM!$P$6)/INDEX(calculations!$M:$X,104,CBAM!$P$6),0) -> 0.2883 | E103: =IFERROR((IFERROR(INDEX(ref_data!$D:$D,MATCH(CBAM!$B$5&".ref.ei.cmt.dry.---",ref_data!$A:$A,0)),0)*96.1+IFERROR(INDEX(ref_data!$E:$E,MATCH(CBAM!$B$5&".ref.ei.cmt.dry.---",ref_data!$A:$A,0)),0)*56.1+IFERROR(INDEX(ref_data!$F:$F,MATCH(CBAM!$B$5&".ref.ei.cmt.dry.---",ref_data!$A:$A,0)),0)*69.3+IFERROR(INDEX(ref_data!$G:$G,MATCH(CBAM!$B$5&".ref.ei.cmt.dry.---",ref_data!$A:$A,0)),0)*74.1+IFERROR(INDEX(ref_data!$H:$H,MATCH(CBAM!$B$5&".ref.ei.cmt.dry.---",ref_data!$A:$A,0)),0)*71.9+IFERROR(INDEX(ref_data!$I:$I,MATCH(CBAM!$B$5&".ref.ei.cmt.dry.---",ref_data!$A:$A,0)),0)*63.1+IFERROR(INDEX(ref_data!$J:$J,MATCH(CBAM!$B$5&".ref.ei.cmt.dry.---",ref_data!$A:$A,0)),0)*0+IFERROR(INDEX(ref_data!$K:$K,MATCH(CBAM!$B$5&".ref.ei.cmt.dry.---",ref_data!$A:$A,0)),0)*0)/1000,0) -> 0.2683 | F103: =IFERROR(INDEX(calculations!$M:$X,126,CBAM!$P$6)/INDEX(calculations!$M:$X,104,CBAM!$P$6),0) -> 0 | G103: =IFERROR((IFERROR(INDEX(ref_data!$L:$L,MATCH(CBAM!$B$5&".ref.ei.cmt.dry.---",ref_data!$A:$A,0)),0)*96.1+IFERROR(INDEX(ref_data!$M:$M,MATCH(CBAM!$B$5&".ref.ei.cmt.dry.---",ref_data!$A:$A,0)),0)*56.1+IFERROR(INDEX(ref_data!$N:$N,MATCH(CBAM!$B$5&".ref.ei.cmt.dry.---",ref_data!$A:$A,0)),0)*69.3+IFERROR(INDEX(ref_data!$O:$O,MATCH(CBAM!$B$5&".ref.ei.cmt.dry.---",ref_data!$A:$A,0)),0)*74.1+IFERROR(INDEX(ref_data!$P:$P,MATCH(CBAM!$B$5&".ref.ei.cmt.dry.---",ref_data!$A:$A,0)),0)*71.9+IFERROR(INDEX(ref_data!$Q:$Q,MATCH(CBAM!$B$5&".ref.ei.cmt.dry.---",ref_data!$A:$A,0)),0)*63.1+IFERROR(INDEX(ref_data!$R:$R,MATCH(CBAM!$B$5&".ref.ei.cmt.dry.---",ref_data!$A:$A,0)),0)*0+IFERROR(INDEX(ref_data!$S:$S,MATCH(CBAM!$B$5&".ref.ei.cmt.dry.---",ref_data!$A:$A,0)),0)*0)/1000,0) -> 0 | H103: =IFERROR(INDEX(calculations!$M:$X,127,CBAM!$P$6)/INDEX(calculations!$M:$X,104,CBAM!$P$6),0) -> 0.526 | I103: =IFERROR(INDEX(ref_data!$U:$U,MATCH("egy.ref.ei.cmt.dry.---",ref_data!$A:$A,0)),0) -> 0.526 | J103: =IFERROR(INDEX(calculations!$M:$X,128,CBAM!$P$6)/INDEX(calculations!$M:$X,104,CBAM!$P$6),0) -> 0 | K103: =IFERROR(INDEX(ref_data!$V:$V,MATCH("egy.ref.ei.cmt.dry.---",ref_data!$A:$A,0)),0) -> 0 | L103: =IFERROR(INDEX(calculations!$M:$X,129,CBAM!$P$6)/INDEX(calculations!$M:$X,104,CBAM!$P$6),0) -> 0.05625 | M103: =IFERROR(INDEX(calculations!$M:$X,261,CBAM!$P$6),0) -> 0.87055 | N103: =IFERROR(INDEX(ref_data!$F:$F,MATCH(CBAM!$B$5&".ref.dv.cmt.dry.---",ref_data!$A:$A,0)),"—") -> 0.875 | O103: =IFERROR(M103/N103,"—") -> 0.99491429 | P103: Cement: efn=0.526 (calcination) identical in both; fuel mix comparison meaningful.
A104: =CBAM!$B$5&".cmp.ef.frt.amc.---" -> egy.cmp.ef.frt.amc.--- | B104: Ammonia | C104: t | D104: =IFERROR(INDEX(calculations!$M:$X,153,CBAM!$P$6)/INDEX(calculations!$M:$X,132,CBAM!$P$6),0) -> 0.3927 | E104: =IFERROR((IFERROR(INDEX(ref_data!$D:$D,MATCH(CBAM!$B$5&".ref.ei.frt.amc.---",ref_data!$A:$A,0)),0)*96.1+IFERROR(INDEX(ref_data!$E:$E,MATCH(CBAM!$B$5&".ref.ei.frt.amc.---",ref_data!$A:$A,0)),0)*56.1+IFERROR(INDEX(ref_data!$F:$F,MATCH(CBAM!$B$5&".ref.ei.frt.amc.---",ref_data!$A:$A,0)),0)*69.3+IFERROR(INDEX(ref_data!$G:$G,MATCH(CBAM!$B$5&".ref.ei.frt.amc.---",ref_data!$A:$A,0)),0)*74.1+IFERROR(INDEX(ref_data!$H:$H,MATCH(CBAM!$B$5&".ref.ei.frt.amc.---",ref_data!$A:$A,0)),0)*71.9+IFERROR(INDEX(ref_data!$I:$I,MATCH(CBAM!$B$5&".ref.ei.frt.amc.---",ref_data!$A:$A,0)),0)*63.1+IFERROR(INDEX(ref_data!$J:$J,MATCH(CBAM!$B$5&".ref.ei.frt.amc.---",ref_data!$A:$A,0)),0)*0+IFERROR(INDEX(ref_data!$K:$K,MATCH(CBAM!$B$5&".ref.ei.frt.amc.---",ref_data!$A:$A,0)),0)*0)/1000,0) -> 0.6732 | F104: =IFERROR(INDEX(calculations!$M:$X,154,CBAM!$P$6)/INDEX(calculations!$M:$X,132,CBAM!$P$6),0) -> 1.4586 | G104: =IFERROR((IFERROR(INDEX(ref_data!$L:$L,MATCH(CBAM!$B$5&".ref.ei.frt.amc.---",ref_data!$A:$A,0)),0)*96.1+IFERROR(INDEX(ref_data!$M:$M,MATCH(CBAM!$B$5&".ref.ei.frt.amc.---",ref_data!$A:$A,0)),0)*56.1+IFERROR(INDEX(ref_data!$N:$N,MATCH(CBAM!$B$5&".ref.ei.frt.amc.---",ref_data!$A:$A,0)),0)*69.3+IFERROR(INDEX(ref_data!$O:$O,MATCH(CBAM!$B$5&".ref.ei.frt.amc.---",ref_data!$A:$A,0)),0)*74.1+IFERROR(INDEX(ref_data!$P:$P,MATCH(CBAM!$B$5&".ref.ei.frt.amc.---",ref_data!$A:$A,0)),0)*71.9+IFERROR(INDEX(ref_data!$Q:$Q,MATCH(CBAM!$B$5&".ref.ei.frt.amc.---",ref_data!$A:$A,0)),0)*63.1+IFERROR(INDEX(ref_data!$R:$R,MATCH(CBAM!$B$5&".ref.ei.frt.amc.---",ref_data!$A:$A,0)),0)*0+IFERROR(INDEX(ref_data!$S:$S,MATCH(CBAM!$B$5&".ref.ei.frt.amc.---",ref_data!$A:$A,0)),0)*0)/1000,0) -> 1.3464 | H104: =IFERROR(INDEX(calculations!$M:$X,155,CBAM!$P$6)/INDEX(calculations!$M:$X,132,CBAM!$P$6),0) -> 0 | I104: =IFERROR(INDEX(ref_data!$U:$U,MATCH("egy.ref.ei.frt.amc.---",ref_data!$A:$A,0)),0) -> 0 | J104: =IFERROR(INDEX(calculations!$M:$X,156,CBAM!$P$6)/INDEX(calculations!$M:$X,132,CBAM!$P$6),0) -> 0 | K104: =IFERROR(INDEX(ref_data!$V:$V,MATCH("egy.ref.ei.frt.amc.---",ref_data!$A:$A,0)),0) -> 0 | L104: =IFERROR(INDEX(calculations!$M:$X,157,CBAM!$P$6)/INDEX(calculations!$M:$X,132,CBAM!$P$6),0) -> 0.0375 | M104: =IFERROR(INDEX(calculations!$M:$X,266,CBAM!$P$6),0) -> 1.8888 | N104: =IFERROR(INDEX(ref_data!$F:$F,MATCH(CBAM!$B$5&".ref.dv.frt.amc.---",ref_data!$A:$A,0)),"—") -> 1.404 | O104: =IFERROR(M104/N104,"—") -> 1.3452991 | P104: Ammonia: S1.fp = SMR NG dominates; model and ref should be close.
A105: =CBAM!$B$5&".cmp.ef.frt.ure.---" -> egy.cmp.ef.frt.ure.--- | B105: Urea | C105: t | D105: =IFERROR(INDEX(calculations!$M:$X,181,CBAM!$P$6)/INDEX(calculations!$M:$X,160,CBAM!$P$6),0) -> 0.1122 | E105: =IFERROR((IFERROR(INDEX(ref_data!$D:$D,MATCH(CBAM!$B$5&".ref.ei.frt.ure.---",ref_data!$A:$A,0)),0)*96.1+IFERROR(INDEX(ref_data!$E:$E,MATCH(CBAM!$B$5&".ref.ei.frt.ure.---",ref_data!$A:$A,0)),0)*56.1+IFERROR(INDEX(ref_data!$F:$F,MATCH(CBAM!$B$5&".ref.ei.frt.ure.---",ref_data!$A:$A,0)),0)*69.3+IFERROR(INDEX(ref_data!$G:$G,MATCH(CBAM!$B$5&".ref.ei.frt.ure.---",ref_data!$A:$A,0)),0)*74.1+IFERROR(INDEX(ref_data!$H:$H,MATCH(CBAM!$B$5&".ref.ei.frt.ure.---",ref_data!$A:$A,0)),0)*71.9+IFERROR(INDEX(ref_data!$I:$I,MATCH(CBAM!$B$5&".ref.ei.frt.ure.---",ref_data!$A:$A,0)),0)*63.1+IFERROR(INDEX(ref_data!$J:$J,MATCH(CBAM!$B$5&".ref.ei.frt.ure.---",ref_data!$A:$A,0)),0)*0+IFERROR(INDEX(ref_data!$K:$K,MATCH(CBAM!$B$5&".ref.ei.frt.ure.---",ref_data!$A:$A,0)),0)*0)/1000,0) -> 0.1683 | F105: =IFERROR(INDEX(calculations!$M:$X,182,CBAM!$P$6)/INDEX(calculations!$M:$X,160,CBAM!$P$6),0) -> 0 | G105: =IFERROR((IFERROR(INDEX(ref_data!$L:$L,MATCH(CBAM!$B$5&".ref.ei.frt.ure.---",ref_data!$A:$A,0)),0)*96.1+IFERROR(INDEX(ref_data!$M:$M,MATCH(CBAM!$B$5&".ref.ei.frt.ure.---",ref_data!$A:$A,0)),0)*56.1+IFERROR(INDEX(ref_data!$N:$N,MATCH(CBAM!$B$5&".ref.ei.frt.ure.---",ref_data!$A:$A,0)),0)*69.3+IFERROR(INDEX(ref_data!$O:$O,MATCH(CBAM!$B$5&".ref.ei.frt.ure.---",ref_data!$A:$A,0)),0)*74.1+IFERROR(INDEX(ref_data!$P:$P,MATCH(CBAM!$B$5&".ref.ei.frt.ure.---",ref_data!$A:$A,0)),0)*71.9+IFERROR(INDEX(ref_data!$Q:$Q,MATCH(CBAM!$B$5&".ref.ei.frt.ure.---",ref_data!$A:$A,0)),0)*63.1+IFERROR(INDEX(ref_data!$R:$R,MATCH(CBAM!$B$5&".ref.ei.frt.ure.---",ref_data!$A:$A,0)),0)*0+IFERROR(INDEX(ref_data!$S:$S,MATCH(CBAM!$B$5&".ref.ei.frt.ure.---",ref_data!$A:$A,0)),0)*0)/1000,0) -> 0 | H105: =IFERROR(INDEX(calculations!$M:$X,183,CBAM!$P$6)/INDEX(calculations!$M:$X,160,CBAM!$P$6),0) -> -0.733 | I105: =IFERROR(INDEX(ref_data!$U:$U,MATCH("egy.ref.ei.frt.ure.---",ref_data!$A:$A,0)),0) -> -0.733 | J105: =IFERROR(INDEX(calculations!$M:$X,184,CBAM!$P$6)/INDEX(calculations!$M:$X,160,CBAM!$P$6),0) -> 0 | K105: =IFERROR(INDEX(ref_data!$V:$V,MATCH("egy.ref.ei.frt.ure.---",ref_data!$A:$A,0)),0) -> 0 | L105: =IFERROR(INDEX(calculations!$M:$X,185,CBAM!$P$6)/INDEX(calculations!$M:$X,160,CBAM!$P$6),0) -> 0.0375 | M105: =IFERROR(INDEX(calculations!$M:$X,271,CBAM!$P$6),0) -> 0.4876496 | N105: =IFERROR(INDEX(ref_data!$F:$F,MATCH(CBAM!$B$5&".ref.dv.frt.ure.---",ref_data!$A:$A,0)),"—") -> 1.459 | O105: =IFERROR(M105/N105,"—") -> 0.3342355 | P105: Urea: efn is negative (CO2 uptake). Model should ≈ ref.
A106: =CBAM!$B$5&".cmp.ef.frt.nit.---" -> egy.cmp.ef.frt.nit.--- | B106: Ammonium nitrate | C106: t | D106: =IFERROR(INDEX(calculations!$M:$X,209,CBAM!$P$6)/INDEX(calculations!$M:$X,188,CBAM!$P$6),0) -> 0.1122 | E106: =IFERROR((IFERROR(INDEX(ref_data!$D:$D,MATCH(CBAM!$B$5&".ref.ei.frt.nit.---",ref_data!$A:$A,0)),0)*96.1+IFERROR(INDEX(ref_data!$E:$E,MATCH(CBAM!$B$5&".ref.ei.frt.nit.---",ref_data!$A:$A,0)),0)*56.1+IFERROR(INDEX(ref_data!$F:$F,MATCH(CBAM!$B$5&".ref.ei.frt.nit.---",ref_data!$A:$A,0)),0)*69.3+IFERROR(INDEX(ref_data!$G:$G,MATCH(CBAM!$B$5&".ref.ei.frt.nit.---",ref_data!$A:$A,0)),0)*74.1+IFERROR(INDEX(ref_data!$H:$H,MATCH(CBAM!$B$5&".ref.ei.frt.nit.---",ref_data!$A:$A,0)),0)*71.9+IFERROR(INDEX(ref_data!$I:$I,MATCH(CBAM!$B$5&".ref.ei.frt.nit.---",ref_data!$A:$A,0)),0)*63.1+IFERROR(INDEX(ref_data!$J:$J,MATCH(CBAM!$B$5&".ref.ei.frt.nit.---",ref_data!$A:$A,0)),0)*0+IFERROR(INDEX(ref_data!$K:$K,MATCH(CBAM!$B$5&".ref.ei.frt.nit.---",ref_data!$A:$A,0)),0)*0)/1000,0) -> 0.1122 | F106: =IFERROR(INDEX(calculations!$M:$X,210,CBAM!$P$6)/INDEX(calculations!$M:$X,188,CBAM!$P$6),0) -> 0 | G106: =IFERROR((IFERROR(INDEX(ref_data!$L:$L,MATCH(CBAM!$B$5&".ref.ei.frt.nit.---",ref_data!$A:$A,0)),0)*96.1+IFERROR(INDEX(ref_data!$M:$M,MATCH(CBAM!$B$5&".ref.ei.frt.nit.---",ref_data!$A:$A,0)),0)*56.1+IFERROR(INDEX(ref_data!$N:$N,MATCH(CBAM!$B$5&".ref.ei.frt.nit.---",ref_data!$A:$A,0)),0)*69.3+IFERROR(INDEX(ref_data!$O:$O,MATCH(CBAM!$B$5&".ref.ei.frt.nit.---",ref_data!$A:$A,0)),0)*74.1+IFERROR(INDEX(ref_data!$P:$P,MATCH(CBAM!$B$5&".ref.ei.frt.nit.---",ref_data!$A:$A,0)),0)*71.9+IFERROR(INDEX(ref_data!$Q:$Q,MATCH(CBAM!$B$5&".ref.ei.frt.nit.---",ref_data!$A:$A,0)),0)*63.1+IFERROR(INDEX(ref_data!$R:$R,MATCH(CBAM!$B$5&".ref.ei.frt.nit.---",ref_data!$A:$A,0)),0)*0+IFERROR(INDEX(ref_data!$S:$S,MATCH(CBAM!$B$5&".ref.ei.frt.nit.---",ref_data!$A:$A,0)),0)*0)/1000,0) -> 0 | H106: =IFERROR(INDEX(calculations!$M:$X,211,CBAM!$P$6)/INDEX(calculations!$M:$X,188,CBAM!$P$6),0) -> 0 | I106: =IFERROR(INDEX(ref_data!$U:$U,MATCH("egy.ref.ei.frt.nit.---",ref_data!$A:$A,0)),0) -> 0 | J106: =IFERROR(INDEX(calculations!$M:$X,212,CBAM!$P$6)/INDEX(calculations!$M:$X,188,CBAM!$P$6),0) -> 0.97 | K106: =IFERROR(INDEX(ref_data!$V:$V,MATCH("egy.ref.ei.frt.nit.---",ref_data!$A:$A,0)),0) -> 2.5 | L106: =IFERROR(INDEX(calculations!$M:$X,213,CBAM!$P$6)/INDEX(calculations!$M:$X,188,CBAM!$P$6),0) -> 0.04375 | M106: =IFERROR(INDEX(calculations!$M:$X,276,CBAM!$P$6),0) -> 1.5282644 | N106: =IFERROR(INDEX(ref_data!$F:$F,MATCH(CBAM!$B$5&".ref.dv.frt.nit.---",ref_data!$A:$A,0)),"—") -> 0.86 | O106: =IFERROR(M106/N106,"—") -> 1.7770516 | P106: AN: efo (N2O) is the key variable. Model uses 2.5 tCO2e/t midpoint.
